Workbook
Name _EPS01: #REF!
Name _EPS02: #REF!
Name _EPS1: #REF!
Name _EPS2: #REF!
Name _EPS3: #REF!
Name _EPS99: #REF!
Name _exp2: #REF!
Name _lev2: #REF!
Name _Low1: #REF!
Name _Low2: #REF!
Name _Low3: #REF!
Name _Low4: #REF!
Name _Low5: #REF!
Name _Low6: #REF!
Name _Low7: #REF!
Name _Low8: #REF!
Name _Low9: #REF!
Name _mu2: #REF!
Name _PE1: #REF!
Name _PE2: #REF!
Name _PE3: #REF!
Name _PFY1: #REF!
Name _PFY2: #REF!
Name _PFY3: #REF!
Name _PFY4: #REF!
Name _pr2: #REF!
Name _TAB1: #REF!
Name _Yr1: #REF!
Name _Yr2: #REF!
Name aaaafff: #REF!
Name AccPay: #REF!
Name AccRec: #REF!
Name ACCRETE: #REF!
Name Acq: #REF!
Name AcqNum: #REF!
Name AcqTrig: #REF!
Name Acquirors: #REF!
Name AdjTaxes: #REF!
Name ADLTM: #REF!
Name ADYear1: #REF!
Name ADYear2: #REF!
Name AfterTaxItems: #REF!
Name allokay: #REF!
Name allsicempty: #REF!
Name AmortLTM: #REF!
Name AmortPeriod: #REF!
Name AmortYear1: #REF!
Name AmortYear2: #REF!
Name amt: #REF!
Name Assets: #REF!
Name AssetsA: #REF!
Name AssetsT: #REF!
Name AssetWriteup: #REF!
Name AttritionMonthly: #REF!
Name AVG_CPM: #REF!
Name AvgShares: #REF!
Name BaseTick: #REF!
Name Beg_Bal: #REF!
Name BenefitsLoad: #REF!
Name Beta: #REF!

Sheet Claude Log
A1: Turn # | B1: Date | C1: User Request | D1: Action Taken | E1: Details | F1: Outcome
A2: 1 | B2: 46281 | C2: Make the COO P&L tab the sum of FO, PO, CO, FE and PE; also asked that all sheets be formatted the same. | D2: Rewrote all single-sheet pull formulas on COO; compared formatting across the six P&L tabs. | E2: 2,142 cells in COO!A9:AJ145 changed from =SUM(PO!x) to =SUM(FO!x,PO!x,CO!x,FE!x,PE!x). Formatting: user chose fonts/number formats/column widths only (no fill changes). Set uniform column widths on all six P&L tabs (A=301.5; month cols 62.5; N=78; O=70; P/Q=41.5; R=82.5; S=75; T=70.5; AG=78), body font Calibri 10 in A9:AJ145, and copied COO's line-item number formats to B9:Q142 and U9:AJ142 on FO/PO/CO/FE/PE. Excluded dept-only budget driver columns R:T and header rows 1:8; left all cell fills and font colors (blue = input convention) untouched. | F2: Verified: no error values on any of the six tabs; COO tie-out check row 133 nets to ~0 in every column; number formats in the shared body now identical across all six tabs; % rows (e.g. row 65 margins) now render as percentages on the dept tabs. Fill/highlight differences intentionally left as-is.
A3: 2 | B3: 46283 | C3: Add a headcount (#) summary to the COO HC total tab. | D3: Built a monthly active-headcount roll-up by department plus a COGS/SG&A split on COO HC rows 64-76. | E3: Rows 65-69 use =COUNTIF('<Dept> HC'!I$14:I$57,">0") per month (counts any employee/new hire/transfer-in row carrying salary in that month; transfer-out memo rows carry no cost so they aren't double-counted). Row 70 totals; rows 73-74 split via SUMIF on the D65:D69 P&L classification; row 75 total and row 76 tie-out check. Column Z shows Dec-27 ending headcount (point in time) rather than a sum of months, labeled in Z64. | F3: COO HC!B64:Z76. Sep-26 total 35 (PO 9, FO 16, FE 6, PE 0, CO 4); Dec-27 ending 36. Tie-out row 76 = 0 in every month. Verified I65:X76 and Z65:Z75 read back with no errors.
A4: 3 | B4: 46283 | C4: Excel agent (CRO HC and PL workfile) asked for the COO HC headcount summary so it could replicate the block on its CRO HC tab. | D4: Read the block with styles plus surrounding context and shared it as a file with the other Excel file; no changes made to this workbook. | E4: Shared coo-hc-headcount-summary.json containing values, formulas, displayed text, number formats, styling and layout notes for COO HC!B62:Z78 and the row 8-12 header context. Documented the COUNTIF('<Dept> HC'!I$14:I$57,">0") pattern, the SUMIF P&L split off D65:D69, and that column Z is Dec-27 ending headcount rather than a sum. | F4: File shared and message sent to the CRO workbook agent. Note: PE HC now has 9 staffed rows (added outside this chat), so COO totals now read 44 in Sep-26 and 45 from Oct-26 on; tie-out row 76 still 0 in every month.
A5: 4 | B5: 46283 | C5: Status update from the CRO workbook agent confirming it replicated the headcount summary; no action requested. | D5: Absorbed the update; no changes to this workbook beyond this log entry. | E5: CRO built the block at CRO HC!B54:Z64 (offset because CRO's grid ends at row 52): row 54 header, 55-57 AM/MK/SL, 58 total, 60 header, 61 COGS, 62 SG&A, 63 total, 64 check. It used =COUNTIF('<Dept> HC'!I$14:I$52,">0") since CRO dept tabs are cost-bearing through row 52 (transfers-in 47:52, transfer-out memo 54:59) versus 14:57 here. Same SUMIF split, Z as point-in-time, same formats. | F5: Noted: the row-range difference is a correct adaptation to CRO's tab layout, not an inconsistency. CRO reports no errors and a zero check row across all 16 months.
A6: 5 | B6: 46283 | C6: A Total Company roll-up workbook (Book1) asked for a structure map of this file so it can point external-link formulas at the right cells; explicitly no changes to this workbook. | D6: Read the layout of all five department HC tabs to confirm they are identical, then shared coo-map.json. No cells in this workbook were modified. | E6: Map covers: month grid (dates row 10, index row 11, columns I=Sep-26 through X=Dec-27, Y spacer), roster blocks (current employees 14-33, open positions 35-39, new hires 41-50, transfers-in 52-57 cost-bearing, transfers-out 59-64 memo-only, effective month in column E and end month in F), totals rows 67 S&W / 68 taxes / 69 benefits / 70 total payroll, per-dept names, codes, P&L class (PO+FO = COGS; FE, PE, CO = SG&A) and GL accounts, plus the COO HC roll-up row map. | F6: File shared and message sent to the Book1 agent, recommending it link to the COO HC roll-up rather than re-summing the department tabs. Verified all five dept tabs use the same row layout and =SUM(I14:I57) for Total Salaries & Wages.
A7: 7 | B7: 46286 | C7: CEO workbook agent asked for a hc-transfers.csv listing every transfer-in/out row and any current employee flagged "Transfer out" in column A, for a cross-file transfer reconciliation. | D7: Scanned column A and the transfers sections of all five department HC tabs (FO, PO, CO, FE, PE) plus the COO HC roll-up; shared hc-transfers.csv (header row only). No changes to workbook data. | E7: Transfers-In block sits at rows 52-57 and Transfers-Out memo block at rows 59-64 on each dept tab; all of these rows are blank (name, title, salary, start/end all empty). No current-employee row on any tab carries a "Transfer out" flag in column A - column A holds only the "From Dept"/"To Dept" section labels. COO HC is a formula roll-up with no employee rows. | F7: hc-transfers.csv shared with headers block,dept_code,counterparty_dept,employee,title,annual_salary,start_month,end_month and zero data rows: the COO workbook currently has no inter-department transfer activity.
A8: 8 | B8: 46289 | C8: CEO workbook agent asked (read-only) for hc-transfers.csv in a new column layout: sheet, row, block (IN/OUT/ROSTER), own_dept, counterparty_dept, employee, title, annual_salary, start_month, end_month. | D8: Re-scanned FO/PO/CO/FE/PE HC tabs and shared hc-transfers.csv (header row only). No workbook data changed. | E8: Blocks located by their headers on each tab: Transfers In rows 52-57 (header row 51), Transfers Out rows 59-66 (header row 58), totals from row 67. Rows counted as populated if cols A-E had any content (F:H hold template defaults for end month / increase % / increase month). Column A of roster rows checked for any 'Transfer' flag - none found. | F8: Zero transfer rows across all five tabs; confirmed to CEO agent. Correction to turn 5 map: Transfers Out memo block runs rows 59-66, not 59-64.
A9: 9 | B9: 46289 | C9: CEO workbook agent asked (read-only) to re-share hc-transfers.csv from FO/PO/CO/FE/PE HC in the same columns and say whether anything changed since the last extract. | D9: Re-scanned the five dept HC tabs and re-shared hc-transfers.csv (header row only). No workbook data changed. | E9: Same logic as turn 8: blocks located by header (Transfers In header row 51 / rows 52-57; Transfers Out header row 58 / rows 59-66; totals row 67 on every tab). Checked cols A-E for content, Transfers In F:H for any non-default values, and roster column A for any 'Transfer' flag. | F9: No change since turn 8: zero transfer rows, no transfer-out flags, block positions unchanged, F:H still template defaults. Reported to CEO agent.
A10: 10 | B10: 46289 | C10: CEO workfile (Excel peer) requested read-only export of all Transfers In/Out rows and 'Transfer out'-flagged current employees on each HC tab as hc-transfers.csv. | D10: Scanned HC tabs and shared hc-transfers.csv (header only). | E10: Checked FO/PO/CO/FE/PE HC Transfers In (rows 52-57) and Transfers Out (rows 59-66) for any entries in cols A-D; searched all cells for 'transfer' flags on current employees. COO HC is a formula roll-up with no transfer rows. No workbook data edited. | F10: No transfer activity found; header-only CSV shared and CEO agent notified.
A11: 11 | B11: 46290 | C11: Peer (TC PL Rollup Excel) requested read-only layout export of the 2027 Budget P&L tabs for linking. | D11: Wrote shared file layout-COO.json; no workbook data changed | E11: Tabs: COO P&L, FO, PO, CO, FE, PE. Budget Jan-Dec = U:AF, FY2027 = AG, Net Income row 132. Budget cells almost all formulas (COO P&L has 12 hardcoded zeros in U124:AF124). | F11: File shared with rollup agent; reply sent
A12: 12 | B12: 46290 | C12: Rollup Excel agent (read-only request): report HC tabs A1:H10, D5/D6 labels & references, external links, sheet names; write hc_info_COO.json | D12: Read-only scan; wrote shared file hc_info_COO.json; replied to Rollup agent | E12: HC tabs: COO HC (summary, D5/D6 blank), FO/PO/CO/FE/PE HC. D5 blank (B5 'ASSUMPTIONS'); D6=0.04 payroll tax rate, referenced 16x per tab in row 68 (=I67*$D$6). External links: ~2,160 formulas per P&L tab to [2027B Expense TC Prep w Aug Act.xlsx]; none to 2027B TC PL Rollup. | F12: No workbook data changed (only this log row added)
A13: 13 | B13: 46290 | C13: Rollup Excel agent asked to apply hc_rate_links.json: link D6 (payroll tax) and D7 (benefits) on CO/FE/FO/PE/PO HC to the rollup's T&B rates, green font, 0.0% | D13: Replaced hardcoded 4%/9% in D6:D7 on 5 HC tabs with external INDEX/MATCH links | E13: Formula: =INDEX('G:\My Drive\SLIP Folders\Budget\2027\[2027B TC PL Rollup.xlsx]T&B'!$S$104:$S$120 (D6) / $T (D7), MATCH(dept code, $R$104:$R$120,0)). Prior values 0.04/0.09 on all 5 tabs. COO HC untouched. | F13: CO 5.2%/11.9%, FE 4.1%/7.2%, FO 6.8%/16.4%, PE 3.6%/8.8%, PO 3.6%/6.2%; all match expected, no errors
A14: 14 | B14: 46290 | C14: Rollup agent asked to read back (no edits) D6/D7 T&B formulas on CO/FE/FO/PE/PO HC after rollup summary moved to R11:T27, confirm refs and values, then save. | D14: Read-only verification of D6:D7 on 5 HC sheets; saved workbook | E14: Formulas use INDEX/MATCH on '[2027B TC PL Rollup.xlsx]T&B' with ranges $R$11:$R$120 / $S$11:$S$120 / $T$11:$T$120 (not $11:$27 as expected). No errors. Values: CO 5.2%/11.9%, FE 4.1%/7.2%, FO 6.8%/16.4%, PE 3.6%/8.8%, PO 3.6%/20.6%. | F14: All values match expected; range end-row discrepancy ($120 vs $27) reported to rollup agent, not edited

Sheet Headcount -->

Sheet COO HC
A1: Slip Robotics, Inc.
A2: COO — ORGANIZATION ROLL-UP | Sep-2026 → Dec-2027 | 2027 Budget Planning
A3: Rolls up the department tabs in this workbook. All figures are formulas — edit the department tabs, not this one. Transfers between departments net to zero only at the total-company level (Org Total tab).
B10: Dept | C10: Department Name | D10: P&L | I10: ='PO HC'!I10 -> 46266 | J10: ='PO HC'!J10 -> 46296 | K10: ='PO HC'!K10 -> 46327 | L10: ='PO HC'!L10 -> 46357 | M10: ='PO HC'!M10 -> 46388 | N10: ='PO HC'!N10 -> 46419 | O10: ='PO HC'!O10 -> 46447 | P10: ='PO HC'!P10 -> 46478 | ... X10: ='PO HC'!X10 -> 46722 | Z10: 2027 Total
I11: ='PO HC'!I11 -> 1 | J11: ='PO HC'!J11 -> 2 | K11: ='PO HC'!K11 -> 3 | L11: ='PO HC'!L11 -> 4 | M11: ='PO HC'!M11 -> 5 | N11: ='PO HC'!N11 -> 6 | O11: ='PO HC'!O11 -> 7 | P11: ='PO HC'!P11 -> 8 | ... X11: ='PO HC'!X11 -> 16
B13: Total Salaries & Wages
B14: PO | C14: Production Operations | D14: COGS | I14: ='PO HC'!I67 -> 43450 | J14: ='PO HC'!J67 -> 43450 | K14: ='PO HC'!K67 -> 43450 | L14: ='PO HC'!L67 -> 43450 | M14: ='PO HC'!M67 -> 43450 | N14: ='PO HC'!N67 -> 43450 | O14: ='PO HC'!O67 -> 43450 | P14: ='PO HC'!P67 -> 43450 | ... X14: ='PO HC'!X67 -> 44753.5 | Z14: =SUM(M14:X14) -> 525310.5
B15: FO | C15: Field Operations | D15: COGS | I15: ='FO HC'!I67 -> 90012.583 | J15: ='FO HC'!J67 -> 90012.583 | K15: ='FO HC'!K67 -> 90012.583 | L15: ='FO HC'!L67 -> 90012.583 | M15: ='FO HC'!M67 -> 90012.583 | N15: ='FO HC'!N67 -> 90012.583 | O15: ='FO HC'!O67 -> 90012.583 | P15: ='FO HC'!P67 -> 90012.583 | ... X15: ='FO HC'!X67 -> 92712.961 | Z15: =SUM(M15:X15) -> 1088252.1
B16: FE | C16: Field Engineering | D16: SG&A | I16: ='FE HC'!I67 -> 55889.25 | J16: ='FE HC'!J67 -> 55889.25 | K16: ='FE HC'!K67 -> 55889.25 | L16: ='FE HC'!L67 -> 67555.917 | M16: ='FE HC'!M67 -> 67555.917 | N16: ='FE HC'!N67 -> 67555.917 | O16: ='FE HC'!O67 -> 67555.917 | P16: ='FE HC'!P67 -> 67555.917 | ... X16: ='FE HC'!X67 -> 69582.594 | Z16: =SUM(M16:X16) -> 816751.03
B17: PE | C17: Production Engineering | D17: SG&A | I17: ='PE HC'!I67 -> 89166.25 | J17: ='PE HC'!J67 -> 89166.25 | K17: ='PE HC'!K67 -> 89166.25 | L17: ='PE HC'!L67 -> 89166.25 | M17: ='PE HC'!M67 -> 89166.25 | N17: ='PE HC'!N67 -> 89166.25 | O17: ='PE HC'!O67 -> 89166.25 | P17: ='PE HC'!P67 -> 89166.25 | ... X17: ='PE HC'!X67 -> 91841.238 | Z17: =SUM(M17:X17) -> 1078020
B18: CO | C18: Central Operations | D18: SG&A | I18: ='CO HC'!I67 -> 36209.833 | J18: ='CO HC'!J67 -> 43709.833 | K18: ='CO HC'!K67 -> 43709.833 | L18: ='CO HC'!L67 -> 43709.833 | M18: ='CO HC'!M67 -> 43709.833 | N18: ='CO HC'!N67 -> 43709.833 | O18: ='CO HC'!O67 -> 43709.833 | P18: ='CO HC'!P67 -> 43709.833 | ... X18: ='CO HC'!X67 -> 45021.128 | Z18: =SUM(M18:X18) -> 528451.88
B19: Total Salaries & Wages — COO Total | I19: =SUM(I14:I18) -> 314727.92 | J19: =SUM(J14:J18) -> 322227.92 | K19: =SUM(K14:K18) -> 322227.92 | L19: =SUM(L14:L18) -> 333894.58 | M19: =SUM(M14:M18) -> 333894.58 | N19: =SUM(N14:N18) -> 333894.58 | O19: =SUM(O14:O18) -> 333894.58 | P19: =SUM(P14:P18) -> 333894.58 | ... X19: =SUM(X14:X18) -> 343911.42 | Z19: =SUM(M19:X19) -> 4036785.5
B21: Payroll Taxes
B22: PO | C22: Production Operations | D22: COGS | I22: ='PO HC'!I68 -> 1580.2286 | J22: ='PO HC'!J68 -> 1580.2286 | K22: ='PO HC'!K68 -> 1580.2286 | L22: ='PO HC'!L68 -> 1580.2286 | M22: ='PO HC'!M68 -> 1580.2286 | N22: ='PO HC'!N68 -> 1580.2286 | O22: ='PO HC'!O68 -> 1580.2286 | P22: ='PO HC'!P68 -> 1580.2286 | ... X22: ='PO HC'!X68 -> 1627.6354 | Z22: =SUM(M22:X22) -> 19104.963
B23: FO | C23: Field Operations | D23: COGS | I23: ='FO HC'!I68 -> 6163.2434 | J23: ='FO HC'!J68 -> 6163.2434 | K23: ='FO HC'!K68 -> 6163.2434 | L23: ='FO HC'!L68 -> 6163.2434 | M23: ='FO HC'!M68 -> 6163.2434 | N23: ='FO HC'!N68 -> 6163.2434 | O23: ='FO HC'!O68 -> 6163.2434 | P23: ='FO HC'!P68 -> 6163.2434 | ... X23: ='FO HC'!X68 -> 6348.1407 | Z23: =SUM(M23:X23) -> 74513.612
B24: FE | C24: Field Engineering | D24: SG&A | I24: ='FE HC'!I68 -> 2274.2492 | J24: ='FE HC'!J68 -> 2274.2492 | K24: ='FE HC'!K68 -> 2274.2492 | L24: ='FE HC'!L68 -> 2748.99 | M24: ='FE HC'!M68 -> 2748.99 | N24: ='FE HC'!N68 -> 2748.99 | O24: ='FE HC'!O68 -> 2748.99 | P24: ='FE HC'!P68 -> 2748.99 | ... X24: ='FE HC'!X68 -> 2831.4597 | Z24: =SUM(M24:X24) -> 33235.29
B25: PE | C25: Production Engineering | D25: SG&A | I25: ='PE HC'!I68 -> 3184.5425 | J25: ='PE HC'!J68 -> 3184.5425 | K25: ='PE HC'!K68 -> 3184.5425 | L25: ='PE HC'!L68 -> 3184.5425 | M25: ='PE HC'!M68 -> 3184.5425 | N25: ='PE HC'!N68 -> 3184.5425 | O25: ='PE HC'!O68 -> 3184.5425 | P25: ='PE HC'!P68 -> 3184.5425 | ... X25: ='PE HC'!X68 -> 3280.0788 | Z25: =SUM(M25:X25) -> 38501.119
B26: CO | C26: Central Operations | D26: SG&A | I26: ='CO HC'!I68 -> 1890.6805 | J26: ='CO HC'!J68 -> 2282.2898 | K26: ='CO HC'!K68 -> 2282.2898 | L26: ='CO HC'!L68 -> 2282.2898 | M26: ='CO HC'!M68 -> 2282.2898 | N26: ='CO HC'!N68 -> 2282.2898 | O26: ='CO HC'!O68 -> 2282.2898 | P26: ='CO HC'!P68 -> 2282.2898 | ... X26: ='CO HC'!X68 -> 2350.7584 | Z26: =SUM(M26:X26) -> 27592.883
B27: Payroll Taxes — COO Total | I27: =SUM(I22:I26) -> 15092.944 | J27: =SUM(J22:J26) -> 15484.553 | K27: =SUM(K22:K26) -> 15484.553 | L27: =SUM(L22:L26) -> 15959.294 | M27: =SUM(M22:M26) -> 15959.294 | N27: =SUM(N22:N26) -> 15959.294 | O27: =SUM(O22:O26) -> 15959.294 | P27: =SUM(P22:P26) -> 15959.294 | ... X27: =SUM(X22:X26) -> 16438.073 | Z27: =SUM(M27:X27) -> 192947.87
B29: Benefits
B30: PO | C30: Production Operations | D30: COGS | I30: ='PO HC'!I69 -> 8966.4588 | J30: ='PO HC'!J69 -> 8966.4588 | K30: ='PO HC'!K69 -> 8966.4588 | L30: ='PO HC'!L69 -> 8966.4588 | M30: ='PO HC'!M69 -> 8966.4588 | N30: ='PO HC'!N69 -> 8966.4588 | O30: ='PO HC'!O69 -> 8966.4588 | P30: ='PO HC'!P69 -> 8966.4588 | ... X30: ='PO HC'!X69 -> 9235.4525 | Z30: =SUM(M30:X30) -> 108404.49
B31: FO | C31: Field Operations | D31: COGS | I31: ='FO HC'!I69 -> 14766.898 | J31: ='FO HC'!J69 -> 14766.898 | K31: ='FO HC'!K69 -> 14766.898 | L31: ='FO HC'!L69 -> 14766.898 | M31: ='FO HC'!M69 -> 14766.898 | N31: ='FO HC'!N69 -> 14766.898 | O31: ='FO HC'!O69 -> 14766.898 | P31: ='FO HC'!P69 -> 14766.898 | ... X31: ='FO HC'!X69 -> 15209.905 | Z31: =SUM(M31:X31) -> 178531.8
B32: FE | C32: Field Engineering | D32: SG&A | I32: ='FE HC'!I69 -> 4036.8294 | J32: ='FE HC'!J69 -> 4036.8294 | K32: ='FE HC'!K69 -> 4036.8294 | L32: ='FE HC'!L69 -> 4879.5021 | M32: ='FE HC'!M69 -> 4879.5021 | N32: ='FE HC'!N69 -> 4879.5021 | O32: ='FE HC'!O69 -> 4879.5021 | P32: ='FE HC'!P69 -> 4879.5021 | ... X32: ='FE HC'!X69 -> 5025.8871 | Z32: =SUM(M32:X32) -> 58993.18
B33: PE | C33: Production Engineering | D33: SG&A | I33: ='PE HC'!I69 -> 7867.3457 | J33: ='PE HC'!J69 -> 7867.3457 | K33: ='PE HC'!K69 -> 7867.3457 | L33: ='PE HC'!L69 -> 7867.3457 | M33: ='PE HC'!M69 -> 7867.3457 | N33: ='PE HC'!N69 -> 7867.3457 | O33: ='PE HC'!O69 -> 7867.3457 | P33: ='PE HC'!P69 -> 7867.3457 | ... X33: ='PE HC'!X69 -> 8103.3661 | Z33: =SUM(M33:X33) -> 95116.21
B34: CO | C34: Central Operations | D34: SG&A | I34: ='CO HC'!I69 -> 4311.0723 | J34: ='CO HC'!J69 -> 5204.0077 | K34: ='CO HC'!K69 -> 5204.0077 | L34: ='CO HC'!L69 -> 5204.0077 | M34: ='CO HC'!M69 -> 5204.0077 | N34: ='CO HC'!N69 -> 5204.0077 | O34: ='CO HC'!O69 -> 5204.0077 | P34: ='CO HC'!P69 -> 5204.0077 | ... X34: ='CO HC'!X69 -> 5360.1279 | Z34: =SUM(M34:X34) -> 62916.453
B35: Benefits — COO Total | I35: =SUM(I30:I34) -> 39948.604 | J35: =SUM(J30:J34) -> 40841.54 | K35: =SUM(K30:K34) -> 40841.54 | L35: =SUM(L30:L34) -> 41684.212 | M35: =SUM(M30:M34) -> 41684.212 | N35: =SUM(N30:N34) -> 41684.212 | O35: =SUM(O30:O34) -> 41684.212 | P35: =SUM(P30:P34) -> 41684.212 | ... X35: =SUM(X30:X34) -> 42934.739 | Z35: =SUM(M35:X35) -> 503962.13
B37: Total Payroll
B38: PO | C38: Production Operations | D38: COGS | I38: ='PO HC'!I70 -> 53996.687 | J38: ='PO HC'!J70 -> 53996.687 | K38: ='PO HC'!K70 -> 53996.687 | L38: ='PO HC'!L70 -> 53996.687 | M38: ='PO HC'!M70 -> 53996.687 | N38: ='PO HC'!N70 -> 53996.687 | O38: ='PO HC'!O70 -> 53996.687 | P38: ='PO HC'!P70 -> 53996.687 | ... X38: ='PO HC'!X70 -> 55616.588 | Z38: =SUM(M38:X38) -> 652819.95
B39: FO | C39: Field Operations | D39: COGS | I39: ='FO HC'!I70 -> 110942.72 | J39: ='FO HC'!J70 -> 110942.72 | K39: ='FO HC'!K70 -> 110942.72 | L39: ='FO HC'!L70 -> 110942.72 | M39: ='FO HC'!M70 -> 110942.72 | N39: ='FO HC'!N70 -> 110942.72 | O39: ='FO HC'!O70 -> 110942.72 | P39: ='FO HC'!P70 -> 110942.72 | ... X39: ='FO HC'!X70 -> 114271.01 | Z39: =SUM(M39:X39) -> 1341297.5
B40: FE | C40: Field Engineering | D40: SG&A | I40: ='FE HC'!I70 -> 62200.329 | J40: ='FE HC'!J70 -> 62200.329 | K40: ='FE HC'!K70 -> 62200.329 | L40: ='FE HC'!L70 -> 75184.409 | M40: ='FE HC'!M70 -> 75184.409 | N40: ='FE HC'!N70 -> 75184.409 | O40: ='FE HC'!O70 -> 75184.409 | P40: ='FE HC'!P70 -> 75184.409 | ... X40: ='FE HC'!X70 -> 77439.941 | Z40: =SUM(M40:X40) -> 908979.5
B41: PE | C41: Production Engineering | D41: SG&A | I41: ='PE HC'!I70 -> 100218.14 | J41: ='PE HC'!J70 -> 100218.14 | K41: ='PE HC'!K70 -> 100218.14 | L41: ='PE HC'!L70 -> 100218.14 | M41: ='PE HC'!M70 -> 100218.14 | N41: ='PE HC'!N70 -> 100218.14 | O41: ='PE HC'!O70 -> 100218.14 | P41: ='PE HC'!P70 -> 100218.14 | ... X41: ='PE HC'!X70 -> 103224.68 | Z41: =SUM(M41:X41) -> 1211637.3
B42: CO | C42: Central Operations | D42: SG&A | I42: ='CO HC'!I70 -> 42411.586 | J42: ='CO HC'!J70 -> 51196.131 | K42: ='CO HC'!K70 -> 51196.131 | L42: ='CO HC'!L70 -> 51196.131 | M42: ='CO HC'!M70 -> 51196.131 | N42: ='CO HC'!N70 -> 51196.131 | O42: ='CO HC'!O70 -> 51196.131 | P42: ='CO HC'!P70 -> 51196.131 | ... X42: ='CO HC'!X70 -> 52732.015 | Z42: =SUM(M42:X42) -> 618961.22
B43: Total Payroll — COO Total | I43: =SUM(I38:I42) -> 369769.47 | J43: =SUM(J38:J42) -> 378554.01 | K43: =SUM(K38:K42) -> 378554.01 | L43: =SUM(L38:L42) -> 391538.09 | M43: =SUM(M38:M42) -> 391538.09 | N43: =SUM(N38:N42) -> 391538.09 | O43: =SUM(O38:O42) -> 391538.09 | P43: =SUM(P38:P42) -> 391538.09 | ... X43: =SUM(X38:X42) -> 403284.23 | Z43: =SUM(M43:X43) -> 4733695.5
B45: Total Payroll by P&L Classification
B46: COGS | I46: =SUMIF($D$38:$D$42,$B46,I$38:I$42) -> 164939.41 | J46: =SUMIF($D$38:$D$42,$B46,J$38:J$42) -> 164939.41 | K46: =SUMIF($D$38:$D$42,$B46,K$38:K$42) -> 164939.41 | L46: =SUMIF($D$38:$D$42,$B46,L$38:L$42) -> 164939.41 | M46: =SUMIF($D$38:$D$42,$B46,M$38:M$42) -> 164939.41 | N46: =SUMIF($D$38:$D$42,$B46,N$38:N$42) -> 164939.41 | O46: =SUMIF($D$38:$D$42,$B46,O$38:O$42) -> 164939.41 | P46: =SUMIF($D$38:$D$42,$B46,P$38:P$42) -> 164939.41 | ... X46: =SUMIF($D$38:$D$42,$B46,X$38:X$42) -> 169887.59 | Z46: =SUM(M46:X46) -> 1994117.5
B47: SG&A | I47: =SUMIF($D$38:$D$42,$B47,I$38:I$42) -> 204830.05 | J47: =SUMIF($D$38:$D$42,$B47,J$38:J$42) -> 213614.6 | K47: =SUMIF($D$38:$D$42,$B47,K$38:K$42) -> 213614.6 | L47: =SUMIF($D$38:$D$42,$B47,L$38:L$42) -> 226598.68 | M47: =SUMIF($D$38:$D$42,$B47,M$38:M$42) -> 226598.68 | N47: =SUMIF($D$38:$D$42,$B47,N$38:N$42) -> 226598.68 | O47: =SUMIF($D$38:$D$42,$B47,O$38:O$42) -> 226598.68 | P47: =SUMIF($D$38:$D$42,$B47,P$38:P$42) -> 226598.68 | ... X47: =SUMIF($D$38:$D$42,$B47,X$38:X$42) -> 233396.64 | Z47: =SUM(M47:X47) -> 2739578
B48: Total Payroll — COO | I48: =SUM(I46:I47) -> 369769.47 | J48: =SUM(J46:J47) -> 378554.01 | K48: =SUM(K46:K47) -> 378554.01 | L48: =SUM(L46:L47) -> 391538.09 | M48: =SUM(M46:M47) -> 391538.09 | N48: =SUM(N46:N47) -> 391538.09 | O48: =SUM(O46:O47) -> 391538.09 | P48: =SUM(P46:P47) -> 391538.09 | ... X48: =SUM(X46:X47) -> 403284.23 | Z48: =SUM(M48:X48) -> 4733695.5
B49: Check: ties to Total Payroll above (should be zero) | I49: =I48-I43 -> 0 | J49: =J48-J43 -> 0 | K49: =K48-K43 -> 0 | L49: =L48-L43 -> 0 | M49: =M48-M43 -> 0 | N49: =N48-N43 -> 0 | O49: =O48-O43 -> 0 | P49: =P48-P43 -> 0 | ... X49: =X48-X43 -> 0
B51: Transfers In — Cost Landing in This Organization ($)
B52: PO | C52: Production Operations | I52: =SUM('PO HC'!I52:I57) -> 0 | J52: =SUM('PO HC'!J52:J57) -> 0 | K52: =SUM('PO HC'!K52:K57) -> 0 | L52: =SUM('PO HC'!L52:L57) -> 0 | M52: =SUM('PO HC'!M52:M57) -> 0 | N52: =SUM('PO HC'!N52:N57) -> 0 | O52: =SUM('PO HC'!O52:O57) -> 0 | P52: =SUM('PO HC'!P52:P57) -> 0 | ... X52: =SUM('PO HC'!X52:X57) -> 0 | Z52: =SUM(M52:X52) -> 0
B53: FO | C53: Field Operations | I53: =SUM('FO HC'!I52:I57) -> 0 | J53: =SUM('FO HC'!J52:J57) -> 0 | K53: =SUM('FO HC'!K52:K57) -> 0 | L53: =SUM('FO HC'!L52:L57) -> 0 | M53: =SUM('FO HC'!M52:M57) -> 0 | N53: =SUM('FO HC'!N52:N57) -> 0 | O53: =SUM('FO HC'!O52:O57) -> 0 | P53: =SUM('FO HC'!P52:P57) -> 0 | ... X53: =SUM('FO HC'!X52:X57) -> 0 | Z53: =SUM(M53:X53) -> 0
B54: FE | C54: Field Engineering | I54: =SUM('FE HC'!I52:I57) -> 0 | J54: =SUM('FE HC'!J52:J57) -> 0 | K54: =SUM('FE HC'!K52:K57) -> 0 | L54: =SUM('FE HC'!L52:L57) -> 0 | M54: =SUM('FE HC'!M52:M57) -> 0 | N54: =SUM('FE HC'!N52:N57) -> 0 | O54: =SUM('FE HC'!O52:O57) -> 0 | P54: =SUM('FE HC'!P52:P57) -> 0 | ... X54: =SUM('FE HC'!X52:X57) -> 0 | Z54: =SUM(M54:X54) -> 0
B55: PE | C55: Production Engineering | I55: =SUM('PE HC'!I52:I57) -> 0 | J55: =SUM('PE HC'!J52:J57) -> 0 | K55: =SUM('PE HC'!K52:K57) -> 0 | L55: =SUM('PE HC'!L52:L57) -> 0 | M55: =SUM('PE HC'!M52:M57) -> 0 | N55: =SUM('PE HC'!N52:N57) -> 0 | O55: =SUM('PE HC'!O52:O57) -> 0 | P55: =SUM('PE HC'!P52:P57) -> 0 | ... X55: =SUM('PE HC'!X52:X57) -> 0 | Z55: =SUM(M55:X55) -> 0
B56: CO | C56: Central Operations | I56: =SUM('CO HC'!I52:I57) -> 0 | J56: =SUM('CO HC'!J52:J57) -> 0 | K56: =SUM('CO HC'!K52:K57) -> 0 | L56: =SUM('CO HC'!L52:L57) -> 0 | M56: =SUM('CO HC'!M52:M57) -> 0 | N56: =SUM('CO HC'!N52:N57) -> 0 | O56: =SUM('CO HC'!O52:O57) -> 0 | P56: =SUM('CO HC'!P52:P57) -> 0 | ... X56: =SUM('CO HC'!X52:X57) -> 0 | Z56: =SUM(M56:X56) -> 0
B57: Total Transfers In — COO | I57: =SUM(I52:I56) -> 0 | J57: =SUM(J52:J56) -> 0 | K57: =SUM(K52:K56) -> 0 | L57: =SUM(L52:L56) -> 0 | M57: =SUM(M52:M56) -> 0 | N57: =SUM(N52:N56) -> 0 | O57: =SUM(O52:O56) -> 0 | P57: =SUM(P52:P56) -> 0 | ... X57: =SUM(X52:X56) -> 0 | Z57: =SUM(M57:X57) -> 0
B59: Transfer Headcount Activity (people moving, by effective month)
B60: Transfers In (headcount) | I60: =COUNTIF('PO HC'!$E$52:$E$57,I$10)+COUNTIF('FO HC'!$E$52:$E$57,I$10)+COUNTIF('FE HC'!$E$52:$E$57,I$10)+COUNTIF('PE HC'!$E$52:$E$57,I$10)+COUNTIF('CO HC'!$E$52:$E$57,I$10) -> 0 | J60: =COUNTIF('PO HC'!$E$52:$E$57,J$10)+COUNTIF('FO HC'!$E$52:$E$57,J$10)+COUNTIF('FE HC'!$E$52:$E$57,J$10)+COUNTIF('PE HC'!$E$52:$E$57,J$10)+COUNTIF('CO HC'!$E$52:$E$57,J$10) -> 0 | K60: =COUNTIF('PO HC'!$E$52:$E$57,K$10)+COUNTIF('FO HC'!$E$52:$E$57,K$10)+COUNTIF('FE HC'!$E$52:$E$57,K$10)+COUNTIF('PE HC'!$E$52:$E$57,K$10)+COUNTIF('CO HC'!$E$52:$E$57,K$10) -> 0 | L60: =COUNTIF('PO HC'!$E$52:$E$57,L$10)+COUNTIF('FO HC'!$E$52:$E$57,L$10)+COUNTIF('FE HC'!$E$52:$E$57,L$10)+COUNTIF('PE HC'!$E$52:$E$57,L$10)+COUNTIF('CO HC'!$E$52:$E$57,L$10) -> 0 | M60: =COUNTIF('PO HC'!$E$52:$E$57,M$10)+COUNTIF('FO HC'!$E$52:$E$57,M$10)+COUNTIF('FE HC'!$E$52:$E$57,M$10)+COUNTIF('PE HC'!$E$52:$E$57,M$10)+COUNTIF('CO HC'!$E$52:$E$57,M$10) -> 0 | N60: =COUNTIF('PO HC'!$E$52:$E$57,N$10)+COUNTIF('FO HC'!$E$52:$E$57,N$10)+COUNTIF('FE HC'!$E$52:$E$57,N$10)+COUNTIF('PE HC'!$E$52:$E$57,N$10)+COUNTIF('CO HC'!$E$52:$E$57,N$10) -> 0 | O60: =COUNTIF('PO HC'!$E$52:$E$57,O$10)+COUNTIF('FO HC'!$E$52:$E$57,O$10)+COUNTIF('FE HC'!$E$52:$E$57,O$10)+COUNTIF('PE HC'!$E$52:$E$57,O$10)+COUNTIF('CO HC'!$E$52:$E$57,O$10) -> 0 | P60: =COUNTIF('PO HC'!$E$52:$E$57,P$10)+COUNTIF('FO HC'!$E$52:$E$57,P$10)+COUNTIF('FE HC'!$E$52:$E$57,P$10)+COUNTIF('PE HC'!$E$52:$E$57,P$10)+COUNTIF('CO HC'!$E$52:$E$57,P$10) -> 0 | ... X60: =COUNTIF('PO HC'!$E$52:$E$57,X$10)+COUNTIF('FO HC'!$E$52:$E$57,X$10)+COUNTIF('FE HC'!$E$52:$E$57,X$10)+COUNTIF('PE HC'!$E$52:$E$57,X$10)+COUNTIF('CO HC'!$E$52:$E$57,X$10) -> 0 | Z60: =SUM(M60:X60) -> 0
B61: Transfers Out (headcount) | I61: =COUNTIF('PO HC'!$E$59:$E$64,I$10)+COUNTIF('FO HC'!$E$59:$E$64,I$10)+COUNTIF('FE HC'!$E$59:$E$64,I$10)+COUNTIF('PE HC'!$E$59:$E$64,I$10)+COUNTIF('CO HC'!$E$59:$E$64,I$10) -> 0 | J61: =COUNTIF('PO HC'!$E$59:$E$64,J$10)+COUNTIF('FO HC'!$E$59:$E$64,J$10)+COUNTIF('FE HC'!$E$59:$E$64,J$10)+COUNTIF('PE HC'!$E$59:$E$64,J$10)+COUNTIF('CO HC'!$E$59:$E$64,J$10) -> 0 | K61: =COUNTIF('PO HC'!$E$59:$E$64,K$10)+COUNTIF('FO HC'!$E$59:$E$64,K$10)+COUNTIF('FE HC'!$E$59:$E$64,K$10)+COUNTIF('PE HC'!$E$59:$E$64,K$10)+COUNTIF('CO HC'!$E$59:$E$64,K$10) -> 0 | L61: =COUNTIF('PO HC'!$E$59:$E$64,L$10)+COUNTIF('FO HC'!$E$59:$E$64,L$10)+COUNTIF('FE HC'!$E$59:$E$64,L$10)+COUNTIF('PE HC'!$E$59:$E$64,L$10)+COUNTIF('CO HC'!$E$59:$E$64,L$10) -> 0 | M61: =COUNTIF('PO HC'!$E$59:$E$64,M$10)+COUNTIF('FO HC'!$E$59:$E$64,M$10)+COUNTIF('FE HC'!$E$59:$E$64,M$10)+COUNTIF('PE HC'!$E$59:$E$64,M$10)+COUNTIF('CO HC'!$E$59:$E$64,M$10) -> 0 | N61: =COUNTIF('PO HC'!$E$59:$E$64,N$10)+COUNTIF('FO HC'!$E$59:$E$64,N$10)+COUNTIF('FE HC'!$E$59:$E$64,N$10)+COUNTIF('PE HC'!$E$59:$E$64,N$10)+COUNTIF('CO HC'!$E$59:$E$64,N$10) -> 0 | O61: =COUNTIF('PO HC'!$E$59:$E$64,O$10)+COUNTIF('FO HC'!$E$59:$E$64,O$10)+COUNTIF('FE HC'!$E$59:$E$64,O$10)+COUNTIF('PE HC'!$E$59:$E$64,O$10)+COUNTIF('CO HC'!$E$59:$E$64,O$10) -> 0 | P61: =COUNTIF('PO HC'!$E$59:$E$64,P$10)+COUNTIF('FO HC'!$E$59:$E$64,P$10)+COUNTIF('FE HC'!$E$59:$E$64,P$10)+COUNTIF('PE HC'!$E$59:$E$64,P$10)+COUNTIF('CO HC'!$E$59:$E$64,P$10) -> 0 | ... X61: =COUNTIF('PO HC'!$E$59:$E$64,X$10)+COUNTIF('FO HC'!$E$59:$E$64,X$10)+COUNTIF('FE HC'!$E$59:$E$64,X$10)+COUNTIF('PE HC'!$E$59:$E$64,X$10)+COUNTIF('CO HC'!$E$59:$E$64,X$10) -> 0 | Z61: =SUM(M61:X61) -> 0
B62: Net Headcount Change from Transfers | I62: =I60-I61 -> 0 | J62: =J60-J61 -> 0 | K62: =K60-K61 -> 0 | L62: =L60-L61 -> 0 | M62: =M60-M61 -> 0 | N62: =N60-N61 -> 0 | O62: =O60-O61 -> 0 | P62: =P60-P61 -> 0 | ... X62: =X60-X61 -> 0 | Z62: =SUM(M62:X62) -> 0
B64: Headcount (#) — Active Employees by Month | Z64: Dec-27 Ending
B65: PO | C65: Production Operations | D65: COGS | I65: =COUNTIF('PO HC'!I$14:I$57,">0") -> 9 | J65: =COUNTIF('PO HC'!J$14:J$57,">0") -> 9 | K65: =COUNTIF('PO HC'!K$14:K$57,">0") -> 9 | L65: =COUNTIF('PO HC'!L$14:L$57,">0") -> 9 | M65: =COUNTIF('PO HC'!M$14:M$57,">0") -> 9 | N65: =COUNTIF('PO HC'!N$14:N$57,">0") -> 9 | O65: =COUNTIF('PO HC'!O$14:O$57,">0") -> 9 | P65: =COUNTIF('PO HC'!P$14:P$57,">0") -> 9 | ... X65: =COUNTIF('PO HC'!X$14:X$57,">0") -> 9 | Z65: =X65 -> 9
B66: FO | C66: Field Operations | D66: COGS | I66: =COUNTIF('FO HC'!I$14:I$57,">0") -> 16 | J66: =COUNTIF('FO HC'!J$14:J$57,">0") -> 16 | K66: =COUNTIF('FO HC'!K$14:K$57,">0") -> 16 | L66: =COUNTIF('FO HC'!L$14:L$57,">0") -> 16 | M66: =COUNTIF('FO HC'!M$14:M$57,">0") -> 16 | N66: =COUNTIF('FO HC'!N$14:N$57,">0") -> 16 | O66: =COUNTIF('FO HC'!O$14:O$57,">0") -> 16 | P66: =COUNTIF('FO HC'!P$14:P$57,">0") -> 16 | ... X66: =COUNTIF('FO HC'!X$14:X$57,">0") -> 16 | Z66: =X66 -> 16
B67: FE | C67: Field Engineering | D67: SG&A | I67: =COUNTIF('FE HC'!I$14:I$57,">0") -> 6 | J67: =COUNTIF('FE HC'!J$14:J$57,">0") -> 6 | K67: =COUNTIF('FE HC'!K$14:K$57,">0") -> 6 | L67: =COUNTIF('FE HC'!L$14:L$57,">0") -> 7 | M67: =COUNTIF('FE HC'!M$14:M$57,">0") -> 7 | N67: =COUNTIF('FE HC'!N$14:N$57,">0") -> 7 | O67: =COUNTIF('FE HC'!O$14:O$57,">0") -> 7 | P67: =COUNTIF('FE HC'!P$14:P$57,">0") -> 7 | ... X67: =COUNTIF('FE HC'!X$14:X$57,">0") -> 7 | Z67: =X67 -> 7
B68: PE | C68: Production Engineering | D68: SG&A | I68: =COUNTIF('PE HC'!I$14:I$57,">0") -> 9 | J68: =COUNTIF('PE HC'!J$14:J$57,">0") -> 9 | K68: =COUNTIF('PE HC'!K$14:K$57,">0") -> 9 | L68: =COUNTIF('PE HC'!L$14:L$57,">0") -> 9 | M68: =COUNTIF('PE HC'!M$14:M$57,">0") -> 9 | N68: =COUNTIF('PE HC'!N$14:N$57,">0") -> 9 | O68: =COUNTIF('PE HC'!O$14:O$57,">0") -> 9 | P68: =COUNTIF('PE HC'!P$14:P$57,">0") -> 9 | ... X68: =COUNTIF('PE HC'!X$14:X$57,">0") -> 9 | Z68: =X68 -> 9
B69: CO | C69: Central Operations | D69: SG&A | I69: =COUNTIF('CO HC'!I$14:I$57,">0") -> 4 | J69: =COUNTIF('CO HC'!J$14:J$57,">0") -> 5 | K69: =COUNTIF('CO HC'!K$14:K$57,">0") -> 5 | L69: =COUNTIF('CO HC'!L$14:L$57,">0") -> 5 | M69: =COUNTIF('CO HC'!M$14:M$57,">0") -> 5 | N69: =COUNTIF('CO HC'!N$14:N$57,">0") -> 5 | O69: =COUNTIF('CO HC'!O$14:O$57,">0") -> 5 | P69: =COUNTIF('CO HC'!P$14:P$57,">0") -> 5 | ... X69: =COUNTIF('CO HC'!X$14:X$57,">0") -> 5 | Z69: =X69 -> 5
B70: Total Headcount — COO Total | I70: =SUM(I65:I69) -> 44 | J70: =SUM(J65:J69) -> 45 | K70: =SUM(K65:K69) -> 45 | L70: =SUM(L65:L69) -> 46 | M70: =SUM(M65:M69) -> 46 | N70: =SUM(N65:N69) -> 46 | O70: =SUM(O65:O69) -> 46 | P70: =SUM(P65:P69) -> 46 | ... X70: =SUM(X65:X69) -> 46 | Z70: =X70 -> 46
B72: Headcount by P&L Classification (#)
B73: COGS | I73: =SUMIF($D$65:$D$69,$B73,I$65:I$69) -> 25 | J73: =SUMIF($D$65:$D$69,$B73,J$65:J$69) -> 25 | K73: =SUMIF($D$65:$D$69,$B73,K$65:K$69) -> 25 | L73: =SUMIF($D$65:$D$69,$B73,L$65:L$69) -> 25 | M73: =SUMIF($D$65:$D$69,$B73,M$65:M$69) -> 25 | N73: =SUMIF($D$65:$D$69,$B73,N$65:N$69) -> 25 | O73: =SUMIF($D$65:$D$69,$B73,O$65:O$69) -> 25 | P73: =SUMIF($D$65:$D$69,$B73,P$65:P$69) -> 25 | ... X73: =SUMIF($D$65:$D$69,$B73,X$65:X$69) -> 25 | Z73: =X73 -> 25
B74: SG&A | I74: =SUMIF($D$65:$D$69,$B74,I$65:I$69) -> 19 | J74: =SUMIF($D$65:$D$69,$B74,J$65:J$69) -> 20 | K74: =SUMIF($D$65:$D$69,$B74,K$65:K$69) -> 20 | L74: =SUMIF($D$65:$D$69,$B74,L$65:L$69) -> 21 | M74: =SUMIF($D$65:$D$69,$B74,M$65:M$69) -> 21 | N74: =SUMIF($D$65:$D$69,$B74,N$65:N$69) -> 21 | O74: =SUMIF($D$65:$D$69,$B74,O$65:O$69) -> 21 | P74: =SUMIF($D$65:$D$69,$B74,P$65:P$69) -> 21 | ... X74: =SUMIF($D$65:$D$69,$B74,X$65:X$69) -> 21 | Z74: =X74 -> 21
B75: Total Headcount — COO | I75: =SUM(I73:I74) -> 44 | J75: =SUM(J73:J74) -> 45 | K75: =SUM(K73:K74) -> 45 | L75: =SUM(L73:L74) -> 46 | M75: =SUM(M73:M74) -> 46 | N75: =SUM(N73:N74) -> 46 | O75: =SUM(O73:O74) -> 46 | P75: =SUM(P73:P74) -> 46 | ... X75: =SUM(X73:X74) -> 46 | Z75: =X75 -> 46
B76: Check: ties to Total Headcount above (should be zero) | I76: =I75-I70 -> 0 | J76: =J75-J70 -> 0 | K76: =K75-K70 -> 0 | L76: =L75-L70 -> 0 | M76: =M75-M70 -> 0 | N76: =N75-N70 -> 0 | O76: =O75-O70 -> 0 | P76: =P75-P70 -> 0 | ... X76: =X75-X70 -> 0

Sheet FO HC
A1: Slip Robotics, Inc.
A2: FIELD OPERATIONS (FO) — 16 Month Headcount & Labor Build (Sep-2026 → Dec-2027)
A3: Build labor by employee for 16 months: Sep-2026 through Dec-2027. Pick Start and End months from the dropdown (End defaults to Dec-27). Leave Start blank for unfilled positions. Salaries / Taxes / Benefits flow to the Budget file.
A4: Leader: COO | Dept Code: FO | P&L Classification: COGS | GL Accounts — Salaries 5510 · Taxes 5530 · Benefits 5540
B5: ASSUMPTIONS
B6: Employer payroll tax rate (% of wages) | D6: =INDEX('[1]T&B'!$S$13:$S$122,MATCH("FO",'[1]T&B'!$R$13:$R$122,0)) -> 0.068470908
B7: Benefits load (% of salary) | D7: =INDEX('[1]T&B'!$T$13:$T$122,MATCH("FO",'[1]T&B'!$R$13:$R$122,0)) -> 0.16405371
B8: Annual Increase Month in Budget year | D8: 46661 | V8: Annual
V9: Increase
B10: Employee | C10: Title | D10: Annual Salary | E10: Start Month | F10: End Month | G10: Annual Increase | H10: Increase Month | I10: =DATE(2026,9,1) -> 46266 | J10: =DATE(2026,10,1) -> 46296 | K10: =DATE(2026,11,1) -> 46327 | L10: =DATE(2026,12,1) -> 46357 | M10: =DATE(2027,1,1) -> 46388 | N10: =DATE(2027,2,1) -> 46419 | O10: =DATE(2027,3,1) -> 46447 | P10: =DATE(2027,4,1) -> 46478 | Q10: =DATE(2027,5,1) -> 46508 | R10: =DATE(2027,6,1) -> 46539 | S10: =DATE(2027,7,1) -> 46569 | T10: =DATE(2027,8,1) -> 46600 | U10: =DATE(2027,9,1) -> 46631 | V10: =DATE(2027,10,1) -> 46661 | W10: =DATE(2027,11,1) -> 46692 | X10: =DATE(2027,12,1) -> 46722 | Z10: 2027 Total | AB10: Input check
E11: (pick from list) | F11: (pick from list) | H11: Month index → | I11: 1 | J11: 2 | K11: 3 | L11: 4 | M11: 5 | N11: 6 | O11: 7 | P11: 8 | Q11: 9 | R11: 10 | S11: 11 | T11: 12 | U11: 13 | V11: 14 | W11: 15 | X11: 16
B13: Current Employees
B14: Gavin Grizzle | C14: Field Technician | D14: 60513 | E14: 46266 | F14: 46722 | G14: 0.03 | H14: =$D$8 -> 46661 | I14: =IF(OR($D14="",$E14="",NOT(ISNUMBER($D14))),"",IF(AND($E14<=I$10,IF($F14="",$X$10,$F14)>=I$10),$D14/12*(1+N($G14))^IF(AND(ISNUMBER($H14),I$10>=$H14),1+INT(DATEDIF($H14,I$10,"m")/12),0),0)) -> 5042.75 | J14: =IF(OR($D14="",$E14="",NOT(ISNUMBER($D14))),"",IF(AND($E14<=J$10,IF($F14="",$X$10,$F14)>=J$10),$D14/12*(1+N($G14))^IF(AND(ISNUMBER($H14),J$10>=$H14),1+INT(DATEDIF($H14,J$10,"m")/12),0),0)) -> 5042.75 | K14: =IF(OR($D14="",$E14="",NOT(ISNUMBER($D14))),"",IF(AND($E14<=K$10,IF($F14="",$X$10,$F14)>=K$10),$D14/12*(1+N($G14))^IF(AND(ISNUMBER($H14),K$10>=$H14),1+INT(DATEDIF($H14,K$10,"m")/12),0),0)) -> 5042.75 | L14: =IF(OR($D14="",$E14="",NOT(ISNUMBER($D14))),"",IF(AND($E14<=L$10,IF($F14="",$X$10,$F14)>=L$10),$D14/12*(1+N($G14))^IF(AND(ISNUMBER($H14),L$10>=$H14),1+INT(DATEDIF($H14,L$10,"m")/12),0),0)) -> 5042.75 | M14: =IF(OR($D14="",$E14="",NOT(ISNUMBER($D14))),"",IF(AND($E14<=M$10,IF($F14="",$X$10,$F14)>=M$10),$D14/12*(1+N($G14))^IF(AND(ISNUMBER($H14),M$10>=$H14),1+INT(DATEDIF($H14,M$10,"m")/12),0),0)) -> 5042.75 | N14: =IF(OR($D14="",$E14="",NOT(ISNUMBER($D14))),"",IF(AND($E14<=N$10,IF($F14="",$X$10,$F14)>=N$10),$D14/12*(1+N($G14))^IF(AND(ISNUMBER($H14),N$10>=$H14),1+INT(DATEDIF($H14,N$10,"m")/12),0),0)) -> 5042.75 | O14: =IF(OR($D14="",$E14="",NOT(ISNUMBER($D14))),"",IF(AND($E14<=O$10,IF($F14="",$X$10,$F14)>=O$10),$D14/12*(1+N($G14))^IF(AND(ISNUMBER($H14),O$10>=$H14),1+INT(DATEDIF($H14,O$10,"m")/12),0),0)) -> 5042.75 | P14: =IF(OR($D14="",$E14="",NOT(ISNUMBER($D14))),"",IF(AND($E14<=P$10,IF($F14="",$X$10,$F14)>=P$10),$D14/12*(1+N($G14))^IF(AND(ISNUMBER($H14),P$10>=$H14),1+INT(DATEDIF($H14,P$10,"m")/12),0),0)) -> 5042.75 | ... X14: =IF(OR($D14="",$E14="",NOT(ISNUMBER($D14))),"",IF(AND($E14<=X$10,IF($F14="",$X$10,$F14)>=X$10),$D14/12*(1+N($G14))^IF(AND(ISNUMBER($H14),X$10>=$H14),1+INT(DATEDIF($H14,X$10,"m")/12),0),0)) -> 5194.0325 | Z14: =SUM(M14:X14) -> 60966.848 | AB14: =IF($D14&$E14="","",IF(AND($D14<>"",NOT(ISNUMBER($D14))),"Salary must be a number",IF(AND($D14<>"",$E14=""),"Start month missing",IF(AND(ISNUMBER($E14),ISNUMBER($F14),$F14<$E14),"End is before Start",IF(AND($D14<>"",NOT(ISNUMBER($H14))),"Increase month missing","")))))
B15: James Murphy | C15: Field Technician | D15: 70021 | E15: 46266 | F15: 46722 | G15: 0.03 | H15: =$D$8 -> 46661 | I15: =IF(OR($D15="",$E15="",NOT(ISNUMBER($D15))),"",IF(AND($E15<=I$10,IF($F15="",$X$10,$F15)>=I$10),$D15/12*(1+N($G15))^IF(AND(ISNUMBER($H15),I$10>=$H15),1+INT(DATEDIF($H15,I$10,"m")/12),0),0)) -> 5835.0833 | J15: =IF(OR($D15="",$E15="",NOT(ISNUMBER($D15))),"",IF(AND($E15<=J$10,IF($F15="",$X$10,$F15)>=J$10),$D15/12*(1+N($G15))^IF(AND(ISNUMBER($H15),J$10>=$H15),1+INT(DATEDIF($H15,J$10,"m")/12),0),0)) -> 5835.0833 | K15: =IF(OR($D15="",$E15="",NOT(ISNUMBER($D15))),"",IF(AND($E15<=K$10,IF($F15="",$X$10,$F15)>=K$10),$D15/12*(1+N($G15))^IF(AND(ISNUMBER($H15),K$10>=$H15),1+INT(DATEDIF($H15,K$10,"m")/12),0),0)) -> 5835.0833 | L15: =IF(OR($D15="",$E15="",NOT(ISNUMBER($D15))),"",IF(AND($E15<=L$10,IF($F15="",$X$10,$F15)>=L$10),$D15/12*(1+N($G15))^IF(AND(ISNUMBER($H15),L$10>=$H15),1+INT(DATEDIF($H15,L$10,"m")/12),0),0)) -> 5835.0833 | M15: =IF(OR($D15="",$E15="",NOT(ISNUMBER($D15))),"",IF(AND($E15<=M$10,IF($F15="",$X$10,$F15)>=M$10),$D15/12*(1+N($G15))^IF(AND(ISNUMBER($H15),M$10>=$H15),1+INT(DATEDIF($H15,M$10,"m")/12),0),0)) -> 5835.0833 | N15: =IF(OR($D15="",$E15="",NOT(ISNUMBER($D15))),"",IF(AND($E15<=N$10,IF($F15="",$X$10,$F15)>=N$10),$D15/12*(1+N($G15))^IF(AND(ISNUMBER($H15),N$10>=$H15),1+INT(DATEDIF($H15,N$10,"m")/12),0),0)) -> 5835.0833 | O15: =IF(OR($D15="",$E15="",NOT(ISNUMBER($D15))),"",IF(AND($E15<=O$10,IF($F15="",$X$10,$F15)>=O$10),$D15/12*(1+N($G15))^IF(AND(ISNUMBER($H15),O$10>=$H15),1+INT(DATEDIF($H15,O$10,"m")/12),0),0)) -> 5835.0833 | P15: =IF(OR($D15="",$E15="",NOT(ISNUMBER($D15))),"",IF(AND($E15<=P$10,IF($F15="",$X$10,$F15)>=P$10),$D15/12*(1+N($G15))^IF(AND(ISNUMBER($H15),P$10>=$H15),1+INT(DATEDIF($H15,P$10,"m")/12),0),0)) -> 5835.0833 | ... X15: =IF(OR($D15="",$E15="",NOT(ISNUMBER($D15))),"",IF(AND($E15<=X$10,IF($F15="",$X$10,$F15)>=X$10),$D15/12*(1+N($G15))^IF(AND(ISNUMBER($H15),X$10>=$H15),1+INT(DATEDIF($H15,X$10,"m")/12),0),0)) -> 6010.1358 | Z15: =SUM(M15:X15) -> 70546.158 | AB15: =IF($D15&$E15="","",IF(AND($D15<>"",NOT(ISNUMBER($D15))),"Salary must be a number",IF(AND($D15<>"",$E15=""),"Start month missing",IF(AND(ISNUMBER($E15),ISNUMBER($F15),$F15<$E15),"End is before Start",IF(AND($D15<>"",NOT(ISNUMBER($H15))),"Increase month missing","")))))
B16: Adam Trostle | C16: Field Technician | D16: 69376 | E16: 46266 | F16: 46722 | G16: 0.03 | H16: =$D$8 -> 46661 | I16: =IF(OR($D16="",$E16="",NOT(ISNUMBER($D16))),"",IF(AND($E16<=I$10,IF($F16="",$X$10,$F16)>=I$10),$D16/12*(1+N($G16))^IF(AND(ISNUMBER($H16),I$10>=$H16),1+INT(DATEDIF($H16,I$10,"m")/12),0),0)) -> 5781.3333 | J16: =IF(OR($D16="",$E16="",NOT(ISNUMBER($D16))),"",IF(AND($E16<=J$10,IF($F16="",$X$10,$F16)>=J$10),$D16/12*(1+N($G16))^IF(AND(ISNUMBER($H16),J$10>=$H16),1+INT(DATEDIF($H16,J$10,"m")/12),0),0)) -> 5781.3333 | K16: =IF(OR($D16="",$E16="",NOT(ISNUMBER($D16))),"",IF(AND($E16<=K$10,IF($F16="",$X$10,$F16)>=K$10),$D16/12*(1+N($G16))^IF(AND(ISNUMBER($H16),K$10>=$H16),1+INT(DATEDIF($H16,K$10,"m")/12),0),0)) -> 5781.3333 | L16: =IF(OR($D16="",$E16="",NOT(ISNUMBER($D16))),"",IF(AND($E16<=L$10,IF($F16="",$X$10,$F16)>=L$10),$D16/12*(1+N($G16))^IF(AND(ISNUMBER($H16),L$10>=$H16),1+INT(DATEDIF($H16,L$10,"m")/12),0),0)) -> 5781.3333 | M16: =IF(OR($D16="",$E16="",NOT(ISNUMBER($D16))),"",IF(AND($E16<=M$10,IF($F16="",$X$10,$F16)>=M$10),$D16/12*(1+N($G16))^IF(AND(ISNUMBER($H16),M$10>=$H16),1+INT(DATEDIF($H16,M$10,"m")/12),0),0)) -> 5781.3333 | N16: =IF(OR($D16="",$E16="",NOT(ISNUMBER($D16))),"",IF(AND($E16<=N$10,IF($F16="",$X$10,$F16)>=N$10),$D16/12*(1+N($G16))^IF(AND(ISNUMBER($H16),N$10>=$H16),1+INT(DATEDIF($H16,N$10,"m")/12),0),0)) -> 5781.3333 | O16: =IF(OR($D16="",$E16="",NOT(ISNUMBER($D16))),"",IF(AND($E16<=O$10,IF($F16="",$X$10,$F16)>=O$10),$D16/12*(1+N($G16))^IF(AND(ISNUMBER($H16),O$10>=$H16),1+INT(DATEDIF($H16,O$10,"m")/12),0),0)) -> 5781.3333 | P16: =IF(OR($D16="",$E16="",NOT(ISNUMBER($D16))),"",IF(AND($E16<=P$10,IF($F16="",$X$10,$F16)>=P$10),$D16/12*(1+N($G16))^IF(AND(ISNUMBER($H16),P$10>=$H16),1+INT(DATEDIF($H16,P$10,"m")/12),0),0)) -> 5781.3333 | ... X16: =IF(OR($D16="",$E16="",NOT(ISNUMBER($D16))),"",IF(AND($E16<=X$10,IF($F16="",$X$10,$F16)>=X$10),$D16/12*(1+N($G16))^IF(AND(ISNUMBER($H16),X$10>=$H16),1+INT(DATEDIF($H16,X$10,"m")/12),0),0)) -> 5954.7733 | Z16: =SUM(M16:X16) -> 69896.32 | AB16: =IF($D16&$E16="","",IF(AND($D16<>"",NOT(ISNUMBER($D16))),"Salary must be a number",IF(AND($D16<>"",$E16=""),"Start month missing",IF(AND(ISNUMBER($E16),ISNUMBER($F16),$F16<$E16),"End is before Start",IF(AND($D16<>"",NOT(ISNUMBER($H16))),"Increase month missing","")))))
B17: Joe Byers | C17: Field Technician | D17: 61687 | E17: 46266 | F17: 46722 | G17: 0.03 | H17: =$D$8 -> 46661 | I17: =IF(OR($D17="",$E17="",NOT(ISNUMBER($D17))),"",IF(AND($E17<=I$10,IF($F17="",$X$10,$F17)>=I$10),$D17/12*(1+N($G17))^IF(AND(ISNUMBER($H17),I$10>=$H17),1+INT(DATEDIF($H17,I$10,"m")/12),0),0)) -> 5140.5833 | J17: =IF(OR($D17="",$E17="",NOT(ISNUMBER($D17))),"",IF(AND($E17<=J$10,IF($F17="",$X$10,$F17)>=J$10),$D17/12*(1+N($G17))^IF(AND(ISNUMBER($H17),J$10>=$H17),1+INT(DATEDIF($H17,J$10,"m")/12),0),0)) -> 5140.5833 | K17: =IF(OR($D17="",$E17="",NOT(ISNUMBER($D17))),"",IF(AND($E17<=K$10,IF($F17="",$X$10,$F17)>=K$10),$D17/12*(1+N($G17))^IF(AND(ISNUMBER($H17),K$10>=$H17),1+INT(DATEDIF($H17,K$10,"m")/12),0),0)) -> 5140.5833 | L17: =IF(OR($D17="",$E17="",NOT(ISNUMBER($D17))),"",IF(AND($E17<=L$10,IF($F17="",$X$10,$F17)>=L$10),$D17/12*(1+N($G17))^IF(AND(ISNUMBER($H17),L$10>=$H17),1+INT(DATEDIF($H17,L$10,"m")/12),0),0)) -> 5140.5833 | M17: =IF(OR($D17="",$E17="",NOT(ISNUMBER($D17))),"",IF(AND($E17<=M$10,IF($F17="",$X$10,$F17)>=M$10),$D17/12*(1+N($G17))^IF(AND(ISNUMBER($H17),M$10>=$H17),1+INT(DATEDIF($H17,M$10,"m")/12),0),0)) -> 5140.5833 | N17: =IF(OR($D17="",$E17="",NOT(ISNUMBER($D17))),"",IF(AND($E17<=N$10,IF($F17="",$X$10,$F17)>=N$10),$D17/12*(1+N($G17))^IF(AND(ISNUMBER($H17),N$10>=$H17),1+INT(DATEDIF($H17,N$10,"m")/12),0),0)) -> 5140.5833 | O17: =IF(OR($D17="",$E17="",NOT(ISNUMBER($D17))),"",IF(AND($E17<=O$10,IF($F17="",$X$10,$F17)>=O$10),$D17/12*(1+N($G17))^IF(AND(ISNUMBER($H17),O$10>=$H17),1+INT(DATEDIF($H17,O$10,"m")/12),0),0)) -> 5140.5833 | P17: =IF(OR($D17="",$E17="",NOT(ISNUMBER($D17))),"",IF(AND($E17<=P$10,IF($F17="",$X$10,$F17)>=P$10),$D17/12*(1+N($G17))^IF(AND(ISNUMBER($H17),P$10>=$H17),1+INT(DATEDIF($H17,P$10,"m")/12),0),0)) -> 5140.5833 | ... X17: =IF(OR($D17="",$E17="",NOT(ISNUMBER($D17))),"",IF(AND($E17<=X$10,IF($F17="",$X$10,$F17)>=X$10),$D17/12*(1+N($G17))^IF(AND(ISNUMBER($H17),X$10>=$H17),1+INT(DATEDIF($H17,X$10,"m")/12),0),0)) -> 5294.8008 | Z17: =SUM(M17:X17) -> 62149.653 | AB17: =IF($D17&$E17="","",IF(AND($D17<>"",NOT(ISNUMBER($D17))),"Salary must be a number",IF(AND($D17<>"",$E17=""),"Start month missing",IF(AND(ISNUMBER($E17),ISNUMBER($F17),$F17<$E17),"End is before Start",IF(AND($D17<>"",NOT(ISNUMBER($H17))),"Increase month missing","")))))
B18: Chad Seyfried | C18: Field Technician | D18: 60593 | E18: 46266 | F18: 46722 | G18: 0.03 | H18: =$D$8 -> 46661 | I18: =IF(OR($D18="",$E18="",NOT(ISNUMBER($D18))),"",IF(AND($E18<=I$10,IF($F18="",$X$10,$F18)>=I$10),$D18/12*(1+N($G18))^IF(AND(ISNUMBER($H18),I$10>=$H18),1+INT(DATEDIF($H18,I$10,"m")/12),0),0)) -> 5049.4167 | J18: =IF(OR($D18="",$E18="",NOT(ISNUMBER($D18))),"",IF(AND($E18<=J$10,IF($F18="",$X$10,$F18)>=J$10),$D18/12*(1+N($G18))^IF(AND(ISNUMBER($H18),J$10>=$H18),1+INT(DATEDIF($H18,J$10,"m")/12),0),0)) -> 5049.4167 | K18: =IF(OR($D18="",$E18="",NOT(ISNUMBER($D18))),"",IF(AND($E18<=K$10,IF($F18="",$X$10,$F18)>=K$10),$D18/12*(1+N($G18))^IF(AND(ISNUMBER($H18),K$10>=$H18),1+INT(DATEDIF($H18,K$10,"m")/12),0),0)) -> 5049.4167 | L18: =IF(OR($D18="",$E18="",NOT(ISNUMBER($D18))),"",IF(AND($E18<=L$10,IF($F18="",$X$10,$F18)>=L$10),$D18/12*(1+N($G18))^IF(AND(ISNUMBER($H18),L$10>=$H18),1+INT(DATEDIF($H18,L$10,"m")/12),0),0)) -> 5049.4167 | M18: =IF(OR($D18="",$E18="",NOT(ISNUMBER($D18))),"",IF(AND($E18<=M$10,IF($F18="",$X$10,$F18)>=M$10),$D18/12*(1+N($G18))^IF(AND(ISNUMBER($H18),M$10>=$H18),1+INT(DATEDIF($H18,M$10,"m")/12),0),0)) -> 5049.4167 | N18: =IF(OR($D18="",$E18="",NOT(ISNUMBER($D18))),"",IF(AND($E18<=N$10,IF($F18="",$X$10,$F18)>=N$10),$D18/12*(1+N($G18))^IF(AND(ISNUMBER($H18),N$10>=$H18),1+INT(DATEDIF($H18,N$10,"m")/12),0),0)) -> 5049.4167 | O18: =IF(OR($D18="",$E18="",NOT(ISNUMBER($D18))),"",IF(AND($E18<=O$10,IF($F18="",$X$10,$F18)>=O$10),$D18/12*(1+N($G18))^IF(AND(ISNUMBER($H18),O$10>=$H18),1+INT(DATEDIF($H18,O$10,"m")/12),0),0)) -> 5049.4167 | P18: =IF(OR($D18="",$E18="",NOT(ISNUMBER($D18))),"",IF(AND($E18<=P$10,IF($F18="",$X$10,$F18)>=P$10),$D18/12*(1+N($G18))^IF(AND(ISNUMBER($H18),P$10>=$H18),1+INT(DATEDIF($H18,P$10,"m")/12),0),0)) -> 5049.4167 | ... X18: =IF(OR($D18="",$E18="",NOT(ISNUMBER($D18))),"",IF(AND($E18<=X$10,IF($F18="",$X$10,$F18)>=X$10),$D18/12*(1+N($G18))^IF(AND(ISNUMBER($H18),X$10>=$H18),1+INT(DATEDIF($H18,X$10,"m")/12),0),0)) -> 5200.8992 | Z18: =SUM(M18:X18) -> 61047.448 | AB18: =IF($D18&$E18="","",IF(AND($D18<>"",NOT(ISNUMBER($D18))),"Salary must be a number",IF(AND($D18<>"",$E18=""),"Start month missing",IF(AND(ISNUMBER($E18),ISNUMBER($F18),$F18<$E18),"End is before Start",IF(AND($D18<>"",NOT(ISNUMBER($H18))),"Increase month missing","")))))
B19: Benjamin Phillips | C19: Field Technician | D19: 53092 | E19: 46266 | F19: 46722 | G19: 0.03 | H19: =$D$8 -> 46661 | I19: =IF(OR($D19="",$E19="",NOT(ISNUMBER($D19))),"",IF(AND($E19<=I$10,IF($F19="",$X$10,$F19)>=I$10),$D19/12*(1+N($G19))^IF(AND(ISNUMBER($H19),I$10>=$H19),1+INT(DATEDIF($H19,I$10,"m")/12),0),0)) -> 4424.3333 | J19: =IF(OR($D19="",$E19="",NOT(ISNUMBER($D19))),"",IF(AND($E19<=J$10,IF($F19="",$X$10,$F19)>=J$10),$D19/12*(1+N($G19))^IF(AND(ISNUMBER($H19),J$10>=$H19),1+INT(DATEDIF($H19,J$10,"m")/12),0),0)) -> 4424.3333 | K19: =IF(OR($D19="",$E19="",NOT(ISNUMBER($D19))),"",IF(AND($E19<=K$10,IF($F19="",$X$10,$F19)>=K$10),$D19/12*(1+N($G19))^IF(AND(ISNUMBER($H19),K$10>=$H19),1+INT(DATEDIF($H19,K$10,"m")/12),0),0)) -> 4424.3333 | L19: =IF(OR($D19="",$E19="",NOT(ISNUMBER($D19))),"",IF(AND($E19<=L$10,IF($F19="",$X$10,$F19)>=L$10),$D19/12*(1+N($G19))^IF(AND(ISNUMBER($H19),L$10>=$H19),1+INT(DATEDIF($H19,L$10,"m")/12),0),0)) -> 4424.3333 | M19: =IF(OR($D19="",$E19="",NOT(ISNUMBER($D19))),"",IF(AND($E19<=M$10,IF($F19="",$X$10,$F19)>=M$10),$D19/12*(1+N($G19))^IF(AND(ISNUMBER($H19),M$10>=$H19),1+INT(DATEDIF($H19,M$10,"m")/12),0),0)) -> 4424.3333 | N19: =IF(OR($D19="",$E19="",NOT(ISNUMBER($D19))),"",IF(AND($E19<=N$10,IF($F19="",$X$10,$F19)>=N$10),$D19/12*(1+N($G19))^IF(AND(ISNUMBER($H19),N$10>=$H19),1+INT(DATEDIF($H19,N$10,"m")/12),0),0)) -> 4424.3333 | O19: =IF(OR($D19="",$E19="",NOT(ISNUMBER($D19))),"",IF(AND($E19<=O$10,IF($F19="",$X$10,$F19)>=O$10),$D19/12*(1+N($G19))^IF(AND(ISNUMBER($H19),O$10>=$H19),1+INT(DATEDIF($H19,O$10,"m")/12),0),0)) -> 4424.3333 | P19: =IF(OR($D19="",$E19="",NOT(ISNUMBER($D19))),"",IF(AND($E19<=P$10,IF($F19="",$X$10,$F19)>=P$10),$D19/12*(1+N($G19))^IF(AND(ISNUMBER($H19),P$10>=$H19),1+INT(DATEDIF($H19,P$10,"m")/12),0),0)) -> 4424.3333 | ... X19: =IF(OR($D19="",$E19="",NOT(ISNUMBER($D19))),"",IF(AND($E19<=X$10,IF($F19="",$X$10,$F19)>=X$10),$D19/12*(1+N($G19))^IF(AND(ISNUMBER($H19),X$10>=$H19),1+INT(DATEDIF($H19,X$10,"m")/12),0),0)) -> 4557.0633 | Z19: =SUM(M19:X19) -> 53490.19 | AB19: =IF($D19&$E19="","",IF(AND($D19<>"",NOT(ISNUMBER($D19))),"Salary must be a number",IF(AND($D19<>"",$E19=""),"Start month missing",IF(AND(ISNUMBER($E19),ISNUMBER($F19),$F19<$E19),"End is before Start",IF(AND($D19<>"",NOT(ISNUMBER($H19))),"Increase month missing","")))))
B20: Brian McSween | C20: Field Technician | D20: 59032 | E20: 46266 | F20: 46722 | G20: 0.03 | H20: =$D$8 -> 46661 | I20: =IF(OR($D20="",$E20="",NOT(ISNUMBER($D20))),"",IF(AND($E20<=I$10,IF($F20="",$X$10,$F20)>=I$10),$D20/12*(1+N($G20))^IF(AND(ISNUMBER($H20),I$10>=$H20),1+INT(DATEDIF($H20,I$10,"m")/12),0),0)) -> 4919.3333 | J20: =IF(OR($D20="",$E20="",NOT(ISNUMBER($D20))),"",IF(AND($E20<=J$10,IF($F20="",$X$10,$F20)>=J$10),$D20/12*(1+N($G20))^IF(AND(ISNUMBER($H20),J$10>=$H20),1+INT(DATEDIF($H20,J$10,"m")/12),0),0)) -> 4919.3333 | K20: =IF(OR($D20="",$E20="",NOT(ISNUMBER($D20))),"",IF(AND($E20<=K$10,IF($F20="",$X$10,$F20)>=K$10),$D20/12*(1+N($G20))^IF(AND(ISNUMBER($H20),K$10>=$H20),1+INT(DATEDIF($H20,K$10,"m")/12),0),0)) -> 4919.3333 | L20: =IF(OR($D20="",$E20="",NOT(ISNUMBER($D20))),"",IF(AND($E20<=L$10,IF($F20="",$X$10,$F20)>=L$10),$D20/12*(1+N($G20))^IF(AND(ISNUMBER($H20),L$10>=$H20),1+INT(DATEDIF($H20,L$10,"m")/12),0),0)) -> 4919.3333 | M20: =IF(OR($D20="",$E20="",NOT(ISNUMBER($D20))),"",IF(AND($E20<=M$10,IF($F20="",$X$10,$F20)>=M$10),$D20/12*(1+N($G20))^IF(AND(ISNUMBER($H20),M$10>=$H20),1+INT(DATEDIF($H20,M$10,"m")/12),0),0)) -> 4919.3333 | N20: =IF(OR($D20="",$E20="",NOT(ISNUMBER($D20))),"",IF(AND($E20<=N$10,IF($F20="",$X$10,$F20)>=N$10),$D20/12*(1+N($G20))^IF(AND(ISNUMBER($H20),N$10>=$H20),1+INT(DATEDIF($H20,N$10,"m")/12),0),0)) -> 4919.3333 | O20: =IF(OR($D20="",$E20="",NOT(ISNUMBER($D20))),"",IF(AND($E20<=O$10,IF($F20="",$X$10,$F20)>=O$10),$D20/12*(1+N($G20))^IF(AND(ISNUMBER($H20),O$10>=$H20),1+INT(DATEDIF($H20,O$10,"m")/12),0),0)) -> 4919.3333 | P20: =IF(OR($D20="",$E20="",NOT(ISNUMBER($D20))),"",IF(AND($E20<=P$10,IF($F20="",$X$10,$F20)>=P$10),$D20/12*(1+N($G20))^IF(AND(ISNUMBER($H20),P$10>=$H20),1+INT(DATEDIF($H20,P$10,"m")/12),0),0)) -> 4919.3333 | ... X20: =IF(OR($D20="",$E20="",NOT(ISNUMBER($D20))),"",IF(AND($E20<=X$10,IF($F20="",$X$10,$F20)>=X$10),$D20/12*(1+N($G20))^IF(AND(ISNUMBER($H20),X$10>=$H20),1+INT(DATEDIF($H20,X$10,"m")/12),0),0)) -> 5066.9133 | Z20: =SUM(M20:X20) -> 59474.74 | AB20: =IF($D20&$E20="","",IF(AND($D20<>"",NOT(ISNUMBER($D20))),"Salary must be a number",IF(AND($D20<>"",$E20=""),"Start month missing",IF(AND(ISNUMBER($E20),ISNUMBER($F20),$F20<$E20),"End is before Start",IF(AND($D20<>"",NOT(ISNUMBER($H20))),"Increase month missing","")))))
B21: Rebecca Tien | C21: Operations Coordinator | D21: 76515 | E21: 46266 | F21: 46722 | G21: 0.03 | H21: =$D$8 -> 46661 | I21: =IF(OR($D21="",$E21="",NOT(ISNUMBER($D21))),"",IF(AND($E21<=I$10,IF($F21="",$X$10,$F21)>=I$10),$D21/12*(1+N($G21))^IF(AND(ISNUMBER($H21),I$10>=$H21),1+INT(DATEDIF($H21,I$10,"m")/12),0),0)) -> 6376.25 | J21: =IF(OR($D21="",$E21="",NOT(ISNUMBER($D21))),"",IF(AND($E21<=J$10,IF($F21="",$X$10,$F21)>=J$10),$D21/12*(1+N($G21))^IF(AND(ISNUMBER($H21),J$10>=$H21),1+INT(DATEDIF($H21,J$10,"m")/12),0),0)) -> 6376.25 | K21: =IF(OR($D21="",$E21="",NOT(ISNUMBER($D21))),"",IF(AND($E21<=K$10,IF($F21="",$X$10,$F21)>=K$10),$D21/12*(1+N($G21))^IF(AND(ISNUMBER($H21),K$10>=$H21),1+INT(DATEDIF($H21,K$10,"m")/12),0),0)) -> 6376.25 | L21: =IF(OR($D21="",$E21="",NOT(ISNUMBER($D21))),"",IF(AND($E21<=L$10,IF($F21="",$X$10,$F21)>=L$10),$D21/12*(1+N($G21))^IF(AND(ISNUMBER($H21),L$10>=$H21),1+INT(DATEDIF($H21,L$10,"m")/12),0),0)) -> 6376.25 | M21: =IF(OR($D21="",$E21="",NOT(ISNUMBER($D21))),"",IF(AND($E21<=M$10,IF($F21="",$X$10,$F21)>=M$10),$D21/12*(1+N($G21))^IF(AND(ISNUMBER($H21),M$10>=$H21),1+INT(DATEDIF($H21,M$10,"m")/12),0),0)) -> 6376.25 | N21: =IF(OR($D21="",$E21="",NOT(ISNUMBER($D21))),"",IF(AND($E21<=N$10,IF($F21="",$X$10,$F21)>=N$10),$D21/12*(1+N($G21))^IF(AND(ISNUMBER($H21),N$10>=$H21),1+INT(DATEDIF($H21,N$10,"m")/12),0),0)) -> 6376.25 | O21: =IF(OR($D21="",$E21="",NOT(ISNUMBER($D21))),"",IF(AND($E21<=O$10,IF($F21="",$X$10,$F21)>=O$10),$D21/12*(1+N($G21))^IF(AND(ISNUMBER($H21),O$10>=$H21),1+INT(DATEDIF($H21,O$10,"m")/12),0),0)) -> 6376.25 | P21: =IF(OR($D21="",$E21="",NOT(ISNUMBER($D21))),"",IF(AND($E21<=P$10,IF($F21="",$X$10,$F21)>=P$10),$D21/12*(1+N($G21))^IF(AND(ISNUMBER($H21),P$10>=$H21),1+INT(DATEDIF($H21,P$10,"m")/12),0),0)) -> 6376.25 | ... X21: =IF(OR($D21="",$E21="",NOT(ISNUMBER($D21))),"",IF(AND($E21<=X$10,IF($F21="",$X$10,$F21)>=X$10),$D21/12*(1+N($G21))^IF(AND(ISNUMBER($H21),X$10>=$H21),1+INT(DATEDIF($H21,X$10,"m")/12),0),0)) -> 6567.5375 | Z21: =SUM(M21:X21) -> 77088.863 | AB21: =IF($D21&$E21="","",IF(AND($D21<>"",NOT(ISNUMBER($D21))),"Salary must be a number",IF(AND($D21<>"",$E21=""),"Start month missing",IF(AND(ISNUMBER($E21),ISNUMBER($F21),$F21<$E21),"End is before Start",IF(AND($D21<>"",NOT(ISNUMBER($H21))),"Increase month missing","")))))
B22: Juan Rodriguez | C22: Field Technician | D22: 64522 | E22: 46266 | F22: 46722 | G22: 0.03 | H22: =$D$8 -> 46661 | I22: =IF(OR($D22="",$E22="",NOT(ISNUMBER($D22))),"",IF(AND($E22<=I$10,IF($F22="",$X$10,$F22)>=I$10),$D22/12*(1+N($G22))^IF(AND(ISNUMBER($H22),I$10>=$H22),1+INT(DATEDIF($H22,I$10,"m")/12),0),0)) -> 5376.8333 | J22: =IF(OR($D22="",$E22="",NOT(ISNUMBER($D22))),"",IF(AND($E22<=J$10,IF($F22="",$X$10,$F22)>=J$10),$D22/12*(1+N($G22))^IF(AND(ISNUMBER($H22),J$10>=$H22),1+INT(DATEDIF($H22,J$10,"m")/12),0),0)) -> 5376.8333 | K22: =IF(OR($D22="",$E22="",NOT(ISNUMBER($D22))),"",IF(AND($E22<=K$10,IF($F22="",$X$10,$F22)>=K$10),$D22/12*(1+N($G22))^IF(AND(ISNUMBER($H22),K$10>=$H22),1+INT(DATEDIF($H22,K$10,"m")/12),0),0)) -> 5376.8333 | L22: =IF(OR($D22="",$E22="",NOT(ISNUMBER($D22))),"",IF(AND($E22<=L$10,IF($F22="",$X$10,$F22)>=L$10),$D22/12*(1+N($G22))^IF(AND(ISNUMBER($H22),L$10>=$H22),1+INT(DATEDIF($H22,L$10,"m")/12),0),0)) -> 5376.8333 | M22: =IF(OR($D22="",$E22="",NOT(ISNUMBER($D22))),"",IF(AND($E22<=M$10,IF($F22="",$X$10,$F22)>=M$10),$D22/12*(1+N($G22))^IF(AND(ISNUMBER($H22),M$10>=$H22),1+INT(DATEDIF($H22,M$10,"m")/12),0),0)) -> 5376.8333 | N22: =IF(OR($D22="",$E22="",NOT(ISNUMBER($D22))),"",IF(AND($E22<=N$10,IF($F22="",$X$10,$F22)>=N$10),$D22/12*(1+N($G22))^IF(AND(ISNUMBER($H22),N$10>=$H22),1+INT(DATEDIF($H22,N$10,"m")/12),0),0)) -> 5376.8333 | O22: =IF(OR($D22="",$E22="",NOT(ISNUMBER($D22))),"",IF(AND($E22<=O$10,IF($F22="",$X$10,$F22)>=O$10),$D22/12*(1+N($G22))^IF(AND(ISNUMBER($H22),O$10>=$H22),1+INT(DATEDIF($H22,O$10,"m")/12),0),0)) -> 5376.8333 | P22: =IF(OR($D22="",$E22="",NOT(ISNUMBER($D22))),"",IF(AND($E22<=P$10,IF($F22="",$X$10,$F22)>=P$10),$D22/12*(1+N($G22))^IF(AND(ISNUMBER($H22),P$10>=$H22),1+INT(DATEDIF($H22,P$10,"m")/12),0),0)) -> 5376.8333 | ... X22: =IF(OR($D22="",$E22="",NOT(ISNUMBER($D22))),"",IF(AND($E22<=X$10,IF($F22="",$X$10,$F22)>=X$10),$D22/12*(1+N($G22))^IF(AND(ISNUMBER($H22),X$10>=$H22),1+INT(DATEDIF($H22,X$10,"m")/12),0),0)) -> 5538.1383 | Z22: =SUM(M22:X22) -> 65005.915 | AB22: =IF($D22&$E22="","",IF(AND($D22<>"",NOT(ISNUMBER($D22))),"Salary must be a number",IF(AND($D22<>"",$E22=""),"Start month missing",IF(AND(ISNUMBER($E22),ISNUMBER($F22),$F22<$E22),"End is before Start",IF(AND($D22<>"",NOT(ISNUMBER($H22))),"Increase month missing","")))))
B23: Shanndon Ferguson | C23: Field Technician | D23: 49920 | E23: 46266 | F23: 46722 | G23: 0.03 | H23: =$D$8 -> 46661 | I23: =IF(OR($D23="",$E23="",NOT(ISNUMBER($D23))),"",IF(AND($E23<=I$10,IF($F23="",$X$10,$F23)>=I$10),$D23/12*(1+N($G23))^IF(AND(ISNUMBER($H23),I$10>=$H23),1+INT(DATEDIF($H23,I$10,"m")/12),0),0)) -> 4160 | J23: =IF(OR($D23="",$E23="",NOT(ISNUMBER($D23))),"",IF(AND($E23<=J$10,IF($F23="",$X$10,$F23)>=J$10),$D23/12*(1+N($G23))^IF(AND(ISNUMBER($H23),J$10>=$H23),1+INT(DATEDIF($H23,J$10,"m")/12),0),0)) -> 4160 | K23: =IF(OR($D23="",$E23="",NOT(ISNUMBER($D23))),"",IF(AND($E23<=K$10,IF($F23="",$X$10,$F23)>=K$10),$D23/12*(1+N($G23))^IF(AND(ISNUMBER($H23),K$10>=$H23),1+INT(DATEDIF($H23,K$10,"m")/12),0),0)) -> 4160 | L23: =IF(OR($D23="",$E23="",NOT(ISNUMBER($D23))),"",IF(AND($E23<=L$10,IF($F23="",$X$10,$F23)>=L$10),$D23/12*(1+N($G23))^IF(AND(ISNUMBER($H23),L$10>=$H23),1+INT(DATEDIF($H23,L$10,"m")/12),0),0)) -> 4160 | M23: =IF(OR($D23="",$E23="",NOT(ISNUMBER($D23))),"",IF(AND($E23<=M$10,IF($F23="",$X$10,$F23)>=M$10),$D23/12*(1+N($G23))^IF(AND(ISNUMBER($H23),M$10>=$H23),1+INT(DATEDIF($H23,M$10,"m")/12),0),0)) -> 4160 | N23: =IF(OR($D23="",$E23="",NOT(ISNUMBER($D23))),"",IF(AND($E23<=N$10,IF($F23="",$X$10,$F23)>=N$10),$D23/12*(1+N($G23))^IF(AND(ISNUMBER($H23),N$10>=$H23),1+INT(DATEDIF($H23,N$10,"m")/12),0),0)) -> 4160 | O23: =IF(OR($D23="",$E23="",NOT(ISNUMBER($D23))),"",IF(AND($E23<=O$10,IF($F23="",$X$10,$F23)>=O$10),$D23/12*(1+N($G23))^IF(AND(ISNUMBER($H23),O$10>=$H23),1+INT(DATEDIF($H23,O$10,"m")/12),0),0)) -> 4160 | P23: =IF(OR($D23="",$E23="",NOT(ISNUMBER($D23))),"",IF(AND($E23<=P$10,IF($F23="",$X$10,$F23)>=P$10),$D23/12*(1+N($G23))^IF(AND(ISNUMBER($H23),P$10>=$H23),1+INT(DATEDIF($H23,P$10,"m")/12),0),0)) -> 4160 | ... X23: =IF(OR($D23="",$E23="",NOT(ISNUMBER($D23))),"",IF(AND($E23<=X$10,IF($F23="",$X$10,$F23)>=X$10),$D23/12*(1+N($G23))^IF(AND(ISNUMBER($H23),X$10>=$H23),1+INT(DATEDIF($H23,X$10,"m")/12),0),0)) -> 4284.8 | Z23: =SUM(M23:X23) -> 50294.4 | AB23: =IF($D23&$E23="","",IF(AND($D23<>"",NOT(ISNUMBER($D23))),"Salary must be a number",IF(AND($D23<>"",$E23=""),"Start month missing",IF(AND(ISNUMBER($E23),ISNUMBER($F23),$F23<$E23),"End is before Start",IF(AND($D23<>"",NOT(ISNUMBER($H23))),"Increase month missing","")))))
B24: Bernadette Sanchez | C24: Field Technician | D24: 70720 | E24: 46266 | F24: 46722 | G24: 0.03 | H24: =$D$8 -> 46661 | I24: =IF(OR($D24="",$E24="",NOT(ISNUMBER($D24))),"",IF(AND($E24<=I$10,IF($F24="",$X$10,$F24)>=I$10),$D24/12*(1+N($G24))^IF(AND(ISNUMBER($H24),I$10>=$H24),1+INT(DATEDIF($H24,I$10,"m")/12),0),0)) -> 5893.3333 | J24: =IF(OR($D24="",$E24="",NOT(ISNUMBER($D24))),"",IF(AND($E24<=J$10,IF($F24="",$X$10,$F24)>=J$10),$D24/12*(1+N($G24))^IF(AND(ISNUMBER($H24),J$10>=$H24),1+INT(DATEDIF($H24,J$10,"m")/12),0),0)) -> 5893.3333 | K24: =IF(OR($D24="",$E24="",NOT(ISNUMBER($D24))),"",IF(AND($E24<=K$10,IF($F24="",$X$10,$F24)>=K$10),$D24/12*(1+N($G24))^IF(AND(ISNUMBER($H24),K$10>=$H24),1+INT(DATEDIF($H24,K$10,"m")/12),0),0)) -> 5893.3333 | L24: =IF(OR($D24="",$E24="",NOT(ISNUMBER($D24))),"",IF(AND($E24<=L$10,IF($F24="",$X$10,$F24)>=L$10),$D24/12*(1+N($G24))^IF(AND(ISNUMBER($H24),L$10>=$H24),1+INT(DATEDIF($H24,L$10,"m")/12),0),0)) -> 5893.3333 | M24: =IF(OR($D24="",$E24="",NOT(ISNUMBER($D24))),"",IF(AND($E24<=M$10,IF($F24="",$X$10,$F24)>=M$10),$D24/12*(1+N($G24))^IF(AND(ISNUMBER($H24),M$10>=$H24),1+INT(DATEDIF($H24,M$10,"m")/12),0),0)) -> 5893.3333 | N24: =IF(OR($D24="",$E24="",NOT(ISNUMBER($D24))),"",IF(AND($E24<=N$10,IF($F24="",$X$10,$F24)>=N$10),$D24/12*(1+N($G24))^IF(AND(ISNUMBER($H24),N$10>=$H24),1+INT(DATEDIF($H24,N$10,"m")/12),0),0)) -> 5893.3333 | O24: =IF(OR($D24="",$E24="",NOT(ISNUMBER($D24))),"",IF(AND($E24<=O$10,IF($F24="",$X$10,$F24)>=O$10),$D24/12*(1+N($G24))^IF(AND(ISNUMBER($H24),O$10>=$H24),1+INT(DATEDIF($H24,O$10,"m")/12),0),0)) -> 5893.3333 | P24: =IF(OR($D24="",$E24="",NOT(ISNUMBER($D24))),"",IF(AND($E24<=P$10,IF($F24="",$X$10,$F24)>=P$10),$D24/12*(1+N($G24))^IF(AND(ISNUMBER($H24),P$10>=$H24),1+INT(DATEDIF($H24,P$10,"m")/12),0),0)) -> 5893.3333 | ... X24: =IF(OR($D24="",$E24="",NOT(ISNUMBER($D24))),"",IF(AND($E24<=X$10,IF($F24="",$X$10,$F24)>=X$10),$D24/12*(1+N($G24))^IF(AND(ISNUMBER($H24),X$10>=$H24),1+INT(DATEDIF($H24,X$10,"m")/12),0),0)) -> 6070.1333 | Z24: =SUM(M24:X24) -> 71250.4 | AB24: =IF($D24&$E24="","",IF(AND($D24<>"",NOT(ISNUMBER($D24))),"Salary must be a number",IF(AND($D24<>"",$E24=""),"Start month missing",IF(AND(ISNUMBER($E24),ISNUMBER($F24),$F24<$E24),"End is before Start",IF(AND($D24<>"",NOT(ISNUMBER($H24))),"Increase month missing","")))))
B25: Isaiah Swallow | C25: Field Maintenance Manager | D25: 120000 | E25: 46266 | F25: 46722 | G25: 0.03 | H25: =$D$8 -> 46661 | I25: =IF(OR($D25="",$E25="",NOT(ISNUMBER($D25))),"",IF(AND($E25<=I$10,IF($F25="",$X$10,$F25)>=I$10),$D25/12*(1+N($G25))^IF(AND(ISNUMBER($H25),I$10>=$H25),1+INT(DATEDIF($H25,I$10,"m")/12),0),0)) -> 10000 | J25: =IF(OR($D25="",$E25="",NOT(ISNUMBER($D25))),"",IF(AND($E25<=J$10,IF($F25="",$X$10,$F25)>=J$10),$D25/12*(1+N($G25))^IF(AND(ISNUMBER($H25),J$10>=$H25),1+INT(DATEDIF($H25,J$10,"m")/12),0),0)) -> 10000 | K25: =IF(OR($D25="",$E25="",NOT(ISNUMBER($D25))),"",IF(AND($E25<=K$10,IF($F25="",$X$10,$F25)>=K$10),$D25/12*(1+N($G25))^IF(AND(ISNUMBER($H25),K$10>=$H25),1+INT(DATEDIF($H25,K$10,"m")/12),0),0)) -> 10000 | L25: =IF(OR($D25="",$E25="",NOT(ISNUMBER($D25))),"",IF(AND($E25<=L$10,IF($F25="",$X$10,$F25)>=L$10),$D25/12*(1+N($G25))^IF(AND(ISNUMBER($H25),L$10>=$H25),1+INT(DATEDIF($H25,L$10,"m")/12),0),0)) -> 10000 | M25: =IF(OR($D25="",$E25="",NOT(ISNUMBER($D25))),"",IF(AND($E25<=M$10,IF($F25="",$X$10,$F25)>=M$10),$D25/12*(1+N($G25))^IF(AND(ISNUMBER($H25),M$10>=$H25),1+INT(DATEDIF($H25,M$10,"m")/12),0),0)) -> 10000 | N25: =IF(OR($D25="",$E25="",NOT(ISNUMBER($D25))),"",IF(AND($E25<=N$10,IF($F25="",$X$10,$F25)>=N$10),$D25/12*(1+N($G25))^IF(AND(ISNUMBER($H25),N$10>=$H25),1+INT(DATEDIF($H25,N$10,"m")/12),0),0)) -> 10000 | O25: =IF(OR($D25="",$E25="",NOT(ISNUMBER($D25))),"",IF(AND($E25<=O$10,IF($F25="",$X$10,$F25)>=O$10),$D25/12*(1+N($G25))^IF(AND(ISNUMBER($H25),O$10>=$H25),1+INT(DATEDIF($H25,O$10,"m")/12),0),0)) -> 10000 | P25: =IF(OR($D25="",$E25="",NOT(ISNUMBER($D25))),"",IF(AND($E25<=P$10,IF($F25="",$X$10,$F25)>=P$10),$D25/12*(1+N($G25))^IF(AND(ISNUMBER($H25),P$10>=$H25),1+INT(DATEDIF($H25,P$10,"m")/12),0),0)) -> 10000 | ... X25: =IF(OR($D25="",$E25="",NOT(ISNUMBER($D25))),"",IF(AND($E25<=X$10,IF($F25="",$X$10,$F25)>=X$10),$D25/12*(1+N($G25))^IF(AND(ISNUMBER($H25),X$10>=$H25),1+INT(DATEDIF($H25,X$10,"m")/12),0),0)) -> 10300 | Z25: =SUM(M25:X25) -> 120900 | AB25: =IF($D25&$E25="","",IF(AND($D25<>"",NOT(ISNUMBER($D25))),"Salary must be a number",IF(AND($D25<>"",$E25=""),"Start month missing",IF(AND(ISNUMBER($E25),ISNUMBER($F25),$F25<$E25),"End is before Start",IF(AND($D25<>"",NOT(ISNUMBER($H25))),"Increase month missing","")))))
... B29: Michael Yunker | C29: Field Technician | D29: 66560 | E29: 46266 | F29: 46722 | G29: 0.03 | H29: =$D$8 -> 46661 | I29: =IF(OR($D29="",$E29="",NOT(ISNUMBER($D29))),"",IF(AND($E29<=I$10,IF($F29="",$X$10,$F29)>=I$10),$D29/12*(1+N($G29))^IF(AND(ISNUMBER($H29),I$10>=$H29),1+INT(DATEDIF($H29,I$10,"m")/12),0),0)) -> 5546.6667 | J29: =IF(OR($D29="",$E29="",NOT(ISNUMBER($D29))),"",IF(AND($E29<=J$10,IF($F29="",$X$10,$F29)>=J$10),$D29/12*(1+N($G29))^IF(AND(ISNUMBER($H29),J$10>=$H29),1+INT(DATEDIF($H29,J$10,"m")/12),0),0)) -> 5546.6667 | K29: =IF(OR($D29="",$E29="",NOT(ISNUMBER($D29))),"",IF(AND($E29<=K$10,IF($F29="",$X$10,$F29)>=K$10),$D29/12*(1+N($G29))^IF(AND(ISNUMBER($H29),K$10>=$H29),1+INT(DATEDIF($H29,K$10,"m")/12),0),0)) -> 5546.6667 | L29: =IF(OR($D29="",$E29="",NOT(ISNUMBER($D29))),"",IF(AND($E29<=L$10,IF($F29="",$X$10,$F29)>=L$10),$D29/12*(1+N($G29))^IF(AND(ISNUMBER($H29),L$10>=$H29),1+INT(DATEDIF($H29,L$10,"m")/12),0),0)) -> 5546.6667 | M29: =IF(OR($D29="",$E29="",NOT(ISNUMBER($D29))),"",IF(AND($E29<=M$10,IF($F29="",$X$10,$F29)>=M$10),$D29/12*(1+N($G29))^IF(AND(ISNUMBER($H29),M$10>=$H29),1+INT(DATEDIF($H29,M$10,"m")/12),0),0)) -> 5546.6667 | N29: =IF(OR($D29="",$E29="",NOT(ISNUMBER($D29))),"",IF(AND($E29<=N$10,IF($F29="",$X$10,$F29)>=N$10),$D29/12*(1+N($G29))^IF(AND(ISNUMBER($H29),N$10>=$H29),1+INT(DATEDIF($H29,N$10,"m")/12),0),0)) -> 5546.6667 | O29: =IF(OR($D29="",$E29="",NOT(ISNUMBER($D29))),"",IF(AND($E29<=O$10,IF($F29="",$X$10,$F29)>=O$10),$D29/12*(1+N($G29))^IF(AND(ISNUMBER($H29),O$10>=$H29),1+INT(DATEDIF($H29,O$10,"m")/12),0),0)) -> 5546.6667 | P29: =IF(OR($D29="",$E29="",NOT(ISNUMBER($D29))),"",IF(AND($E29<=P$10,IF($F29="",$X$10,$F29)>=P$10),$D29/12*(1+N($G29))^IF(AND(ISNUMBER($H29),P$10>=$H29),1+INT(DATEDIF($H29,P$10,"m")/12),0),0)) -> 5546.6667 | ... X29: =IF(OR($D29="",$E29="",NOT(ISNUMBER($D29))),"",IF(AND($E29<=X$10,IF($F29="",$X$10,$F29)>=X$10),$D29/12*(1+N($G29))^IF(AND(ISNUMBER($H29),X$10>=$H29),1+INT(DATEDIF($H29,X$10,"m")/12),0),0)) -> 5713.0667 | Z29: =SUM(M29:X29) -> 67059.2 | AB29: =IF($D29&$E29="","",IF(AND($D29<>"",NOT(ISNUMBER($D29))),"Salary must be a number",IF(AND($D29<>"",$E29=""),"Start month missing",IF(AND(ISNUMBER($E29),ISNUMBER($F29),$F29<$E29),"End is before Start",IF(AND($D29<>"",NOT(ISNUMBER($H29))),"Increase month missing","")))))
E30: 46266 | F30: 46722 | G30: 0.03 | H30: =$D$8 -> 46661 | I30: =IF(OR($D30="",$E30="",NOT(ISNUMBER($D30))),"",IF(AND($E30<=I$10,IF($F30="",$X$10,$F30)>=I$10),$D30/12*(1+N($G30))^IF(AND(ISNUMBER($H30),I$10>=$H30),1+INT(DATEDIF($H30,I$10,"m")/12),0),0)) | J30: =IF(OR($D30="",$E30="",NOT(ISNUMBER($D30))),"",IF(AND($E30<=J$10,IF($F30="",$X$10,$F30)>=J$10),$D30/12*(1+N($G30))^IF(AND(ISNUMBER($H30),J$10>=$H30),1+INT(DATEDIF($H30,J$10,"m")/12),0),0)) | K30: =IF(OR($D30="",$E30="",NOT(ISNUMBER($D30))),"",IF(AND($E30<=K$10,IF($F30="",$X$10,$F30)>=K$10),$D30/12*(1+N($G30))^IF(AND(ISNUMBER($H30),K$10>=$H30),1+INT(DATEDIF($H30,K$10,"m")/12),0),0)) | L30: =IF(OR($D30="",$E30="",NOT(ISNUMBER($D30))),"",IF(AND($E30<=L$10,IF($F30="",$X$10,$F30)>=L$10),$D30/12*(1+N($G30))^IF(AND(ISNUMBER($H30),L$10>=$H30),1+INT(DATEDIF($H30,L$10,"m")/12),0),0)) | M30: =IF(OR($D30="",$E30="",NOT(ISNUMBER($D30))),"",IF(AND($E30<=M$10,IF($F30="",$X$10,$F30)>=M$10),$D30/12*(1+N($G30))^IF(AND(ISNUMBER($H30),M$10>=$H30),1+INT(DATEDIF($H30,M$10,"m")/12),0),0)) | N30: =IF(OR($D30="",$E30="",NOT(ISNUMBER($D30))),"",IF(AND($E30<=N$10,IF($F30="",$X$10,$F30)>=N$10),$D30/12*(1+N($G30))^IF(AND(ISNUMBER($H30),N$10>=$H30),1+INT(DATEDIF($H30,N$10,"m")/12),0),0)) | O30: =IF(OR($D30="",$E30="",NOT(ISNUMBER($D30))),"",IF(AND($E30<=O$10,IF($F30="",$X$10,$F30)>=O$10),$D30/12*(1+N($G30))^IF(AND(ISNUMBER($H30),O$10>=$H30),1+INT(DATEDIF($H30,O$10,"m")/12),0),0)) | P30: =IF(OR($D30="",$E30="",NOT(ISNUMBER($D30))),"",IF(AND($E30<=P$10,IF($F30="",$X$10,$F30)>=P$10),$D30/12*(1+N($G30))^IF(AND(ISNUMBER($H30),P$10>=$H30),1+INT(DATEDIF($H30,P$10,"m")/12),0),0)) | ... X30: =IF(OR($D30="",$E30="",NOT(ISNUMBER($D30))),"",IF(AND($E30<=X$10,IF($F30="",$X$10,$F30)>=X$10),$D30/12*(1+N($G30))^IF(AND(ISNUMBER($H30),X$10>=$H30),1+INT(DATEDIF($H30,X$10,"m")/12),0),0)) | Z30: =SUM(M30:X30) -> 0 | AB30: =IF($D30&$E30="","",IF(AND($D30<>"",NOT(ISNUMBER($D30))),"Salary must be a number",IF(AND($D30<>"",$E30=""),"Start month missing",IF(AND(ISNUMBER($E30),ISNUMBER($F30),$F30<$E30),"End is before Start",IF(AND($D30<>"",NOT(ISNUMBER($H30))),"Increase month missing","")))))
E31: 46266 | F31: 46722 | G31: 0.03 | H31: =$D$8 -> 46661 | I31: =IF(OR($D31="",$E31="",NOT(ISNUMBER($D31))),"",IF(AND($E31<=I$10,IF($F31="",$X$10,$F31)>=I$10),$D31/12*(1+N($G31))^IF(AND(ISNUMBER($H31),I$10>=$H31),1+INT(DATEDIF($H31,I$10,"m")/12),0),0)) | J31: =IF(OR($D31="",$E31="",NOT(ISNUMBER($D31))),"",IF(AND($E31<=J$10,IF($F31="",$X$10,$F31)>=J$10),$D31/12*(1+N($G31))^IF(AND(ISNUMBER($H31),J$10>=$H31),1+INT(DATEDIF($H31,J$10,"m")/12),0),0)) | K31: =IF(OR($D31="",$E31="",NOT(ISNUMBER($D31))),"",IF(AND($E31<=K$10,IF($F31="",$X$10,$F31)>=K$10),$D31/12*(1+N($G31))^IF(AND(ISNUMBER($H31),K$10>=$H31),1+INT(DATEDIF($H31,K$10,"m")/12),0),0)) | L31: =IF(OR($D31="",$E31="",NOT(ISNUMBER($D31))),"",IF(AND($E31<=L$10,IF($F31="",$X$10,$F31)>=L$10),$D31/12*(1+N($G31))^IF(AND(ISNUMBER($H31),L$10>=$H31),1+INT(DATEDIF($H31,L$10,"m")/12),0),0)) | M31: =IF(OR($D31="",$E31="",NOT(ISNUMBER($D31))),"",IF(AND($E31<=M$10,IF($F31="",$X$10,$F31)>=M$10),$D31/12*(1+N($G31))^IF(AND(ISNUMBER($H31),M$10>=$H31),1+INT(DATEDIF($H31,M$10,"m")/12),0),0)) | N31: =IF(OR($D31="",$E31="",NOT(ISNUMBER($D31))),"",IF(AND($E31<=N$10,IF($F31="",$X$10,$F31)>=N$10),$D31/12*(1+N($G31))^IF(AND(ISNUMBER($H31),N$10>=$H31),1+INT(DATEDIF($H31,N$10,"m")/12),0),0)) | O31: =IF(OR($D31="",$E31="",NOT(ISNUMBER($D31))),"",IF(AND($E31<=O$10,IF($F31="",$X$10,$F31)>=O$10),$D31/12*(1+N($G31))^IF(AND(ISNUMBER($H31),O$10>=$H31),1+INT(DATEDIF($H31,O$10,"m")/12),0),0)) | P31: =IF(OR($D31="",$E31="",NOT(ISNUMBER($D31))),"",IF(AND($E31<=P$10,IF($F31="",$X$10,$F31)>=P$10),$D31/12*(1+N($G31))^IF(AND(ISNUMBER($H31),P$10>=$H31),1+INT(DATEDIF($H31,P$10,"m")/12),0),0)) | ... X31: =IF(OR($D31="",$E31="",NOT(ISNUMBER($D31))),"",IF(AND($E31<=X$10,IF($F31="",$X$10,$F31)>=X$10),$D31/12*(1+N($G31))^IF(AND(ISNUMBER($H31),X$10>=$H31),1+INT(DATEDIF($H31,X$10,"m")/12),0),0)) | Z31: =SUM(M31:X31) -> 0 | AB31: =IF($D31&$E31="","",IF(AND($D31<>"",NOT(ISNUMBER($D31))),"Salary must be a number",IF(AND($D31<>"",$E31=""),"Start month missing",IF(AND(ISNUMBER($E31),ISNUMBER($F31),$F31<$E31),"End is before Start",IF(AND($D31<>"",NOT(ISNUMBER($H31))),"Increase month missing","")))))
E32: 46266 | F32: 46722 | G32: 0.03 | H32: =$D$8 -> 46661 | I32: =IF(OR($D32="",$E32="",NOT(ISNUMBER($D32))),"",IF(AND($E32<=I$10,IF($F32="",$X$10,$F32)>=I$10),$D32/12*(1+N($G32))^IF(AND(ISNUMBER($H32),I$10>=$H32),1+INT(DATEDIF($H32,I$10,"m")/12),0),0)) | J32: =IF(OR($D32="",$E32="",NOT(ISNUMBER($D32))),"",IF(AND($E32<=J$10,IF($F32="",$X$10,$F32)>=J$10),$D32/12*(1+N($G32))^IF(AND(ISNUMBER($H32),J$10>=$H32),1+INT(DATEDIF($H32,J$10,"m")/12),0),0)) | K32: =IF(OR($D32="",$E32="",NOT(ISNUMBER($D32))),"",IF(AND($E32<=K$10,IF($F32="",$X$10,$F32)>=K$10),$D32/12*(1+N($G32))^IF(AND(ISNUMBER($H32),K$10>=$H32),1+INT(DATEDIF($H32,K$10,"m")/12),0),0)) | L32: =IF(OR($D32="",$E32="",NOT(ISNUMBER($D32))),"",IF(AND($E32<=L$10,IF($F32="",$X$10,$F32)>=L$10),$D32/12*(1+N($G32))^IF(AND(ISNUMBER($H32),L$10>=$H32),1+INT(DATEDIF($H32,L$10,"m")/12),0),0)) | M32: =IF(OR($D32="",$E32="",NOT(ISNUMBER($D32))),"",IF(AND($E32<=M$10,IF($F32="",$X$10,$F32)>=M$10),$D32/12*(1+N($G32))^IF(AND(ISNUMBER($H32),M$10>=$H32),1+INT(DATEDIF($H32,M$10,"m")/12),0),0)) | N32: =IF(OR($D32="",$E32="",NOT(ISNUMBER($D32))),"",IF(AND($E32<=N$10,IF($F32="",$X$10,$F32)>=N$10),$D32/12*(1+N($G32))^IF(AND(ISNUMBER($H32),N$10>=$H32),1+INT(DATEDIF($H32,N$10,"m")/12),0),0)) | O32: =IF(OR($D32="",$E32="",NOT(ISNUMBER($D32))),"",IF(AND($E32<=O$10,IF($F32="",$X$10,$F32)>=O$10),$D32/12*(1+N($G32))^IF(AND(ISNUMBER($H32),O$10>=$H32),1+INT(DATEDIF($H32,O$10,"m")/12),0),0)) | P32: =IF(OR($D32="",$E32="",NOT(ISNUMBER($D32))),"",IF(AND($E32<=P$10,IF($F32="",$X$10,$F32)>=P$10),$D32/12*(1+N($G32))^IF(AND(ISNUMBER($H32),P$10>=$H32),1+INT(DATEDIF($H32,P$10,"m")/12),0),0)) | ... X32: =IF(OR($D32="",$E32="",NOT(ISNUMBER($D32))),"",IF(AND($E32<=X$10,IF($F32="",$X$10,$F32)>=X$10),$D32/12*(1+N($G32))^IF(AND(ISNUMBER($H32),X$10>=$H32),1+INT(DATEDIF($H32,X$10,"m")/12),0),0)) | Z32: =SUM(M32:X32) -> 0 | AB32: =IF($D32&$E32="","",IF(AND($D32<>"",NOT(ISNUMBER($D32))),"Salary must be a number",IF(AND($D32<>"",$E32=""),"Start month missing",IF(AND(ISNUMBER($E32),ISNUMBER($F32),$F32<$E32),"End is before Start",IF(AND($D32<>"",NOT(ISNUMBER($H32))),"Increase month missing","")))))
E33: 46266 | F33: 46722 | G33: 0.03 | H33: =$D$8 -> 46661 | I33: =IF(OR($D33="",$E33="",NOT(ISNUMBER($D33))),"",IF(AND($E33<=I$10,IF($F33="",$X$10,$F33)>=I$10),$D33/12*(1+N($G33))^IF(AND(ISNUMBER($H33),I$10>=$H33),1+INT(DATEDIF($H33,I$10,"m")/12),0),0)) | J33: =IF(OR($D33="",$E33="",NOT(ISNUMBER($D33))),"",IF(AND($E33<=J$10,IF($F33="",$X$10,$F33)>=J$10),$D33/12*(1+N($G33))^IF(AND(ISNUMBER($H33),J$10>=$H33),1+INT(DATEDIF($H33,J$10,"m")/12),0),0)) | K33: =IF(OR($D33="",$E33="",NOT(ISNUMBER($D33))),"",IF(AND($E33<=K$10,IF($F33="",$X$10,$F33)>=K$10),$D33/12*(1+N($G33))^IF(AND(ISNUMBER($H33),K$10>=$H33),1+INT(DATEDIF($H33,K$10,"m")/12),0),0)) | L33: =IF(OR($D33="",$E33="",NOT(ISNUMBER($D33))),"",IF(AND($E33<=L$10,IF($F33="",$X$10,$F33)>=L$10),$D33/12*(1+N($G33))^IF(AND(ISNUMBER($H33),L$10>=$H33),1+INT(DATEDIF($H33,L$10,"m")/12),0),0)) | M33: =IF(OR($D33="",$E33="",NOT(ISNUMBER($D33))),"",IF(AND($E33<=M$10,IF($F33="",$X$10,$F33)>=M$10),$D33/12*(1+N($G33))^IF(AND(ISNUMBER($H33),M$10>=$H33),1+INT(DATEDIF($H33,M$10,"m")/12),0),0)) | N33: =IF(OR($D33="",$E33="",NOT(ISNUMBER($D33))),"",IF(AND($E33<=N$10,IF($F33="",$X$10,$F33)>=N$10),$D33/12*(1+N($G33))^IF(AND(ISNUMBER($H33),N$10>=$H33),1+INT(DATEDIF($H33,N$10,"m")/12),0),0)) | O33: =IF(OR($D33="",$E33="",NOT(ISNUMBER($D33))),"",IF(AND($E33<=O$10,IF($F33="",$X$10,$F33)>=O$10),$D33/12*(1+N($G33))^IF(AND(ISNUMBER($H33),O$10>=$H33),1+INT(DATEDIF($H33,O$10,"m")/12),0),0)) | P33: =IF(OR($D33="",$E33="",NOT(ISNUMBER($D33))),"",IF(AND($E33<=P$10,IF($F33="",$X$10,$F33)>=P$10),$D33/12*(1+N($G33))^IF(AND(ISNUMBER($H33),P$10>=$H33),1+INT(DATEDIF($H33,P$10,"m")/12),0),0)) | ... X33: =IF(OR($D33="",$E33="",NOT(ISNUMBER($D33))),"",IF(AND($E33<=X$10,IF($F33="",$X$10,$F33)>=X$10),$D33/12*(1+N($G33))^IF(AND(ISNUMBER($H33),X$10>=$H33),1+INT(DATEDIF($H33,X$10,"m")/12),0),0)) | Z33: =SUM(M33:X33) -> 0 | AB33: =IF($D33&$E33="","",IF(AND($D33<>"",NOT(ISNUMBER($D33))),"Salary must be a number",IF(AND($D33<>"",$E33=""),"Start month missing",IF(AND(ISNUMBER($E33),ISNUMBER($F33),$F33<$E33),"End is before Start",IF(AND($D33<>"",NOT(ISNUMBER($H33))),"Increase month missing","")))))
B34: Open Positions
F35: 46722 | G35: 0.03 | H35: =$D$8 -> 46661 | I35: =IF(OR($D35="",$E35="",NOT(ISNUMBER($D35))),"",IF(AND($E35<=I$10,IF($F35="",$X$10,$F35)>=I$10),$D35/12*(1+N($G35))^IF(AND(ISNUMBER($H35),I$10>=$H35),1+INT(DATEDIF($H35,I$10,"m")/12),0),0)) | J35: =IF(OR($D35="",$E35="",NOT(ISNUMBER($D35))),"",IF(AND($E35<=J$10,IF($F35="",$X$10,$F35)>=J$10),$D35/12*(1+N($G35))^IF(AND(ISNUMBER($H35),J$10>=$H35),1+INT(DATEDIF($H35,J$10,"m")/12),0),0)) | K35: =IF(OR($D35="",$E35="",NOT(ISNUMBER($D35))),"",IF(AND($E35<=K$10,IF($F35="",$X$10,$F35)>=K$10),$D35/12*(1+N($G35))^IF(AND(ISNUMBER($H35),K$10>=$H35),1+INT(DATEDIF($H35,K$10,"m")/12),0),0)) | L35: =IF(OR($D35="",$E35="",NOT(ISNUMBER($D35))),"",IF(AND($E35<=L$10,IF($F35="",$X$10,$F35)>=L$10),$D35/12*(1+N($G35))^IF(AND(ISNUMBER($H35),L$10>=$H35),1+INT(DATEDIF($H35,L$10,"m")/12),0),0)) | M35: =IF(OR($D35="",$E35="",NOT(ISNUMBER($D35))),"",IF(AND($E35<=M$10,IF($F35="",$X$10,$F35)>=M$10),$D35/12*(1+N($G35))^IF(AND(ISNUMBER($H35),M$10>=$H35),1+INT(DATEDIF($H35,M$10,"m")/12),0),0)) | N35: =IF(OR($D35="",$E35="",NOT(ISNUMBER($D35))),"",IF(AND($E35<=N$10,IF($F35="",$X$10,$F35)>=N$10),$D35/12*(1+N($G35))^IF(AND(ISNUMBER($H35),N$10>=$H35),1+INT(DATEDIF($H35,N$10,"m")/12),0),0)) | O35: =IF(OR($D35="",$E35="",NOT(ISNUMBER($D35))),"",IF(AND($E35<=O$10,IF($F35="",$X$10,$F35)>=O$10),$D35/12*(1+N($G35))^IF(AND(ISNUMBER($H35),O$10>=$H35),1+INT(DATEDIF($H35,O$10,"m")/12),0),0)) | P35: =IF(OR($D35="",$E35="",NOT(ISNUMBER($D35))),"",IF(AND($E35<=P$10,IF($F35="",$X$10,$F35)>=P$10),$D35/12*(1+N($G35))^IF(AND(ISNUMBER($H35),P$10>=$H35),1+INT(DATEDIF($H35,P$10,"m")/12),0),0)) | ... X35: =IF(OR($D35="",$E35="",NOT(ISNUMBER($D35))),"",IF(AND($E35<=X$10,IF($F35="",$X$10,$F35)>=X$10),$D35/12*(1+N($G35))^IF(AND(ISNUMBER($H35),X$10>=$H35),1+INT(DATEDIF($H35,X$10,"m")/12),0),0)) | Z35: =SUM(M35:X35) -> 0 | AB35: =IF($D35&$E35="","",IF(AND($D35<>"",NOT(ISNUMBER($D35))),"Salary must be a number",IF(AND($D35<>"",$E35=""),"Start month missing",IF(AND(ISNUMBER($E35),ISNUMBER($F35),$F35<$E35),"End is before Start",IF(AND($D35<>"",NOT(ISNUMBER($H35))),"Increase month missing","")))))
F36: 46722 | G36: 0.03 | H36: =$D$8 -> 46661 | I36: =IF(OR($D36="",$E36="",NOT(ISNUMBER($D36))),"",IF(AND($E36<=I$10,IF($F36="",$X$10,$F36)>=I$10),$D36/12*(1+N($G36))^IF(AND(ISNUMBER($H36),I$10>=$H36),1+INT(DATEDIF($H36,I$10,"m")/12),0),0)) | J36: =IF(OR($D36="",$E36="",NOT(ISNUMBER($D36))),"",IF(AND($E36<=J$10,IF($F36="",$X$10,$F36)>=J$10),$D36/12*(1+N($G36))^IF(AND(ISNUMBER($H36),J$10>=$H36),1+INT(DATEDIF($H36,J$10,"m")/12),0),0)) | K36: =IF(OR($D36="",$E36="",NOT(ISNUMBER($D36))),"",IF(AND($E36<=K$10,IF($F36="",$X$10,$F36)>=K$10),$D36/12*(1+N($G36))^IF(AND(ISNUMBER($H36),K$10>=$H36),1+INT(DATEDIF($H36,K$10,"m")/12),0),0)) | L36: =IF(OR($D36="",$E36="",NOT(ISNUMBER($D36))),"",IF(AND($E36<=L$10,IF($F36="",$X$10,$F36)>=L$10),$D36/12*(1+N($G36))^IF(AND(ISNUMBER($H36),L$10>=$H36),1+INT(DATEDIF($H36,L$10,"m")/12),0),0)) | M36: =IF(OR($D36="",$E36="",NOT(ISNUMBER($D36))),"",IF(AND($E36<=M$10,IF($F36="",$X$10,$F36)>=M$10),$D36/12*(1+N($G36))^IF(AND(ISNUMBER($H36),M$10>=$H36),1+INT(DATEDIF($H36,M$10,"m")/12),0),0)) | N36: =IF(OR($D36="",$E36="",NOT(ISNUMBER($D36))),"",IF(AND($E36<=N$10,IF($F36="",$X$10,$F36)>=N$10),$D36/12*(1+N($G36))^IF(AND(ISNUMBER($H36),N$10>=$H36),1+INT(DATEDIF($H36,N$10,"m")/12),0),0)) | O36: =IF(OR($D36="",$E36="",NOT(ISNUMBER($D36))),"",IF(AND($E36<=O$10,IF($F36="",$X$10,$F36)>=O$10),$D36/12*(1+N($G36))^IF(AND(ISNUMBER($H36),O$10>=$H36),1+INT(DATEDIF($H36,O$10,"m")/12),0),0)) | P36: =IF(OR($D36="",$E36="",NOT(ISNUMBER($D36))),"",IF(AND($E36<=P$10,IF($F36="",$X$10,$F36)>=P$10),$D36/12*(1+N($G36))^IF(AND(ISNUMBER($H36),P$10>=$H36),1+INT(DATEDIF($H36,P$10,"m")/12),0),0)) | ... X36: =IF(OR($D36="",$E36="",NOT(ISNUMBER($D36))),"",IF(AND($E36<=X$10,IF($F36="",$X$10,$F36)>=X$10),$D36/12*(1+N($G36))^IF(AND(ISNUMBER($H36),X$10>=$H36),1+INT(DATEDIF($H36,X$10,"m")/12),0),0)) | Z36: =SUM(M36:X36) -> 0 | AB36: =IF($D36&$E36="","",IF(AND($D36<>"",NOT(ISNUMBER($D36))),"Salary must be a number",IF(AND($D36<>"",$E36=""),"Start month missing",IF(AND(ISNUMBER($E36),ISNUMBER($F36),$F36<$E36),"End is before Start",IF(AND($D36<>"",NOT(ISNUMBER($H36))),"Increase month missing","")))))
F37: 46722 | G37: 0.03 | H37: =$D$8 -> 46661 | I37: =IF(OR($D37="",$E37="",NOT(ISNUMBER($D37))),"",IF(AND($E37<=I$10,IF($F37="",$X$10,$F37)>=I$10),$D37/12*(1+N($G37))^IF(AND(ISNUMBER($H37),I$10>=$H37),1+INT(DATEDIF($H37,I$10,"m")/12),0),0)) | J37: =IF(OR($D37="",$E37="",NOT(ISNUMBER($D37))),"",IF(AND($E37<=J$10,IF($F37="",$X$10,$F37)>=J$10),$D37/12*(1+N($G37))^IF(AND(ISNUMBER($H37),J$10>=$H37),1+INT(DATEDIF($H37,J$10,"m")/12),0),0)) | K37: =IF(OR($D37="",$E37="",NOT(ISNUMBER($D37))),"",IF(AND($E37<=K$10,IF($F37="",$X$10,$F37)>=K$10),$D37/12*(1+N($G37))^IF(AND(ISNUMBER($H37),K$10>=$H37),1+INT(DATEDIF($H37,K$10,"m")/12),0),0)) | L37: =IF(OR($D37="",$E37="",NOT(ISNUMBER($D37))),"",IF(AND($E37<=L$10,IF($F37="",$X$10,$F37)>=L$10),$D37/12*(1+N($G37))^IF(AND(ISNUMBER($H37),L$10>=$H37),1+INT(DATEDIF($H37,L$10,"m")/12),0),0)) | M37: =IF(OR($D37="",$E37="",NOT(ISNUMBER($D37))),"",IF(AND($E37<=M$10,IF($F37="",$X$10,$F37)>=M$10),$D37/12*(1+N($G37))^IF(AND(ISNUMBER($H37),M$10>=$H37),1+INT(DATEDIF($H37,M$10,"m")/12),0),0)) | N37: =IF(OR($D37="",$E37="",NOT(ISNUMBER($D37))),"",IF(AND($E37<=N$10,IF($F37="",$X$10,$F37)>=N$10),$D37/12*(1+N($G37))^IF(AND(ISNUMBER($H37),N$10>=$H37),1+INT(DATEDIF($H37,N$10,"m")/12),0),0)) | O37: =IF(OR($D37="",$E37="",NOT(ISNUMBER($D37))),"",IF(AND($E37<=O$10,IF($F37="",$X$10,$F37)>=O$10),$D37/12*(1+N($G37))^IF(AND(ISNUMBER($H37),O$10>=$H37),1+INT(DATEDIF($H37,O$10,"m")/12),0),0)) | P37: =IF(OR($D37="",$E37="",NOT(ISNUMBER($D37))),"",IF(AND($E37<=P$10,IF($F37="",$X$10,$F37)>=P$10),$D37/12*(1+N($G37))^IF(AND(ISNUMBER($H37),P$10>=$H37),1+INT(DATEDIF($H37,P$10,"m")/12),0),0)) | ... X37: =IF(OR($D37="",$E37="",NOT(ISNUMBER($D37))),"",IF(AND($E37<=X$10,IF($F37="",$X$10,$F37)>=X$10),$D37/12*(1+N($G37))^IF(AND(ISNUMBER($H37),X$10>=$H37),1+INT(DATEDIF($H37,X$10,"m")/12),0),0)) | Z37: =SUM(M37:X37) -> 0 | AB37: =IF($D37&$E37="","",IF(AND($D37<>"",NOT(ISNUMBER($D37))),"Salary must be a number",IF(AND($D37<>"",$E37=""),"Start month missing",IF(AND(ISNUMBER($E37),ISNUMBER($F37),$F37<$E37),"End is before Start",IF(AND($D37<>"",NOT(ISNUMBER($H37))),"Increase month missing","")))))
F38: 46722 | G38: 0.03 | H38: =$D$8 -> 46661 | I38: =IF(OR($D38="",$E38="",NOT(ISNUMBER($D38))),"",IF(AND($E38<=I$10,IF($F38="",$X$10,$F38)>=I$10),$D38/12*(1+N($G38))^IF(AND(ISNUMBER($H38),I$10>=$H38),1+INT(DATEDIF($H38,I$10,"m")/12),0),0)) | J38: =IF(OR($D38="",$E38="",NOT(ISNUMBER($D38))),"",IF(AND($E38<=J$10,IF($F38="",$X$10,$F38)>=J$10),$D38/12*(1+N($G38))^IF(AND(ISNUMBER($H38),J$10>=$H38),1+INT(DATEDIF($H38,J$10,"m")/12),0),0)) | K38: =IF(OR($D38="",$E38="",NOT(ISNUMBER($D38))),"",IF(AND($E38<=K$10,IF($F38="",$X$10,$F38)>=K$10),$D38/12*(1+N($G38))^IF(AND(ISNUMBER($H38),K$10>=$H38),1+INT(DATEDIF($H38,K$10,"m")/12),0),0)) | L38: =IF(OR($D38="",$E38="",NOT(ISNUMBER($D38))),"",IF(AND($E38<=L$10,IF($F38="",$X$10,$F38)>=L$10),$D38/12*(1+N($G38))^IF(AND(ISNUMBER($H38),L$10>=$H38),1+INT(DATEDIF($H38,L$10,"m")/12),0),0)) | M38: =IF(OR($D38="",$E38="",NOT(ISNUMBER($D38))),"",IF(AND($E38<=M$10,IF($F38="",$X$10,$F38)>=M$10),$D38/12*(1+N($G38))^IF(AND(ISNUMBER($H38),M$10>=$H38),1+INT(DATEDIF($H38,M$10,"m")/12),0),0)) | N38: =IF(OR($D38="",$E38="",NOT(ISNUMBER($D38))),"",IF(AND($E38<=N$10,IF($F38="",$X$10,$F38)>=N$10),$D38/12*(1+N($G38))^IF(AND(ISNUMBER($H38),N$10>=$H38),1+INT(DATEDIF($H38,N$10,"m")/12),0),0)) | O38: =IF(OR($D38="",$E38="",NOT(ISNUMBER($D38))),"",IF(AND($E38<=O$10,IF($F38="",$X$10,$F38)>=O$10),$D38/12*(1+N($G38))^IF(AND(ISNUMBER($H38),O$10>=$H38),1+INT(DATEDIF($H38,O$10,"m")/12),0),0)) | P38: =IF(OR($D38="",$E38="",NOT(ISNUMBER($D38))),"",IF(AND($E38<=P$10,IF($F38="",$X$10,$F38)>=P$10),$D38/12*(1+N($G38))^IF(AND(ISNUMBER($H38),P$10>=$H38),1+INT(DATEDIF($H38,P$10,"m")/12),0),0)) | ... X38: =IF(OR($D38="",$E38="",NOT(ISNUMBER($D38))),"",IF(AND($E38<=X$10,IF($F38="",$X$10,$F38)>=X$10),$D38/12*(1+N($G38))^IF(AND(ISNUMBER($H38),X$10>=$H38),1+INT(DATEDIF($H38,X$10,"m")/12),0),0)) | Z38: =SUM(M38:X38) -> 0 | AB38: =IF($D38&$E38="","",IF(AND($D38<>"",NOT(ISNUMBER($D38))),"Salary must be a number",IF(AND($D38<>"",$E38=""),"Start month missing",IF(AND(ISNUMBER($E38),ISNUMBER($F38),$F38<$E38),"End is before Start",IF(AND($D38<>"",NOT(ISNUMBER($H38))),"Increase month missing","")))))
F39: 46722 | G39: 0.03 | H39: =$D$8 -> 46661 | I39: =IF(OR($D39="",$E39="",NOT(ISNUMBER($D39))),"",IF(AND($E39<=I$10,IF($F39="",$X$10,$F39)>=I$10),$D39/12*(1+N($G39))^IF(AND(ISNUMBER($H39),I$10>=$H39),1+INT(DATEDIF($H39,I$10,"m")/12),0),0)) | J39: =IF(OR($D39="",$E39="",NOT(ISNUMBER($D39))),"",IF(AND($E39<=J$10,IF($F39="",$X$10,$F39)>=J$10),$D39/12*(1+N($G39))^IF(AND(ISNUMBER($H39),J$10>=$H39),1+INT(DATEDIF($H39,J$10,"m")/12),0),0)) | K39: =IF(OR($D39="",$E39="",NOT(ISNUMBER($D39))),"",IF(AND($E39<=K$10,IF($F39="",$X$10,$F39)>=K$10),$D39/12*(1+N($G39))^IF(AND(ISNUMBER($H39),K$10>=$H39),1+INT(DATEDIF($H39,K$10,"m")/12),0),0)) | L39: =IF(OR($D39="",$E39="",NOT(ISNUMBER($D39))),"",IF(AND($E39<=L$10,IF($F39="",$X$10,$F39)>=L$10),$D39/12*(1+N($G39))^IF(AND(ISNUMBER($H39),L$10>=$H39),1+INT(DATEDIF($H39,L$10,"m")/12),0),0)) | M39: =IF(OR($D39="",$E39="",NOT(ISNUMBER($D39))),"",IF(AND($E39<=M$10,IF($F39="",$X$10,$F39)>=M$10),$D39/12*(1+N($G39))^IF(AND(ISNUMBER($H39),M$10>=$H39),1+INT(DATEDIF($H39,M$10,"m")/12),0),0)) | N39: =IF(OR($D39="",$E39="",NOT(ISNUMBER($D39))),"",IF(AND($E39<=N$10,IF($F39="",$X$10,$F39)>=N$10),$D39/12*(1+N($G39))^IF(AND(ISNUMBER($H39),N$10>=$H39),1+INT(DATEDIF($H39,N$10,"m")/12),0),0)) | O39: =IF(OR($D39="",$E39="",NOT(ISNUMBER($D39))),"",IF(AND($E39<=O$10,IF($F39="",$X$10,$F39)>=O$10),$D39/12*(1+N($G39))^IF(AND(ISNUMBER($H39),O$10>=$H39),1+INT(DATEDIF($H39,O$10,"m")/12),0),0)) | P39: =IF(OR($D39="",$E39="",NOT(ISNUMBER($D39))),"",IF(AND($E39<=P$10,IF($F39="",$X$10,$F39)>=P$10),$D39/12*(1+N($G39))^IF(AND(ISNUMBER($H39),P$10>=$H39),1+INT(DATEDIF($H39,P$10,"m")/12),0),0)) | ... X39: =IF(OR($D39="",$E39="",NOT(ISNUMBER($D39))),"",IF(AND($E39<=X$10,IF($F39="",$X$10,$F39)>=X$10),$D39/12*(1+N($G39))^IF(AND(ISNUMBER($H39),X$10>=$H39),1+INT(DATEDIF($H39,X$10,"m")/12),0),0)) | Z39: =SUM(M39:X39) -> 0 | AB39: =IF($D39&$E39="","",IF(AND($D39<>"",NOT(ISNUMBER($D39))),"Salary must be a number",IF(AND($D39<>"",$E39=""),"Start month missing",IF(AND(ISNUMBER($E39),ISNUMBER($F39),$F39<$E39),"End is before Start",IF(AND($D39<>"",NOT(ISNUMBER($H39))),"Increase month missing","")))))
B40: New Hires
F41: 46722 | G41: 0.03 | H41: =$D$8 -> 46661 | I41: =IF(OR($D41="",$E41="",NOT(ISNUMBER($D41))),"",IF(AND($E41<=I$10,IF($F41="",$X$10,$F41)>=I$10),$D41/12*(1+N($G41))^IF(AND(ISNUMBER($H41),I$10>=$H41),1+INT(DATEDIF($H41,I$10,"m")/12),0),0)) | J41: =IF(OR($D41="",$E41="",NOT(ISNUMBER($D41))),"",IF(AND($E41<=J$10,IF($F41="",$X$10,$F41)>=J$10),$D41/12*(1+N($G41))^IF(AND(ISNUMBER($H41),J$10>=$H41),1+INT(DATEDIF($H41,J$10,"m")/12),0),0)) | K41: =IF(OR($D41="",$E41="",NOT(ISNUMBER($D41))),"",IF(AND($E41<=K$10,IF($F41="",$X$10,$F41)>=K$10),$D41/12*(1+N($G41))^IF(AND(ISNUMBER($H41),K$10>=$H41),1+INT(DATEDIF($H41,K$10,"m")/12),0),0)) | L41: =IF(OR($D41="",$E41="",NOT(ISNUMBER($D41))),"",IF(AND($E41<=L$10,IF($F41="",$X$10,$F41)>=L$10),$D41/12*(1+N($G41))^IF(AND(ISNUMBER($H41),L$10>=$H41),1+INT(DATEDIF($H41,L$10,"m")/12),0),0)) | M41: =IF(OR($D41="",$E41="",NOT(ISNUMBER($D41))),"",IF(AND($E41<=M$10,IF($F41="",$X$10,$F41)>=M$10),$D41/12*(1+N($G41))^IF(AND(ISNUMBER($H41),M$10>=$H41),1+INT(DATEDIF($H41,M$10,"m")/12),0),0)) | N41: =IF(OR($D41="",$E41="",NOT(ISNUMBER($D41))),"",IF(AND($E41<=N$10,IF($F41="",$X$10,$F41)>=N$10),$D41/12*(1+N($G41))^IF(AND(ISNUMBER($H41),N$10>=$H41),1+INT(DATEDIF($H41,N$10,"m")/12),0),0)) | O41: =IF(OR($D41="",$E41="",NOT(ISNUMBER($D41))),"",IF(AND($E41<=O$10,IF($F41="",$X$10,$F41)>=O$10),$D41/12*(1+N($G41))^IF(AND(ISNUMBER($H41),O$10>=$H41),1+INT(DATEDIF($H41,O$10,"m")/12),0),0)) | P41: =IF(OR($D41="",$E41="",NOT(ISNUMBER($D41))),"",IF(AND($E41<=P$10,IF($F41="",$X$10,$F41)>=P$10),$D41/12*(1+N($G41))^IF(AND(ISNUMBER($H41),P$10>=$H41),1+INT(DATEDIF($H41,P$10,"m")/12),0),0)) | ... X41: =IF(OR($D41="",$E41="",NOT(ISNUMBER($D41))),"",IF(AND($E41<=X$10,IF($F41="",$X$10,$F41)>=X$10),$D41/12*(1+N($G41))^IF(AND(ISNUMBER($H41),X$10>=$H41),1+INT(DATEDIF($H41,X$10,"m")/12),0),0)) | Z41: =SUM(M41:X41) -> 0 | AB41: =IF($D41&$E41="","",IF(AND($D41<>"",NOT(ISNUMBER($D41))),"Salary must be a number",IF(AND($D41<>"",$E41=""),"Start month missing",IF(AND(ISNUMBER($E41),ISNUMBER($F41),$F41<$E41),"End is before Start",IF(AND($D41<>"",NOT(ISNUMBER($H41))),"Increase month missing","")))))
F42: 46722 | G42: 0.03 | H42: =$D$8 -> 46661 | I42: =IF(OR($D42="",$E42="",NOT(ISNUMBER($D42))),"",IF(AND($E42<=I$10,IF($F42="",$X$10,$F42)>=I$10),$D42/12*(1+N($G42))^IF(AND(ISNUMBER($H42),I$10>=$H42),1+INT(DATEDIF($H42,I$10,"m")/12),0),0)) | J42: =IF(OR($D42="",$E42="",NOT(ISNUMBER($D42))),"",IF(AND($E42<=J$10,IF($F42="",$X$10,$F42)>=J$10),$D42/12*(1+N($G42))^IF(AND(ISNUMBER($H42),J$10>=$H42),1+INT(DATEDIF($H42,J$10,"m")/12),0),0)) | K42: =IF(OR($D42="",$E42="",NOT(ISNUMBER($D42))),"",IF(AND($E42<=K$10,IF($F42="",$X$10,$F42)>=K$10),$D42/12*(1+N($G42))^IF(AND(ISNUMBER($H42),K$10>=$H42),1+INT(DATEDIF($H42,K$10,"m")/12),0),0)) | L42: =IF(OR($D42="",$E42="",NOT(ISNUMBER($D42))),"",IF(AND($E42<=L$10,IF($F42="",$X$10,$F42)>=L$10),$D42/12*(1+N($G42))^IF(AND(ISNUMBER($H42),L$10>=$H42),1+INT(DATEDIF($H42,L$10,"m")/12),0),0)) | M42: =IF(OR($D42="",$E42="",NOT(ISNUMBER($D42))),"",IF(AND($E42<=M$10,IF($F42="",$X$10,$F42)>=M$10),$D42/12*(1+N($G42))^IF(AND(ISNUMBER($H42),M$10>=$H42),1+INT(DATEDIF($H42,M$10,"m")/12),0),0)) | N42: =IF(OR($D42="",$E42="",NOT(ISNUMBER($D42))),"",IF(AND($E42<=N$10,IF($F42="",$X$10,$F42)>=N$10),$D42/12*(1+N($G42))^IF(AND(ISNUMBER($H42),N$10>=$H42),1+INT(DATEDIF($H42,N$10,"m")/12),0),0)) | O42: =IF(OR($D42="",$E42="",NOT(ISNUMBER($D42))),"",IF(AND($E42<=O$10,IF($F42="",$X$10,$F42)>=O$10),$D42/12*(1+N($G42))^IF(AND(ISNUMBER($H42),O$10>=$H42),1+INT(DATEDIF($H42,O$10,"m")/12),0),0)) | P42: =IF(OR($D42="",$E42="",NOT(ISNUMBER($D42))),"",IF(AND($E42<=P$10,IF($F42="",$X$10,$F42)>=P$10),$D42/12*(1+N($G42))^IF(AND(ISNUMBER($H42),P$10>=$H42),1+INT(DATEDIF($H42,P$10,"m")/12),0),0)) | ... X42: =IF(OR($D42="",$E42="",NOT(ISNUMBER($D42))),"",IF(AND($E42<=X$10,IF($F42="",$X$10,$F42)>=X$10),$D42/12*(1+N($G42))^IF(AND(ISNUMBER($H42),X$10>=$H42),1+INT(DATEDIF($H42,X$10,"m")/12),0),0)) | Z42: =SUM(M42:X42) -> 0 | AB42: =IF($D42&$E42="","",IF(AND($D42<>"",NOT(ISNUMBER($D42))),"Salary must be a number",IF(AND($D42<>"",$E42=""),"Start month missing",IF(AND(ISNUMBER($E42),ISNUMBER($F42),$F42<$E42),"End is before Start",IF(AND($D42<>"",NOT(ISNUMBER($H42))),"Increase month missing","")))))
F43: 46722 | G43: 0.03 | H43: =$D$8 -> 46661 | I43: =IF(OR($D43="",$E43="",NOT(ISNUMBER($D43))),"",IF(AND($E43<=I$10,IF($F43="",$X$10,$F43)>=I$10),$D43/12*(1+N($G43))^IF(AND(ISNUMBER($H43),I$10>=$H43),1+INT(DATEDIF($H43,I$10,"m")/12),0),0)) | J43: =IF(OR($D43="",$E43="",NOT(ISNUMBER($D43))),"",IF(AND($E43<=J$10,IF($F43="",$X$10,$F43)>=J$10),$D43/12*(1+N($G43))^IF(AND(ISNUMBER($H43),J$10>=$H43),1+INT(DATEDIF($H43,J$10,"m")/12),0),0)) | K43: =IF(OR($D43="",$E43="",NOT(ISNUMBER($D43))),"",IF(AND($E43<=K$10,IF($F43="",$X$10,$F43)>=K$10),$D43/12*(1+N($G43))^IF(AND(ISNUMBER($H43),K$10>=$H43),1+INT(DATEDIF($H43,K$10,"m")/12),0),0)) | L43: =IF(OR($D43="",$E43="",NOT(ISNUMBER($D43))),"",IF(AND($E43<=L$10,IF($F43="",$X$10,$F43)>=L$10),$D43/12*(1+N($G43))^IF(AND(ISNUMBER($H43),L$10>=$H43),1+INT(DATEDIF($H43,L$10,"m")/12),0),0)) | M43: =IF(OR($D43="",$E43="",NOT(ISNUMBER($D43))),"",IF(AND($E43<=M$10,IF($F43="",$X$10,$F43)>=M$10),$D43/12*(1+N($G43))^IF(AND(ISNUMBER($H43),M$10>=$H43),1+INT(DATEDIF($H43,M$10,"m")/12),0),0)) | N43: =IF(OR($D43="",$E43="",NOT(ISNUMBER($D43))),"",IF(AND($E43<=N$10,IF($F43="",$X$10,$F43)>=N$10),$D43/12*(1+N($G43))^IF(AND(ISNUMBER($H43),N$10>=$H43),1+INT(DATEDIF($H43,N$10,"m")/12),0),0)) | O43: =IF(OR($D43="",$E43="",NOT(ISNUMBER($D43))),"",IF(AND($E43<=O$10,IF($F43="",$X$10,$F43)>=O$10),$D43/12*(1+N($G43))^IF(AND(ISNUMBER($H43),O$10>=$H43),1+INT(DATEDIF($H43,O$10,"m")/12),0),0)) | P43: =IF(OR($D43="",$E43="",NOT(ISNUMBER($D43))),"",IF(AND($E43<=P$10,IF($F43="",$X$10,$F43)>=P$10),$D43/12*(1+N($G43))^IF(AND(ISNUMBER($H43),P$10>=$H43),1+INT(DATEDIF($H43,P$10,"m")/12),0),0)) | ... X43: =IF(OR($D43="",$E43="",NOT(ISNUMBER($D43))),"",IF(AND($E43<=X$10,IF($F43="",$X$10,$F43)>=X$10),$D43/12*(1+N($G43))^IF(AND(ISNUMBER($H43),X$10>=$H43),1+INT(DATEDIF($H43,X$10,"m")/12),0),0)) | Z43: =SUM(M43:X43) -> 0 | AB43: =IF($D43&$E43="","",IF(AND($D43<>"",NOT(ISNUMBER($D43))),"Salary must be a number",IF(AND($D43<>"",$E43=""),"Start month missing",IF(AND(ISNUMBER($E43),ISNUMBER($F43),$F43<$E43),"End is before Start",IF(AND($D43<>"",NOT(ISNUMBER($H43))),"Increase month missing","")))))
F44: 46722 | G44: 0.03 | H44: =$D$8 -> 46661 | I44: =IF(OR($D44="",$E44="",NOT(ISNUMBER($D44))),"",IF(AND($E44<=I$10,IF($F44="",$X$10,$F44)>=I$10),$D44/12*(1+N($G44))^IF(AND(ISNUMBER($H44),I$10>=$H44),1+INT(DATEDIF($H44,I$10,"m")/12),0),0)) | J44: =IF(OR($D44="",$E44="",NOT(ISNUMBER($D44))),"",IF(AND($E44<=J$10,IF($F44="",$X$10,$F44)>=J$10),$D44/12*(1+N($G44))^IF(AND(ISNUMBER($H44),J$10>=$H44),1+INT(DATEDIF($H44,J$10,"m")/12),0),0)) | K44: =IF(OR($D44="",$E44="",NOT(ISNUMBER($D44))),"",IF(AND($E44<=K$10,IF($F44="",$X$10,$F44)>=K$10),$D44/12*(1+N($G44))^IF(AND(ISNUMBER($H44),K$10>=$H44),1+INT(DATEDIF($H44,K$10,"m")/12),0),0)) | L44: =IF(OR($D44="",$E44="",NOT(ISNUMBER($D44))),"",IF(AND($E44<=L$10,IF($F44="",$X$10,$F44)>=L$10),$D44/12*(1+N($G44))^IF(AND(ISNUMBER($H44),L$10>=$H44),1+INT(DATEDIF($H44,L$10,"m")/12),0),0)) | M44: =IF(OR($D44="",$E44="",NOT(ISNUMBER($D44))),"",IF(AND($E44<=M$10,IF($F44="",$X$10,$F44)>=M$10),$D44/12*(1+N($G44))^IF(AND(ISNUMBER($H44),M$10>=$H44),1+INT(DATEDIF($H44,M$10,"m")/12),0),0)) | N44: =IF(OR($D44="",$E44="",NOT(ISNUMBER($D44))),"",IF(AND($E44<=N$10,IF($F44="",$X$10,$F44)>=N$10),$D44/12*(1+N($G44))^IF(AND(ISNUMBER($H44),N$10>=$H44),1+INT(DATEDIF($H44,N$10,"m")/12),0),0)) | O44: =IF(OR($D44="",$E44="",NOT(ISNUMBER($D44))),"",IF(AND($E44<=O$10,IF($F44="",$X$10,$F44)>=O$10),$D44/12*(1+N($G44))^IF(AND(ISNUMBER($H44),O$10>=$H44),1+INT(DATEDIF($H44,O$10,"m")/12),0),0)) | P44: =IF(OR($D44="",$E44="",NOT(ISNUMBER($D44))),"",IF(AND($E44<=P$10,IF($F44="",$X$10,$F44)>=P$10),$D44/12*(1+N($G44))^IF(AND(ISNUMBER($H44),P$10>=$H44),1+INT(DATEDIF($H44,P$10,"m")/12),0),0)) | ... X44: =IF(OR($D44="",$E44="",NOT(ISNUMBER($D44))),"",IF(AND($E44<=X$10,IF($F44="",$X$10,$F44)>=X$10),$D44/12*(1+N($G44))^IF(AND(ISNUMBER($H44),X$10>=$H44),1+INT(DATEDIF($H44,X$10,"m")/12),0),0)) | Z44: =SUM(M44:X44) -> 0 | AB44: =IF($D44&$E44="","",IF(AND($D44<>"",NOT(ISNUMBER($D44))),"Salary must be a number",IF(AND($D44<>"",$E44=""),"Start month missing",IF(AND(ISNUMBER($E44),ISNUMBER($F44),$F44<$E44),"End is before Start",IF(AND($D44<>"",NOT(ISNUMBER($H44))),"Increase month missing","")))))
F45: 46722 | G45: 0.03 | H45: =$D$8 -> 46661 | I45: =IF(OR($D45="",$E45="",NOT(ISNUMBER($D45))),"",IF(AND($E45<=I$10,IF($F45="",$X$10,$F45)>=I$10),$D45/12*(1+N($G45))^IF(AND(ISNUMBER($H45),I$10>=$H45),1+INT(DATEDIF($H45,I$10,"m")/12),0),0)) | J45: =IF(OR($D45="",$E45="",NOT(ISNUMBER($D45))),"",IF(AND($E45<=J$10,IF($F45="",$X$10,$F45)>=J$10),$D45/12*(1+N($G45))^IF(AND(ISNUMBER($H45),J$10>=$H45),1+INT(DATEDIF($H45,J$10,"m")/12),0),0)) | K45: =IF(OR($D45="",$E45="",NOT(ISNUMBER($D45))),"",IF(AND($E45<=K$10,IF($F45="",$X$10,$F45)>=K$10),$D45/12*(1+N($G45))^IF(AND(ISNUMBER($H45),K$10>=$H45),1+INT(DATEDIF($H45,K$10,"m")/12),0),0)) | L45: =IF(OR($D45="",$E45="",NOT(ISNUMBER($D45))),"",IF(AND($E45<=L$10,IF($F45="",$X$10,$F45)>=L$10),$D45/12*(1+N($G45))^IF(AND(ISNUMBER($H45),L$10>=$H45),1+INT(DATEDIF($H45,L$10,"m")/12),0),0)) | M45: =IF(OR($D45="",$E45="",NOT(ISNUMBER($D45))),"",IF(AND($E45<=M$10,IF($F45="",$X$10,$F45)>=M$10),$D45/12*(1+N($G45))^IF(AND(ISNUMBER($H45),M$10>=$H45),1+INT(DATEDIF($H45,M$10,"m")/12),0),0)) | N45: =IF(OR($D45="",$E45="",NOT(ISNUMBER($D45))),"",IF(AND($E45<=N$10,IF($F45="",$X$10,$F45)>=N$10),$D45/12*(1+N($G45))^IF(AND(ISNUMBER($H45),N$10>=$H45),1+INT(DATEDIF($H45,N$10,"m")/12),0),0)) | O45: =IF(OR($D45="",$E45="",NOT(ISNUMBER($D45))),"",IF(AND($E45<=O$10,IF($F45="",$X$10,$F45)>=O$10),$D45/12*(1+N($G45))^IF(AND(ISNUMBER($H45),O$10>=$H45),1+INT(DATEDIF($H45,O$10,"m")/12),0),0)) | P45: =IF(OR($D45="",$E45="",NOT(ISNUMBER($D45))),"",IF(AND($E45<=P$10,IF($F45="",$X$10,$F45)>=P$10),$D45/12*(1+N($G45))^IF(AND(ISNUMBER($H45),P$10>=$H45),1+INT(DATEDIF($H45,P$10,"m")/12),0),0)) | ... X45: =IF(OR($D45="",$E45="",NOT(ISNUMBER($D45))),"",IF(AND($E45<=X$10,IF($F45="",$X$10,$F45)>=X$10),$D45/12*(1+N($G45))^IF(AND(ISNUMBER($H45),X$10>=$H45),1+INT(DATEDIF($H45,X$10,"m")/12),0),0)) | Z45: =SUM(M45:X45) -> 0 | AB45: =IF($D45&$E45="","",IF(AND($D45<>"",NOT(ISNUMBER($D45))),"Salary must be a number",IF(AND($D45<>"",$E45=""),"Start month missing",IF(AND(ISNUMBER($E45),ISNUMBER($F45),$F45<$E45),"End is before Start",IF(AND($D45<>"",NOT(ISNUMBER($H45))),"Increase month missing","")))))
F46: 46722 | G46: 0.03 | H46: =$D$8 -> 46661 | I46: =IF(OR($D46="",$E46="",NOT(ISNUMBER($D46))),"",IF(AND($E46<=I$10,IF($F46="",$X$10,$F46)>=I$10),$D46/12*(1+N($G46))^IF(AND(ISNUMBER($H46),I$10>=$H46),1+INT(DATEDIF($H46,I$10,"m")/12),0),0)) | J46: =IF(OR($D46="",$E46="",NOT(ISNUMBER($D46))),"",IF(AND($E46<=J$10,IF($F46="",$X$10,$F46)>=J$10),$D46/12*(1+N($G46))^IF(AND(ISNUMBER($H46),J$10>=$H46),1+INT(DATEDIF($H46,J$10,"m")/12),0),0)) | K46: =IF(OR($D46="",$E46="",NOT(ISNUMBER($D46))),"",IF(AND($E46<=K$10,IF($F46="",$X$10,$F46)>=K$10),$D46/12*(1+N($G46))^IF(AND(ISNUMBER($H46),K$10>=$H46),1+INT(DATEDIF($H46,K$10,"m")/12),0),0)) | L46: =IF(OR($D46="",$E46="",NOT(ISNUMBER($D46))),"",IF(AND($E46<=L$10,IF($F46="",$X$10,$F46)>=L$10),$D46/12*(1+N($G46))^IF(AND(ISNUMBER($H46),L$10>=$H46),1+INT(DATEDIF($H46,L$10,"m")/12),0),0)) | M46: =IF(OR($D46="",$E46="",NOT(ISNUMBER($D46))),"",IF(AND($E46<=M$10,IF($F46="",$X$10,$F46)>=M$10),$D46/12*(1+N($G46))^IF(AND(ISNUMBER($H46),M$10>=$H46),1+INT(DATEDIF($H46,M$10,"m")/12),0),0)) | N46: =IF(OR($D46="",$E46="",NOT(ISNUMBER($D46))),"",IF(AND($E46<=N$10,IF($F46="",$X$10,$F46)>=N$10),$D46/12*(1+N($G46))^IF(AND(ISNUMBER($H46),N$10>=$H46),1+INT(DATEDIF($H46,N$10,"m")/12),0),0)) | O46: =IF(OR($D46="",$E46="",NOT(ISNUMBER($D46))),"",IF(AND($E46<=O$10,IF($F46="",$X$10,$F46)>=O$10),$D46/12*(1+N($G46))^IF(AND(ISNUMBER($H46),O$10>=$H46),1+INT(DATEDIF($H46,O$10,"m")/12),0),0)) | P46: =IF(OR($D46="",$E46="",NOT(ISNUMBER($D46))),"",IF(AND($E46<=P$10,IF($F46="",$X$10,$F46)>=P$10),$D46/12*(1+N($G46))^IF(AND(ISNUMBER($H46),P$10>=$H46),1+INT(DATEDIF($H46,P$10,"m")/12),0),0)) | ... X46: =IF(OR($D46="",$E46="",NOT(ISNUMBER($D46))),"",IF(AND($E46<=X$10,IF($F46="",$X$10,$F46)>=X$10),$D46/12*(1+N($G46))^IF(AND(ISNUMBER($H46),X$10>=$H46),1+INT(DATEDIF($H46,X$10,"m")/12),0),0)) | Z46: =SUM(M46:X46) -> 0 | AB46: =IF($D46&$E46="","",IF(AND($D46<>"",NOT(ISNUMBER($D46))),"Salary must be a number",IF(AND($D46<>"",$E46=""),"Start month missing",IF(AND(ISNUMBER($E46),ISNUMBER($F46),$F46<$E46),"End is before Start",IF(AND($D46<>"",NOT(ISNUMBER($H46))),"Increase month missing","")))))
F47: 46722 | G47: 0.03 | H47: =$D$8 -> 46661 | I47: =IF(OR($D47="",$E47="",NOT(ISNUMBER($D47))),"",IF(AND($E47<=I$10,IF($F47="",$X$10,$F47)>=I$10),$D47/12*(1+N($G47))^IF(AND(ISNUMBER($H47),I$10>=$H47),1+INT(DATEDIF($H47,I$10,"m")/12),0),0)) | J47: =IF(OR($D47="",$E47="",NOT(ISNUMBER($D47))),"",IF(AND($E47<=J$10,IF($F47="",$X$10,$F47)>=J$10),$D47/12*(1+N($G47))^IF(AND(ISNUMBER($H47),J$10>=$H47),1+INT(DATEDIF($H47,J$10,"m")/12),0),0)) | K47: =IF(OR($D47="",$E47="",NOT(ISNUMBER($D47))),"",IF(AND($E47<=K$10,IF($F47="",$X$10,$F47)>=K$10),$D47/12*(1+N($G47))^IF(AND(ISNUMBER($H47),K$10>=$H47),1+INT(DATEDIF($H47,K$10,"m")/12),0),0)) | L47: =IF(OR($D47="",$E47="",NOT(ISNUMBER($D47))),"",IF(AND($E47<=L$10,IF($F47="",$X$10,$F47)>=L$10),$D47/12*(1+N($G47))^IF(AND(ISNUMBER($H47),L$10>=$H47),1+INT(DATEDIF($H47,L$10,"m")/12),0),0)) | M47: =IF(OR($D47="",$E47="",NOT(ISNUMBER($D47))),"",IF(AND($E47<=M$10,IF($F47="",$X$10,$F47)>=M$10),$D47/12*(1+N($G47))^IF(AND(ISNUMBER($H47),M$10>=$H47),1+INT(DATEDIF($H47,M$10,"m")/12),0),0)) | N47: =IF(OR($D47="",$E47="",NOT(ISNUMBER($D47))),"",IF(AND($E47<=N$10,IF($F47="",$X$10,$F47)>=N$10),$D47/12*(1+N($G47))^IF(AND(ISNUMBER($H47),N$10>=$H47),1+INT(DATEDIF($H47,N$10,"m")/12),0),0)) | O47: =IF(OR($D47="",$E47="",NOT(ISNUMBER($D47))),"",IF(AND($E47<=O$10,IF($F47="",$X$10,$F47)>=O$10),$D47/12*(1+N($G47))^IF(AND(ISNUMBER($H47),O$10>=$H47),1+INT(DATEDIF($H47,O$10,"m")/12),0),0)) | P47: =IF(OR($D47="",$E47="",NOT(ISNUMBER($D47))),"",IF(AND($E47<=P$10,IF($F47="",$X$10,$F47)>=P$10),$D47/12*(1+N($G47))^IF(AND(ISNUMBER($H47),P$10>=$H47),1+INT(DATEDIF($H47,P$10,"m")/12),0),0)) | ... X47: =IF(OR($D47="",$E47="",NOT(ISNUMBER($D47))),"",IF(AND($E47<=X$10,IF($F47="",$X$10,$F47)>=X$10),$D47/12*(1+N($G47))^IF(AND(ISNUMBER($H47),X$10>=$H47),1+INT(DATEDIF($H47,X$10,"m")/12),0),0)) | Z47: =SUM(M47:X47) -> 0 | AB47: =IF($D47&$E47="","",IF(AND($D47<>"",NOT(ISNUMBER($D47))),"Salary must be a number",IF(AND($D47<>"",$E47=""),"Start month missing",IF(AND(ISNUMBER($E47),ISNUMBER($F47),$F47<$E47),"End is before Start",IF(AND($D47<>"",NOT(ISNUMBER($H47))),"Increase month missing","")))))
F48: 46722 | G48: 0.03 | H48: =$D$8 -> 46661 | I48: =IF(OR($D48="",$E48="",NOT(ISNUMBER($D48))),"",IF(AND($E48<=I$10,IF($F48="",$X$10,$F48)>=I$10),$D48/12*(1+N($G48))^IF(AND(ISNUMBER($H48),I$10>=$H48),1+INT(DATEDIF($H48,I$10,"m")/12),0),0)) | J48: =IF(OR($D48="",$E48="",NOT(ISNUMBER($D48))),"",IF(AND($E48<=J$10,IF($F48="",$X$10,$F48)>=J$10),$D48/12*(1+N($G48))^IF(AND(ISNUMBER($H48),J$10>=$H48),1+INT(DATEDIF($H48,J$10,"m")/12),0),0)) | K48: =IF(OR($D48="",$E48="",NOT(ISNUMBER($D48))),"",IF(AND($E48<=K$10,IF($F48="",$X$10,$F48)>=K$10),$D48/12*(1+N($G48))^IF(AND(ISNUMBER($H48),K$10>=$H48),1+INT(DATEDIF($H48,K$10,"m")/12),0),0)) | L48: =IF(OR($D48="",$E48="",NOT(ISNUMBER($D48))),"",IF(AND($E48<=L$10,IF($F48="",$X$10,$F48)>=L$10),$D48/12*(1+N($G48))^IF(AND(ISNUMBER($H48),L$10>=$H48),1+INT(DATEDIF($H48,L$10,"m")/12),0),0)) | M48: =IF(OR($D48="",$E48="",NOT(ISNUMBER($D48))),"",IF(AND($E48<=M$10,IF($F48="",$X$10,$F48)>=M$10),$D48/12*(1+N($G48))^IF(AND(ISNUMBER($H48),M$10>=$H48),1+INT(DATEDIF($H48,M$10,"m")/12),0),0)) | N48: =IF(OR($D48="",$E48="",NOT(ISNUMBER($D48))),"",IF(AND($E48<=N$10,IF($F48="",$X$10,$F48)>=N$10),$D48/12*(1+N($G48))^IF(AND(ISNUMBER($H48),N$10>=$H48),1+INT(DATEDIF($H48,N$10,"m")/12),0),0)) | O48: =IF(OR($D48="",$E48="",NOT(ISNUMBER($D48))),"",IF(AND($E48<=O$10,IF($F48="",$X$10,$F48)>=O$10),$D48/12*(1+N($G48))^IF(AND(ISNUMBER($H48),O$10>=$H48),1+INT(DATEDIF($H48,O$10,"m")/12),0),0)) | P48: =IF(OR($D48="",$E48="",NOT(ISNUMBER($D48))),"",IF(AND($E48<=P$10,IF($F48="",$X$10,$F48)>=P$10),$D48/12*(1+N($G48))^IF(AND(ISNUMBER($H48),P$10>=$H48),1+INT(DATEDIF($H48,P$10,"m")/12),0),0)) | ... X48: =IF(OR($D48="",$E48="",NOT(ISNUMBER($D48))),"",IF(AND($E48<=X$10,IF($F48="",$X$10,$F48)>=X$10),$D48/12*(1+N($G48))^IF(AND(ISNUMBER($H48),X$10>=$H48),1+INT(DATEDIF($H48,X$10,"m")/12),0),0)) | Z48: =SUM(M48:X48) -> 0 | AB48: =IF($D48&$E48="","",IF(AND($D48<>"",NOT(ISNUMBER($D48))),"Salary must be a number",IF(AND($D48<>"",$E48=""),"Start month missing",IF(AND(ISNUMBER($E48),ISNUMBER($F48),$F48<$E48),"End is before Start",IF(AND($D48<>"",NOT(ISNUMBER($H48))),"Increase month missing","")))))
F49: 46722 | G49: 0.03 | H49: =$D$8 -> 46661 | I49: =IF(OR($D49="",$E49="",NOT(ISNUMBER($D49))),"",IF(AND($E49<=I$10,IF($F49="",$X$10,$F49)>=I$10),$D49/12*(1+N($G49))^IF(AND(ISNUMBER($H49),I$10>=$H49),1+INT(DATEDIF($H49,I$10,"m")/12),0),0)) | J49: =IF(OR($D49="",$E49="",NOT(ISNUMBER($D49))),"",IF(AND($E49<=J$10,IF($F49="",$X$10,$F49)>=J$10),$D49/12*(1+N($G49))^IF(AND(ISNUMBER($H49),J$10>=$H49),1+INT(DATEDIF($H49,J$10,"m")/12),0),0)) | K49: =IF(OR($D49="",$E49="",NOT(ISNUMBER($D49))),"",IF(AND($E49<=K$10,IF($F49="",$X$10,$F49)>=K$10),$D49/12*(1+N($G49))^IF(AND(ISNUMBER($H49),K$10>=$H49),1+INT(DATEDIF($H49,K$10,"m")/12),0),0)) | L49: =IF(OR($D49="",$E49="",NOT(ISNUMBER($D49))),"",IF(AND($E49<=L$10,IF($F49="",$X$10,$F49)>=L$10),$D49/12*(1+N($G49))^IF(AND(ISNUMBER($H49),L$10>=$H49),1+INT(DATEDIF($H49,L$10,"m")/12),0),0)) | M49: =IF(OR($D49="",$E49="",NOT(ISNUMBER($D49))),"",IF(AND($E49<=M$10,IF($F49="",$X$10,$F49)>=M$10),$D49/12*(1+N($G49))^IF(AND(ISNUMBER($H49),M$10>=$H49),1+INT(DATEDIF($H49,M$10,"m")/12),0),0)) | N49: =IF(OR($D49="",$E49="",NOT(ISNUMBER($D49))),"",IF(AND($E49<=N$10,IF($F49="",$X$10,$F49)>=N$10),$D49/12*(1+N($G49))^IF(AND(ISNUMBER($H49),N$10>=$H49),1+INT(DATEDIF($H49,N$10,"m")/12),0),0)) | O49: =IF(OR($D49="",$E49="",NOT(ISNUMBER($D49))),"",IF(AND($E49<=O$10,IF($F49="",$X$10,$F49)>=O$10),$D49/12*(1+N($G49))^IF(AND(ISNUMBER($H49),O$10>=$H49),1+INT(DATEDIF($H49,O$10,"m")/12),0),0)) | P49: =IF(OR($D49="",$E49="",NOT(ISNUMBER($D49))),"",IF(AND($E49<=P$10,IF($F49="",$X$10,$F49)>=P$10),$D49/12*(1+N($G49))^IF(AND(ISNUMBER($H49),P$10>=$H49),1+INT(DATEDIF($H49,P$10,"m")/12),0),0)) | ... X49: =IF(OR($D49="",$E49="",NOT(ISNUMBER($D49))),"",IF(AND($E49<=X$10,IF($F49="",$X$10,$F49)>=X$10),$D49/12*(1+N($G49))^IF(AND(ISNUMBER($H49),X$10>=$H49),1+INT(DATEDIF($H49,X$10,"m")/12),0),0)) | Z49: =SUM(M49:X49) -> 0 | AB49: =IF($D49&$E49="","",IF(AND($D49<>"",NOT(ISNUMBER($D49))),"Salary must be a number",IF(AND($D49<>"",$E49=""),"Start month missing",IF(AND(ISNUMBER($E49),ISNUMBER($F49),$F49<$E49),"End is before Start",IF(AND($D49<>"",NOT(ISNUMBER($H49))),"Increase month missing","")))))
F50: 46722 | G50: 0.03 | H50: =$D$8 -> 46661 | I50: =IF(OR($D50="",$E50="",NOT(ISNUMBER($D50))),"",IF(AND($E50<=I$10,IF($F50="",$X$10,$F50)>=I$10),$D50/12*(1+N($G50))^IF(AND(ISNUMBER($H50),I$10>=$H50),1+INT(DATEDIF($H50,I$10,"m")/12),0),0)) | J50: =IF(OR($D50="",$E50="",NOT(ISNUMBER($D50))),"",IF(AND($E50<=J$10,IF($F50="",$X$10,$F50)>=J$10),$D50/12*(1+N($G50))^IF(AND(ISNUMBER($H50),J$10>=$H50),1+INT(DATEDIF($H50,J$10,"m")/12),0),0)) | K50: =IF(OR($D50="",$E50="",NOT(ISNUMBER($D50))),"",IF(AND($E50<=K$10,IF($F50="",$X$10,$F50)>=K$10),$D50/12*(1+N($G50))^IF(AND(ISNUMBER($H50),K$10>=$H50),1+INT(DATEDIF($H50,K$10,"m")/12),0),0)) | L50: =IF(OR($D50="",$E50="",NOT(ISNUMBER($D50))),"",IF(AND($E50<=L$10,IF($F50="",$X$10,$F50)>=L$10),$D50/12*(1+N($G50))^IF(AND(ISNUMBER($H50),L$10>=$H50),1+INT(DATEDIF($H50,L$10,"m")/12),0),0)) | M50: =IF(OR($D50="",$E50="",NOT(ISNUMBER($D50))),"",IF(AND($E50<=M$10,IF($F50="",$X$10,$F50)>=M$10),$D50/12*(1+N($G50))^IF(AND(ISNUMBER($H50),M$10>=$H50),1+INT(DATEDIF($H50,M$10,"m")/12),0),0)) | N50: =IF(OR($D50="",$E50="",NOT(ISNUMBER($D50))),"",IF(AND($E50<=N$10,IF($F50="",$X$10,$F50)>=N$10),$D50/12*(1+N($G50))^IF(AND(ISNUMBER($H50),N$10>=$H50),1+INT(DATEDIF($H50,N$10,"m")/12),0),0)) | O50: =IF(OR($D50="",$E50="",NOT(ISNUMBER($D50))),"",IF(AND($E50<=O$10,IF($F50="",$X$10,$F50)>=O$10),$D50/12*(1+N($G50))^IF(AND(ISNUMBER($H50),O$10>=$H50),1+INT(DATEDIF($H50,O$10,"m")/12),0),0)) | P50: =IF(OR($D50="",$E50="",NOT(ISNUMBER($D50))),"",IF(AND($E50<=P$10,IF($F50="",$X$10,$F50)>=P$10),$D50/12*(1+N($G50))^IF(AND(ISNUMBER($H50),P$10>=$H50),1+INT(DATEDIF($H50,P$10,"m")/12),0),0)) | ... X50: =IF(OR($D50="",$E50="",NOT(ISNUMBER($D50))),"",IF(AND($E50<=X$10,IF($F50="",$X$10,$F50)>=X$10),$D50/12*(1+N($G50))^IF(AND(ISNUMBER($H50),X$10>=$H50),1+INT(DATEDIF($H50,X$10,"m")/12),0),0)) | Z50: =SUM(M50:X50) -> 0 | AB50: =IF($D50&$E50="","",IF(AND($D50<>"",NOT(ISNUMBER($D50))),"Salary must be a number",IF(AND($D50<>"",$E50=""),"Start month missing",IF(AND(ISNUMBER($E50),ISNUMBER($F50),$F50<$E50),"End is before Start",IF(AND($D50<>"",NOT(ISNUMBER($H50))),"Increase month missing","")))))
A51: From Dept | B51: Transfers In (arriving from another department — cost starts here)
F52: 46722 | G52: 0.03 | H52: =$D$8 -> 46661 | I52: =IF(OR($D52="",$E52="",NOT(ISNUMBER($D52))),"",IF(AND($E52<=I$10,IF($F52="",$X$10,$F52)>=I$10),$D52/12*(1+N($G52))^IF(AND(ISNUMBER($H52),I$10>=$H52),1+INT(DATEDIF($H52,I$10,"m")/12),0),0)) | J52: =IF(OR($D52="",$E52="",NOT(ISNUMBER($D52))),"",IF(AND($E52<=J$10,IF($F52="",$X$10,$F52)>=J$10),$D52/12*(1+N($G52))^IF(AND(ISNUMBER($H52),J$10>=$H52),1+INT(DATEDIF($H52,J$10,"m")/12),0),0)) | K52: =IF(OR($D52="",$E52="",NOT(ISNUMBER($D52))),"",IF(AND($E52<=K$10,IF($F52="",$X$10,$F52)>=K$10),$D52/12*(1+N($G52))^IF(AND(ISNUMBER($H52),K$10>=$H52),1+INT(DATEDIF($H52,K$10,"m")/12),0),0)) | L52: =IF(OR($D52="",$E52="",NOT(ISNUMBER($D52))),"",IF(AND($E52<=L$10,IF($F52="",$X$10,$F52)>=L$10),$D52/12*(1+N($G52))^IF(AND(ISNUMBER($H52),L$10>=$H52),1+INT(DATEDIF($H52,L$10,"m")/12),0),0)) | M52: =IF(OR($D52="",$E52="",NOT(ISNUMBER($D52))),"",IF(AND($E52<=M$10,IF($F52="",$X$10,$F52)>=M$10),$D52/12*(1+N($G52))^IF(AND(ISNUMBER($H52),M$10>=$H52),1+INT(DATEDIF($H52,M$10,"m")/12),0),0)) | N52: =IF(OR($D52="",$E52="",NOT(ISNUMBER($D52))),"",IF(AND($E52<=N$10,IF($F52="",$X$10,$F52)>=N$10),$D52/12*(1+N($G52))^IF(AND(ISNUMBER($H52),N$10>=$H52),1+INT(DATEDIF($H52,N$10,"m")/12),0),0)) | O52: =IF(OR($D52="",$E52="",NOT(ISNUMBER($D52))),"",IF(AND($E52<=O$10,IF($F52="",$X$10,$F52)>=O$10),$D52/12*(1+N($G52))^IF(AND(ISNUMBER($H52),O$10>=$H52),1+INT(DATEDIF($H52,O$10,"m")/12),0),0)) | P52: =IF(OR($D52="",$E52="",NOT(ISNUMBER($D52))),"",IF(AND($E52<=P$10,IF($F52="",$X$10,$F52)>=P$10),$D52/12*(1+N($G52))^IF(AND(ISNUMBER($H52),P$10>=$H52),1+INT(DATEDIF($H52,P$10,"m")/12),0),0)) | ... X52: =IF(OR($D52="",$E52="",NOT(ISNUMBER($D52))),"",IF(AND($E52<=X$10,IF($F52="",$X$10,$F52)>=X$10),$D52/12*(1+N($G52))^IF(AND(ISNUMBER($H52),X$10>=$H52),1+INT(DATEDIF($H52,X$10,"m")/12),0),0)) | Z52: =SUM(M52:X52) -> 0 | AB52: =IF($D52&$E52="","",IF(AND($D52<>"",NOT(ISNUMBER($D52))),"Salary must be a number",IF(AND($D52<>"",$E52=""),"Start month missing",IF(AND(ISNUMBER($E52),ISNUMBER($F52),$F52<$E52),"End is before Start",IF(AND($D52<>"",NOT(ISNUMBER($H52))),"Increase month missing","")))))
F53: 46722 | G53: 0.03 | H53: =$D$8 -> 46661 | I53: =IF(OR($D53="",$E53="",NOT(ISNUMBER($D53))),"",IF(AND($E53<=I$10,IF($F53="",$X$10,$F53)>=I$10),$D53/12*(1+N($G53))^IF(AND(ISNUMBER($H53),I$10>=$H53),1+INT(DATEDIF($H53,I$10,"m")/12),0),0)) | J53: =IF(OR($D53="",$E53="",NOT(ISNUMBER($D53))),"",IF(AND($E53<=J$10,IF($F53="",$X$10,$F53)>=J$10),$D53/12*(1+N($G53))^IF(AND(ISNUMBER($H53),J$10>=$H53),1+INT(DATEDIF($H53,J$10,"m")/12),0),0)) | K53: =IF(OR($D53="",$E53="",NOT(ISNUMBER($D53))),"",IF(AND($E53<=K$10,IF($F53="",$X$10,$F53)>=K$10),$D53/12*(1+N($G53))^IF(AND(ISNUMBER($H53),K$10>=$H53),1+INT(DATEDIF($H53,K$10,"m")/12),0),0)) | L53: =IF(OR($D53="",$E53="",NOT(ISNUMBER($D53))),"",IF(AND($E53<=L$10,IF($F53="",$X$10,$F53)>=L$10),$D53/12*(1+N($G53))^IF(AND(ISNUMBER($H53),L$10>=$H53),1+INT(DATEDIF($H53,L$10,"m")/12),0),0)) | M53: =IF(OR($D53="",$E53="",NOT(ISNUMBER($D53))),"",IF(AND($E53<=M$10,IF($F53="",$X$10,$F53)>=M$10),$D53/12*(1+N($G53))^IF(AND(ISNUMBER($H53),M$10>=$H53),1+INT(DATEDIF($H53,M$10,"m")/12),0),0)) | N53: =IF(OR($D53="",$E53="",NOT(ISNUMBER($D53))),"",IF(AND($E53<=N$10,IF($F53="",$X$10,$F53)>=N$10),$D53/12*(1+N($G53))^IF(AND(ISNUMBER($H53),N$10>=$H53),1+INT(DATEDIF($H53,N$10,"m")/12),0),0)) | O53: =IF(OR($D53="",$E53="",NOT(ISNUMBER($D53))),"",IF(AND($E53<=O$10,IF($F53="",$X$10,$F53)>=O$10),$D53/12*(1+N($G53))^IF(AND(ISNUMBER($H53),O$10>=$H53),1+INT(DATEDIF($H53,O$10,"m")/12),0),0)) | P53: =IF(OR($D53="",$E53="",NOT(ISNUMBER($D53))),"",IF(AND($E53<=P$10,IF($F53="",$X$10,$F53)>=P$10),$D53/12*(1+N($G53))^IF(AND(ISNUMBER($H53),P$10>=$H53),1+INT(DATEDIF($H53,P$10,"m")/12),0),0)) | ... X53: =IF(OR($D53="",$E53="",NOT(ISNUMBER($D53))),"",IF(AND($E53<=X$10,IF($F53="",$X$10,$F53)>=X$10),$D53/12*(1+N($G53))^IF(AND(ISNUMBER($H53),X$10>=$H53),1+INT(DATEDIF($H53,X$10,"m")/12),0),0)) | Z53: =SUM(M53:X53) -> 0 | AB53: =IF($D53&$E53="","",IF(AND($D53<>"",NOT(ISNUMBER($D53))),"Salary must be a number",IF(AND($D53<>"",$E53=""),"Start month missing",IF(AND(ISNUMBER($E53),ISNUMBER($F53),$F53<$E53),"End is before Start",IF(AND($D53<>"",NOT(ISNUMBER($H53))),"Increase month missing","")))))
F54: 46722 | G54: 0.03 | H54: =$D$8 -> 46661 | I54: =IF(OR($D54="",$E54="",NOT(ISNUMBER($D54))),"",IF(AND($E54<=I$10,IF($F54="",$X$10,$F54)>=I$10),$D54/12*(1+N($G54))^IF(AND(ISNUMBER($H54),I$10>=$H54),1+INT(DATEDIF($H54,I$10,"m")/12),0),0)) | J54: =IF(OR($D54="",$E54="",NOT(ISNUMBER($D54))),"",IF(AND($E54<=J$10,IF($F54="",$X$10,$F54)>=J$10),$D54/12*(1+N($G54))^IF(AND(ISNUMBER($H54),J$10>=$H54),1+INT(DATEDIF($H54,J$10,"m")/12),0),0)) | K54: =IF(OR($D54="",$E54="",NOT(ISNUMBER($D54))),"",IF(AND($E54<=K$10,IF($F54="",$X$10,$F54)>=K$10),$D54/12*(1+N($G54))^IF(AND(ISNUMBER($H54),K$10>=$H54),1+INT(DATEDIF($H54,K$10,"m")/12),0),0)) | L54: =IF(OR($D54="",$E54="",NOT(ISNUMBER($D54))),"",IF(AND($E54<=L$10,IF($F54="",$X$10,$F54)>=L$10),$D54/12*(1+N($G54))^IF(AND(ISNUMBER($H54),L$10>=$H54),1+INT(DATEDIF($H54,L$10,"m")/12),0),0)) | M54: =IF(OR($D54="",$E54="",NOT(ISNUMBER($D54))),"",IF(AND($E54<=M$10,IF($F54="",$X$10,$F54)>=M$10),$D54/12*(1+N($G54))^IF(AND(ISNUMBER($H54),M$10>=$H54),1+INT(DATEDIF($H54,M$10,"m")/12),0),0)) | N54: =IF(OR($D54="",$E54="",NOT(ISNUMBER($D54))),"",IF(AND($E54<=N$10,IF($F54="",$X$10,$F54)>=N$10),$D54/12*(1+N($G54))^IF(AND(ISNUMBER($H54),N$10>=$H54),1+INT(DATEDIF($H54,N$10,"m")/12),0),0)) | O54: =IF(OR($D54="",$E54="",NOT(ISNUMBER($D54))),"",IF(AND($E54<=O$10,IF($F54="",$X$10,$F54)>=O$10),$D54/12*(1+N($G54))^IF(AND(ISNUMBER($H54),O$10>=$H54),1+INT(DATEDIF($H54,O$10,"m")/12),0),0)) | P54: =IF(OR($D54="",$E54="",NOT(ISNUMBER($D54))),"",IF(AND($E54<=P$10,IF($F54="",$X$10,$F54)>=P$10),$D54/12*(1+N($G54))^IF(AND(ISNUMBER($H54),P$10>=$H54),1+INT(DATEDIF($H54,P$10,"m")/12),0),0)) | ... X54: =IF(OR($D54="",$E54="",NOT(ISNUMBER($D54))),"",IF(AND($E54<=X$10,IF($F54="",$X$10,$F54)>=X$10),$D54/12*(1+N($G54))^IF(AND(ISNUMBER($H54),X$10>=$H54),1+INT(DATEDIF($H54,X$10,"m")/12),0),0)) | Z54: =SUM(M54:X54) -> 0 | AB54: =IF($D54&$E54="","",IF(AND($D54<>"",NOT(ISNUMBER($D54))),"Salary must be a number",IF(AND($D54<>"",$E54=""),"Start month missing",IF(AND(ISNUMBER($E54),ISNUMBER($F54),$F54<$E54),"End is before Start",IF(AND($D54<>"",NOT(ISNUMBER($H54))),"Increase month missing","")))))
F55: 46722 | G55: 0.03 | H55: =$D$8 -> 46661 | I55: =IF(OR($D55="",$E55="",NOT(ISNUMBER($D55))),"",IF(AND($E55<=I$10,IF($F55="",$X$10,$F55)>=I$10),$D55/12*(1+N($G55))^IF(AND(ISNUMBER($H55),I$10>=$H55),1+INT(DATEDIF($H55,I$10,"m")/12),0),0)) | J55: =IF(OR($D55="",$E55="",NOT(ISNUMBER($D55))),"",IF(AND($E55<=J$10,IF($F55="",$X$10,$F55)>=J$10),$D55/12*(1+N($G55))^IF(AND(ISNUMBER($H55),J$10>=$H55),1+INT(DATEDIF($H55,J$10,"m")/12),0),0)) | K55: =IF(OR($D55="",$E55="",NOT(ISNUMBER($D55))),"",IF(AND($E55<=K$10,IF($F55="",$X$10,$F55)>=K$10),$D55/12*(1+N($G55))^IF(AND(ISNUMBER($H55),K$10>=$H55),1+INT(DATEDIF($H55,K$10,"m")/12),0),0)) | L55: =IF(OR($D55="",$E55="",NOT(ISNUMBER($D55))),"",IF(AND($E55<=L$10,IF($F55="",$X$10,$F55)>=L$10),$D55/12*(1+N($G55))^IF(AND(ISNUMBER($H55),L$10>=$H55),1+INT(DATEDIF($H55,L$10,"m")/12),0),0)) | M55: =IF(OR($D55="",$E55="",NOT(ISNUMBER($D55))),"",IF(AND($E55<=M$10,IF($F55="",$X$10,$F55)>=M$10),$D55/12*(1+N($G55))^IF(AND(ISNUMBER($H55),M$10>=$H55),1+INT(DATEDIF($H55,M$10,"m")/12),0),0)) | N55: =IF(OR($D55="",$E55="",NOT(ISNUMBER($D55))),"",IF(AND($E55<=N$10,IF($F55="",$X$10,$F55)>=N$10),$D55/12*(1+N($G55))^IF(AND(ISNUMBER($H55),N$10>=$H55),1+INT(DATEDIF($H55,N$10,"m")/12),0),0)) | O55: =IF(OR($D55="",$E55="",NOT(ISNUMBER($D55))),"",IF(AND($E55<=O$10,IF($F55="",$X$10,$F55)>=O$10),$D55/12*(1+N($G55))^IF(AND(ISNUMBER($H55),O$10>=$H55),1+INT(DATEDIF($H55,O$10,"m")/12),0),0)) | P55: =IF(OR($D55="",$E55="",NOT(ISNUMBER($D55))),"",IF(AND($E55<=P$10,IF($F55="",$X$10,$F55)>=P$10),$D55/12*(1+N($G55))^IF(AND(ISNUMBER($H55),P$10>=$H55),1+INT(DATEDIF($H55,P$10,"m")/12),0),0)) | ... X55: =IF(OR($D55="",$E55="",NOT(ISNUMBER($D55))),"",IF(AND($E55<=X$10,IF($F55="",$X$10,$F55)>=X$10),$D55/12*(1+N($G55))^IF(AND(ISNUMBER($H55),X$10>=$H55),1+INT(DATEDIF($H55,X$10,"m")/12),0),0)) | Z55: =SUM(M55:X55) -> 0 | AB55: =IF($D55&$E55="","",IF(AND($D55<>"",NOT(ISNUMBER($D55))),"Salary must be a number",IF(AND($D55<>"",$E55=""),"Start month missing",IF(AND(ISNUMBER($E55),ISNUMBER($F55),$F55<$E55),"End is before Start",IF(AND($D55<>"",NOT(ISNUMBER($H55))),"Increase month missing","")))))
F56: 46722 | G56: 0.03 | H56: =$D$8 -> 46661 | I56: =IF(OR($D56="",$E56="",NOT(ISNUMBER($D56))),"",IF(AND($E56<=I$10,IF($F56="",$X$10,$F56)>=I$10),$D56/12*(1+N($G56))^IF(AND(ISNUMBER($H56),I$10>=$H56),1+INT(DATEDIF($H56,I$10,"m")/12),0),0)) | J56: =IF(OR($D56="",$E56="",NOT(ISNUMBER($D56))),"",IF(AND($E56<=J$10,IF($F56="",$X$10,$F56)>=J$10),$D56/12*(1+N($G56))^IF(AND(ISNUMBER($H56),J$10>=$H56),1+INT(DATEDIF($H56,J$10,"m")/12),0),0)) | K56: =IF(OR($D56="",$E56="",NOT(ISNUMBER($D56))),"",IF(AND($E56<=K$10,IF($F56="",$X$10,$F56)>=K$10),$D56/12*(1+N($G56))^IF(AND(ISNUMBER($H56),K$10>=$H56),1+INT(DATEDIF($H56,K$10,"m")/12),0),0)) | L56: =IF(OR($D56="",$E56="",NOT(ISNUMBER($D56))),"",IF(AND($E56<=L$10,IF($F56="",$X$10,$F56)>=L$10),$D56/12*(1+N($G56))^IF(AND(ISNUMBER($H56),L$10>=$H56),1+INT(DATEDIF($H56,L$10,"m")/12),0),0)) | M56: =IF(OR($D56="",$E56="",NOT(ISNUMBER($D56))),"",IF(AND($E56<=M$10,IF($F56="",$X$10,$F56)>=M$10),$D56/12*(1+N($G56))^IF(AND(ISNUMBER($H56),M$10>=$H56),1+INT(DATEDIF($H56,M$10,"m")/12),0),0)) | N56: =IF(OR($D56="",$E56="",NOT(ISNUMBER($D56))),"",IF(AND($E56<=N$10,IF($F56="",$X$10,$F56)>=N$10),$D56/12*(1+N($G56))^IF(AND(ISNUMBER($H56),N$10>=$H56),1+INT(DATEDIF($H56,N$10,"m")/12),0),0)) | O56: =IF(OR($D56="",$E56="",NOT(ISNUMBER($D56))),"",IF(AND($E56<=O$10,IF($F56="",$X$10,$F56)>=O$10),$D56/12*(1+N($G56))^IF(AND(ISNUMBER($H56),O$10>=$H56),1+INT(DATEDIF($H56,O$10,"m")/12),0),0)) | P56: =IF(OR($D56="",$E56="",NOT(ISNUMBER($D56))),"",IF(AND($E56<=P$10,IF($F56="",$X$10,$F56)>=P$10),$D56/12*(1+N($G56))^IF(AND(ISNUMBER($H56),P$10>=$H56),1+INT(DATEDIF($H56,P$10,"m")/12),0),0)) | ... X56: =IF(OR($D56="",$E56="",NOT(ISNUMBER($D56))),"",IF(AND($E56<=X$10,IF($F56="",$X$10,$F56)>=X$10),$D56/12*(1+N($G56))^IF(AND(ISNUMBER($H56),X$10>=$H56),1+INT(DATEDIF($H56,X$10,"m")/12),0),0)) | Z56: =SUM(M56:X56) -> 0 | AB56: =IF($D56&$E56="","",IF(AND($D56<>"",NOT(ISNUMBER($D56))),"Salary must be a number",IF(AND($D56<>"",$E56=""),"Start month missing",IF(AND(ISNUMBER($E56),ISNUMBER($F56),$F56<$E56),"End is before Start",IF(AND($D56<>"",NOT(ISNUMBER($H56))),"Increase month missing","")))))
F57: 46722 | G57: 0.03 | H57: =$D$8 -> 46661 | I57: =IF(OR($D57="",$E57="",NOT(ISNUMBER($D57))),"",IF(AND($E57<=I$10,IF($F57="",$X$10,$F57)>=I$10),$D57/12*(1+N($G57))^IF(AND(ISNUMBER($H57),I$10>=$H57),1+INT(DATEDIF($H57,I$10,"m")/12),0),0)) | J57: =IF(OR($D57="",$E57="",NOT(ISNUMBER($D57))),"",IF(AND($E57<=J$10,IF($F57="",$X$10,$F57)>=J$10),$D57/12*(1+N($G57))^IF(AND(ISNUMBER($H57),J$10>=$H57),1+INT(DATEDIF($H57,J$10,"m")/12),0),0)) | K57: =IF(OR($D57="",$E57="",NOT(ISNUMBER($D57))),"",IF(AND($E57<=K$10,IF($F57="",$X$10,$F57)>=K$10),$D57/12*(1+N($G57))^IF(AND(ISNUMBER($H57),K$10>=$H57),1+INT(DATEDIF($H57,K$10,"m")/12),0),0)) | L57: =IF(OR($D57="",$E57="",NOT(ISNUMBER($D57))),"",IF(AND($E57<=L$10,IF($F57="",$X$10,$F57)>=L$10),$D57/12*(1+N($G57))^IF(AND(ISNUMBER($H57),L$10>=$H57),1+INT(DATEDIF($H57,L$10,"m")/12),0),0)) | M57: =IF(OR($D57="",$E57="",NOT(ISNUMBER($D57))),"",IF(AND($E57<=M$10,IF($F57="",$X$10,$F57)>=M$10),$D57/12*(1+N($G57))^IF(AND(ISNUMBER($H57),M$10>=$H57),1+INT(DATEDIF($H57,M$10,"m")/12),0),0)) | N57: =IF(OR($D57="",$E57="",NOT(ISNUMBER($D57))),"",IF(AND($E57<=N$10,IF($F57="",$X$10,$F57)>=N$10),$D57/12*(1+N($G57))^IF(AND(ISNUMBER($H57),N$10>=$H57),1+INT(DATEDIF($H57,N$10,"m")/12),0),0)) | O57: =IF(OR($D57="",$E57="",NOT(ISNUMBER($D57))),"",IF(AND($E57<=O$10,IF($F57="",$X$10,$F57)>=O$10),$D57/12*(1+N($G57))^IF(AND(ISNUMBER($H57),O$10>=$H57),1+INT(DATEDIF($H57,O$10,"m")/12),0),0)) | P57: =IF(OR($D57="",$E57="",NOT(ISNUMBER($D57))),"",IF(AND($E57<=P$10,IF($F57="",$X$10,$F57)>=P$10),$D57/12*(1+N($G57))^IF(AND(ISNUMBER($H57),P$10>=$H57),1+INT(DATEDIF($H57,P$10,"m")/12),0),0)) | ... X57: =IF(OR($D57="",$E57="",NOT(ISNUMBER($D57))),"",IF(AND($E57<=X$10,IF($F57="",$X$10,$F57)>=X$10),$D57/12*(1+N($G57))^IF(AND(ISNUMBER($H57),X$10>=$H57),1+INT(DATEDIF($H57,X$10,"m")/12),0),0)) | Z57: =SUM(M57:X57) -> 0 | AB57: =IF($D57&$E57="","",IF(AND($D57<>"",NOT(ISNUMBER($D57))),"Salary must be a number",IF(AND($D57<>"",$E57=""),"Start month missing",IF(AND(ISNUMBER($E57),ISNUMBER($F57),$F57<$E57),"End is before Start",IF(AND($D57<>"",NOT(ISNUMBER($H57))),"Increase month missing","")))))
A58: To Dept | B58: Transfers Out (leaving to another department — MEMO ONLY, no cost; set this person's End Month above to the month before they leave)
AB59: =IF($B59&$E59="","",IF($A59="","Receiving dept missing",IF(NOT(ISNUMBER($E59)),"Effective month missing","")))
AB60: =IF($B60&$E60="","",IF($A60="","Receiving dept missing",IF(NOT(ISNUMBER($E60)),"Effective month missing","")))
AB61: =IF($B61&$E61="","",IF($A61="","Receiving dept missing",IF(NOT(ISNUMBER($E61)),"Effective month missing","")))
AB62: =IF($B62&$E62="","",IF($A62="","Receiving dept missing",IF(NOT(ISNUMBER($E62)),"Effective month missing","")))
AB63: =IF($B63&$E63="","",IF($A63="","Receiving dept missing",IF(NOT(ISNUMBER($E63)),"Effective month missing","")))
AB64: =IF($B64&$E64="","",IF($A64="","Receiving dept missing",IF(NOT(ISNUMBER($E64)),"Effective month missing","")))
B67: Total Salaries & Wages | I67: =SUM(I14:I57) -> 90012.583 | J67: =SUM(J14:J57) -> 90012.583 | K67: =SUM(K14:K57) -> 90012.583 | L67: =SUM(L14:L57) -> 90012.583 | M67: =SUM(M14:M57) -> 90012.583 | N67: =SUM(N14:N57) -> 90012.583 | O67: =SUM(O14:O57) -> 90012.583 | P67: =SUM(P14:P57) -> 90012.583 | ... X67: =SUM(X14:X57) -> 92712.961 | Z67: =SUM(M67:X67) -> 1088252.1
B68: Payroll Taxes | I68: =I67*$D$6 -> 6163.2434 | J68: =J67*$D$6 -> 6163.2434 | K68: =K67*$D$6 -> 6163.2434 | L68: =L67*$D$6 -> 6163.2434 | M68: =M67*$D$6 -> 6163.2434 | N68: =N67*$D$6 -> 6163.2434 | O68: =O67*$D$6 -> 6163.2434 | P68: =P67*$D$6 -> 6163.2434 | ... X68: =X67*$D$6 -> 6348.1407 | Z68: =SUM(M68:X68) -> 74513.612
B69: Benefits | I69: =I67*$D$7 -> 14766.898 | J69: =J67*$D$7 -> 14766.898 | K69: =K67*$D$7 -> 14766.898 | L69: =L67*$D$7 -> 14766.898 | M69: =M67*$D$7 -> 14766.898 | N69: =N67*$D$7 -> 14766.898 | O69: =O67*$D$7 -> 14766.898 | P69: =P67*$D$7 -> 14766.898 | ... X69: =X67*$D$7 -> 15209.905 | Z69: =SUM(M69:X69) -> 178531.8
B70: Total Payroll | I70: =SUM(I67:I69) -> 110942.72 | J70: =SUM(J67:J69) -> 110942.72 | K70: =SUM(K67:K69) -> 110942.72 | L70: =SUM(L67:L69) -> 110942.72 | M70: =SUM(M67:M69) -> 110942.72 | N70: =SUM(N67:N69) -> 110942.72 | O70: =SUM(O67:O69) -> 110942.72 | P70: =SUM(P67:P69) -> 110942.72 | ... X70: =SUM(X67:X69) -> 114271.01 | Z70: =SUM(M70:X70) -> 1341297.5

Sheet PO HC
A1: Slip Robotics, Inc.
A2: PRODUCTION OPERATIONS (PO) — 16 Month Headcount & Labor Build (Sep-2026 → Dec-2027)
A3: Build labor by employee for 16 months: Sep-2026 through Dec-2027. Pick Start and End months from the dropdown (End defaults to Dec-27). Leave Start blank for unfilled positions. Salaries / Taxes / Benefits flow to the Budget file.
A4: Leader: COO | Dept Code: PO | P&L Classification: COGS | GL Accounts — Salaries 5110 · Taxes 5130 · Benefits 5140
B5: ASSUMPTIONS
B6: Employer payroll tax rate (% of wages) | D6: =INDEX('[1]T&B'!$S$13:$S$122,MATCH("PO",'[1]T&B'!$R$13:$R$122,0)) -> 0.036368897
B7: Benefits load (% of salary) | D7: =INDEX('[1]T&B'!$T$13:$T$122,MATCH("PO",'[1]T&B'!$R$13:$R$122,0)) -> 0.20636269
B8: Annual Increase Month in Budget year | D8: 46661 | V8: Annual
V9: Increase
B10: Employee | C10: Title | D10: Annual Salary | E10: Start Month | F10: End Month | G10: Annual Increase | H10: Increase Month | I10: =DATE(2026,9,1) -> 46266 | J10: =DATE(2026,10,1) -> 46296 | K10: =DATE(2026,11,1) -> 46327 | L10: =DATE(2026,12,1) -> 46357 | M10: =DATE(2027,1,1) -> 46388 | N10: =DATE(2027,2,1) -> 46419 | O10: =DATE(2027,3,1) -> 46447 | P10: =DATE(2027,4,1) -> 46478 | Q10: =DATE(2027,5,1) -> 46508 | R10: =DATE(2027,6,1) -> 46539 | S10: =DATE(2027,7,1) -> 46569 | T10: =DATE(2027,8,1) -> 46600 | U10: =DATE(2027,9,1) -> 46631 | V10: =DATE(2027,10,1) -> 46661 | W10: =DATE(2027,11,1) -> 46692 | X10: =DATE(2027,12,1) -> 46722 | Z10: 2027 Total | AB10: Input check
E11: (pick from list) | F11: (pick from list) | H11: Month index → | I11: 1 | J11: 2 | K11: 3 | L11: 4 | M11: 5 | N11: 6 | O11: 7 | P11: 8 | Q11: 9 | R11: 10 | S11: 11 | T11: 12 | U11: 13 | V11: 14 | W11: 15 | X11: 16
B13: Current Employees
B14: Jose Pagan | C14: Team Lead | D14: 67891 | E14: 46266 | F14: 46722 | G14: 0.03 | H14: =$D$8 -> 46661 | I14: =IF(OR($D14="",$E14="",NOT(ISNUMBER($D14))),"",IF(AND($E14<=I$10,IF($F14="",$X$10,$F14)>=I$10),$D14/12*(1+N($G14))^IF(AND(ISNUMBER($H14),I$10>=$H14),1+INT(DATEDIF($H14,I$10,"m")/12),0),0)) -> 5657.5833 | J14: =IF(OR($D14="",$E14="",NOT(ISNUMBER($D14))),"",IF(AND($E14<=J$10,IF($F14="",$X$10,$F14)>=J$10),$D14/12*(1+N($G14))^IF(AND(ISNUMBER($H14),J$10>=$H14),1+INT(DATEDIF($H14,J$10,"m")/12),0),0)) -> 5657.5833 | K14: =IF(OR($D14="",$E14="",NOT(ISNUMBER($D14))),"",IF(AND($E14<=K$10,IF($F14="",$X$10,$F14)>=K$10),$D14/12*(1+N($G14))^IF(AND(ISNUMBER($H14),K$10>=$H14),1+INT(DATEDIF($H14,K$10,"m")/12),0),0)) -> 5657.5833 | L14: =IF(OR($D14="",$E14="",NOT(ISNUMBER($D14))),"",IF(AND($E14<=L$10,IF($F14="",$X$10,$F14)>=L$10),$D14/12*(1+N($G14))^IF(AND(ISNUMBER($H14),L$10>=$H14),1+INT(DATEDIF($H14,L$10,"m")/12),0),0)) -> 5657.5833 | M14: =IF(OR($D14="",$E14="",NOT(ISNUMBER($D14))),"",IF(AND($E14<=M$10,IF($F14="",$X$10,$F14)>=M$10),$D14/12*(1+N($G14))^IF(AND(ISNUMBER($H14),M$10>=$H14),1+INT(DATEDIF($H14,M$10,"m")/12),0),0)) -> 5657.5833 | N14: =IF(OR($D14="",$E14="",NOT(ISNUMBER($D14))),"",IF(AND($E14<=N$10,IF($F14="",$X$10,$F14)>=N$10),$D14/12*(1+N($G14))^IF(AND(ISNUMBER($H14),N$10>=$H14),1+INT(DATEDIF($H14,N$10,"m")/12),0),0)) -> 5657.5833 | O14: =IF(OR($D14="",$E14="",NOT(ISNUMBER($D14))),"",IF(AND($E14<=O$10,IF($F14="",$X$10,$F14)>=O$10),$D14/12*(1+N($G14))^IF(AND(ISNUMBER($H14),O$10>=$H14),1+INT(DATEDIF($H14,O$10,"m")/12),0),0)) -> 5657.5833 | P14: =IF(OR($D14="",$E14="",NOT(ISNUMBER($D14))),"",IF(AND($E14<=P$10,IF($F14="",$X$10,$F14)>=P$10),$D14/12*(1+N($G14))^IF(AND(ISNUMBER($H14),P$10>=$H14),1+INT(DATEDIF($H14,P$10,"m")/12),0),0)) -> 5657.5833 | ... X14: =IF(OR($D14="",$E14="",NOT(ISNUMBER($D14))),"",IF(AND($E14<=X$10,IF($F14="",$X$10,$F14)>=X$10),$D14/12*(1+N($G14))^IF(AND(ISNUMBER($H14),X$10>=$H14),1+INT(DATEDIF($H14,X$10,"m")/12),0),0)) -> 5827.3108 | Z14: =SUM(M14:X14) -> 68400.183 | AB14: =IF($D14&$E14="","",IF(AND($D14<>"",NOT(ISNUMBER($D14))),"Salary must be a number",IF(AND($D14<>"",$E14=""),"Start month missing",IF(AND(ISNUMBER($E14),ISNUMBER($F14),$F14<$E14),"End is before Start",IF(AND($D14<>"",NOT(ISNUMBER($H14))),"Increase month missing","")))))
A15: x | B15: JB Bryant | C15: Team Lead | D15: 68810 | E15: 46266 | F15: 46722 | G15: 0.03 | H15: =$D$8 -> 46661 | I15: =IF(OR($D15="",$E15="",NOT(ISNUMBER($D15))),"",IF(AND($E15<=I$10,IF($F15="",$X$10,$F15)>=I$10),$D15/12*(1+N($G15))^IF(AND(ISNUMBER($H15),I$10>=$H15),1+INT(DATEDIF($H15,I$10,"m")/12),0),0)) -> 5734.1667 | J15: =IF(OR($D15="",$E15="",NOT(ISNUMBER($D15))),"",IF(AND($E15<=J$10,IF($F15="",$X$10,$F15)>=J$10),$D15/12*(1+N($G15))^IF(AND(ISNUMBER($H15),J$10>=$H15),1+INT(DATEDIF($H15,J$10,"m")/12),0),0)) -> 5734.1667 | K15: =IF(OR($D15="",$E15="",NOT(ISNUMBER($D15))),"",IF(AND($E15<=K$10,IF($F15="",$X$10,$F15)>=K$10),$D15/12*(1+N($G15))^IF(AND(ISNUMBER($H15),K$10>=$H15),1+INT(DATEDIF($H15,K$10,"m")/12),0),0)) -> 5734.1667 | L15: =IF(OR($D15="",$E15="",NOT(ISNUMBER($D15))),"",IF(AND($E15<=L$10,IF($F15="",$X$10,$F15)>=L$10),$D15/12*(1+N($G15))^IF(AND(ISNUMBER($H15),L$10>=$H15),1+INT(DATEDIF($H15,L$10,"m")/12),0),0)) -> 5734.1667 | M15: =IF(OR($D15="",$E15="",NOT(ISNUMBER($D15))),"",IF(AND($E15<=M$10,IF($F15="",$X$10,$F15)>=M$10),$D15/12*(1+N($G15))^IF(AND(ISNUMBER($H15),M$10>=$H15),1+INT(DATEDIF($H15,M$10,"m")/12),0),0)) -> 5734.1667 | N15: =IF(OR($D15="",$E15="",NOT(ISNUMBER($D15))),"",IF(AND($E15<=N$10,IF($F15="",$X$10,$F15)>=N$10),$D15/12*(1+N($G15))^IF(AND(ISNUMBER($H15),N$10>=$H15),1+INT(DATEDIF($H15,N$10,"m")/12),0),0)) -> 5734.1667 | O15: =IF(OR($D15="",$E15="",NOT(ISNUMBER($D15))),"",IF(AND($E15<=O$10,IF($F15="",$X$10,$F15)>=O$10),$D15/12*(1+N($G15))^IF(AND(ISNUMBER($H15),O$10>=$H15),1+INT(DATEDIF($H15,O$10,"m")/12),0),0)) -> 5734.1667 | P15: =IF(OR($D15="",$E15="",NOT(ISNUMBER($D15))),"",IF(AND($E15<=P$10,IF($F15="",$X$10,$F15)>=P$10),$D15/12*(1+N($G15))^IF(AND(ISNUMBER($H15),P$10>=$H15),1+INT(DATEDIF($H15,P$10,"m")/12),0),0)) -> 5734.1667 | ... X15: =IF(OR($D15="",$E15="",NOT(ISNUMBER($D15))),"",IF(AND($E15<=X$10,IF($F15="",$X$10,$F15)>=X$10),$D15/12*(1+N($G15))^IF(AND(ISNUMBER($H15),X$10>=$H15),1+INT(DATEDIF($H15,X$10,"m")/12),0),0)) -> 5906.1917 | Z15: =SUM(M15:X15) -> 69326.075 | AB15: =IF($D15&$E15="","",IF(AND($D15<>"",NOT(ISNUMBER($D15))),"Salary must be a number",IF(AND($D15<>"",$E15=""),"Start month missing",IF(AND(ISNUMBER($E15),ISNUMBER($F15),$F15<$E15),"End is before Start",IF(AND($D15<>"",NOT(ISNUMBER($H15))),"Increase month missing","")))))
B16: Servando Flores Barrios | C16: Material Handling Team Lead | D16: 57554 | E16: 46266 | F16: 46722 | G16: 0.03 | H16: =$D$8 -> 46661 | I16: =IF(OR($D16="",$E16="",NOT(ISNUMBER($D16))),"",IF(AND($E16<=I$10,IF($F16="",$X$10,$F16)>=I$10),$D16/12*(1+N($G16))^IF(AND(ISNUMBER($H16),I$10>=$H16),1+INT(DATEDIF($H16,I$10,"m")/12),0),0)) -> 4796.1667 | J16: =IF(OR($D16="",$E16="",NOT(ISNUMBER($D16))),"",IF(AND($E16<=J$10,IF($F16="",$X$10,$F16)>=J$10),$D16/12*(1+N($G16))^IF(AND(ISNUMBER($H16),J$10>=$H16),1+INT(DATEDIF($H16,J$10,"m")/12),0),0)) -> 4796.1667 | K16: =IF(OR($D16="",$E16="",NOT(ISNUMBER($D16))),"",IF(AND($E16<=K$10,IF($F16="",$X$10,$F16)>=K$10),$D16/12*(1+N($G16))^IF(AND(ISNUMBER($H16),K$10>=$H16),1+INT(DATEDIF($H16,K$10,"m")/12),0),0)) -> 4796.1667 | L16: =IF(OR($D16="",$E16="",NOT(ISNUMBER($D16))),"",IF(AND($E16<=L$10,IF($F16="",$X$10,$F16)>=L$10),$D16/12*(1+N($G16))^IF(AND(ISNUMBER($H16),L$10>=$H16),1+INT(DATEDIF($H16,L$10,"m")/12),0),0)) -> 4796.1667 | M16: =IF(OR($D16="",$E16="",NOT(ISNUMBER($D16))),"",IF(AND($E16<=M$10,IF($F16="",$X$10,$F16)>=M$10),$D16/12*(1+N($G16))^IF(AND(ISNUMBER($H16),M$10>=$H16),1+INT(DATEDIF($H16,M$10,"m")/12),0),0)) -> 4796.1667 | N16: =IF(OR($D16="",$E16="",NOT(ISNUMBER($D16))),"",IF(AND($E16<=N$10,IF($F16="",$X$10,$F16)>=N$10),$D16/12*(1+N($G16))^IF(AND(ISNUMBER($H16),N$10>=$H16),1+INT(DATEDIF($H16,N$10,"m")/12),0),0)) -> 4796.1667 | O16: =IF(OR($D16="",$E16="",NOT(ISNUMBER($D16))),"",IF(AND($E16<=O$10,IF($F16="",$X$10,$F16)>=O$10),$D16/12*(1+N($G16))^IF(AND(ISNUMBER($H16),O$10>=$H16),1+INT(DATEDIF($H16,O$10,"m")/12),0),0)) -> 4796.1667 | P16: =IF(OR($D16="",$E16="",NOT(ISNUMBER($D16))),"",IF(AND($E16<=P$10,IF($F16="",$X$10,$F16)>=P$10),$D16/12*(1+N($G16))^IF(AND(ISNUMBER($H16),P$10>=$H16),1+INT(DATEDIF($H16,P$10,"m")/12),0),0)) -> 4796.1667 | ... X16: =IF(OR($D16="",$E16="",NOT(ISNUMBER($D16))),"",IF(AND($E16<=X$10,IF($F16="",$X$10,$F16)>=X$10),$D16/12*(1+N($G16))^IF(AND(ISNUMBER($H16),X$10>=$H16),1+INT(DATEDIF($H16,X$10,"m")/12),0),0)) -> 4940.0517 | Z16: =SUM(M16:X16) -> 57985.655 | AB16: =IF($D16&$E16="","",IF(AND($D16<>"",NOT(ISNUMBER($D16))),"Salary must be a number",IF(AND($D16<>"",$E16=""),"Start month missing",IF(AND(ISNUMBER($E16),ISNUMBER($F16),$F16<$E16),"End is before Start",IF(AND($D16<>"",NOT(ISNUMBER($H16))),"Increase month missing","")))))
B17: Oz Exposito | C17: Senior Production Technician | D17: 64409 | E17: 46266 | F17: 46722 | G17: 0.03 | H17: =$D$8 -> 46661 | I17: =IF(OR($D17="",$E17="",NOT(ISNUMBER($D17))),"",IF(AND($E17<=I$10,IF($F17="",$X$10,$F17)>=I$10),$D17/12*(1+N($G17))^IF(AND(ISNUMBER($H17),I$10>=$H17),1+INT(DATEDIF($H17,I$10,"m")/12),0),0)) -> 5367.4167 | J17: =IF(OR($D17="",$E17="",NOT(ISNUMBER($D17))),"",IF(AND($E17<=J$10,IF($F17="",$X$10,$F17)>=J$10),$D17/12*(1+N($G17))^IF(AND(ISNUMBER($H17),J$10>=$H17),1+INT(DATEDIF($H17,J$10,"m")/12),0),0)) -> 5367.4167 | K17: =IF(OR($D17="",$E17="",NOT(ISNUMBER($D17))),"",IF(AND($E17<=K$10,IF($F17="",$X$10,$F17)>=K$10),$D17/12*(1+N($G17))^IF(AND(ISNUMBER($H17),K$10>=$H17),1+INT(DATEDIF($H17,K$10,"m")/12),0),0)) -> 5367.4167 | L17: =IF(OR($D17="",$E17="",NOT(ISNUMBER($D17))),"",IF(AND($E17<=L$10,IF($F17="",$X$10,$F17)>=L$10),$D17/12*(1+N($G17))^IF(AND(ISNUMBER($H17),L$10>=$H17),1+INT(DATEDIF($H17,L$10,"m")/12),0),0)) -> 5367.4167 | M17: =IF(OR($D17="",$E17="",NOT(ISNUMBER($D17))),"",IF(AND($E17<=M$10,IF($F17="",$X$10,$F17)>=M$10),$D17/12*(1+N($G17))^IF(AND(ISNUMBER($H17),M$10>=$H17),1+INT(DATEDIF($H17,M$10,"m")/12),0),0)) -> 5367.4167 | N17: =IF(OR($D17="",$E17="",NOT(ISNUMBER($D17))),"",IF(AND($E17<=N$10,IF($F17="",$X$10,$F17)>=N$10),$D17/12*(1+N($G17))^IF(AND(ISNUMBER($H17),N$10>=$H17),1+INT(DATEDIF($H17,N$10,"m")/12),0),0)) -> 5367.4167 | O17: =IF(OR($D17="",$E17="",NOT(ISNUMBER($D17))),"",IF(AND($E17<=O$10,IF($F17="",$X$10,$F17)>=O$10),$D17/12*(1+N($G17))^IF(AND(ISNUMBER($H17),O$10>=$H17),1+INT(DATEDIF($H17,O$10,"m")/12),0),0)) -> 5367.4167 | P17: =IF(OR($D17="",$E17="",NOT(ISNUMBER($D17))),"",IF(AND($E17<=P$10,IF($F17="",$X$10,$F17)>=P$10),$D17/12*(1+N($G17))^IF(AND(ISNUMBER($H17),P$10>=$H17),1+INT(DATEDIF($H17,P$10,"m")/12),0),0)) -> 5367.4167 | ... X17: =IF(OR($D17="",$E17="",NOT(ISNUMBER($D17))),"",IF(AND($E17<=X$10,IF($F17="",$X$10,$F17)>=X$10),$D17/12*(1+N($G17))^IF(AND(ISNUMBER($H17),X$10>=$H17),1+INT(DATEDIF($H17,X$10,"m")/12),0),0)) -> 5528.4392 | Z17: =SUM(M17:X17) -> 64892.067 | AB17: =IF($D17&$E17="","",IF(AND($D17<>"",NOT(ISNUMBER($D17))),"Salary must be a number",IF(AND($D17<>"",$E17=""),"Start month missing",IF(AND(ISNUMBER($E17),ISNUMBER($F17),$F17<$E17),"End is before Start",IF(AND($D17<>"",NOT(ISNUMBER($H17))),"Increase month missing","")))))
A18: x | B18: Todd VanDyke | C18: Senior Production Technician | D18: 57814 | E18: 46266 | F18: 46722 | G18: 0.03 | H18: =$D$8 -> 46661 | I18: =IF(OR($D18="",$E18="",NOT(ISNUMBER($D18))),"",IF(AND($E18<=I$10,IF($F18="",$X$10,$F18)>=I$10),$D18/12*(1+N($G18))^IF(AND(ISNUMBER($H18),I$10>=$H18),1+INT(DATEDIF($H18,I$10,"m")/12),0),0)) -> 4817.8333 | J18: =IF(OR($D18="",$E18="",NOT(ISNUMBER($D18))),"",IF(AND($E18<=J$10,IF($F18="",$X$10,$F18)>=J$10),$D18/12*(1+N($G18))^IF(AND(ISNUMBER($H18),J$10>=$H18),1+INT(DATEDIF($H18,J$10,"m")/12),0),0)) -> 4817.8333 | K18: =IF(OR($D18="",$E18="",NOT(ISNUMBER($D18))),"",IF(AND($E18<=K$10,IF($F18="",$X$10,$F18)>=K$10),$D18/12*(1+N($G18))^IF(AND(ISNUMBER($H18),K$10>=$H18),1+INT(DATEDIF($H18,K$10,"m")/12),0),0)) -> 4817.8333 | L18: =IF(OR($D18="",$E18="",NOT(ISNUMBER($D18))),"",IF(AND($E18<=L$10,IF($F18="",$X$10,$F18)>=L$10),$D18/12*(1+N($G18))^IF(AND(ISNUMBER($H18),L$10>=$H18),1+INT(DATEDIF($H18,L$10,"m")/12),0),0)) -> 4817.8333 | M18: =IF(OR($D18="",$E18="",NOT(ISNUMBER($D18))),"",IF(AND($E18<=M$10,IF($F18="",$X$10,$F18)>=M$10),$D18/12*(1+N($G18))^IF(AND(ISNUMBER($H18),M$10>=$H18),1+INT(DATEDIF($H18,M$10,"m")/12),0),0)) -> 4817.8333 | N18: =IF(OR($D18="",$E18="",NOT(ISNUMBER($D18))),"",IF(AND($E18<=N$10,IF($F18="",$X$10,$F18)>=N$10),$D18/12*(1+N($G18))^IF(AND(ISNUMBER($H18),N$10>=$H18),1+INT(DATEDIF($H18,N$10,"m")/12),0),0)) -> 4817.8333 | O18: =IF(OR($D18="",$E18="",NOT(ISNUMBER($D18))),"",IF(AND($E18<=O$10,IF($F18="",$X$10,$F18)>=O$10),$D18/12*(1+N($G18))^IF(AND(ISNUMBER($H18),O$10>=$H18),1+INT(DATEDIF($H18,O$10,"m")/12),0),0)) -> 4817.8333 | P18: =IF(OR($D18="",$E18="",NOT(ISNUMBER($D18))),"",IF(AND($E18<=P$10,IF($F18="",$X$10,$F18)>=P$10),$D18/12*(1+N($G18))^IF(AND(ISNUMBER($H18),P$10>=$H18),1+INT(DATEDIF($H18,P$10,"m")/12),0),0)) -> 4817.8333 | ... X18: =IF(OR($D18="",$E18="",NOT(ISNUMBER($D18))),"",IF(AND($E18<=X$10,IF($F18="",$X$10,$F18)>=X$10),$D18/12*(1+N($G18))^IF(AND(ISNUMBER($H18),X$10>=$H18),1+INT(DATEDIF($H18,X$10,"m")/12),0),0)) -> 4962.3683 | Z18: =SUM(M18:X18) -> 58247.605 | AB18: =IF($D18&$E18="","",IF(AND($D18<>"",NOT(ISNUMBER($D18))),"Salary must be a number",IF(AND($D18<>"",$E18=""),"Start month missing",IF(AND(ISNUMBER($E18),ISNUMBER($F18),$F18<$E18),"End is before Start",IF(AND($D18<>"",NOT(ISNUMBER($H18))),"Increase month missing","")))))
A19: x | B19: Johnathan Argueta | C19: Production Technician | D19: 55162 | E19: 46266 | F19: 46722 | G19: 0.03 | H19: =$D$8 -> 46661 | I19: =IF(OR($D19="",$E19="",NOT(ISNUMBER($D19))),"",IF(AND($E19<=I$10,IF($F19="",$X$10,$F19)>=I$10),$D19/12*(1+N($G19))^IF(AND(ISNUMBER($H19),I$10>=$H19),1+INT(DATEDIF($H19,I$10,"m")/12),0),0)) -> 4596.8333 | J19: =IF(OR($D19="",$E19="",NOT(ISNUMBER($D19))),"",IF(AND($E19<=J$10,IF($F19="",$X$10,$F19)>=J$10),$D19/12*(1+N($G19))^IF(AND(ISNUMBER($H19),J$10>=$H19),1+INT(DATEDIF($H19,J$10,"m")/12),0),0)) -> 4596.8333 | K19: =IF(OR($D19="",$E19="",NOT(ISNUMBER($D19))),"",IF(AND($E19<=K$10,IF($F19="",$X$10,$F19)>=K$10),$D19/12*(1+N($G19))^IF(AND(ISNUMBER($H19),K$10>=$H19),1+INT(DATEDIF($H19,K$10,"m")/12),0),0)) -> 4596.8333 | L19: =IF(OR($D19="",$E19="",NOT(ISNUMBER($D19))),"",IF(AND($E19<=L$10,IF($F19="",$X$10,$F19)>=L$10),$D19/12*(1+N($G19))^IF(AND(ISNUMBER($H19),L$10>=$H19),1+INT(DATEDIF($H19,L$10,"m")/12),0),0)) -> 4596.8333 | M19: =IF(OR($D19="",$E19="",NOT(ISNUMBER($D19))),"",IF(AND($E19<=M$10,IF($F19="",$X$10,$F19)>=M$10),$D19/12*(1+N($G19))^IF(AND(ISNUMBER($H19),M$10>=$H19),1+INT(DATEDIF($H19,M$10,"m")/12),0),0)) -> 4596.8333 | N19: =IF(OR($D19="",$E19="",NOT(ISNUMBER($D19))),"",IF(AND($E19<=N$10,IF($F19="",$X$10,$F19)>=N$10),$D19/12*(1+N($G19))^IF(AND(ISNUMBER($H19),N$10>=$H19),1+INT(DATEDIF($H19,N$10,"m")/12),0),0)) -> 4596.8333 | O19: =IF(OR($D19="",$E19="",NOT(ISNUMBER($D19))),"",IF(AND($E19<=O$10,IF($F19="",$X$10,$F19)>=O$10),$D19/12*(1+N($G19))^IF(AND(ISNUMBER($H19),O$10>=$H19),1+INT(DATEDIF($H19,O$10,"m")/12),0),0)) -> 4596.8333 | P19: =IF(OR($D19="",$E19="",NOT(ISNUMBER($D19))),"",IF(AND($E19<=P$10,IF($F19="",$X$10,$F19)>=P$10),$D19/12*(1+N($G19))^IF(AND(ISNUMBER($H19),P$10>=$H19),1+INT(DATEDIF($H19,P$10,"m")/12),0),0)) -> 4596.8333 | ... X19: =IF(OR($D19="",$E19="",NOT(ISNUMBER($D19))),"",IF(AND($E19<=X$10,IF($F19="",$X$10,$F19)>=X$10),$D19/12*(1+N($G19))^IF(AND(ISNUMBER($H19),X$10>=$H19),1+INT(DATEDIF($H19,X$10,"m")/12),0),0)) -> 4734.7383 | Z19: =SUM(M19:X19) -> 55575.715 | AB19: =IF($D19&$E19="","",IF(AND($D19<>"",NOT(ISNUMBER($D19))),"Salary must be a number",IF(AND($D19<>"",$E19=""),"Start month missing",IF(AND(ISNUMBER($E19),ISNUMBER($F19),$F19<$E19),"End is before Start",IF(AND($D19<>"",NOT(ISNUMBER($H19))),"Increase month missing","")))))
A20: x | B20: Austin Steed | C20: Material Handler | D20: 49920 | E20: 46266 | F20: 46722 | G20: 0.03 | H20: =$D$8 -> 46661 | I20: =IF(OR($D20="",$E20="",NOT(ISNUMBER($D20))),"",IF(AND($E20<=I$10,IF($F20="",$X$10,$F20)>=I$10),$D20/12*(1+N($G20))^IF(AND(ISNUMBER($H20),I$10>=$H20),1+INT(DATEDIF($H20,I$10,"m")/12),0),0)) -> 4160 | J20: =IF(OR($D20="",$E20="",NOT(ISNUMBER($D20))),"",IF(AND($E20<=J$10,IF($F20="",$X$10,$F20)>=J$10),$D20/12*(1+N($G20))^IF(AND(ISNUMBER($H20),J$10>=$H20),1+INT(DATEDIF($H20,J$10,"m")/12),0),0)) -> 4160 | K20: =IF(OR($D20="",$E20="",NOT(ISNUMBER($D20))),"",IF(AND($E20<=K$10,IF($F20="",$X$10,$F20)>=K$10),$D20/12*(1+N($G20))^IF(AND(ISNUMBER($H20),K$10>=$H20),1+INT(DATEDIF($H20,K$10,"m")/12),0),0)) -> 4160 | L20: =IF(OR($D20="",$E20="",NOT(ISNUMBER($D20))),"",IF(AND($E20<=L$10,IF($F20="",$X$10,$F20)>=L$10),$D20/12*(1+N($G20))^IF(AND(ISNUMBER($H20),L$10>=$H20),1+INT(DATEDIF($H20,L$10,"m")/12),0),0)) -> 4160 | M20: =IF(OR($D20="",$E20="",NOT(ISNUMBER($D20))),"",IF(AND($E20<=M$10,IF($F20="",$X$10,$F20)>=M$10),$D20/12*(1+N($G20))^IF(AND(ISNUMBER($H20),M$10>=$H20),1+INT(DATEDIF($H20,M$10,"m")/12),0),0)) -> 4160 | N20: =IF(OR($D20="",$E20="",NOT(ISNUMBER($D20))),"",IF(AND($E20<=N$10,IF($F20="",$X$10,$F20)>=N$10),$D20/12*(1+N($G20))^IF(AND(ISNUMBER($H20),N$10>=$H20),1+INT(DATEDIF($H20,N$10,"m")/12),0),0)) -> 4160 | O20: =IF(OR($D20="",$E20="",NOT(ISNUMBER($D20))),"",IF(AND($E20<=O$10,IF($F20="",$X$10,$F20)>=O$10),$D20/12*(1+N($G20))^IF(AND(ISNUMBER($H20),O$10>=$H20),1+INT(DATEDIF($H20,O$10,"m")/12),0),0)) -> 4160 | P20: =IF(OR($D20="",$E20="",NOT(ISNUMBER($D20))),"",IF(AND($E20<=P$10,IF($F20="",$X$10,$F20)>=P$10),$D20/12*(1+N($G20))^IF(AND(ISNUMBER($H20),P$10>=$H20),1+INT(DATEDIF($H20,P$10,"m")/12),0),0)) -> 4160 | ... X20: =IF(OR($D20="",$E20="",NOT(ISNUMBER($D20))),"",IF(AND($E20<=X$10,IF($F20="",$X$10,$F20)>=X$10),$D20/12*(1+N($G20))^IF(AND(ISNUMBER($H20),X$10>=$H20),1+INT(DATEDIF($H20,X$10,"m")/12),0),0)) -> 4284.8 | Z20: =SUM(M20:X20) -> 50294.4 | AB20: =IF($D20&$E20="","",IF(AND($D20<>"",NOT(ISNUMBER($D20))),"Salary must be a number",IF(AND($D20<>"",$E20=""),"Start month missing",IF(AND(ISNUMBER($E20),ISNUMBER($F20),$F20<$E20),"End is before Start",IF(AND($D20<>"",NOT(ISNUMBER($H20))),"Increase month missing","")))))
A21: x | B21: Jason Price | C21: Production Associate | D21: 49920 | E21: 46266 | F21: 46722 | G21: 0.03 | H21: =$D$8 -> 46661 | I21: =IF(OR($D21="",$E21="",NOT(ISNUMBER($D21))),"",IF(AND($E21<=I$10,IF($F21="",$X$10,$F21)>=I$10),$D21/12*(1+N($G21))^IF(AND(ISNUMBER($H21),I$10>=$H21),1+INT(DATEDIF($H21,I$10,"m")/12),0),0)) -> 4160 | J21: =IF(OR($D21="",$E21="",NOT(ISNUMBER($D21))),"",IF(AND($E21<=J$10,IF($F21="",$X$10,$F21)>=J$10),$D21/12*(1+N($G21))^IF(AND(ISNUMBER($H21),J$10>=$H21),1+INT(DATEDIF($H21,J$10,"m")/12),0),0)) -> 4160 | K21: =IF(OR($D21="",$E21="",NOT(ISNUMBER($D21))),"",IF(AND($E21<=K$10,IF($F21="",$X$10,$F21)>=K$10),$D21/12*(1+N($G21))^IF(AND(ISNUMBER($H21),K$10>=$H21),1+INT(DATEDIF($H21,K$10,"m")/12),0),0)) -> 4160 | L21: =IF(OR($D21="",$E21="",NOT(ISNUMBER($D21))),"",IF(AND($E21<=L$10,IF($F21="",$X$10,$F21)>=L$10),$D21/12*(1+N($G21))^IF(AND(ISNUMBER($H21),L$10>=$H21),1+INT(DATEDIF($H21,L$10,"m")/12),0),0)) -> 4160 | M21: =IF(OR($D21="",$E21="",NOT(ISNUMBER($D21))),"",IF(AND($E21<=M$10,IF($F21="",$X$10,$F21)>=M$10),$D21/12*(1+N($G21))^IF(AND(ISNUMBER($H21),M$10>=$H21),1+INT(DATEDIF($H21,M$10,"m")/12),0),0)) -> 4160 | N21: =IF(OR($D21="",$E21="",NOT(ISNUMBER($D21))),"",IF(AND($E21<=N$10,IF($F21="",$X$10,$F21)>=N$10),$D21/12*(1+N($G21))^IF(AND(ISNUMBER($H21),N$10>=$H21),1+INT(DATEDIF($H21,N$10,"m")/12),0),0)) -> 4160 | O21: =IF(OR($D21="",$E21="",NOT(ISNUMBER($D21))),"",IF(AND($E21<=O$10,IF($F21="",$X$10,$F21)>=O$10),$D21/12*(1+N($G21))^IF(AND(ISNUMBER($H21),O$10>=$H21),1+INT(DATEDIF($H21,O$10,"m")/12),0),0)) -> 4160 | P21: =IF(OR($D21="",$E21="",NOT(ISNUMBER($D21))),"",IF(AND($E21<=P$10,IF($F21="",$X$10,$F21)>=P$10),$D21/12*(1+N($G21))^IF(AND(ISNUMBER($H21),P$10>=$H21),1+INT(DATEDIF($H21,P$10,"m")/12),0),0)) -> 4160 | ... X21: =IF(OR($D21="",$E21="",NOT(ISNUMBER($D21))),"",IF(AND($E21<=X$10,IF($F21="",$X$10,$F21)>=X$10),$D21/12*(1+N($G21))^IF(AND(ISNUMBER($H21),X$10>=$H21),1+INT(DATEDIF($H21,X$10,"m")/12),0),0)) -> 4284.8 | Z21: =SUM(M21:X21) -> 50294.4 | AB21: =IF($D21&$E21="","",IF(AND($D21<>"",NOT(ISNUMBER($D21))),"Salary must be a number",IF(AND($D21<>"",$E21=""),"Start month missing",IF(AND(ISNUMBER($E21),ISNUMBER($F21),$F21<$E21),"End is before Start",IF(AND($D21<>"",NOT(ISNUMBER($H21))),"Increase month missing","")))))
A22: x | B22: Mose Carter | C22: Production Associate | D22: 49920 | E22: 46266 | F22: 46722 | G22: 0.03 | H22: =$D$8 -> 46661 | I22: =IF(OR($D22="",$E22="",NOT(ISNUMBER($D22))),"",IF(AND($E22<=I$10,IF($F22="",$X$10,$F22)>=I$10),$D22/12*(1+N($G22))^IF(AND(ISNUMBER($H22),I$10>=$H22),1+INT(DATEDIF($H22,I$10,"m")/12),0),0)) -> 4160 | J22: =IF(OR($D22="",$E22="",NOT(ISNUMBER($D22))),"",IF(AND($E22<=J$10,IF($F22="",$X$10,$F22)>=J$10),$D22/12*(1+N($G22))^IF(AND(ISNUMBER($H22),J$10>=$H22),1+INT(DATEDIF($H22,J$10,"m")/12),0),0)) -> 4160 | K22: =IF(OR($D22="",$E22="",NOT(ISNUMBER($D22))),"",IF(AND($E22<=K$10,IF($F22="",$X$10,$F22)>=K$10),$D22/12*(1+N($G22))^IF(AND(ISNUMBER($H22),K$10>=$H22),1+INT(DATEDIF($H22,K$10,"m")/12),0),0)) -> 4160 | L22: =IF(OR($D22="",$E22="",NOT(ISNUMBER($D22))),"",IF(AND($E22<=L$10,IF($F22="",$X$10,$F22)>=L$10),$D22/12*(1+N($G22))^IF(AND(ISNUMBER($H22),L$10>=$H22),1+INT(DATEDIF($H22,L$10,"m")/12),0),0)) -> 4160 | M22: =IF(OR($D22="",$E22="",NOT(ISNUMBER($D22))),"",IF(AND($E22<=M$10,IF($F22="",$X$10,$F22)>=M$10),$D22/12*(1+N($G22))^IF(AND(ISNUMBER($H22),M$10>=$H22),1+INT(DATEDIF($H22,M$10,"m")/12),0),0)) -> 4160 | N22: =IF(OR($D22="",$E22="",NOT(ISNUMBER($D22))),"",IF(AND($E22<=N$10,IF($F22="",$X$10,$F22)>=N$10),$D22/12*(1+N($G22))^IF(AND(ISNUMBER($H22),N$10>=$H22),1+INT(DATEDIF($H22,N$10,"m")/12),0),0)) -> 4160 | O22: =IF(OR($D22="",$E22="",NOT(ISNUMBER($D22))),"",IF(AND($E22<=O$10,IF($F22="",$X$10,$F22)>=O$10),$D22/12*(1+N($G22))^IF(AND(ISNUMBER($H22),O$10>=$H22),1+INT(DATEDIF($H22,O$10,"m")/12),0),0)) -> 4160 | P22: =IF(OR($D22="",$E22="",NOT(ISNUMBER($D22))),"",IF(AND($E22<=P$10,IF($F22="",$X$10,$F22)>=P$10),$D22/12*(1+N($G22))^IF(AND(ISNUMBER($H22),P$10>=$H22),1+INT(DATEDIF($H22,P$10,"m")/12),0),0)) -> 4160 | ... X22: =IF(OR($D22="",$E22="",NOT(ISNUMBER($D22))),"",IF(AND($E22<=X$10,IF($F22="",$X$10,$F22)>=X$10),$D22/12*(1+N($G22))^IF(AND(ISNUMBER($H22),X$10>=$H22),1+INT(DATEDIF($H22,X$10,"m")/12),0),0)) -> 4284.8 | Z22: =SUM(M22:X22) -> 50294.4 | AB22: =IF($D22&$E22="","",IF(AND($D22<>"",NOT(ISNUMBER($D22))),"Salary must be a number",IF(AND($D22<>"",$E22=""),"Start month missing",IF(AND(ISNUMBER($E22),ISNUMBER($F22),$F22<$E22),"End is before Start",IF(AND($D22<>"",NOT(ISNUMBER($H22))),"Increase month missing","")))))
E23: 46266 | F23: 46722 | G23: 0.03 | H23: =$D$8 -> 46661 | I23: =IF(OR($D23="",$E23="",NOT(ISNUMBER($D23))),"",IF(AND($E23<=I$10,IF($F23="",$X$10,$F23)>=I$10),$D23/12*(1+N($G23))^IF(AND(ISNUMBER($H23),I$10>=$H23),1+INT(DATEDIF($H23,I$10,"m")/12),0),0)) | J23: =IF(OR($D23="",$E23="",NOT(ISNUMBER($D23))),"",IF(AND($E23<=J$10,IF($F23="",$X$10,$F23)>=J$10),$D23/12*(1+N($G23))^IF(AND(ISNUMBER($H23),J$10>=$H23),1+INT(DATEDIF($H23,J$10,"m")/12),0),0)) | K23: =IF(OR($D23="",$E23="",NOT(ISNUMBER($D23))),"",IF(AND($E23<=K$10,IF($F23="",$X$10,$F23)>=K$10),$D23/12*(1+N($G23))^IF(AND(ISNUMBER($H23),K$10>=$H23),1+INT(DATEDIF($H23,K$10,"m")/12),0),0)) | L23: =IF(OR($D23="",$E23="",NOT(ISNUMBER($D23))),"",IF(AND($E23<=L$10,IF($F23="",$X$10,$F23)>=L$10),$D23/12*(1+N($G23))^IF(AND(ISNUMBER($H23),L$10>=$H23),1+INT(DATEDIF($H23,L$10,"m")/12),0),0)) | M23: =IF(OR($D23="",$E23="",NOT(ISNUMBER($D23))),"",IF(AND($E23<=M$10,IF($F23="",$X$10,$F23)>=M$10),$D23/12*(1+N($G23))^IF(AND(ISNUMBER($H23),M$10>=$H23),1+INT(DATEDIF($H23,M$10,"m")/12),0),0)) | N23: =IF(OR($D23="",$E23="",NOT(ISNUMBER($D23))),"",IF(AND($E23<=N$10,IF($F23="",$X$10,$F23)>=N$10),$D23/12*(1+N($G23))^IF(AND(ISNUMBER($H23),N$10>=$H23),1+INT(DATEDIF($H23,N$10,"m")/12),0),0)) | O23: =IF(OR($D23="",$E23="",NOT(ISNUMBER($D23))),"",IF(AND($E23<=O$10,IF($F23="",$X$10,$F23)>=O$10),$D23/12*(1+N($G23))^IF(AND(ISNUMBER($H23),O$10>=$H23),1+INT(DATEDIF($H23,O$10,"m")/12),0),0)) | P23: =IF(OR($D23="",$E23="",NOT(ISNUMBER($D23))),"",IF(AND($E23<=P$10,IF($F23="",$X$10,$F23)>=P$10),$D23/12*(1+N($G23))^IF(AND(ISNUMBER($H23),P$10>=$H23),1+INT(DATEDIF($H23,P$10,"m")/12),0),0)) | ... X23: =IF(OR($D23="",$E23="",NOT(ISNUMBER($D23))),"",IF(AND($E23<=X$10,IF($F23="",$X$10,$F23)>=X$10),$D23/12*(1+N($G23))^IF(AND(ISNUMBER($H23),X$10>=$H23),1+INT(DATEDIF($H23,X$10,"m")/12),0),0)) | Z23: =SUM(M23:X23) -> 0 | AB23: =IF($D23&$E23="","",IF(AND($D23<>"",NOT(ISNUMBER($D23))),"Salary must be a number",IF(AND($D23<>"",$E23=""),"Start month missing",IF(AND(ISNUMBER($E23),ISNUMBER($F23),$F23<$E23),"End is before Start",IF(AND($D23<>"",NOT(ISNUMBER($H23))),"Increase month missing","")))))
E24: 46266 | F24: 46722 | G24: 0.03 | H24: =$D$8 -> 46661 | I24: =IF(OR($D24="",$E24="",NOT(ISNUMBER($D24))),"",IF(AND($E24<=I$10,IF($F24="",$X$10,$F24)>=I$10),$D24/12*(1+N($G24))^IF(AND(ISNUMBER($H24),I$10>=$H24),1+INT(DATEDIF($H24,I$10,"m")/12),0),0)) | J24: =IF(OR($D24="",$E24="",NOT(ISNUMBER($D24))),"",IF(AND($E24<=J$10,IF($F24="",$X$10,$F24)>=J$10),$D24/12*(1+N($G24))^IF(AND(ISNUMBER($H24),J$10>=$H24),1+INT(DATEDIF($H24,J$10,"m")/12),0),0)) | K24: =IF(OR($D24="",$E24="",NOT(ISNUMBER($D24))),"",IF(AND($E24<=K$10,IF($F24="",$X$10,$F24)>=K$10),$D24/12*(1+N($G24))^IF(AND(ISNUMBER($H24),K$10>=$H24),1+INT(DATEDIF($H24,K$10,"m")/12),0),0)) | L24: =IF(OR($D24="",$E24="",NOT(ISNUMBER($D24))),"",IF(AND($E24<=L$10,IF($F24="",$X$10,$F24)>=L$10),$D24/12*(1+N($G24))^IF(AND(ISNUMBER($H24),L$10>=$H24),1+INT(DATEDIF($H24,L$10,"m")/12),0),0)) | M24: =IF(OR($D24="",$E24="",NOT(ISNUMBER($D24))),"",IF(AND($E24<=M$10,IF($F24="",$X$10,$F24)>=M$10),$D24/12*(1+N($G24))^IF(AND(ISNUMBER($H24),M$10>=$H24),1+INT(DATEDIF($H24,M$10,"m")/12),0),0)) | N24: =IF(OR($D24="",$E24="",NOT(ISNUMBER($D24))),"",IF(AND($E24<=N$10,IF($F24="",$X$10,$F24)>=N$10),$D24/12*(1+N($G24))^IF(AND(ISNUMBER($H24),N$10>=$H24),1+INT(DATEDIF($H24,N$10,"m")/12),0),0)) | O24: =IF(OR($D24="",$E24="",NOT(ISNUMBER($D24))),"",IF(AND($E24<=O$10,IF($F24="",$X$10,$F24)>=O$10),$D24/12*(1+N($G24))^IF(AND(ISNUMBER($H24),O$10>=$H24),1+INT(DATEDIF($H24,O$10,"m")/12),0),0)) | P24: =IF(OR($D24="",$E24="",NOT(ISNUMBER($D24))),"",IF(AND($E24<=P$10,IF($F24="",$X$10,$F24)>=P$10),$D24/12*(1+N($G24))^IF(AND(ISNUMBER($H24),P$10>=$H24),1+INT(DATEDIF($H24,P$10,"m")/12),0),0)) | ... X24: =IF(OR($D24="",$E24="",NOT(ISNUMBER($D24))),"",IF(AND($E24<=X$10,IF($F24="",$X$10,$F24)>=X$10),$D24/12*(1+N($G24))^IF(AND(ISNUMBER($H24),X$10>=$H24),1+INT(DATEDIF($H24,X$10,"m")/12),0),0)) | Z24: =SUM(M24:X24) -> 0 | AB24: =IF($D24&$E24="","",IF(AND($D24<>"",NOT(ISNUMBER($D24))),"Salary must be a number",IF(AND($D24<>"",$E24=""),"Start month missing",IF(AND(ISNUMBER($E24),ISNUMBER($F24),$F24<$E24),"End is before Start",IF(AND($D24<>"",NOT(ISNUMBER($H24))),"Increase month missing","")))))
E25: 46266 | F25: 46722 | G25: 0.03 | H25: =$D$8 -> 46661 | I25: =IF(OR($D25="",$E25="",NOT(ISNUMBER($D25))),"",IF(AND($E25<=I$10,IF($F25="",$X$10,$F25)>=I$10),$D25/12*(1+N($G25))^IF(AND(ISNUMBER($H25),I$10>=$H25),1+INT(DATEDIF($H25,I$10,"m")/12),0),0)) | J25: =IF(OR($D25="",$E25="",NOT(ISNUMBER($D25))),"",IF(AND($E25<=J$10,IF($F25="",$X$10,$F25)>=J$10),$D25/12*(1+N($G25))^IF(AND(ISNUMBER($H25),J$10>=$H25),1+INT(DATEDIF($H25,J$10,"m")/12),0),0)) | K25: =IF(OR($D25="",$E25="",NOT(ISNUMBER($D25))),"",IF(AND($E25<=K$10,IF($F25="",$X$10,$F25)>=K$10),$D25/12*(1+N($G25))^IF(AND(ISNUMBER($H25),K$10>=$H25),1+INT(DATEDIF($H25,K$10,"m")/12),0),0)) | L25: =IF(OR($D25="",$E25="",NOT(ISNUMBER($D25))),"",IF(AND($E25<=L$10,IF($F25="",$X$10,$F25)>=L$10),$D25/12*(1+N($G25))^IF(AND(ISNUMBER($H25),L$10>=$H25),1+INT(DATEDIF($H25,L$10,"m")/12),0),0)) | M25: =IF(OR($D25="",$E25="",NOT(ISNUMBER($D25))),"",IF(AND($E25<=M$10,IF($F25="",$X$10,$F25)>=M$10),$D25/12*(1+N($G25))^IF(AND(ISNUMBER($H25),M$10>=$H25),1+INT(DATEDIF($H25,M$10,"m")/12),0),0)) | N25: =IF(OR($D25="",$E25="",NOT(ISNUMBER($D25))),"",IF(AND($E25<=N$10,IF($F25="",$X$10,$F25)>=N$10),$D25/12*(1+N($G25))^IF(AND(ISNUMBER($H25),N$10>=$H25),1+INT(DATEDIF($H25,N$10,"m")/12),0),0)) | O25: =IF(OR($D25="",$E25="",NOT(ISNUMBER($D25))),"",IF(AND($E25<=O$10,IF($F25="",$X$10,$F25)>=O$10),$D25/12*(1+N($G25))^IF(AND(ISNUMBER($H25),O$10>=$H25),1+INT(DATEDIF($H25,O$10,"m")/12),0),0)) | P25: =IF(OR($D25="",$E25="",NOT(ISNUMBER($D25))),"",IF(AND($E25<=P$10,IF($F25="",$X$10,$F25)>=P$10),$D25/12*(1+N($G25))^IF(AND(ISNUMBER($H25),P$10>=$H25),1+INT(DATEDIF($H25,P$10,"m")/12),0),0)) | ... X25: =IF(OR($D25="",$E25="",NOT(ISNUMBER($D25))),"",IF(AND($E25<=X$10,IF($F25="",$X$10,$F25)>=X$10),$D25/12*(1+N($G25))^IF(AND(ISNUMBER($H25),X$10>=$H25),1+INT(DATEDIF($H25,X$10,"m")/12),0),0)) | Z25: =SUM(M25:X25) -> 0 | AB25: =IF($D25&$E25="","",IF(AND($D25<>"",NOT(ISNUMBER($D25))),"Salary must be a number",IF(AND($D25<>"",$E25=""),"Start month missing",IF(AND(ISNUMBER($E25),ISNUMBER($F25),$F25<$E25),"End is before Start",IF(AND($D25<>"",NOT(ISNUMBER($H25))),"Increase month missing","")))))
E26: 46266 | F26: 46722 | G26: 0.03 | H26: =$D$8 -> 46661 | I26: =IF(OR($D26="",$E26="",NOT(ISNUMBER($D26))),"",IF(AND($E26<=I$10,IF($F26="",$X$10,$F26)>=I$10),$D26/12*(1+N($G26))^IF(AND(ISNUMBER($H26),I$10>=$H26),1+INT(DATEDIF($H26,I$10,"m")/12),0),0)) | J26: =IF(OR($D26="",$E26="",NOT(ISNUMBER($D26))),"",IF(AND($E26<=J$10,IF($F26="",$X$10,$F26)>=J$10),$D26/12*(1+N($G26))^IF(AND(ISNUMBER($H26),J$10>=$H26),1+INT(DATEDIF($H26,J$10,"m")/12),0),0)) | K26: =IF(OR($D26="",$E26="",NOT(ISNUMBER($D26))),"",IF(AND($E26<=K$10,IF($F26="",$X$10,$F26)>=K$10),$D26/12*(1+N($G26))^IF(AND(ISNUMBER($H26),K$10>=$H26),1+INT(DATEDIF($H26,K$10,"m")/12),0),0)) | L26: =IF(OR($D26="",$E26="",NOT(ISNUMBER($D26))),"",IF(AND($E26<=L$10,IF($F26="",$X$10,$F26)>=L$10),$D26/12*(1+N($G26))^IF(AND(ISNUMBER($H26),L$10>=$H26),1+INT(DATEDIF($H26,L$10,"m")/12),0),0)) | M26: =IF(OR($D26="",$E26="",NOT(ISNUMBER($D26))),"",IF(AND($E26<=M$10,IF($F26="",$X$10,$F26)>=M$10),$D26/12*(1+N($G26))^IF(AND(ISNUMBER($H26),M$10>=$H26),1+INT(DATEDIF($H26,M$10,"m")/12),0),0)) | N26: =IF(OR($D26="",$E26="",NOT(ISNUMBER($D26))),"",IF(AND($E26<=N$10,IF($F26="",$X$10,$F26)>=N$10),$D26/12*(1+N($G26))^IF(AND(ISNUMBER($H26),N$10>=$H26),1+INT(DATEDIF($H26,N$10,"m")/12),0),0)) | O26: =IF(OR($D26="",$E26="",NOT(ISNUMBER($D26))),"",IF(AND($E26<=O$10,IF($F26="",$X$10,$F26)>=O$10),$D26/12*(1+N($G26))^IF(AND(ISNUMBER($H26),O$10>=$H26),1+INT(DATEDIF($H26,O$10,"m")/12),0),0)) | P26: =IF(OR($D26="",$E26="",NOT(ISNUMBER($D26))),"",IF(AND($E26<=P$10,IF($F26="",$X$10,$F26)>=P$10),$D26/12*(1+N($G26))^IF(AND(ISNUMBER($H26),P$10>=$H26),1+INT(DATEDIF($H26,P$10,"m")/12),0),0)) | ... X26: =IF(OR($D26="",$E26="",NOT(ISNUMBER($D26))),"",IF(AND($E26<=X$10,IF($F26="",$X$10,$F26)>=X$10),$D26/12*(1+N($G26))^IF(AND(ISNUMBER($H26),X$10>=$H26),1+INT(DATEDIF($H26,X$10,"m")/12),0),0)) | Z26: =SUM(M26:X26) -> 0 | AB26: =IF($D26&$E26="","",IF(AND($D26<>"",NOT(ISNUMBER($D26))),"Salary must be a number",IF(AND($D26<>"",$E26=""),"Start month missing",IF(AND(ISNUMBER($E26),ISNUMBER($F26),$F26<$E26),"End is before Start",IF(AND($D26<>"",NOT(ISNUMBER($H26))),"Increase month missing","")))))
E27: 46266 | F27: 46722 | G27: 0.03 | H27: =$D$8 -> 46661 | I27: =IF(OR($D27="",$E27="",NOT(ISNUMBER($D27))),"",IF(AND($E27<=I$10,IF($F27="",$X$10,$F27)>=I$10),$D27/12*(1+N($G27))^IF(AND(ISNUMBER($H27),I$10>=$H27),1+INT(DATEDIF($H27,I$10,"m")/12),0),0)) | J27: =IF(OR($D27="",$E27="",NOT(ISNUMBER($D27))),"",IF(AND($E27<=J$10,IF($F27="",$X$10,$F27)>=J$10),$D27/12*(1+N($G27))^IF(AND(ISNUMBER($H27),J$10>=$H27),1+INT(DATEDIF($H27,J$10,"m")/12),0),0)) | K27: =IF(OR($D27="",$E27="",NOT(ISNUMBER($D27))),"",IF(AND($E27<=K$10,IF($F27="",$X$10,$F27)>=K$10),$D27/12*(1+N($G27))^IF(AND(ISNUMBER($H27),K$10>=$H27),1+INT(DATEDIF($H27,K$10,"m")/12),0),0)) | L27: =IF(OR($D27="",$E27="",NOT(ISNUMBER($D27))),"",IF(AND($E27<=L$10,IF($F27="",$X$10,$F27)>=L$10),$D27/12*(1+N($G27))^IF(AND(ISNUMBER($H27),L$10>=$H27),1+INT(DATEDIF($H27,L$10,"m")/12),0),0)) | M27: =IF(OR($D27="",$E27="",NOT(ISNUMBER($D27))),"",IF(AND($E27<=M$10,IF($F27="",$X$10,$F27)>=M$10),$D27/12*(1+N($G27))^IF(AND(ISNUMBER($H27),M$10>=$H27),1+INT(DATEDIF($H27,M$10,"m")/12),0),0)) | N27: =IF(OR($D27="",$E27="",NOT(ISNUMBER($D27))),"",IF(AND($E27<=N$10,IF($F27="",$X$10,$F27)>=N$10),$D27/12*(1+N($G27))^IF(AND(ISNUMBER($H27),N$10>=$H27),1+INT(DATEDIF($H27,N$10,"m")/12),0),0)) | O27: =IF(OR($D27="",$E27="",NOT(ISNUMBER($D27))),"",IF(AND($E27<=O$10,IF($F27="",$X$10,$F27)>=O$10),$D27/12*(1+N($G27))^IF(AND(ISNUMBER($H27),O$10>=$H27),1+INT(DATEDIF($H27,O$10,"m")/12),0),0)) | P27: =IF(OR($D27="",$E27="",NOT(ISNUMBER($D27))),"",IF(AND($E27<=P$10,IF($F27="",$X$10,$F27)>=P$10),$D27/12*(1+N($G27))^IF(AND(ISNUMBER($H27),P$10>=$H27),1+INT(DATEDIF($H27,P$10,"m")/12),0),0)) | ... X27: =IF(OR($D27="",$E27="",NOT(ISNUMBER($D27))),"",IF(AND($E27<=X$10,IF($F27="",$X$10,$F27)>=X$10),$D27/12*(1+N($G27))^IF(AND(ISNUMBER($H27),X$10>=$H27),1+INT(DATEDIF($H27,X$10,"m")/12),0),0)) | Z27: =SUM(M27:X27) -> 0 | AB27: =IF($D27&$E27="","",IF(AND($D27<>"",NOT(ISNUMBER($D27))),"Salary must be a number",IF(AND($D27<>"",$E27=""),"Start month missing",IF(AND(ISNUMBER($E27),ISNUMBER($F27),$F27<$E27),"End is before Start",IF(AND($D27<>"",NOT(ISNUMBER($H27))),"Increase month missing","")))))
E28: 46266 | F28: 46722 | G28: 0.03 | H28: =$D$8 -> 46661 | I28: =IF(OR($D28="",$E28="",NOT(ISNUMBER($D28))),"",IF(AND($E28<=I$10,IF($F28="",$X$10,$F28)>=I$10),$D28/12*(1+N($G28))^IF(AND(ISNUMBER($H28),I$10>=$H28),1+INT(DATEDIF($H28,I$10,"m")/12),0),0)) | J28: =IF(OR($D28="",$E28="",NOT(ISNUMBER($D28))),"",IF(AND($E28<=J$10,IF($F28="",$X$10,$F28)>=J$10),$D28/12*(1+N($G28))^IF(AND(ISNUMBER($H28),J$10>=$H28),1+INT(DATEDIF($H28,J$10,"m")/12),0),0)) | K28: =IF(OR($D28="",$E28="",NOT(ISNUMBER($D28))),"",IF(AND($E28<=K$10,IF($F28="",$X$10,$F28)>=K$10),$D28/12*(1+N($G28))^IF(AND(ISNUMBER($H28),K$10>=$H28),1+INT(DATEDIF($H28,K$10,"m")/12),0),0)) | L28: =IF(OR($D28="",$E28="",NOT(ISNUMBER($D28))),"",IF(AND($E28<=L$10,IF($F28="",$X$10,$F28)>=L$10),$D28/12*(1+N($G28))^IF(AND(ISNUMBER($H28),L$10>=$H28),1+INT(DATEDIF($H28,L$10,"m")/12),0),0)) | M28: =IF(OR($D28="",$E28="",NOT(ISNUMBER($D28))),"",IF(AND($E28<=M$10,IF($F28="",$X$10,$F28)>=M$10),$D28/12*(1+N($G28))^IF(AND(ISNUMBER($H28),M$10>=$H28),1+INT(DATEDIF($H28,M$10,"m")/12),0),0)) | N28: =IF(OR($D28="",$E28="",NOT(ISNUMBER($D28))),"",IF(AND($E28<=N$10,IF($F28="",$X$10,$F28)>=N$10),$D28/12*(1+N($G28))^IF(AND(ISNUMBER($H28),N$10>=$H28),1+INT(DATEDIF($H28,N$10,"m")/12),0),0)) | O28: =IF(OR($D28="",$E28="",NOT(ISNUMBER($D28))),"",IF(AND($E28<=O$10,IF($F28="",$X$10,$F28)>=O$10),$D28/12*(1+N($G28))^IF(AND(ISNUMBER($H28),O$10>=$H28),1+INT(DATEDIF($H28,O$10,"m")/12),0),0)) | P28: =IF(OR($D28="",$E28="",NOT(ISNUMBER($D28))),"",IF(AND($E28<=P$10,IF($F28="",$X$10,$F28)>=P$10),$D28/12*(1+N($G28))^IF(AND(ISNUMBER($H28),P$10>=$H28),1+INT(DATEDIF($H28,P$10,"m")/12),0),0)) | ... X28: =IF(OR($D28="",$E28="",NOT(ISNUMBER($D28))),"",IF(AND($E28<=X$10,IF($F28="",$X$10,$F28)>=X$10),$D28/12*(1+N($G28))^IF(AND(ISNUMBER($H28),X$10>=$H28),1+INT(DATEDIF($H28,X$10,"m")/12),0),0)) | Z28: =SUM(M28:X28) -> 0 | AB28: =IF($D28&$E28="","",IF(AND($D28<>"",NOT(ISNUMBER($D28))),"Salary must be a number",IF(AND($D28<>"",$E28=""),"Start month missing",IF(AND(ISNUMBER($E28),ISNUMBER($F28),$F28<$E28),"End is before Start",IF(AND($D28<>"",NOT(ISNUMBER($H28))),"Increase month missing","")))))
E29: 46266 | F29: 46722 | G29: 0.03 | H29: =$D$8 -> 46661 | I29: =IF(OR($D29="",$E29="",NOT(ISNUMBER($D29))),"",IF(AND($E29<=I$10,IF($F29="",$X$10,$F29)>=I$10),$D29/12*(1+N($G29))^IF(AND(ISNUMBER($H29),I$10>=$H29),1+INT(DATEDIF($H29,I$10,"m")/12),0),0)) | J29: =IF(OR($D29="",$E29="",NOT(ISNUMBER($D29))),"",IF(AND($E29<=J$10,IF($F29="",$X$10,$F29)>=J$10),$D29/12*(1+N($G29))^IF(AND(ISNUMBER($H29),J$10>=$H29),1+INT(DATEDIF($H29,J$10,"m")/12),0),0)) | K29: =IF(OR($D29="",$E29="",NOT(ISNUMBER($D29))),"",IF(AND($E29<=K$10,IF($F29="",$X$10,$F29)>=K$10),$D29/12*(1+N($G29))^IF(AND(ISNUMBER($H29),K$10>=$H29),1+INT(DATEDIF($H29,K$10,"m")/12),0),0)) | L29: =IF(OR($D29="",$E29="",NOT(ISNUMBER($D29))),"",IF(AND($E29<=L$10,IF($F29="",$X$10,$F29)>=L$10),$D29/12*(1+N($G29))^IF(AND(ISNUMBER($H29),L$10>=$H29),1+INT(DATEDIF($H29,L$10,"m")/12),0),0)) | M29: =IF(OR($D29="",$E29="",NOT(ISNUMBER($D29))),"",IF(AND($E29<=M$10,IF($F29="",$X$10,$F29)>=M$10),$D29/12*(1+N($G29))^IF(AND(ISNUMBER($H29),M$10>=$H29),1+INT(DATEDIF($H29,M$10,"m")/12),0),0)) | N29: =IF(OR($D29="",$E29="",NOT(ISNUMBER($D29))),"",IF(AND($E29<=N$10,IF($F29="",$X$10,$F29)>=N$10),$D29/12*(1+N($G29))^IF(AND(ISNUMBER($H29),N$10>=$H29),1+INT(DATEDIF($H29,N$10,"m")/12),0),0)) | O29: =IF(OR($D29="",$E29="",NOT(ISNUMBER($D29))),"",IF(AND($E29<=O$10,IF($F29="",$X$10,$F29)>=O$10),$D29/12*(1+N($G29))^IF(AND(ISNUMBER($H29),O$10>=$H29),1+INT(DATEDIF($H29,O$10,"m")/12),0),0)) | P29: =IF(OR($D29="",$E29="",NOT(ISNUMBER($D29))),"",IF(AND($E29<=P$10,IF($F29="",$X$10,$F29)>=P$10),$D29/12*(1+N($G29))^IF(AND(ISNUMBER($H29),P$10>=$H29),1+INT(DATEDIF($H29,P$10,"m")/12),0),0)) | ... X29: =IF(OR($D29="",$E29="",NOT(ISNUMBER($D29))),"",IF(AND($E29<=X$10,IF($F29="",$X$10,$F29)>=X$10),$D29/12*(1+N($G29))^IF(AND(ISNUMBER($H29),X$10>=$H29),1+INT(DATEDIF($H29,X$10,"m")/12),0),0)) | Z29: =SUM(M29:X29) -> 0 | AB29: =IF($D29&$E29="","",IF(AND($D29<>"",NOT(ISNUMBER($D29))),"Salary must be a number",IF(AND($D29<>"",$E29=""),"Start month missing",IF(AND(ISNUMBER($E29),ISNUMBER($F29),$F29<$E29),"End is before Start",IF(AND($D29<>"",NOT(ISNUMBER($H29))),"Increase month missing","")))))
E30: 46266 | F30: 46722 | G30: 0.03 | H30: =$D$8 -> 46661 | I30: =IF(OR($D30="",$E30="",NOT(ISNUMBER($D30))),"",IF(AND($E30<=I$10,IF($F30="",$X$10,$F30)>=I$10),$D30/12*(1+N($G30))^IF(AND(ISNUMBER($H30),I$10>=$H30),1+INT(DATEDIF($H30,I$10,"m")/12),0),0)) | J30: =IF(OR($D30="",$E30="",NOT(ISNUMBER($D30))),"",IF(AND($E30<=J$10,IF($F30="",$X$10,$F30)>=J$10),$D30/12*(1+N($G30))^IF(AND(ISNUMBER($H30),J$10>=$H30),1+INT(DATEDIF($H30,J$10,"m")/12),0),0)) | K30: =IF(OR($D30="",$E30="",NOT(ISNUMBER($D30))),"",IF(AND($E30<=K$10,IF($F30="",$X$10,$F30)>=K$10),$D30/12*(1+N($G30))^IF(AND(ISNUMBER($H30),K$10>=$H30),1+INT(DATEDIF($H30,K$10,"m")/12),0),0)) | L30: =IF(OR($D30="",$E30="",NOT(ISNUMBER($D30))),"",IF(AND($E30<=L$10,IF($F30="",$X$10,$F30)>=L$10),$D30/12*(1+N($G30))^IF(AND(ISNUMBER($H30),L$10>=$H30),1+INT(DATEDIF($H30,L$10,"m")/12),0),0)) | M30: =IF(OR($D30="",$E30="",NOT(ISNUMBER($D30))),"",IF(AND($E30<=M$10,IF($F30="",$X$10,$F30)>=M$10),$D30/12*(1+N($G30))^IF(AND(ISNUMBER($H30),M$10>=$H30),1+INT(DATEDIF($H30,M$10,"m")/12),0),0)) | N30: =IF(OR($D30="",$E30="",NOT(ISNUMBER($D30))),"",IF(AND($E30<=N$10,IF($F30="",$X$10,$F30)>=N$10),$D30/12*(1+N($G30))^IF(AND(ISNUMBER($H30),N$10>=$H30),1+INT(DATEDIF($H30,N$10,"m")/12),0),0)) | O30: =IF(OR($D30="",$E30="",NOT(ISNUMBER($D30))),"",IF(AND($E30<=O$10,IF($F30="",$X$10,$F30)>=O$10),$D30/12*(1+N($G30))^IF(AND(ISNUMBER($H30),O$10>=$H30),1+INT(DATEDIF($H30,O$10,"m")/12),0),0)) | P30: =IF(OR($D30="",$E30="",NOT(ISNUMBER($D30))),"",IF(AND($E30<=P$10,IF($F30="",$X$10,$F30)>=P$10),$D30/12*(1+N($G30))^IF(AND(ISNUMBER($H30),P$10>=$H30),1+INT(DATEDIF($H30,P$10,"m")/12),0),0)) | ... X30: =IF(OR($D30="",$E30="",NOT(ISNUMBER($D30))),"",IF(AND($E30<=X$10,IF($F30="",$X$10,$F30)>=X$10),$D30/12*(1+N($G30))^IF(AND(ISNUMBER($H30),X$10>=$H30),1+INT(DATEDIF($H30,X$10,"m")/12),0),0)) | Z30: =SUM(M30:X30) -> 0 | AB30: =IF($D30&$E30="","",IF(AND($D30<>"",NOT(ISNUMBER($D30))),"Salary must be a number",IF(AND($D30<>"",$E30=""),"Start month missing",IF(AND(ISNUMBER($E30),ISNUMBER($F30),$F30<$E30),"End is before Start",IF(AND($D30<>"",NOT(ISNUMBER($H30))),"Increase month missing","")))))
E31: 46266 | F31: 46722 | G31: 0.03 | H31: =$D$8 -> 46661 | I31: =IF(OR($D31="",$E31="",NOT(ISNUMBER($D31))),"",IF(AND($E31<=I$10,IF($F31="",$X$10,$F31)>=I$10),$D31/12*(1+N($G31))^IF(AND(ISNUMBER($H31),I$10>=$H31),1+INT(DATEDIF($H31,I$10,"m")/12),0),0)) | J31: =IF(OR($D31="",$E31="",NOT(ISNUMBER($D31))),"",IF(AND($E31<=J$10,IF($F31="",$X$10,$F31)>=J$10),$D31/12*(1+N($G31))^IF(AND(ISNUMBER($H31),J$10>=$H31),1+INT(DATEDIF($H31,J$10,"m")/12),0),0)) | K31: =IF(OR($D31="",$E31="",NOT(ISNUMBER($D31))),"",IF(AND($E31<=K$10,IF($F31="",$X$10,$F31)>=K$10),$D31/12*(1+N($G31))^IF(AND(ISNUMBER($H31),K$10>=$H31),1+INT(DATEDIF($H31,K$10,"m")/12),0),0)) | L31: =IF(OR($D31="",$E31="",NOT(ISNUMBER($D31))),"",IF(AND($E31<=L$10,IF($F31="",$X$10,$F31)>=L$10),$D31/12*(1+N($G31))^IF(AND(ISNUMBER($H31),L$10>=$H31),1+INT(DATEDIF($H31,L$10,"m")/12),0),0)) | M31: =IF(OR($D31="",$E31="",NOT(ISNUMBER($D31))),"",IF(AND($E31<=M$10,IF($F31="",$X$10,$F31)>=M$10),$D31/12*(1+N($G31))^IF(AND(ISNUMBER($H31),M$10>=$H31),1+INT(DATEDIF($H31,M$10,"m")/12),0),0)) | N31: =IF(OR($D31="",$E31="",NOT(ISNUMBER($D31))),"",IF(AND($E31<=N$10,IF($F31="",$X$10,$F31)>=N$10),$D31/12*(1+N($G31))^IF(AND(ISNUMBER($H31),N$10>=$H31),1+INT(DATEDIF($H31,N$10,"m")/12),0),0)) | O31: =IF(OR($D31="",$E31="",NOT(ISNUMBER($D31))),"",IF(AND($E31<=O$10,IF($F31="",$X$10,$F31)>=O$10),$D31/12*(1+N($G31))^IF(AND(ISNUMBER($H31),O$10>=$H31),1+INT(DATEDIF($H31,O$10,"m")/12),0),0)) | P31: =IF(OR($D31="",$E31="",NOT(ISNUMBER($D31))),"",IF(AND($E31<=P$10,IF($F31="",$X$10,$F31)>=P$10),$D31/12*(1+N($G31))^IF(AND(ISNUMBER($H31),P$10>=$H31),1+INT(DATEDIF($H31,P$10,"m")/12),0),0)) | ... X31: =IF(OR($D31="",$E31="",NOT(ISNUMBER($D31))),"",IF(AND($E31<=X$10,IF($F31="",$X$10,$F31)>=X$10),$D31/12*(1+N($G31))^IF(AND(ISNUMBER($H31),X$10>=$H31),1+INT(DATEDIF($H31,X$10,"m")/12),0),0)) | Z31: =SUM(M31:X31) -> 0 | AB31: =IF($D31&$E31="","",IF(AND($D31<>"",NOT(ISNUMBER($D31))),"Salary must be a number",IF(AND($D31<>"",$E31=""),"Start month missing",IF(AND(ISNUMBER($E31),ISNUMBER($F31),$F31<$E31),"End is before Start",IF(AND($D31<>"",NOT(ISNUMBER($H31))),"Increase month missing","")))))
E32: 46266 | F32: 46722 | G32: 0.03 | H32: =$D$8 -> 46661 | I32: =IF(OR($D32="",$E32="",NOT(ISNUMBER($D32))),"",IF(AND($E32<=I$10,IF($F32="",$X$10,$F32)>=I$10),$D32/12*(1+N($G32))^IF(AND(ISNUMBER($H32),I$10>=$H32),1+INT(DATEDIF($H32,I$10,"m")/12),0),0)) | J32: =IF(OR($D32="",$E32="",NOT(ISNUMBER($D32))),"",IF(AND($E32<=J$10,IF($F32="",$X$10,$F32)>=J$10),$D32/12*(1+N($G32))^IF(AND(ISNUMBER($H32),J$10>=$H32),1+INT(DATEDIF($H32,J$10,"m")/12),0),0)) | K32: =IF(OR($D32="",$E32="",NOT(ISNUMBER($D32))),"",IF(AND($E32<=K$10,IF($F32="",$X$10,$F32)>=K$10),$D32/12*(1+N($G32))^IF(AND(ISNUMBER($H32),K$10>=$H32),1+INT(DATEDIF($H32,K$10,"m")/12),0),0)) | L32: =IF(OR($D32="",$E32="",NOT(ISNUMBER($D32))),"",IF(AND($E32<=L$10,IF($F32="",$X$10,$F32)>=L$10),$D32/12*(1+N($G32))^IF(AND(ISNUMBER($H32),L$10>=$H32),1+INT(DATEDIF($H32,L$10,"m")/12),0),0)) | M32: =IF(OR($D32="",$E32="",NOT(ISNUMBER($D32))),"",IF(AND($E32<=M$10,IF($F32="",$X$10,$F32)>=M$10),$D32/12*(1+N($G32))^IF(AND(ISNUMBER($H32),M$10>=$H32),1+INT(DATEDIF($H32,M$10,"m")/12),0),0)) | N32: =IF(OR($D32="",$E32="",NOT(ISNUMBER($D32))),"",IF(AND($E32<=N$10,IF($F32="",$X$10,$F32)>=N$10),$D32/12*(1+N($G32))^IF(AND(ISNUMBER($H32),N$10>=$H32),1+INT(DATEDIF($H32,N$10,"m")/12),0),0)) | O32: =IF(OR($D32="",$E32="",NOT(ISNUMBER($D32))),"",IF(AND($E32<=O$10,IF($F32="",$X$10,$F32)>=O$10),$D32/12*(1+N($G32))^IF(AND(ISNUMBER($H32),O$10>=$H32),1+INT(DATEDIF($H32,O$10,"m")/12),0),0)) | P32: =IF(OR($D32="",$E32="",NOT(ISNUMBER($D32))),"",IF(AND($E32<=P$10,IF($F32="",$X$10,$F32)>=P$10),$D32/12*(1+N($G32))^IF(AND(ISNUMBER($H32),P$10>=$H32),1+INT(DATEDIF($H32,P$10,"m")/12),0),0)) | ... X32: =IF(OR($D32="",$E32="",NOT(ISNUMBER($D32))),"",IF(AND($E32<=X$10,IF($F32="",$X$10,$F32)>=X$10),$D32/12*(1+N($G32))^IF(AND(ISNUMBER($H32),X$10>=$H32),1+INT(DATEDIF($H32,X$10,"m")/12),0),0)) | Z32: =SUM(M32:X32) -> 0 | AB32: =IF($D32&$E32="","",IF(AND($D32<>"",NOT(ISNUMBER($D32))),"Salary must be a number",IF(AND($D32<>"",$E32=""),"Start month missing",IF(AND(ISNUMBER($E32),ISNUMBER($F32),$F32<$E32),"End is before Start",IF(AND($D32<>"",NOT(ISNUMBER($H32))),"Increase month missing","")))))
E33: 46266 | F33: 46722 | G33: 0.03 | H33: =$D$8 -> 46661 | I33: =IF(OR($D33="",$E33="",NOT(ISNUMBER($D33))),"",IF(AND($E33<=I$10,IF($F33="",$X$10,$F33)>=I$10),$D33/12*(1+N($G33))^IF(AND(ISNUMBER($H33),I$10>=$H33),1+INT(DATEDIF($H33,I$10,"m")/12),0),0)) | J33: =IF(OR($D33="",$E33="",NOT(ISNUMBER($D33))),"",IF(AND($E33<=J$10,IF($F33="",$X$10,$F33)>=J$10),$D33/12*(1+N($G33))^IF(AND(ISNUMBER($H33),J$10>=$H33),1+INT(DATEDIF($H33,J$10,"m")/12),0),0)) | K33: =IF(OR($D33="",$E33="",NOT(ISNUMBER($D33))),"",IF(AND($E33<=K$10,IF($F33="",$X$10,$F33)>=K$10),$D33/12*(1+N($G33))^IF(AND(ISNUMBER($H33),K$10>=$H33),1+INT(DATEDIF($H33,K$10,"m")/12),0),0)) | L33: =IF(OR($D33="",$E33="",NOT(ISNUMBER($D33))),"",IF(AND($E33<=L$10,IF($F33="",$X$10,$F33)>=L$10),$D33/12*(1+N($G33))^IF(AND(ISNUMBER($H33),L$10>=$H33),1+INT(DATEDIF($H33,L$10,"m")/12),0),0)) | M33: =IF(OR($D33="",$E33="",NOT(ISNUMBER($D33))),"",IF(AND($E33<=M$10,IF($F33="",$X$10,$F33)>=M$10),$D33/12*(1+N($G33))^IF(AND(ISNUMBER($H33),M$10>=$H33),1+INT(DATEDIF($H33,M$10,"m")/12),0),0)) | N33: =IF(OR($D33="",$E33="",NOT(ISNUMBER($D33))),"",IF(AND($E33<=N$10,IF($F33="",$X$10,$F33)>=N$10),$D33/12*(1+N($G33))^IF(AND(ISNUMBER($H33),N$10>=$H33),1+INT(DATEDIF($H33,N$10,"m")/12),0),0)) | O33: =IF(OR($D33="",$E33="",NOT(ISNUMBER($D33))),"",IF(AND($E33<=O$10,IF($F33="",$X$10,$F33)>=O$10),$D33/12*(1+N($G33))^IF(AND(ISNUMBER($H33),O$10>=$H33),1+INT(DATEDIF($H33,O$10,"m")/12),0),0)) | P33: =IF(OR($D33="",$E33="",NOT(ISNUMBER($D33))),"",IF(AND($E33<=P$10,IF($F33="",$X$10,$F33)>=P$10),$D33/12*(1+N($G33))^IF(AND(ISNUMBER($H33),P$10>=$H33),1+INT(DATEDIF($H33,P$10,"m")/12),0),0)) | ... X33: =IF(OR($D33="",$E33="",NOT(ISNUMBER($D33))),"",IF(AND($E33<=X$10,IF($F33="",$X$10,$F33)>=X$10),$D33/12*(1+N($G33))^IF(AND(ISNUMBER($H33),X$10>=$H33),1+INT(DATEDIF($H33,X$10,"m")/12),0),0)) | Z33: =SUM(M33:X33) -> 0 | AB33: =IF($D33&$E33="","",IF(AND($D33<>"",NOT(ISNUMBER($D33))),"Salary must be a number",IF(AND($D33<>"",$E33=""),"Start month missing",IF(AND(ISNUMBER($E33),ISNUMBER($F33),$F33<$E33),"End is before Start",IF(AND($D33<>"",NOT(ISNUMBER($H33))),"Increase month missing","")))))
B34: Open Positions
F35: 46722 | G35: 0.03 | H35: =$D$8 -> 46661 | I35: =IF(OR($D35="",$E35="",NOT(ISNUMBER($D35))),"",IF(AND($E35<=I$10,IF($F35="",$X$10,$F35)>=I$10),$D35/12*(1+N($G35))^IF(AND(ISNUMBER($H35),I$10>=$H35),1+INT(DATEDIF($H35,I$10,"m")/12),0),0)) | J35: =IF(OR($D35="",$E35="",NOT(ISNUMBER($D35))),"",IF(AND($E35<=J$10,IF($F35="",$X$10,$F35)>=J$10),$D35/12*(1+N($G35))^IF(AND(ISNUMBER($H35),J$10>=$H35),1+INT(DATEDIF($H35,J$10,"m")/12),0),0)) | K35: =IF(OR($D35="",$E35="",NOT(ISNUMBER($D35))),"",IF(AND($E35<=K$10,IF($F35="",$X$10,$F35)>=K$10),$D35/12*(1+N($G35))^IF(AND(ISNUMBER($H35),K$10>=$H35),1+INT(DATEDIF($H35,K$10,"m")/12),0),0)) | L35: =IF(OR($D35="",$E35="",NOT(ISNUMBER($D35))),"",IF(AND($E35<=L$10,IF($F35="",$X$10,$F35)>=L$10),$D35/12*(1+N($G35))^IF(AND(ISNUMBER($H35),L$10>=$H35),1+INT(DATEDIF($H35,L$10,"m")/12),0),0)) | M35: =IF(OR($D35="",$E35="",NOT(ISNUMBER($D35))),"",IF(AND($E35<=M$10,IF($F35="",$X$10,$F35)>=M$10),$D35/12*(1+N($G35))^IF(AND(ISNUMBER($H35),M$10>=$H35),1+INT(DATEDIF($H35,M$10,"m")/12),0),0)) | N35: =IF(OR($D35="",$E35="",NOT(ISNUMBER($D35))),"",IF(AND($E35<=N$10,IF($F35="",$X$10,$F35)>=N$10),$D35/12*(1+N($G35))^IF(AND(ISNUMBER($H35),N$10>=$H35),1+INT(DATEDIF($H35,N$10,"m")/12),0),0)) | O35: =IF(OR($D35="",$E35="",NOT(ISNUMBER($D35))),"",IF(AND($E35<=O$10,IF($F35="",$X$10,$F35)>=O$10),$D35/12*(1+N($G35))^IF(AND(ISNUMBER($H35),O$10>=$H35),1+INT(DATEDIF($H35,O$10,"m")/12),0),0)) | P35: =IF(OR($D35="",$E35="",NOT(ISNUMBER($D35))),"",IF(AND($E35<=P$10,IF($F35="",$X$10,$F35)>=P$10),$D35/12*(1+N($G35))^IF(AND(ISNUMBER($H35),P$10>=$H35),1+INT(DATEDIF($H35,P$10,"m")/12),0),0)) | ... X35: =IF(OR($D35="",$E35="",NOT(ISNUMBER($D35))),"",IF(AND($E35<=X$10,IF($F35="",$X$10,$F35)>=X$10),$D35/12*(1+N($G35))^IF(AND(ISNUMBER($H35),X$10>=$H35),1+INT(DATEDIF($H35,X$10,"m")/12),0),0)) | Z35: =SUM(M35:X35) -> 0 | AB35: =IF($D35&$E35="","",IF(AND($D35<>"",NOT(ISNUMBER($D35))),"Salary must be a number",IF(AND($D35<>"",$E35=""),"Start month missing",IF(AND(ISNUMBER($E35),ISNUMBER($F35),$F35<$E35),"End is before Start",IF(AND($D35<>"",NOT(ISNUMBER($H35))),"Increase month missing","")))))
F36: 46722 | G36: 0.03 | H36: =$D$8 -> 46661 | I36: =IF(OR($D36="",$E36="",NOT(ISNUMBER($D36))),"",IF(AND($E36<=I$10,IF($F36="",$X$10,$F36)>=I$10),$D36/12*(1+N($G36))^IF(AND(ISNUMBER($H36),I$10>=$H36),1+INT(DATEDIF($H36,I$10,"m")/12),0),0)) | J36: =IF(OR($D36="",$E36="",NOT(ISNUMBER($D36))),"",IF(AND($E36<=J$10,IF($F36="",$X$10,$F36)>=J$10),$D36/12*(1+N($G36))^IF(AND(ISNUMBER($H36),J$10>=$H36),1+INT(DATEDIF($H36,J$10,"m")/12),0),0)) | K36: =IF(OR($D36="",$E36="",NOT(ISNUMBER($D36))),"",IF(AND($E36<=K$10,IF($F36="",$X$10,$F36)>=K$10),$D36/12*(1+N($G36))^IF(AND(ISNUMBER($H36),K$10>=$H36),1+INT(DATEDIF($H36,K$10,"m")/12),0),0)) | L36: =IF(OR($D36="",$E36="",NOT(ISNUMBER($D36))),"",IF(AND($E36<=L$10,IF($F36="",$X$10,$F36)>=L$10),$D36/12*(1+N($G36))^IF(AND(ISNUMBER($H36),L$10>=$H36),1+INT(DATEDIF($H36,L$10,"m")/12),0),0)) | M36: =IF(OR($D36="",$E36="",NOT(ISNUMBER($D36))),"",IF(AND($E36<=M$10,IF($F36="",$X$10,$F36)>=M$10),$D36/12*(1+N($G36))^IF(AND(ISNUMBER($H36),M$10>=$H36),1+INT(DATEDIF($H36,M$10,"m")/12),0),0)) | N36: =IF(OR($D36="",$E36="",NOT(ISNUMBER($D36))),"",IF(AND($E36<=N$10,IF($F36="",$X$10,$F36)>=N$10),$D36/12*(1+N($G36))^IF(AND(ISNUMBER($H36),N$10>=$H36),1+INT(DATEDIF($H36,N$10,"m")/12),0),0)) | O36: =IF(OR($D36="",$E36="",NOT(ISNUMBER($D36))),"",IF(AND($E36<=O$10,IF($F36="",$X$10,$F36)>=O$10),$D36/12*(1+N($G36))^IF(AND(ISNUMBER($H36),O$10>=$H36),1+INT(DATEDIF($H36,O$10,"m")/12),0),0)) | P36: =IF(OR($D36="",$E36="",NOT(ISNUMBER($D36))),"",IF(AND($E36<=P$10,IF($F36="",$X$10,$F36)>=P$10),$D36/12*(1+N($G36))^IF(AND(ISNUMBER($H36),P$10>=$H36),1+INT(DATEDIF($H36,P$10,"m")/12),0),0)) | ... X36: =IF(OR($D36="",$E36="",NOT(ISNUMBER($D36))),"",IF(AND($E36<=X$10,IF($F36="",$X$10,$F36)>=X$10),$D36/12*(1+N($G36))^IF(AND(ISNUMBER($H36),X$10>=$H36),1+INT(DATEDIF($H36,X$10,"m")/12),0),0)) | Z36: =SUM(M36:X36) -> 0 | AB36: =IF($D36&$E36="","",IF(AND($D36<>"",NOT(ISNUMBER($D36))),"Salary must be a number",IF(AND($D36<>"",$E36=""),"Start month missing",IF(AND(ISNUMBER($E36),ISNUMBER($F36),$F36<$E36),"End is before Start",IF(AND($D36<>"",NOT(ISNUMBER($H36))),"Increase month missing","")))))
F37: 46722 | G37: 0.03 | H37: =$D$8 -> 46661 | I37: =IF(OR($D37="",$E37="",NOT(ISNUMBER($D37))),"",IF(AND($E37<=I$10,IF($F37="",$X$10,$F37)>=I$10),$D37/12*(1+N($G37))^IF(AND(ISNUMBER($H37),I$10>=$H37),1+INT(DATEDIF($H37,I$10,"m")/12),0),0)) | J37: =IF(OR($D37="",$E37="",NOT(ISNUMBER($D37))),"",IF(AND($E37<=J$10,IF($F37="",$X$10,$F37)>=J$10),$D37/12*(1+N($G37))^IF(AND(ISNUMBER($H37),J$10>=$H37),1+INT(DATEDIF($H37,J$10,"m")/12),0),0)) | K37: =IF(OR($D37="",$E37="",NOT(ISNUMBER($D37))),"",IF(AND($E37<=K$10,IF($F37="",$X$10,$F37)>=K$10),$D37/12*(1+N($G37))^IF(AND(ISNUMBER($H37),K$10>=$H37),1+INT(DATEDIF($H37,K$10,"m")/12),0),0)) | L37: =IF(OR($D37="",$E37="",NOT(ISNUMBER($D37))),"",IF(AND($E37<=L$10,IF($F37="",$X$10,$F37)>=L$10),$D37/12*(1+N($G37))^IF(AND(ISNUMBER($H37),L$10>=$H37),1+INT(DATEDIF($H37,L$10,"m")/12),0),0)) | M37: =IF(OR($D37="",$E37="",NOT(ISNUMBER($D37))),"",IF(AND($E37<=M$10,IF($F37="",$X$10,$F37)>=M$10),$D37/12*(1+N($G37))^IF(AND(ISNUMBER($H37),M$10>=$H37),1+INT(DATEDIF($H37,M$10,"m")/12),0),0)) | N37: =IF(OR($D37="",$E37="",NOT(ISNUMBER($D37))),"",IF(AND($E37<=N$10,IF($F37="",$X$10,$F37)>=N$10),$D37/12*(1+N($G37))^IF(AND(ISNUMBER($H37),N$10>=$H37),1+INT(DATEDIF($H37,N$10,"m")/12),0),0)) | O37: =IF(OR($D37="",$E37="",NOT(ISNUMBER($D37))),"",IF(AND($E37<=O$10,IF($F37="",$X$10,$F37)>=O$10),$D37/12*(1+N($G37))^IF(AND(ISNUMBER($H37),O$10>=$H37),1+INT(DATEDIF($H37,O$10,"m")/12),0),0)) | P37: =IF(OR($D37="",$E37="",NOT(ISNUMBER($D37))),"",IF(AND($E37<=P$10,IF($F37="",$X$10,$F37)>=P$10),$D37/12*(1+N($G37))^IF(AND(ISNUMBER($H37),P$10>=$H37),1+INT(DATEDIF($H37,P$10,"m")/12),0),0)) | ... X37: =IF(OR($D37="",$E37="",NOT(ISNUMBER($D37))),"",IF(AND($E37<=X$10,IF($F37="",$X$10,$F37)>=X$10),$D37/12*(1+N($G37))^IF(AND(ISNUMBER($H37),X$10>=$H37),1+INT(DATEDIF($H37,X$10,"m")/12),0),0)) | Z37: =SUM(M37:X37) -> 0 | AB37: =IF($D37&$E37="","",IF(AND($D37<>"",NOT(ISNUMBER($D37))),"Salary must be a number",IF(AND($D37<>"",$E37=""),"Start month missing",IF(AND(ISNUMBER($E37),ISNUMBER($F37),$F37<$E37),"End is before Start",IF(AND($D37<>"",NOT(ISNUMBER($H37))),"Increase month missing","")))))
F38: 46722 | G38: 0.03 | H38: =$D$8 -> 46661 | I38: =IF(OR($D38="",$E38="",NOT(ISNUMBER($D38))),"",IF(AND($E38<=I$10,IF($F38="",$X$10,$F38)>=I$10),$D38/12*(1+N($G38))^IF(AND(ISNUMBER($H38),I$10>=$H38),1+INT(DATEDIF($H38,I$10,"m")/12),0),0)) | J38: =IF(OR($D38="",$E38="",NOT(ISNUMBER($D38))),"",IF(AND($E38<=J$10,IF($F38="",$X$10,$F38)>=J$10),$D38/12*(1+N($G38))^IF(AND(ISNUMBER($H38),J$10>=$H38),1+INT(DATEDIF($H38,J$10,"m")/12),0),0)) | K38: =IF(OR($D38="",$E38="",NOT(ISNUMBER($D38))),"",IF(AND($E38<=K$10,IF($F38="",$X$10,$F38)>=K$10),$D38/12*(1+N($G38))^IF(AND(ISNUMBER($H38),K$10>=$H38),1+INT(DATEDIF($H38,K$10,"m")/12),0),0)) | L38: =IF(OR($D38="",$E38="",NOT(ISNUMBER($D38))),"",IF(AND($E38<=L$10,IF($F38="",$X$10,$F38)>=L$10),$D38/12*(1+N($G38))^IF(AND(ISNUMBER($H38),L$10>=$H38),1+INT(DATEDIF($H38,L$10,"m")/12),0),0)) | M38: =IF(OR($D38="",$E38="",NOT(ISNUMBER($D38))),"",IF(AND($E38<=M$10,IF($F38="",$X$10,$F38)>=M$10),$D38/12*(1+N($G38))^IF(AND(ISNUMBER($H38),M$10>=$H38),1+INT(DATEDIF($H38,M$10,"m")/12),0),0)) | N38: =IF(OR($D38="",$E38="",NOT(ISNUMBER($D38))),"",IF(AND($E38<=N$10,IF($F38="",$X$10,$F38)>=N$10),$D38/12*(1+N($G38))^IF(AND(ISNUMBER($H38),N$10>=$H38),1+INT(DATEDIF($H38,N$10,"m")/12),0),0)) | O38: =IF(OR($D38="",$E38="",NOT(ISNUMBER($D38))),"",IF(AND($E38<=O$10,IF($F38="",$X$10,$F38)>=O$10),$D38/12*(1+N($G38))^IF(AND(ISNUMBER($H38),O$10>=$H38),1+INT(DATEDIF($H38,O$10,"m")/12),0),0)) | P38: =IF(OR($D38="",$E38="",NOT(ISNUMBER($D38))),"",IF(AND($E38<=P$10,IF($F38="",$X$10,$F38)>=P$10),$D38/12*(1+N($G38))^IF(AND(ISNUMBER($H38),P$10>=$H38),1+INT(DATEDIF($H38,P$10,"m")/12),0),0)) | ... X38: =IF(OR($D38="",$E38="",NOT(ISNUMBER($D38))),"",IF(AND($E38<=X$10,IF($F38="",$X$10,$F38)>=X$10),$D38/12*(1+N($G38))^IF(AND(ISNUMBER($H38),X$10>=$H38),1+INT(DATEDIF($H38,X$10,"m")/12),0),0)) | Z38: =SUM(M38:X38) -> 0 | AB38: =IF($D38&$E38="","",IF(AND($D38<>"",NOT(ISNUMBER($D38))),"Salary must be a number",IF(AND($D38<>"",$E38=""),"Start month missing",IF(AND(ISNUMBER($E38),ISNUMBER($F38),$F38<$E38),"End is before Start",IF(AND($D38<>"",NOT(ISNUMBER($H38))),"Increase month missing","")))))
F39: 46722 | G39: 0.03 | H39: =$D$8 -> 46661 | I39: =IF(OR($D39="",$E39="",NOT(ISNUMBER($D39))),"",IF(AND($E39<=I$10,IF($F39="",$X$10,$F39)>=I$10),$D39/12*(1+N($G39))^IF(AND(ISNUMBER($H39),I$10>=$H39),1+INT(DATEDIF($H39,I$10,"m")/12),0),0)) | J39: =IF(OR($D39="",$E39="",NOT(ISNUMBER($D39))),"",IF(AND($E39<=J$10,IF($F39="",$X$10,$F39)>=J$10),$D39/12*(1+N($G39))^IF(AND(ISNUMBER($H39),J$10>=$H39),1+INT(DATEDIF($H39,J$10,"m")/12),0),0)) | K39: =IF(OR($D39="",$E39="",NOT(ISNUMBER($D39))),"",IF(AND($E39<=K$10,IF($F39="",$X$10,$F39)>=K$10),$D39/12*(1+N($G39))^IF(AND(ISNUMBER($H39),K$10>=$H39),1+INT(DATEDIF($H39,K$10,"m")/12),0),0)) | L39: =IF(OR($D39="",$E39="",NOT(ISNUMBER($D39))),"",IF(AND($E39<=L$10,IF($F39="",$X$10,$F39)>=L$10),$D39/12*(1+N($G39))^IF(AND(ISNUMBER($H39),L$10>=$H39),1+INT(DATEDIF($H39,L$10,"m")/12),0),0)) | M39: =IF(OR($D39="",$E39="",NOT(ISNUMBER($D39))),"",IF(AND($E39<=M$10,IF($F39="",$X$10,$F39)>=M$10),$D39/12*(1+N($G39))^IF(AND(ISNUMBER($H39),M$10>=$H39),1+INT(DATEDIF($H39,M$10,"m")/12),0),0)) | N39: =IF(OR($D39="",$E39="",NOT(ISNUMBER($D39))),"",IF(AND($E39<=N$10,IF($F39="",$X$10,$F39)>=N$10),$D39/12*(1+N($G39))^IF(AND(ISNUMBER($H39),N$10>=$H39),1+INT(DATEDIF($H39,N$10,"m")/12),0),0)) | O39: =IF(OR($D39="",$E39="",NOT(ISNUMBER($D39))),"",IF(AND($E39<=O$10,IF($F39="",$X$10,$F39)>=O$10),$D39/12*(1+N($G39))^IF(AND(ISNUMBER($H39),O$10>=$H39),1+INT(DATEDIF($H39,O$10,"m")/12),0),0)) | P39: =IF(OR($D39="",$E39="",NOT(ISNUMBER($D39))),"",IF(AND($E39<=P$10,IF($F39="",$X$10,$F39)>=P$10),$D39/12*(1+N($G39))^IF(AND(ISNUMBER($H39),P$10>=$H39),1+INT(DATEDIF($H39,P$10,"m")/12),0),0)) | ... X39: =IF(OR($D39="",$E39="",NOT(ISNUMBER($D39))),"",IF(AND($E39<=X$10,IF($F39="",$X$10,$F39)>=X$10),$D39/12*(1+N($G39))^IF(AND(ISNUMBER($H39),X$10>=$H39),1+INT(DATEDIF($H39,X$10,"m")/12),0),0)) | Z39: =SUM(M39:X39) -> 0 | AB39: =IF($D39&$E39="","",IF(AND($D39<>"",NOT(ISNUMBER($D39))),"Salary must be a number",IF(AND($D39<>"",$E39=""),"Start month missing",IF(AND(ISNUMBER($E39),ISNUMBER($F39),$F39<$E39),"End is before Start",IF(AND($D39<>"",NOT(ISNUMBER($H39))),"Increase month missing","")))))
B40: New Hires
F41: 46722 | G41: 0.03 | H41: =$D$8 -> 46661 | I41: =IF(OR($D41="",$E41="",NOT(ISNUMBER($D41))),"",IF(AND($E41<=I$10,IF($F41="",$X$10,$F41)>=I$10),$D41/12*(1+N($G41))^IF(AND(ISNUMBER($H41),I$10>=$H41),1+INT(DATEDIF($H41,I$10,"m")/12),0),0)) | J41: =IF(OR($D41="",$E41="",NOT(ISNUMBER($D41))),"",IF(AND($E41<=J$10,IF($F41="",$X$10,$F41)>=J$10),$D41/12*(1+N($G41))^IF(AND(ISNUMBER($H41),J$10>=$H41),1+INT(DATEDIF($H41,J$10,"m")/12),0),0)) | K41: =IF(OR($D41="",$E41="",NOT(ISNUMBER($D41))),"",IF(AND($E41<=K$10,IF($F41="",$X$10,$F41)>=K$10),$D41/12*(1+N($G41))^IF(AND(ISNUMBER($H41),K$10>=$H41),1+INT(DATEDIF($H41,K$10,"m")/12),0),0)) | L41: =IF(OR($D41="",$E41="",NOT(ISNUMBER($D41))),"",IF(AND($E41<=L$10,IF($F41="",$X$10,$F41)>=L$10),$D41/12*(1+N($G41))^IF(AND(ISNUMBER($H41),L$10>=$H41),1+INT(DATEDIF($H41,L$10,"m")/12),0),0)) | M41: =IF(OR($D41="",$E41="",NOT(ISNUMBER($D41))),"",IF(AND($E41<=M$10,IF($F41="",$X$10,$F41)>=M$10),$D41/12*(1+N($G41))^IF(AND(ISNUMBER($H41),M$10>=$H41),1+INT(DATEDIF($H41,M$10,"m")/12),0),0)) | N41: =IF(OR($D41="",$E41="",NOT(ISNUMBER($D41))),"",IF(AND($E41<=N$10,IF($F41="",$X$10,$F41)>=N$10),$D41/12*(1+N($G41))^IF(AND(ISNUMBER($H41),N$10>=$H41),1+INT(DATEDIF($H41,N$10,"m")/12),0),0)) | O41: =IF(OR($D41="",$E41="",NOT(ISNUMBER($D41))),"",IF(AND($E41<=O$10,IF($F41="",$X$10,$F41)>=O$10),$D41/12*(1+N($G41))^IF(AND(ISNUMBER($H41),O$10>=$H41),1+INT(DATEDIF($H41,O$10,"m")/12),0),0)) | P41: =IF(OR($D41="",$E41="",NOT(ISNUMBER($D41))),"",IF(AND($E41<=P$10,IF($F41="",$X$10,$F41)>=P$10),$D41/12*(1+N($G41))^IF(AND(ISNUMBER($H41),P$10>=$H41),1+INT(DATEDIF($H41,P$10,"m")/12),0),0)) | ... X41: =IF(OR($D41="",$E41="",NOT(ISNUMBER($D41))),"",IF(AND($E41<=X$10,IF($F41="",$X$10,$F41)>=X$10),$D41/12*(1+N($G41))^IF(AND(ISNUMBER($H41),X$10>=$H41),1+INT(DATEDIF($H41,X$10,"m")/12),0),0)) | Z41: =SUM(M41:X41) -> 0 | AB41: =IF($D41&$E41="","",IF(AND($D41<>"",NOT(ISNUMBER($D41))),"Salary must be a number",IF(AND($D41<>"",$E41=""),"Start month missing",IF(AND(ISNUMBER($E41),ISNUMBER($F41),$F41<$E41),"End is before Start",IF(AND($D41<>"",NOT(ISNUMBER($H41))),"Increase month missing","")))))
F42: 46722 | G42: 0.03 | H42: =$D$8 -> 46661 | I42: =IF(OR($D42="",$E42="",NOT(ISNUMBER($D42))),"",IF(AND($E42<=I$10,IF($F42="",$X$10,$F42)>=I$10),$D42/12*(1+N($G42))^IF(AND(ISNUMBER($H42),I$10>=$H42),1+INT(DATEDIF($H42,I$10,"m")/12),0),0)) | J42: =IF(OR($D42="",$E42="",NOT(ISNUMBER($D42))),"",IF(AND($E42<=J$10,IF($F42="",$X$10,$F42)>=J$10),$D42/12*(1+N($G42))^IF(AND(ISNUMBER($H42),J$10>=$H42),1+INT(DATEDIF($H42,J$10,"m")/12),0),0)) | K42: =IF(OR($D42="",$E42="",NOT(ISNUMBER($D42))),"",IF(AND($E42<=K$10,IF($F42="",$X$10,$F42)>=K$10),$D42/12*(1+N($G42))^IF(AND(ISNUMBER($H42),K$10>=$H42),1+INT(DATEDIF($H42,K$10,"m")/12),0),0)) | L42: =IF(OR($D42="",$E42="",NOT(ISNUMBER($D42))),"",IF(AND($E42<=L$10,IF($F42="",$X$10,$F42)>=L$10),$D42/12*(1+N($G42))^IF(AND(ISNUMBER($H42),L$10>=$H42),1+INT(DATEDIF($H42,L$10,"m")/12),0),0)) | M42: =IF(OR($D42="",$E42="",NOT(ISNUMBER($D42))),"",IF(AND($E42<=M$10,IF($F42="",$X$10,$F42)>=M$10),$D42/12*(1+N($G42))^IF(AND(ISNUMBER($H42),M$10>=$H42),1+INT(DATEDIF($H42,M$10,"m")/12),0),0)) | N42: =IF(OR($D42="",$E42="",NOT(ISNUMBER($D42))),"",IF(AND($E42<=N$10,IF($F42="",$X$10,$F42)>=N$10),$D42/12*(1+N($G42))^IF(AND(ISNUMBER($H42),N$10>=$H42),1+INT(DATEDIF($H42,N$10,"m")/12),0),0)) | O42: =IF(OR($D42="",$E42="",NOT(ISNUMBER($D42))),"",IF(AND($E42<=O$10,IF($F42="",$X$10,$F42)>=O$10),$D42/12*(1+N($G42))^IF(AND(ISNUMBER($H42),O$10>=$H42),1+INT(DATEDIF($H42,O$10,"m")/12),0),0)) | P42: =IF(OR($D42="",$E42="",NOT(ISNUMBER($D42))),"",IF(AND($E42<=P$10,IF($F42="",$X$10,$F42)>=P$10),$D42/12*(1+N($G42))^IF(AND(ISNUMBER($H42),P$10>=$H42),1+INT(DATEDIF($H42,P$10,"m")/12),0),0)) | ... X42: =IF(OR($D42="",$E42="",NOT(ISNUMBER($D42))),"",IF(AND($E42<=X$10,IF($F42="",$X$10,$F42)>=X$10),$D42/12*(1+N($G42))^IF(AND(ISNUMBER($H42),X$10>=$H42),1+INT(DATEDIF($H42,X$10,"m")/12),0),0)) | Z42: =SUM(M42:X42) -> 0 | AB42: =IF($D42&$E42="","",IF(AND($D42<>"",NOT(ISNUMBER($D42))),"Salary must be a number",IF(AND($D42<>"",$E42=""),"Start month missing",IF(AND(ISNUMBER($E42),ISNUMBER($F42),$F42<$E42),"End is before Start",IF(AND($D42<>"",NOT(ISNUMBER($H42))),"Increase month missing","")))))
F43: 46722 | G43: 0.03 | H43: =$D$8 -> 46661 | I43: =IF(OR($D43="",$E43="",NOT(ISNUMBER($D43))),"",IF(AND($E43<=I$10,IF($F43="",$X$10,$F43)>=I$10),$D43/12*(1+N($G43))^IF(AND(ISNUMBER($H43),I$10>=$H43),1+INT(DATEDIF($H43,I$10,"m")/12),0),0)) | J43: =IF(OR($D43="",$E43="",NOT(ISNUMBER($D43))),"",IF(AND($E43<=J$10,IF($F43="",$X$10,$F43)>=J$10),$D43/12*(1+N($G43))^IF(AND(ISNUMBER($H43),J$10>=$H43),1+INT(DATEDIF($H43,J$10,"m")/12),0),0)) | K43: =IF(OR($D43="",$E43="",NOT(ISNUMBER($D43))),"",IF(AND($E43<=K$10,IF($F43="",$X$10,$F43)>=K$10),$D43/12*(1+N($G43))^IF(AND(ISNUMBER($H43),K$10>=$H43),1+INT(DATEDIF($H43,K$10,"m")/12),0),0)) | L43: =IF(OR($D43="",$E43="",NOT(ISNUMBER($D43))),"",IF(AND($E43<=L$10,IF($F43="",$X$10,$F43)>=L$10),$D43/12*(1+N($G43))^IF(AND(ISNUMBER($H43),L$10>=$H43),1+INT(DATEDIF($H43,L$10,"m")/12),0),0)) | M43: =IF(OR($D43="",$E43="",NOT(ISNUMBER($D43))),"",IF(AND($E43<=M$10,IF($F43="",$X$10,$F43)>=M$10),$D43/12*(1+N($G43))^IF(AND(ISNUMBER($H43),M$10>=$H43),1+INT(DATEDIF($H43,M$10,"m")/12),0),0)) | N43: =IF(OR($D43="",$E43="",NOT(ISNUMBER($D43))),"",IF(AND($E43<=N$10,IF($F43="",$X$10,$F43)>=N$10),$D43/12*(1+N($G43))^IF(AND(ISNUMBER($H43),N$10>=$H43),1+INT(DATEDIF($H43,N$10,"m")/12),0),0)) | O43: =IF(OR($D43="",$E43="",NOT(ISNUMBER($D43))),"",IF(AND($E43<=O$10,IF($F43="",$X$10,$F43)>=O$10),$D43/12*(1+N($G43))^IF(AND(ISNUMBER($H43),O$10>=$H43),1+INT(DATEDIF($H43,O$10,"m")/12),0),0)) | P43: =IF(OR($D43="",$E43="",NOT(ISNUMBER($D43))),"",IF(AND($E43<=P$10,IF($F43="",$X$10,$F43)>=P$10),$D43/12*(1+N($G43))^IF(AND(ISNUMBER($H43),P$10>=$H43),1+INT(DATEDIF($H43,P$10,"m")/12),0),0)) | ... X43: =IF(OR($D43="",$E43="",NOT(ISNUMBER($D43))),"",IF(AND($E43<=X$10,IF($F43="",$X$10,$F43)>=X$10),$D43/12*(1+N($G43))^IF(AND(ISNUMBER($H43),X$10>=$H43),1+INT(DATEDIF($H43,X$10,"m")/12),0),0)) | Z43: =SUM(M43:X43) -> 0 | AB43: =IF($D43&$E43="","",IF(AND($D43<>"",NOT(ISNUMBER($D43))),"Salary must be a number",IF(AND($D43<>"",$E43=""),"Start month missing",IF(AND(ISNUMBER($E43),ISNUMBER($F43),$F43<$E43),"End is before Start",IF(AND($D43<>"",NOT(ISNUMBER($H43))),"Increase month missing","")))))
F44: 46722 | G44: 0.03 | H44: =$D$8 -> 46661 | I44: =IF(OR($D44="",$E44="",NOT(ISNUMBER($D44))),"",IF(AND($E44<=I$10,IF($F44="",$X$10,$F44)>=I$10),$D44/12*(1+N($G44))^IF(AND(ISNUMBER($H44),I$10>=$H44),1+INT(DATEDIF($H44,I$10,"m")/12),0),0)) | J44: =IF(OR($D44="",$E44="",NOT(ISNUMBER($D44))),"",IF(AND($E44<=J$10,IF($F44="",$X$10,$F44)>=J$10),$D44/12*(1+N($G44))^IF(AND(ISNUMBER($H44),J$10>=$H44),1+INT(DATEDIF($H44,J$10,"m")/12),0),0)) | K44: =IF(OR($D44="",$E44="",NOT(ISNUMBER($D44))),"",IF(AND($E44<=K$10,IF($F44="",$X$10,$F44)>=K$10),$D44/12*(1+N($G44))^IF(AND(ISNUMBER($H44),K$10>=$H44),1+INT(DATEDIF($H44,K$10,"m")/12),0),0)) | L44: =IF(OR($D44="",$E44="",NOT(ISNUMBER($D44))),"",IF(AND($E44<=L$10,IF($F44="",$X$10,$F44)>=L$10),$D44/12*(1+N($G44))^IF(AND(ISNUMBER($H44),L$10>=$H44),1+INT(DATEDIF($H44,L$10,"m")/12),0),0)) | M44: =IF(OR($D44="",$E44="",NOT(ISNUMBER($D44))),"",IF(AND($E44<=M$10,IF($F44="",$X$10,$F44)>=M$10),$D44/12*(1+N($G44))^IF(AND(ISNUMBER($H44),M$10>=$H44),1+INT(DATEDIF($H44,M$10,"m")/12),0),0)) | N44: =IF(OR($D44="",$E44="",NOT(ISNUMBER($D44))),"",IF(AND($E44<=N$10,IF($F44="",$X$10,$F44)>=N$10),$D44/12*(1+N($G44))^IF(AND(ISNUMBER($H44),N$10>=$H44),1+INT(DATEDIF($H44,N$10,"m")/12),0),0)) | O44: =IF(OR($D44="",$E44="",NOT(ISNUMBER($D44))),"",IF(AND($E44<=O$10,IF($F44="",$X$10,$F44)>=O$10),$D44/12*(1+N($G44))^IF(AND(ISNUMBER($H44),O$10>=$H44),1+INT(DATEDIF($H44,O$10,"m")/12),0),0)) | P44: =IF(OR($D44="",$E44="",NOT(ISNUMBER($D44))),"",IF(AND($E44<=P$10,IF($F44="",$X$10,$F44)>=P$10),$D44/12*(1+N($G44))^IF(AND(ISNUMBER($H44),P$10>=$H44),1+INT(DATEDIF($H44,P$10,"m")/12),0),0)) | ... X44: =IF(OR($D44="",$E44="",NOT(ISNUMBER($D44))),"",IF(AND($E44<=X$10,IF($F44="",$X$10,$F44)>=X$10),$D44/12*(1+N($G44))^IF(AND(ISNUMBER($H44),X$10>=$H44),1+INT(DATEDIF($H44,X$10,"m")/12),0),0)) | Z44: =SUM(M44:X44) -> 0 | AB44: =IF($D44&$E44="","",IF(AND($D44<>"",NOT(ISNUMBER($D44))),"Salary must be a number",IF(AND($D44<>"",$E44=""),"Start month missing",IF(AND(ISNUMBER($E44),ISNUMBER($F44),$F44<$E44),"End is before Start",IF(AND($D44<>"",NOT(ISNUMBER($H44))),"Increase month missing","")))))
F45: 46722 | G45: 0.03 | H45: =$D$8 -> 46661 | I45: =IF(OR($D45="",$E45="",NOT(ISNUMBER($D45))),"",IF(AND($E45<=I$10,IF($F45="",$X$10,$F45)>=I$10),$D45/12*(1+N($G45))^IF(AND(ISNUMBER($H45),I$10>=$H45),1+INT(DATEDIF($H45,I$10,"m")/12),0),0)) | J45: =IF(OR($D45="",$E45="",NOT(ISNUMBER($D45))),"",IF(AND($E45<=J$10,IF($F45="",$X$10,$F45)>=J$10),$D45/12*(1+N($G45))^IF(AND(ISNUMBER($H45),J$10>=$H45),1+INT(DATEDIF($H45,J$10,"m")/12),0),0)) | K45: =IF(OR($D45="",$E45="",NOT(ISNUMBER($D45))),"",IF(AND($E45<=K$10,IF($F45="",$X$10,$F45)>=K$10),$D45/12*(1+N($G45))^IF(AND(ISNUMBER($H45),K$10>=$H45),1+INT(DATEDIF($H45,K$10,"m")/12),0),0)) | L45: =IF(OR($D45="",$E45="",NOT(ISNUMBER($D45))),"",IF(AND($E45<=L$10,IF($F45="",$X$10,$F45)>=L$10),$D45/12*(1+N($G45))^IF(AND(ISNUMBER($H45),L$10>=$H45),1+INT(DATEDIF($H45,L$10,"m")/12),0),0)) | M45: =IF(OR($D45="",$E45="",NOT(ISNUMBER($D45))),"",IF(AND($E45<=M$10,IF($F45="",$X$10,$F45)>=M$10),$D45/12*(1+N($G45))^IF(AND(ISNUMBER($H45),M$10>=$H45),1+INT(DATEDIF($H45,M$10,"m")/12),0),0)) | N45: =IF(OR($D45="",$E45="",NOT(ISNUMBER($D45))),"",IF(AND($E45<=N$10,IF($F45="",$X$10,$F45)>=N$10),$D45/12*(1+N($G45))^IF(AND(ISNUMBER($H45),N$10>=$H45),1+INT(DATEDIF($H45,N$10,"m")/12),0),0)) | O45: =IF(OR($D45="",$E45="",NOT(ISNUMBER($D45))),"",IF(AND($E45<=O$10,IF($F45="",$X$10,$F45)>=O$10),$D45/12*(1+N($G45))^IF(AND(ISNUMBER($H45),O$10>=$H45),1+INT(DATEDIF($H45,O$10,"m")/12),0),0)) | P45: =IF(OR($D45="",$E45="",NOT(ISNUMBER($D45))),"",IF(AND($E45<=P$10,IF($F45="",$X$10,$F45)>=P$10),$D45/12*(1+N($G45))^IF(AND(ISNUMBER($H45),P$10>=$H45),1+INT(DATEDIF($H45,P$10,"m")/12),0),0)) | ... X45: =IF(OR($D45="",$E45="",NOT(ISNUMBER($D45))),"",IF(AND($E45<=X$10,IF($F45="",$X$10,$F45)>=X$10),$D45/12*(1+N($G45))^IF(AND(ISNUMBER($H45),X$10>=$H45),1+INT(DATEDIF($H45,X$10,"m")/12),0),0)) | Z45: =SUM(M45:X45) -> 0 | AB45: =IF($D45&$E45="","",IF(AND($D45<>"",NOT(ISNUMBER($D45))),"Salary must be a number",IF(AND($D45<>"",$E45=""),"Start month missing",IF(AND(ISNUMBER($E45),ISNUMBER($F45),$F45<$E45),"End is before Start",IF(AND($D45<>"",NOT(ISNUMBER($H45))),"Increase month missing","")))))
F46: 46722 | G46: 0.03 | H46: =$D$8 -> 46661 | I46: =IF(OR($D46="",$E46="",NOT(ISNUMBER($D46))),"",IF(AND($E46<=I$10,IF($F46="",$X$10,$F46)>=I$10),$D46/12*(1+N($G46))^IF(AND(ISNUMBER($H46),I$10>=$H46),1+INT(DATEDIF($H46,I$10,"m")/12),0),0)) | J46: =IF(OR($D46="",$E46="",NOT(ISNUMBER($D46))),"",IF(AND($E46<=J$10,IF($F46="",$X$10,$F46)>=J$10),$D46/12*(1+N($G46))^IF(AND(ISNUMBER($H46),J$10>=$H46),1+INT(DATEDIF($H46,J$10,"m")/12),0),0)) | K46: =IF(OR($D46="",$E46="",NOT(ISNUMBER($D46))),"",IF(AND($E46<=K$10,IF($F46="",$X$10,$F46)>=K$10),$D46/12*(1+N($G46))^IF(AND(ISNUMBER($H46),K$10>=$H46),1+INT(DATEDIF($H46,K$10,"m")/12),0),0)) | L46: =IF(OR($D46="",$E46="",NOT(ISNUMBER($D46))),"",IF(AND($E46<=L$10,IF($F46="",$X$10,$F46)>=L$10),$D46/12*(1+N($G46))^IF(AND(ISNUMBER($H46),L$10>=$H46),1+INT(DATEDIF($H46,L$10,"m")/12),0),0)) | M46: =IF(OR($D46="",$E46="",NOT(ISNUMBER($D46))),"",IF(AND($E46<=M$10,IF($F46="",$X$10,$F46)>=M$10),$D46/12*(1+N($G46))^IF(AND(ISNUMBER($H46),M$10>=$H46),1+INT(DATEDIF($H46,M$10,"m")/12),0),0)) | N46: =IF(OR($D46="",$E46="",NOT(ISNUMBER($D46))),"",IF(AND($E46<=N$10,IF($F46="",$X$10,$F46)>=N$10),$D46/12*(1+N($G46))^IF(AND(ISNUMBER($H46),N$10>=$H46),1+INT(DATEDIF($H46,N$10,"m")/12),0),0)) | O46: =IF(OR($D46="",$E46="",NOT(ISNUMBER($D46))),"",IF(AND($E46<=O$10,IF($F46="",$X$10,$F46)>=O$10),$D46/12*(1+N($G46))^IF(AND(ISNUMBER($H46),O$10>=$H46),1+INT(DATEDIF($H46,O$10,"m")/12),0),0)) | P46: =IF(OR($D46="",$E46="",NOT(ISNUMBER($D46))),"",IF(AND($E46<=P$10,IF($F46="",$X$10,$F46)>=P$10),$D46/12*(1+N($G46))^IF(AND(ISNUMBER($H46),P$10>=$H46),1+INT(DATEDIF($H46,P$10,"m")/12),0),0)) | ... X46: =IF(OR($D46="",$E46="",NOT(ISNUMBER($D46))),"",IF(AND($E46<=X$10,IF($F46="",$X$10,$F46)>=X$10),$D46/12*(1+N($G46))^IF(AND(ISNUMBER($H46),X$10>=$H46),1+INT(DATEDIF($H46,X$10,"m")/12),0),0)) | Z46: =SUM(M46:X46) -> 0 | AB46: =IF($D46&$E46="","",IF(AND($D46<>"",NOT(ISNUMBER($D46))),"Salary must be a number",IF(AND($D46<>"",$E46=""),"Start month missing",IF(AND(ISNUMBER($E46),ISNUMBER($F46),$F46<$E46),"End is before Start",IF(AND($D46<>"",NOT(ISNUMBER($H46))),"Increase month missing","")))))
F47: 46722 | G47: 0.03 | H47: =$D$8 -> 46661 | I47: =IF(OR($D47="",$E47="",NOT(ISNUMBER($D47))),"",IF(AND($E47<=I$10,IF($F47="",$X$10,$F47)>=I$10),$D47/12*(1+N($G47))^IF(AND(ISNUMBER($H47),I$10>=$H47),1+INT(DATEDIF($H47,I$10,"m")/12),0),0)) | J47: =IF(OR($D47="",$E47="",NOT(ISNUMBER($D47))),"",IF(AND($E47<=J$10,IF($F47="",$X$10,$F47)>=J$10),$D47/12*(1+N($G47))^IF(AND(ISNUMBER($H47),J$10>=$H47),1+INT(DATEDIF($H47,J$10,"m")/12),0),0)) | K47: =IF(OR($D47="",$E47="",NOT(ISNUMBER($D47))),"",IF(AND($E47<=K$10,IF($F47="",$X$10,$F47)>=K$10),$D47/12*(1+N($G47))^IF(AND(ISNUMBER($H47),K$10>=$H47),1+INT(DATEDIF($H47,K$10,"m")/12),0),0)) | L47: =IF(OR($D47="",$E47="",NOT(ISNUMBER($D47))),"",IF(AND($E47<=L$10,IF($F47="",$X$10,$F47)>=L$10),$D47/12*(1+N($G47))^IF(AND(ISNUMBER($H47),L$10>=$H47),1+INT(DATEDIF($H47,L$10,"m")/12),0),0)) | M47: =IF(OR($D47="",$E47="",NOT(ISNUMBER($D47))),"",IF(AND($E47<=M$10,IF($F47="",$X$10,$F47)>=M$10),$D47/12*(1+N($G47))^IF(AND(ISNUMBER($H47),M$10>=$H47),1+INT(DATEDIF($H47,M$10,"m")/12),0),0)) | N47: =IF(OR($D47="",$E47="",NOT(ISNUMBER($D47))),"",IF(AND($E47<=N$10,IF($F47="",$X$10,$F47)>=N$10),$D47/12*(1+N($G47))^IF(AND(ISNUMBER($H47),N$10>=$H47),1+INT(DATEDIF($H47,N$10,"m")/12),0),0)) | O47: =IF(OR($D47="",$E47="",NOT(ISNUMBER($D47))),"",IF(AND($E47<=O$10,IF($F47="",$X$10,$F47)>=O$10),$D47/12*(1+N($G47))^IF(AND(ISNUMBER($H47),O$10>=$H47),1+INT(DATEDIF($H47,O$10,"m")/12),0),0)) | P47: =IF(OR($D47="",$E47="",NOT(ISNUMBER($D47))),"",IF(AND($E47<=P$10,IF($F47="",$X$10,$F47)>=P$10),$D47/12*(1+N($G47))^IF(AND(ISNUMBER($H47),P$10>=$H47),1+INT(DATEDIF($H47,P$10,"m")/12),0),0)) | ... X47: =IF(OR($D47="",$E47="",NOT(ISNUMBER($D47))),"",IF(AND($E47<=X$10,IF($F47="",$X$10,$F47)>=X$10),$D47/12*(1+N($G47))^IF(AND(ISNUMBER($H47),X$10>=$H47),1+INT(DATEDIF($H47,X$10,"m")/12),0),0)) | Z47: =SUM(M47:X47) -> 0 | AB47: =IF($D47&$E47="","",IF(AND($D47<>"",NOT(ISNUMBER($D47))),"Salary must be a number",IF(AND($D47<>"",$E47=""),"Start month missing",IF(AND(ISNUMBER($E47),ISNUMBER($F47),$F47<$E47),"End is before Start",IF(AND($D47<>"",NOT(ISNUMBER($H47))),"Increase month missing","")))))
F48: 46722 | G48: 0.03 | H48: =$D$8 -> 46661 | I48: =IF(OR($D48="",$E48="",NOT(ISNUMBER($D48))),"",IF(AND($E48<=I$10,IF($F48="",$X$10,$F48)>=I$10),$D48/12*(1+N($G48))^IF(AND(ISNUMBER($H48),I$10>=$H48),1+INT(DATEDIF($H48,I$10,"m")/12),0),0)) | J48: =IF(OR($D48="",$E48="",NOT(ISNUMBER($D48))),"",IF(AND($E48<=J$10,IF($F48="",$X$10,$F48)>=J$10),$D48/12*(1+N($G48))^IF(AND(ISNUMBER($H48),J$10>=$H48),1+INT(DATEDIF($H48,J$10,"m")/12),0),0)) | K48: =IF(OR($D48="",$E48="",NOT(ISNUMBER($D48))),"",IF(AND($E48<=K$10,IF($F48="",$X$10,$F48)>=K$10),$D48/12*(1+N($G48))^IF(AND(ISNUMBER($H48),K$10>=$H48),1+INT(DATEDIF($H48,K$10,"m")/12),0),0)) | L48: =IF(OR($D48="",$E48="",NOT(ISNUMBER($D48))),"",IF(AND($E48<=L$10,IF($F48="",$X$10,$F48)>=L$10),$D48/12*(1+N($G48))^IF(AND(ISNUMBER($H48),L$10>=$H48),1+INT(DATEDIF($H48,L$10,"m")/12),0),0)) | M48: =IF(OR($D48="",$E48="",NOT(ISNUMBER($D48))),"",IF(AND($E48<=M$10,IF($F48="",$X$10,$F48)>=M$10),$D48/12*(1+N($G48))^IF(AND(ISNUMBER($H48),M$10>=$H48),1+INT(DATEDIF($H48,M$10,"m")/12),0),0)) | N48: =IF(OR($D48="",$E48="",NOT(ISNUMBER($D48))),"",IF(AND($E48<=N$10,IF($F48="",$X$10,$F48)>=N$10),$D48/12*(1+N($G48))^IF(AND(ISNUMBER($H48),N$10>=$H48),1+INT(DATEDIF($H48,N$10,"m")/12),0),0)) | O48: =IF(OR($D48="",$E48="",NOT(ISNUMBER($D48))),"",IF(AND($E48<=O$10,IF($F48="",$X$10,$F48)>=O$10),$D48/12*(1+N($G48))^IF(AND(ISNUMBER($H48),O$10>=$H48),1+INT(DATEDIF($H48,O$10,"m")/12),0),0)) | P48: =IF(OR($D48="",$E48="",NOT(ISNUMBER($D48))),"",IF(AND($E48<=P$10,IF($F48="",$X$10,$F48)>=P$10),$D48/12*(1+N($G48))^IF(AND(ISNUMBER($H48),P$10>=$H48),1+INT(DATEDIF($H48,P$10,"m")/12),0),0)) | ... X48: =IF(OR($D48="",$E48="",NOT(ISNUMBER($D48))),"",IF(AND($E48<=X$10,IF($F48="",$X$10,$F48)>=X$10),$D48/12*(1+N($G48))^IF(AND(ISNUMBER($H48),X$10>=$H48),1+INT(DATEDIF($H48,X$10,"m")/12),0),0)) | Z48: =SUM(M48:X48) -> 0 | AB48: =IF($D48&$E48="","",IF(AND($D48<>"",NOT(ISNUMBER($D48))),"Salary must be a number",IF(AND($D48<>"",$E48=""),"Start month missing",IF(AND(ISNUMBER($E48),ISNUMBER($F48),$F48<$E48),"End is before Start",IF(AND($D48<>"",NOT(ISNUMBER($H48))),"Increase month missing","")))))
F49: 46722 | G49: 0.03 | H49: =$D$8 -> 46661 | I49: =IF(OR($D49="",$E49="",NOT(ISNUMBER($D49))),"",IF(AND($E49<=I$10,IF($F49="",$X$10,$F49)>=I$10),$D49/12*(1+N($G49))^IF(AND(ISNUMBER($H49),I$10>=$H49),1+INT(DATEDIF($H49,I$10,"m")/12),0),0)) | J49: =IF(OR($D49="",$E49="",NOT(ISNUMBER($D49))),"",IF(AND($E49<=J$10,IF($F49="",$X$10,$F49)>=J$10),$D49/12*(1+N($G49))^IF(AND(ISNUMBER($H49),J$10>=$H49),1+INT(DATEDIF($H49,J$10,"m")/12),0),0)) | K49: =IF(OR($D49="",$E49="",NOT(ISNUMBER($D49))),"",IF(AND($E49<=K$10,IF($F49="",$X$10,$F49)>=K$10),$D49/12*(1+N($G49))^IF(AND(ISNUMBER($H49),K$10>=$H49),1+INT(DATEDIF($H49,K$10,"m")/12),0),0)) | L49: =IF(OR($D49="",$E49="",NOT(ISNUMBER($D49))),"",IF(AND($E49<=L$10,IF($F49="",$X$10,$F49)>=L$10),$D49/12*(1+N($G49))^IF(AND(ISNUMBER($H49),L$10>=$H49),1+INT(DATEDIF($H49,L$10,"m")/12),0),0)) | M49: =IF(OR($D49="",$E49="",NOT(ISNUMBER($D49))),"",IF(AND($E49<=M$10,IF($F49="",$X$10,$F49)>=M$10),$D49/12*(1+N($G49))^IF(AND(ISNUMBER($H49),M$10>=$H49),1+INT(DATEDIF($H49,M$10,"m")/12),0),0)) | N49: =IF(OR($D49="",$E49="",NOT(ISNUMBER($D49))),"",IF(AND($E49<=N$10,IF($F49="",$X$10,$F49)>=N$10),$D49/12*(1+N($G49))^IF(AND(ISNUMBER($H49),N$10>=$H49),1+INT(DATEDIF($H49,N$10,"m")/12),0),0)) | O49: =IF(OR($D49="",$E49="",NOT(ISNUMBER($D49))),"",IF(AND($E49<=O$10,IF($F49="",$X$10,$F49)>=O$10),$D49/12*(1+N($G49))^IF(AND(ISNUMBER($H49),O$10>=$H49),1+INT(DATEDIF($H49,O$10,"m")/12),0),0)) | P49: =IF(OR($D49="",$E49="",NOT(ISNUMBER($D49))),"",IF(AND($E49<=P$10,IF($F49="",$X$10,$F49)>=P$10),$D49/12*(1+N($G49))^IF(AND(ISNUMBER($H49),P$10>=$H49),1+INT(DATEDIF($H49,P$10,"m")/12),0),0)) | ... X49: =IF(OR($D49="",$E49="",NOT(ISNUMBER($D49))),"",IF(AND($E49<=X$10,IF($F49="",$X$10,$F49)>=X$10),$D49/12*(1+N($G49))^IF(AND(ISNUMBER($H49),X$10>=$H49),1+INT(DATEDIF($H49,X$10,"m")/12),0),0)) | Z49: =SUM(M49:X49) -> 0 | AB49: =IF($D49&$E49="","",IF(AND($D49<>"",NOT(ISNUMBER($D49))),"Salary must be a number",IF(AND($D49<>"",$E49=""),"Start month missing",IF(AND(ISNUMBER($E49),ISNUMBER($F49),$F49<$E49),"End is before Start",IF(AND($D49<>"",NOT(ISNUMBER($H49))),"Increase month missing","")))))
F50: 46722 | G50: 0.03 | H50: =$D$8 -> 46661 | I50: =IF(OR($D50="",$E50="",NOT(ISNUMBER($D50))),"",IF(AND($E50<=I$10,IF($F50="",$X$10,$F50)>=I$10),$D50/12*(1+N($G50))^IF(AND(ISNUMBER($H50),I$10>=$H50),1+INT(DATEDIF($H50,I$10,"m")/12),0),0)) | J50: =IF(OR($D50="",$E50="",NOT(ISNUMBER($D50))),"",IF(AND($E50<=J$10,IF($F50="",$X$10,$F50)>=J$10),$D50/12*(1+N($G50))^IF(AND(ISNUMBER($H50),J$10>=$H50),1+INT(DATEDIF($H50,J$10,"m")/12),0),0)) | K50: =IF(OR($D50="",$E50="",NOT(ISNUMBER($D50))),"",IF(AND($E50<=K$10,IF($F50="",$X$10,$F50)>=K$10),$D50/12*(1+N($G50))^IF(AND(ISNUMBER($H50),K$10>=$H50),1+INT(DATEDIF($H50,K$10,"m")/12),0),0)) | L50: =IF(OR($D50="",$E50="",NOT(ISNUMBER($D50))),"",IF(AND($E50<=L$10,IF($F50="",$X$10,$F50)>=L$10),$D50/12*(1+N($G50))^IF(AND(ISNUMBER($H50),L$10>=$H50),1+INT(DATEDIF($H50,L$10,"m")/12),0),0)) | M50: =IF(OR($D50="",$E50="",NOT(ISNUMBER($D50))),"",IF(AND($E50<=M$10,IF($F50="",$X$10,$F50)>=M$10),$D50/12*(1+N($G50))^IF(AND(ISNUMBER($H50),M$10>=$H50),1+INT(DATEDIF($H50,M$10,"m")/12),0),0)) | N50: =IF(OR($D50="",$E50="",NOT(ISNUMBER($D50))),"",IF(AND($E50<=N$10,IF($F50="",$X$10,$F50)>=N$10),$D50/12*(1+N($G50))^IF(AND(ISNUMBER($H50),N$10>=$H50),1+INT(DATEDIF($H50,N$10,"m")/12),0),0)) | O50: =IF(OR($D50="",$E50="",NOT(ISNUMBER($D50))),"",IF(AND($E50<=O$10,IF($F50="",$X$10,$F50)>=O$10),$D50/12*(1+N($G50))^IF(AND(ISNUMBER($H50),O$10>=$H50),1+INT(DATEDIF($H50,O$10,"m")/12),0),0)) | P50: =IF(OR($D50="",$E50="",NOT(ISNUMBER($D50))),"",IF(AND($E50<=P$10,IF($F50="",$X$10,$F50)>=P$10),$D50/12*(1+N($G50))^IF(AND(ISNUMBER($H50),P$10>=$H50),1+INT(DATEDIF($H50,P$10,"m")/12),0),0)) | ... X50: =IF(OR($D50="",$E50="",NOT(ISNUMBER($D50))),"",IF(AND($E50<=X$10,IF($F50="",$X$10,$F50)>=X$10),$D50/12*(1+N($G50))^IF(AND(ISNUMBER($H50),X$10>=$H50),1+INT(DATEDIF($H50,X$10,"m")/12),0),0)) | Z50: =SUM(M50:X50) -> 0 | AB50: =IF($D50&$E50="","",IF(AND($D50<>"",NOT(ISNUMBER($D50))),"Salary must be a number",IF(AND($D50<>"",$E50=""),"Start month missing",IF(AND(ISNUMBER($E50),ISNUMBER($F50),$F50<$E50),"End is before Start",IF(AND($D50<>"",NOT(ISNUMBER($H50))),"Increase month missing","")))))
A51: From Dept | B51: Transfers In (arriving from another department — cost starts here)
