Workbook

Sheet DeploySum
A1: 2027 Production & Deployment Plan — Summary for COO
A2: Bookings, deployments and production by month (base case). Dollars in $000s. Sep–Dec 26 = remaining 2026 (existing + forecast contracts); FY2027 = Jan–Dec 27.
A3: {="Tie-out to Deploy Detail (bookings $, deployments, production): "&IF(AND(SUMPRODUCT(ABS(B18:Q18-'[1]Deploy Detail'!K172:Z172))+ABS(R18-'[1]Deploy Detail'!AB172)<0.01,SUMPRODUCT(ABS(B24:Q24+B25:Q25+B26:Q26-'[1]Deploy Detail'!K252:Z252))+ABS(SUM(R24:R26)-'[1]Deploy Detail'!AB252)<0.01,SUMPRODUCT(ABS(B13:Q13-'[1]Deploy Detail'!K92:Z92))+ABS(R13-'[1]Deploy Detail'!AB92)<0.5),"OK","CHECK")} -> #ERROR!
B4: ='[1]Revenue Roll-up'!D17 -> #REF! | C4: ='[1]Revenue Roll-up'!E17 -> #REF! | D4: ='[1]Revenue Roll-up'!F17 -> #REF! | E4: ='[1]Revenue Roll-up'!G17 -> #REF! | F4: ='[1]Revenue Roll-up'!H17 -> #REF! | G4: ='[1]Revenue Roll-up'!I17 -> #REF! | H4: ='[1]Revenue Roll-up'!J17 -> #REF! | I4: ='[1]Revenue Roll-up'!K17 -> #REF! | ... Q4: ='[1]Revenue Roll-up'!S17 -> #REF! | R4: FY2027
A5: BOOKINGS
A6: New logos – deals booked (#) | B6: ='[1]Revenue Roll-up'!D51 -> #REF! | C6: ='[1]Revenue Roll-up'!E51 -> #REF! | D6: ='[1]Revenue Roll-up'!F51 -> #REF! | E6: ='[1]Revenue Roll-up'!G51 -> #REF! | F6: ='[1]Revenue Roll-up'!H51 -> #REF! | G6: ='[1]Revenue Roll-up'!I51 -> #REF! | H6: ='[1]Revenue Roll-up'!J51 -> #REF! | I6: ='[1]Revenue Roll-up'!K51 -> #REF! | ... Q6: ='[1]Revenue Roll-up'!S51 -> #REF! | R6: ='[1]Revenue Roll-up'!U51 -> #REF!
A7: New logos – bookings ($000s) | B7: ='[1]Revenue Roll-up'!D50 -> #REF! | C7: ='[1]Revenue Roll-up'!E50 -> #REF! | D7: ='[1]Revenue Roll-up'!F50 -> #REF! | E7: ='[1]Revenue Roll-up'!G50 -> #REF! | F7: ='[1]Revenue Roll-up'!H50 -> #REF! | G7: ='[1]Revenue Roll-up'!I50 -> #REF! | H7: ='[1]Revenue Roll-up'!J50 -> #REF! | I7: ='[1]Revenue Roll-up'!K50 -> #REF! | ... Q7: ='[1]Revenue Roll-up'!S50 -> #REF! | R7: ='[1]Revenue Roll-up'!U50 -> #REF!
A8: Expansion – deals booked (#) | B8: ='[1]Revenue Roll-up'!D65 -> #REF! | C8: ='[1]Revenue Roll-up'!E65 -> #REF! | D8: ='[1]Revenue Roll-up'!F65 -> #REF! | E8: ='[1]Revenue Roll-up'!G65 -> #REF! | F8: ='[1]Revenue Roll-up'!H65 -> #REF! | G8: ='[1]Revenue Roll-up'!I65 -> #REF! | H8: ='[1]Revenue Roll-up'!J65 -> #REF! | I8: ='[1]Revenue Roll-up'!K65 -> #REF! | ... Q8: ='[1]Revenue Roll-up'!S65 -> #REF! | R8: ='[1]Revenue Roll-up'!U65 -> #REF!
A9: Expansion – bookings ($000s) | B9: ='[1]Revenue Roll-up'!D64 -> #REF! | C9: ='[1]Revenue Roll-up'!E64 -> #REF! | D9: ='[1]Revenue Roll-up'!F64 -> #REF! | E9: ='[1]Revenue Roll-up'!G64 -> #REF! | F9: ='[1]Revenue Roll-up'!H64 -> #REF! | G9: ='[1]Revenue Roll-up'!I64 -> #REF! | H9: ='[1]Revenue Roll-up'!J64 -> #REF! | I9: ='[1]Revenue Roll-up'!K64 -> #REF! | ... Q9: ='[1]Revenue Roll-up'!S64 -> #REF! | R9: ='[1]Revenue Roll-up'!U64 -> #REF!
A10: Existing & forecast contracts – booked (#) | B10: =COUNTIF('[1]Deploy Detail'!K21:K62,">0") -> #REF! | C10: =COUNTIF('[1]Deploy Detail'!L21:L62,">0") -> #REF! | D10: =COUNTIF('[1]Deploy Detail'!M21:M62,">0") -> #REF! | E10: =COUNTIF('[1]Deploy Detail'!N21:N62,">0") -> #REF! | F10: =COUNTIF('[1]Deploy Detail'!O21:O62,">0") -> #REF! | G10: =COUNTIF('[1]Deploy Detail'!P21:P62,">0") -> #REF! | H10: =COUNTIF('[1]Deploy Detail'!Q21:Q62,">0") -> #REF! | I10: =COUNTIF('[1]Deploy Detail'!R21:R62,">0") -> #REF! | ... Q10: =COUNTIF('[1]Deploy Detail'!Z21:Z62,">0") -> #REF! | R10: =SUM(F10:Q10) -> #REF!
A11: Existing & forecast contracts – bookings ($000s) | B11: ='[1]Deploy Detail'!K63 -> #REF! | C11: ='[1]Deploy Detail'!L63 -> #REF! | D11: ='[1]Deploy Detail'!M63 -> #REF! | E11: ='[1]Deploy Detail'!N63 -> #REF! | F11: ='[1]Deploy Detail'!O63 -> #REF! | G11: ='[1]Deploy Detail'!P63 -> #REF! | H11: ='[1]Deploy Detail'!Q63 -> #REF! | I11: ='[1]Deploy Detail'!R63 -> #REF! | ... Q11: ='[1]Deploy Detail'!Z63 -> #REF! | R11: ='[1]Deploy Detail'!AB63 -> #REF!
A12: Total bookings (#) | B12: =B6+B8+B10 -> #REF! | C12: =C6+C8+C10 -> #REF! | D12: =D6+D8+D10 -> #REF! | E12: =E6+E8+E10 -> #REF! | F12: =F6+F8+F10 -> #REF! | G12: =G6+G8+G10 -> #REF! | H12: =H6+H8+H10 -> #REF! | I12: =I6+I8+I10 -> #REF! | ... R12: =R6+R8+R10 -> #REF!
A13: Total bookings ($000s) | B13: =B7+B9+B11 -> #REF! | C13: =C7+C9+C11 -> #REF! | D13: =D7+D9+D11 -> #REF! | E13: =E7+E9+E11 -> #REF! | F13: =F7+F9+F11 -> #REF! | G13: =G7+G9+G11 -> #REF! | H13: =H7+H9+H11 -> #REF! | I13: =I7+I9+I11 -> #REF! | ... R13: =R7+R9+R11 -> #REF!
A15: DEPLOYMENTS (deals going live)
A16: SlipLift deployments (#) | B16: =COUNTIFS('[1]2026 Exist New'!$U$9:$U$50,"Yes",'[1]2026 Exist New'!$E$9:$E$50,"SlipLift",'[1]2026 Exist New'!$I$9:$I$50,">"&EOMONTH(B$4,-1),'[1]2026 Exist New'!$I$9:$I$50,"<="&B$4)+[1]Deploy!D36+[1]Deploy!D41 -> #ERROR! | C16: =COUNTIFS('[1]2026 Exist New'!$U$9:$U$50,"Yes",'[1]2026 Exist New'!$E$9:$E$50,"SlipLift",'[1]2026 Exist New'!$I$9:$I$50,">"&EOMONTH(C$4,-1),'[1]2026 Exist New'!$I$9:$I$50,"<="&C$4)+[1]Deploy!E36+[1]Deploy!E41 -> #ERROR! | D16: =COUNTIFS('[1]2026 Exist New'!$U$9:$U$50,"Yes",'[1]2026 Exist New'!$E$9:$E$50,"SlipLift",'[1]2026 Exist New'!$I$9:$I$50,">"&EOMONTH(D$4,-1),'[1]2026 Exist New'!$I$9:$I$50,"<="&D$4)+[1]Deploy!F36+[1]Deploy!F41 -> #ERROR! | E16: =COUNTIFS('[1]2026 Exist New'!$U$9:$U$50,"Yes",'[1]2026 Exist New'!$E$9:$E$50,"SlipLift",'[1]2026 Exist New'!$I$9:$I$50,">"&EOMONTH(E$4,-1),'[1]2026 Exist New'!$I$9:$I$50,"<="&E$4)+[1]Deploy!G36+[1]Deploy!G41 -> #ERROR! | F16: =COUNTIFS('[1]2026 Exist New'!$U$9:$U$50,"Yes",'[1]2026 Exist New'!$E$9:$E$50,"SlipLift",'[1]2026 Exist New'!$I$9:$I$50,">"&EOMONTH(F$4,-1),'[1]2026 Exist New'!$I$9:$I$50,"<="&F$4)+[1]Deploy!H36+[1]Deploy!H41 -> #ERROR! | G16: =COUNTIFS('[1]2026 Exist New'!$U$9:$U$50,"Yes",'[1]2026 Exist New'!$E$9:$E$50,"SlipLift",'[1]2026 Exist New'!$I$9:$I$50,">"&EOMONTH(G$4,-1),'[1]2026 Exist New'!$I$9:$I$50,"<="&G$4)+[1]Deploy!I36+[1]Deploy!I41 -> #ERROR! | H16: =COUNTIFS('[1]2026 Exist New'!$U$9:$U$50,"Yes",'[1]2026 Exist New'!$E$9:$E$50,"SlipLift",'[1]2026 Exist New'!$I$9:$I$50,">"&EOMONTH(H$4,-1),'[1]2026 Exist New'!$I$9:$I$50,"<="&H$4)+[1]Deploy!J36+[1]Deploy!J41 -> #ERROR! | I16: =COUNTIFS('[1]2026 Exist New'!$U$9:$U$50,"Yes",'[1]2026 Exist New'!$E$9:$E$50,"SlipLift",'[1]2026 Exist New'!$I$9:$I$50,">"&EOMONTH(I$4,-1),'[1]2026 Exist New'!$I$9:$I$50,"<="&I$4)+[1]Deploy!K36+[1]Deploy!K41 -> #ERROR! | ... Q16: =COUNTIFS('[1]2026 Exist New'!$U$9:$U$50,"Yes",'[1]2026 Exist New'!$E$9:$E$50,"SlipLift",'[1]2026 Exist New'!$I$9:$I$50,">"&EOMONTH(Q$4,-1),'[1]2026 Exist New'!$I$9:$I$50,"<="&Q$4)+[1]Deploy!S36+[1]Deploy!S41 -> #ERROR! | R16: =COUNTIFS('[1]2026 Exist New'!$U$9:$U$50,"Yes",'[1]2026 Exist New'!$E$9:$E$50,"SlipLift",'[1]2026 Exist New'!$I$9:$I$50,">"&EOMONTH($F$4,-1),'[1]2026 Exist New'!$I$9:$I$50,"<="&$Q$4)+[1]Deploy!U36+[1]Deploy!U41 -> #ERROR!
A17: SlipBot deployments (#) | B17: =COUNTIFS('[1]2026 Exist New'!$U$9:$U$50,"Yes",'[1]2026 Exist New'!$E$9:$E$50,"SlipBot",'[1]2026 Exist New'!$I$9:$I$50,">"&EOMONTH(B$4,-1),'[1]2026 Exist New'!$I$9:$I$50,"<="&B$4) -> 0 | C17: =COUNTIFS('[1]2026 Exist New'!$U$9:$U$50,"Yes",'[1]2026 Exist New'!$E$9:$E$50,"SlipBot",'[1]2026 Exist New'!$I$9:$I$50,">"&EOMONTH(C$4,-1),'[1]2026 Exist New'!$I$9:$I$50,"<="&C$4) -> 0 | D17: =COUNTIFS('[1]2026 Exist New'!$U$9:$U$50,"Yes",'[1]2026 Exist New'!$E$9:$E$50,"SlipBot",'[1]2026 Exist New'!$I$9:$I$50,">"&EOMONTH(D$4,-1),'[1]2026 Exist New'!$I$9:$I$50,"<="&D$4) -> 0 | E17: =COUNTIFS('[1]2026 Exist New'!$U$9:$U$50,"Yes",'[1]2026 Exist New'!$E$9:$E$50,"SlipBot",'[1]2026 Exist New'!$I$9:$I$50,">"&EOMONTH(E$4,-1),'[1]2026 Exist New'!$I$9:$I$50,"<="&E$4) -> 0 | F17: =COUNTIFS('[1]2026 Exist New'!$U$9:$U$50,"Yes",'[1]2026 Exist New'!$E$9:$E$50,"SlipBot",'[1]2026 Exist New'!$I$9:$I$50,">"&EOMONTH(F$4,-1),'[1]2026 Exist New'!$I$9:$I$50,"<="&F$4) -> 0 | G17: =COUNTIFS('[1]2026 Exist New'!$U$9:$U$50,"Yes",'[1]2026 Exist New'!$E$9:$E$50,"SlipBot",'[1]2026 Exist New'!$I$9:$I$50,">"&EOMONTH(G$4,-1),'[1]2026 Exist New'!$I$9:$I$50,"<="&G$4) -> 0 | H17: =COUNTIFS('[1]2026 Exist New'!$U$9:$U$50,"Yes",'[1]2026 Exist New'!$E$9:$E$50,"SlipBot",'[1]2026 Exist New'!$I$9:$I$50,">"&EOMONTH(H$4,-1),'[1]2026 Exist New'!$I$9:$I$50,"<="&H$4) -> 0 | I17: =COUNTIFS('[1]2026 Exist New'!$U$9:$U$50,"Yes",'[1]2026 Exist New'!$E$9:$E$50,"SlipBot",'[1]2026 Exist New'!$I$9:$I$50,">"&EOMONTH(I$4,-1),'[1]2026 Exist New'!$I$9:$I$50,"<="&I$4) -> 0 | ... Q17: =COUNTIFS('[1]2026 Exist New'!$U$9:$U$50,"Yes",'[1]2026 Exist New'!$E$9:$E$50,"SlipBot",'[1]2026 Exist New'!$I$9:$I$50,">"&EOMONTH(Q$4,-1),'[1]2026 Exist New'!$I$9:$I$50,"<="&Q$4) -> 0 | R17: =COUNTIFS('[1]2026 Exist New'!$U$9:$U$50,"Yes",'[1]2026 Exist New'!$E$9:$E$50,"SlipBot",'[1]2026 Exist New'!$I$9:$I$50,">"&EOMONTH($F$4,-1),'[1]2026 Exist New'!$I$9:$I$50,"<="&$Q$4) -> 0
A18: Total deployments (#) | B18: =B16+B17 -> #ERROR! | C18: =C16+C17 -> #ERROR! | D18: =D16+D17 -> #ERROR! | E18: =E16+E17 -> #ERROR! | F18: =F16+F17 -> #ERROR! | G18: =G16+G17 -> #ERROR! | H18: =H16+H17 -> #ERROR! | I18: =I16+I17 -> #ERROR! | ... R18: =R16+R17 -> #ERROR!
A19: SlipLifts going live (units) | B19: =[1]Deploy!D47 -> #ERROR! | C19: =[1]Deploy!E47 -> #ERROR! | D19: =[1]Deploy!F47 -> #ERROR! | E19: =[1]Deploy!G47 -> #ERROR! | F19: =[1]Deploy!H47 -> #ERROR! | G19: =[1]Deploy!I47 -> #ERROR! | H19: =[1]Deploy!J47 -> #ERROR! | I19: =[1]Deploy!K47 -> #ERROR! | ... Q19: =[1]Deploy!S47 -> #ERROR! | R19: =[1]Deploy!U47 -> #ERROR!
A20: SlipTrays going live (units) | B20: =[1]Deploy!D48 -> #ERROR! | C20: =[1]Deploy!E48 -> #ERROR! | D20: =[1]Deploy!F48 -> #ERROR! | E20: =[1]Deploy!G48 -> #ERROR! | F20: =[1]Deploy!H48 -> #ERROR! | G20: =[1]Deploy!I48 -> #ERROR! | H20: =[1]Deploy!J48 -> #ERROR! | I20: =[1]Deploy!K48 -> #ERROR! | ... Q20: =[1]Deploy!S48 -> #ERROR! | R20: =[1]Deploy!U48 -> #ERROR!
A21: SlipBots going live (units) | B21: =[1]Deploy!D49 -> #ERROR! | C21: =[1]Deploy!E49 -> #ERROR! | D21: =[1]Deploy!F49 -> #ERROR! | E21: =[1]Deploy!G49 -> #ERROR! | F21: =[1]Deploy!H49 -> #ERROR! | G21: =[1]Deploy!I49 -> #ERROR! | H21: =[1]Deploy!J49 -> #ERROR! | I21: =[1]Deploy!K49 -> #ERROR! | ... Q21: =[1]Deploy!S49 -> #ERROR! | R21: =[1]Deploy!U49 -> #ERROR!
A23: PRODUCTION (units to build, by production month)
A24: SlipLifts to build | B24: =[1]Deploy!D53 -> #ERROR! | C24: =[1]Deploy!E53 -> #ERROR! | D24: =[1]Deploy!F53 -> #ERROR! | E24: =[1]Deploy!G53 -> #ERROR! | F24: =[1]Deploy!H53 -> #ERROR! | G24: =[1]Deploy!I53 -> #ERROR! | H24: =[1]Deploy!J53 -> #ERROR! | I24: =[1]Deploy!K53 -> #ERROR! | ... Q24: =[1]Deploy!S53 -> #ERROR! | R24: =[1]Deploy!U53 -> #ERROR!
A25: SlipTrays to build | B25: =[1]Deploy!D54 -> #ERROR! | C25: =[1]Deploy!E54 -> #ERROR! | D25: =[1]Deploy!F54 -> #ERROR! | E25: =[1]Deploy!G54 -> #ERROR! | F25: =[1]Deploy!H54 -> #ERROR! | G25: =[1]Deploy!I54 -> #ERROR! | H25: =[1]Deploy!J54 -> #ERROR! | I25: =[1]Deploy!K54 -> #ERROR! | ... Q25: =[1]Deploy!S54 -> #ERROR! | R25: =[1]Deploy!U54 -> #ERROR!
A26: SlipBots to build | B26: =[1]Deploy!D55 -> #ERROR! | C26: =[1]Deploy!E55 -> #ERROR! | D26: =[1]Deploy!F55 -> #ERROR! | E26: =[1]Deploy!G55 -> #ERROR! | F26: =[1]Deploy!H55 -> #ERROR! | G26: =[1]Deploy!I55 -> #ERROR! | H26: =[1]Deploy!J55 -> #ERROR! | I26: =[1]Deploy!K55 -> #ERROR! | ... Q26: =[1]Deploy!S55 -> #ERROR! | R26: =[1]Deploy!U55 -> #ERROR!
A27: SlipLifts – avg per week (units ÷ weeks in month) | B27: =B24/(DAY(B$4)/7) -> #ERROR! | C27: =C24/(DAY(C$4)/7) -> #ERROR! | D27: =D24/(DAY(D$4)/7) -> #ERROR! | E27: =E24/(DAY(E$4)/7) -> #ERROR! | F27: =F24/(DAY(F$4)/7) -> #ERROR! | G27: =G24/(DAY(G$4)/7) -> #ERROR! | H27: =H24/(DAY(H$4)/7) -> #ERROR! | I27: =I24/(DAY(I$4)/7) -> #ERROR! | ... Q27: =Q24/(DAY(Q$4)/7) -> #ERROR! | R27: {=R24/(SUMPRODUCT(DAY($F$4:$Q$4))/7)} -> #ERROR!
A28: SlipTrays – avg per week (units ÷ weeks in month) | B28: =B25/(DAY(B$4)/7) -> #ERROR! | C28: =C25/(DAY(C$4)/7) -> #ERROR! | D28: =D25/(DAY(D$4)/7) -> #ERROR! | E28: =E25/(DAY(E$4)/7) -> #ERROR! | F28: =F25/(DAY(F$4)/7) -> #ERROR! | G28: =G25/(DAY(G$4)/7) -> #ERROR! | H28: =H25/(DAY(H$4)/7) -> #ERROR! | I28: =I25/(DAY(I$4)/7) -> #ERROR! | ... Q28: =Q25/(DAY(Q$4)/7) -> #ERROR! | R28: {=R25/(SUMPRODUCT(DAY($F$4:$Q$4))/7)} -> #ERROR!
A29: Production CapEx ($000s) | B29: =[1]Deploy!D68 -> #ERROR! | C29: =[1]Deploy!E68 -> #ERROR! | D29: =[1]Deploy!F68 -> #ERROR! | E29: =[1]Deploy!G68 -> #ERROR! | F29: =[1]Deploy!H68 -> #ERROR! | G29: =[1]Deploy!I68 -> #ERROR! | H29: =[1]Deploy!J68 -> #ERROR! | I29: =[1]Deploy!K68 -> #ERROR! | ... Q29: =[1]Deploy!S68 -> #ERROR! | R29: =[1]Deploy!U68 -> #ERROR!
A30: Deployment freight – expensed ($000s) | B30: =[1]Deploy!D69 -> #ERROR! | C30: =[1]Deploy!E69 -> #ERROR! | D30: =[1]Deploy!F69 -> #ERROR! | E30: =[1]Deploy!G69 -> #ERROR! | F30: =[1]Deploy!H69 -> #ERROR! | G30: =[1]Deploy!I69 -> #ERROR! | H30: =[1]Deploy!J69 -> #ERROR! | I30: =[1]Deploy!K69 -> #ERROR! | ... Q30: =[1]Deploy!S69 -> #ERROR! | R30: =[1]Deploy!U69 -> #ERROR!
A32: OF WHICH (already included in the production lines above): builds in Nov/Dec-27 for Q1-28 go-lives from Q4-27 bookings
A33: SlipLifts built for 2028 go-lives | B33: =SUMIFS('[1]Deploy Detail'!$G$225:$G$236,'[1]Deploy Detail'!$E$225:$E$236,B$4,'[1]Deploy Detail'!$D$225:$D$236,">"&'[1]Deploy Detail'!$B$13)+SUMIFS('[1]Deploy Detail'!$G$239:$G$250,'[1]Deploy Detail'!$E$239:$E$250,B$4,'[1]Deploy Detail'!$D$239:$D$250,">"&'[1]Deploy Detail'!$B$13) -> #N/A | C33: =SUMIFS('[1]Deploy Detail'!$G$225:$G$236,'[1]Deploy Detail'!$E$225:$E$236,C$4,'[1]Deploy Detail'!$D$225:$D$236,">"&'[1]Deploy Detail'!$B$13)+SUMIFS('[1]Deploy Detail'!$G$239:$G$250,'[1]Deploy Detail'!$E$239:$E$250,C$4,'[1]Deploy Detail'!$D$239:$D$250,">"&'[1]Deploy Detail'!$B$13) -> #N/A | D33: =SUMIFS('[1]Deploy Detail'!$G$225:$G$236,'[1]Deploy Detail'!$E$225:$E$236,D$4,'[1]Deploy Detail'!$D$225:$D$236,">"&'[1]Deploy Detail'!$B$13)+SUMIFS('[1]Deploy Detail'!$G$239:$G$250,'[1]Deploy Detail'!$E$239:$E$250,D$4,'[1]Deploy Detail'!$D$239:$D$250,">"&'[1]Deploy Detail'!$B$13) -> #N/A | E33: =SUMIFS('[1]Deploy Detail'!$G$225:$G$236,'[1]Deploy Detail'!$E$225:$E$236,E$4,'[1]Deploy Detail'!$D$225:$D$236,">"&'[1]Deploy Detail'!$B$13)+SUMIFS('[1]Deploy Detail'!$G$239:$G$250,'[1]Deploy Detail'!$E$239:$E$250,E$4,'[1]Deploy Detail'!$D$239:$D$250,">"&'[1]Deploy Detail'!$B$13) -> #N/A | F33: =SUMIFS('[1]Deploy Detail'!$G$225:$G$236,'[1]Deploy Detail'!$E$225:$E$236,F$4,'[1]Deploy Detail'!$D$225:$D$236,">"&'[1]Deploy Detail'!$B$13)+SUMIFS('[1]Deploy Detail'!$G$239:$G$250,'[1]Deploy Detail'!$E$239:$E$250,F$4,'[1]Deploy Detail'!$D$239:$D$250,">"&'[1]Deploy Detail'!$B$13) -> #N/A | G33: =SUMIFS('[1]Deploy Detail'!$G$225:$G$236,'[1]Deploy Detail'!$E$225:$E$236,G$4,'[1]Deploy Detail'!$D$225:$D$236,">"&'[1]Deploy Detail'!$B$13)+SUMIFS('[1]Deploy Detail'!$G$239:$G$250,'[1]Deploy Detail'!$E$239:$E$250,G$4,'[1]Deploy Detail'!$D$239:$D$250,">"&'[1]Deploy Detail'!$B$13) -> #N/A | H33: =SUMIFS('[1]Deploy Detail'!$G$225:$G$236,'[1]Deploy Detail'!$E$225:$E$236,H$4,'[1]Deploy Detail'!$D$225:$D$236,">"&'[1]Deploy Detail'!$B$13)+SUMIFS('[1]Deploy Detail'!$G$239:$G$250,'[1]Deploy Detail'!$E$239:$E$250,H$4,'[1]Deploy Detail'!$D$239:$D$250,">"&'[1]Deploy Detail'!$B$13) -> #N/A | I33: =SUMIFS('[1]Deploy Detail'!$G$225:$G$236,'[1]Deploy Detail'!$E$225:$E$236,I$4,'[1]Deploy Detail'!$D$225:$D$236,">"&'[1]Deploy Detail'!$B$13)+SUMIFS('[1]Deploy Detail'!$G$239:$G$250,'[1]Deploy Detail'!$E$239:$E$250,I$4,'[1]Deploy Detail'!$D$239:$D$250,">"&'[1]Deploy Detail'!$B$13) -> #N/A | ... Q33: =SUMIFS('[1]Deploy Detail'!$G$225:$G$236,'[1]Deploy Detail'!$E$225:$E$236,Q$4,'[1]Deploy Detail'!$D$225:$D$236,">"&'[1]Deploy Detail'!$B$13)+SUMIFS('[1]Deploy Detail'!$G$239:$G$250,'[1]Deploy Detail'!$E$239:$E$250,Q$4,'[1]Deploy Detail'!$D$239:$D$250,">"&'[1]Deploy Detail'!$B$13) -> #N/A | R33: =SUM(F33:Q33) -> #N/A
A34: SlipTrays built for 2028 go-lives | B34: =SUMIFS('[1]Deploy Detail'!$H$225:$H$236,'[1]Deploy Detail'!$E$225:$E$236,B$4,'[1]Deploy Detail'!$D$225:$D$236,">"&'[1]Deploy Detail'!$B$13)+SUMIFS('[1]Deploy Detail'!$H$239:$H$250,'[1]Deploy Detail'!$E$239:$E$250,B$4,'[1]Deploy Detail'!$D$239:$D$250,">"&'[1]Deploy Detail'!$B$13) -> #N/A | C34: =SUMIFS('[1]Deploy Detail'!$H$225:$H$236,'[1]Deploy Detail'!$E$225:$E$236,C$4,'[1]Deploy Detail'!$D$225:$D$236,">"&'[1]Deploy Detail'!$B$13)+SUMIFS('[1]Deploy Detail'!$H$239:$H$250,'[1]Deploy Detail'!$E$239:$E$250,C$4,'[1]Deploy Detail'!$D$239:$D$250,">"&'[1]Deploy Detail'!$B$13) -> #N/A | D34: =SUMIFS('[1]Deploy Detail'!$H$225:$H$236,'[1]Deploy Detail'!$E$225:$E$236,D$4,'[1]Deploy Detail'!$D$225:$D$236,">"&'[1]Deploy Detail'!$B$13)+SUMIFS('[1]Deploy Detail'!$H$239:$H$250,'[1]Deploy Detail'!$E$239:$E$250,D$4,'[1]Deploy Detail'!$D$239:$D$250,">"&'[1]Deploy Detail'!$B$13) -> #N/A | E34: =SUMIFS('[1]Deploy Detail'!$H$225:$H$236,'[1]Deploy Detail'!$E$225:$E$236,E$4,'[1]Deploy Detail'!$D$225:$D$236,">"&'[1]Deploy Detail'!$B$13)+SUMIFS('[1]Deploy Detail'!$H$239:$H$250,'[1]Deploy Detail'!$E$239:$E$250,E$4,'[1]Deploy Detail'!$D$239:$D$250,">"&'[1]Deploy Detail'!$B$13) -> #N/A | F34: =SUMIFS('[1]Deploy Detail'!$H$225:$H$236,'[1]Deploy Detail'!$E$225:$E$236,F$4,'[1]Deploy Detail'!$D$225:$D$236,">"&'[1]Deploy Detail'!$B$13)+SUMIFS('[1]Deploy Detail'!$H$239:$H$250,'[1]Deploy Detail'!$E$239:$E$250,F$4,'[1]Deploy Detail'!$D$239:$D$250,">"&'[1]Deploy Detail'!$B$13) -> #N/A | G34: =SUMIFS('[1]Deploy Detail'!$H$225:$H$236,'[1]Deploy Detail'!$E$225:$E$236,G$4,'[1]Deploy Detail'!$D$225:$D$236,">"&'[1]Deploy Detail'!$B$13)+SUMIFS('[1]Deploy Detail'!$H$239:$H$250,'[1]Deploy Detail'!$E$239:$E$250,G$4,'[1]Deploy Detail'!$D$239:$D$250,">"&'[1]Deploy Detail'!$B$13) -> #N/A | H34: =SUMIFS('[1]Deploy Detail'!$H$225:$H$236,'[1]Deploy Detail'!$E$225:$E$236,H$4,'[1]Deploy Detail'!$D$225:$D$236,">"&'[1]Deploy Detail'!$B$13)+SUMIFS('[1]Deploy Detail'!$H$239:$H$250,'[1]Deploy Detail'!$E$239:$E$250,H$4,'[1]Deploy Detail'!$D$239:$D$250,">"&'[1]Deploy Detail'!$B$13) -> #N/A | I34: =SUMIFS('[1]Deploy Detail'!$H$225:$H$236,'[1]Deploy Detail'!$E$225:$E$236,I$4,'[1]Deploy Detail'!$D$225:$D$236,">"&'[1]Deploy Detail'!$B$13)+SUMIFS('[1]Deploy Detail'!$H$239:$H$250,'[1]Deploy Detail'!$E$239:$E$250,I$4,'[1]Deploy Detail'!$D$239:$D$250,">"&'[1]Deploy Detail'!$B$13) -> #N/A | ... Q34: =SUMIFS('[1]Deploy Detail'!$H$225:$H$236,'[1]Deploy Detail'!$E$225:$E$236,Q$4,'[1]Deploy Detail'!$D$225:$D$236,">"&'[1]Deploy Detail'!$B$13)+SUMIFS('[1]Deploy Detail'!$H$239:$H$250,'[1]Deploy Detail'!$E$239:$E$250,Q$4,'[1]Deploy Detail'!$D$239:$D$250,">"&'[1]Deploy Detail'!$B$13) -> #N/A | R34: =SUM(F34:Q34) -> #N/A
A35: CapEx for 2028 go-lives – estimate ($000s) | B35: =B33*([1]Deploy!$B$7+[1]Deploy!$B$14)+B34*[1]Deploy!$B$8 -> #ERROR! | C35: =C33*([1]Deploy!$B$7+[1]Deploy!$B$14)+C34*[1]Deploy!$B$8 -> #ERROR! | D35: =D33*([1]Deploy!$B$7+[1]Deploy!$B$14)+D34*[1]Deploy!$B$8 -> #ERROR! | E35: =E33*([1]Deploy!$B$7+[1]Deploy!$B$14)+E34*[1]Deploy!$B$8 -> #ERROR! | F35: =F33*([1]Deploy!$B$7+[1]Deploy!$B$14)+F34*[1]Deploy!$B$8 -> #ERROR! | G35: =G33*([1]Deploy!$B$7+[1]Deploy!$B$14)+G34*[1]Deploy!$B$8 -> #ERROR! | H35: =H33*([1]Deploy!$B$7+[1]Deploy!$B$14)+H34*[1]Deploy!$B$8 -> #ERROR! | I35: =I33*([1]Deploy!$B$7+[1]Deploy!$B$14)+I34*[1]Deploy!$B$8 -> #ERROR! | ... R35: =R33*([1]Deploy!$B$7+[1]Deploy!$B$14)+R34*[1]Deploy!$B$8 -> #ERROR!
A37: OTHER CONTEXT
A38: CARR – end of period ($000s) | B38: ='[1]Revenue Roll-up'!D24 -> #REF! | C38: ='[1]Revenue Roll-up'!E24 -> #REF! | D38: ='[1]Revenue Roll-up'!F24 -> #REF! | E38: ='[1]Revenue Roll-up'!G24 -> #REF! | F38: ='[1]Revenue Roll-up'!H24 -> #REF! | G38: ='[1]Revenue Roll-up'!I24 -> #REF! | H38: ='[1]Revenue Roll-up'!J24 -> #REF! | I38: ='[1]Revenue Roll-up'!K24 -> #REF! | ... Q38: ='[1]Revenue Roll-up'!S24 -> #REF! | R38: ='[1]Revenue Roll-up'!S24 -> #REF!
A39: ARR – end of period ($000s) | B39: ='[1]Revenue Roll-up'!D30 -> #REF! | C39: ='[1]Revenue Roll-up'!E30 -> #REF! | D39: ='[1]Revenue Roll-up'!F30 -> #REF! | E39: ='[1]Revenue Roll-up'!G30 -> #REF! | F39: ='[1]Revenue Roll-up'!H30 -> #REF! | G39: ='[1]Revenue Roll-up'!I30 -> #REF! | H39: ='[1]Revenue Roll-up'!J30 -> #REF! | I39: ='[1]Revenue Roll-up'!K30 -> #REF! | ... Q39: ='[1]Revenue Roll-up'!S30 -> #REF! | R39: ='[1]Revenue Roll-up'!S30 -> #REF!
A40: Recognized revenue ($000s) | B40: ='[1]Revenue Roll-up'!D38 -> #REF! | C40: ='[1]Revenue Roll-up'!E38 -> #REF! | D40: ='[1]Revenue Roll-up'!F38 -> #REF! | E40: ='[1]Revenue Roll-up'!G38 -> #REF! | F40: ='[1]Revenue Roll-up'!H38 -> #REF! | G40: ='[1]Revenue Roll-up'!I38 -> #REF! | H40: ='[1]Revenue Roll-up'!J38 -> #REF! | I40: ='[1]Revenue Roll-up'!K38 -> #REF! | ... Q40: ='[1]Revenue Roll-up'!S38 -> #REF! | R40: ='[1]Revenue Roll-up'!U38 -> #REF!
A41: Billings ($000s) | B41: ='[1]Revenue Roll-up'!D40 -> #REF! | C41: ='[1]Revenue Roll-up'!E40 -> #REF! | D41: ='[1]Revenue Roll-up'!F40 -> #REF! | E41: ='[1]Revenue Roll-up'!G40 -> #REF! | F41: ='[1]Revenue Roll-up'!H40 -> #REF! | G41: ='[1]Revenue Roll-up'!I40 -> #REF! | H41: ='[1]Revenue Roll-up'!J40 -> #REF! | I41: ='[1]Revenue Roll-up'!K40 -> #REF! | ... Q41: ='[1]Revenue Roll-up'!S40 -> #REF! | R41: ='[1]Revenue Roll-up'!U40 -> #REF!
A42: Deferred revenue – end of period ($000s) | B42: ='[1]Revenue Roll-up'!D45 -> #REF! | C42: ='[1]Revenue Roll-up'!E45 -> #REF! | D42: ='[1]Revenue Roll-up'!F45 -> #REF! | E42: ='[1]Revenue Roll-up'!G45 -> #REF! | F42: ='[1]Revenue Roll-up'!H45 -> #REF! | G42: ='[1]Revenue Roll-up'!I45 -> #REF! | H42: ='[1]Revenue Roll-up'!J45 -> #REF! | I42: ='[1]Revenue Roll-up'!K45 -> #REF! | ... Q42: ='[1]Revenue Roll-up'!S45 -> #REF! | R42: ='[1]Revenue Roll-up'!S45 -> #REF!
A44: KEY ASSUMPTIONS & NOTES
A45: ="1. Timing: bookings go live "&'[1]Deploy Detail'!B8&" months after booking (new logos & expansion); units are built "&[1]Deploy!B16&" months before go-live." -> #ERROR!
A46: ="2. Deal size: new-logo deal = "&[1]Deploy!B18&" SlipLifts + "&[1]Deploy!B19&" SlipTrays ("&TEXT('[1]New Sales'!B8,"$#,##0")&"); expansion deal = "&[1]Deploy!B20&" SlipLifts + "&[1]Deploy!B21&" SlipTrays ("&TEXT([1]Expansion!B11,"$#,##0")&"). Deal counts are whole numbers." -> #ERROR!
A47: ="3. Unit cost (CapEx): SlipLift "&TEXT([1]Deploy!B7,"$#,##0")&" + "&TEXT([1]Deploy!B14,"$#,##0")&" peripherals, SlipTray "&TEXT([1]Deploy!B8,"$#,##0")&", SlipBot "&TEXT([1]Deploy!B6,"$#,##0")&". Freight "&TEXT([1]Deploy!B15,"$#,##0")&" per deployment (expensed)." -> #ERROR!
A48: ="4. SlipBots: "&IF([1]Deploy!B17="Y","none are built – returned/existing bots are redeployed (incl. the Meli bridge bots).","built per deployments.")&" Only contracts flagged 'New production = Yes' create deployments and production." -> #ERROR!
A49: ="5. Sep–Dec 26 bookings include unsigned forecast of "&TEXT(SUMIFS('[1]2026 Exist New'!$P$9:$P$50,'[1]2026 Exist New'!$D$9:$D$50,"Forecast (unsigned)"),"$#,##0")&" (Arconic + placeholders) at 100%; bookings are gross ACV." -> #N/A
A50: 6. Production includes Nov/Dec-27 builds for Jan–Feb 28 go-lives from Q4-27 bookings (the 'of which' lines).
A52: DEPLOYMENT SPLIT – NEW LOGOS vs EXPANSION (deals going live, by go-live month)
A53: Month | B53: 46295 | C53: 46326 | D53: 46356 | E53: 46387 | F53: 46418 | G53: 46446 | H53: 46477 | I53: 46507 | J53: 46538 | K53: 46568 | L53: 46599 | M53: 46630 | N53: 46660 | O53: 46691 | P53: 46721 | Q53: 46752 | R53: FY2027
A54: New logos – deployments (#) (incl. 2026 Exist New 'New Logo' rows) | B54: 0 | C54: 0 | D54: 0 | E54: 0 | F54: 3 | G54: 2 | H54: 0 | I54: 3 | J54: 3 | K54: 4 | L54: 4 | M54: 5 | N54: 6 | O54: 6 | P54: 7 | Q54: 8 | R54: 51
A55: SlipLifts going live (units) | B55: 0 | C55: 0 | D55: 0 | E55: 0 | F55: 20 | G55: 8 | H55: 0 | I55: 12 | J55: 12 | K55: 16 | L55: 16 | M55: 20 | N55: 24 | O55: 24 | P55: 28 | Q55: 32 | R55: 212
A56: SlipTrays going live (units) | B56: 0 | C56: 0 | D56: 0 | E56: 0 | F56: 60 | G56: 24 | H56: 0 | I56: 36 | J56: 36 | K56: 48 | L56: 48 | M56: 60 | N56: 72 | O56: 72 | P56: 84 | Q56: 96 | R56: 636
A57: Expansion – deployments (#) | B57: 0 | C57: 0 | D57: 0 | E57: 0 | F57: 0 | G57: 0 | H57: 0 | I57: 1 | J57: 1 | K57: 2 | L57: 1 | M57: 1 | N57: 2 | O57: 2 | P57: 3 | Q57: 2 | R57: 15
A58: SlipLifts going live (units) | B58: 0 | C58: 0 | D58: 0 | E58: 0 | F58: 0 | G58: 0 | H58: 0 | I58: 2 | J58: 2 | K58: 4 | L58: 2 | M58: 2 | N58: 4 | O58: 4 | P58: 6 | Q58: 4 | R58: 30
A59: SlipTrays going live (units) | B59: 0 | C59: 0 | D59: 0 | E59: 0 | F59: 0 | G59: 0 | H59: 0 | I59: 25 | J59: 25 | K59: 50 | L59: 25 | M59: 25 | N59: 50 | O59: 50 | P59: 75 | Q59: 50 | R59: 375
A60: Existing & forecast contracts – deployments (#) (excl. 'New Logo' rows) | B60: 0 | C60: 2 | D60: 2 | E60: 0 | F60: 0 | G60: 0 | H60: 0 | I60: 1 | J60: 0 | K60: 0 | L60: 0 | M60: 0 | N60: 0 | O60: 0 | P60: 0 | Q60: 0 | R60: 1
A61: SlipLifts going live (units) | B61: 0 | C61: 9 | D61: 9 | E61: 0 | F61: 0 | G61: 0 | H61: 0 | I61: 8 | J61: 0 | K61: 0 | L61: 0 | M61: 0 | N61: 0 | O61: 0 | P61: 0 | Q61: 0 | R61: 8
A62: SlipTrays going live (units) | B62: 0 | C62: 35 | D62: 32 | E62: 0 | F62: 0 | G62: 0 | H62: 0 | I62: 25 | J62: 0 | K62: 0 | L62: 0 | M62: 0 | N62: 0 | O62: 0 | P62: 0 | Q62: 0 | R62: 25
A63: SlipBots going live (units) | B63: 0 | C63: 0 | D63: 0 | E63: 0 | F63: 0 | G63: 0 | H63: 0 | I63: 0 | J63: 0 | K63: 0 | L63: 0 | M63: 0 | N63: 0 | O63: 0 | P63: 0 | Q63: 0 | R63: 0
A64: Total deployments (#) | B64: 0 | C64: 2 | D64: 2 | E64: 0 | F64: 3 | G64: 2 | H64: 0 | I64: 5 | J64: 4 | K64: 6 | L64: 5 | M64: 6 | N64: 8 | O64: 8 | P64: 10 | Q64: 10 | R64: 67
A65: New logos – % of deployments | B65: 0 | C65: 0 | D65: 0 | E65: 0 | F65: 1 | G65: 1 | H65: 0 | I65: 0.6 | J65: 0.75 | K65: 0.66666667 | L65: 0.8 | M65: 0.83333333 | N65: 0.75 | O65: 0.75 | P65: 0.7 | Q65: 0.8 | R65: 0.76119403
A66: Expansion – % of deployments | B66: 0 | C66: 0 | D66: 0 | E66: 0 | F66: 0 | G66: 0 | H66: 0 | I66: 0.2 | J66: 0.25 | K66: 0.33333333 | L66: 0.2 | M66: 0.16666667 | N66: 0.25 | O66: 0.25 | P66: 0.3 | Q66: 0.2 | R66: 0.2238806
A67: Tie-out to Total deployments (row 18): OK

Sheet FO
A1: Field Operations
A2: 2026 Actuals/Forecast & 2027 Budget
B7: Actual | C7: Actual | D7: Actual | E7: Actual | F7: Actual | G7: Actual | H7: Actual | I7: Actual | J7: Forecast | K7: Forecast | L7: Forecast | M7: Forecast | N7: Forecast | O7: Forecast | S7: Annual Input | T7: YOY | U7: Budget | V7: Budget | W7: Budget | X7: Budget | Y7: Budget | Z7: Budget | AA7: Budget | AB7: Budget | AC7: Budget | AD7: Budget | AE7: Budget | AF7: Budget | AG7: Budget | AH7: Budget | AJ7: YOY
B8: Jan | C8: Feb | D8: Mar | E8: Apr | F8: May | G8: Jun | H8: Jul | I8: Aug | J8: Sep | K8: Oct | L8: Nov | M8: Dec | N8: 2026 | O8: % Total Rev | R8: Input Method | S8: "Even" spread | T8: Growth % | U8: Jan | V8: Feb | W8: Mar | X8: Apr | Y8: May | Z8: Jun | AA8: Jul | AB8: Aug | AC8: Sep | AD8: Oct | AE8: Nov | AF8: Dec | AG8: 2027 | AH8: % Total Rev | AJ8: Fav / (Unfav)
A9: Ordinary Income/Expense
A10: Income
A11: 4000 - Sales
A12: 4100 - Subscription/Platform Fees | B12: 0 | C12: 0 | D12: 0 | E12: 0 | F12: 0 | G12: 0 | H12: 0 | I12: 0 | N12: =SUM(B12:M12) -> 0 | O12: =IFERROR(N12/N$16,"") | R12: Even | T12: 0.05 | U12: =IF($R12="Manual","",IFERROR(IF($R12="YOY Growth",$N12*(1+$T12)/12,$S12/12),"")) -> 0 | V12: =IF($R12="Manual","",IFERROR(IF($R12="YOY Growth",$N12*(1+$T12)/12,$S12/12),"")) -> 0 | W12: =IF($R12="Manual","",IFERROR(IF($R12="YOY Growth",$N12*(1+$T12)/12,$S12/12),"")) -> 0 | X12: =IF($R12="Manual","",IFERROR(IF($R12="YOY Growth",$N12*(1+$T12)/12,$S12/12),"")) -> 0 | Y12: =IF($R12="Manual","",IFERROR(IF($R12="YOY Growth",$N12*(1+$T12)/12,$S12/12),"")) -> 0 | Z12: =IF($R12="Manual","",IFERROR(IF($R12="YOY Growth",$N12*(1+$T12)/12,$S12/12),"")) -> 0 | AA12: =IF($R12="Manual","",IFERROR(IF($R12="YOY Growth",$N12*(1+$T12)/12,$S12/12),"")) -> 0 | AB12: =IF($R12="Manual","",IFERROR(IF($R12="YOY Growth",$N12*(1+$T12)/12,$S12/12),"")) -> 0 | ... AF12: =IF($R12="Manual","",IFERROR(IF($R12="YOY Growth",$N12*(1+$T12)/12,$S12/12),"")) -> 0 | AG12: =SUM(U12:AF12) -> 0 | AH12: =IFERROR(AG12/AG$16,"") | AJ12: =AG12-N12 -> 0
A13: 4500 - Implementation Fees | B13: 0 | C13: 0 | D13: 0 | E13: 0 | F13: 0 | G13: 0 | H13: 0 | I13: 0 | N13: =SUM(B13:M13) -> 0 | O13: =IFERROR(N13/N$16,"") | R13: Even | S13: 0 | T13: 0.05 | U13: =IF($R13="Manual","",IFERROR(IF($R13="YOY Growth",$N13*(1+$T13)/12,$S13/12),"")) -> 0 | V13: =IF($R13="Manual","",IFERROR(IF($R13="YOY Growth",$N13*(1+$T13)/12,$S13/12),"")) -> 0 | W13: =IF($R13="Manual","",IFERROR(IF($R13="YOY Growth",$N13*(1+$T13)/12,$S13/12),"")) -> 0 | X13: =IF($R13="Manual","",IFERROR(IF($R13="YOY Growth",$N13*(1+$T13)/12,$S13/12),"")) -> 0 | Y13: =IF($R13="Manual","",IFERROR(IF($R13="YOY Growth",$N13*(1+$T13)/12,$S13/12),"")) -> 0 | Z13: =IF($R13="Manual","",IFERROR(IF($R13="YOY Growth",$N13*(1+$T13)/12,$S13/12),"")) -> 0 | AA13: =IF($R13="Manual","",IFERROR(IF($R13="YOY Growth",$N13*(1+$T13)/12,$S13/12),"")) -> 0 | AB13: =IF($R13="Manual","",IFERROR(IF($R13="YOY Growth",$N13*(1+$T13)/12,$S13/12),"")) -> 0 | ... AF13: =IF($R13="Manual","",IFERROR(IF($R13="YOY Growth",$N13*(1+$T13)/12,$S13/12),"")) -> 0 | AG13: =SUM(U13:AF13) -> 0 | AH13: =IFERROR(AG13/AG$16,"") | AJ13: =AG13-N13 -> 0
A14: Total - 4000 - Sales | B14: =SUM(B12:B13) -> 0 | C14: =SUM(C12:C13) -> 0 | D14: =SUM(D12:D13) -> 0 | E14: =SUM(E12:E13) -> 0 | F14: =SUM(F12:F13) -> 0 | G14: =SUM(G12:G13) -> 0 | H14: =SUM(H12:H13) -> 0 | I14: =SUM(I12:I13) -> 0 | ... M14: =SUM(M12:M13) -> 0 | N14: =SUM(B14:M14) -> 0 | O14: =SUM(O12:O13) -> 0 | U14: =SUM(U12:U13) -> 0 | V14: =SUM(V12:V13) -> 0 | W14: =SUM(W12:W13) -> 0 | X14: =SUM(X12:X13) -> 0 | Y14: =SUM(Y12:Y13) -> 0 | Z14: =SUM(Z12:Z13) -> 0 | AA14: =SUM(AA12:AA13) -> 0 | AB14: =SUM(AB12:AB13) -> 0 | ... AF14: =SUM(AF12:AF13) -> 0 | AG14: =SUM(U14:AF14) -> 0 | AH14: =SUM(AH12:AH13) -> 0 | AJ14: =AG14-N14 -> 0
A15: 4900 - One-Time Revenue | B15: 0 | C15: 0 | D15: 0 | E15: 0 | F15: 0 | G15: 0 | H15: 0 | I15: 0 | N15: =SUM(B15:M15) -> 0 | O15: =IFERROR(N15/N$16,"") | R15: Even | S15: 0 | T15: 0.05 | U15: =IF($R15="Manual","",IFERROR(IF($R15="YOY Growth",$N15*(1+$T15)/12,$S15/12),"")) -> 0 | V15: =IF($R15="Manual","",IFERROR(IF($R15="YOY Growth",$N15*(1+$T15)/12,$S15/12),"")) -> 0 | W15: =IF($R15="Manual","",IFERROR(IF($R15="YOY Growth",$N15*(1+$T15)/12,$S15/12),"")) -> 0 | X15: =IF($R15="Manual","",IFERROR(IF($R15="YOY Growth",$N15*(1+$T15)/12,$S15/12),"")) -> 0 | Y15: =IF($R15="Manual","",IFERROR(IF($R15="YOY Growth",$N15*(1+$T15)/12,$S15/12),"")) -> 0 | Z15: =IF($R15="Manual","",IFERROR(IF($R15="YOY Growth",$N15*(1+$T15)/12,$S15/12),"")) -> 0 | AA15: =IF($R15="Manual","",IFERROR(IF($R15="YOY Growth",$N15*(1+$T15)/12,$S15/12),"")) -> 0 | AB15: =IF($R15="Manual","",IFERROR(IF($R15="YOY Growth",$N15*(1+$T15)/12,$S15/12),"")) -> 0 | ... AF15: =IF($R15="Manual","",IFERROR(IF($R15="YOY Growth",$N15*(1+$T15)/12,$S15/12),"")) -> 0 | AG15: =SUM(U15:AF15) -> 0 | AH15: =IFERROR(AG15/AG$16,"") | AJ15: =AG15-N15 -> 0
A16: Total - Income | B16: =B14+B15 -> 0 | C16: =C14+C15 -> 0 | D16: =D14+D15 -> 0 | E16: =E14+E15 -> 0 | F16: =F14+F15 -> 0 | G16: =G14+G15 -> 0 | H16: =H14+H15 -> 0 | I16: =I14+I15 -> 0 | ... M16: =M14+M15 -> 0 | N16: =SUM(B16:M16) -> 0 | O16: =SUM(O14:O15) -> 0 | U16: =U14+U15 -> 0 | V16: =V14+V15 -> 0 | W16: =W14+W15 -> 0 | X16: =X14+X15 -> 0 | Y16: =Y14+Y15 -> 0 | Z16: =Z14+Z15 -> 0 | AA16: =AA14+AA15 -> 0 | AB16: =AB14+AB15 -> 0 | ... AF16: =AF14+AF15 -> 0 | AG16: =SUM(U16:AF16) -> 0 | AH16: =SUM(AH14:AH15) -> 0 | AJ16: =AG16-N16 -> 0
A17: Cost Of Sales
A18: 5000 - Robot Production and Deployment
A19: 5010 - SlipBot Depreciation | B19: 0 | C19: 0 | D19: 0 | E19: 0 | F19: 0 | G19: 0 | H19: 0 | I19: 0 | N19: =SUM(B19:M19) -> 0 | O19: =IFERROR(N19/N$16,"") | R19: Even | S19: 0 | T19: 0.05 | U19: =IF($R19="Manual","",IFERROR(IF($R19="YOY Growth",$N19*(1+$T19)/12,$S19/12),"")) -> 0 | V19: =IF($R19="Manual","",IFERROR(IF($R19="YOY Growth",$N19*(1+$T19)/12,$S19/12),"")) -> 0 | W19: =IF($R19="Manual","",IFERROR(IF($R19="YOY Growth",$N19*(1+$T19)/12,$S19/12),"")) -> 0 | X19: =IF($R19="Manual","",IFERROR(IF($R19="YOY Growth",$N19*(1+$T19)/12,$S19/12),"")) -> 0 | Y19: =IF($R19="Manual","",IFERROR(IF($R19="YOY Growth",$N19*(1+$T19)/12,$S19/12),"")) -> 0 | Z19: =IF($R19="Manual","",IFERROR(IF($R19="YOY Growth",$N19*(1+$T19)/12,$S19/12),"")) -> 0 | AA19: =IF($R19="Manual","",IFERROR(IF($R19="YOY Growth",$N19*(1+$T19)/12,$S19/12),"")) -> 0 | AB19: =IF($R19="Manual","",IFERROR(IF($R19="YOY Growth",$N19*(1+$T19)/12,$S19/12),"")) -> 0 | ... AF19: =IF($R19="Manual","",IFERROR(IF($R19="YOY Growth",$N19*(1+$T19)/12,$S19/12),"")) -> 0 | AG19: =SUM(U19:AF19) -> 0 | AH19: =IFERROR(AG19/AG$16,"") | AJ19: =N19-AG19 -> 0
A20: 5011 - SlipLift Depreciation | B20: 0 | C20: 0 | D20: 0 | E20: 0 | F20: 0 | G20: 0 | H20: 0 | I20: 0 | N20: =SUM(B20:M20) -> 0 | O20: =IFERROR(N20/N$16,"") | R20: Even | S20: 0 | T20: 0.05 | U20: =IF($R20="Manual","",IFERROR(IF($R20="YOY Growth",$N20*(1+$T20)/12,$S20/12),"")) -> 0 | V20: =IF($R20="Manual","",IFERROR(IF($R20="YOY Growth",$N20*(1+$T20)/12,$S20/12),"")) -> 0 | W20: =IF($R20="Manual","",IFERROR(IF($R20="YOY Growth",$N20*(1+$T20)/12,$S20/12),"")) -> 0 | X20: =IF($R20="Manual","",IFERROR(IF($R20="YOY Growth",$N20*(1+$T20)/12,$S20/12),"")) -> 0 | Y20: =IF($R20="Manual","",IFERROR(IF($R20="YOY Growth",$N20*(1+$T20)/12,$S20/12),"")) -> 0 | Z20: =IF($R20="Manual","",IFERROR(IF($R20="YOY Growth",$N20*(1+$T20)/12,$S20/12),"")) -> 0 | AA20: =IF($R20="Manual","",IFERROR(IF($R20="YOY Growth",$N20*(1+$T20)/12,$S20/12),"")) -> 0 | AB20: =IF($R20="Manual","",IFERROR(IF($R20="YOY Growth",$N20*(1+$T20)/12,$S20/12),"")) -> 0 | ... AF20: =IF($R20="Manual","",IFERROR(IF($R20="YOY Growth",$N20*(1+$T20)/12,$S20/12),"")) -> 0 | AG20: =SUM(U20:AF20) -> 0 | AH20: =IFERROR(AG20/AG$16,"") | AJ20: =N20-AG20 -> 0
A21: 5012 - SlipCarrier Depreciation | B21: 0 | C21: 0 | D21: 0 | E21: 0 | F21: 0 | G21: 0 | H21: 0 | I21: 0 | N21: =SUM(B21:M21) -> 0 | O21: =IFERROR(N21/N$16,"") | R21: Even | S21: 0 | T21: 0.05 | U21: =IF($R21="Manual","",IFERROR(IF($R21="YOY Growth",$N21*(1+$T21)/12,$S21/12),"")) -> 0 | V21: =IF($R21="Manual","",IFERROR(IF($R21="YOY Growth",$N21*(1+$T21)/12,$S21/12),"")) -> 0 | W21: =IF($R21="Manual","",IFERROR(IF($R21="YOY Growth",$N21*(1+$T21)/12,$S21/12),"")) -> 0 | X21: =IF($R21="Manual","",IFERROR(IF($R21="YOY Growth",$N21*(1+$T21)/12,$S21/12),"")) -> 0 | Y21: =IF($R21="Manual","",IFERROR(IF($R21="YOY Growth",$N21*(1+$T21)/12,$S21/12),"")) -> 0 | Z21: =IF($R21="Manual","",IFERROR(IF($R21="YOY Growth",$N21*(1+$T21)/12,$S21/12),"")) -> 0 | AA21: =IF($R21="Manual","",IFERROR(IF($R21="YOY Growth",$N21*(1+$T21)/12,$S21/12),"")) -> 0 | AB21: =IF($R21="Manual","",IFERROR(IF($R21="YOY Growth",$N21*(1+$T21)/12,$S21/12),"")) -> 0 | ... AF21: =IF($R21="Manual","",IFERROR(IF($R21="YOY Growth",$N21*(1+$T21)/12,$S21/12),"")) -> 0 | AG21: =SUM(U21:AF21) -> 0 | AH21: =IFERROR(AG21/AG$16,"") | AJ21: =N21-AG21 -> 0
A22: 5020 - Robot Peripherals Depreciation | B22: 0 | C22: 0 | D22: 0 | E22: 0 | F22: 0 | G22: 0 | H22: 0 | I22: 0 | N22: =SUM(B22:M22) -> 0 | O22: =IFERROR(N22/N$16,"") | R22: Even | S22: 0 | T22: 0.05 | U22: =IF($R22="Manual","",IFERROR(IF($R22="YOY Growth",$N22*(1+$T22)/12,$S22/12),"")) -> 0 | V22: =IF($R22="Manual","",IFERROR(IF($R22="YOY Growth",$N22*(1+$T22)/12,$S22/12),"")) -> 0 | W22: =IF($R22="Manual","",IFERROR(IF($R22="YOY Growth",$N22*(1+$T22)/12,$S22/12),"")) -> 0 | X22: =IF($R22="Manual","",IFERROR(IF($R22="YOY Growth",$N22*(1+$T22)/12,$S22/12),"")) -> 0 | Y22: =IF($R22="Manual","",IFERROR(IF($R22="YOY Growth",$N22*(1+$T22)/12,$S22/12),"")) -> 0 | Z22: =IF($R22="Manual","",IFERROR(IF($R22="YOY Growth",$N22*(1+$T22)/12,$S22/12),"")) -> 0 | AA22: =IF($R22="Manual","",IFERROR(IF($R22="YOY Growth",$N22*(1+$T22)/12,$S22/12),"")) -> 0 | AB22: =IF($R22="Manual","",IFERROR(IF($R22="YOY Growth",$N22*(1+$T22)/12,$S22/12),"")) -> 0 | ... AF22: =IF($R22="Manual","",IFERROR(IF($R22="YOY Growth",$N22*(1+$T22)/12,$S22/12),"")) -> 0 | AG22: =SUM(U22:AF22) -> 0 | AH22: =IFERROR(AG22/AG$16,"") | AJ22: =N22-AG22 -> 0
A23: 5025 - Freight and Delivery - Production (Summary)
A24: 5025 - Freight and Delivery - Production (Summary) | B24: 376 | C24: 850.7 | D24: 783.62 | E24: 1861.07 | F24: 0 | G24: 0 | H24: 0 | I24: 0 | J24: 0 | K24: 0 | L24: 0 | M24: 0 | N24: =SUM(B24:M24) -> 3871.39 | O24: =IFERROR(N24/N$16,"") | R24: Even | S24: 0 | T24: 0.05 | U24: =IF($R24="Manual","",IFERROR(IF($R24="YOY Growth",$N24*(1+$T24)/12,$S24/12),"")) -> 0 | V24: =IF($R24="Manual","",IFERROR(IF($R24="YOY Growth",$N24*(1+$T24)/12,$S24/12),"")) -> 0 | W24: =IF($R24="Manual","",IFERROR(IF($R24="YOY Growth",$N24*(1+$T24)/12,$S24/12),"")) -> 0 | X24: =IF($R24="Manual","",IFERROR(IF($R24="YOY Growth",$N24*(1+$T24)/12,$S24/12),"")) -> 0 | Y24: =IF($R24="Manual","",IFERROR(IF($R24="YOY Growth",$N24*(1+$T24)/12,$S24/12),"")) -> 0 | Z24: =IF($R24="Manual","",IFERROR(IF($R24="YOY Growth",$N24*(1+$T24)/12,$S24/12),"")) -> 0 | AA24: =IF($R24="Manual","",IFERROR(IF($R24="YOY Growth",$N24*(1+$T24)/12,$S24/12),"")) -> 0 | AB24: =IF($R24="Manual","",IFERROR(IF($R24="YOY Growth",$N24*(1+$T24)/12,$S24/12),"")) -> 0 | ... AF24: =IF($R24="Manual","",IFERROR(IF($R24="YOY Growth",$N24*(1+$T24)/12,$S24/12),"")) -> 0 | AG24: =SUM(U24:AF24) -> 0 | AH24: =IFERROR(AG24/AG$16,"") | AJ24: =N24-AG24 -> 3871.39
A25: 5026 - Freight and Delivery - Production - Expedited | B25: 0 | C25: 0 | D25: 0 | E25: 261.8 | F25: 0 | G25: 0 | H25: 0 | I25: 0 | J25: 0 | K25: 0 | L25: 0 | M25: 0 | N25: =SUM(B25:M25) -> 261.8 | O25: =IFERROR(N25/N$16,"") | R25: Even | S25: 0 | T25: 0.05 | U25: =IF($R25="Manual","",IFERROR(IF($R25="YOY Growth",$N25*(1+$T25)/12,$S25/12),"")) -> 0 | V25: =IF($R25="Manual","",IFERROR(IF($R25="YOY Growth",$N25*(1+$T25)/12,$S25/12),"")) -> 0 | W25: =IF($R25="Manual","",IFERROR(IF($R25="YOY Growth",$N25*(1+$T25)/12,$S25/12),"")) -> 0 | X25: =IF($R25="Manual","",IFERROR(IF($R25="YOY Growth",$N25*(1+$T25)/12,$S25/12),"")) -> 0 | Y25: =IF($R25="Manual","",IFERROR(IF($R25="YOY Growth",$N25*(1+$T25)/12,$S25/12),"")) -> 0 | Z25: =IF($R25="Manual","",IFERROR(IF($R25="YOY Growth",$N25*(1+$T25)/12,$S25/12),"")) -> 0 | AA25: =IF($R25="Manual","",IFERROR(IF($R25="YOY Growth",$N25*(1+$T25)/12,$S25/12),"")) -> 0 | AB25: =IF($R25="Manual","",IFERROR(IF($R25="YOY Growth",$N25*(1+$T25)/12,$S25/12),"")) -> 0 | ... AF25: =IF($R25="Manual","",IFERROR(IF($R25="YOY Growth",$N25*(1+$T25)/12,$S25/12),"")) -> 0 | AG25: =SUM(U25:AF25) -> 0 | AH25: =IFERROR(AG25/AG$16,"") | AJ25: =N25-AG25 -> 261.8
A26: 5027 - Freight and Delivery - Production - Standard | B26: 0 | C26: 0 | D26: 0 | E26: 348.38 | F26: 79.47 | G26: 0 | H26: 0 | I26: 250 | J26: 0 | K26: 0 | L26: 0 | M26: 0 | N26: =SUM(B26:M26) -> 677.85 | O26: =IFERROR(N26/N$16,"") | R26: Even | S26: 0 | T26: 0.05 | U26: =IF($R26="Manual","",IFERROR(IF($R26="YOY Growth",$N26*(1+$T26)/12,$S26/12),"")) -> 0 | V26: =IF($R26="Manual","",IFERROR(IF($R26="YOY Growth",$N26*(1+$T26)/12,$S26/12),"")) -> 0 | W26: =IF($R26="Manual","",IFERROR(IF($R26="YOY Growth",$N26*(1+$T26)/12,$S26/12),"")) -> 0 | X26: =IF($R26="Manual","",IFERROR(IF($R26="YOY Growth",$N26*(1+$T26)/12,$S26/12),"")) -> 0 | Y26: =IF($R26="Manual","",IFERROR(IF($R26="YOY Growth",$N26*(1+$T26)/12,$S26/12),"")) -> 0 | Z26: =IF($R26="Manual","",IFERROR(IF($R26="YOY Growth",$N26*(1+$T26)/12,$S26/12),"")) -> 0 | AA26: =IF($R26="Manual","",IFERROR(IF($R26="YOY Growth",$N26*(1+$T26)/12,$S26/12),"")) -> 0 | AB26: =IF($R26="Manual","",IFERROR(IF($R26="YOY Growth",$N26*(1+$T26)/12,$S26/12),"")) -> 0 | ... AF26: =IF($R26="Manual","",IFERROR(IF($R26="YOY Growth",$N26*(1+$T26)/12,$S26/12),"")) -> 0 | AG26: =SUM(U26:AF26) -> 0 | AH26: =IFERROR(AG26/AG$16,"") | AJ26: =N26-AG26 -> 677.85
A27: Total - 5025 - Freight and Delivery - Production (Summary) | B27: =SUM(B24:B26) -> 376 | C27: =SUM(C24:C26) -> 850.7 | D27: =SUM(D24:D26) -> 783.62 | E27: =SUM(E24:E26) -> 2471.25 | F27: =SUM(F24:F26) -> 79.47 | G27: =SUM(G24:G26) -> 0 | H27: =SUM(H24:H26) -> 0 | I27: =SUM(I24:I26) -> 250 | ... M27: =SUM(M24:M26) -> 0 | N27: =SUM(B27:M27) -> 4811.04 | O27: =IFERROR(N27/N$16,"") | U27: =SUM(U24:U26) -> 0 | V27: =SUM(V24:V26) -> 0 | W27: =SUM(W24:W26) -> 0 | X27: =SUM(X24:X26) -> 0 | Y27: =SUM(Y24:Y26) -> 0 | Z27: =SUM(Z24:Z26) -> 0 | AA27: =SUM(AA24:AA26) -> 0 | AB27: =SUM(AB24:AB26) -> 0 | ... AF27: =SUM(AF24:AF26) -> 0 | AG27: =SUM(U27:AF27) -> 0 | AH27: =IFERROR(AG27/AG$16,"") | AJ27: =N27-AG27 -> 4811.04
A28: 5030 - Production Tools and Supplies | B28: 0 | C28: 0 | D28: 0 | E28: 2186.18 | F28: 0 | G28: 0 | H28: 117.53 | I28: 0 | J28: 0 | K28: 0 | L28: 0 | M28: 0 | N28: =SUM(B28:M28) -> 2303.71 | O28: =IFERROR(N28/N$16,"") | R28: Even | S28: 0 | T28: 0.05 | U28: =IF($R28="Manual","",IFERROR(IF($R28="YOY Growth",$N28*(1+$T28)/12,$S28/12),"")) -> 0 | V28: =IF($R28="Manual","",IFERROR(IF($R28="YOY Growth",$N28*(1+$T28)/12,$S28/12),"")) -> 0 | W28: =IF($R28="Manual","",IFERROR(IF($R28="YOY Growth",$N28*(1+$T28)/12,$S28/12),"")) -> 0 | X28: =IF($R28="Manual","",IFERROR(IF($R28="YOY Growth",$N28*(1+$T28)/12,$S28/12),"")) -> 0 | Y28: =IF($R28="Manual","",IFERROR(IF($R28="YOY Growth",$N28*(1+$T28)/12,$S28/12),"")) -> 0 | Z28: =IF($R28="Manual","",IFERROR(IF($R28="YOY Growth",$N28*(1+$T28)/12,$S28/12),"")) -> 0 | AA28: =IF($R28="Manual","",IFERROR(IF($R28="YOY Growth",$N28*(1+$T28)/12,$S28/12),"")) -> 0 | AB28: =IF($R28="Manual","",IFERROR(IF($R28="YOY Growth",$N28*(1+$T28)/12,$S28/12),"")) -> 0 | ... AF28: =IF($R28="Manual","",IFERROR(IF($R28="YOY Growth",$N28*(1+$T28)/12,$S28/12),"")) -> 0 | AG28: =SUM(U28:AF28) -> 0 | AH28: =IFERROR(AG28/AG$16,"") | AJ28: =N28-AG28 -> 2303.71
A29: 5040 - Freight & Delivery - Deployment | B29: 7000 | C29: 5000.95 | D29: 3522.7 | E29: 3294.47 | F29: 0 | G29: 122.59 | H29: 0 | I29: 3240.99 | J29: 15000 | K29: 10000 | L29: 5000 | M29: 5000 | N29: =SUM(B29:M29) -> 57181.7 | O29: =IFERROR(N29/N$16,"") | R29: Manual | S29: 0 | T29: 0.05 | U29: ='Fld Maint Budget'!B89 -> 45000 | V29: ='Fld Maint Budget'!C89 -> 20000 | W29: ='Fld Maint Budget'!D89 -> 0 | X29: ='Fld Maint Budget'!E89 -> 60000 | Y29: ='Fld Maint Budget'!F89 -> 45000 | Z29: ='Fld Maint Budget'!G89 -> 70000 | AA29: ='Fld Maint Budget'!H89 -> 55000 | AB29: ='Fld Maint Budget'!I89 -> 65000 | ... AF29: ='Fld Maint Budget'!M89 -> 110000 | AG29: =SUM(U29:AF29) -> 765000 | AH29: =IFERROR(AG29/AG$16,"") | AJ29: =N29-AG29 -> -707818.3
A30: 5050 - Travel - Deployment | B30: 0 | C30: 0 | D30: 0 | E30: 0 | F30: 0 | G30: 0 | H30: 911.81 | I30: 1772.23 | J30: 0 | K30: 0 | L30: 0 | M30: 0 | N30: =SUM(B30:M30) -> 2684.04 | O30: =IFERROR(N30/N$16,"") | R30: Manual | S30: 0 | T30: 0.05 | U30: ='Fld Maint Budget'!B90 -> 2279.7 | V30: ='Fld Maint Budget'!C90 -> 1519.8 | W30: ='Fld Maint Budget'!D90 -> 0 | X30: ='Fld Maint Budget'!E90 -> 3495.54 | Y30: ='Fld Maint Budget'!F90 -> 2735.64 | Z30: ='Fld Maint Budget'!G90 -> 3951.48 | AA30: ='Fld Maint Budget'!H90 -> 3495.54 | AB30: ='Fld Maint Budget'!I90 -> 4255.44 | ... AF30: ='Fld Maint Budget'!M90 -> 6991.08 | AG30: =SUM(U30:AF30) -> 46353.9 | AH30: =IFERROR(AG30/AG$16,"") | AJ30: =N30-AG30 -> -43669.86
A31: 5060 - Meals - Deployment | B31: 0 | C31: 0 | D31: 0 | E31: 0 | F31: 0 | G31: 20.14 | H31: 0 | I31: 528.6 | J31: 0 | K31: 0 | L31: 0 | M31: 0 | N31: =SUM(B31:M31) -> 548.74 | O31: =IFERROR(N31/N$16,"") | R31: Even | S31: 0 | T31: 0.05 | U31: =IF($R31="Manual","",IFERROR(IF($R31="YOY Growth",$N31*(1+$T31)/12,$S31/12),"")) -> 0 | V31: =IF($R31="Manual","",IFERROR(IF($R31="YOY Growth",$N31*(1+$T31)/12,$S31/12),"")) -> 0 | W31: =IF($R31="Manual","",IFERROR(IF($R31="YOY Growth",$N31*(1+$T31)/12,$S31/12),"")) -> 0 | X31: =IF($R31="Manual","",IFERROR(IF($R31="YOY Growth",$N31*(1+$T31)/12,$S31/12),"")) -> 0 | Y31: =IF($R31="Manual","",IFERROR(IF($R31="YOY Growth",$N31*(1+$T31)/12,$S31/12),"")) -> 0 | Z31: =IF($R31="Manual","",IFERROR(IF($R31="YOY Growth",$N31*(1+$T31)/12,$S31/12),"")) -> 0 | AA31: =IF($R31="Manual","",IFERROR(IF($R31="YOY Growth",$N31*(1+$T31)/12,$S31/12),"")) -> 0 | AB31: =IF($R31="Manual","",IFERROR(IF($R31="YOY Growth",$N31*(1+$T31)/12,$S31/12),"")) -> 0 | ... AF31: =IF($R31="Manual","",IFERROR(IF($R31="YOY Growth",$N31*(1+$T31)/12,$S31/12),"")) -> 0 | AG31: =SUM(U31:AF31) -> 0 | AH31: =IFERROR(AG31/AG$16,"") | AJ31: =N31-AG31 -> 548.74
A32: 5100 - Labor Expense - Production
A33: 5110 - Salaries and Wages - Production | B33: 0 | C33: 0 | D33: 0 | E33: 0 | F33: 0 | G33: 0 | H33: 0 | I33: 0 | J33: 0 | K33: 0 | L33: 0 | M33: 0 | N33: =SUM(B33:M33) -> 0 | O33: =IFERROR(N33/N$16,"") | AG33: =SUM(U33:AF33) -> 0 | AH33: =IFERROR(AG33/AG$16,"") | AJ33: =N33-AG33 -> 0
A34: 5130 - Payroll Taxes - Production | B34: 0 | C34: 0 | D34: 0 | E34: 0 | F34: 0 | G34: 0 | H34: 0 | I34: 0 | J34: 0 | K34: 0 | L34: 0 | M34: 0 | N34: =SUM(B34:M34) -> 0 | O34: =IFERROR(N34/N$16,"") | AG34: =SUM(U34:AF34) -> 0 | AH34: =IFERROR(AG34/AG$16,"") | AJ34: =N34-AG34 -> 0
A35: 5140 - Benefits - Production | B35: 0 | C35: 0 | D35: 0 | E35: 0 | F35: 0 | G35: 0 | H35: 0 | I35: 0 | J35: 0 | K35: 0 | L35: 0 | M35: 0 | N35: =SUM(B35:M35) -> 0 | O35: =IFERROR(N35/N$16,"") | AG35: =SUM(U35:AF35) -> 0 | AH35: =IFERROR(AG35/AG$16,"") | AJ35: =N35-AG35 -> 0
A36: Total - 5100 - Labor Expense - Production | B36: =SUM(B33:B35) -> 0 | C36: =SUM(C33:C35) -> 0 | D36: =SUM(D33:D35) -> 0 | E36: =SUM(E33:E35) -> 0 | F36: =SUM(F33:F35) -> 0 | G36: =SUM(G33:G35) -> 0 | H36: =SUM(H33:H35) -> 0 | I36: =SUM(I33:I35) -> 0 | ... M36: =SUM(M33:M35) -> 0 | N36: =SUM(B36:M36) -> 0 | O36: =IFERROR(N36/N$16,"") | U36: =SUM(U33:U35) -> 0 | V36: =SUM(V33:V35) -> 0 | W36: =SUM(W33:W35) -> 0 | X36: =SUM(X33:X35) -> 0 | Y36: =SUM(Y33:Y35) -> 0 | Z36: =SUM(Z33:Z35) -> 0 | AA36: =SUM(AA33:AA35) -> 0 | AB36: =SUM(AB33:AB35) -> 0 | ... AF36: =SUM(AF33:AF35) -> 0 | AG36: =SUM(U36:AF36) -> 0 | AH36: =IFERROR(AG36/AG$16,"") | AJ36: =N36-AG36 -> 0
A37: Total - 5000 - Robot Production and Deployment | B37: =B19+B22+B27+B28+B29+B30+B31+B36+B20+B21 -> 7376 | C37: =C19+C22+C27+C28+C29+C30+C31+C36+C20+C21 -> 5851.65 | D37: =D19+D22+D27+D28+D29+D30+D31+D36+D20+D21 -> 4306.32 | E37: =E19+E22+E27+E28+E29+E30+E31+E36+E20+E21 -> 7951.9 | F37: =F19+F22+F27+F28+F29+F30+F31+F36+F20+F21 -> 79.47 | G37: =G19+G22+G27+G28+G29+G30+G31+G36+G20+G21 -> 142.73 | H37: =H19+H22+H27+H28+H29+H30+H31+H36+H20+H21 -> 1029.34 | I37: =I19+I22+I27+I28+I29+I30+I31+I36+I20+I21 -> 5791.82 | ... M37: =M19+M22+M27+M28+M29+M30+M31+M36+M20+M21 -> 5000 | N37: =SUM(B37:M37) -> 67529.23 | O37: =IFERROR(N37/N$16,"") | U37: =U19+U22+U27+U28+U29+U30+U31+U36+U20+U21 -> 47279.7 | V37: =V19+V22+V27+V28+V29+V30+V31+V36+V20+V21 -> 21519.8 | W37: =W19+W22+W27+W28+W29+W30+W31+W36+W20+W21 -> 0 | X37: =X19+X22+X27+X28+X29+X30+X31+X36+X20+X21 -> 63495.54 | Y37: =Y19+Y22+Y27+Y28+Y29+Y30+Y31+Y36+Y20+Y21 -> 47735.64 | Z37: =Z19+Z22+Z27+Z28+Z29+Z30+Z31+Z36+Z20+Z21 -> 73951.48 | AA37: =AA19+AA22+AA27+AA28+AA29+AA30+AA31+AA36+AA20+AA21 -> 58495.54 | AB37: =AB19+AB22+AB27+AB28+AB29+AB30+AB31+AB36+AB20+AB21 -> 69255.44 | ... AF37: =AF19+AF22+AF27+AF28+AF29+AF30+AF31+AF36+AF20+AF21 -> 116991.08 | AG37: =SUM(U37:AF37) -> 811353.9 | AH37: =IFERROR(AG37/AG$16,"") | AJ37: =N37-AG37 -> -743824.67
A38: 5015 - Supplies and Materials | B38: 0 | C38: 0 | D38: 0 | E38: 0 | F38: 0 | G38: -352.47 | H38: 0 | I38: 0 | J38: 0 | K38: 0 | L38: 0 | M38: 0 | N38: =SUM(B38:M38) -> -352.47 | O38: =IFERROR(N38/N$16,"") | R38: Even | S38: 0 | T38: 0.05 | U38: =IF($R38="Manual","",IFERROR(IF($R38="YOY Growth",$N38*(1+$T38)/12,$S38/12),"")) -> 0 | V38: =IF($R38="Manual","",IFERROR(IF($R38="YOY Growth",$N38*(1+$T38)/12,$S38/12),"")) -> 0 | W38: =IF($R38="Manual","",IFERROR(IF($R38="YOY Growth",$N38*(1+$T38)/12,$S38/12),"")) -> 0 | X38: =IF($R38="Manual","",IFERROR(IF($R38="YOY Growth",$N38*(1+$T38)/12,$S38/12),"")) -> 0 | Y38: =IF($R38="Manual","",IFERROR(IF($R38="YOY Growth",$N38*(1+$T38)/12,$S38/12),"")) -> 0 | Z38: =IF($R38="Manual","",IFERROR(IF($R38="YOY Growth",$N38*(1+$T38)/12,$S38/12),"")) -> 0 | AA38: =IF($R38="Manual","",IFERROR(IF($R38="YOY Growth",$N38*(1+$T38)/12,$S38/12),"")) -> 0 | AB38: =IF($R38="Manual","",IFERROR(IF($R38="YOY Growth",$N38*(1+$T38)/12,$S38/12),"")) -> 0 | ... AF38: =IF($R38="Manual","",IFERROR(IF($R38="YOY Growth",$N38*(1+$T38)/12,$S38/12),"")) -> 0 | AG38: =SUM(U38:AF38) -> 0 | AH38: =IFERROR(AG38/AG$16,"") | AJ38: =N38-AG38 -> -352.47
A39: 5028 - Duties & Tariffs - Production | B39: 0 | C39: 0 | D39: 0 | E39: 0 | F39: 0 | G39: 0 | H39: 0 | I39: 0 | J39: 0 | K39: 0 | L39: 0 | M39: 0 | N39: =SUM(B39:M39) -> 0 | O39: =IFERROR(N39/N$16,"") | R39: Even | S39: 0 | T39: 0.05 | U39: =IF($R39="Manual","",IFERROR(IF($R39="YOY Growth",$N39*(1+$T39)/12,$S39/12),"")) -> 0 | V39: =IF($R39="Manual","",IFERROR(IF($R39="YOY Growth",$N39*(1+$T39)/12,$S39/12),"")) -> 0 | W39: =IF($R39="Manual","",IFERROR(IF($R39="YOY Growth",$N39*(1+$T39)/12,$S39/12),"")) -> 0 | X39: =IF($R39="Manual","",IFERROR(IF($R39="YOY Growth",$N39*(1+$T39)/12,$S39/12),"")) -> 0 | Y39: =IF($R39="Manual","",IFERROR(IF($R39="YOY Growth",$N39*(1+$T39)/12,$S39/12),"")) -> 0 | Z39: =IF($R39="Manual","",IFERROR(IF($R39="YOY Growth",$N39*(1+$T39)/12,$S39/12),"")) -> 0 | AA39: =IF($R39="Manual","",IFERROR(IF($R39="YOY Growth",$N39*(1+$T39)/12,$S39/12),"")) -> 0 | AB39: =IF($R39="Manual","",IFERROR(IF($R39="YOY Growth",$N39*(1+$T39)/12,$S39/12),"")) -> 0 | ... AF39: =IF($R39="Manual","",IFERROR(IF($R39="YOY Growth",$N39*(1+$T39)/12,$S39/12),"")) -> 0 | AG39: =SUM(U39:AF39) -> 0 | AH39: =IFERROR(AG39/AG$16,"") | AJ39: =N39-AG39 -> 0
A40: 5029 - Processing Fee - Production | B40: 0 | C40: 0 | D40: 0 | E40: 0 | F40: 0 | G40: 0 | H40: 0 | I40: 0 | J40: 0 | K40: 0 | L40: 0 | M40: 0 | N40: =SUM(B40:M40) -> 0 | O40: =IFERROR(N40/N$16,"") | R40: Even | S40: 0 | T40: 0.05 | U40: =IF($R40="Manual","",IFERROR(IF($R40="YOY Growth",$N40*(1+$T40)/12,$S40/12),"")) -> 0 | V40: =IF($R40="Manual","",IFERROR(IF($R40="YOY Growth",$N40*(1+$T40)/12,$S40/12),"")) -> 0 | W40: =IF($R40="Manual","",IFERROR(IF($R40="YOY Growth",$N40*(1+$T40)/12,$S40/12),"")) -> 0 | X40: =IF($R40="Manual","",IFERROR(IF($R40="YOY Growth",$N40*(1+$T40)/12,$S40/12),"")) -> 0 | Y40: =IF($R40="Manual","",IFERROR(IF($R40="YOY Growth",$N40*(1+$T40)/12,$S40/12),"")) -> 0 | Z40: =IF($R40="Manual","",IFERROR(IF($R40="YOY Growth",$N40*(1+$T40)/12,$S40/12),"")) -> 0 | AA40: =IF($R40="Manual","",IFERROR(IF($R40="YOY Growth",$N40*(1+$T40)/12,$S40/12),"")) -> 0 | AB40: =IF($R40="Manual","",IFERROR(IF($R40="YOY Growth",$N40*(1+$T40)/12,$S40/12),"")) -> 0 | ... AF40: =IF($R40="Manual","",IFERROR(IF($R40="YOY Growth",$N40*(1+$T40)/12,$S40/12),"")) -> 0 | AG40: =SUM(U40:AF40) -> 0 | AH40: =IFERROR(AG40/AG$16,"") | AJ40: =N40-AG40 -> 0
A41: 5070 - Scrap | B41: 0 | C41: 0 | D41: 0 | E41: 0 | F41: 0 | G41: 0 | H41: 0 | I41: 0 | N41: =SUM(B41:M41) -> 0 | O41: =IFERROR(N41/N$16,"") | R41: Even | S41: 0 | T41: 0.05 | U41: =IF($R41="Manual","",IFERROR(IF($R41="YOY Growth",$N41*(1+$T41)/12,$S41/12),"")) -> 0 | V41: =IF($R41="Manual","",IFERROR(IF($R41="YOY Growth",$N41*(1+$T41)/12,$S41/12),"")) -> 0 | W41: =IF($R41="Manual","",IFERROR(IF($R41="YOY Growth",$N41*(1+$T41)/12,$S41/12),"")) -> 0 | X41: =IF($R41="Manual","",IFERROR(IF($R41="YOY Growth",$N41*(1+$T41)/12,$S41/12),"")) -> 0 | Y41: =IF($R41="Manual","",IFERROR(IF($R41="YOY Growth",$N41*(1+$T41)/12,$S41/12),"")) -> 0 | Z41: =IF($R41="Manual","",IFERROR(IF($R41="YOY Growth",$N41*(1+$T41)/12,$S41/12),"")) -> 0 | AA41: =IF($R41="Manual","",IFERROR(IF($R41="YOY Growth",$N41*(1+$T41)/12,$S41/12),"")) -> 0 | AB41: =IF($R41="Manual","",IFERROR(IF($R41="YOY Growth",$N41*(1+$T41)/12,$S41/12),"")) -> 0 | ... AF41: =IF($R41="Manual","",IFERROR(IF($R41="YOY Growth",$N41*(1+$T41)/12,$S41/12),"")) -> 0 | AG41: =SUM(U41:AF41) -> 0 | AH41: =IFERROR(AG41/AG$16,"") | AJ41: =N41-AG41 -> 0
A42: 5201 - Inventory Adjustments | B42: 0 | C42: 0 | D42: 0 | E42: 0 | F42: 0 | G42: 0 | H42: 0 | I42: 0 | J42: 0 | K42: 0 | L42: 0 | M42: 0 | N42: =SUM(B42:M42) -> 0 | O42: =IFERROR(N42/N$16,"") | R42: Even | S42: 0 | T42: 0.05 | U42: =IF($R42="Manual","",IFERROR(IF($R42="YOY Growth",$N42*(1+$T42)/12,$S42/12),"")) -> 0 | V42: =IF($R42="Manual","",IFERROR(IF($R42="YOY Growth",$N42*(1+$T42)/12,$S42/12),"")) -> 0 | W42: =IF($R42="Manual","",IFERROR(IF($R42="YOY Growth",$N42*(1+$T42)/12,$S42/12),"")) -> 0 | X42: =IF($R42="Manual","",IFERROR(IF($R42="YOY Growth",$N42*(1+$T42)/12,$S42/12),"")) -> 0 | Y42: =IF($R42="Manual","",IFERROR(IF($R42="YOY Growth",$N42*(1+$T42)/12,$S42/12),"")) -> 0 | Z42: =IF($R42="Manual","",IFERROR(IF($R42="YOY Growth",$N42*(1+$T42)/12,$S42/12),"")) -> 0 | AA42: =IF($R42="Manual","",IFERROR(IF($R42="YOY Growth",$N42*(1+$T42)/12,$S42/12),"")) -> 0 | AB42: =IF($R42="Manual","",IFERROR(IF($R42="YOY Growth",$N42*(1+$T42)/12,$S42/12),"")) -> 0 | ... AF42: =IF($R42="Manual","",IFERROR(IF($R42="YOY Growth",$N42*(1+$T42)/12,$S42/12),"")) -> 0 | AG42: =SUM(U42:AF42) -> 0 | AH42: =IFERROR(AG42/AG$16,"") | AJ42: =N42-AG42 -> 0
A43: 5300 - Maintenance
A44: 5310 - Contractors - Field | B44: 0 | C44: 0 | D44: 0 | E44: 0 | F44: 19808 | G44: 10009 | H44: 10968.52 | I44: 6116.47 | J44: 40350 | K44: 44270 | L44: 48190 | M44: 52110 | N44: =SUM(B44:M44) -> 231821.99 | O44: =IFERROR(N44/N$16,"") | R44: Manual | T44: 0.05 | U44: ='Fld Maint Budget'!B91 -> 37614 | V44: ='Fld Maint Budget'!C91 -> 37614 | W44: ='Fld Maint Budget'!D91 -> 50004 | X44: ='Fld Maint Budget'!E91 -> 50004 | Y44: ='Fld Maint Budget'!F91 -> 50004 | Z44: ='Fld Maint Budget'!G91 -> 50004 | AA44: ='Fld Maint Budget'!H91 -> 50004 | AB44: ='Fld Maint Budget'!I91 -> 50004 | ... AF44: ='Fld Maint Budget'!M91 -> 50004 | AG44: =SUM(U44:AF44) -> 575268 | AH44: =IFERROR(AG44/AG$16,"") | AJ44: =N44-AG44 -> -343446.01
A45: 5320 - Freight & Delivery - Maintenance | B45: 5823.29 | C45: 256.47 | D45: 1327.17 | E45: 6164.18 | F45: 4983.81 | G45: 7888.65 | H45: 14179.16 | I45: 11260.12 | J45: 5750 | K45: 6000 | L45: 6250 | M45: 6500 | N45: =SUM(B45:M45) -> 76382.85 | O45: =IFERROR(N45/N$16,"") | R45: Manual | S45: 0 | T45: 0.05 | U45: ='Fld Maint Budget'!B92 -> 5185.8217 | V45: ='Fld Maint Budget'!C92 -> 5561.3594 | W45: ='Fld Maint Budget'!D92 -> 5561.3594 | X45: ='Fld Maint Budget'!E92 -> 6594.0881 | Y45: ='Fld Maint Budget'!F92 -> 7251.2791 | Z45: ='Fld Maint Budget'!G92 -> 8190.1234 | AA45: ='Fld Maint Budget'!H92 -> 9035.0832 | AB45: ='Fld Maint Budget'!I92 -> 10067.812 | ... AF45: ='Fld Maint Budget'!M92 -> 15982.531 | AG45: =SUM(U45:AF45) -> 111800.84 | AH45: =IFERROR(AG45/AG$16,"") | AJ45: =N45-AG45 -> -35417.988
A46: 5330 - Maintenance Tools and Supplies | B46: 1378.29 | C46: 1054.59 | D46: 2655.82 | E46: 0 | F46: 1059.27 | G46: 334.92 | H46: 1237.14 | I46: 9400.74 | J46: 1500 | K46: 1500 | L46: 1500 | M46: 1500 | N46: =SUM(B46:M46) -> 23120.77 | O46: =IFERROR(N46/N$16,"") | R46: Manual | S46: 0 | T46: 0.05 | U46: ='Fld Maint Budget'!B93 -> 14024.02 | V46: ='Fld Maint Budget'!C93 -> 9524.02 | W46: ='Fld Maint Budget'!D93 -> 551.6 | X46: ='Fld Maint Budget'!E93 -> 21334.34 | Y46: ='Fld Maint Budget'!F93 -> 16972.24 | Z46: ='Fld Maint Budget'!G93 -> 24310.14 | AA46: ='Fld Maint Budget'!H93 -> 21775.62 | AB46: ='Fld Maint Budget'!I93 -> 26468.68 | ... AF46: ='Fld Maint Budget'!M93 -> 43578.82 | AG46: =SUM(U46:AF46) -> 288069.36 | AH46: =IFERROR(AG46/AG$16,"") | AJ46: =N46-AG46 -> -264948.59
A47: 5340 - Spare Parts | B47: 13329.1 | C47: 5064.23 | D47: 58626.27 | E47: 12810.6 | F47: 28158.41 | G47: 19000.31 | H47: 10810.67 | I47: -8095.66 | J47: 28000 | K47: 28000 | L47: 30000 | M47: 30000 | N47: =SUM(B47:M47) -> 255703.93 | O47: =IFERROR(N47/N$16,"") | R47: Manual | S47: 0 | T47: 0.05 | U47: ='Fld Maint Budget'!B94 -> 48713.618 | V47: ='Fld Maint Budget'!C94 -> 55799.235 | W47: ='Fld Maint Budget'!D94 -> 55799.235 | X47: ='Fld Maint Budget'!E94 -> 75284.682 | Y47: ='Fld Maint Budget'!F94 -> 87684.512 | Z47: ='Fld Maint Budget'!G94 -> 105398.55 | AA47: ='Fld Maint Budget'!H94 -> 121341.19 | AB47: ='Fld Maint Budget'!I94 -> 140826.64 | ... AF47: ='Fld Maint Budget'!M94 -> 252425.11 | AG47: =SUM(U47:AF47) -> 1519864.9 | AH47: =IFERROR(AG47/AG$16,"") | AJ47: =N47-AG47 -> -1264160.9
A48: 5350 - Warehouse | B48: 1000 | C48: 3800 | D48: 4120 | E48: 2500 | F48: 2680 | G48: 2560 | H48: 1240 | I48: 1060 | J48: 3000 | K48: 3000 | L48: 3000 | M48: 3000 | N48: =SUM(B48:M48) -> 30960 | O48: =IFERROR(N48/N$16,"") | R48: Manual | S48: 0 | T48: 0.05 | U48: ='Fld Maint Budget'!B95 -> 3000 | V48: ='Fld Maint Budget'!C95 -> 3000 | W48: ='Fld Maint Budget'!D95 -> 3000 | X48: ='Fld Maint Budget'!E95 -> 3000 | Y48: ='Fld Maint Budget'!F95 -> 3000 | Z48: ='Fld Maint Budget'!G95 -> 3000 | AA48: ='Fld Maint Budget'!H95 -> 3000 | AB48: ='Fld Maint Budget'!I95 -> 3000 | ... AF48: ='Fld Maint Budget'!M95 -> 3000 | AG48: =SUM(U48:AF48) -> 36000 | AH48: =IFERROR(AG48/AG$16,"") | AJ48: =N48-AG48 -> -5040
A49: 5360 - Travel - Maintenance | B49: 1900.25 | C49: 1371.12 | D49: 616.4 | E49: 579.5 | F49: 7011.68 | G49: 4314.54 | H49: 2792.06 | I49: 8642.38 | J49: 5000 | K49: 5000 | L49: 4000 | M49: 4000 | N49: =SUM(B49:M49) -> 45227.93 | O49: =IFERROR(N49/N$16,"") | R49: Manual | S49: 0 | T49: 0.05 | U49: ='Fld Maint Budget'!B96 -> 3992 | V49: ='Fld Maint Budget'!C96 -> 3992 | W49: ='Fld Maint Budget'!D96 -> 3992 | X49: ='Fld Maint Budget'!E96 -> 3992 | Y49: ='Fld Maint Budget'!F96 -> 3992 | Z49: ='Fld Maint Budget'!G96 -> 3992 | AA49: ='Fld Maint Budget'!H96 -> 3992 | AB49: ='Fld Maint Budget'!I96 -> 3992 | ... AF49: ='Fld Maint Budget'!M96 -> 3992 | AG49: =SUM(U49:AF49) -> 47904 | AH49: =IFERROR(AG49/AG$16,"") | AJ49: =N49-AG49 -> -2676.07
A50: 5370 - Meals - Maintenance | B50: 0 | C50: 121.5 | D50: 0 | E50: 0 | F50: 18.64 | G50: 0 | H50: 0 | I50: 0 | J50: 150 | K50: 150 | L50: 150 | M50: 150 | N50: =SUM(B50:M50) -> 740.14 | O50: =IFERROR(N50/N$16,"") | R50: Even | S50: 0 | T50: 0.05 | U50: =IF($R50="Manual","",IFERROR(IF($R50="YOY Growth",$N50*(1+$T50)/12,$S50/12),"")) -> 0 | V50: =IF($R50="Manual","",IFERROR(IF($R50="YOY Growth",$N50*(1+$T50)/12,$S50/12),"")) -> 0 | W50: =IF($R50="Manual","",IFERROR(IF($R50="YOY Growth",$N50*(1+$T50)/12,$S50/12),"")) -> 0 | X50: =IF($R50="Manual","",IFERROR(IF($R50="YOY Growth",$N50*(1+$T50)/12,$S50/12),"")) -> 0 | Y50: =IF($R50="Manual","",IFERROR(IF($R50="YOY Growth",$N50*(1+$T50)/12,$S50/12),"")) -> 0 | Z50: =IF($R50="Manual","",IFERROR(IF($R50="YOY Growth",$N50*(1+$T50)/12,$S50/12),"")) -> 0 | AA50: =IF($R50="Manual","",IFERROR(IF($R50="YOY Growth",$N50*(1+$T50)/12,$S50/12),"")) -> 0 | AB50: =IF($R50="Manual","",IFERROR(IF($R50="YOY Growth",$N50*(1+$T50)/12,$S50/12),"")) -> 0 | ... AF50: =IF($R50="Manual","",IFERROR(IF($R50="YOY Growth",$N50*(1+$T50)/12,$S50/12),"")) -> 0 | AG50: =SUM(U50:AF50) -> 0 | AH50: =IFERROR(AG50/AG$16,"") | AJ50: =N50-AG50 -> 740.14
A51: 5500 - Labor Expense - Field Operations
A52: 5510 - :Salaries and Wages - Field Operations | B52: 41771.03 | C52: 27453.8 | D52: 55703.48 | E52: 77202.08 | F52: 72865.8 | G52: 64701.68 | H52: 82139.24 | I52: 79454.55 | J52: 90000 | K52: 92700 | L52: 95800 | M52: 96900 | N52: =SUM(B52:M52) -> 876691.66 | O52: =IFERROR(N52/N$16,"") | U52: ='Fld Ops Payroll'!F21+'Fld Ops Payroll'!F31+'Fld Ops Payroll'!F43+'Fld Ops Payroll'!F56+'Fld Ops Payroll'!F69+'Fld Ops Payroll'!F76+'Fld Ops Payroll'!F77+'Fld Ops Payroll'!F34+'Fld Ops Payroll'!F46+'Fld Ops Payroll'!F59+'Fld Ops Payroll'!F72 -> 120126.25 | V52: ='Fld Ops Payroll'!G21+'Fld Ops Payroll'!G31+'Fld Ops Payroll'!G43+'Fld Ops Payroll'!G56+'Fld Ops Payroll'!G69+'Fld Ops Payroll'!G76+'Fld Ops Payroll'!G77+'Fld Ops Payroll'!G34+'Fld Ops Payroll'!G46+'Fld Ops Payroll'!G59+'Fld Ops Payroll'!G72 -> 116126.25 | W52: ='Fld Ops Payroll'!H21+'Fld Ops Payroll'!H31+'Fld Ops Payroll'!H43+'Fld Ops Payroll'!H56+'Fld Ops Payroll'!H69+'Fld Ops Payroll'!H76+'Fld Ops Payroll'!H77+'Fld Ops Payroll'!H34+'Fld Ops Payroll'!H46+'Fld Ops Payroll'!H59+'Fld Ops Payroll'!H72 -> 154626.25 | X52: ='Fld Ops Payroll'!I21+'Fld Ops Payroll'!I31+'Fld Ops Payroll'!I43+'Fld Ops Payroll'!I56+'Fld Ops Payroll'!I69+'Fld Ops Payroll'!I76+'Fld Ops Payroll'!I77+'Fld Ops Payroll'!I34+'Fld Ops Payroll'!I46+'Fld Ops Payroll'!I59+'Fld Ops Payroll'!I72 -> 166376.25 | Y52: ='Fld Ops Payroll'!J21+'Fld Ops Payroll'!J31+'Fld Ops Payroll'!J43+'Fld Ops Payroll'!J56+'Fld Ops Payroll'!J69+'Fld Ops Payroll'!J76+'Fld Ops Payroll'!J77+'Fld Ops Payroll'!J34+'Fld Ops Payroll'!J46+'Fld Ops Payroll'!J59+'Fld Ops Payroll'!J72 -> 196626.25 | Z52: ='Fld Ops Payroll'!K21+'Fld Ops Payroll'!K31+'Fld Ops Payroll'!K43+'Fld Ops Payroll'!K56+'Fld Ops Payroll'!K69+'Fld Ops Payroll'!K76+'Fld Ops Payroll'!K77+'Fld Ops Payroll'!K34+'Fld Ops Payroll'!K46+'Fld Ops Payroll'!K59+'Fld Ops Payroll'!K72 -> 222876.25 | AA52: ='Fld Ops Payroll'!L21+'Fld Ops Payroll'!L31+'Fld Ops Payroll'!L43+'Fld Ops Payroll'!L56+'Fld Ops Payroll'!L69+'Fld Ops Payroll'!L76+'Fld Ops Payroll'!L77+'Fld Ops Payroll'!L34+'Fld Ops Payroll'!L46+'Fld Ops Payroll'!L59+'Fld Ops Payroll'!L72 -> 265876.25 | AB52: ='Fld Ops Payroll'!M21+'Fld Ops Payroll'!M31+'Fld Ops Payroll'!M43+'Fld Ops Payroll'!M56+'Fld Ops Payroll'!M69+'Fld Ops Payroll'!M76+'Fld Ops Payroll'!M77+'Fld Ops Payroll'!M34+'Fld Ops Payroll'!M46+'Fld Ops Payroll'!M59+'Fld Ops Payroll'!M72 -> 302626.25 | ... AF52: ='Fld Ops Payroll'!Q21+'Fld Ops Payroll'!Q31+'Fld Ops Payroll'!Q43+'Fld Ops Payroll'!Q56+'Fld Ops Payroll'!Q69+'Fld Ops Payroll'!Q76+'Fld Ops Payroll'!Q77+'Fld Ops Payroll'!Q34+'Fld Ops Payroll'!Q46+'Fld Ops Payroll'!Q59+'Fld Ops Payroll'!Q72 -> 499215.04 | AG52: =SUM(U52:AF52) -> 3238031.4 | AH52: =IFERROR(AG52/AG$16,"") | AJ52: =N52-AG52 -> -2361339.7
A53: 5530 - :Payroll Taxes - Field Operations | B53: 3714.57 | C53: 3251.23 | D53: 3711.25 | E53: 5152.42 | F53: 4827.71 | G53: 4403.72 | H53: 5573.24 | I53: 5853.77 | J53: 5850 | K53: 6026 | L53: 6227 | M53: 6299 | N53: =SUM(B53:M53) -> 60889.91 | O53: =IFERROR(N53/N$16,"") | U53: ='Fld Ops Payroll'!F22+'Fld Ops Payroll'!F32+'Fld Ops Payroll'!F44+'Fld Ops Payroll'!F57+'Fld Ops Payroll'!F70+'Fld Ops Payroll'!F78 -> 7896.585 | V53: ='Fld Ops Payroll'!G22+'Fld Ops Payroll'!G32+'Fld Ops Payroll'!G44+'Fld Ops Payroll'!G57+'Fld Ops Payroll'!G70+'Fld Ops Payroll'!G78 -> 7896.585 | W53: ='Fld Ops Payroll'!H22+'Fld Ops Payroll'!H32+'Fld Ops Payroll'!H44+'Fld Ops Payroll'!H57+'Fld Ops Payroll'!H70+'Fld Ops Payroll'!H78 -> 9834.585 | X53: ='Fld Ops Payroll'!I22+'Fld Ops Payroll'!I32+'Fld Ops Payroll'!I44+'Fld Ops Payroll'!I57+'Fld Ops Payroll'!I70+'Fld Ops Payroll'!I78 -> 10905.585 | Y53: ='Fld Ops Payroll'!J22+'Fld Ops Payroll'!J32+'Fld Ops Payroll'!J44+'Fld Ops Payroll'!J57+'Fld Ops Payroll'!J70+'Fld Ops Payroll'!J78 -> 12690.585 | Z53: ='Fld Ops Payroll'!K22+'Fld Ops Payroll'!K32+'Fld Ops Payroll'!K44+'Fld Ops Payroll'!K57+'Fld Ops Payroll'!K70+'Fld Ops Payroll'!K78 -> 14475.585 | AA53: ='Fld Ops Payroll'!L22+'Fld Ops Payroll'!L32+'Fld Ops Payroll'!L44+'Fld Ops Payroll'!L57+'Fld Ops Payroll'!L70+'Fld Ops Payroll'!L78 -> 17127.585 | AB53: ='Fld Ops Payroll'!M22+'Fld Ops Payroll'!M32+'Fld Ops Payroll'!M44+'Fld Ops Payroll'!M57+'Fld Ops Payroll'!M70+'Fld Ops Payroll'!M78 -> 19626.585 | ... AF53: ='Fld Ops Payroll'!Q22+'Fld Ops Payroll'!Q32+'Fld Ops Payroll'!Q44+'Fld Ops Payroll'!Q57+'Fld Ops Payroll'!Q70+'Fld Ops Payroll'!Q78 -> 32722.623 | AG53: =SUM(U53:AF53) -> 210802.13 | AH53: =IFERROR(AG53/AG$16,"") | AJ53: =N53-AG53 -> -149912.22
A54: 5540 - :Benefits - Field Operations | B54: 30690.72 | C54: 21236.59 | D54: 9448.65 | E54: 12493.8 | F54: 12115.76 | G54: 16324.25 | H54: 13014.13 | I54: 17324.26 | J54: 10800 | K54: 11124 | L54: 11496 | M54: 11628 | N54: =SUM(B54:M54) -> 177696.16 | O54: =IFERROR(N54/N$16,"") | U54: ='Fld Ops Payroll'!F23+'Fld Ops Payroll'!F33+'Fld Ops Payroll'!F45+'Fld Ops Payroll'!F58+'Fld Ops Payroll'!F71+'Fld Ops Payroll'!F79 -> 19044.705 | V54: ='Fld Ops Payroll'!G23+'Fld Ops Payroll'!G33+'Fld Ops Payroll'!G45+'Fld Ops Payroll'!G58+'Fld Ops Payroll'!G71+'Fld Ops Payroll'!G79 -> 19044.705 | W54: ='Fld Ops Payroll'!H23+'Fld Ops Payroll'!H33+'Fld Ops Payroll'!H45+'Fld Ops Payroll'!H58+'Fld Ops Payroll'!H71+'Fld Ops Payroll'!H79 -> 23718.705 | X54: ='Fld Ops Payroll'!I23+'Fld Ops Payroll'!I33+'Fld Ops Payroll'!I45+'Fld Ops Payroll'!I58+'Fld Ops Payroll'!I71+'Fld Ops Payroll'!I79 -> 26301.705 | Y54: ='Fld Ops Payroll'!J23+'Fld Ops Payroll'!J33+'Fld Ops Payroll'!J45+'Fld Ops Payroll'!J58+'Fld Ops Payroll'!J71+'Fld Ops Payroll'!J79 -> 30606.705 | Z54: ='Fld Ops Payroll'!K23+'Fld Ops Payroll'!K33+'Fld Ops Payroll'!K45+'Fld Ops Payroll'!K58+'Fld Ops Payroll'!K71+'Fld Ops Payroll'!K79 -> 34911.705 | AA54: ='Fld Ops Payroll'!L23+'Fld Ops Payroll'!L33+'Fld Ops Payroll'!L45+'Fld Ops Payroll'!L58+'Fld Ops Payroll'!L71+'Fld Ops Payroll'!L79 -> 41307.705 | AB54: ='Fld Ops Payroll'!M23+'Fld Ops Payroll'!M33+'Fld Ops Payroll'!M45+'Fld Ops Payroll'!M58+'Fld Ops Payroll'!M71+'Fld Ops Payroll'!M79 -> 47334.705 | ... AF54: ='Fld Ops Payroll'!Q23+'Fld Ops Payroll'!Q33+'Fld Ops Payroll'!Q45+'Fld Ops Payroll'!Q58+'Fld Ops Payroll'!Q71+'Fld Ops Payroll'!Q79 -> 78919.266 | AG54: =SUM(U54:AF54) -> 508405.14 | AH54: =IFERROR(AG54/AG$16,"") | AJ54: =N54-AG54 -> -330708.98
A55: Total - 5500 - Labor Expense - Field Operations | B55: =SUM(B52:B54) -> 76176.32 | C55: =SUM(C52:C54) -> 51941.62 | D55: =SUM(D52:D54) -> 68863.38 | E55: =SUM(E52:E54) -> 94848.3 | F55: =SUM(F52:F54) -> 89809.27 | G55: =SUM(G52:G54) -> 85429.65 | H55: =SUM(H52:H54) -> 100726.61 | I55: =SUM(I52:I54) -> 102632.58 | ... M55: =SUM(M52:M54) -> 114827 | N55: =SUM(B55:M55) -> 1115277.7 | O55: =IFERROR(N55/N$16,"") | U55: =SUM(U52:U54) -> 147067.54 | V55: =SUM(V52:V54) -> 143067.54 | W55: =SUM(W52:W54) -> 188179.54 | X55: =SUM(X52:X54) -> 203583.54 | Y55: =SUM(Y52:Y54) -> 239923.54 | Z55: =SUM(Z52:Z54) -> 272263.54 | AA55: =SUM(AA52:AA54) -> 324311.54 | AB55: =SUM(AB52:AB54) -> 369587.54 | ... AF55: =SUM(AF52:AF54) -> 610856.93 | AG55: =SUM(U55:AF55) -> 3957238.6 | AH55: =IFERROR(AG55/AG$16,"") | AJ55: =N55-AG55 -> -2841960.9
A56: Total - 5300 - Maintenance | B56: =B44+B45+B46+B47+B48+B49+B50+B55 -> 99607.25 | C56: =C44+C45+C46+C47+C48+C49+C50+C55 -> 63609.53 | D56: =D44+D45+D46+D47+D48+D49+D50+D55 -> 136209.04 | E56: =E44+E45+E46+E47+E48+E49+E50+E55 -> 116902.58 | F56: =F44+F45+F46+F47+F48+F49+F50+F55 -> 153529.08 | G56: =G44+G45+G46+G47+G48+G49+G50+G55 -> 129537.07 | H56: =H44+H45+H46+H47+H48+H49+H50+H55 -> 141954.16 | I56: =I44+I45+I46+I47+I48+I49+I50+I55 -> 131016.63 | ... M56: =M44+M45+M46+M47+M48+M49+M50+M55 -> 212087 | N56: =SUM(B56:M56) -> 1779235.3 | O56: =IFERROR(N56/N$16,"") | U56: =U44+U45+U46+U47+U48+U49+U50+U55 -> 259597 | V56: =V44+V45+V46+V47+V48+V49+V50+V55 -> 258558.15 | W56: =W44+W45+W46+W47+W48+W49+W50+W55 -> 307087.73 | X56: =X44+X45+X46+X47+X48+X49+X50+X55 -> 363792.65 | Y56: =Y44+Y45+Y46+Y47+Y48+Y49+Y50+Y55 -> 408827.57 | Z56: =Z44+Z45+Z46+Z47+Z48+Z49+Z50+Z55 -> 467158.36 | AA56: =AA44+AA45+AA46+AA47+AA48+AA49+AA50+AA55 -> 533459.44 | AB56: =AB44+AB45+AB46+AB47+AB48+AB49+AB50+AB55 -> 603946.67 | ... AF56: =AF44+AF45+AF46+AF47+AF48+AF49+AF50+AF55 -> 979839.39 | AG56: =SUM(U56:AF56) -> 6536145.7 | AH56: =IFERROR(AG56/AG$16,"") | AJ56: =N56-AG56 -> -4756910.4
A57: 5900 - Other COGS
A58: 5920 - Software - COGS | B58: 10955.85 | C58: 11156.17 | D58: 11961.24 | E58: 7055.46 | F58: 12334.88 | G58: 13838.18 | H58: 17445.88 | I58: 13679.97 | J58: 5208 | K58: 5208 | L58: 5208 | M58: 5208 | N58: =SUM(B58:M58) -> 119259.63 | O58: =IFERROR(N58/N$16,"") | R58: Even | S58: 0 | T58: 0.05 | U58: =IF($R58="Manual","",IFERROR(IF($R58="YOY Growth",$N58*(1+$T58)/12,$S58/12),"")) -> 0 | V58: =IF($R58="Manual","",IFERROR(IF($R58="YOY Growth",$N58*(1+$T58)/12,$S58/12),"")) -> 0 | W58: =IF($R58="Manual","",IFERROR(IF($R58="YOY Growth",$N58*(1+$T58)/12,$S58/12),"")) -> 0 | X58: =IF($R58="Manual","",IFERROR(IF($R58="YOY Growth",$N58*(1+$T58)/12,$S58/12),"")) -> 0 | Y58: =IF($R58="Manual","",IFERROR(IF($R58="YOY Growth",$N58*(1+$T58)/12,$S58/12),"")) -> 0 | Z58: =IF($R58="Manual","",IFERROR(IF($R58="YOY Growth",$N58*(1+$T58)/12,$S58/12),"")) -> 0 | AA58: =IF($R58="Manual","",IFERROR(IF($R58="YOY Growth",$N58*(1+$T58)/12,$S58/12),"")) -> 0 | AB58: =IF($R58="Manual","",IFERROR(IF($R58="YOY Growth",$N58*(1+$T58)/12,$S58/12),"")) -> 0 | ... AF58: =IF($R58="Manual","",IFERROR(IF($R58="YOY Growth",$N58*(1+$T58)/12,$S58/12),"")) -> 0 | AG58: =SUM(U58:AF58) -> 0 | AH58: =IFERROR(AG58/AG$16,"") | AJ58: =N58-AG58 -> 119259.63
A59: 5950 - Certification Expense | B59: 0 | C59: 0 | D59: 0 | E59: 0 | F59: 0 | G59: 0 | H59: 1861.34 | I59: 0 | J59: 0 | K59: 0 | L59: 0 | M59: 0 | N59: =SUM(B59:M59) -> 1861.34 | O59: =IFERROR(N59/N$16,"") | R59: Even | S59: 0 | T59: 0.05 | U59: =IF($R59="Manual","",IFERROR(IF($R59="YOY Growth",$N59*(1+$T59)/12,$S59/12),"")) -> 0 | V59: =IF($R59="Manual","",IFERROR(IF($R59="YOY Growth",$N59*(1+$T59)/12,$S59/12),"")) -> 0 | W59: =IF($R59="Manual","",IFERROR(IF($R59="YOY Growth",$N59*(1+$T59)/12,$S59/12),"")) -> 0 | X59: =IF($R59="Manual","",IFERROR(IF($R59="YOY Growth",$N59*(1+$T59)/12,$S59/12),"")) -> 0 | Y59: =IF($R59="Manual","",IFERROR(IF($R59="YOY Growth",$N59*(1+$T59)/12,$S59/12),"")) -> 0 | Z59: =IF($R59="Manual","",IFERROR(IF($R59="YOY Growth",$N59*(1+$T59)/12,$S59/12),"")) -> 0 | AA59: =IF($R59="Manual","",IFERROR(IF($R59="YOY Growth",$N59*(1+$T59)/12,$S59/12),"")) -> 0 | AB59: =IF($R59="Manual","",IFERROR(IF($R59="YOY Growth",$N59*(1+$T59)/12,$S59/12),"")) -> 0 | ... AF59: =IF($R59="Manual","",IFERROR(IF($R59="YOY Growth",$N59*(1+$T59)/12,$S59/12),"")) -> 0 | AG59: =SUM(U59:AF59) -> 0 | AH59: =IFERROR(AG59/AG$16,"") | AJ59: =N59-AG59 -> 1861.34
A60: 5980 - Employee Meals | B60: 0 | C60: 47.22 | D60: 0 | E60: 0 | F60: 0 | G60: 0 | H60: 0 | I60: 0 | J60: 0 | K60: 0 | L60: 0 | M60: 0 | N60: =SUM(B60:M60) -> 47.22 | O60: =IFERROR(N60/N$16,"") | R60: Even | S60: 0 | T60: 0.05 | U60: =IF($R60="Manual","",IFERROR(IF($R60="YOY Growth",$N60*(1+$T60)/12,$S60/12),"")) -> 0 | V60: =IF($R60="Manual","",IFERROR(IF($R60="YOY Growth",$N60*(1+$T60)/12,$S60/12),"")) -> 0 | W60: =IF($R60="Manual","",IFERROR(IF($R60="YOY Growth",$N60*(1+$T60)/12,$S60/12),"")) -> 0 | X60: =IF($R60="Manual","",IFERROR(IF($R60="YOY Growth",$N60*(1+$T60)/12,$S60/12),"")) -> 0 | Y60: =IF($R60="Manual","",IFERROR(IF($R60="YOY Growth",$N60*(1+$T60)/12,$S60/12),"")) -> 0 | Z60: =IF($R60="Manual","",IFERROR(IF($R60="YOY Growth",$N60*(1+$T60)/12,$S60/12),"")) -> 0 | AA60: =IF($R60="Manual","",IFERROR(IF($R60="YOY Growth",$N60*(1+$T60)/12,$S60/12),"")) -> 0 | AB60: =IF($R60="Manual","",IFERROR(IF($R60="YOY Growth",$N60*(1+$T60)/12,$S60/12),"")) -> 0 | ... AF60: =IF($R60="Manual","",IFERROR(IF($R60="YOY Growth",$N60*(1+$T60)/12,$S60/12),"")) -> 0 | AG60: =SUM(U60:AF60) -> 0 | AH60: =IFERROR(AG60/AG$16,"") | AJ60: =N60-AG60 -> 47.22
A61: Total - 5900 - Other COGS | B61: =SUM(B58:B60) -> 10955.85 | C61: =SUM(C58:C60) -> 11203.39 | D61: =SUM(D58:D60) -> 11961.24 | E61: =SUM(E58:E60) -> 7055.46 | F61: =SUM(F58:F60) -> 12334.88 | G61: =SUM(G58:G60) -> 13838.18 | H61: =SUM(H58:H60) -> 19307.22 | I61: =SUM(I58:I60) -> 13679.97 | ... M61: =SUM(M58:M60) -> 5208 | N61: =SUM(B61:M61) -> 121168.19 | O61: =IFERROR(N61/N$16,"") | U61: =SUM(U58:U60) -> 0 | V61: =SUM(V58:V60) -> 0 | W61: =SUM(W58:W60) -> 0 | X61: =SUM(X58:X60) -> 0 | Y61: =SUM(Y58:Y60) -> 0 | Z61: =SUM(Z58:Z60) -> 0 | AA61: =SUM(AA58:AA60) -> 0 | AB61: =SUM(AB58:AB60) -> 0 | ... AF61: =SUM(AF58:AF60) -> 0 | AG61: =SUM(U61:AF61) -> 0 | AH61: =IFERROR(AG61/AG$16,"") | AJ61: =N61-AG61 -> 121168.19
A62: 5990 - Purchase Discounts | B62: 0 | C62: 0 | D62: 0 | E62: 0 | F62: 0 | G62: 0 | H62: 0 | I62: 0 | J62: 0 | K62: 0 | L62: 0 | M62: 0 | N62: =SUM(B62:M62) -> 0 | O62: =IFERROR(N62/N$16,"") | R62: Even | S62: 0 | T62: 0.05 | U62: =IF($R62="Manual","",IFERROR(IF($R62="YOY Growth",$N62*(1+$T62)/12,$S62/12),"")) -> 0 | V62: =IF($R62="Manual","",IFERROR(IF($R62="YOY Growth",$N62*(1+$T62)/12,$S62/12),"")) -> 0 | W62: =IF($R62="Manual","",IFERROR(IF($R62="YOY Growth",$N62*(1+$T62)/12,$S62/12),"")) -> 0 | X62: =IF($R62="Manual","",IFERROR(IF($R62="YOY Growth",$N62*(1+$T62)/12,$S62/12),"")) -> 0 | Y62: =IF($R62="Manual","",IFERROR(IF($R62="YOY Growth",$N62*(1+$T62)/12,$S62/12),"")) -> 0 | Z62: =IF($R62="Manual","",IFERROR(IF($R62="YOY Growth",$N62*(1+$T62)/12,$S62/12),"")) -> 0 | AA62: =IF($R62="Manual","",IFERROR(IF($R62="YOY Growth",$N62*(1+$T62)/12,$S62/12),"")) -> 0 | AB62: =IF($R62="Manual","",IFERROR(IF($R62="YOY Growth",$N62*(1+$T62)/12,$S62/12),"")) -> 0 | ... AF62: =IF($R62="Manual","",IFERROR(IF($R62="YOY Growth",$N62*(1+$T62)/12,$S62/12),"")) -> 0 | AG62: =SUM(U62:AF62) -> 0 | AH62: =IFERROR(AG62/AG$16,"") | AJ62: =N62-AG62 -> 0
A63: Total - Cost Of Sales | B63: =B37+B38+B39+B40+B41+B42+B56+B61+B62 -> 117939.1 | C63: =C37+C38+C39+C40+C41+C42+C56+C61+C62 -> 80664.57 | D63: =D37+D38+D39+D40+D41+D42+D56+D61+D62 -> 152476.6 | E63: =E37+E38+E39+E40+E41+E42+E56+E61+E62 -> 131909.94 | F63: =F37+F38+F39+F40+F41+F42+F56+F61+F62 -> 165943.43 | G63: =G37+G38+G39+G40+G41+G42+G56+G61+G62 -> 143165.51 | H63: =H37+H38+H39+H40+H41+H42+H56+H61+H62 -> 162290.72 | I63: =I37+I38+I39+I40+I41+I42+I56+I61+I62 -> 150488.42 | ... M63: =M37+M38+M39+M40+M41+M42+M56+M61+M62 -> 222295 | N63: =SUM(B63:M63) -> 1967580.3 | O63: =IFERROR(N63/N$16,"") | U63: =U37+U38+U39+U40+U41+U42+U56+U61+U62 -> 306876.7 | V63: =V37+V38+V39+V40+V41+V42+V56+V61+V62 -> 280077.95 | W63: =W37+W38+W39+W40+W41+W42+W56+W61+W62 -> 307087.73 | X63: =X37+X38+X39+X40+X41+X42+X56+X61+X62 -> 427288.19 | Y63: =Y37+Y38+Y39+Y40+Y41+Y42+Y56+Y61+Y62 -> 456563.21 | Z63: =Z37+Z38+Z39+Z40+Z41+Z42+Z56+Z61+Z62 -> 541109.84 | AA63: =AA37+AA38+AA39+AA40+AA41+AA42+AA56+AA61+AA62 -> 591954.98 | AB63: =AB37+AB38+AB39+AB40+AB41+AB42+AB56+AB61+AB62 -> 673202.11 | ... AF63: =AF37+AF38+AF39+AF40+AF41+AF42+AF56+AF61+AF62 -> 1096830.5 | AG63: =SUM(U63:AF63) -> 7347499.6 | AH63: =IFERROR(AG63/AG$16,"") | AJ63: =N63-AG63 -> -5379919.3
A64: Gross Profit | B64: =B16-B63 -> -117939.1 | C64: =C16-C63 -> -80664.57 | D64: =D16-D63 -> -152476.6 | E64: =E16-E63 -> -131909.94 | F64: =F16-F63 -> -165943.43 | G64: =G16-G63 -> -143165.51 | H64: =H16-H63 -> -162290.72 | I64: =I16-I63 -> -150488.42 | ... M64: =M16-M63 -> -222295 | N64: =SUM(B64:M64) -> -1967580.3 | O64: =IFERROR(N64/N$16,"") | U64: =U16-U63 -> -306876.7 | V64: =V16-V63 -> -280077.95 | W64: =W16-W63 -> -307087.73 | X64: =X16-X63 -> -427288.19 | Y64: =Y16-Y63 -> -456563.21 | Z64: =Z16-Z63 -> -541109.84 | AA64: =AA16-AA63 -> -591954.98 | AB64: =AB16-AB63 -> -673202.11 | ... AF64: =AF16-AF63 -> -1096830.5 | AG64: =SUM(U64:AF64) -> -7347499.6 | AH64: =IFERROR(AG64/AG$16,"") | AJ64: =AG64-N64 -> -5379919.3
A65: Expense
A66: 6000 - Labor Expense - SG&A
A67: 6610 - Salaries and Wages - SG&A | B67: 28787.31 | C67: 8716.01 | D67: 13071.44 | E67: 0 | F67: 0 | G67: 0 | H67: 0 | I67: 0 | J67: 0 | K67: 0 | L67: 0 | M67: 0 | N67: =SUM(B67:M67) -> 50574.76 | O67: =IFERROR(N67/N$16,"") | AG67: =SUM(U67:AF67) -> 0 | AH67: =IFERROR(AG67/AG$16,"") | AJ67: =N67-AG67 -> 50574.76
A68: 6630 - Payroll Taxes - SG&A | B68: 2063.17 | C68: 0 | D68: 1025.96 | E68: 0 | F68: 0 | G68: 0 | H68: 0 | I68: 0 | J68: 0 | K68: 0 | L68: 0 | M68: 0 | N68: =SUM(B68:M68) -> 3089.13 | O68: =IFERROR(N68/N$16,"") | AG68: =SUM(U68:AF68) -> 0 | AH68: =IFERROR(AG68/AG$16,"") | AJ68: =N68-AG68 -> 3089.13
A69: 6640 - Benefits - SG&A | B69: 167.72 | C69: 413.16 | D69: -353.62 | E69: 0 | F69: 0 | G69: 0 | H69: 0 | I69: 0 | J69: 0 | K69: 0 | L69: 0 | M69: 0 | N69: =SUM(B69:M69) -> 227.26 | O69: =IFERROR(N69/N$16,"") | AG69: =SUM(U69:AF69) -> 0 | AH69: =IFERROR(AG69/AG$16,"") | AJ69: =N69-AG69 -> 227.26
A70: 6650 - Commissions - SG&A | B70: 0 | C70: 0 | D70: 0 | E70: 0 | F70: 0 | G70: 0 | H70: 0 | I70: 0 | J70: 0 | K70: 0 | L70: 0 | M70: 0 | N70: =SUM(B70:M70) -> 0 | O70: =IFERROR(N70/N$16,"") | R70: Even | S70: 0 | T70: 0.05 | U70: =IF($R70="Manual","",IFERROR(IF($R70="YOY Growth",$N70*(1+$T70)/12,$S70/12),"")) -> 0 | V70: =IF($R70="Manual","",IFERROR(IF($R70="YOY Growth",$N70*(1+$T70)/12,$S70/12),"")) -> 0 | W70: =IF($R70="Manual","",IFERROR(IF($R70="YOY Growth",$N70*(1+$T70)/12,$S70/12),"")) -> 0 | X70: =IF($R70="Manual","",IFERROR(IF($R70="YOY Growth",$N70*(1+$T70)/12,$S70/12),"")) -> 0 | Y70: =IF($R70="Manual","",IFERROR(IF($R70="YOY Growth",$N70*(1+$T70)/12,$S70/12),"")) -> 0 | Z70: =IF($R70="Manual","",IFERROR(IF($R70="YOY Growth",$N70*(1+$T70)/12,$S70/12),"")) -> 0 | AA70: =IF($R70="Manual","",IFERROR(IF($R70="YOY Growth",$N70*(1+$T70)/12,$S70/12),"")) -> 0 | AB70: =IF($R70="Manual","",IFERROR(IF($R70="YOY Growth",$N70*(1+$T70)/12,$S70/12),"")) -> 0 | ... AF70: =IF($R70="Manual","",IFERROR(IF($R70="YOY Growth",$N70*(1+$T70)/12,$S70/12),"")) -> 0 | AG70: =SUM(U70:AF70) -> 0 | AH70: =IFERROR(AG70/AG$16,"") | AJ70: =N70-AG70 -> 0
A71: 6660 - Recruiting | B71: 0 | C71: 0 | D71: 0 | E71: 0 | F71: 0 | G71: 0 | H71: 0 | I71: 0 | J71: 0 | K71: 0 | L71: 0 | M71: 0 | N71: =SUM(B71:M71) -> 0 | O71: =IFERROR(N71/N$16,"") | R71: Even | S71: 0 | T71: 0.05 | U71: =IF($R71="Manual","",IFERROR(IF($R71="YOY Growth",$N71*(1+$T71)/12,$S71/12),"")) -> 0 | V71: =IF($R71="Manual","",IFERROR(IF($R71="YOY Growth",$N71*(1+$T71)/12,$S71/12),"")) -> 0 | W71: =IF($R71="Manual","",IFERROR(IF($R71="YOY Growth",$N71*(1+$T71)/12,$S71/12),"")) -> 0 | X71: =IF($R71="Manual","",IFERROR(IF($R71="YOY Growth",$N71*(1+$T71)/12,$S71/12),"")) -> 0 | Y71: =IF($R71="Manual","",IFERROR(IF($R71="YOY Growth",$N71*(1+$T71)/12,$S71/12),"")) -> 0 | Z71: =IF($R71="Manual","",IFERROR(IF($R71="YOY Growth",$N71*(1+$T71)/12,$S71/12),"")) -> 0 | AA71: =IF($R71="Manual","",IFERROR(IF($R71="YOY Growth",$N71*(1+$T71)/12,$S71/12),"")) -> 0 | AB71: =IF($R71="Manual","",IFERROR(IF($R71="YOY Growth",$N71*(1+$T71)/12,$S71/12),"")) -> 0 | ... AF71: =IF($R71="Manual","",IFERROR(IF($R71="YOY Growth",$N71*(1+$T71)/12,$S71/12),"")) -> 0 | AG71: =SUM(U71:AF71) -> 0 | AH71: =IFERROR(AG71/AG$16,"") | AJ71: =N71-AG71 -> 0
A72: 6670 - Stock Compensation Expense | B72: 0 | C72: 0 | D72: 0 | E72: 0 | F72: 0 | G72: 0 | H72: 0 | I72: 0 | J72: 0 | K72: 0 | L72: 0 | M72: 0 | N72: =SUM(B72:M72) -> 0 | O72: =IFERROR(N72/N$16,"") | R72: Even | S72: 0 | T72: 0.05 | U72: =IF($R72="Manual","",IFERROR(IF($R72="YOY Growth",$N72*(1+$T72)/12,$S72/12),"")) -> 0 | V72: =IF($R72="Manual","",IFERROR(IF($R72="YOY Growth",$N72*(1+$T72)/12,$S72/12),"")) -> 0 | W72: =IF($R72="Manual","",IFERROR(IF($R72="YOY Growth",$N72*(1+$T72)/12,$S72/12),"")) -> 0 | X72: =IF($R72="Manual","",IFERROR(IF($R72="YOY Growth",$N72*(1+$T72)/12,$S72/12),"")) -> 0 | Y72: =IF($R72="Manual","",IFERROR(IF($R72="YOY Growth",$N72*(1+$T72)/12,$S72/12),"")) -> 0 | Z72: =IF($R72="Manual","",IFERROR(IF($R72="YOY Growth",$N72*(1+$T72)/12,$S72/12),"")) -> 0 | AA72: =IF($R72="Manual","",IFERROR(IF($R72="YOY Growth",$N72*(1+$T72)/12,$S72/12),"")) -> 0 | AB72: =IF($R72="Manual","",IFERROR(IF($R72="YOY Growth",$N72*(1+$T72)/12,$S72/12),"")) -> 0 | ... AF72: =IF($R72="Manual","",IFERROR(IF($R72="YOY Growth",$N72*(1+$T72)/12,$S72/12),"")) -> 0 | AG72: =SUM(U72:AF72) -> 0 | AH72: =IFERROR(AG72/AG$16,"") | AJ72: =N72-AG72 -> 0
A73: Total - 6000 - Labor Expense - SG&A | B73: =SUM(B67:B72) -> 31018.2 | C73: =SUM(C67:C72) -> 9129.17 | D73: =SUM(D67:D72) -> 13743.78 | E73: =SUM(E67:E72) -> 0 | F73: =SUM(F67:F72) -> 0 | G73: =SUM(G67:G72) -> 0 | H73: =SUM(H67:H72) -> 0 | I73: =SUM(I67:I72) -> 0 | ... M73: =SUM(M67:M72) -> 0 | N73: =SUM(B73:M73) -> 53891.15 | O73: =IFERROR(N73/N$16,"") | U73: =SUM(U67:U72) -> 0 | V73: =SUM(V67:V72) -> 0 | W73: =SUM(W67:W72) -> 0 | X73: =SUM(X67:X72) -> 0 | Y73: =SUM(Y67:Y72) -> 0 | Z73: =SUM(Z67:Z72) -> 0 | AA73: =SUM(AA67:AA72) -> 0 | AB73: =SUM(AB67:AB72) -> 0 | ... AF73: =SUM(AF67:AF72) -> 0 | AG73: =SUM(U73:AF73) -> 0 | AH73: =IFERROR(AG73/AG$16,"") | AJ73: =N73-AG73 -> 53891.15
A74: 6100 - Travel | B74: 11.96 | C74: 9.99 | D74: 960.43 | E74: 1228.86 | F74: 2504.31 | G74: 3441.65 | H74: 8082.14 | I74: 666.92 | J74: 2500 | K74: 2500 | L74: 2500 | M74: 2500 | N74: =SUM(B74:M74) -> 26906.26 | O74: =IFERROR(N74/N$16,"") | R74: Even | S74: 0 | T74: 0.05 | U74: =IF($R74="Manual","",IFERROR(IF($R74="YOY Growth",$N74*(1+$T74)/12,$S74/12),"")) -> 0 | V74: =IF($R74="Manual","",IFERROR(IF($R74="YOY Growth",$N74*(1+$T74)/12,$S74/12),"")) -> 0 | W74: =IF($R74="Manual","",IFERROR(IF($R74="YOY Growth",$N74*(1+$T74)/12,$S74/12),"")) -> 0 | X74: =IF($R74="Manual","",IFERROR(IF($R74="YOY Growth",$N74*(1+$T74)/12,$S74/12),"")) -> 0 | Y74: =IF($R74="Manual","",IFERROR(IF($R74="YOY Growth",$N74*(1+$T74)/12,$S74/12),"")) -> 0 | Z74: =IF($R74="Manual","",IFERROR(IF($R74="YOY Growth",$N74*(1+$T74)/12,$S74/12),"")) -> 0 | AA74: =IF($R74="Manual","",IFERROR(IF($R74="YOY Growth",$N74*(1+$T74)/12,$S74/12),"")) -> 0 | AB74: =IF($R74="Manual","",IFERROR(IF($R74="YOY Growth",$N74*(1+$T74)/12,$S74/12),"")) -> 0 | ... AF74: =IF($R74="Manual","",IFERROR(IF($R74="YOY Growth",$N74*(1+$T74)/12,$S74/12),"")) -> 0 | AG74: =SUM(U74:AF74) -> 0 | AH74: =IFERROR(AG74/AG$16,"") | AJ74: =N74-AG74 -> 26906.26
A75: 6110 - Travel Meals | B75: 0 | C75: 0 | D75: 0 | E75: 139.29 | F75: 0 | G75: -147.89 | H75: 0 | I75: 0 | J75: 150 | K75: 150 | L75: 150 | M75: 150 | N75: =SUM(B75:M75) -> 591.4 | O75: =IFERROR(N75/N$16,"") | R75: Even | S75: 0 | T75: 0.05 | U75: =IF($R75="Manual","",IFERROR(IF($R75="YOY Growth",$N75*(1+$T75)/12,$S75/12),"")) -> 0 | V75: =IF($R75="Manual","",IFERROR(IF($R75="YOY Growth",$N75*(1+$T75)/12,$S75/12),"")) -> 0 | W75: =IF($R75="Manual","",IFERROR(IF($R75="YOY Growth",$N75*(1+$T75)/12,$S75/12),"")) -> 0 | X75: =IF($R75="Manual","",IFERROR(IF($R75="YOY Growth",$N75*(1+$T75)/12,$S75/12),"")) -> 0 | Y75: =IF($R75="Manual","",IFERROR(IF($R75="YOY Growth",$N75*(1+$T75)/12,$S75/12),"")) -> 0 | Z75: =IF($R75="Manual","",IFERROR(IF($R75="YOY Growth",$N75*(1+$T75)/12,$S75/12),"")) -> 0 | AA75: =IF($R75="Manual","",IFERROR(IF($R75="YOY Growth",$N75*(1+$T75)/12,$S75/12),"")) -> 0 | AB75: =IF($R75="Manual","",IFERROR(IF($R75="YOY Growth",$N75*(1+$T75)/12,$S75/12),"")) -> 0 | ... AF75: =IF($R75="Manual","",IFERROR(IF($R75="YOY Growth",$N75*(1+$T75)/12,$S75/12),"")) -> 0 | AG75: =SUM(U75:AF75) -> 0 | AH75: =IFERROR(AG75/AG$16,"") | AJ75: =N75-AG75 -> 591.4
A76: 6120 - Meals and Entertainment | B76: 0 | C76: 0 | D76: 256.68 | E76: 655.57 | F76: 0 | G76: 0 | H76: 0 | I76: 0 | J76: 200 | K76: 200 | L76: 200 | M76: 200 | N76: =SUM(B76:M76) -> 1712.25 | O76: =IFERROR(N76/N$16,"") | R76: Even | S76: 0 | T76: 0.05 | U76: =IF($R76="Manual","",IFERROR(IF($R76="YOY Growth",$N76*(1+$T76)/12,$S76/12),"")) -> 0 | V76: =IF($R76="Manual","",IFERROR(IF($R76="YOY Growth",$N76*(1+$T76)/12,$S76/12),"")) -> 0 | W76: =IF($R76="Manual","",IFERROR(IF($R76="YOY Growth",$N76*(1+$T76)/12,$S76/12),"")) -> 0 | X76: =IF($R76="Manual","",IFERROR(IF($R76="YOY Growth",$N76*(1+$T76)/12,$S76/12),"")) -> 0 | Y76: =IF($R76="Manual","",IFERROR(IF($R76="YOY Growth",$N76*(1+$T76)/12,$S76/12),"")) -> 0 | Z76: =IF($R76="Manual","",IFERROR(IF($R76="YOY Growth",$N76*(1+$T76)/12,$S76/12),"")) -> 0 | AA76: =IF($R76="Manual","",IFERROR(IF($R76="YOY Growth",$N76*(1+$T76)/12,$S76/12),"")) -> 0 | AB76: =IF($R76="Manual","",IFERROR(IF($R76="YOY Growth",$N76*(1+$T76)/12,$S76/12),"")) -> 0 | ... AF76: =IF($R76="Manual","",IFERROR(IF($R76="YOY Growth",$N76*(1+$T76)/12,$S76/12),"")) -> 0 | AG76: =SUM(U76:AF76) -> 0 | AH76: =IFERROR(AG76/AG$16,"") | AJ76: =N76-AG76 -> 1712.25
A77: 6200 - Advertising | B77: 0 | C77: 0 | D77: 0 | E77: 0 | F77: 0 | G77: 0 | H77: 0 | I77: 0 | J77: 0 | K77: 0 | L77: 0 | M77: 0 | N77: =SUM(B77:M77) -> 0 | O77: =IFERROR(N77/N$16,"") | R77: Even | S77: 0 | T77: 0.05 | U77: =IF($R77="Manual","",IFERROR(IF($R77="YOY Growth",$N77*(1+$T77)/12,$S77/12),"")) -> 0 | V77: =IF($R77="Manual","",IFERROR(IF($R77="YOY Growth",$N77*(1+$T77)/12,$S77/12),"")) -> 0 | W77: =IF($R77="Manual","",IFERROR(IF($R77="YOY Growth",$N77*(1+$T77)/12,$S77/12),"")) -> 0 | X77: =IF($R77="Manual","",IFERROR(IF($R77="YOY Growth",$N77*(1+$T77)/12,$S77/12),"")) -> 0 | Y77: =IF($R77="Manual","",IFERROR(IF($R77="YOY Growth",$N77*(1+$T77)/12,$S77/12),"")) -> 0 | Z77: =IF($R77="Manual","",IFERROR(IF($R77="YOY Growth",$N77*(1+$T77)/12,$S77/12),"")) -> 0 | AA77: =IF($R77="Manual","",IFERROR(IF($R77="YOY Growth",$N77*(1+$T77)/12,$S77/12),"")) -> 0 | AB77: =IF($R77="Manual","",IFERROR(IF($R77="YOY Growth",$N77*(1+$T77)/12,$S77/12),"")) -> 0 | ... AF77: =IF($R77="Manual","",IFERROR(IF($R77="YOY Growth",$N77*(1+$T77)/12,$S77/12),"")) -> 0 | AG77: =SUM(U77:AF77) -> 0 | AH77: =IFERROR(AG77/AG$16,"") | AJ77: =N77-AG77 -> 0
A78: 6210 - Marketing Expense | B78: 0 | C78: 0 | D78: 0 | E78: 0 | F78: 0 | G78: 0 | H78: 0 | I78: 0 | J78: 0 | K78: 0 | L78: 0 | M78: 0 | N78: =SUM(B78:M78) -> 0 | O78: =IFERROR(N78/N$16,"") | R78: Even | S78: 0 | T78: 0.05 | U78: =IF($R78="Manual","",IFERROR(IF($R78="YOY Growth",$N78*(1+$T78)/12,$S78/12),"")) -> 0 | V78: =IF($R78="Manual","",IFERROR(IF($R78="YOY Growth",$N78*(1+$T78)/12,$S78/12),"")) -> 0 | W78: =IF($R78="Manual","",IFERROR(IF($R78="YOY Growth",$N78*(1+$T78)/12,$S78/12),"")) -> 0 | X78: =IF($R78="Manual","",IFERROR(IF($R78="YOY Growth",$N78*(1+$T78)/12,$S78/12),"")) -> 0 | Y78: =IF($R78="Manual","",IFERROR(IF($R78="YOY Growth",$N78*(1+$T78)/12,$S78/12),"")) -> 0 | Z78: =IF($R78="Manual","",IFERROR(IF($R78="YOY Growth",$N78*(1+$T78)/12,$S78/12),"")) -> 0 | AA78: =IF($R78="Manual","",IFERROR(IF($R78="YOY Growth",$N78*(1+$T78)/12,$S78/12),"")) -> 0 | AB78: =IF($R78="Manual","",IFERROR(IF($R78="YOY Growth",$N78*(1+$T78)/12,$S78/12),"")) -> 0 | ... AF78: =IF($R78="Manual","",IFERROR(IF($R78="YOY Growth",$N78*(1+$T78)/12,$S78/12),"")) -> 0 | AG78: =SUM(U78:AF78) -> 0 | AH78: =IFERROR(AG78/AG$16,"") | AJ78: =N78-AG78 -> 0
A79: 6220 - Trade Shows | B79: 0 | C79: 0 | D79: 0 | E79: 0 | F79: 0 | G79: 2900 | H79: 0 | I79: 0 | J79: 0 | K79: 0 | L79: 0 | M79: 0 | N79: =SUM(B79:M79) -> 2900 | O79: =IFERROR(N79/N$16,"") | R79: Even | S79: 0 | T79: 0.05 | U79: =IF($R79="Manual","",IFERROR(IF($R79="YOY Growth",$N79*(1+$T79)/12,$S79/12),"")) -> 0 | V79: =IF($R79="Manual","",IFERROR(IF($R79="YOY Growth",$N79*(1+$T79)/12,$S79/12),"")) -> 0 | W79: =IF($R79="Manual","",IFERROR(IF($R79="YOY Growth",$N79*(1+$T79)/12,$S79/12),"")) -> 0 | X79: =IF($R79="Manual","",IFERROR(IF($R79="YOY Growth",$N79*(1+$T79)/12,$S79/12),"")) -> 0 | Y79: =IF($R79="Manual","",IFERROR(IF($R79="YOY Growth",$N79*(1+$T79)/12,$S79/12),"")) -> 0 | Z79: =IF($R79="Manual","",IFERROR(IF($R79="YOY Growth",$N79*(1+$T79)/12,$S79/12),"")) -> 0 | AA79: =IF($R79="Manual","",IFERROR(IF($R79="YOY Growth",$N79*(1+$T79)/12,$S79/12),"")) -> 0 | AB79: =IF($R79="Manual","",IFERROR(IF($R79="YOY Growth",$N79*(1+$T79)/12,$S79/12),"")) -> 0 | ... AF79: =IF($R79="Manual","",IFERROR(IF($R79="YOY Growth",$N79*(1+$T79)/12,$S79/12),"")) -> 0 | AG79: =SUM(U79:AF79) -> 0 | AH79: =IFERROR(AG79/AG$16,"") | AJ79: =N79-AG79 -> 2900
A80: 6400 - Memberships and Subscriptions | B80: 0 | C80: 0 | D80: 0 | E80: 0 | F80: 0 | G80: 0 | H80: 0 | I80: 0 | J80: 0 | K80: 0 | L80: 0 | M80: 0 | N80: =SUM(B80:M80) -> 0 | O80: =IFERROR(N80/N$16,"") | R80: Even | S80: 0 | T80: 0.05 | U80: =IF($R80="Manual","",IFERROR(IF($R80="YOY Growth",$N80*(1+$T80)/12,$S80/12),"")) -> 0 | V80: =IF($R80="Manual","",IFERROR(IF($R80="YOY Growth",$N80*(1+$T80)/12,$S80/12),"")) -> 0 | W80: =IF($R80="Manual","",IFERROR(IF($R80="YOY Growth",$N80*(1+$T80)/12,$S80/12),"")) -> 0 | X80: =IF($R80="Manual","",IFERROR(IF($R80="YOY Growth",$N80*(1+$T80)/12,$S80/12),"")) -> 0 | Y80: =IF($R80="Manual","",IFERROR(IF($R80="YOY Growth",$N80*(1+$T80)/12,$S80/12),"")) -> 0 | Z80: =IF($R80="Manual","",IFERROR(IF($R80="YOY Growth",$N80*(1+$T80)/12,$S80/12),"")) -> 0 | AA80: =IF($R80="Manual","",IFERROR(IF($R80="YOY Growth",$N80*(1+$T80)/12,$S80/12),"")) -> 0 | AB80: =IF($R80="Manual","",IFERROR(IF($R80="YOY Growth",$N80*(1+$T80)/12,$S80/12),"")) -> 0 | ... AF80: =IF($R80="Manual","",IFERROR(IF($R80="YOY Growth",$N80*(1+$T80)/12,$S80/12),"")) -> 0 | AG80: =SUM(U80:AF80) -> 0 | AH80: =IFERROR(AG80/AG$16,"") | AJ80: =N80-AG80 -> 0
A81: 6500 - Demos
A82: 6510 - Storage Facilities - Demos | B82: 0 | C82: 0 | D82: 0 | E82: 0 | F82: 0 | G82: 0 | H82: 0 | I82: 0 | J82: 0 | K82: 0 | L82: 0 | M82: 0 | N82: =SUM(B82:M82) -> 0 | O82: =IFERROR(N82/N$16,"") | R82: Even | S82: 0 | T82: 0.05 | U82: =IF($R82="Manual","",IFERROR(IF($R82="YOY Growth",$N82*(1+$T82)/12,$S82/12),"")) -> 0 | V82: =IF($R82="Manual","",IFERROR(IF($R82="YOY Growth",$N82*(1+$T82)/12,$S82/12),"")) -> 0 | W82: =IF($R82="Manual","",IFERROR(IF($R82="YOY Growth",$N82*(1+$T82)/12,$S82/12),"")) -> 0 | X82: =IF($R82="Manual","",IFERROR(IF($R82="YOY Growth",$N82*(1+$T82)/12,$S82/12),"")) -> 0 | Y82: =IF($R82="Manual","",IFERROR(IF($R82="YOY Growth",$N82*(1+$T82)/12,$S82/12),"")) -> 0 | Z82: =IF($R82="Manual","",IFERROR(IF($R82="YOY Growth",$N82*(1+$T82)/12,$S82/12),"")) -> 0 | AA82: =IF($R82="Manual","",IFERROR(IF($R82="YOY Growth",$N82*(1+$T82)/12,$S82/12),"")) -> 0 | AB82: =IF($R82="Manual","",IFERROR(IF($R82="YOY Growth",$N82*(1+$T82)/12,$S82/12),"")) -> 0 | ... AF82: =IF($R82="Manual","",IFERROR(IF($R82="YOY Growth",$N82*(1+$T82)/12,$S82/12),"")) -> 0 | AG82: =SUM(U82:AF82) -> 0 | AH82: =IFERROR(AG82/AG$16,"") | AJ82: =N82-AG82 -> 0
A83: 6520 - Truck Rental - Demos | B83: 0 | C83: 0 | D83: 0 | E83: 0 | F83: 0 | G83: 0 | H83: 0 | I83: 0 | J83: 0 | K83: 0 | L83: 0 | M83: 0 | N83: =SUM(B83:M83) -> 0 | O83: =IFERROR(N83/N$16,"") | R83: Even | S83: 0 | T83: 0.05 | U83: =IF($R83="Manual","",IFERROR(IF($R83="YOY Growth",$N83*(1+$T83)/12,$S83/12),"")) -> 0 | V83: =IF($R83="Manual","",IFERROR(IF($R83="YOY Growth",$N83*(1+$T83)/12,$S83/12),"")) -> 0 | W83: =IF($R83="Manual","",IFERROR(IF($R83="YOY Growth",$N83*(1+$T83)/12,$S83/12),"")) -> 0 | X83: =IF($R83="Manual","",IFERROR(IF($R83="YOY Growth",$N83*(1+$T83)/12,$S83/12),"")) -> 0 | Y83: =IF($R83="Manual","",IFERROR(IF($R83="YOY Growth",$N83*(1+$T83)/12,$S83/12),"")) -> 0 | Z83: =IF($R83="Manual","",IFERROR(IF($R83="YOY Growth",$N83*(1+$T83)/12,$S83/12),"")) -> 0 | AA83: =IF($R83="Manual","",IFERROR(IF($R83="YOY Growth",$N83*(1+$T83)/12,$S83/12),"")) -> 0 | AB83: =IF($R83="Manual","",IFERROR(IF($R83="YOY Growth",$N83*(1+$T83)/12,$S83/12),"")) -> 0 | ... AF83: =IF($R83="Manual","",IFERROR(IF($R83="YOY Growth",$N83*(1+$T83)/12,$S83/12),"")) -> 0 | AG83: =SUM(U83:AF83) -> 0 | AH83: =IFERROR(AG83/AG$16,"") | AJ83: =N83-AG83 -> 0
A84: 6530 - Other Demo Expense | B84: 0 | C84: 0 | D84: 0 | E84: 0 | F84: 0 | G84: 0 | H84: 0 | I84: 0 | J84: 0 | K84: 0 | L84: 0 | M84: 0 | N84: =SUM(B84:M84) -> 0 | O84: =IFERROR(N84/N$16,"") | R84: Even | S84: 0 | T84: 0.05 | U84: =IF($R84="Manual","",IFERROR(IF($R84="YOY Growth",$N84*(1+$T84)/12,$S84/12),"")) -> 0 | V84: =IF($R84="Manual","",IFERROR(IF($R84="YOY Growth",$N84*(1+$T84)/12,$S84/12),"")) -> 0 | W84: =IF($R84="Manual","",IFERROR(IF($R84="YOY Growth",$N84*(1+$T84)/12,$S84/12),"")) -> 0 | X84: =IF($R84="Manual","",IFERROR(IF($R84="YOY Growth",$N84*(1+$T84)/12,$S84/12),"")) -> 0 | Y84: =IF($R84="Manual","",IFERROR(IF($R84="YOY Growth",$N84*(1+$T84)/12,$S84/12),"")) -> 0 | Z84: =IF($R84="Manual","",IFERROR(IF($R84="YOY Growth",$N84*(1+$T84)/12,$S84/12),"")) -> 0 | AA84: =IF($R84="Manual","",IFERROR(IF($R84="YOY Growth",$N84*(1+$T84)/12,$S84/12),"")) -> 0 | AB84: =IF($R84="Manual","",IFERROR(IF($R84="YOY Growth",$N84*(1+$T84)/12,$S84/12),"")) -> 0 | ... AF84: =IF($R84="Manual","",IFERROR(IF($R84="YOY Growth",$N84*(1+$T84)/12,$S84/12),"")) -> 0 | AG84: =SUM(U84:AF84) -> 0 | AH84: =IFERROR(AG84/AG$16,"") | AJ84: =N84-AG84 -> 0
A85: 6540 - Travel - Demos | B85: 0 | C85: 0 | D85: 0 | E85: 0 | F85: 0 | G85: 0 | H85: 0 | I85: 0 | J85: 0 | K85: 0 | L85: 0 | M85: 0 | N85: =SUM(B85:M85) -> 0 | O85: =IFERROR(N85/N$16,"") | R85: Even | S85: 0 | T85: 0.05 | U85: =IF($R85="Manual","",IFERROR(IF($R85="YOY Growth",$N85*(1+$T85)/12,$S85/12),"")) -> 0 | V85: =IF($R85="Manual","",IFERROR(IF($R85="YOY Growth",$N85*(1+$T85)/12,$S85/12),"")) -> 0 | W85: =IF($R85="Manual","",IFERROR(IF($R85="YOY Growth",$N85*(1+$T85)/12,$S85/12),"")) -> 0 | X85: =IF($R85="Manual","",IFERROR(IF($R85="YOY Growth",$N85*(1+$T85)/12,$S85/12),"")) -> 0 | Y85: =IF($R85="Manual","",IFERROR(IF($R85="YOY Growth",$N85*(1+$T85)/12,$S85/12),"")) -> 0 | Z85: =IF($R85="Manual","",IFERROR(IF($R85="YOY Growth",$N85*(1+$T85)/12,$S85/12),"")) -> 0 | AA85: =IF($R85="Manual","",IFERROR(IF($R85="YOY Growth",$N85*(1+$T85)/12,$S85/12),"")) -> 0 | AB85: =IF($R85="Manual","",IFERROR(IF($R85="YOY Growth",$N85*(1+$T85)/12,$S85/12),"")) -> 0 | ... AF85: =IF($R85="Manual","",IFERROR(IF($R85="YOY Growth",$N85*(1+$T85)/12,$S85/12),"")) -> 0 | AG85: =SUM(U85:AF85) -> 0 | AH85: =IFERROR(AG85/AG$16,"") | AJ85: =N85-AG85 -> 0
A86: 6550 - Meals - Demos | B86: 0 | C86: 0 | D86: 0 | E86: 0 | F86: 0 | G86: 0 | H86: 0 | I86: 0 | J86: 0 | K86: 0 | L86: 0 | M86: 0 | N86: =SUM(B86:M86) -> 0 | O86: =IFERROR(N86/N$16,"") | R86: Even | S86: 0 | T86: 0.05 | U86: =IF($R86="Manual","",IFERROR(IF($R86="YOY Growth",$N86*(1+$T86)/12,$S86/12),"")) -> 0 | V86: =IF($R86="Manual","",IFERROR(IF($R86="YOY Growth",$N86*(1+$T86)/12,$S86/12),"")) -> 0 | W86: =IF($R86="Manual","",IFERROR(IF($R86="YOY Growth",$N86*(1+$T86)/12,$S86/12),"")) -> 0 | X86: =IF($R86="Manual","",IFERROR(IF($R86="YOY Growth",$N86*(1+$T86)/12,$S86/12),"")) -> 0 | Y86: =IF($R86="Manual","",IFERROR(IF($R86="YOY Growth",$N86*(1+$T86)/12,$S86/12),"")) -> 0 | Z86: =IF($R86="Manual","",IFERROR(IF($R86="YOY Growth",$N86*(1+$T86)/12,$S86/12),"")) -> 0 | AA86: =IF($R86="Manual","",IFERROR(IF($R86="YOY Growth",$N86*(1+$T86)/12,$S86/12),"")) -> 0 | AB86: =IF($R86="Manual","",IFERROR(IF($R86="YOY Growth",$N86*(1+$T86)/12,$S86/12),"")) -> 0 | ... AF86: =IF($R86="Manual","",IFERROR(IF($R86="YOY Growth",$N86*(1+$T86)/12,$S86/12),"")) -> 0 | AG86: =SUM(U86:AF86) -> 0 | AH86: =IFERROR(AG86/AG$16,"") | AJ86: =N86-AG86 -> 0
A87: Total - 6500 - Demos | B87: =SUM(B82:B86) -> 0 | C87: =SUM(C82:C86) -> 0 | D87: =SUM(D82:D86) -> 0 | E87: =SUM(E82:E86) -> 0 | F87: =SUM(F82:F86) -> 0 | G87: =SUM(G82:G86) -> 0 | H87: =SUM(H82:H86) -> 0 | I87: =SUM(I82:I86) -> 0 | ... M87: =SUM(M82:M86) -> 0 | N87: =SUM(B87:M87) -> 0 | O87: =IFERROR(N87/N$16,"") | U87: =SUM(U82:U86) -> 0 | V87: =SUM(V82:V86) -> 0 | W87: =SUM(W82:W86) -> 0 | X87: =SUM(X82:X86) -> 0 | Y87: =SUM(Y82:Y86) -> 0 | Z87: =SUM(Z82:Z86) -> 0 | AA87: =SUM(AA82:AA86) -> 0 | AB87: =SUM(AB82:AB86) -> 0 | ... AF87: =SUM(AF82:AF86) -> 0 | AG87: =SUM(U87:AF87) -> 0 | AH87: =IFERROR(AG87/AG$16,"") | AJ87: =N87-AG87 -> 0
A88: 7000 - Professional Fees | B88: 0 | C88: 0 | D88: 0 | E88: 0 | F88: 0 | G88: 0 | H88: 0 | I88: 0 | J88: 0 | K88: 0 | L88: 0 | M88: 0 | N88: =SUM(B88:M88) -> 0 | O88: =IFERROR(N88/N$16,"") | R88: Even | S88: 0 | T88: 0.05 | U88: =IF($R88="Manual","",IFERROR(IF($R88="YOY Growth",$N88*(1+$T88)/12,$S88/12),"")) -> 0 | V88: =IF($R88="Manual","",IFERROR(IF($R88="YOY Growth",$N88*(1+$T88)/12,$S88/12),"")) -> 0 | W88: =IF($R88="Manual","",IFERROR(IF($R88="YOY Growth",$N88*(1+$T88)/12,$S88/12),"")) -> 0 | X88: =IF($R88="Manual","",IFERROR(IF($R88="YOY Growth",$N88*(1+$T88)/12,$S88/12),"")) -> 0 | Y88: =IF($R88="Manual","",IFERROR(IF($R88="YOY Growth",$N88*(1+$T88)/12,$S88/12),"")) -> 0 | Z88: =IF($R88="Manual","",IFERROR(IF($R88="YOY Growth",$N88*(1+$T88)/12,$S88/12),"")) -> 0 | AA88: =IF($R88="Manual","",IFERROR(IF($R88="YOY Growth",$N88*(1+$T88)/12,$S88/12),"")) -> 0 | AB88: =IF($R88="Manual","",IFERROR(IF($R88="YOY Growth",$N88*(1+$T88)/12,$S88/12),"")) -> 0 | ... AF88: =IF($R88="Manual","",IFERROR(IF($R88="YOY Growth",$N88*(1+$T88)/12,$S88/12),"")) -> 0 | AG88: =SUM(U88:AF88) -> 0 | AH88: =IFERROR(AG88/AG$16,"") | AJ88: =N88-AG88 -> 0
A89: 7050 - Education | B89: 0 | C89: 0 | D89: 0 | E89: 0 | F89: 0 | G89: 31320 | H89: -8375 | I89: -8375 | J89: 0 | K89: 0 | L89: 0 | M89: 0 | N89: =SUM(B89:M89) -> 14570 | O89: =IFERROR(N89/N$16,"") | R89: Even | S89: 0 | T89: 0.05 | U89: =IF($R89="Manual","",IFERROR(IF($R89="YOY Growth",$N89*(1+$T89)/12,$S89/12),"")) -> 0 | V89: =IF($R89="Manual","",IFERROR(IF($R89="YOY Growth",$N89*(1+$T89)/12,$S89/12),"")) -> 0 | W89: =IF($R89="Manual","",IFERROR(IF($R89="YOY Growth",$N89*(1+$T89)/12,$S89/12),"")) -> 0 | X89: =IF($R89="Manual","",IFERROR(IF($R89="YOY Growth",$N89*(1+$T89)/12,$S89/12),"")) -> 0 | Y89: =IF($R89="Manual","",IFERROR(IF($R89="YOY Growth",$N89*(1+$T89)/12,$S89/12),"")) -> 0 | Z89: =IF($R89="Manual","",IFERROR(IF($R89="YOY Growth",$N89*(1+$T89)/12,$S89/12),"")) -> 0 | AA89: =IF($R89="Manual","",IFERROR(IF($R89="YOY Growth",$N89*(1+$T89)/12,$S89/12),"")) -> 0 | AB89: =IF($R89="Manual","",IFERROR(IF($R89="YOY Growth",$N89*(1+$T89)/12,$S89/12),"")) -> 0 | ... AF89: =IF($R89="Manual","",IFERROR(IF($R89="YOY Growth",$N89*(1+$T89)/12,$S89/12),"")) -> 0 | AG89: =SUM(U89:AF89) -> 0 | AH89: =IFERROR(AG89/AG$16,"") | AJ89: =N89-AG89 -> 14570
A90: 7100 - Legal Expense | B90: 0 | C90: 0 | D90: 0 | E90: 0 | F90: 0 | G90: 0 | H90: 0 | I90: 0 | J90: 0 | K90: 0 | L90: 0 | M90: 0 | N90: =SUM(B90:M90) -> 0 | O90: =IFERROR(N90/N$16,"") | R90: Even | S90: 0 | T90: 0.05 | U90: =IF($R90="Manual","",IFERROR(IF($R90="YOY Growth",$N90*(1+$T90)/12,$S90/12),"")) -> 0 | V90: =IF($R90="Manual","",IFERROR(IF($R90="YOY Growth",$N90*(1+$T90)/12,$S90/12),"")) -> 0 | W90: =IF($R90="Manual","",IFERROR(IF($R90="YOY Growth",$N90*(1+$T90)/12,$S90/12),"")) -> 0 | X90: =IF($R90="Manual","",IFERROR(IF($R90="YOY Growth",$N90*(1+$T90)/12,$S90/12),"")) -> 0 | Y90: =IF($R90="Manual","",IFERROR(IF($R90="YOY Growth",$N90*(1+$T90)/12,$S90/12),"")) -> 0 | Z90: =IF($R90="Manual","",IFERROR(IF($R90="YOY Growth",$N90*(1+$T90)/12,$S90/12),"")) -> 0 | AA90: =IF($R90="Manual","",IFERROR(IF($R90="YOY Growth",$N90*(1+$T90)/12,$S90/12),"")) -> 0 | AB90: =IF($R90="Manual","",IFERROR(IF($R90="YOY Growth",$N90*(1+$T90)/12,$S90/12),"")) -> 0 | ... AF90: =IF($R90="Manual","",IFERROR(IF($R90="YOY Growth",$N90*(1+$T90)/12,$S90/12),"")) -> 0 | AG90: =SUM(U90:AF90) -> 0 | AH90: =IFERROR(AG90/AG$16,"") | AJ90: =N90-AG90 -> 0
A91: 7200 - Contractors | B91: 0 | C91: 11217.74 | D91: 22578.69 | E91: 2247.84 | F91: 0 | G91: 0 | H91: 8883.71 | I91: 14805.67 | J91: 0 | K91: 0 | L91: 0 | M91: 0 | N91: =SUM(B91:M91) -> 59733.65 | O91: =IFERROR(N91/N$16,"") | R91: Even | S91: 0 | T91: 0.05 | U91: =IF($R91="Manual","",IFERROR(IF($R91="YOY Growth",$N91*(1+$T91)/12,$S91/12),"")) -> 0 | V91: =IF($R91="Manual","",IFERROR(IF($R91="YOY Growth",$N91*(1+$T91)/12,$S91/12),"")) -> 0 | W91: =IF($R91="Manual","",IFERROR(IF($R91="YOY Growth",$N91*(1+$T91)/12,$S91/12),"")) -> 0 | X91: =IF($R91="Manual","",IFERROR(IF($R91="YOY Growth",$N91*(1+$T91)/12,$S91/12),"")) -> 0 | Y91: =IF($R91="Manual","",IFERROR(IF($R91="YOY Growth",$N91*(1+$T91)/12,$S91/12),"")) -> 0 | Z91: =IF($R91="Manual","",IFERROR(IF($R91="YOY Growth",$N91*(1+$T91)/12,$S91/12),"")) -> 0 | AA91: =IF($R91="Manual","",IFERROR(IF($R91="YOY Growth",$N91*(1+$T91)/12,$S91/12),"")) -> 0 | AB91: =IF($R91="Manual","",IFERROR(IF($R91="YOY Growth",$N91*(1+$T91)/12,$S91/12),"")) -> 0 | ... AF91: =IF($R91="Manual","",IFERROR(IF($R91="YOY Growth",$N91*(1+$T91)/12,$S91/12),"")) -> 0 | AG91: =SUM(U91:AF91) -> 0 | AH91: =IFERROR(AG91/AG$16,"") | AJ91: =N91-AG91 -> 59733.65
A92: 7300 - R&D Expense | B92: 0 | C92: 1173.39 | D92: -83.85 | E92: 0 | F92: 0 | G92: 0 | H92: 0 | I92: 0 | J92: 0 | K92: 0 | L92: 0 | M92: 0 | N92: =SUM(B92:M92) -> 1089.54 | O92: =IFERROR(N92/N$16,"") | R92: Even | S92: 0 | T92: 0.05 | U92: =IF($R92="Manual","",IFERROR(IF($R92="YOY Growth",$N92*(1+$T92)/12,$S92/12),"")) -> 0 | V92: =IF($R92="Manual","",IFERROR(IF($R92="YOY Growth",$N92*(1+$T92)/12,$S92/12),"")) -> 0 | W92: =IF($R92="Manual","",IFERROR(IF($R92="YOY Growth",$N92*(1+$T92)/12,$S92/12),"")) -> 0 | X92: =IF($R92="Manual","",IFERROR(IF($R92="YOY Growth",$N92*(1+$T92)/12,$S92/12),"")) -> 0 | Y92: =IF($R92="Manual","",IFERROR(IF($R92="YOY Growth",$N92*(1+$T92)/12,$S92/12),"")) -> 0 | Z92: =IF($R92="Manual","",IFERROR(IF($R92="YOY Growth",$N92*(1+$T92)/12,$S92/12),"")) -> 0 | AA92: =IF($R92="Manual","",IFERROR(IF($R92="YOY Growth",$N92*(1+$T92)/12,$S92/12),"")) -> 0 | AB92: =IF($R92="Manual","",IFERROR(IF($R92="YOY Growth",$N92*(1+$T92)/12,$S92/12),"")) -> 0 | ... AF92: =IF($R92="Manual","",IFERROR(IF($R92="YOY Growth",$N92*(1+$T92)/12,$S92/12),"")) -> 0 | AG92: =SUM(U92:AF92) -> 0 | AH92: =IFERROR(AG92/AG$16,"") | AJ92: =N92-AG92 -> 1089.54
A93: 7500 - Facility Expenses | B93: 0 | C93: 0 | D93: 0 | E93: 0 | F93: 0 | G93: 0 | H93: 0 | I93: 0 | J93: 0 | K93: 0 | L93: 0 | M93: 0 | N93: =SUM(B93:M93) -> 0 | O93: =IFERROR(N93/N$16,"") | R93: Even | S93: 0 | T93: 0.05 | U93: =IF($R93="Manual","",IFERROR(IF($R93="YOY Growth",$N93*(1+$T93)/12,$S93/12),"")) -> 0 | V93: =IF($R93="Manual","",IFERROR(IF($R93="YOY Growth",$N93*(1+$T93)/12,$S93/12),"")) -> 0 | W93: =IF($R93="Manual","",IFERROR(IF($R93="YOY Growth",$N93*(1+$T93)/12,$S93/12),"")) -> 0 | X93: =IF($R93="Manual","",IFERROR(IF($R93="YOY Growth",$N93*(1+$T93)/12,$S93/12),"")) -> 0 | Y93: =IF($R93="Manual","",IFERROR(IF($R93="YOY Growth",$N93*(1+$T93)/12,$S93/12),"")) -> 0 | Z93: =IF($R93="Manual","",IFERROR(IF($R93="YOY Growth",$N93*(1+$T93)/12,$S93/12),"")) -> 0 | AA93: =IF($R93="Manual","",IFERROR(IF($R93="YOY Growth",$N93*(1+$T93)/12,$S93/12),"")) -> 0 | AB93: =IF($R93="Manual","",IFERROR(IF($R93="YOY Growth",$N93*(1+$T93)/12,$S93/12),"")) -> 0 | ... AF93: =IF($R93="Manual","",IFERROR(IF($R93="YOY Growth",$N93*(1+$T93)/12,$S93/12),"")) -> 0 | AG93: =SUM(U93:AF93) -> 0 | AH93: =IFERROR(AG93/AG$16,"") | AJ93: =N93-AG93 -> 0
A94: 7510 - Custodial | B94: 0 | C94: 0 | D94: 0 | E94: 0 | F94: 0 | G94: 0 | H94: 0 | I94: 0 | J94: 0 | K94: 0 | L94: 0 | M94: 0 | N94: =SUM(B94:M94) -> 0 | O94: =IFERROR(N94/N$16,"") | R94: Even | S94: 0 | T94: 0.05 | U94: =IF($R94="Manual","",IFERROR(IF($R94="YOY Growth",$N94*(1+$T94)/12,$S94/12),"")) -> 0 | V94: =IF($R94="Manual","",IFERROR(IF($R94="YOY Growth",$N94*(1+$T94)/12,$S94/12),"")) -> 0 | W94: =IF($R94="Manual","",IFERROR(IF($R94="YOY Growth",$N94*(1+$T94)/12,$S94/12),"")) -> 0 | X94: =IF($R94="Manual","",IFERROR(IF($R94="YOY Growth",$N94*(1+$T94)/12,$S94/12),"")) -> 0 | Y94: =IF($R94="Manual","",IFERROR(IF($R94="YOY Growth",$N94*(1+$T94)/12,$S94/12),"")) -> 0 | Z94: =IF($R94="Manual","",IFERROR(IF($R94="YOY Growth",$N94*(1+$T94)/12,$S94/12),"")) -> 0 | AA94: =IF($R94="Manual","",IFERROR(IF($R94="YOY Growth",$N94*(1+$T94)/12,$S94/12),"")) -> 0 | AB94: =IF($R94="Manual","",IFERROR(IF($R94="YOY Growth",$N94*(1+$T94)/12,$S94/12),"")) -> 0 | ... AF94: =IF($R94="Manual","",IFERROR(IF($R94="YOY Growth",$N94*(1+$T94)/12,$S94/12),"")) -> 0 | AG94: =SUM(U94:AF94) -> 0 | AH94: =IFERROR(AG94/AG$16,"") | AJ94: =N94-AG94 -> 0
A95: 7550 - Tools and Equipment | B95: 0 | C95: 0 | D95: 0 | E95: 1515.48 | F95: 0 | G95: 2962.39 | H95: 3138.29 | I95: 2047.26 | J95: 500 | K95: 500 | L95: 500 | M95: 500 | N95: =SUM(B95:M95) -> 11663.42 | O95: =IFERROR(N95/N$16,"") | R95: Even | S95: 0 | T95: 0.05 | U95: =IF($R95="Manual","",IFERROR(IF($R95="YOY Growth",$N95*(1+$T95)/12,$S95/12),"")) -> 0 | V95: =IF($R95="Manual","",IFERROR(IF($R95="YOY Growth",$N95*(1+$T95)/12,$S95/12),"")) -> 0 | W95: =IF($R95="Manual","",IFERROR(IF($R95="YOY Growth",$N95*(1+$T95)/12,$S95/12),"")) -> 0 | X95: =IF($R95="Manual","",IFERROR(IF($R95="YOY Growth",$N95*(1+$T95)/12,$S95/12),"")) -> 0 | Y95: =IF($R95="Manual","",IFERROR(IF($R95="YOY Growth",$N95*(1+$T95)/12,$S95/12),"")) -> 0 | Z95: =IF($R95="Manual","",IFERROR(IF($R95="YOY Growth",$N95*(1+$T95)/12,$S95/12),"")) -> 0 | AA95: =IF($R95="Manual","",IFERROR(IF($R95="YOY Growth",$N95*(1+$T95)/12,$S95/12),"")) -> 0 | AB95: =IF($R95="Manual","",IFERROR(IF($R95="YOY Growth",$N95*(1+$T95)/12,$S95/12),"")) -> 0 | ... AF95: =IF($R95="Manual","",IFERROR(IF($R95="YOY Growth",$N95*(1+$T95)/12,$S95/12),"")) -> 0 | AG95: =SUM(U95:AF95) -> 0 | AH95: =IFERROR(AG95/AG$16,"") | AJ95: =N95-AG95 -> 11663.42
A96: 7600 - Freight & Delivery | B96: 4965.69 | C96: 0 | D96: 99.36 | E96: 127.27 | F96: 45 | G96: 5460.04 | H96: 0 | I96: 0 | J96: 100 | K96: 100 | L96: 100 | M96: 100 | N96: =SUM(B96:M96) -> 11097.36 | O96: =IFERROR(N96/N$16,"") | R96: Even | S96: 0 | T96: 0.05 | U96: =IF($R96="Manual","",IFERROR(IF($R96="YOY Growth",$N96*(1+$T96)/12,$S96/12),"")) -> 0 | V96: =IF($R96="Manual","",IFERROR(IF($R96="YOY Growth",$N96*(1+$T96)/12,$S96/12),"")) -> 0 | W96: =IF($R96="Manual","",IFERROR(IF($R96="YOY Growth",$N96*(1+$T96)/12,$S96/12),"")) -> 0 | X96: =IF($R96="Manual","",IFERROR(IF($R96="YOY Growth",$N96*(1+$T96)/12,$S96/12),"")) -> 0 | Y96: =IF($R96="Manual","",IFERROR(IF($R96="YOY Growth",$N96*(1+$T96)/12,$S96/12),"")) -> 0 | Z96: =IF($R96="Manual","",IFERROR(IF($R96="YOY Growth",$N96*(1+$T96)/12,$S96/12),"")) -> 0 | AA96: =IF($R96="Manual","",IFERROR(IF($R96="YOY Growth",$N96*(1+$T96)/12,$S96/12),"")) -> 0 | AB96: =IF($R96="Manual","",IFERROR(IF($R96="YOY Growth",$N96*(1+$T96)/12,$S96/12),"")) -> 0 | ... AF96: =IF($R96="Manual","",IFERROR(IF($R96="YOY Growth",$N96*(1+$T96)/12,$S96/12),"")) -> 0 | AG96: =SUM(U96:AF96) -> 0 | AH96: =IFERROR(AG96/AG$16,"") | AJ96: =N96-AG96 -> 11097.36
A97: 7610 - Duties & Tariffs - Other | B97: 0 | C97: 0 | D97: 0 | E97: 0 | F97: 0 | G97: 0 | H97: 0 | I97: 0 | J97: 0 | K97: 0 | L97: 0 | M97: 0 | N97: =SUM(B97:M97) -> 0 | O97: =IFERROR(N97/N$16,"") | R97: Even | S97: 0 | T97: 0.05 | U97: =IF($R97="Manual","",IFERROR(IF($R97="YOY Growth",$N97*(1+$T97)/12,$S97/12),"")) -> 0 | V97: =IF($R97="Manual","",IFERROR(IF($R97="YOY Growth",$N97*(1+$T97)/12,$S97/12),"")) -> 0 | W97: =IF($R97="Manual","",IFERROR(IF($R97="YOY Growth",$N97*(1+$T97)/12,$S97/12),"")) -> 0 | X97: =IF($R97="Manual","",IFERROR(IF($R97="YOY Growth",$N97*(1+$T97)/12,$S97/12),"")) -> 0 | Y97: =IF($R97="Manual","",IFERROR(IF($R97="YOY Growth",$N97*(1+$T97)/12,$S97/12),"")) -> 0 | Z97: =IF($R97="Manual","",IFERROR(IF($R97="YOY Growth",$N97*(1+$T97)/12,$S97/12),"")) -> 0 | AA97: =IF($R97="Manual","",IFERROR(IF($R97="YOY Growth",$N97*(1+$T97)/12,$S97/12),"")) -> 0 | AB97: =IF($R97="Manual","",IFERROR(IF($R97="YOY Growth",$N97*(1+$T97)/12,$S97/12),"")) -> 0 | ... AF97: =IF($R97="Manual","",IFERROR(IF($R97="YOY Growth",$N97*(1+$T97)/12,$S97/12),"")) -> 0 | AG97: =SUM(U97:AF97) -> 0 | AH97: =IFERROR(AG97/AG$16,"") | AJ97: =N97-AG97 -> 0
A98: 7700 - Inventory Obsolescence-old | B98: 0 | C98: 0 | D98: 0 | E98: 0 | F98: 0 | G98: 0 | H98: 0 | I98: 0 | J98: 0 | K98: 0 | L98: 0 | M98: 0 | N98: =SUM(B98:M98) -> 0 | O98: =IFERROR(N98/N$16,"") | R98: Even | S98: 0 | T98: 0.05 | U98: =IF($R98="Manual","",IFERROR(IF($R98="YOY Growth",$N98*(1+$T98)/12,$S98/12),"")) -> 0 | V98: =IF($R98="Manual","",IFERROR(IF($R98="YOY Growth",$N98*(1+$T98)/12,$S98/12),"")) -> 0 | W98: =IF($R98="Manual","",IFERROR(IF($R98="YOY Growth",$N98*(1+$T98)/12,$S98/12),"")) -> 0 | X98: =IF($R98="Manual","",IFERROR(IF($R98="YOY Growth",$N98*(1+$T98)/12,$S98/12),"")) -> 0 | Y98: =IF($R98="Manual","",IFERROR(IF($R98="YOY Growth",$N98*(1+$T98)/12,$S98/12),"")) -> 0 | Z98: =IF($R98="Manual","",IFERROR(IF($R98="YOY Growth",$N98*(1+$T98)/12,$S98/12),"")) -> 0 | AA98: =IF($R98="Manual","",IFERROR(IF($R98="YOY Growth",$N98*(1+$T98)/12,$S98/12),"")) -> 0 | AB98: =IF($R98="Manual","",IFERROR(IF($R98="YOY Growth",$N98*(1+$T98)/12,$S98/12),"")) -> 0 | ... AF98: =IF($R98="Manual","",IFERROR(IF($R98="YOY Growth",$N98*(1+$T98)/12,$S98/12),"")) -> 0 | AG98: =SUM(U98:AF98) -> 0 | AH98: =IFERROR(AG98/AG$16,"") | AJ98: =N98-AG98 -> 0
A99: 8100 - Technology | B99: 0 | C99: 0 | D99: 0 | E99: 0 | F99: 0 | G99: 0 | H99: 0 | I99: 0 | J99: 0 | K99: 0 | L99: 0 | M99: 0 | N99: =SUM(B99:M99) -> 0 | O99: =IFERROR(N99/N$16,"") | R99: Even | S99: 0 | T99: 0.05 | U99: =IF($R99="Manual","",IFERROR(IF($R99="YOY Growth",$N99*(1+$T99)/12,$S99/12),"")) -> 0 | V99: =IF($R99="Manual","",IFERROR(IF($R99="YOY Growth",$N99*(1+$T99)/12,$S99/12),"")) -> 0 | W99: =IF($R99="Manual","",IFERROR(IF($R99="YOY Growth",$N99*(1+$T99)/12,$S99/12),"")) -> 0 | X99: =IF($R99="Manual","",IFERROR(IF($R99="YOY Growth",$N99*(1+$T99)/12,$S99/12),"")) -> 0 | Y99: =IF($R99="Manual","",IFERROR(IF($R99="YOY Growth",$N99*(1+$T99)/12,$S99/12),"")) -> 0 | Z99: =IF($R99="Manual","",IFERROR(IF($R99="YOY Growth",$N99*(1+$T99)/12,$S99/12),"")) -> 0 | AA99: =IF($R99="Manual","",IFERROR(IF($R99="YOY Growth",$N99*(1+$T99)/12,$S99/12),"")) -> 0 | AB99: =IF($R99="Manual","",IFERROR(IF($R99="YOY Growth",$N99*(1+$T99)/12,$S99/12),"")) -> 0 | ... AF99: =IF($R99="Manual","",IFERROR(IF($R99="YOY Growth",$N99*(1+$T99)/12,$S99/12),"")) -> 0 | AG99: =SUM(U99:AF99) -> 0 | AH99: =IFERROR(AG99/AG$16,"") | AJ99: =N99-AG99 -> 0
... A115: 9999 - Uncategorized Expenses | B115: 0 | C115: 0 | D115: 0 | E115: 0 | F115: 0 | G115: 0 | H115: 0 | I115: 0 | J115: 0 | K115: 0 | L115: 0 | M115: 0 | N115: =SUM(B115:M115) -> 0 | O115: =IFERROR(N115/N$16,"") | R115: Even | S115: 0 | T115: 0.05 | U115: =IF($R115="Manual","",IFERROR(IF($R115="YOY Growth",$N115*(1+$T115)/12,$S115/12),"")) -> 0 | V115: =IF($R115="Manual","",IFERROR(IF($R115="YOY Growth",$N115*(1+$T115)/12,$S115/12),"")) -> 0 | W115: =IF($R115="Manual","",IFERROR(IF($R115="YOY Growth",$N115*(1+$T115)/12,$S115/12),"")) -> 0 | X115: =IF($R115="Manual","",IFERROR(IF($R115="YOY Growth",$N115*(1+$T115)/12,$S115/12),"")) -> 0 | Y115: =IF($R115="Manual","",IFERROR(IF($R115="YOY Growth",$N115*(1+$T115)/12,$S115/12),"")) -> 0 | Z115: =IF($R115="Manual","",IFERROR(IF($R115="YOY Growth",$N115*(1+$T115)/12,$S115/12),"")) -> 0 | AA115: =IF($R115="Manual","",IFERROR(IF($R115="YOY Growth",$N115*(1+$T115)/12,$S115/12),"")) -> 0 | AB115: =IF($R115="Manual","",IFERROR(IF($R115="YOY Growth",$N115*(1+$T115)/12,$S115/12),"")) -> 0 | ... AF115: =IF($R115="Manual","",IFERROR(IF($R115="YOY Growth",$N115*(1+$T115)/12,$S115/12),"")) -> 0 | AG115: =SUM(U115:AF115) -> 0 | AH115: =IFERROR(AG115/AG$16,"") | AJ115: =N115-AG115 -> 0
A116: Total - Expense | B116: =B73+SUM(B74:B80)+B87+SUM(B88:B115) -> 35995.85 | C116: =C73+SUM(C74:C80)+C87+SUM(C88:C115) -> 27174.95 | D116: =D73+SUM(D74:D80)+D87+SUM(D88:D115) -> 38485.09 | E116: =E73+SUM(E74:E80)+E87+SUM(E88:E115) -> 12323.71 | F116: =F73+SUM(F74:F80)+F87+SUM(F88:F115) -> 2999.31 | G116: =G73+SUM(G74:G80)+G87+SUM(G88:G115) -> 46686.32 | H116: =H73+SUM(H74:H80)+H87+SUM(H88:H115) -> 16079.14 | I116: =I73+SUM(I74:I80)+I87+SUM(I88:I115) -> 13698.13 | ... M116: =M73+SUM(M74:M80)+M87+SUM(M88:M115) -> 5950 | N116: =SUM(B116:M116) -> 217242.5 | O116: =IFERROR(N116/N$16,"") | U116: =U73+SUM(U74:U80)+U87+SUM(U88:U115) -> 0 | V116: =V73+SUM(V74:V80)+V87+SUM(V88:V115) -> 0 | W116: =W73+SUM(W74:W80)+W87+SUM(W88:W115) -> 0 | X116: =X73+SUM(X74:X80)+X87+SUM(X88:X115) -> 0 | Y116: =Y73+SUM(Y74:Y80)+Y87+SUM(Y88:Y115) -> 0 | Z116: =Z73+SUM(Z74:Z80)+Z87+SUM(Z88:Z115) -> 0 | AA116: =AA73+SUM(AA74:AA80)+AA87+SUM(AA88:AA115) -> 0 | AB116: =AB73+SUM(AB74:AB80)+AB87+SUM(AB88:AB115) -> 0 | ... AF116: =AF73+SUM(AF74:AF80)+AF87+SUM(AF88:AF115) -> 0 | AG116: =SUM(U116:AF116) -> 0 | AH116: =IFERROR(AG116/AG$16,"") | AJ116: =N116-AG116 -> 217242.5
A117: Net Ordinary Income | B117: =B64-B116 -> -153934.95 | C117: =C64-C116 -> -107839.52 | D117: =D64-D116 -> -190961.69 | E117: =E64-E116 -> -144233.65 | F117: =F64-F116 -> -168942.74 | G117: =G64-G116 -> -189851.83 | H117: =H64-H116 -> -178369.86 | I117: =I64-I116 -> -164186.55 | ... M117: =M64-M116 -> -228245 | N117: =SUM(B117:M117) -> -2184822.8 | O117: =IFERROR(N117/N$16,"") | U117: =U64-U116 -> -306876.7 | V117: =V64-V116 -> -280077.95 | W117: =W64-W116 -> -307087.73 | X117: =X64-X116 -> -427288.19 | Y117: =Y64-Y116 -> -456563.21 | Z117: =Z64-Z116 -> -541109.84 | AA117: =AA64-AA116 -> -591954.98 | AB117: =AB64-AB116 -> -673202.11 | ... AF117: =AF64-AF116 -> -1096830.5 | AG117: =SUM(U117:AF117) -> -7347499.6 | AH117: =IFERROR(AG117/AG$16,"") | AJ117: =AG117-N117 -> -5162676.8
A118: Other Income and Expenses
A119: Other Income
...

Sheet FE
A1: Field Engineering
A2: 2026 Actuals/Forecast & 2027 Budget
B7: Actual | C7: Actual | D7: Actual | E7: Actual | F7: Actual | G7: Actual | H7: Actual | I7: Actual | J7: Forecast | K7: Forecast | L7: Forecast | M7: Forecast | N7: Forecast | O7: Forecast | S7: Annual Input | T7: YOY | U7: Budget | V7: Budget | W7: Budget | X7: Budget | Y7: Budget | Z7: Budget | AA7: Budget | AB7: Budget | AC7: Budget | AD7: Budget | AE7: Budget | AF7: Budget | AG7: Budget | AH7: Budget | AJ7: YOY
B8: Jan | C8: Feb | D8: Mar | E8: Apr | F8: May | G8: Jun | H8: Jul | I8: Aug | J8: Sep | K8: Oct | L8: Nov | M8: Dec | N8: 2026 | O8: % Total Rev | R8: Input Method | S8: "Even" spread | T8: Growth % | U8: Jan | V8: Feb | W8: Mar | X8: Apr | Y8: May | Z8: Jun | AA8: Jul | AB8: Aug | AC8: Sep | AD8: Oct | AE8: Nov | AF8: Dec | AG8: 2027 | AH8: % Total Rev | AJ8: Fav / (Unfav)
A9: Ordinary Income/Expense
A10: Income
A11: 4000 - Sales
A12: 4100 - Subscription/Platform Fees | B12: 0 | C12: 0 | D12: 0 | E12: 0 | F12: 0 | G12: 0 | H12: 0 | I12: 0 | N12: =SUM(B12:M12) -> 0 | O12: =IFERROR(N12/N$16,"") | R12: Even | T12: 0.05 | U12: =IF($R12="Manual","",IFERROR(IF($R12="YOY Growth",$N12*(1+$T12)/12,$S12/12),"")) -> 0 | V12: =IF($R12="Manual","",IFERROR(IF($R12="YOY Growth",$N12*(1+$T12)/12,$S12/12),"")) -> 0 | W12: =IF($R12="Manual","",IFERROR(IF($R12="YOY Growth",$N12*(1+$T12)/12,$S12/12),"")) -> 0 | X12: =IF($R12="Manual","",IFERROR(IF($R12="YOY Growth",$N12*(1+$T12)/12,$S12/12),"")) -> 0 | Y12: =IF($R12="Manual","",IFERROR(IF($R12="YOY Growth",$N12*(1+$T12)/12,$S12/12),"")) -> 0 | Z12: =IF($R12="Manual","",IFERROR(IF($R12="YOY Growth",$N12*(1+$T12)/12,$S12/12),"")) -> 0 | AA12: =IF($R12="Manual","",IFERROR(IF($R12="YOY Growth",$N12*(1+$T12)/12,$S12/12),"")) -> 0 | AB12: =IF($R12="Manual","",IFERROR(IF($R12="YOY Growth",$N12*(1+$T12)/12,$S12/12),"")) -> 0 | ... AF12: =IF($R12="Manual","",IFERROR(IF($R12="YOY Growth",$N12*(1+$T12)/12,$S12/12),"")) -> 0 | AG12: =SUM(U12:AF12) -> 0 | AH12: =IFERROR(AG12/AG$16,"") | AJ12: =AG12-N12 -> 0
A13: 4500 - Implementation Fees | B13: 0 | C13: 0 | D13: 0 | E13: 0 | F13: 0 | G13: 0 | H13: 0 | I13: 0 | N13: =SUM(B13:M13) -> 0 | O13: =IFERROR(N13/N$16,"") | R13: Even | S13: 0 | T13: 0.05 | U13: =IF($R13="Manual","",IFERROR(IF($R13="YOY Growth",$N13*(1+$T13)/12,$S13/12),"")) -> 0 | V13: =IF($R13="Manual","",IFERROR(IF($R13="YOY Growth",$N13*(1+$T13)/12,$S13/12),"")) -> 0 | W13: =IF($R13="Manual","",IFERROR(IF($R13="YOY Growth",$N13*(1+$T13)/12,$S13/12),"")) -> 0 | X13: =IF($R13="Manual","",IFERROR(IF($R13="YOY Growth",$N13*(1+$T13)/12,$S13/12),"")) -> 0 | Y13: =IF($R13="Manual","",IFERROR(IF($R13="YOY Growth",$N13*(1+$T13)/12,$S13/12),"")) -> 0 | Z13: =IF($R13="Manual","",IFERROR(IF($R13="YOY Growth",$N13*(1+$T13)/12,$S13/12),"")) -> 0 | AA13: =IF($R13="Manual","",IFERROR(IF($R13="YOY Growth",$N13*(1+$T13)/12,$S13/12),"")) -> 0 | AB13: =IF($R13="Manual","",IFERROR(IF($R13="YOY Growth",$N13*(1+$T13)/12,$S13/12),"")) -> 0 | ... AF13: =IF($R13="Manual","",IFERROR(IF($R13="YOY Growth",$N13*(1+$T13)/12,$S13/12),"")) -> 0 | AG13: =SUM(U13:AF13) -> 0 | AH13: =IFERROR(AG13/AG$16,"") | AJ13: =AG13-N13 -> 0
A14: Total - 4000 - Sales | B14: =SUM(B12:B13) -> 0 | C14: =SUM(C12:C13) -> 0 | D14: =SUM(D12:D13) -> 0 | E14: =SUM(E12:E13) -> 0 | F14: =SUM(F12:F13) -> 0 | G14: =SUM(G12:G13) -> 0 | H14: =SUM(H12:H13) -> 0 | I14: =SUM(I12:I13) -> 0 | ... M14: =SUM(M12:M13) -> 0 | N14: =SUM(B14:M14) -> 0 | O14: =SUM(O12:O13) -> 0 | U14: =SUM(U12:U13) -> 0 | V14: =SUM(V12:V13) -> 0 | W14: =SUM(W12:W13) -> 0 | X14: =SUM(X12:X13) -> 0 | Y14: =SUM(Y12:Y13) -> 0 | Z14: =SUM(Z12:Z13) -> 0 | AA14: =SUM(AA12:AA13) -> 0 | AB14: =SUM(AB12:AB13) -> 0 | ... AF14: =SUM(AF12:AF13) -> 0 | AG14: =SUM(U14:AF14) -> 0 | AH14: =SUM(AH12:AH13) -> 0 | AJ14: =AG14-N14 -> 0
A15: 4900 - One-Time Revenue | B15: 0 | C15: 0 | D15: 0 | E15: 0 | F15: 0 | G15: 0 | H15: 0 | I15: 0 | N15: =SUM(B15:M15) -> 0 | O15: =IFERROR(N15/N$16,"") | R15: Even | S15: 0 | T15: 0.05 | U15: =IF($R15="Manual","",IFERROR(IF($R15="YOY Growth",$N15*(1+$T15)/12,$S15/12),"")) -> 0 | V15: =IF($R15="Manual","",IFERROR(IF($R15="YOY Growth",$N15*(1+$T15)/12,$S15/12),"")) -> 0 | W15: =IF($R15="Manual","",IFERROR(IF($R15="YOY Growth",$N15*(1+$T15)/12,$S15/12),"")) -> 0 | X15: =IF($R15="Manual","",IFERROR(IF($R15="YOY Growth",$N15*(1+$T15)/12,$S15/12),"")) -> 0 | Y15: =IF($R15="Manual","",IFERROR(IF($R15="YOY Growth",$N15*(1+$T15)/12,$S15/12),"")) -> 0 | Z15: =IF($R15="Manual","",IFERROR(IF($R15="YOY Growth",$N15*(1+$T15)/12,$S15/12),"")) -> 0 | AA15: =IF($R15="Manual","",IFERROR(IF($R15="YOY Growth",$N15*(1+$T15)/12,$S15/12),"")) -> 0 | AB15: =IF($R15="Manual","",IFERROR(IF($R15="YOY Growth",$N15*(1+$T15)/12,$S15/12),"")) -> 0 | ... AF15: =IF($R15="Manual","",IFERROR(IF($R15="YOY Growth",$N15*(1+$T15)/12,$S15/12),"")) -> 0 | AG15: =SUM(U15:AF15) -> 0 | AH15: =IFERROR(AG15/AG$16,"") | AJ15: =AG15-N15 -> 0
A16: Total - Income | B16: =B14+B15 -> 0 | C16: =C14+C15 -> 0 | D16: =D14+D15 -> 0 | E16: =E14+E15 -> 0 | F16: =F14+F15 -> 0 | G16: =G14+G15 -> 0 | H16: =H14+H15 -> 0 | I16: =I14+I15 -> 0 | ... M16: =M14+M15 -> 0 | N16: =SUM(B16:M16) -> 0 | O16: =SUM(O14:O15) -> 0 | U16: =U14+U15 -> 0 | V16: =V14+V15 -> 0 | W16: =W14+W15 -> 0 | X16: =X14+X15 -> 0 | Y16: =Y14+Y15 -> 0 | Z16: =Z14+Z15 -> 0 | AA16: =AA14+AA15 -> 0 | AB16: =AB14+AB15 -> 0 | ... AF16: =AF14+AF15 -> 0 | AG16: =SUM(U16:AF16) -> 0 | AH16: =SUM(AH14:AH15) -> 0 | AJ16: =AG16-N16 -> 0
A17: Cost Of Sales
A18: 5000 - Robot Production and Deployment
A19: 5010 - SlipBot Depreciation | B19: 0 | C19: 0 | D19: 0 | E19: 0 | F19: 0 | G19: 0 | H19: 0 | I19: 0 | N19: =SUM(B19:M19) -> 0 | O19: =IFERROR(N19/N$16,"") | R19: Even | S19: 0 | T19: 0.05 | U19: =IF($R19="Manual","",IFERROR(IF($R19="YOY Growth",$N19*(1+$T19)/12,$S19/12),"")) -> 0 | V19: =IF($R19="Manual","",IFERROR(IF($R19="YOY Growth",$N19*(1+$T19)/12,$S19/12),"")) -> 0 | W19: =IF($R19="Manual","",IFERROR(IF($R19="YOY Growth",$N19*(1+$T19)/12,$S19/12),"")) -> 0 | X19: =IF($R19="Manual","",IFERROR(IF($R19="YOY Growth",$N19*(1+$T19)/12,$S19/12),"")) -> 0 | Y19: =IF($R19="Manual","",IFERROR(IF($R19="YOY Growth",$N19*(1+$T19)/12,$S19/12),"")) -> 0 | Z19: =IF($R19="Manual","",IFERROR(IF($R19="YOY Growth",$N19*(1+$T19)/12,$S19/12),"")) -> 0 | AA19: =IF($R19="Manual","",IFERROR(IF($R19="YOY Growth",$N19*(1+$T19)/12,$S19/12),"")) -> 0 | AB19: =IF($R19="Manual","",IFERROR(IF($R19="YOY Growth",$N19*(1+$T19)/12,$S19/12),"")) -> 0 | ... AF19: =IF($R19="Manual","",IFERROR(IF($R19="YOY Growth",$N19*(1+$T19)/12,$S19/12),"")) -> 0 | AG19: =SUM(U19:AF19) -> 0 | AH19: =IFERROR(AG19/AG$16,"") | AJ19: =N19-AG19 -> 0
A20: 5011 - SlipLift Depreciation | B20: 0 | C20: 0 | D20: 0 | E20: 0 | F20: 0 | G20: 0 | H20: 0 | I20: 0 | N20: =SUM(B20:M20) -> 0 | O20: =IFERROR(N20/N$16,"") | R20: Even | S20: 0 | T20: 0.05 | U20: =IF($R20="Manual","",IFERROR(IF($R20="YOY Growth",$N20*(1+$T20)/12,$S20/12),"")) -> 0 | V20: =IF($R20="Manual","",IFERROR(IF($R20="YOY Growth",$N20*(1+$T20)/12,$S20/12),"")) -> 0 | W20: =IF($R20="Manual","",IFERROR(IF($R20="YOY Growth",$N20*(1+$T20)/12,$S20/12),"")) -> 0 | X20: =IF($R20="Manual","",IFERROR(IF($R20="YOY Growth",$N20*(1+$T20)/12,$S20/12),"")) -> 0 | Y20: =IF($R20="Manual","",IFERROR(IF($R20="YOY Growth",$N20*(1+$T20)/12,$S20/12),"")) -> 0 | Z20: =IF($R20="Manual","",IFERROR(IF($R20="YOY Growth",$N20*(1+$T20)/12,$S20/12),"")) -> 0 | AA20: =IF($R20="Manual","",IFERROR(IF($R20="YOY Growth",$N20*(1+$T20)/12,$S20/12),"")) -> 0 | AB20: =IF($R20="Manual","",IFERROR(IF($R20="YOY Growth",$N20*(1+$T20)/12,$S20/12),"")) -> 0 | ... AF20: =IF($R20="Manual","",IFERROR(IF($R20="YOY Growth",$N20*(1+$T20)/12,$S20/12),"")) -> 0 | AG20: =SUM(U20:AF20) -> 0 | AH20: =IFERROR(AG20/AG$16,"") | AJ20: =N20-AG20 -> 0
A21: 5012 - SlipCarrier Depreciation | B21: 0 | C21: 0 | D21: 0 | E21: 0 | F21: 0 | G21: 0 | H21: 0 | I21: 0 | N21: =SUM(B21:M21) -> 0 | O21: =IFERROR(N21/N$16,"") | R21: Even | S21: 0 | T21: 0.05 | U21: =IF($R21="Manual","",IFERROR(IF($R21="YOY Growth",$N21*(1+$T21)/12,$S21/12),"")) -> 0 | V21: =IF($R21="Manual","",IFERROR(IF($R21="YOY Growth",$N21*(1+$T21)/12,$S21/12),"")) -> 0 | W21: =IF($R21="Manual","",IFERROR(IF($R21="YOY Growth",$N21*(1+$T21)/12,$S21/12),"")) -> 0 | X21: =IF($R21="Manual","",IFERROR(IF($R21="YOY Growth",$N21*(1+$T21)/12,$S21/12),"")) -> 0 | Y21: =IF($R21="Manual","",IFERROR(IF($R21="YOY Growth",$N21*(1+$T21)/12,$S21/12),"")) -> 0 | Z21: =IF($R21="Manual","",IFERROR(IF($R21="YOY Growth",$N21*(1+$T21)/12,$S21/12),"")) -> 0 | AA21: =IF($R21="Manual","",IFERROR(IF($R21="YOY Growth",$N21*(1+$T21)/12,$S21/12),"")) -> 0 | AB21: =IF($R21="Manual","",IFERROR(IF($R21="YOY Growth",$N21*(1+$T21)/12,$S21/12),"")) -> 0 | ... AF21: =IF($R21="Manual","",IFERROR(IF($R21="YOY Growth",$N21*(1+$T21)/12,$S21/12),"")) -> 0 | AG21: =SUM(U21:AF21) -> 0 | AH21: =IFERROR(AG21/AG$16,"") | AJ21: =N21-AG21 -> 0
A22: 5020 - Robot Peripherals Depreciation | B22: 0 | C22: 0 | D22: 0 | E22: 0 | F22: 0 | G22: 0 | H22: 0 | I22: 0 | N22: =SUM(B22:M22) -> 0 | O22: =IFERROR(N22/N$16,"") | R22: Even | S22: 0 | T22: 0.05 | U22: =IF($R22="Manual","",IFERROR(IF($R22="YOY Growth",$N22*(1+$T22)/12,$S22/12),"")) -> 0 | V22: =IF($R22="Manual","",IFERROR(IF($R22="YOY Growth",$N22*(1+$T22)/12,$S22/12),"")) -> 0 | W22: =IF($R22="Manual","",IFERROR(IF($R22="YOY Growth",$N22*(1+$T22)/12,$S22/12),"")) -> 0 | X22: =IF($R22="Manual","",IFERROR(IF($R22="YOY Growth",$N22*(1+$T22)/12,$S22/12),"")) -> 0 | Y22: =IF($R22="Manual","",IFERROR(IF($R22="YOY Growth",$N22*(1+$T22)/12,$S22/12),"")) -> 0 | Z22: =IF($R22="Manual","",IFERROR(IF($R22="YOY Growth",$N22*(1+$T22)/12,$S22/12),"")) -> 0 | AA22: =IF($R22="Manual","",IFERROR(IF($R22="YOY Growth",$N22*(1+$T22)/12,$S22/12),"")) -> 0 | AB22: =IF($R22="Manual","",IFERROR(IF($R22="YOY Growth",$N22*(1+$T22)/12,$S22/12),"")) -> 0 | ... AF22: =IF($R22="Manual","",IFERROR(IF($R22="YOY Growth",$N22*(1+$T22)/12,$S22/12),"")) -> 0 | AG22: =SUM(U22:AF22) -> 0 | AH22: =IFERROR(AG22/AG$16,"") | AJ22: =N22-AG22 -> 0
A23: 5025 - Freight and Delivery - Production (Summary)
A24: 5025 - Freight and Delivery - Production (Summary) | B24: 0 | C24: 0 | D24: 0 | E24: 0 | F24: 0 | G24: 0 | H24: 0 | I24: 0 | J24: 0 | K24: 0 | L24: 0 | M24: 0 | N24: =SUM(B24:M24) -> 0 | O24: =IFERROR(N24/N$16,"") | R24: Even | S24: 0 | T24: 0.05 | U24: =IF($R24="Manual","",IFERROR(IF($R24="YOY Growth",$N24*(1+$T24)/12,$S24/12),"")) -> 0 | V24: =IF($R24="Manual","",IFERROR(IF($R24="YOY Growth",$N24*(1+$T24)/12,$S24/12),"")) -> 0 | W24: =IF($R24="Manual","",IFERROR(IF($R24="YOY Growth",$N24*(1+$T24)/12,$S24/12),"")) -> 0 | X24: =IF($R24="Manual","",IFERROR(IF($R24="YOY Growth",$N24*(1+$T24)/12,$S24/12),"")) -> 0 | Y24: =IF($R24="Manual","",IFERROR(IF($R24="YOY Growth",$N24*(1+$T24)/12,$S24/12),"")) -> 0 | Z24: =IF($R24="Manual","",IFERROR(IF($R24="YOY Growth",$N24*(1+$T24)/12,$S24/12),"")) -> 0 | AA24: =IF($R24="Manual","",IFERROR(IF($R24="YOY Growth",$N24*(1+$T24)/12,$S24/12),"")) -> 0 | AB24: =IF($R24="Manual","",IFERROR(IF($R24="YOY Growth",$N24*(1+$T24)/12,$S24/12),"")) -> 0 | ... AF24: =IF($R24="Manual","",IFERROR(IF($R24="YOY Growth",$N24*(1+$T24)/12,$S24/12),"")) -> 0 | AG24: =SUM(U24:AF24) -> 0 | AH24: =IFERROR(AG24/AG$16,"") | AJ24: =N24-AG24 -> 0
A25: 5026 - Freight and Delivery - Production - Expedited | B25: 0 | C25: 0 | D25: 0 | E25: 0 | F25: 0 | G25: 0 | H25: 0 | I25: 0 | J25: 0 | K25: 0 | L25: 0 | M25: 0 | N25: =SUM(B25:M25) -> 0 | O25: =IFERROR(N25/N$16,"") | R25: Even | S25: 0 | T25: 0.05 | U25: =IF($R25="Manual","",IFERROR(IF($R25="YOY Growth",$N25*(1+$T25)/12,$S25/12),"")) -> 0 | V25: =IF($R25="Manual","",IFERROR(IF($R25="YOY Growth",$N25*(1+$T25)/12,$S25/12),"")) -> 0 | W25: =IF($R25="Manual","",IFERROR(IF($R25="YOY Growth",$N25*(1+$T25)/12,$S25/12),"")) -> 0 | X25: =IF($R25="Manual","",IFERROR(IF($R25="YOY Growth",$N25*(1+$T25)/12,$S25/12),"")) -> 0 | Y25: =IF($R25="Manual","",IFERROR(IF($R25="YOY Growth",$N25*(1+$T25)/12,$S25/12),"")) -> 0 | Z25: =IF($R25="Manual","",IFERROR(IF($R25="YOY Growth",$N25*(1+$T25)/12,$S25/12),"")) -> 0 | AA25: =IF($R25="Manual","",IFERROR(IF($R25="YOY Growth",$N25*(1+$T25)/12,$S25/12),"")) -> 0 | AB25: =IF($R25="Manual","",IFERROR(IF($R25="YOY Growth",$N25*(1+$T25)/12,$S25/12),"")) -> 0 | ... AF25: =IF($R25="Manual","",IFERROR(IF($R25="YOY Growth",$N25*(1+$T25)/12,$S25/12),"")) -> 0 | AG25: =SUM(U25:AF25) -> 0 | AH25: =IFERROR(AG25/AG$16,"") | AJ25: =N25-AG25 -> 0
A26: 5027 - Freight and Delivery - Production - Standard | B26: 0 | C26: 0 | D26: 0 | E26: 0 | F26: 0 | G26: 0 | H26: 0 | I26: 0 | J26: 0 | K26: 0 | L26: 0 | M26: 0 | N26: =SUM(B26:M26) -> 0 | O26: =IFERROR(N26/N$16,"") | R26: Even | S26: 0 | T26: 0.05 | U26: =IF($R26="Manual","",IFERROR(IF($R26="YOY Growth",$N26*(1+$T26)/12,$S26/12),"")) -> 0 | V26: =IF($R26="Manual","",IFERROR(IF($R26="YOY Growth",$N26*(1+$T26)/12,$S26/12),"")) -> 0 | W26: =IF($R26="Manual","",IFERROR(IF($R26="YOY Growth",$N26*(1+$T26)/12,$S26/12),"")) -> 0 | X26: =IF($R26="Manual","",IFERROR(IF($R26="YOY Growth",$N26*(1+$T26)/12,$S26/12),"")) -> 0 | Y26: =IF($R26="Manual","",IFERROR(IF($R26="YOY Growth",$N26*(1+$T26)/12,$S26/12),"")) -> 0 | Z26: =IF($R26="Manual","",IFERROR(IF($R26="YOY Growth",$N26*(1+$T26)/12,$S26/12),"")) -> 0 | AA26: =IF($R26="Manual","",IFERROR(IF($R26="YOY Growth",$N26*(1+$T26)/12,$S26/12),"")) -> 0 | AB26: =IF($R26="Manual","",IFERROR(IF($R26="YOY Growth",$N26*(1+$T26)/12,$S26/12),"")) -> 0 | ... AF26: =IF($R26="Manual","",IFERROR(IF($R26="YOY Growth",$N26*(1+$T26)/12,$S26/12),"")) -> 0 | AG26: =SUM(U26:AF26) -> 0 | AH26: =IFERROR(AG26/AG$16,"") | AJ26: =N26-AG26 -> 0
A27: Total - 5025 - Freight and Delivery - Production (Summary) | B27: =SUM(B24:B26) -> 0 | C27: =SUM(C24:C26) -> 0 | D27: =SUM(D24:D26) -> 0 | E27: =SUM(E24:E26) -> 0 | F27: =SUM(F24:F26) -> 0 | G27: =SUM(G24:G26) -> 0 | H27: =SUM(H24:H26) -> 0 | I27: =SUM(I24:I26) -> 0 | ... M27: =SUM(M24:M26) -> 0 | N27: =SUM(B27:M27) -> 0 | O27: =IFERROR(N27/N$16,"") | U27: =SUM(U24:U26) -> 0 | V27: =SUM(V24:V26) -> 0 | W27: =SUM(W24:W26) -> 0 | X27: =SUM(X24:X26) -> 0 | Y27: =SUM(Y24:Y26) -> 0 | Z27: =SUM(Z24:Z26) -> 0 | AA27: =SUM(AA24:AA26) -> 0 | AB27: =SUM(AB24:AB26) -> 0 | ... AF27: =SUM(AF24:AF26) -> 0 | AG27: =SUM(U27:AF27) -> 0 | AH27: =IFERROR(AG27/AG$16,"") | AJ27: =N27-AG27 -> 0
A28: 5030 - Production Tools and Supplies | B28: 0 | C28: 0 | D28: 0 | E28: 1312.33 | F28: 0 | G28: 0 | H28: 0 | I28: 0 | J28: 0 | K28: 0 | L28: 0 | M28: 0 | N28: =SUM(B28:M28) -> 1312.33 | O28: =IFERROR(N28/N$16,"") | R28: Even | S28: 0 | T28: 0.05 | U28: =IF($R28="Manual","",IFERROR(IF($R28="YOY Growth",$N28*(1+$T28)/12,$S28/12),"")) -> 0 | V28: =IF($R28="Manual","",IFERROR(IF($R28="YOY Growth",$N28*(1+$T28)/12,$S28/12),"")) -> 0 | W28: =IF($R28="Manual","",IFERROR(IF($R28="YOY Growth",$N28*(1+$T28)/12,$S28/12),"")) -> 0 | X28: =IF($R28="Manual","",IFERROR(IF($R28="YOY Growth",$N28*(1+$T28)/12,$S28/12),"")) -> 0 | Y28: =IF($R28="Manual","",IFERROR(IF($R28="YOY Growth",$N28*(1+$T28)/12,$S28/12),"")) -> 0 | Z28: =IF($R28="Manual","",IFERROR(IF($R28="YOY Growth",$N28*(1+$T28)/12,$S28/12),"")) -> 0 | AA28: =IF($R28="Manual","",IFERROR(IF($R28="YOY Growth",$N28*(1+$T28)/12,$S28/12),"")) -> 0 | AB28: =IF($R28="Manual","",IFERROR(IF($R28="YOY Growth",$N28*(1+$T28)/12,$S28/12),"")) -> 0 | ... AF28: =IF($R28="Manual","",IFERROR(IF($R28="YOY Growth",$N28*(1+$T28)/12,$S28/12),"")) -> 0 | AG28: =SUM(U28:AF28) -> 0 | AH28: =IFERROR(AG28/AG$16,"") | AJ28: =N28-AG28 -> 1312.33
A29: 5040 - Freight & Delivery - Deployment | B29: 118.63 | C29: 0 | D29: 0 | E29: 0 | F29: 14.38 | G29: 0 | H29: 0 | I29: 0 | J29: 0 | K29: 0 | L29: 0 | M29: 0 | N29: =SUM(B29:M29) -> 133.01 | O29: =IFERROR(N29/N$16,"") | R29: Even | S29: 0 | T29: 0.05 | U29: =IF($R29="Manual","",IFERROR(IF($R29="YOY Growth",$N29*(1+$T29)/12,$S29/12),"")) -> 0 | V29: =IF($R29="Manual","",IFERROR(IF($R29="YOY Growth",$N29*(1+$T29)/12,$S29/12),"")) -> 0 | W29: =IF($R29="Manual","",IFERROR(IF($R29="YOY Growth",$N29*(1+$T29)/12,$S29/12),"")) -> 0 | X29: =IF($R29="Manual","",IFERROR(IF($R29="YOY Growth",$N29*(1+$T29)/12,$S29/12),"")) -> 0 | Y29: =IF($R29="Manual","",IFERROR(IF($R29="YOY Growth",$N29*(1+$T29)/12,$S29/12),"")) -> 0 | Z29: =IF($R29="Manual","",IFERROR(IF($R29="YOY Growth",$N29*(1+$T29)/12,$S29/12),"")) -> 0 | AA29: =IF($R29="Manual","",IFERROR(IF($R29="YOY Growth",$N29*(1+$T29)/12,$S29/12),"")) -> 0 | AB29: =IF($R29="Manual","",IFERROR(IF($R29="YOY Growth",$N29*(1+$T29)/12,$S29/12),"")) -> 0 | ... AF29: =IF($R29="Manual","",IFERROR(IF($R29="YOY Growth",$N29*(1+$T29)/12,$S29/12),"")) -> 0 | AG29: =SUM(U29:AF29) -> 0 | AH29: =IFERROR(AG29/AG$16,"") | AJ29: =N29-AG29 -> 133.01
A30: 5050 - Travel - Deployment | B30: 6093.31 | C30: 3188.15 | D30: 6516.64 | E30: 4232.23 | F30: 13531.9 | G30: 2938.06 | H30: 3402.48 | I30: 5552.25 | J30: 13000 | K30: 13000 | L30: 9000 | M30: 7000 | N30: =SUM(B30:M30) -> 87455.02 | O30: =IFERROR(N30/N$16,"") | R30: Manual | S30: 0 | T30: 0.05 | U30: ='Fld Eng Budget'!B74 -> 16558.911 | V30: ='Fld Eng Budget'!C74 -> 11039.274 | W30: ='Fld Eng Budget'!D74 -> 0 | X30: ='Fld Eng Budget'!E74 -> 26052.686 | Y30: ='Fld Eng Budget'!F74 -> 20533.049 | Z30: ='Fld Eng Budget'!G74 -> 30026.825 | AA30: ='Fld Eng Budget'!H74 -> 26052.686 | AB30: ='Fld Eng Budget'!I74 -> 31572.323 | ... AF30: ='Fld Eng Budget'!M74 -> 52105.373 | AG30: =SUM(U30:AF30) -> 346633.2 | AH30: =IFERROR(AG30/AG$16,"") | AJ30: =N30-AG30 -> -259178.18
A31: 5060 - Meals - Deployment | B31: 623.1 | C31: 491.08 | D31: 878.77 | E31: 846.11 | F31: 1479.8 | G31: 235.83 | H31: 436.9 | I31: 721.59 | J31: 1400 | K31: 1400 | L31: 1000 | M31: 800 | N31: =SUM(B31:M31) -> 10313.18 | O31: =IFERROR(N31/N$16,"") | R31: Manual | S31: 0 | T31: 0.05 | U31: ='Fld Eng Budget'!B75 -> 2014.994 | V31: ='Fld Eng Budget'!C75 -> 1343.3293 | W31: ='Fld Eng Budget'!D75 -> 0 | X31: ='Fld Eng Budget'!E75 -> 3170.2572 | Y31: ='Fld Eng Budget'!F75 -> 2498.5925 | Z31: ='Fld Eng Budget'!G75 -> 3653.8557 | AA31: ='Fld Eng Budget'!H75 -> 3170.2572 | AB31: ='Fld Eng Budget'!I75 -> 3841.9218 | ... AF31: ='Fld Eng Budget'!M75 -> 6340.5144 | AG31: =SUM(U31:AF31) -> 42180.541 | AH31: =IFERROR(AG31/AG$16,"") | AJ31: =N31-AG31 -> -31867.361
A32: 5100 - Labor Expense - Production
A33: 5110 - Salaries and Wages - Production | B33: 0 | C33: 0 | D33: 0 | E33: 0 | F33: 0 | G33: 0 | H33: 0 | I33: 0 | J33: 0 | K33: 0 | L33: 0 | M33: 0 | N33: =SUM(B33:M33) -> 0 | O33: =IFERROR(N33/N$16,"") | AG33: =SUM(U33:AF33) -> 0 | AH33: =IFERROR(AG33/AG$16,"") | AJ33: =N33-AG33 -> 0
A34: 5130 - Payroll Taxes - Production | B34: 0 | C34: 0 | D34: 0 | E34: 0 | F34: 0 | G34: 0 | H34: 0 | I34: 0 | J34: 0 | K34: 0 | L34: 0 | M34: 0 | N34: =SUM(B34:M34) -> 0 | O34: =IFERROR(N34/N$16,"") | AG34: =SUM(U34:AF34) -> 0 | AH34: =IFERROR(AG34/AG$16,"") | AJ34: =N34-AG34 -> 0
A35: 5140 - Benefits - Production | B35: 0 | C35: 0 | D35: 0 | E35: 0 | F35: 0 | G35: 0 | H35: 0 | I35: 0 | J35: 0 | K35: 0 | L35: 0 | M35: 0 | N35: =SUM(B35:M35) -> 0 | O35: =IFERROR(N35/N$16,"") | AG35: =SUM(U35:AF35) -> 0 | AH35: =IFERROR(AG35/AG$16,"") | AJ35: =N35-AG35 -> 0
A36: Total - 5100 - Labor Expense - Production | B36: =SUM(B33:B35) -> 0 | C36: =SUM(C33:C35) -> 0 | D36: =SUM(D33:D35) -> 0 | E36: =SUM(E33:E35) -> 0 | F36: =SUM(F33:F35) -> 0 | G36: =SUM(G33:G35) -> 0 | H36: =SUM(H33:H35) -> 0 | I36: =SUM(I33:I35) -> 0 | ... M36: =SUM(M33:M35) -> 0 | N36: =SUM(B36:M36) -> 0 | O36: =IFERROR(N36/N$16,"") | U36: =SUM(U33:U35) -> 0 | V36: =SUM(V33:V35) -> 0 | W36: =SUM(W33:W35) -> 0 | X36: =SUM(X33:X35) -> 0 | Y36: =SUM(Y33:Y35) -> 0 | Z36: =SUM(Z33:Z35) -> 0 | AA36: =SUM(AA33:AA35) -> 0 | AB36: =SUM(AB33:AB35) -> 0 | ... AF36: =SUM(AF33:AF35) -> 0 | AG36: =SUM(U36:AF36) -> 0 | AH36: =IFERROR(AG36/AG$16,"") | AJ36: =N36-AG36 -> 0
A37: Total - 5000 - Robot Production and Deployment | B37: =B19+B22+B27+B28+B29+B30+B31+B36+B20+B21 -> 6835.04 | C37: =C19+C22+C27+C28+C29+C30+C31+C36+C20+C21 -> 3679.23 | D37: =D19+D22+D27+D28+D29+D30+D31+D36+D20+D21 -> 7395.41 | E37: =E19+E22+E27+E28+E29+E30+E31+E36+E20+E21 -> 6390.67 | F37: =F19+F22+F27+F28+F29+F30+F31+F36+F20+F21 -> 15026.08 | G37: =G19+G22+G27+G28+G29+G30+G31+G36+G20+G21 -> 3173.89 | H37: =H19+H22+H27+H28+H29+H30+H31+H36+H20+H21 -> 3839.38 | I37: =I19+I22+I27+I28+I29+I30+I31+I36+I20+I21 -> 6273.84 | ... M37: =M19+M22+M27+M28+M29+M30+M31+M36+M20+M21 -> 7800 | N37: =SUM(B37:M37) -> 99213.54 | O37: =IFERROR(N37/N$16,"") | U37: =U19+U22+U27+U28+U29+U30+U31+U36+U20+U21 -> 18573.905 | V37: =V19+V22+V27+V28+V29+V30+V31+V36+V20+V21 -> 12382.603 | W37: =W19+W22+W27+W28+W29+W30+W31+W36+W20+W21 -> 0 | X37: =X19+X22+X27+X28+X29+X30+X31+X36+X20+X21 -> 29222.943 | Y37: =Y19+Y22+Y27+Y28+Y29+Y30+Y31+Y36+Y20+Y21 -> 23031.642 | Z37: =Z19+Z22+Z27+Z28+Z29+Z30+Z31+Z36+Z20+Z21 -> 33680.681 | AA37: =AA19+AA22+AA27+AA28+AA29+AA30+AA31+AA36+AA20+AA21 -> 29222.943 | AB37: =AB19+AB22+AB27+AB28+AB29+AB30+AB31+AB36+AB20+AB21 -> 35414.245 | ... AF37: =AF19+AF22+AF27+AF28+AF29+AF30+AF31+AF36+AF20+AF21 -> 58445.887 | AG37: =SUM(U37:AF37) -> 388813.74 | AH37: =IFERROR(AG37/AG$16,"") | AJ37: =N37-AG37 -> -289600.2
A38: 5015 - Supplies and Materials | B38: 0 | C38: 0 | D38: 0 | E38: 0 | F38: 0 | G38: 0 | H38: 0 | I38: 0 | J38: 0 | K38: 0 | L38: 0 | M38: 0 | N38: =SUM(B38:M38) -> 0 | O38: =IFERROR(N38/N$16,"") | R38: Even | S38: 0 | T38: 0.05 | U38: =IF($R38="Manual","",IFERROR(IF($R38="YOY Growth",$N38*(1+$T38)/12,$S38/12),"")) -> 0 | V38: =IF($R38="Manual","",IFERROR(IF($R38="YOY Growth",$N38*(1+$T38)/12,$S38/12),"")) -> 0 | W38: =IF($R38="Manual","",IFERROR(IF($R38="YOY Growth",$N38*(1+$T38)/12,$S38/12),"")) -> 0 | X38: =IF($R38="Manual","",IFERROR(IF($R38="YOY Growth",$N38*(1+$T38)/12,$S38/12),"")) -> 0 | Y38: =IF($R38="Manual","",IFERROR(IF($R38="YOY Growth",$N38*(1+$T38)/12,$S38/12),"")) -> 0 | Z38: =IF($R38="Manual","",IFERROR(IF($R38="YOY Growth",$N38*(1+$T38)/12,$S38/12),"")) -> 0 | AA38: =IF($R38="Manual","",IFERROR(IF($R38="YOY Growth",$N38*(1+$T38)/12,$S38/12),"")) -> 0 | AB38: =IF($R38="Manual","",IFERROR(IF($R38="YOY Growth",$N38*(1+$T38)/12,$S38/12),"")) -> 0 | ... AF38: =IF($R38="Manual","",IFERROR(IF($R38="YOY Growth",$N38*(1+$T38)/12,$S38/12),"")) -> 0 | AG38: =SUM(U38:AF38) -> 0 | AH38: =IFERROR(AG38/AG$16,"") | AJ38: =N38-AG38 -> 0
A39: 5028 - Duties & Tariffs - Production | B39: 0 | C39: 0 | D39: 0 | E39: 0 | F39: 0 | G39: 0 | H39: 0 | I39: 0 | J39: 0 | K39: 0 | L39: 0 | M39: 0 | N39: =SUM(B39:M39) -> 0 | O39: =IFERROR(N39/N$16,"") | R39: Even | S39: 0 | T39: 0.05 | U39: =IF($R39="Manual","",IFERROR(IF($R39="YOY Growth",$N39*(1+$T39)/12,$S39/12),"")) -> 0 | V39: =IF($R39="Manual","",IFERROR(IF($R39="YOY Growth",$N39*(1+$T39)/12,$S39/12),"")) -> 0 | W39: =IF($R39="Manual","",IFERROR(IF($R39="YOY Growth",$N39*(1+$T39)/12,$S39/12),"")) -> 0 | X39: =IF($R39="Manual","",IFERROR(IF($R39="YOY Growth",$N39*(1+$T39)/12,$S39/12),"")) -> 0 | Y39: =IF($R39="Manual","",IFERROR(IF($R39="YOY Growth",$N39*(1+$T39)/12,$S39/12),"")) -> 0 | Z39: =IF($R39="Manual","",IFERROR(IF($R39="YOY Growth",$N39*(1+$T39)/12,$S39/12),"")) -> 0 | AA39: =IF($R39="Manual","",IFERROR(IF($R39="YOY Growth",$N39*(1+$T39)/12,$S39/12),"")) -> 0 | AB39: =IF($R39="Manual","",IFERROR(IF($R39="YOY Growth",$N39*(1+$T39)/12,$S39/12),"")) -> 0 | ... AF39: =IF($R39="Manual","",IFERROR(IF($R39="YOY Growth",$N39*(1+$T39)/12,$S39/12),"")) -> 0 | AG39: =SUM(U39:AF39) -> 0 | AH39: =IFERROR(AG39/AG$16,"") | AJ39: =N39-AG39 -> 0
A40: 5029 - Processing Fee - Production | B40: 0 | C40: 0 | D40: 0 | E40: 0 | F40: 0 | G40: 0 | H40: 0 | I40: 0 | J40: 0 | K40: 0 | L40: 0 | M40: 0 | N40: =SUM(B40:M40) -> 0 | O40: =IFERROR(N40/N$16,"") | R40: Even | S40: 0 | T40: 0.05 | U40: =IF($R40="Manual","",IFERROR(IF($R40="YOY Growth",$N40*(1+$T40)/12,$S40/12),"")) -> 0 | V40: =IF($R40="Manual","",IFERROR(IF($R40="YOY Growth",$N40*(1+$T40)/12,$S40/12),"")) -> 0 | W40: =IF($R40="Manual","",IFERROR(IF($R40="YOY Growth",$N40*(1+$T40)/12,$S40/12),"")) -> 0 | X40: =IF($R40="Manual","",IFERROR(IF($R40="YOY Growth",$N40*(1+$T40)/12,$S40/12),"")) -> 0 | Y40: =IF($R40="Manual","",IFERROR(IF($R40="YOY Growth",$N40*(1+$T40)/12,$S40/12),"")) -> 0 | Z40: =IF($R40="Manual","",IFERROR(IF($R40="YOY Growth",$N40*(1+$T40)/12,$S40/12),"")) -> 0 | AA40: =IF($R40="Manual","",IFERROR(IF($R40="YOY Growth",$N40*(1+$T40)/12,$S40/12),"")) -> 0 | AB40: =IF($R40="Manual","",IFERROR(IF($R40="YOY Growth",$N40*(1+$T40)/12,$S40/12),"")) -> 0 | ... AF40: =IF($R40="Manual","",IFERROR(IF($R40="YOY Growth",$N40*(1+$T40)/12,$S40/12),"")) -> 0 | AG40: =SUM(U40:AF40) -> 0 | AH40: =IFERROR(AG40/AG$16,"") | AJ40: =N40-AG40 -> 0
A41: 5070 - Scrap | B41: 0 | C41: 0 | D41: 0 | E41: 0 | F41: 0 | G41: 0 | H41: 0 | I41: 0 | N41: =SUM(B41:M41) -> 0 | O41: =IFERROR(N41/N$16,"") | R41: Even | S41: 0 | T41: 0.05 | U41: =IF($R41="Manual","",IFERROR(IF($R41="YOY Growth",$N41*(1+$T41)/12,$S41/12),"")) -> 0 | V41: =IF($R41="Manual","",IFERROR(IF($R41="YOY Growth",$N41*(1+$T41)/12,$S41/12),"")) -> 0 | W41: =IF($R41="Manual","",IFERROR(IF($R41="YOY Growth",$N41*(1+$T41)/12,$S41/12),"")) -> 0 | X41: =IF($R41="Manual","",IFERROR(IF($R41="YOY Growth",$N41*(1+$T41)/12,$S41/12),"")) -> 0 | Y41: =IF($R41="Manual","",IFERROR(IF($R41="YOY Growth",$N41*(1+$T41)/12,$S41/12),"")) -> 0 | Z41: =IF($R41="Manual","",IFERROR(IF($R41="YOY Growth",$N41*(1+$T41)/12,$S41/12),"")) -> 0 | AA41: =IF($R41="Manual","",IFERROR(IF($R41="YOY Growth",$N41*(1+$T41)/12,$S41/12),"")) -> 0 | AB41: =IF($R41="Manual","",IFERROR(IF($R41="YOY Growth",$N41*(1+$T41)/12,$S41/12),"")) -> 0 | ... AF41: =IF($R41="Manual","",IFERROR(IF($R41="YOY Growth",$N41*(1+$T41)/12,$S41/12),"")) -> 0 | AG41: =SUM(U41:AF41) -> 0 | AH41: =IFERROR(AG41/AG$16,"") | AJ41: =N41-AG41 -> 0
A42: 5201 - Inventory Adjustments | B42: 0 | C42: 0 | D42: 0 | E42: 0 | F42: 0 | G42: 0 | H42: 0 | I42: 0 | J42: 0 | K42: 0 | L42: 0 | M42: 0 | N42: =SUM(B42:M42) -> 0 | O42: =IFERROR(N42/N$16,"") | R42: Even | S42: 0 | T42: 0.05 | U42: =IF($R42="Manual","",IFERROR(IF($R42="YOY Growth",$N42*(1+$T42)/12,$S42/12),"")) -> 0 | V42: =IF($R42="Manual","",IFERROR(IF($R42="YOY Growth",$N42*(1+$T42)/12,$S42/12),"")) -> 0 | W42: =IF($R42="Manual","",IFERROR(IF($R42="YOY Growth",$N42*(1+$T42)/12,$S42/12),"")) -> 0 | X42: =IF($R42="Manual","",IFERROR(IF($R42="YOY Growth",$N42*(1+$T42)/12,$S42/12),"")) -> 0 | Y42: =IF($R42="Manual","",IFERROR(IF($R42="YOY Growth",$N42*(1+$T42)/12,$S42/12),"")) -> 0 | Z42: =IF($R42="Manual","",IFERROR(IF($R42="YOY Growth",$N42*(1+$T42)/12,$S42/12),"")) -> 0 | AA42: =IF($R42="Manual","",IFERROR(IF($R42="YOY Growth",$N42*(1+$T42)/12,$S42/12),"")) -> 0 | AB42: =IF($R42="Manual","",IFERROR(IF($R42="YOY Growth",$N42*(1+$T42)/12,$S42/12),"")) -> 0 | ... AF42: =IF($R42="Manual","",IFERROR(IF($R42="YOY Growth",$N42*(1+$T42)/12,$S42/12),"")) -> 0 | AG42: =SUM(U42:AF42) -> 0 | AH42: =IFERROR(AG42/AG$16,"") | AJ42: =N42-AG42 -> 0
A43: 5300 - Maintenance
A44: 5310 - Contractors - Field | B44: 0 | C44: 0 | D44: 0 | E44: 0 | F44: 0 | G44: 0 | H44: 0 | I44: 0 | J44: 0 | K44: 0 | L44: 0 | M44: 0 | N44: =SUM(B44:M44) -> 0 | O44: =IFERROR(N44/N$16,"") | R44: Even | S44: 0 | T44: 0.05 | U44: =IF($R44="Manual","",IFERROR(IF($R44="YOY Growth",$N44*(1+$T44)/12,$S44/12),"")) -> 0 | V44: =IF($R44="Manual","",IFERROR(IF($R44="YOY Growth",$N44*(1+$T44)/12,$S44/12),"")) -> 0 | W44: =IF($R44="Manual","",IFERROR(IF($R44="YOY Growth",$N44*(1+$T44)/12,$S44/12),"")) -> 0 | X44: =IF($R44="Manual","",IFERROR(IF($R44="YOY Growth",$N44*(1+$T44)/12,$S44/12),"")) -> 0 | Y44: =IF($R44="Manual","",IFERROR(IF($R44="YOY Growth",$N44*(1+$T44)/12,$S44/12),"")) -> 0 | Z44: =IF($R44="Manual","",IFERROR(IF($R44="YOY Growth",$N44*(1+$T44)/12,$S44/12),"")) -> 0 | AA44: =IF($R44="Manual","",IFERROR(IF($R44="YOY Growth",$N44*(1+$T44)/12,$S44/12),"")) -> 0 | AB44: =IF($R44="Manual","",IFERROR(IF($R44="YOY Growth",$N44*(1+$T44)/12,$S44/12),"")) -> 0 | ... AF44: =IF($R44="Manual","",IFERROR(IF($R44="YOY Growth",$N44*(1+$T44)/12,$S44/12),"")) -> 0 | AG44: =SUM(U44:AF44) -> 0 | AH44: =IFERROR(AG44/AG$16,"") | AJ44: =N44-AG44 -> 0
A45: 5320 - Freight & Delivery - Maintenance | B45: 166.17 | C45: 0 | D45: 0 | E45: 0 | F45: 0 | G45: 0 | H45: 0 | I45: 0 | J45: 0 | K45: 0 | L45: 0 | M45: 0 | N45: =SUM(B45:M45) -> 166.17 | O45: =IFERROR(N45/N$16,"") | R45: Even | S45: 0 | T45: 0.05 | U45: =IF($R45="Manual","",IFERROR(IF($R45="YOY Growth",$N45*(1+$T45)/12,$S45/12),"")) -> 0 | V45: =IF($R45="Manual","",IFERROR(IF($R45="YOY Growth",$N45*(1+$T45)/12,$S45/12),"")) -> 0 | W45: =IF($R45="Manual","",IFERROR(IF($R45="YOY Growth",$N45*(1+$T45)/12,$S45/12),"")) -> 0 | X45: =IF($R45="Manual","",IFERROR(IF($R45="YOY Growth",$N45*(1+$T45)/12,$S45/12),"")) -> 0 | Y45: =IF($R45="Manual","",IFERROR(IF($R45="YOY Growth",$N45*(1+$T45)/12,$S45/12),"")) -> 0 | Z45: =IF($R45="Manual","",IFERROR(IF($R45="YOY Growth",$N45*(1+$T45)/12,$S45/12),"")) -> 0 | AA45: =IF($R45="Manual","",IFERROR(IF($R45="YOY Growth",$N45*(1+$T45)/12,$S45/12),"")) -> 0 | AB45: =IF($R45="Manual","",IFERROR(IF($R45="YOY Growth",$N45*(1+$T45)/12,$S45/12),"")) -> 0 | ... AF45: =IF($R45="Manual","",IFERROR(IF($R45="YOY Growth",$N45*(1+$T45)/12,$S45/12),"")) -> 0 | AG45: =SUM(U45:AF45) -> 0 | AH45: =IFERROR(AG45/AG$16,"") | AJ45: =N45-AG45 -> 166.17
A46: 5330 - Maintenance Tools and Supplies | B46: 2183.21 | C46: 1487.15 | D46: 1055.56 | E46: 37.64 | F46: 1945.1 | G46: 359.11 | H46: -16.62 | I46: 169.57 | J46: 1900 | K46: 1900 | L46: 1900 | M46: 1900 | N46: =SUM(B46:M46) -> 14820.72 | O46: =IFERROR(N46/N$16,"") | R46: Even | S46: 0 | T46: 0.05 | U46: =IF($R46="Manual","",IFERROR(IF($R46="YOY Growth",$N46*(1+$T46)/12,$S46/12),"")) -> 0 | V46: =IF($R46="Manual","",IFERROR(IF($R46="YOY Growth",$N46*(1+$T46)/12,$S46/12),"")) -> 0 | W46: =IF($R46="Manual","",IFERROR(IF($R46="YOY Growth",$N46*(1+$T46)/12,$S46/12),"")) -> 0 | X46: =IF($R46="Manual","",IFERROR(IF($R46="YOY Growth",$N46*(1+$T46)/12,$S46/12),"")) -> 0 | Y46: =IF($R46="Manual","",IFERROR(IF($R46="YOY Growth",$N46*(1+$T46)/12,$S46/12),"")) -> 0 | Z46: =IF($R46="Manual","",IFERROR(IF($R46="YOY Growth",$N46*(1+$T46)/12,$S46/12),"")) -> 0 | AA46: =IF($R46="Manual","",IFERROR(IF($R46="YOY Growth",$N46*(1+$T46)/12,$S46/12),"")) -> 0 | AB46: =IF($R46="Manual","",IFERROR(IF($R46="YOY Growth",$N46*(1+$T46)/12,$S46/12),"")) -> 0 | ... AF46: =IF($R46="Manual","",IFERROR(IF($R46="YOY Growth",$N46*(1+$T46)/12,$S46/12),"")) -> 0 | AG46: =SUM(U46:AF46) -> 0 | AH46: =IFERROR(AG46/AG$16,"") | AJ46: =N46-AG46 -> 14820.72
A47: 5340 - Spare Parts | B47: 245.8 | C47: 0 | D47: 0 | E47: 21.59 | F47: 12.62 | G47: 0 | H47: 0 | I47: 73.45 | J47: 0 | K47: 0 | L47: 0 | M47: 0 | N47: =SUM(B47:M47) -> 353.46 | O47: =IFERROR(N47/N$16,"") | R47: Even | S47: 0 | T47: 0.05 | U47: =IF($R47="Manual","",IFERROR(IF($R47="YOY Growth",$N47*(1+$T47)/12,$S47/12),"")) -> 0 | V47: =IF($R47="Manual","",IFERROR(IF($R47="YOY Growth",$N47*(1+$T47)/12,$S47/12),"")) -> 0 | W47: =IF($R47="Manual","",IFERROR(IF($R47="YOY Growth",$N47*(1+$T47)/12,$S47/12),"")) -> 0 | X47: =IF($R47="Manual","",IFERROR(IF($R47="YOY Growth",$N47*(1+$T47)/12,$S47/12),"")) -> 0 | Y47: =IF($R47="Manual","",IFERROR(IF($R47="YOY Growth",$N47*(1+$T47)/12,$S47/12),"")) -> 0 | Z47: =IF($R47="Manual","",IFERROR(IF($R47="YOY Growth",$N47*(1+$T47)/12,$S47/12),"")) -> 0 | AA47: =IF($R47="Manual","",IFERROR(IF($R47="YOY Growth",$N47*(1+$T47)/12,$S47/12),"")) -> 0 | AB47: =IF($R47="Manual","",IFERROR(IF($R47="YOY Growth",$N47*(1+$T47)/12,$S47/12),"")) -> 0 | ... AF47: =IF($R47="Manual","",IFERROR(IF($R47="YOY Growth",$N47*(1+$T47)/12,$S47/12),"")) -> 0 | AG47: =SUM(U47:AF47) -> 0 | AH47: =IFERROR(AG47/AG$16,"") | AJ47: =N47-AG47 -> 353.46
A48: 5350 - Warehouse | B48: 0 | C48: 0 | D48: 0 | E48: 0 | F48: 0 | G48: 0 | H48: 0 | I48: 0 | J48: 0 | K48: 0 | L48: 0 | M48: 0 | N48: =SUM(B48:M48) -> 0 | O48: =IFERROR(N48/N$16,"") | R48: Even | S48: 0 | T48: 0.05 | U48: =IF($R48="Manual","",IFERROR(IF($R48="YOY Growth",$N48*(1+$T48)/12,$S48/12),"")) -> 0 | V48: =IF($R48="Manual","",IFERROR(IF($R48="YOY Growth",$N48*(1+$T48)/12,$S48/12),"")) -> 0 | W48: =IF($R48="Manual","",IFERROR(IF($R48="YOY Growth",$N48*(1+$T48)/12,$S48/12),"")) -> 0 | X48: =IF($R48="Manual","",IFERROR(IF($R48="YOY Growth",$N48*(1+$T48)/12,$S48/12),"")) -> 0 | Y48: =IF($R48="Manual","",IFERROR(IF($R48="YOY Growth",$N48*(1+$T48)/12,$S48/12),"")) -> 0 | Z48: =IF($R48="Manual","",IFERROR(IF($R48="YOY Growth",$N48*(1+$T48)/12,$S48/12),"")) -> 0 | AA48: =IF($R48="Manual","",IFERROR(IF($R48="YOY Growth",$N48*(1+$T48)/12,$S48/12),"")) -> 0 | AB48: =IF($R48="Manual","",IFERROR(IF($R48="YOY Growth",$N48*(1+$T48)/12,$S48/12),"")) -> 0 | ... AF48: =IF($R48="Manual","",IFERROR(IF($R48="YOY Growth",$N48*(1+$T48)/12,$S48/12),"")) -> 0 | AG48: =SUM(U48:AF48) -> 0 | AH48: =IFERROR(AG48/AG$16,"") | AJ48: =N48-AG48 -> 0
A49: 5360 - Travel - Maintenance | B49: 60 | C49: 0 | D49: 281.44 | E49: 302.03 | F49: 0 | G49: 0 | H49: 0 | I49: 471.85 | J49: 0 | K49: 0 | L49: 0 | M49: 0 | N49: =SUM(B49:M49) -> 1115.32 | O49: =IFERROR(N49/N$16,"") | R49: Even | S49: 0 | T49: 0.05 | U49: =IF($R49="Manual","",IFERROR(IF($R49="YOY Growth",$N49*(1+$T49)/12,$S49/12),"")) -> 0 | V49: =IF($R49="Manual","",IFERROR(IF($R49="YOY Growth",$N49*(1+$T49)/12,$S49/12),"")) -> 0 | W49: =IF($R49="Manual","",IFERROR(IF($R49="YOY Growth",$N49*(1+$T49)/12,$S49/12),"")) -> 0 | X49: =IF($R49="Manual","",IFERROR(IF($R49="YOY Growth",$N49*(1+$T49)/12,$S49/12),"")) -> 0 | Y49: =IF($R49="Manual","",IFERROR(IF($R49="YOY Growth",$N49*(1+$T49)/12,$S49/12),"")) -> 0 | Z49: =IF($R49="Manual","",IFERROR(IF($R49="YOY Growth",$N49*(1+$T49)/12,$S49/12),"")) -> 0 | AA49: =IF($R49="Manual","",IFERROR(IF($R49="YOY Growth",$N49*(1+$T49)/12,$S49/12),"")) -> 0 | AB49: =IF($R49="Manual","",IFERROR(IF($R49="YOY Growth",$N49*(1+$T49)/12,$S49/12),"")) -> 0 | ... AF49: =IF($R49="Manual","",IFERROR(IF($R49="YOY Growth",$N49*(1+$T49)/12,$S49/12),"")) -> 0 | AG49: =SUM(U49:AF49) -> 0 | AH49: =IFERROR(AG49/AG$16,"") | AJ49: =N49-AG49 -> 1115.32
A50: 5370 - Meals - Maintenance | B50: 0 | C50: 0 | D50: 160.63 | E50: 0 | F50: 0 | G50: 0 | H50: 0 | I50: 0 | J50: 0 | K50: 0 | L50: 0 | M50: 0 | N50: =SUM(B50:M50) -> 160.63 | O50: =IFERROR(N50/N$16,"") | R50: Even | S50: 0 | T50: 0.05 | U50: =IF($R50="Manual","",IFERROR(IF($R50="YOY Growth",$N50*(1+$T50)/12,$S50/12),"")) -> 0 | V50: =IF($R50="Manual","",IFERROR(IF($R50="YOY Growth",$N50*(1+$T50)/12,$S50/12),"")) -> 0 | W50: =IF($R50="Manual","",IFERROR(IF($R50="YOY Growth",$N50*(1+$T50)/12,$S50/12),"")) -> 0 | X50: =IF($R50="Manual","",IFERROR(IF($R50="YOY Growth",$N50*(1+$T50)/12,$S50/12),"")) -> 0 | Y50: =IF($R50="Manual","",IFERROR(IF($R50="YOY Growth",$N50*(1+$T50)/12,$S50/12),"")) -> 0 | Z50: =IF($R50="Manual","",IFERROR(IF($R50="YOY Growth",$N50*(1+$T50)/12,$S50/12),"")) -> 0 | AA50: =IF($R50="Manual","",IFERROR(IF($R50="YOY Growth",$N50*(1+$T50)/12,$S50/12),"")) -> 0 | AB50: =IF($R50="Manual","",IFERROR(IF($R50="YOY Growth",$N50*(1+$T50)/12,$S50/12),"")) -> 0 | ... AF50: =IF($R50="Manual","",IFERROR(IF($R50="YOY Growth",$N50*(1+$T50)/12,$S50/12),"")) -> 0 | AG50: =SUM(U50:AF50) -> 0 | AH50: =IFERROR(AG50/AG$16,"") | AJ50: =N50-AG50 -> 160.63
A51: 5500 - Labor Expense - Field Operations
A52: 5510 - :Salaries and Wages - Field Operations | B52: 0 | C52: 0 | D52: 0 | E52: 0 | F52: 0 | G52: 0 | H52: 0 | I52: 0 | J52: 0 | K52: 0 | L52: 0 | M52: 0 | N52: =SUM(B52:M52) -> 0 | O52: =IFERROR(N52/N$16,"") | AG52: =SUM(U52:AF52) -> 0 | AH52: =IFERROR(AG52/AG$16,"") | AJ52: =N52-AG52 -> 0
A53: 5530 - :Payroll Taxes - Field Operations | B53: 0 | C53: 0 | D53: 0 | E53: 0 | F53: 0 | G53: 0 | H53: 0 | I53: 0 | J53: 0 | K53: 0 | L53: 0 | M53: 0 | N53: =SUM(B53:M53) -> 0 | O53: =IFERROR(N53/N$16,"") | AG53: =SUM(U53:AF53) -> 0 | AH53: =IFERROR(AG53/AG$16,"") | AJ53: =N53-AG53 -> 0
A54: 5540 - :Benefits - Field Operations | B54: 0 | C54: 0 | D54: 0 | E54: 0 | F54: 0 | G54: 0 | H54: 0 | I54: 0 | J54: 0 | K54: 0 | L54: 0 | M54: 0 | N54: =SUM(B54:M54) -> 0 | O54: =IFERROR(N54/N$16,"") | AG54: =SUM(U54:AF54) -> 0 | AH54: =IFERROR(AG54/AG$16,"") | AJ54: =N54-AG54 -> 0
A55: Total - 5500 - Labor Expense - Field Operations | B55: =SUM(B52:B54) -> 0 | C55: =SUM(C52:C54) -> 0 | D55: =SUM(D52:D54) -> 0 | E55: =SUM(E52:E54) -> 0 | F55: =SUM(F52:F54) -> 0 | G55: =SUM(G52:G54) -> 0 | H55: =SUM(H52:H54) -> 0 | I55: =SUM(I52:I54) -> 0 | ... M55: =SUM(M52:M54) -> 0 | N55: =SUM(B55:M55) -> 0 | O55: =IFERROR(N55/N$16,"") | U55: =SUM(U52:U54) -> 0 | V55: =SUM(V52:V54) -> 0 | W55: =SUM(W52:W54) -> 0 | X55: =SUM(X52:X54) -> 0 | Y55: =SUM(Y52:Y54) -> 0 | Z55: =SUM(Z52:Z54) -> 0 | AA55: =SUM(AA52:AA54) -> 0 | AB55: =SUM(AB52:AB54) -> 0 | ... AF55: =SUM(AF52:AF54) -> 0 | AG55: =SUM(U55:AF55) -> 0 | AH55: =IFERROR(AG55/AG$16,"") | AJ55: =N55-AG55 -> 0
A56: Total - 5300 - Maintenance | B56: =B44+B45+B46+B47+B48+B49+B50+B55 -> 2655.18 | C56: =C44+C45+C46+C47+C48+C49+C50+C55 -> 1487.15 | D56: =D44+D45+D46+D47+D48+D49+D50+D55 -> 1497.63 | E56: =E44+E45+E46+E47+E48+E49+E50+E55 -> 361.26 | F56: =F44+F45+F46+F47+F48+F49+F50+F55 -> 1957.72 | G56: =G44+G45+G46+G47+G48+G49+G50+G55 -> 359.11 | H56: =H44+H45+H46+H47+H48+H49+H50+H55 -> -16.62 | I56: =I44+I45+I46+I47+I48+I49+I50+I55 -> 714.87 | ... M56: =M44+M45+M46+M47+M48+M49+M50+M55 -> 1900 | N56: =SUM(B56:M56) -> 16616.3 | O56: =IFERROR(N56/N$16,"") | U56: =U44+U45+U46+U47+U48+U49+U50+U55 -> 0 | V56: =V44+V45+V46+V47+V48+V49+V50+V55 -> 0 | W56: =W44+W45+W46+W47+W48+W49+W50+W55 -> 0 | X56: =X44+X45+X46+X47+X48+X49+X50+X55 -> 0 | Y56: =Y44+Y45+Y46+Y47+Y48+Y49+Y50+Y55 -> 0 | Z56: =Z44+Z45+Z46+Z47+Z48+Z49+Z50+Z55 -> 0 | AA56: =AA44+AA45+AA46+AA47+AA48+AA49+AA50+AA55 -> 0 | AB56: =AB44+AB45+AB46+AB47+AB48+AB49+AB50+AB55 -> 0 | ... AF56: =AF44+AF45+AF46+AF47+AF48+AF49+AF50+AF55 -> 0 | AG56: =SUM(U56:AF56) -> 0 | AH56: =IFERROR(AG56/AG$16,"") | AJ56: =N56-AG56 -> 16616.3
A57: 5900 - Other COGS
A58: 5920 - Software - COGS | B58: 0 | C58: 0 | D58: 0 | E58: 0 | F58: 0 | G58: 0 | H58: 0 | I58: 93.99 | J58: 0 | K58: 0 | L58: 0 | M58: 0 | N58: =SUM(B58:M58) -> 93.99 | O58: =IFERROR(N58/N$16,"") | R58: Even | S58: 0 | T58: 0.05 | U58: =IF($R58="Manual","",IFERROR(IF($R58="YOY Growth",$N58*(1+$T58)/12,$S58/12),"")) -> 0 | V58: =IF($R58="Manual","",IFERROR(IF($R58="YOY Growth",$N58*(1+$T58)/12,$S58/12),"")) -> 0 | W58: =IF($R58="Manual","",IFERROR(IF($R58="YOY Growth",$N58*(1+$T58)/12,$S58/12),"")) -> 0 | X58: =IF($R58="Manual","",IFERROR(IF($R58="YOY Growth",$N58*(1+$T58)/12,$S58/12),"")) -> 0 | Y58: =IF($R58="Manual","",IFERROR(IF($R58="YOY Growth",$N58*(1+$T58)/12,$S58/12),"")) -> 0 | Z58: =IF($R58="Manual","",IFERROR(IF($R58="YOY Growth",$N58*(1+$T58)/12,$S58/12),"")) -> 0 | AA58: =IF($R58="Manual","",IFERROR(IF($R58="YOY Growth",$N58*(1+$T58)/12,$S58/12),"")) -> 0 | AB58: =IF($R58="Manual","",IFERROR(IF($R58="YOY Growth",$N58*(1+$T58)/12,$S58/12),"")) -> 0 | ... AF58: =IF($R58="Manual","",IFERROR(IF($R58="YOY Growth",$N58*(1+$T58)/12,$S58/12),"")) -> 0 | AG58: =SUM(U58:AF58) -> 0 | AH58: =IFERROR(AG58/AG$16,"") | AJ58: =N58-AG58 -> 93.99
A59: 5950 - Certification Expense | B59: 65 | C59: 0 | D59: 0 | E59: 0 | F59: 0 | G59: 0 | H59: 0 | I59: 0 | J59: 0 | K59: 0 | L59: 0 | M59: 0 | N59: =SUM(B59:M59) -> 65 | O59: =IFERROR(N59/N$16,"") | R59: Even | S59: 0 | T59: 0.05 | U59: =IF($R59="Manual","",IFERROR(IF($R59="YOY Growth",$N59*(1+$T59)/12,$S59/12),"")) -> 0 | V59: =IF($R59="Manual","",IFERROR(IF($R59="YOY Growth",$N59*(1+$T59)/12,$S59/12),"")) -> 0 | W59: =IF($R59="Manual","",IFERROR(IF($R59="YOY Growth",$N59*(1+$T59)/12,$S59/12),"")) -> 0 | X59: =IF($R59="Manual","",IFERROR(IF($R59="YOY Growth",$N59*(1+$T59)/12,$S59/12),"")) -> 0 | Y59: =IF($R59="Manual","",IFERROR(IF($R59="YOY Growth",$N59*(1+$T59)/12,$S59/12),"")) -> 0 | Z59: =IF($R59="Manual","",IFERROR(IF($R59="YOY Growth",$N59*(1+$T59)/12,$S59/12),"")) -> 0 | AA59: =IF($R59="Manual","",IFERROR(IF($R59="YOY Growth",$N59*(1+$T59)/12,$S59/12),"")) -> 0 | AB59: =IF($R59="Manual","",IFERROR(IF($R59="YOY Growth",$N59*(1+$T59)/12,$S59/12),"")) -> 0 | ... AF59: =IF($R59="Manual","",IFERROR(IF($R59="YOY Growth",$N59*(1+$T59)/12,$S59/12),"")) -> 0 | AG59: =SUM(U59:AF59) -> 0 | AH59: =IFERROR(AG59/AG$16,"") | AJ59: =N59-AG59 -> 65
A60: 5980 - Employee Meals | B60: 0 | C60: 0 | D60: 0 | E60: 0 | F60: 0 | G60: 0 | H60: 0 | I60: 0 | J60: 0 | K60: 0 | L60: 0 | M60: 0 | N60: =SUM(B60:M60) -> 0 | O60: =IFERROR(N60/N$16,"") | R60: Even | S60: 0 | T60: 0.05 | U60: =IF($R60="Manual","",IFERROR(IF($R60="YOY Growth",$N60*(1+$T60)/12,$S60/12),"")) -> 0 | V60: =IF($R60="Manual","",IFERROR(IF($R60="YOY Growth",$N60*(1+$T60)/12,$S60/12),"")) -> 0 | W60: =IF($R60="Manual","",IFERROR(IF($R60="YOY Growth",$N60*(1+$T60)/12,$S60/12),"")) -> 0 | X60: =IF($R60="Manual","",IFERROR(IF($R60="YOY Growth",$N60*(1+$T60)/12,$S60/12),"")) -> 0 | Y60: =IF($R60="Manual","",IFERROR(IF($R60="YOY Growth",$N60*(1+$T60)/12,$S60/12),"")) -> 0 | Z60: =IF($R60="Manual","",IFERROR(IF($R60="YOY Growth",$N60*(1+$T60)/12,$S60/12),"")) -> 0 | AA60: =IF($R60="Manual","",IFERROR(IF($R60="YOY Growth",$N60*(1+$T60)/12,$S60/12),"")) -> 0 | AB60: =IF($R60="Manual","",IFERROR(IF($R60="YOY Growth",$N60*(1+$T60)/12,$S60/12),"")) -> 0 | ... AF60: =IF($R60="Manual","",IFERROR(IF($R60="YOY Growth",$N60*(1+$T60)/12,$S60/12),"")) -> 0 | AG60: =SUM(U60:AF60) -> 0 | AH60: =IFERROR(AG60/AG$16,"") | AJ60: =N60-AG60 -> 0
A61: Total - 5900 - Other COGS | B61: =SUM(B58:B60) -> 65 | C61: =SUM(C58:C60) -> 0 | D61: =SUM(D58:D60) -> 0 | E61: =SUM(E58:E60) -> 0 | F61: =SUM(F58:F60) -> 0 | G61: =SUM(G58:G60) -> 0 | H61: =SUM(H58:H60) -> 0 | I61: =SUM(I58:I60) -> 93.99 | ... M61: =SUM(M58:M60) -> 0 | N61: =SUM(B61:M61) -> 158.99 | O61: =IFERROR(N61/N$16,"") | U61: =SUM(U58:U60) -> 0 | V61: =SUM(V58:V60) -> 0 | W61: =SUM(W58:W60) -> 0 | X61: =SUM(X58:X60) -> 0 | Y61: =SUM(Y58:Y60) -> 0 | Z61: =SUM(Z58:Z60) -> 0 | AA61: =SUM(AA58:AA60) -> 0 | AB61: =SUM(AB58:AB60) -> 0 | ... AF61: =SUM(AF58:AF60) -> 0 | AG61: =SUM(U61:AF61) -> 0 | AH61: =IFERROR(AG61/AG$16,"") | AJ61: =N61-AG61 -> 158.99
A62: 5990 - Purchase Discounts | B62: 0 | C62: 0 | D62: 0 | E62: 0 | F62: 0 | G62: 0 | H62: 0 | I62: 0 | J62: 0 | K62: 0 | L62: 0 | M62: 0 | N62: =SUM(B62:M62) -> 0 | O62: =IFERROR(N62/N$16,"") | R62: Even | S62: 0 | T62: 0.05 | U62: =IF($R62="Manual","",IFERROR(IF($R62="YOY Growth",$N62*(1+$T62)/12,$S62/12),"")) -> 0 | V62: =IF($R62="Manual","",IFERROR(IF($R62="YOY Growth",$N62*(1+$T62)/12,$S62/12),"")) -> 0 | W62: =IF($R62="Manual","",IFERROR(IF($R62="YOY Growth",$N62*(1+$T62)/12,$S62/12),"")) -> 0 | X62: =IF($R62="Manual","",IFERROR(IF($R62="YOY Growth",$N62*(1+$T62)/12,$S62/12),"")) -> 0 | Y62: =IF($R62="Manual","",IFERROR(IF($R62="YOY Growth",$N62*(1+$T62)/12,$S62/12),"")) -> 0 | Z62: =IF($R62="Manual","",IFERROR(IF($R62="YOY Growth",$N62*(1+$T62)/12,$S62/12),"")) -> 0 | AA62: =IF($R62="Manual","",IFERROR(IF($R62="YOY Growth",$N62*(1+$T62)/12,$S62/12),"")) -> 0 | AB62: =IF($R62="Manual","",IFERROR(IF($R62="YOY Growth",$N62*(1+$T62)/12,$S62/12),"")) -> 0 | ... AF62: =IF($R62="Manual","",IFERROR(IF($R62="YOY Growth",$N62*(1+$T62)/12,$S62/12),"")) -> 0 | AG62: =SUM(U62:AF62) -> 0 | AH62: =IFERROR(AG62/AG$16,"") | AJ62: =N62-AG62 -> 0
A63: Total - Cost Of Sales | B63: =B37+B38+B39+B40+B41+B42+B56+B61+B62 -> 9555.22 | C63: =C37+C38+C39+C40+C41+C42+C56+C61+C62 -> 5166.38 | D63: =D37+D38+D39+D40+D41+D42+D56+D61+D62 -> 8893.04 | E63: =E37+E38+E39+E40+E41+E42+E56+E61+E62 -> 6751.93 | F63: =F37+F38+F39+F40+F41+F42+F56+F61+F62 -> 16983.8 | G63: =G37+G38+G39+G40+G41+G42+G56+G61+G62 -> 3533 | H63: =H37+H38+H39+H40+H41+H42+H56+H61+H62 -> 3822.76 | I63: =I37+I38+I39+I40+I41+I42+I56+I61+I62 -> 7082.7 | ... M63: =M37+M38+M39+M40+M41+M42+M56+M61+M62 -> 9700 | N63: =SUM(B63:M63) -> 115988.83 | O63: =IFERROR(N63/N$16,"") | U63: =U37+U38+U39+U40+U41+U42+U56+U61+U62 -> 18573.905 | V63: =V37+V38+V39+V40+V41+V42+V56+V61+V62 -> 12382.603 | W63: =W37+W38+W39+W40+W41+W42+W56+W61+W62 -> 0 | X63: =X37+X38+X39+X40+X41+X42+X56+X61+X62 -> 29222.943 | Y63: =Y37+Y38+Y39+Y40+Y41+Y42+Y56+Y61+Y62 -> 23031.642 | Z63: =Z37+Z38+Z39+Z40+Z41+Z42+Z56+Z61+Z62 -> 33680.681 | AA63: =AA37+AA38+AA39+AA40+AA41+AA42+AA56+AA61+AA62 -> 29222.943 | AB63: =AB37+AB38+AB39+AB40+AB41+AB42+AB56+AB61+AB62 -> 35414.245 | ... AF63: =AF37+AF38+AF39+AF40+AF41+AF42+AF56+AF61+AF62 -> 58445.887 | AG63: =SUM(U63:AF63) -> 388813.74 | AH63: =IFERROR(AG63/AG$16,"") | AJ63: =N63-AG63 -> -272824.91
A64: Gross Profit | B64: =B16-B63 -> -9555.22 | C64: =C16-C63 -> -5166.38 | D64: =D16-D63 -> -8893.04 | E64: =E16-E63 -> -6751.93 | F64: =F16-F63 -> -16983.8 | G64: =G16-G63 -> -3533 | H64: =H16-H63 -> -3822.76 | I64: =I16-I63 -> -7082.7 | ... M64: =M16-M63 -> -9700 | N64: =SUM(B64:M64) -> -115988.83 | O64: =IFERROR(N64/N$16,"") | U64: =U16-U63 -> -18573.905 | V64: =V16-V63 -> -12382.603 | W64: =W16-W63 -> 0 | X64: =X16-X63 -> -29222.943 | Y64: =Y16-Y63 -> -23031.642 | Z64: =Z16-Z63 -> -33680.681 | AA64: =AA16-AA63 -> -29222.943 | AB64: =AB16-AB63 -> -35414.245 | ... AF64: =AF16-AF63 -> -58445.887 | AG64: =SUM(U64:AF64) -> -388813.74 | AH64: =IFERROR(AG64/AG$16,"") | AJ64: =AG64-N64 -> -272824.91
A65: Expense
A66: 6000 - Labor Expense - SG&A
A67: 6610 - Salaries and Wages - SG&A | B67: 38333.32 | C67: 27897.23 | D67: 38333.32 | E67: 48324.65 | F67: 69698.22 | G67: 57128.18 | H67: 57596.54 | I67: 62503.19 | J67: 97900 | K67: 116100 | L67: 118400 | M67: 118400 | N67: =SUM(B67:M67) -> 850614.65 | O67: =IFERROR(N67/N$16,"") | U67: ='Fld Eng Budget'!B78 -> 56722.583 | V67: ='Fld Eng Budget'!C78 -> 56722.583 | W67: ='Fld Eng Budget'!D78 -> 56722.583 | X67: ='Fld Eng Budget'!E78 -> 56722.583 | Y67: ='Fld Eng Budget'!F78 -> 56722.583 | Z67: ='Fld Eng Budget'!G78 -> 56722.583 | AA67: ='Fld Eng Budget'!H78 -> 56722.583 | AB67: ='Fld Eng Budget'!I78 -> 62139.25 | ... AF67: ='Fld Eng Budget'!M78 -> 64003.427 | AG67: =SUM(U67:AF67) -> 713346.87 | AH67: =IFERROR(AG67/AG$16,"") | AJ67: =N67-AG67 -> 137267.78
A68: 6630 - Payroll Taxes - SG&A | B68: 2025.41 | C68: 6652.05 | D68: 1617.41 | E68: 1966.43 | F68: 2481.03 | G68: 1978.27 | H68: 1940.51 | I68: 3746.33 | J68: 3916 | K68: 4644 | L68: 4736 | M68: 4736 | N68: =SUM(B68:M68) -> 40439.44 | O68: =IFERROR(N68/N$16,"") | U68: ='Fld Eng Budget'!B79 -> 3857.1357 | V68: ='Fld Eng Budget'!C79 -> 3857.1357 | W68: ='Fld Eng Budget'!D79 -> 3857.1357 | X68: ='Fld Eng Budget'!E79 -> 3857.1357 | Y68: ='Fld Eng Budget'!F79 -> 3857.1357 | Z68: ='Fld Eng Budget'!G79 -> 3857.1357 | AA68: ='Fld Eng Budget'!H79 -> 3857.1357 | AB68: ='Fld Eng Budget'!I79 -> 4225.469 | ... AF68: ='Fld Eng Budget'!M79 -> 4352.2331 | AG68: =SUM(U68:AF68) -> 48507.587 | AH68: =IFERROR(AG68/AG$16,"") | AJ68: =N68-AG68 -> -8068.1469
A69: 6640 - Benefits - SG&A | B69: 2047.73 | C69: 5252.34 | D69: 3981.87 | E69: 4255.59 | F69: 4157.09 | G69: 4325.33 | H69: 3959.5 | I69: 3814.97 | J69: 10573 | K69: 12539 | L69: 12787 | M69: 12787 | N69: =SUM(B69:M69) -> 80480.42 | O69: =IFERROR(N69/N$16,"") | U69: ='Fld Eng Budget'!B80 -> 9302.5037 | V69: ='Fld Eng Budget'!C80 -> 9302.5037 | W69: ='Fld Eng Budget'!D80 -> 9302.5037 | X69: ='Fld Eng Budget'!E80 -> 9302.5037 | Y69: ='Fld Eng Budget'!F80 -> 9302.5037 | Z69: ='Fld Eng Budget'!G80 -> 9302.5037 | AA69: ='Fld Eng Budget'!H80 -> 9302.5037 | AB69: ='Fld Eng Budget'!I80 -> 10190.837 | ... AF69: ='Fld Eng Budget'!M80 -> 10496.562 | AG69: =SUM(U69:AF69) -> 116988.89 | AH69: =IFERROR(AG69/AG$16,"") | AJ69: =N69-AG69 -> -36508.466
A70: 6650 - Commissions - SG&A | B70: 0 | C70: 0 | D70: 0 | E70: 0 | F70: 0 | G70: 0 | H70: 0 | I70: 0 | J70: 0 | K70: 0 | L70: 0 | M70: 0 | N70: =SUM(B70:M70) -> 0 | O70: =IFERROR(N70/N$16,"") | R70: Even | S70: 0 | T70: 0.05 | U70: =IF($R70="Manual","",IFERROR(IF($R70="YOY Growth",$N70*(1+$T70)/12,$S70/12),"")) -> 0 | V70: =IF($R70="Manual","",IFERROR(IF($R70="YOY Growth",$N70*(1+$T70)/12,$S70/12),"")) -> 0 | W70: =IF($R70="Manual","",IFERROR(IF($R70="YOY Growth",$N70*(1+$T70)/12,$S70/12),"")) -> 0 | X70: =IF($R70="Manual","",IFERROR(IF($R70="YOY Growth",$N70*(1+$T70)/12,$S70/12),"")) -> 0 | Y70: =IF($R70="Manual","",IFERROR(IF($R70="YOY Growth",$N70*(1+$T70)/12,$S70/12),"")) -> 0 | Z70: =IF($R70="Manual","",IFERROR(IF($R70="YOY Growth",$N70*(1+$T70)/12,$S70/12),"")) -> 0 | AA70: =IF($R70="Manual","",IFERROR(IF($R70="YOY Growth",$N70*(1+$T70)/12,$S70/12),"")) -> 0 | AB70: =IF($R70="Manual","",IFERROR(IF($R70="YOY Growth",$N70*(1+$T70)/12,$S70/12),"")) -> 0 | ... AF70: =IF($R70="Manual","",IFERROR(IF($R70="YOY Growth",$N70*(1+$T70)/12,$S70/12),"")) -> 0 | AG70: =SUM(U70:AF70) -> 0 | AH70: =IFERROR(AG70/AG$16,"") | AJ70: =N70-AG70 -> 0
A71: 6660 - Recruiting | B71: 0 | C71: 0 | D71: 0 | E71: 0 | F71: 0 | G71: 0 | H71: 0 | I71: 0 | J71: 0 | K71: 0 | L71: 0 | M71: 0 | N71: =SUM(B71:M71) -> 0 | O71: =IFERROR(N71/N$16,"") | R71: Even | S71: 0 | T71: 0.05 | U71: =IF($R71="Manual","",IFERROR(IF($R71="YOY Growth",$N71*(1+$T71)/12,$S71/12),"")) -> 0 | V71: =IF($R71="Manual","",IFERROR(IF($R71="YOY Growth",$N71*(1+$T71)/12,$S71/12),"")) -> 0 | W71: =IF($R71="Manual","",IFERROR(IF($R71="YOY Growth",$N71*(1+$T71)/12,$S71/12),"")) -> 0 | X71: =IF($R71="Manual","",IFERROR(IF($R71="YOY Growth",$N71*(1+$T71)/12,$S71/12),"")) -> 0 | Y71: =IF($R71="Manual","",IFERROR(IF($R71="YOY Growth",$N71*(1+$T71)/12,$S71/12),"")) -> 0 | Z71: =IF($R71="Manual","",IFERROR(IF($R71="YOY Growth",$N71*(1+$T71)/12,$S71/12),"")) -> 0 | AA71: =IF($R71="Manual","",IFERROR(IF($R71="YOY Growth",$N71*(1+$T71)/12,$S71/12),"")) -> 0 | AB71: =IF($R71="Manual","",IFERROR(IF($R71="YOY Growth",$N71*(1+$T71)/12,$S71/12),"")) -> 0 | ... AF71: =IF($R71="Manual","",IFERROR(IF($R71="YOY Growth",$N71*(1+$T71)/12,$S71/12),"")) -> 0 | AG71: =SUM(U71:AF71) -> 0 | AH71: =IFERROR(AG71/AG$16,"") | AJ71: =N71-AG71 -> 0
A72: 6670 - Stock Compensation Expense | B72: 0 | C72: 0 | D72: 0 | E72: 0 | F72: 0 | G72: 0 | H72: 0 | I72: 0 | J72: 0 | K72: 0 | L72: 0 | M72: 0 | N72: =SUM(B72:M72) -> 0 | O72: =IFERROR(N72/N$16,"") | R72: Even | S72: 0 | T72: 0.05 | U72: =IF($R72="Manual","",IFERROR(IF($R72="YOY Growth",$N72*(1+$T72)/12,$S72/12),"")) -> 0 | V72: =IF($R72="Manual","",IFERROR(IF($R72="YOY Growth",$N72*(1+$T72)/12,$S72/12),"")) -> 0 | W72: =IF($R72="Manual","",IFERROR(IF($R72="YOY Growth",$N72*(1+$T72)/12,$S72/12),"")) -> 0 | X72: =IF($R72="Manual","",IFERROR(IF($R72="YOY Growth",$N72*(1+$T72)/12,$S72/12),"")) -> 0 | Y72: =IF($R72="Manual","",IFERROR(IF($R72="YOY Growth",$N72*(1+$T72)/12,$S72/12),"")) -> 0 | Z72: =IF($R72="Manual","",IFERROR(IF($R72="YOY Growth",$N72*(1+$T72)/12,$S72/12),"")) -> 0 | AA72: =IF($R72="Manual","",IFERROR(IF($R72="YOY Growth",$N72*(1+$T72)/12,$S72/12),"")) -> 0 | AB72: =IF($R72="Manual","",IFERROR(IF($R72="YOY Growth",$N72*(1+$T72)/12,$S72/12),"")) -> 0 | ... AF72: =IF($R72="Manual","",IFERROR(IF($R72="YOY Growth",$N72*(1+$T72)/12,$S72/12),"")) -> 0 | AG72: =SUM(U72:AF72) -> 0 | AH72: =IFERROR(AG72/AG$16,"") | AJ72: =N72-AG72 -> 0
A73: Total - 6000 - Labor Expense - SG&A | B73: =SUM(B67:B72) -> 42406.46 | C73: =SUM(C67:C72) -> 39801.62 | D73: =SUM(D67:D72) -> 43932.6 | E73: =SUM(E67:E72) -> 54546.67 | F73: =SUM(F67:F72) -> 76336.34 | G73: =SUM(G67:G72) -> 63431.78 | H73: =SUM(H67:H72) -> 63496.55 | I73: =SUM(I67:I72) -> 70064.49 | ... M73: =SUM(M67:M72) -> 135923 | N73: =SUM(B73:M73) -> 971534.51 | O73: =IFERROR(N73/N$16,"") | U73: =SUM(U67:U72) -> 69882.223 | V73: =SUM(V67:V72) -> 69882.223 | W73: =SUM(W67:W72) -> 69882.223 | X73: =SUM(X67:X72) -> 69882.223 | Y73: =SUM(Y67:Y72) -> 69882.223 | Z73: =SUM(Z67:Z72) -> 69882.223 | AA73: =SUM(AA67:AA72) -> 69882.223 | AB73: =SUM(AB67:AB72) -> 76555.556 | ... AF73: =SUM(AF67:AF72) -> 78852.223 | AG73: =SUM(U73:AF73) -> 878843.34 | AH73: =IFERROR(AG73/AG$16,"") | AJ73: =N73-AG73 -> 92691.171
A74: 6100 - Travel | B74: 0 | C74: -773.5 | D74: 1130.73 | E74: 8303.22 | F74: 2747.17 | G74: 7608.77 | H74: 1346.83 | I74: 2646.86 | J74: 3000 | K74: 3000 | L74: 3000 | M74: 3000 | N74: =SUM(B74:M74) -> 35010.08 | O74: =IFERROR(N74/N$16,"") | R74: Manual | S74: 0 | T74: 0.05 | U74: ='Fld Eng Budget'!B76 -> 3769.5938 | V74: ='Fld Eng Budget'!C76 -> 3769.5938 | W74: ='Fld Eng Budget'!D76 -> 3769.5938 | X74: ='Fld Eng Budget'!E76 -> 3769.5938 | Y74: ='Fld Eng Budget'!F76 -> 3769.5938 | Z74: ='Fld Eng Budget'!G76 -> 3769.5938 | AA74: ='Fld Eng Budget'!H76 -> 3769.5938 | AB74: ='Fld Eng Budget'!I76 -> 3769.5938 | ... AF74: ='Fld Eng Budget'!M76 -> 3769.5938 | AG74: =SUM(U74:AF74) -> 45235.125 | AH74: =IFERROR(AG74/AG$16,"") | AJ74: =N74-AG74 -> -10225.045
A75: 6110 - Travel Meals | B75: 12.29 | C75: 0 | D75: 0 | E75: 2986.15 | F75: 0 | G75: 475.67 | H75: 234.79 | I75: 0 | J75: 400 | K75: 400 | L75: 400 | M75: 400 | N75: =SUM(B75:M75) -> 5308.9 | O75: =IFERROR(N75/N$16,"") | R75: Manual | S75: 0 | T75: 0.05 | U75: ='Fld Eng Budget'!B77 -> 604.61406 | V75: ='Fld Eng Budget'!C77 -> 604.61406 | W75: ='Fld Eng Budget'!D77 -> 604.61406 | X75: ='Fld Eng Budget'!E77 -> 604.61406 | Y75: ='Fld Eng Budget'!F77 -> 604.61406 | Z75: ='Fld Eng Budget'!G77 -> 604.61406 | AA75: ='Fld Eng Budget'!H77 -> 604.61406 | AB75: ='Fld Eng Budget'!I77 -> 604.61406 | ... AF75: ='Fld Eng Budget'!M77 -> 604.61406 | AG75: =SUM(U75:AF75) -> 7255.3687 | AH75: =IFERROR(AG75/AG$16,"") | AJ75: =N75-AG75 -> -1946.4688
A76: 6120 - Meals and Entertainment | B76: 0 | C76: 0 | D76: 0 | E76: 28.2 | F76: 0 | G76: 0 | H76: 0 | I76: 0 | J76: 0 | K76: 0 | L76: 0 | M76: 0 | N76: =SUM(B76:M76) -> 28.2 | O76: =IFERROR(N76/N$16,"") | R76: Even | S76: 0 | T76: 0.05 | U76: =IF($R76="Manual","",IFERROR(IF($R76="YOY Growth",$N76*(1+$T76)/12,$S76/12),"")) -> 0 | V76: =IF($R76="Manual","",IFERROR(IF($R76="YOY Growth",$N76*(1+$T76)/12,$S76/12),"")) -> 0 | W76: =IF($R76="Manual","",IFERROR(IF($R76="YOY Growth",$N76*(1+$T76)/12,$S76/12),"")) -> 0 | X76: =IF($R76="Manual","",IFERROR(IF($R76="YOY Growth",$N76*(1+$T76)/12,$S76/12),"")) -> 0 | Y76: =IF($R76="Manual","",IFERROR(IF($R76="YOY Growth",$N76*(1+$T76)/12,$S76/12),"")) -> 0 | Z76: =IF($R76="Manual","",IFERROR(IF($R76="YOY Growth",$N76*(1+$T76)/12,$S76/12),"")) -> 0 | AA76: =IF($R76="Manual","",IFERROR(IF($R76="YOY Growth",$N76*(1+$T76)/12,$S76/12),"")) -> 0 | AB76: =IF($R76="Manual","",IFERROR(IF($R76="YOY Growth",$N76*(1+$T76)/12,$S76/12),"")) -> 0 | ... AF76: =IF($R76="Manual","",IFERROR(IF($R76="YOY Growth",$N76*(1+$T76)/12,$S76/12),"")) -> 0 | AG76: =SUM(U76:AF76) -> 0 | AH76: =IFERROR(AG76/AG$16,"") | AJ76: =N76-AG76 -> 28.2
A77: 6200 - Advertising | B77: 0 | C77: 0 | D77: 0 | E77: 0 | F77: 0 | G77: 0 | H77: 0 | I77: 0 | J77: 0 | K77: 0 | L77: 0 | M77: 0 | N77: =SUM(B77:M77) -> 0 | O77: =IFERROR(N77/N$16,"") | R77: Even | S77: 0 | T77: 0.05 | U77: =IF($R77="Manual","",IFERROR(IF($R77="YOY Growth",$N77*(1+$T77)/12,$S77/12),"")) -> 0 | V77: =IF($R77="Manual","",IFERROR(IF($R77="YOY Growth",$N77*(1+$T77)/12,$S77/12),"")) -> 0 | W77: =IF($R77="Manual","",IFERROR(IF($R77="YOY Growth",$N77*(1+$T77)/12,$S77/12),"")) -> 0 | X77: =IF($R77="Manual","",IFERROR(IF($R77="YOY Growth",$N77*(1+$T77)/12,$S77/12),"")) -> 0 | Y77: =IF($R77="Manual","",IFERROR(IF($R77="YOY Growth",$N77*(1+$T77)/12,$S77/12),"")) -> 0 | Z77: =IF($R77="Manual","",IFERROR(IF($R77="YOY Growth",$N77*(1+$T77)/12,$S77/12),"")) -> 0 | AA77: =IF($R77="Manual","",IFERROR(IF($R77="YOY Growth",$N77*(1+$T77)/12,$S77/12),"")) -> 0 | AB77: =IF($R77="Manual","",IFERROR(IF($R77="YOY Growth",$N77*(1+$T77)/12,$S77/12),"")) -> 0 | ... AF77: =IF($R77="Manual","",IFERROR(IF($R77="YOY Growth",$N77*(1+$T77)/12,$S77/12),"")) -> 0 | AG77: =SUM(U77:AF77) -> 0 | AH77: =IFERROR(AG77/AG$16,"") | AJ77: =N77-AG77 -> 0
A78: 6210 - Marketing Expense | B78: 0 | C78: 0 | D78: 0 | E78: 0 | F78: 0 | G78: 0 | H78: 0 | I78: 0 | J78: 0 | K78: 0 | L78: 0 | M78: 0 | N78: =SUM(B78:M78) -> 0 | O78: =IFERROR(N78/N$16,"") | R78: Even | S78: 0 | T78: 0.05 | U78: =IF($R78="Manual","",IFERROR(IF($R78="YOY Growth",$N78*(1+$T78)/12,$S78/12),"")) -> 0 | V78: =IF($R78="Manual","",IFERROR(IF($R78="YOY Growth",$N78*(1+$T78)/12,$S78/12),"")) -> 0 | W78: =IF($R78="Manual","",IFERROR(IF($R78="YOY Growth",$N78*(1+$T78)/12,$S78/12),"")) -> 0 | X78: =IF($R78="Manual","",IFERROR(IF($R78="YOY Growth",$N78*(1+$T78)/12,$S78/12),"")) -> 0 | Y78: =IF($R78="Manual","",IFERROR(IF($R78="YOY Growth",$N78*(1+$T78)/12,$S78/12),"")) -> 0 | Z78: =IF($R78="Manual","",IFERROR(IF($R78="YOY Growth",$N78*(1+$T78)/12,$S78/12),"")) -> 0 | AA78: =IF($R78="Manual","",IFERROR(IF($R78="YOY Growth",$N78*(1+$T78)/12,$S78/12),"")) -> 0 | AB78: =IF($R78="Manual","",IFERROR(IF($R78="YOY Growth",$N78*(1+$T78)/12,$S78/12),"")) -> 0 | ... AF78: =IF($R78="Manual","",IFERROR(IF($R78="YOY Growth",$N78*(1+$T78)/12,$S78/12),"")) -> 0 | AG78: =SUM(U78:AF78) -> 0 | AH78: =IFERROR(AG78/AG$16,"") | AJ78: =N78-AG78 -> 0
A79: 6220 - Trade Shows | B79: 0 | C79: 0 | D79: 0 | E79: 2674.33 | F79: 0 | G79: 0 | H79: 0 | I79: 0 | J79: 1000 | K79: 1000 | L79: 3000 | M79: 1000 | N79: =SUM(B79:M79) -> 8674.33 | O79: =IFERROR(N79/N$16,"") | R79: Even | S79: 0 | T79: 0.05 | U79: =IF($R79="Manual","",IFERROR(IF($R79="YOY Growth",$N79*(1+$T79)/12,$S79/12),"")) -> 0 | V79: =IF($R79="Manual","",IFERROR(IF($R79="YOY Growth",$N79*(1+$T79)/12,$S79/12),"")) -> 0 | W79: =IF($R79="Manual","",IFERROR(IF($R79="YOY Growth",$N79*(1+$T79)/12,$S79/12),"")) -> 0 | X79: =IF($R79="Manual","",IFERROR(IF($R79="YOY Growth",$N79*(1+$T79)/12,$S79/12),"")) -> 0 | Y79: =IF($R79="Manual","",IFERROR(IF($R79="YOY Growth",$N79*(1+$T79)/12,$S79/12),"")) -> 0 | Z79: =IF($R79="Manual","",IFERROR(IF($R79="YOY Growth",$N79*(1+$T79)/12,$S79/12),"")) -> 0 | AA79: =IF($R79="Manual","",IFERROR(IF($R79="YOY Growth",$N79*(1+$T79)/12,$S79/12),"")) -> 0 | AB79: =IF($R79="Manual","",IFERROR(IF($R79="YOY Growth",$N79*(1+$T79)/12,$S79/12),"")) -> 0 | ... AF79: =IF($R79="Manual","",IFERROR(IF($R79="YOY Growth",$N79*(1+$T79)/12,$S79/12),"")) -> 0 | AG79: =SUM(U79:AF79) -> 0 | AH79: =IFERROR(AG79/AG$16,"") | AJ79: =N79-AG79 -> 8674.33
A80: 6400 - Memberships and Subscriptions | B80: 35.89 | C80: 0 | D80: 0 | E80: 0 | F80: 0 | G80: 0 | H80: 0 | I80: 0 | J80: 0 | K80: 0 | L80: 0 | M80: 0 | N80: =SUM(B80:M80) -> 35.89 | O80: =IFERROR(N80/N$16,"") | R80: Even | S80: 0 | T80: 0.05 | U80: =IF($R80="Manual","",IFERROR(IF($R80="YOY Growth",$N80*(1+$T80)/12,$S80/12),"")) -> 0 | V80: =IF($R80="Manual","",IFERROR(IF($R80="YOY Growth",$N80*(1+$T80)/12,$S80/12),"")) -> 0 | W80: =IF($R80="Manual","",IFERROR(IF($R80="YOY Growth",$N80*(1+$T80)/12,$S80/12),"")) -> 0 | X80: =IF($R80="Manual","",IFERROR(IF($R80="YOY Growth",$N80*(1+$T80)/12,$S80/12),"")) -> 0 | Y80: =IF($R80="Manual","",IFERROR(IF($R80="YOY Growth",$N80*(1+$T80)/12,$S80/12),"")) -> 0 | Z80: =IF($R80="Manual","",IFERROR(IF($R80="YOY Growth",$N80*(1+$T80)/12,$S80/12),"")) -> 0 | AA80: =IF($R80="Manual","",IFERROR(IF($R80="YOY Growth",$N80*(1+$T80)/12,$S80/12),"")) -> 0 | AB80: =IF($R80="Manual","",IFERROR(IF($R80="YOY Growth",$N80*(1+$T80)/12,$S80/12),"")) -> 0 | ... AF80: =IF($R80="Manual","",IFERROR(IF($R80="YOY Growth",$N80*(1+$T80)/12,$S80/12),"")) -> 0 | AG80: =SUM(U80:AF80) -> 0 | AH80: =IFERROR(AG80/AG$16,"") | AJ80: =N80-AG80 -> 35.89
A81: 6500 - Demos
A82: 6510 - Storage Facilities - Demos | B82: 0 | C82: 0 | D82: 0 | E82: 0 | F82: 0 | G82: 0 | H82: 0 | I82: 0 | J82: 0 | K82: 0 | L82: 0 | M82: 0 | N82: =SUM(B82:M82) -> 0 | O82: =IFERROR(N82/N$16,"") | R82: Even | S82: 0 | T82: 0.05 | U82: =IF($R82="Manual","",IFERROR(IF($R82="YOY Growth",$N82*(1+$T82)/12,$S82/12),"")) -> 0 | V82: =IF($R82="Manual","",IFERROR(IF($R82="YOY Growth",$N82*(1+$T82)/12,$S82/12),"")) -> 0 | W82: =IF($R82="Manual","",IFERROR(IF($R82="YOY Growth",$N82*(1+$T82)/12,$S82/12),"")) -> 0 | X82: =IF($R82="Manual","",IFERROR(IF($R82="YOY Growth",$N82*(1+$T82)/12,$S82/12),"")) -> 0 | Y82: =IF($R82="Manual","",IFERROR(IF($R82="YOY Growth",$N82*(1+$T82)/12,$S82/12),"")) -> 0 | Z82: =IF($R82="Manual","",IFERROR(IF($R82="YOY Growth",$N82*(1+$T82)/12,$S82/12),"")) -> 0 | AA82: =IF($R82="Manual","",IFERROR(IF($R82="YOY Growth",$N82*(1+$T82)/12,$S82/12),"")) -> 0 | AB82: =IF($R82="Manual","",IFERROR(IF($R82="YOY Growth",$N82*(1+$T82)/12,$S82/12),"")) -> 0 | ... AF82: =IF($R82="Manual","",IFERROR(IF($R82="YOY Growth",$N82*(1+$T82)/12,$S82/12),"")) -> 0 | AG82: =SUM(U82:AF82) -> 0 | AH82: =IFERROR(AG82/AG$16,"") | AJ82: =N82-AG82 -> 0
A83: 6520 - Truck Rental - Demos | B83: 0 | C83: 0 | D83: 0 | E83: 0 | F83: 0 | G83: 0 | H83: 0 | I83: 0 | J83: 0 | K83: 0 | L83: 0 | M83: 0 | N83: =SUM(B83:M83) -> 0 | O83: =IFERROR(N83/N$16,"") | R83: Even | S83: 0 | T83: 0.05 | U83: =IF($R83="Manual","",IFERROR(IF($R83="YOY Growth",$N83*(1+$T83)/12,$S83/12),"")) -> 0 | V83: =IF($R83="Manual","",IFERROR(IF($R83="YOY Growth",$N83*(1+$T83)/12,$S83/12),"")) -> 0 | W83: =IF($R83="Manual","",IFERROR(IF($R83="YOY Growth",$N83*(1+$T83)/12,$S83/12),"")) -> 0 | X83: =IF($R83="Manual","",IFERROR(IF($R83="YOY Growth",$N83*(1+$T83)/12,$S83/12),"")) -> 0 | Y83: =IF($R83="Manual","",IFERROR(IF($R83="YOY Growth",$N83*(1+$T83)/12,$S83/12),"")) -> 0 | Z83: =IF($R83="Manual","",IFERROR(IF($R83="YOY Growth",$N83*(1+$T83)/12,$S83/12),"")) -> 0 | AA83: =IF($R83="Manual","",IFERROR(IF($R83="YOY Growth",$N83*(1+$T83)/12,$S83/12),"")) -> 0 | AB83: =IF($R83="Manual","",IFERROR(IF($R83="YOY Growth",$N83*(1+$T83)/12,$S83/12),"")) -> 0 | ... AF83: =IF($R83="Manual","",IFERROR(IF($R83="YOY Growth",$N83*(1+$T83)/12,$S83/12),"")) -> 0 | AG83: =SUM(U83:AF83) -> 0 | AH83: =IFERROR(AG83/AG$16,"") | AJ83: =N83-AG83 -> 0
A84: 6530 - Other Demo Expense | B84: 0 | C84: 0 | D84: 0 | E84: 0 | F84: 0 | G84: 20 | H84: 0 | I84: 0 | J84: 0 | K84: 0 | L84: 0 | M84: 0 | N84: =SUM(B84:M84) -> 20 | O84: =IFERROR(N84/N$16,"") | R84: Even | S84: 0 | T84: 0.05 | U84: =IF($R84="Manual","",IFERROR(IF($R84="YOY Growth",$N84*(1+$T84)/12,$S84/12),"")) -> 0 | V84: =IF($R84="Manual","",IFERROR(IF($R84="YOY Growth",$N84*(1+$T84)/12,$S84/12),"")) -> 0 | W84: =IF($R84="Manual","",IFERROR(IF($R84="YOY Growth",$N84*(1+$T84)/12,$S84/12),"")) -> 0 | X84: =IF($R84="Manual","",IFERROR(IF($R84="YOY Growth",$N84*(1+$T84)/12,$S84/12),"")) -> 0 | Y84: =IF($R84="Manual","",IFERROR(IF($R84="YOY Growth",$N84*(1+$T84)/12,$S84/12),"")) -> 0 | Z84: =IF($R84="Manual","",IFERROR(IF($R84="YOY Growth",$N84*(1+$T84)/12,$S84/12),"")) -> 0 | AA84: =IF($R84="Manual","",IFERROR(IF($R84="YOY Growth",$N84*(1+$T84)/12,$S84/12),"")) -> 0 | AB84: =IF($R84="Manual","",IFERROR(IF($R84="YOY Growth",$N84*(1+$T84)/12,$S84/12),"")) -> 0 | ... AF84: =IF($R84="Manual","",IFERROR(IF($R84="YOY Growth",$N84*(1+$T84)/12,$S84/12),"")) -> 0 | AG84: =SUM(U84:AF84) -> 0 | AH84: =IFERROR(AG84/AG$16,"") | AJ84: =N84-AG84 -> 20
A85: 6540 - Travel - Demos | B85: 1118.97 | C85: 1642.61 | D85: 0 | E85: 1638.14 | F85: 492.8 | G85: 0 | H85: 0 | I85: 0 | J85: 500 | K85: 500 | L85: 1500 | M85: 500 | N85: =SUM(B85:M85) -> 7892.52 | O85: =IFERROR(N85/N$16,"") | R85: Even | S85: 0 | T85: 0.05 | U85: =IF($R85="Manual","",IFERROR(IF($R85="YOY Growth",$N85*(1+$T85)/12,$S85/12),"")) -> 0 | V85: =IF($R85="Manual","",IFERROR(IF($R85="YOY Growth",$N85*(1+$T85)/12,$S85/12),"")) -> 0 | W85: =IF($R85="Manual","",IFERROR(IF($R85="YOY Growth",$N85*(1+$T85)/12,$S85/12),"")) -> 0 | X85: =IF($R85="Manual","",IFERROR(IF($R85="YOY Growth",$N85*(1+$T85)/12,$S85/12),"")) -> 0 | Y85: =IF($R85="Manual","",IFERROR(IF($R85="YOY Growth",$N85*(1+$T85)/12,$S85/12),"")) -> 0 | Z85: =IF($R85="Manual","",IFERROR(IF($R85="YOY Growth",$N85*(1+$T85)/12,$S85/12),"")) -> 0 | AA85: =IF($R85="Manual","",IFERROR(IF($R85="YOY Growth",$N85*(1+$T85)/12,$S85/12),"")) -> 0 | AB85: =IF($R85="Manual","",IFERROR(IF($R85="YOY Growth",$N85*(1+$T85)/12,$S85/12),"")) -> 0 | ... AF85: =IF($R85="Manual","",IFERROR(IF($R85="YOY Growth",$N85*(1+$T85)/12,$S85/12),"")) -> 0 | AG85: =SUM(U85:AF85) -> 0 | AH85: =IFERROR(AG85/AG$16,"") | AJ85: =N85-AG85 -> 7892.52
A86: 6550 - Meals - Demos | B86: 0 | C86: 196.09 | D86: 0 | E86: 0 | F86: 0 | G86: 0 | H86: 0 | I86: 0 | J86: 0 | K86: 0 | L86: 0 | M86: 0 | N86: =SUM(B86:M86) -> 196.09 | O86: =IFERROR(N86/N$16,"") | R86: Even | S86: 0 | T86: 0.05 | U86: =IF($R86="Manual","",IFERROR(IF($R86="YOY Growth",$N86*(1+$T86)/12,$S86/12),"")) -> 0 | V86: =IF($R86="Manual","",IFERROR(IF($R86="YOY Growth",$N86*(1+$T86)/12,$S86/12),"")) -> 0 | W86: =IF($R86="Manual","",IFERROR(IF($R86="YOY Growth",$N86*(1+$T86)/12,$S86/12),"")) -> 0 | X86: =IF($R86="Manual","",IFERROR(IF($R86="YOY Growth",$N86*(1+$T86)/12,$S86/12),"")) -> 0 | Y86: =IF($R86="Manual","",IFERROR(IF($R86="YOY Growth",$N86*(1+$T86)/12,$S86/12),"")) -> 0 | Z86: =IF($R86="Manual","",IFERROR(IF($R86="YOY Growth",$N86*(1+$T86)/12,$S86/12),"")) -> 0 | AA86: =IF($R86="Manual","",IFERROR(IF($R86="YOY Growth",$N86*(1+$T86)/12,$S86/12),"")) -> 0 | AB86: =IF($R86="Manual","",IFERROR(IF($R86="YOY Growth",$N86*(1+$T86)/12,$S86/12),"")) -> 0 | ... AF86: =IF($R86="Manual","",IFERROR(IF($R86="YOY Growth",$N86*(1+$T86)/12,$S86/12),"")) -> 0 | AG86: =SUM(U86:AF86) -> 0 | AH86: =IFERROR(AG86/AG$16,"") | AJ86: =N86-AG86 -> 196.09
A87: Total - 6500 - Demos | B87: =SUM(B82:B86) -> 1118.97 | C87: =SUM(C82:C86) -> 1838.7 | D87: =SUM(D82:D86) -> 0 | E87: =SUM(E82:E86) -> 1638.14 | F87: =SUM(F82:F86) -> 492.8 | G87: =SUM(G82:G86) -> 20 | H87: =SUM(H82:H86) -> 0 | I87: =SUM(I82:I86) -> 0 | ... M87: =SUM(M82:M86) -> 500 | N87: =SUM(B87:M87) -> 8108.61 | O87: =IFERROR(N87/N$16,"") | U87: =SUM(U82:U86) -> 0 | V87: =SUM(V82:V86) -> 0 | W87: =SUM(W82:W86) -> 0 | X87: =SUM(X82:X86) -> 0 | Y87: =SUM(Y82:Y86) -> 0 | Z87: =SUM(Z82:Z86) -> 0 | AA87: =SUM(AA82:AA86) -> 0 | AB87: =SUM(AB82:AB86) -> 0 | ... AF87: =SUM(AF82:AF86) -> 0 | AG87: =SUM(U87:AF87) -> 0 | AH87: =IFERROR(AG87/AG$16,"") | AJ87: =N87-AG87 -> 8108.61
A88: 7000 - Professional Fees | B88: 0 | C88: 0 | D88: 0 | E88: 0 | F88: 0 | G88: 0 | H88: 0 | I88: 0 | J88: 0 | K88: 0 | L88: 0 | M88: 0 | N88: =SUM(B88:M88) -> 0 | O88: =IFERROR(N88/N$16,"") | R88: Even | S88: 0 | T88: 0.05 | U88: =IF($R88="Manual","",IFERROR(IF($R88="YOY Growth",$N88*(1+$T88)/12,$S88/12),"")) -> 0 | V88: =IF($R88="Manual","",IFERROR(IF($R88="YOY Growth",$N88*(1+$T88)/12,$S88/12),"")) -> 0 | W88: =IF($R88="Manual","",IFERROR(IF($R88="YOY Growth",$N88*(1+$T88)/12,$S88/12),"")) -> 0 | X88: =IF($R88="Manual","",IFERROR(IF($R88="YOY Growth",$N88*(1+$T88)/12,$S88/12),"")) -> 0 | Y88: =IF($R88="Manual","",IFERROR(IF($R88="YOY Growth",$N88*(1+$T88)/12,$S88/12),"")) -> 0 | Z88: =IF($R88="Manual","",IFERROR(IF($R88="YOY Growth",$N88*(1+$T88)/12,$S88/12),"")) -> 0 | AA88: =IF($R88="Manual","",IFERROR(IF($R88="YOY Growth",$N88*(1+$T88)/12,$S88/12),"")) -> 0 | AB88: =IF($R88="Manual","",IFERROR(IF($R88="YOY Growth",$N88*(1+$T88)/12,$S88/12),"")) -> 0 | ... AF88: =IF($R88="Manual","",IFERROR(IF($R88="YOY Growth",$N88*(1+$T88)/12,$S88/12),"")) -> 0 | AG88: =SUM(U88:AF88) -> 0 | AH88: =IFERROR(AG88/AG$16,"") | AJ88: =N88-AG88 -> 0
A89: 7050 - Education | B89: 0 | C89: 0 | D89: 0 | E89: 0 | F89: 0 | G89: 0 | H89: 0 | I89: 0 | J89: 0 | K89: 0 | L89: 0 | M89: 0 | N89: =SUM(B89:M89) -> 0 | O89: =IFERROR(N89/N$16,"") | R89: Even | S89: 0 | T89: 0.05 | U89: =IF($R89="Manual","",IFERROR(IF($R89="YOY Growth",$N89*(1+$T89)/12,$S89/12),"")) -> 0 | V89: =IF($R89="Manual","",IFERROR(IF($R89="YOY Growth",$N89*(1+$T89)/12,$S89/12),"")) -> 0 | W89: =IF($R89="Manual","",IFERROR(IF($R89="YOY Growth",$N89*(1+$T89)/12,$S89/12),"")) -> 0 | X89: =IF($R89="Manual","",IFERROR(IF($R89="YOY Growth",$N89*(1+$T89)/12,$S89/12),"")) -> 0 | Y89: =IF($R89="Manual","",IFERROR(IF($R89="YOY Growth",$N89*(1+$T89)/12,$S89/12),"")) -> 0 | Z89: =IF($R89="Manual","",IFERROR(IF($R89="YOY Growth",$N89*(1+$T89)/12,$S89/12),"")) -> 0 | AA89: =IF($R89="Manual","",IFERROR(IF($R89="YOY Growth",$N89*(1+$T89)/12,$S89/12),"")) -> 0 | AB89: =IF($R89="Manual","",IFERROR(IF($R89="YOY Growth",$N89*(1+$T89)/12,$S89/12),"")) -> 0 | ... AF89: =IF($R89="Manual","",IFERROR(IF($R89="YOY Growth",$N89*(1+$T89)/12,$S89/12),"")) -> 0 | AG89: =SUM(U89:AF89) -> 0 | AH89: =IFERROR(AG89/AG$16,"") | AJ89: =N89-AG89 -> 0
A90: 7100 - Legal Expense | B90: 0 | C90: 0 | D90: 0 | E90: 0 | F90: 0 | G90: 0 | H90: 0 | I90: 0 | J90: 0 | K90: 0 | L90: 0 | M90: 0 | N90: =SUM(B90:M90) -> 0 | O90: =IFERROR(N90/N$16,"") | R90: Even | S90: 0 | T90: 0.05 | U90: =IF($R90="Manual","",IFERROR(IF($R90="YOY Growth",$N90*(1+$T90)/12,$S90/12),"")) -> 0 | V90: =IF($R90="Manual","",IFERROR(IF($R90="YOY Growth",$N90*(1+$T90)/12,$S90/12),"")) -> 0 | W90: =IF($R90="Manual","",IFERROR(IF($R90="YOY Growth",$N90*(1+$T90)/12,$S90/12),"")) -> 0 | X90: =IF($R90="Manual","",IFERROR(IF($R90="YOY Growth",$N90*(1+$T90)/12,$S90/12),"")) -> 0 | Y90: =IF($R90="Manual","",IFERROR(IF($R90="YOY Growth",$N90*(1+$T90)/12,$S90/12),"")) -> 0 | Z90: =IF($R90="Manual","",IFERROR(IF($R90="YOY Growth",$N90*(1+$T90)/12,$S90/12),"")) -> 0 | AA90: =IF($R90="Manual","",IFERROR(IF($R90="YOY Growth",$N90*(1+$T90)/12,$S90/12),"")) -> 0 | AB90: =IF($R90="Manual","",IFERROR(IF($R90="YOY Growth",$N90*(1+$T90)/12,$S90/12),"")) -> 0 | ... AF90: =IF($R90="Manual","",IFERROR(IF($R90="YOY Growth",$N90*(1+$T90)/12,$S90/12),"")) -> 0 | AG90: =SUM(U90:AF90) -> 0 | AH90: =IFERROR(AG90/AG$16,"") | AJ90: =N90-AG90 -> 0
A91: 7200 - Contractors | B91: 0 | C91: 0 | D91: 29232.26 | E91: 32442.55 | F91: 36509.27 | G91: 56672.78 | H91: 0 | I91: 0 | J91: 0 | K91: 0 | L91: 0 | M91: 0 | N91: =SUM(B91:M91) -> 154856.86 | O91: =IFERROR(N91/N$16,"") | R91: Even | S91: 0 | T91: 0.05 | U91: =IF($R91="Manual","",IFERROR(IF($R91="YOY Growth",$N91*(1+$T91)/12,$S91/12),"")) -> 0 | V91: =IF($R91="Manual","",IFERROR(IF($R91="YOY Growth",$N91*(1+$T91)/12,$S91/12),"")) -> 0 | W91: =IF($R91="Manual","",IFERROR(IF($R91="YOY Growth",$N91*(1+$T91)/12,$S91/12),"")) -> 0 | X91: =IF($R91="Manual","",IFERROR(IF($R91="YOY Growth",$N91*(1+$T91)/12,$S91/12),"")) -> 0 | Y91: =IF($R91="Manual","",IFERROR(IF($R91="YOY Growth",$N91*(1+$T91)/12,$S91/12),"")) -> 0 | Z91: =IF($R91="Manual","",IFERROR(IF($R91="YOY Growth",$N91*(1+$T91)/12,$S91/12),"")) -> 0 | AA91: =IF($R91="Manual","",IFERROR(IF($R91="YOY Growth",$N91*(1+$T91)/12,$S91/12),"")) -> 0 | AB91: =IF($R91="Manual","",IFERROR(IF($R91="YOY Growth",$N91*(1+$T91)/12,$S91/12),"")) -> 0 | ... AF91: =IF($R91="Manual","",IFERROR(IF($R91="YOY Growth",$N91*(1+$T91)/12,$S91/12),"")) -> 0 | AG91: =SUM(U91:AF91) -> 0 | AH91: =IFERROR(AG91/AG$16,"") | AJ91: =N91-AG91 -> 154856.86
A92: 7300 - R&D Expense | B92: 281.89 | C92: 0 | D92: 148.38 | E92: 55.57 | F92: 0 | G92: 0 | H92: 0 | I92: 0 | J92: 0 | K92: 0 | L92: 0 | M92: 0 | N92: =SUM(B92:M92) -> 485.84 | O92: =IFERROR(N92/N$16,"") | R92: Even | S92: 0 | T92: 0.05 | U92: =IF($R92="Manual","",IFERROR(IF($R92="YOY Growth",$N92*(1+$T92)/12,$S92/12),"")) -> 0 | V92: =IF($R92="Manual","",IFERROR(IF($R92="YOY Growth",$N92*(1+$T92)/12,$S92/12),"")) -> 0 | W92: =IF($R92="Manual","",IFERROR(IF($R92="YOY Growth",$N92*(1+$T92)/12,$S92/12),"")) -> 0 | X92: =IF($R92="Manual","",IFERROR(IF($R92="YOY Growth",$N92*(1+$T92)/12,$S92/12),"")) -> 0 | Y92: =IF($R92="Manual","",IFERROR(IF($R92="YOY Growth",$N92*(1+$T92)/12,$S92/12),"")) -> 0 | Z92: =IF($R92="Manual","",IFERROR(IF($R92="YOY Growth",$N92*(1+$T92)/12,$S92/12),"")) -> 0 | AA92: =IF($R92="Manual","",IFERROR(IF($R92="YOY Growth",$N92*(1+$T92)/12,$S92/12),"")) -> 0 | AB92: =IF($R92="Manual","",IFERROR(IF($R92="YOY Growth",$N92*(1+$T92)/12,$S92/12),"")) -> 0 | ... AF92: =IF($R92="Manual","",IFERROR(IF($R92="YOY Growth",$N92*(1+$T92)/12,$S92/12),"")) -> 0 | AG92: =SUM(U92:AF92) -> 0 | AH92: =IFERROR(AG92/AG$16,"") | AJ92: =N92-AG92 -> 485.84
A93: 7500 - Facility Expenses | B93: 373 | C93: 0 | D93: 0 | E93: 0 | F93: 0 | G93: 0 | H93: 0 | I93: 0 | J93: 0 | K93: 0 | L93: 0 | M93: 0 | N93: =SUM(B93:M93) -> 373 | O93: =IFERROR(N93/N$16,"") | R93: Even | S93: 0 | T93: 0.05 | U93: =IF($R93="Manual","",IFERROR(IF($R93="YOY Growth",$N93*(1+$T93)/12,$S93/12),"")) -> 0 | V93: =IF($R93="Manual","",IFERROR(IF($R93="YOY Growth",$N93*(1+$T93)/12,$S93/12),"")) -> 0 | W93: =IF($R93="Manual","",IFERROR(IF($R93="YOY Growth",$N93*(1+$T93)/12,$S93/12),"")) -> 0 | X93: =IF($R93="Manual","",IFERROR(IF($R93="YOY Growth",$N93*(1+$T93)/12,$S93/12),"")) -> 0 | Y93: =IF($R93="Manual","",IFERROR(IF($R93="YOY Growth",$N93*(1+$T93)/12,$S93/12),"")) -> 0 | Z93: =IF($R93="Manual","",IFERROR(IF($R93="YOY Growth",$N93*(1+$T93)/12,$S93/12),"")) -> 0 | AA93: =IF($R93="Manual","",IFERROR(IF($R93="YOY Growth",$N93*(1+$T93)/12,$S93/12),"")) -> 0 | AB93: =IF($R93="Manual","",IFERROR(IF($R93="YOY Growth",$N93*(1+$T93)/12,$S93/12),"")) -> 0 | ... AF93: =IF($R93="Manual","",IFERROR(IF($R93="YOY Growth",$N93*(1+$T93)/12,$S93/12),"")) -> 0 | AG93: =SUM(U93:AF93) -> 0 | AH93: =IFERROR(AG93/AG$16,"") | AJ93: =N93-AG93 -> 373
A94: 7510 - Custodial | B94: 0 | C94: 0 | D94: 0 | E94: 0 | F94: 0 | G94: 0 | H94: 0 | I94: 0 | J94: 0 | K94: 0 | L94: 0 | M94: 0 | N94: =SUM(B94:M94) -> 0 | O94: =IFERROR(N94/N$16,"") | R94: Even | S94: 0 | T94: 0.05 | U94: =IF($R94="Manual","",IFERROR(IF($R94="YOY Growth",$N94*(1+$T94)/12,$S94/12),"")) -> 0 | V94: =IF($R94="Manual","",IFERROR(IF($R94="YOY Growth",$N94*(1+$T94)/12,$S94/12),"")) -> 0 | W94: =IF($R94="Manual","",IFERROR(IF($R94="YOY Growth",$N94*(1+$T94)/12,$S94/12),"")) -> 0 | X94: =IF($R94="Manual","",IFERROR(IF($R94="YOY Growth",$N94*(1+$T94)/12,$S94/12),"")) -> 0 | Y94: =IF($R94="Manual","",IFERROR(IF($R94="YOY Growth",$N94*(1+$T94)/12,$S94/12),"")) -> 0 | Z94: =IF($R94="Manual","",IFERROR(IF($R94="YOY Growth",$N94*(1+$T94)/12,$S94/12),"")) -> 0 | AA94: =IF($R94="Manual","",IFERROR(IF($R94="YOY Growth",$N94*(1+$T94)/12,$S94/12),"")) -> 0 | AB94: =IF($R94="Manual","",IFERROR(IF($R94="YOY Growth",$N94*(1+$T94)/12,$S94/12),"")) -> 0 | ... AF94: =IF($R94="Manual","",IFERROR(IF($R94="YOY Growth",$N94*(1+$T94)/12,$S94/12),"")) -> 0 | AG94: =SUM(U94:AF94) -> 0 | AH94: =IFERROR(AG94/AG$16,"") | AJ94: =N94-AG94 -> 0
A95: 7550 - Tools and Equipment | B95: 1254.52 | C95: 126.85 | D95: 0 | E95: 122.17 | F95: 0 | G95: 0 | H95: 0 | I95: 0 | J95: 450 | K95: 450 | L95: 450 | M95: 450 | N95: =SUM(B95:M95) -> 3303.54 | O95: =IFERROR(N95/N$16,"") | R95: Even | S95: 0 | T95: 0.05 | U95: =IF($R95="Manual","",IFERROR(IF($R95="YOY Growth",$N95*(1+$T95)/12,$S95/12),"")) -> 0 | V95: =IF($R95="Manual","",IFERROR(IF($R95="YOY Growth",$N95*(1+$T95)/12,$S95/12),"")) -> 0 | W95: =IF($R95="Manual","",IFERROR(IF($R95="YOY Growth",$N95*(1+$T95)/12,$S95/12),"")) -> 0 | X95: =IF($R95="Manual","",IFERROR(IF($R95="YOY Growth",$N95*(1+$T95)/12,$S95/12),"")) -> 0 | Y95: =IF($R95="Manual","",IFERROR(IF($R95="YOY Growth",$N95*(1+$T95)/12,$S95/12),"")) -> 0 | Z95: =IF($R95="Manual","",IFERROR(IF($R95="YOY Growth",$N95*(1+$T95)/12,$S95/12),"")) -> 0 | AA95: =IF($R95="Manual","",IFERROR(IF($R95="YOY Growth",$N95*(1+$T95)/12,$S95/12),"")) -> 0 | AB95: =IF($R95="Manual","",IFERROR(IF($R95="YOY Growth",$N95*(1+$T95)/12,$S95/12),"")) -> 0 | ... AF95: =IF($R95="Manual","",IFERROR(IF($R95="YOY Growth",$N95*(1+$T95)/12,$S95/12),"")) -> 0 | AG95: =SUM(U95:AF95) -> 0 | AH95: =IFERROR(AG95/AG$16,"") | AJ95: =N95-AG95 -> 3303.54
A96: 7600 - Freight & Delivery | B96: 0 | C96: 0 | D96: 0 | E96: 0 | F96: 0 | G96: 0 | H96: 0 | I96: 0 | J96: 0 | K96: 0 | L96: 0 | M96: 0 | N96: =SUM(B96:M96) -> 0 | O96: =IFERROR(N96/N$16,"") | R96: Even | S96: 0 | T96: 0.05 | U96: =IF($R96="Manual","",IFERROR(IF($R96="YOY Growth",$N96*(1+$T96)/12,$S96/12),"")) -> 0 | V96: =IF($R96="Manual","",IFERROR(IF($R96="YOY Growth",$N96*(1+$T96)/12,$S96/12),"")) -> 0 | W96: =IF($R96="Manual","",IFERROR(IF($R96="YOY Growth",$N96*(1+$T96)/12,$S96/12),"")) -> 0 | X96: =IF($R96="Manual","",IFERROR(IF($R96="YOY Growth",$N96*(1+$T96)/12,$S96/12),"")) -> 0 | Y96: =IF($R96="Manual","",IFERROR(IF($R96="YOY Growth",$N96*(1+$T96)/12,$S96/12),"")) -> 0 | Z96: =IF($R96="Manual","",IFERROR(IF($R96="YOY Growth",$N96*(1+$T96)/12,$S96/12),"")) -> 0 | AA96: =IF($R96="Manual","",IFERROR(IF($R96="YOY Growth",$N96*(1+$T96)/12,$S96/12),"")) -> 0 | AB96: =IF($R96="Manual","",IFERROR(IF($R96="YOY Growth",$N96*(1+$T96)/12,$S96/12),"")) -> 0 | ... AF96: =IF($R96="Manual","",IFERROR(IF($R96="YOY Growth",$N96*(1+$T96)/12,$S96/12),"")) -> 0 | AG96: =SUM(U96:AF96) -> 0 | AH96: =IFERROR(AG96/AG$16,"") | AJ96: =N96-AG96 -> 0
A97: 7610 - Duties & Tariffs - Other | B97: 0 | C97: 0 | D97: 0 | E97: 0 | F97: 0 | G97: 0 | H97: 0 | I97: 0 | J97: 0 | K97: 0 | L97: 0 | M97: 0 | N97: =SUM(B97:M97) -> 0 | O97: =IFERROR(N97/N$16,"") | R97: Even | S97: 0 | T97: 0.05 | U97: =IF($R97="Manual","",IFERROR(IF($R97="YOY Growth",$N97*(1+$T97)/12,$S97/12),"")) -> 0 | V97: =IF($R97="Manual","",IFERROR(IF($R97="YOY Growth",$N97*(1+$T97)/12,$S97/12),"")) -> 0 | W97: =IF($R97="Manual","",IFERROR(IF($R97="YOY Growth",$N97*(1+$T97)/12,$S97/12),"")) -> 0 | X97: =IF($R97="Manual","",IFERROR(IF($R97="YOY Growth",$N97*(1+$T97)/12,$S97/12),"")) -> 0 | Y97: =IF($R97="Manual","",IFERROR(IF($R97="YOY Growth",$N97*(1+$T97)/12,$S97/12),"")) -> 0 | Z97: =IF($R97="Manual","",IFERROR(IF($R97="YOY Growth",$N97*(1+$T97)/12,$S97/12),"")) -> 0 | AA97: =IF($R97="Manual","",IFERROR(IF($R97="YOY Growth",$N97*(1+$T97)/12,$S97/12),"")) -> 0 | AB97: =IF($R97="Manual","",IFERROR(IF($R97="YOY Growth",$N97*(1+$T97)/12,$S97/12),"")) -> 0 | ... AF97: =IF($R97="Manual","",IFERROR(IF($R97="YOY Growth",$N97*(1+$T97)/12,$S97/12),"")) -> 0 | AG97: =SUM(U97:AF97) -> 0 | AH97: =IFERROR(AG97/AG$16,"") | AJ97: =N97-AG97 -> 0
A98: 7700 - Inventory Obsolescence-old | B98: 0 | C98: 0 | D98: 0 | E98: 0 | F98: 0 | G98: 0 | H98: 0 | I98: 0 | J98: 0 | K98: 0 | L98: 0 | M98: 0 | N98: =SUM(B98:M98) -> 0 | O98: =IFERROR(N98/N$16,"") | R98: Even | S98: 0 | T98: 0.05 | U98: =IF($R98="Manual","",IFERROR(IF($R98="YOY Growth",$N98*(1+$T98)/12,$S98/12),"")) -> 0 | V98: =IF($R98="Manual","",IFERROR(IF($R98="YOY Growth",$N98*(1+$T98)/12,$S98/12),"")) -> 0 | W98: =IF($R98="Manual","",IFERROR(IF($R98="YOY Growth",$N98*(1+$T98)/12,$S98/12),"")) -> 0 | X98: =IF($R98="Manual","",IFERROR(IF($R98="YOY Growth",$N98*(1+$T98)/12,$S98/12),"")) -> 0 | Y98: =IF($R98="Manual","",IFERROR(IF($R98="YOY Growth",$N98*(1+$T98)/12,$S98/12),"")) -> 0 | Z98: =IF($R98="Manual","",IFERROR(IF($R98="YOY Growth",$N98*(1+$T98)/12,$S98/12),"")) -> 0 | AA98: =IF($R98="Manual","",IFERROR(IF($R98="YOY Growth",$N98*(1+$T98)/12,$S98/12),"")) -> 0 | AB98: =IF($R98="Manual","",IFERROR(IF($R98="YOY Growth",$N98*(1+$T98)/12,$S98/12),"")) -> 0 | ... AF98: =IF($R98="Manual","",IFERROR(IF($R98="YOY Growth",$N98*(1+$T98)/12,$S98/12),"")) -> 0 | AG98: =SUM(U98:AF98) -> 0 | AH98: =IFERROR(AG98/AG$16,"") | AJ98: =N98-AG98 -> 0
A99: 8100 - Technology | B99: 55 | C99: 20 | D99: 80 | E99: 0 | F99: 20 | G99: 0 | H99: 0 | I99: 0 | J99: 100 | K99: 100 | L99: 100 | M99: 100 | N99: =SUM(B99:M99) -> 575 | O99: =IFERROR(N99/N$16,"") | R99: Even | S99: 0 | T99: 0.05 | U99: =IF($R99="Manual","",IFERROR(IF($R99="YOY Growth",$N99*(1+$T99)/12,$S99/12),"")) -> 0 | V99: =IF($R99="Manual","",IFERROR(IF($R99="YOY Growth",$N99*(1+$T99)/12,$S99/12),"")) -> 0 | W99: =IF($R99="Manual","",IFERROR(IF($R99="YOY Growth",$N99*(1+$T99)/12,$S99/12),"")) -> 0 | X99: =IF($R99="Manual","",IFERROR(IF($R99="YOY Growth",$N99*(1+$T99)/12,$S99/12),"")) -> 0 | Y99: =IF($R99="Manual","",IFERROR(IF($R99="YOY Growth",$N99*(1+$T99)/12,$S99/12),"")) -> 0 | Z99: =IF($R99="Manual","",IFERROR(IF($R99="YOY Growth",$N99*(1+$T99)/12,$S99/12),"")) -> 0 | AA99: =IF($R99="Manual","",IFERROR(IF($R99="YOY Growth",$N99*(1+$T99)/12,$S99/12),"")) -> 0 | AB99: =IF($R99="Manual","",IFERROR(IF($R99="YOY Growth",$N99*(1+$T99)/12,$S99/12),"")) -> 0 | ... AF99: =IF($R99="Manual","",IFERROR(IF($R99="YOY Growth",$N99*(1+$T99)/12,$S99/12),"")) -> 0 | AG99: =SUM(U99:AF99) -> 0 | AH99: =IFERROR(AG99/AG$16,"") | AJ99: =N99-AG99 -> 575
... A115: 9999 - Uncategorized Expenses | B115: 0 | C115: 0 | D115: 0 | E115: 0 | F115: 0 | G115: 0 | H115: 0 | I115: 0 | J115: 0 | K115: 0 | L115: 0 | M115: 0 | N115: =SUM(B115:M115) -> 0 | O115: =IFERROR(N115/N$16,"") | R115: Even | S115: 0 | T115: 0.05 | U115: =IF($R115="Manual","",IFERROR(IF($R115="YOY Growth",$N115*(1+$T115)/12,$S115/12),"")) -> 0 | V115: =IF($R115="Manual","",IFERROR(IF($R115="YOY Growth",$N115*(1+$T115)/12,$S115/12),"")) -> 0 | W115: =IF($R115="Manual","",IFERROR(IF($R115="YOY Growth",$N115*(1+$T115)/12,$S115/12),"")) -> 0 | X115: =IF($R115="Manual","",IFERROR(IF($R115="YOY Growth",$N115*(1+$T115)/12,$S115/12),"")) -> 0 | Y115: =IF($R115="Manual","",IFERROR(IF($R115="YOY Growth",$N115*(1+$T115)/12,$S115/12),"")) -> 0 | Z115: =IF($R115="Manual","",IFERROR(IF($R115="YOY Growth",$N115*(1+$T115)/12,$S115/12),"")) -> 0 | AA115: =IF($R115="Manual","",IFERROR(IF($R115="YOY Growth",$N115*(1+$T115)/12,$S115/12),"")) -> 0 | AB115: =IF($R115="Manual","",IFERROR(IF($R115="YOY Growth",$N115*(1+$T115)/12,$S115/12),"")) -> 0 | ... AF115: =IF($R115="Manual","",IFERROR(IF($R115="YOY Growth",$N115*(1+$T115)/12,$S115/12),"")) -> 0 | AG115: =SUM(U115:AF115) -> 0 | AH115: =IFERROR(AG115/AG$16,"") | AJ115: =N115-AG115 -> 0
A116: Total - Expense | B116: =B73+SUM(B74:B80)+B87+SUM(B88:B115) -> 46455.18 | C116: =C73+SUM(C74:C80)+C87+SUM(C88:C115) -> 41015.37 | D116: =D73+SUM(D74:D80)+D87+SUM(D88:D115) -> 74591.09 | E116: =E73+SUM(E74:E80)+E87+SUM(E88:E115) -> 102797 | F116: =F73+SUM(F74:F80)+F87+SUM(F88:F115) -> 116105.58 | G116: =G73+SUM(G74:G80)+G87+SUM(G88:G115) -> 134734.06 | H116: =H73+SUM(H74:H80)+H87+SUM(H88:H115) -> 65078.17 | I116: =I73+SUM(I74:I80)+I87+SUM(I88:I115) -> 72711.35 | ... M116: =M73+SUM(M74:M80)+M87+SUM(M88:M115) -> 141373 | N116: =SUM(B116:M116) -> 1195805.8 | O116: =IFERROR(N116/N$16,"") | U116: =U73+SUM(U74:U80)+U87+SUM(U88:U115) -> 74256.43 | V116: =V73+SUM(V74:V80)+V87+SUM(V88:V115) -> 74256.43 | W116: =W73+SUM(W74:W80)+W87+SUM(W88:W115) -> 74256.43 | X116: =X73+SUM(X74:X80)+X87+SUM(X88:X115) -> 74256.43 | Y116: =Y73+SUM(Y74:Y80)+Y87+SUM(Y88:Y115) -> 74256.43 | Z116: =Z73+SUM(Z74:Z80)+Z87+SUM(Z88:Z115) -> 74256.43 | AA116: =AA73+SUM(AA74:AA80)+AA87+SUM(AA88:AA115) -> 74256.43 | AB116: =AB73+SUM(AB74:AB80)+AB87+SUM(AB88:AB115) -> 80929.764 | ... AF116: =AF73+SUM(AF74:AF80)+AF87+SUM(AF88:AF115) -> 83226.43 | AG116: =SUM(U116:AF116) -> 931333.83 | AH116: =IFERROR(AG116/AG$16,"") | AJ116: =N116-AG116 -> 264471.97
A117: Net Ordinary Income | B117: =B64-B116 -> -56010.4 | C117: =C64-C116 -> -46181.75 | D117: =D64-D116 -> -83484.13 | E117: =E64-E116 -> -109548.93 | F117: =F64-F116 -> -133089.38 | G117: =G64-G116 -> -138267.06 | H117: =H64-H116 -> -68900.93 | I117: =I64-I116 -> -79794.05 | ... M117: =M64-M116 -> -151073 | N117: =SUM(B117:M117) -> -1311794.6 | O117: =IFERROR(N117/N$16,"") | U117: =U64-U116 -> -92830.335 | V117: =V64-V116 -> -86639.034 | W117: =W64-W116 -> -74256.43 | X117: =X64-X116 -> -103479.37 | Y117: =Y64-Y116 -> -97288.072 | Z117: =Z64-Z116 -> -107937.11 | AA117: =AA64-AA116 -> -103479.37 | AB117: =AB64-AB116 -> -116344.01 | ... AF117: =AF64-AF116 -> -141672.32 | AG117: =SUM(U117:AF117) -> -1320147.6 | AH117: =IFERROR(AG117/AG$16,"") | AJ117: =AG117-N117 -> -8352.9421
A118: Other Income and Expenses
A119: Other Income
...

Sheet Fld Ops Payroll
A1: Field Maintenance Payroll Model – Total Field Payroll
A2: Total field payroll: current staff on payroll (Sep-26) + incremental techs for new-logo go-lives (DeploySum row 54) and expansions at new locations (row 57 × %), plus floaters, supervisors, and named Field Ops management/coordination roles (Isaiah, Rebecca). Placeholder inputs in yellow.
A4: FIELD TECH ASSUMPTIONS | B4: Tech | E4: FIELD SUPERVISOR ASSUMPTIONS | J4: RAISE ASSUMPTIONS
A5: Techs per deployment needing a tech (FTE) | B5: 1 | E5: Avg annual salary per supervisor ($) | H5: 90000 | J5: Annual raise (% of salary) | M5: ='Prod Payroll'!M5 -> 0.03
A6: Avg annual salary per tech ($) | B6: 63000 | E6: Payroll taxes (% of salary) | H6: 0.068 | J6: Raise effective month | M6: ='Prod Payroll'!M6 -> 46661
A7: Payroll taxes (% of salary) | B7: 0.068 | E7: Benefits (% of salary) | H7: 0.164 | J7: Raise eligibility – min months employed | M7: ='Prod Payroll'!M9 -> 6
A8: Benefits (% of salary) | B8: 0.164 | E8: Techs per supervisor (add 1 per X) | H8: 20 | J8: Raise links to Prod Payroll (green) – overwrite to set separately.
A9: New-hire cost per tech ($) | B9: 2000 | E9: Minimum # of supervisors | H9: 1
A10: Hire lead time (months before go-live) | B10: 1 | E10: New-hire cost per supervisor ($) | H10: 2000 | J10: FLOATER TECH ASSUMPTIONS
A11: Current site techs on payroll (Sep-26) - Domestic Only | B11: 14 | E11: Current supervisors counted toward ratio (Sep-26) – Isaiah | H11: 1 | J11: Site techs per floater | M11: 40
A12: Expansion go-lives at NEW locations (% needing a tech) | B12: 0.6 | E12: Ratio = domestic techs only. MeLi contract supervisor budgeted in Fld Maint Budget B11. | J12: Minimum # of floaters | M12: 0
A13: Total = current staff (Sep-26) + incremental: each new-logo go-live and each expansion at a new location adds a dedicated tech. Lead time = months hired before go-live. | J13: Current floaters (Sep-26) | M13: 0
A14: DEC-27 HIRING LOOK-AHEAD (Jan-28 go-lives) | B14: Per month | E14: NAMED ROLE ASSUMPTIONS | J14: Use floater pool? (Yes/No) | M14: No
A15: New-logo go-lives beyond Dec-27 (#/month) | B15: =ROUND(AVERAGE(DeploySum!O54:Q54),0) -> 7 | E15: Rebecca – Operations Coordinator base annual salary ($) | H15: 76515
A16: Expansion go-lives beyond Dec-27 (#/month) | B16: =ROUND(AVERAGE(DeploySum!O57:Q57),0) -> 2 | E16: Isaiah – Manager base annual salary ($) | H16: 120000
A19: CURRENT FIELD TECHNICIANS – ON PAYROLL OCT-26 ($) | B19: =DeploySum!B53 -> 46295 | C19: =DeploySum!C53 -> 46326 | D19: =DeploySum!D53 -> 46356 | E19: =DeploySum!E53 -> 46387 | F19: =DeploySum!F53 -> 46418 | G19: =DeploySum!G53 -> 46446 | H19: =DeploySum!H53 -> 46477 | I19: =DeploySum!I53 -> 46507 | ... Q19: =DeploySum!Q53 -> 46752 | R19: Sep–Dec 2026 | S19: FY2027
A20: Current site techs (#) | B20: =$B$11 -> 14 | C20: =$B$11 -> 14 | D20: =$B$11 -> 14 | E20: =$B$11 -> 14 | F20: =$B$11 -> 14 | G20: =$B$11 -> 14 | H20: =$B$11 -> 14 | I20: =$B$11 -> 14 | ... Q20: =$B$11 -> 14 | R20: =AVERAGE(B20:E20) -> 14 | S20: =AVERAGE(F20:Q20) -> 14
A21: Base salaries | B21: =B20*$B$6/12+IF(B$19>=$M$6,MIN(B20,INDEX($B20:$Q20,IFERROR(MATCH(EOMONTH($M$6,-$M$7-1),$B$19:$Q$19,0),1)))*$B$6/12*$M$5,0) -> 73500 | C21: =C20*$B$6/12+IF(C$19>=$M$6,MIN(C20,INDEX($B20:$Q20,IFERROR(MATCH(EOMONTH($M$6,-$M$7-1),$B$19:$Q$19,0),1)))*$B$6/12*$M$5,0) -> 73500 | D21: =D20*$B$6/12+IF(D$19>=$M$6,MIN(D20,INDEX($B20:$Q20,IFERROR(MATCH(EOMONTH($M$6,-$M$7-1),$B$19:$Q$19,0),1)))*$B$6/12*$M$5,0) -> 73500 | E21: =E20*$B$6/12+IF(E$19>=$M$6,MIN(E20,INDEX($B20:$Q20,IFERROR(MATCH(EOMONTH($M$6,-$M$7-1),$B$19:$Q$19,0),1)))*$B$6/12*$M$5,0) -> 73500 | F21: =F20*$B$6/12+IF(F$19>=$M$6,MIN(F20,INDEX($B20:$Q20,IFERROR(MATCH(EOMONTH($M$6,-$M$7-1),$B$19:$Q$19,0),1)))*$B$6/12*$M$5,0) -> 73500 | G21: =G20*$B$6/12+IF(G$19>=$M$6,MIN(G20,INDEX($B20:$Q20,IFERROR(MATCH(EOMONTH($M$6,-$M$7-1),$B$19:$Q$19,0),1)))*$B$6/12*$M$5,0) -> 73500 | H21: =H20*$B$6/12+IF(H$19>=$M$6,MIN(H20,INDEX($B20:$Q20,IFERROR(MATCH(EOMONTH($M$6,-$M$7-1),$B$19:$Q$19,0),1)))*$B$6/12*$M$5,0) -> 73500 | I21: =I20*$B$6/12+IF(I$19>=$M$6,MIN(I20,INDEX($B20:$Q20,IFERROR(MATCH(EOMONTH($M$6,-$M$7-1),$B$19:$Q$19,0),1)))*$B$6/12*$M$5,0) -> 73500 | ... Q21: =Q20*$B$6/12+IF(Q$19>=$M$6,MIN(Q20,INDEX($B20:$Q20,IFERROR(MATCH(EOMONTH($M$6,-$M$7-1),$B$19:$Q$19,0),1)))*$B$6/12*$M$5,0) -> 75705 | R21: =SUM(B21:E21) -> 294000 | S21: =SUM(F21:Q21) -> 888615
A22: Payroll taxes | B22: =B21*$B$7 -> 4998 | C22: =C21*$B$7 -> 4998 | D22: =D21*$B$7 -> 4998 | E22: =E21*$B$7 -> 4998 | F22: =F21*$B$7 -> 4998 | G22: =G21*$B$7 -> 4998 | H22: =H21*$B$7 -> 4998 | I22: =I21*$B$7 -> 4998 | ... Q22: =Q21*$B$7 -> 5147.94 | R22: =SUM(B22:E22) -> 19992 | S22: =SUM(F22:Q22) -> 60425.82
A23: Benefits | B23: =B21*$B$8 -> 12054 | C23: =C21*$B$8 -> 12054 | D23: =D21*$B$8 -> 12054 | E23: =E21*$B$8 -> 12054 | F23: =F21*$B$8 -> 12054 | G23: =G21*$B$8 -> 12054 | H23: =H21*$B$8 -> 12054 | I23: =I21*$B$8 -> 12054 | ... Q23: =Q21*$B$8 -> 12415.62 | R23: =SUM(B23:E23) -> 48216 | S23: =SUM(F23:Q23) -> 145732.86
A24: Total current tech payroll | B24: =SUM(B21:B23) -> 90552 | C24: =SUM(C21:C23) -> 90552 | D24: =SUM(D21:D23) -> 90552 | E24: =SUM(E21:E23) -> 90552 | F24: =SUM(F21:F23) -> 90552 | G24: =SUM(G21:G23) -> 90552 | H24: =SUM(H21:H23) -> 90552 | I24: =SUM(I21:I23) -> 90552 | ... Q24: =SUM(Q21:Q23) -> 93268.56 | R24: =SUM(B24:E24) -> 362208 | S24: =SUM(F24:Q24) -> 1094773.7
A26: NEW LOGO FIELD TECHNICIANS ($) | B26: =DeploySum!B53 -> 46295 | C26: =DeploySum!C53 -> 46326 | D26: =DeploySum!D53 -> 46356 | E26: =DeploySum!E53 -> 46387 | F26: =DeploySum!F53 -> 46418 | G26: =DeploySum!G53 -> 46446 | H26: =DeploySum!H53 -> 46477 | I26: =DeploySum!I53 -> 46507 | ... Q26: =DeploySum!Q53 -> 46752 | R26: Sep–Dec 2026 | S26: FY2027
