Workbook
Name _____I2: {"PVGraph2",#N/A,FALSE,"PV Data"}
Name _____I3: {"PVGraph2",#N/A,FALSE,"PV Data"}
Name _____w1: {"PVGraph2",#N/A,FALSE,"PV Data"}
Name _____w2: {"PVGraph2",#N/A,FALSE,"PV Data"}
Name _____w3: {"PVGraph2",#N/A,FALSE,"PV Data"}
Name _____y2: {"PVGraph2",#N/A,FALSE,"PV Data"}
Name ___I2: {"PVGraph2",#N/A,FALSE,"PV Data"}
Name ___I3: {"PVGraph2",#N/A,FALSE,"PV Data"}
Name ___w1: {"PVGraph2",#N/A,FALSE,"PV Data"}
Name ___w2: {"PVGraph2",#N/A,FALSE,"PV Data"}
Name ___w3: {"PVGraph2",#N/A,FALSE,"PV Data"}
Name ___y2: {"PVGraph2",#N/A,FALSE,"PV Data"}
Name __FDS_HYPERLINK_TOGGLE_STATE__: "ON"
Name __IntlFixup: TRUE()
Name __QTD1: {"Nil","Nil",FALSE,"Detail P&L-M";"Nil","Nil",FALSE,"Dep & Amort-M";"Nil","Nil",FALSE,"Equity-M";"Nil","Nil",FALSE,"Debt & Cash Flow-M";"Nil","Nil",FALSE,"Interest-M"}
Name _ass1: {#N/A,#N/A,FALSE,"Aging Summary";#N/A,#N/A,FALSE,"Ratio Analysis";#N/A,#N/A,FALSE,"Test 120 Day Accts";#N/A,#N/A,FALSE,"Tickmarks"}
Name _I2: {"PVGraph2",#N/A,FALSE,"PV Data"}
Name _I3: {"PVGraph2",#N/A,FALSE,"PV Data"}
Name _new2: {"COM1996",#N/A,FALSE,"ANNUAL COMMISSIONS";"COM1997",#N/A,FALSE,"ANNUAL COMMISSIONS"}
Name _new3: {"COM1996",#N/A,FALSE,"ANNUAL COMMISSIONS";"COM1997",#N/A,FALSE,"ANNUAL COMMISSIONS"}
Name _Order1: 255
Name _Order1a: 0
Name _Order2: 255
Name _QTD1: {"Nil","Nil",FALSE,"Detail P&L-M";"Nil","Nil",FALSE,"Dep & Amort-M";"Nil","Nil",FALSE,"Equity-M";"Nil","Nil",FALSE,"Debt & Cash Flow-M";"Nil","Nil",FALSE,"Interest-M"}
Name _Regression_Int: 1
Name _rod1: {#N/A,#N/A,FALSE,"Projections";#N/A,#N/A,FALSE,"Multiples Valuation";#N/A,#N/A,FALSE,"LBO";#N/A,#N/A,FALSE,"Multiples_Sensitivity";#N/A,#N/A,FALSE,"Summary"}
Name _SDU2: {#N/A,#N/A,FALSE,"Aging Summary";#N/A,#N/A,FALSE,"Ratio Analysis";#N/A,#N/A,FALSE,"Test 120 Day Accts";#N/A,#N/A,FALSE,"Tickmarks"}
Name _w1: {"PVGraph2",#N/A,FALSE,"PV Data"}
Name _w2: {"PVGraph2",#N/A,FALSE,"PV Data"}
Name _w3: {"PVGraph2",#N/A,FALSE,"PV Data"}
Name _wrn2: {#N/A,#N/A,FALSE,"ASSUMPTIONS";#N/A,#N/A,FALSE,"Valuation Summary";"page1",#N/A,FALSE,"PRESENTATION";"page2",#N/A,FALSE,"PRESENTATION";#N/A,#N/A,FALSE,"ORIGINAL_ROLLBACK"}
Name _wrn3: {#N/A,#N/A,FALSE,"ASSUMPTIONS";#N/A,#N/A,FALSE,"Valuation Summary";"page1",#N/A,FALSE,"PRESENTATION";"page2",#N/A,FALSE,"PRESENTATION";#N/A,#N/A,FALSE,"ORIGINAL_ROLLBACK"}
Name _x1: {#N/A,#N/A,FALSE,"FY97";#N/A,#N/A,FALSE,"FY98";#N/A,#N/A,FALSE,"FY99";#N/A,#N/A,FALSE,"FY00";#N/A,#N/A,FALSE,"FY01"}
Name _y2: {"PVGraph2",#N/A,FALSE,"PV Data"}
Name a: {#N/A,#N/A,FALSE,"Projections";#N/A,#N/A,FALSE,"Multiples Valuation";#N/A,#N/A,FALSE,"LBO";#N/A,#N/A,FALSE,"Multiples_Sensitivity";#N/A,#N/A,FALSE,"Summary"}
Name aa: {#N/A,#N/A,FALSE,"Projections";#N/A,#N/A,FALSE,"Multiples Valuation";#N/A,#N/A,FALSE,"LBO";#N/A,#N/A,FALSE,"Multiples_Sensitivity";#N/A,#N/A,FALSE,"Summary"}
Name aaa: {#N/A,#N/A,FALSE,"Projections";#N/A,#N/A,FALSE,"Multiples Valuation";#N/A,#N/A,FALSE,"LBO";#N/A,#N/A,FALSE,"Multiples_Sensitivity";#N/A,#N/A,FALSE,"Summary"}
Name AAA_DOCTOPS: "AAA_SET"
Name AAA_duser: "OFF"
Name aaaaaaa: {"Outflow 1",#N/A,FALSE,"Outflows-Inflows";"Outflow 2",#N/A,FALSE,"Outflows-Inflows";"Inflow 1",#N/A,FALSE,"Outflows-Inflows";"Inflow 2",#N/A,FALSE,"Outflows-Inflows"}
Name AAB_Addin5: "AAB_Description for addin 5,Description for addin 5,Description for addin 5,Description for addin 5,Description for addin 5,Description for addin 5"
Name AAB_GSPPG: "AAB_Goldman Sachs PPG Chart Utilities 1.0g"
Name aabb: {#N/A,#N/A,FALSE,"Projections";#N/A,#N/A,FALSE,"Multiples Valuation";#N/A,#N/A,FALSE,"LBO";#N/A,#N/A,FALSE,"Multiples_Sensitivity";#N/A,#N/A,FALSE,"Summary"}
Name aas: "c4426"
Name aasdfa: {"rtn",#N/A,FALSE,"RTN";"tables",#N/A,FALSE,"RTN";"cf",#N/A,FALSE,"CF";"stats",#N/A,FALSE,"Stats";"prop",#N/A,FALSE,"Prop"}
Name AccessDatabase: "C:\DATA\Kevin\Kevin's Model.mdb"
Name ads: {#N/A,#N/A,FALSE,"AD_Purch";#N/A,#N/A,FALSE,"Projections";#N/A,#N/A,FALSE,"DCF";#N/A,#N/A,FALSE,"Mkt Val"}
Name adsf: {#N/A,#N/A,FALSE,"AD_Purch";#N/A,#N/A,FALSE,"Projections";#N/A,#N/A,FALSE,"DCF";#N/A,#N/A,FALSE,"Mkt Val"}
Name Annual: {"Outflow 1",#N/A,FALSE,"Outflows-Inflows";"Outflow 2",#N/A,FALSE,"Outflows-Inflows";"Inflow 1",#N/A,FALSE,"Outflows-Inflows";"Inflow 2",#N/A,FALSE,"Outflows-Inflows"}
Name anscount: 1
Name argqe: {#N/A,#N/A,FALSE,"puboff";#N/A,#N/A,FALSE,"financials";#N/A,#N/A,FALSE,"valuation";#N/A,#N/A,FALSE,"split"}
Name as: {"Outflow 1",#N/A,FALSE,"Outflows-Inflows";"Outflow 2",#N/A,FALSE,"Outflows-Inflows";"Inflow 1",#N/A,FALSE,"Outflows-Inflows";"Inflow 2",#N/A,FALSE,"Outflows-Inflows"}
Name AS2DocOpenMode: "AS2DocumentEdit"
Name AS2NamedRange: 196
Name AS2ReportLS: 1
Name AS2SyncStepLS: 0
Name AS2VersionLS: 300
Name asdf: 40379.4506944444
Name asdfas: {"print 1.6",#N/A,FALSE,"Sheet1";"print 2.6",#N/A,FALSE,"Sheet1";"print 3.6",#N/A,FALSE,"Sheet1";"print 4.6",#N/A,FALSE,"Sheet1";"print 5.6",#N/A,FALSE,"Sheet1";"print 6.6",#N/A,FALSE,"Sheet1"}
Name asdfasaa: {"print 1.6",#N/A,FALSE,"Sheet1";"print 2.6",#N/A,FALSE,"Sheet1";"print 3.6",#N/A,FALSE,"Sheet1";"print 4.6",#N/A,FALSE,"Sheet1";"print 5.6",#N/A,FALSE,"Sheet1";"print 6.6",#N/A,FALSE,"Sheet1"}

Sheet Collation Notes
A1: 2027 COO Budget - Collation Notes (build v11, draft for review)
A3: CONFIDENTIAL – contains named compensation data (HC-* tabs); restrict distribution
A4: This workbook holds employee names and salaries on the HC-* tabs (copied from the COO HC & PL workfile) and seat-holder names on the 'Logistics&WH Payroll' tab (copied from the SD book). Share it only with people cleared to see compensation. This sheet keeps exact figures. The notes file (02-build_notes_v10.md) rounds per-person amounts to the nearest $5k, but a salary that is itself a multiple of $5k is unchanged by that rounding, so some unique-role salaries appear there at their exact value. The new CO employee's name is on HC-CO r18 only.
A6: Decisions pending (user) - not resolved by the builder (v10: #6 RESOLVED by the user)
A7: # | B7: Decision (user) | C7: Issue | D7: Current treatment in the budget | E7: Alternatives: effect on 2027 COO contribution (+ raises, ( ) lowers) | F7: Who
A8: 1 | B8: RESOLVED (user-confirmed 2026-10-10: 'production labor is capitalized. Use the same formula as the file has.'). Production labour: expensed, or capitalised into the unit cost? | C8: I-05 (RESOLVED), I-23, I-40 | D8: Booked since v8: Prod Payroll labour is capitalised (model 2027 2,592,894, the 9 current staff included) and depreciated by the Depreciation Schedule logic: 5011 +79,290, 5012 +25,126; PO 5110-5140 2027 = 0 (v7 652,820). v9: Sep-Dec 26 labour stays a 2026 cost (B132 = 0). Contribution v10 159,136 (v9 687,435; v10 books the Logistics&WH payroll and the new CO employee (user-confirmed, 110k) in CO, Decision #6). | E8: Resolved. The scope (current staff, Sep-Dec 26 labour, idle months) is Decision #10. | F8: User (resolved)
A9: 2 | B9: SlipBot fleet status (5010 depreciation) | C9: I-32 | D9: Carried flat at the PO Dec-26 run rate 112,797.85/month = 1,353,574 in 2027 (builder assumption, A-17). | E9: Fully depreciated or retired from Jan-27: +1,353,574. Continue the 2026 decline ((3,541)/month, Jan-Sep 26) from the Sep-26 level in Jan-27: +276,164 (actuals Jan-Aug only, (1,945)/month: +151,680). Same decline also running through Oct-Dec 26, floored at 0: +403,624 (actuals-only slope: +221,687). Ongoing at the run rate: 0. Related: the 5020 base of 8,212/month (Jan-26, before any SlipLift depreciation) may end with the SlipBots: up to +98,543. | F9: User, with PO/Finance (fixed-asset register)
A10: 3 | B10: Q4-26 go-lives: PO run rate or DeploySum | C10: I-31 | D10: Inside the PO Dec-26 run rate: PO steps up for 15 lifts / 53 trays (DeploySum: 18 / 67). | E10: Sep-26 run rate + DeploySum Oct-Dec 26 vintages: (39,057). If PO's Dec-26 step-up (3 lifts, 12 trays) is Jan-27 units already in the Jan-27 vintage and PO's Oct/Nov counts are right: +37,457. Keep as is: 0. | F10: User, after the PO owner says what the Q4-26 step-ups are
A11: 4 | B11: SlipLift peripherals: GL and useful life | C11: I-33 | D11: 5020 Robot Peripherals, 84 months: 63,836 of 2027 depreciation (builder assumption, A-10/A-11). | E11: GL 5011 instead of 5020: 0 (moves 63,836 from PO row 22 to row 20). Life 60 months: (25,534). Life 120 months: +19,151. | F11: User
A12: 5 | B12: Revenue split across 4100 / 4500 / 4900 | C12: I-01 (A-02, A-03) | D12: All 15,563,646 of plan revenue on 4100; 4500 and 4900 = 0 (orchestrator assumption). | E12: Split the plan revenue across the three lines: 0 (classification only; gross margin unchanged). Budget implementation / one-time revenue in addition to the plan: not determinable (2026 4500 + 4900: 1,060,861). | F12: User / Finance
A13: 6 | B13: RESOLVED (user decision 2026-10-10: 'The WH and logistics numbers should hit central operations, along with [the named CO employee]'; 'Yes, the material handler should move to CO.'). Warehouse payroll (Logistics&WH) and the material-handling roles | C13: I-17 (RESOLVED), I-41 | D13: Booked in v10: CO 6610-6640 (2027) = CO HC roster (incl. the new CO employee (user-confirmed, 110k)) + the Logistics&WH model less seat LOG-01 (already CO HC r17): 398,492 = the 7 new seats 336,530 + MH-01 61,963, at the model's rates (6.8% / 16.4%); new-hire cost 5,000 to 6610. MH-01 (= PO HC r20) is out of the PO 5110-5140 B131 base. | E13: Resolved. Still open: PO HC r16 Material Handling Team Lead on the 7-of-9 reading (I-41): (72,061) if its cost stays an expense, 0 if r16 fills TL-01. Logistics at CO HC burden rates: +19,396. | F13: User (resolved); PO owner for r16
A14: 7 | B14: One person probably costed in both FO and FE | C14: I-28 | D14: Probably costed twice (name match only; title and salary differ; likely FO->FE move): one of the 14 current techs in Fld Ops Payroll and Fld Eng Budget row 15. | E14: Remove from FO (B11 14 -> 13): +78,529 (payroll +78,198, 5330 +331). Remove from FE (row 15): +93,093. Pro rata if the move happens mid-year. | F14: SD / FO owners
A15: 8 | B15: FE payroll tax and benefit rates | C15: I-34 | D15: SD field rates 6.8% / 16.4% on FE salaries. | E15: FE HC (T&B) rates 4.069% / 7.223%: +109,539. Keep: 0. Caveat: the HC T&B tax rates are below the 7.65% employer FICA and unverified (I-37); with the FE tax rate at 7.65%: +76,600. | F15: User / Finance
A16: 9 | B16: PE 'transfer?' row (Head of Production and Delivery) | C16: I-35 | D16: In PE 6610-6640 for all of 2027 (254,785). | E16: Leaves COO from Jan-27: +254,785. Moves within COO: 0 (budget it once, on the receiving department). Stays: 0. | F16: PE owner
A17: 10 | B17: Scope of the capitalisation policy: are the 9 current production staff capitalised too, and is the labour of months with no builds (idle months) capitalised or expensed? 2026 expensed COO 5100 production labour, so the 2026 policy may have been partial. | C17: I-40 | D17: Current 9 capitalised (brief v5 primary case, B131 = 1); Sep-Dec 26 labour not capitalised: a 2026 period cost, as the 2026 books expense 5100 (B132 = 0, orchestrator ruling on critic v8 B1); idle months rolled into the next build month (B135 = 1). v10: the B131 base holds 8 PO HC people; PO HC r20 (MH-01) is in CO. | E17: Current staff expensed (sensitivity): (558,996) -> (399,860). Idle-month labour expensed (B135 = 0): (126,908) -> 32,228 (with the current staff expensed too: (480,264)). All Sep-Dec 26 labour capitalised (B132 = 1; only with a 2026 restatement): (60,695) -> 98,441. Each is one switch on the Depreciation Schedule; the workbook recalculates. | F17: User / Finance
A19: Headline: 2027 COO contribution (live formulas on COO P&L)
A20: Line | B20: COO P&L row | C20: 2026 (N) | D20: 2027 (AG) | E20: Change | F20: % (n/m if base <= 0 or sign flips) | G20: 2027 in v9 (value)
A21: Revenue (company recognized revenue, 9/30/26 sales plan) | B21: 16 | C21: ='COO P&L'!N16 -> 7423939.5 | D21: ='COO P&L'!AG16 -> 15563646 | E21: ='COO P&L'!AG16-('COO P&L'!N16) -> 8139706 | F21: =IF(OR('COO P&L'!N16<=0,'COO P&L'!AG16<0),"n/m",TEXT(('COO P&L'!AG16-'COO P&L'!N16)/'COO P&L'!N16,"0%")) -> 110% | G21: 15563646
A22: COGS (COO departments) | B22: 63 | C22: ='COO P&L'!N63 -> 4478015.6 | D22: ='COO P&L'!AG63 -> #REF! | E22: ='COO P&L'!AG63-('COO P&L'!N63) -> #REF! | F22: =IF(OR('COO P&L'!N63<=0,'COO P&L'!AG63<0),"n/m",TEXT(('COO P&L'!AG63-'COO P&L'!N63)/'COO P&L'!N63,"0%")) -> #REF! | G22: 11603614
A23: of which depreciation (in COGS) | B23: 19-22 | C23: =SUM('COO P&L'!N19:N22) -> 1788096.5 | D23: =SUM('COO P&L'!AG19:AG22) -> 3423224.8 | E23: =SUM('COO P&L'!AG19:AG22)-(SUM('COO P&L'!N19:N22)) -> 1635128.3 | F23: =IF(OR(SUM('COO P&L'!N19:N22)<=0,SUM('COO P&L'!AG19:AG22)<0),"n/m",TEXT((SUM('COO P&L'!AG19:AG22)-SUM('COO P&L'!N19:N22))/SUM('COO P&L'!N19:N22),"0%")) -> 91% | G23: 3423224.8
A24: Gross Profit | B24: 64 | C24: ='COO P&L'!N64 -> 2945923.9 | D24: ='COO P&L'!AG64 -> #REF! | E24: ='COO P&L'!AG64-('COO P&L'!N64) -> #REF! | F24: =IF(OR('COO P&L'!N64<=0,'COO P&L'!AG64<0),"n/m",TEXT(('COO P&L'!AG64-'COO P&L'!N64)/'COO P&L'!N64,"0%")) -> #REF! | G24: 3960031.6
A25: Opex (COO departments) | B25: 116 | C25: ='COO P&L'!N116 -> 3929957.3 | D25: ='COO P&L'!AG116 -> 4162413.4 | E25: ='COO P&L'!AG116-('COO P&L'!N116) -> 232456.12 | F25: =IF(OR('COO P&L'!N116<=0,'COO P&L'!AG116<0),"n/m",TEXT(('COO P&L'!AG116-'COO P&L'!N116)/'COO P&L'!N116,"0%")) -> 6% | G25: 3272596.5
A26: COO contribution before other income (workbook label 'Net Ordinary Income') | B26: 117 | C26: ='COO P&L'!N117 -> -984033.37 | D26: ='COO P&L'!AG117 -> #REF! | E26: ='COO P&L'!AG117-('COO P&L'!N117) -> #REF! | F26: =IF(OR('COO P&L'!N117<=0,'COO P&L'!AG117<0),"n/m",TEXT(('COO P&L'!AG117-'COO P&L'!N117)/'COO P&L'!N117,"0%")) -> #REF! | G26: 687435.11
A27: Net Other Income | B27: 131 | C27: ='COO P&L'!N131 -> 84811.32 | D27: ='COO P&L'!AG131 -> 0 | E27: ='COO P&L'!AG131-('COO P&L'!N131) -> -84811.32 | F27: =IF(OR('COO P&L'!N131<=0,'COO P&L'!AG131<0),"n/m",TEXT(('COO P&L'!AG131-'COO P&L'!N131)/'COO P&L'!N131,"0%")) -> -100% | G27: 0
A28: COO contribution (workbook label 'Net Income') | B28: 132 | C28: ='COO P&L'!N132 -> -899222.05 | D28: ='COO P&L'!AG132 -> #REF! | E28: ='COO P&L'!AG132-('COO P&L'!N132) -> #REF! | F28: =IF(OR('COO P&L'!N132<=0,'COO P&L'!AG132<0),"n/m",TEXT(('COO P&L'!AG132-'COO P&L'!N132)/'COO P&L'!N132,"0%")) -> #REF! | G28: 687435.11
A30: Caveats on the headline (read before using the figure)
A31: (0) v10 (user decision 2026-10-10): the Logistics & Warehouse payroll and the new CO employee (user-confirmed, 110k) are booked in Central Operations. CO 6610-6640 2027 618,961 -> 1,147,260: Logistics&WH less LOG-01 398,492 (7 new seats 336,530, MH-01 61,963; model rates), new CO employee (user-confirmed, 110k) 129,806 (CO HC rates). The contribution moves from 687,435 to 159,136. Production labour stays capitalised (Decision #1): 2027 CapEx +2,592,894, labour depreciation 104,417. Scope sensitivity (current staff expensed): (399,860); idle-month labour expensed: 32,228.
A32: (0b) Year on year is not like-for-like: 2026 expensed production labour, 2027 capitalises it. Policy effect in v10: +2,448,290 (PO 5110-5140 at B131 = 0 590,318 + the ramp 1,962,389 - booked labour depreciation 104,417; v9 +2,510,793): on the 2026 policy the 2027 contribution would be (2,289,154).
A33: (1) What the figure is. The bottom line, 159,136, is a COO contribution: the company's recognized revenue (15,563,646, all of it) less the costs of the five COO departments only (COGS + Opex of FO, PO, CO, FE, PE: 15,404,509). It is not company Net Income; the workbook row keeps its GL label 'Net Income' (COO P&L!A132).
A34: (2) What the revenue is. 2027 revenue is the 9/30/26 sales plan's recognized revenue (DeploySum row 40, static cached values, A-24), not signed contracts. It includes unsigned and forecast bookings: Sep-Dec 26 bookings of 3,544,300 include 2,264,000 of unsigned forecast at 100% (DeploySum note 5, A49: bookings are gross ACV), and all 29,452,766 of FY27 bookings are forecast (new logos 24,016,000, expansion 5,436,766). 7,618,410 (49%) of 2027 revenue is above the Dec-26 exit rate x 12 (7,945,236), so it depends on go-lives that have not happened yet.
A35: (3) Open exposures, each on its own against the headline. 'n/d' = not determinable from the workbook. Rows marked 'Carried from v9' have inputs v10 does not touch (the v9 -> v10 diff shows 0 changes there); the switch rows are recalculated on v10.
A36: Item | B36: Direction | C36: What could happen | D36: Effect on 2027 COO contribution | E36: Contribution after this item alone | F36: Source cells
A37: Decision #10 scope: current 9 expensed (sensitivity, not booked) | B37: downside | C37: If only the ramp is capitalised and the current PO staff stay expensed, PO 5110-5140 returns to the PO HC roster amount, now without PO HC r20 (Material Handler = Logistics&WH MH-01, booked in CO since v10): 590,318 (v9 652,820). 2027 capitalised labour falls to 1,962,389 and its 2027 depreciation to 73,095 (booked: 104,417). Recalculated with the workbook switch 'Depreciation Schedule'!B131 = 0. v9: (621,499). | D37: -558996.25 | E37: -399859.85 | F37: 'Depreciation Schedule'!B131; PO!U33:AF35; 'HC-PO'!M20:X20
A38: I-40 idle-month labour expensed (critic v8 B2; not booked) | B38: downside | C38: Jan-27 builds nothing, so its labour rolls into the Feb-27 builds (A-38). If idle-month labour is a period cost ('Depreciation Schedule'!B135 = 0) it is expensed in PO 5110-5140 and the depreciation of the Feb-27 builds falls. Recalculated; unchanged from v9 (v10 does not touch the labour block). With the current staff expensed (B131 = 0): (80,404). | D38: -126908.44 | E38: 32227.96 | F38: 'Depreciation Schedule'!B135, rows 221-228; PO!U33:AF35
A39: Decision #10 scope: all Sep-Dec 26 labour capitalised (B132 = 1; only with a 2026 restatement) | B39: downside | C39: Sep-Dec 26 model labour joins the Nov-26 and Jan-Feb 27 go-lives and is depreciated in 2027. Double counts the 2026 PO forecast unless 2026 is restated. Recalculated; unchanged from v9. Not in the range. | D39: -60695.09 | E39: 98441.31 | F39: 'Depreciation Schedule'!B132; rows 231-232
A40: Labour already in the 65,000 / 8,000 unit cost (critic v8 O1) | B40: upside | C40: DeploySum labels the unit costs 'Unit cost (CapEx)' (A47) and gives no build-up, so whether they already include production labour is not determinable from the workbook (v8's 'holds no production labour' is withdrawn: it had no source). If they do, the labour capitalised on top is counted twice and up to its full 2027 depreciation (104,417) goes. Owner: Finance / PO. Carried from v9: labour block unchanged (diff: 0 cells on Depreciation Schedule / Prod Payroll). | D40: 104416.68 | E40: 263553.08 | F40: DeploySum!A47; 'Depreciation Schedule'!R195
A41: I-41 (7-overlap): Material Handling Team Lead stays expensed | B41: downside | C41: v10: PO HC r20 Material Handler (= MH-01) is now booked in CO through the Logistics&WH model (user decision), so I-41 is down to PO HC r16 Material Handling Team Lead. On the 7-of-9 role reading r16 is warehouse staff, not production labour; PO 5110-5140 = 0 removes it and no expense line carries it: its 2027 cost at PO HC rates. 0 if r16 fills Logistics&WH seat TL-01 (same title, Dec-26 start; then costed in CO). v9 (r16 + r20): (134,563). | D41: -72060.6 | E41: 87075.8 | F41: 'HC-PO'!C16:Z16, D6:D7; PO!U33:AF35; Logistics&WH TL-01
A42: MH-01 on the 9-of-9 count reading: capitalised in PO and expensed in CO (v10) | B42: upside | C42: Prod Payroll counts its 9 current staff by number only and is unchanged (brief v6). On the 9-of-9 reading one of those 9 is PO HC r20 = MH-01, now expensed in CO 6610-6640: the capitalised labour then holds one head too many (the model's average current cost per head 70,056; 2027 CapEx overstated by that amount). Taking it out lowers 2027 labour depreciation pro rata (4.03% of 2027 capitalised payroll is depreciated in 2027). Not on the 7-of-9 reading. | D42: 2821.18 | E42: 161957.58 | F42: 'Depreciation Schedule'!B214, R195, B236; Prod Payroll B9:C9
A43: Logistics&WH seats at CO HC burden rates instead of the model's (v10) | B43: upside | C43: v10 books the logistics seats at the model's own rates (payroll tax 6.8%, benefits 16.4%: 'the WH and logistics numbers'). CO HC rates are 5.22% / 11.91%. On the 319,393 of 2027 logistics salaries in CO: burden 74,099 booked vs 54,703 at CO HC rates. Both CO HC rates are unverified (I-37). | D43: 19395.91 | E43: 178532.31 | F43: 'Logistics&WH Payroll'!B5:B6; 'HC-CO'!D6:D7; CO!U68:AF69
A44: New CO employee start month (A-43; new CO employee (user-confirmed, 110k)) | B44: upside | C44: Booked as in seat all of 2027 (HC-CO r18, Jan-27 start, CO HC rates, 3% from Oct-27). Each month the start is later lowers 2027 cost by ~10,000 (Jan-Sep monthly cost incl. CO HC burden). | D44: per month later: ~10,000 | E44: - | F44: 'HC-CO'!E18, M18:X18
A45: I-05 burden (O1), capitalised | B45: downside | C45: The ramp at PO HC burden rates (+141,924 of 2027 cost, v7 O1) is now capitalised, so only its depreciation reaches 2027 (pro rata: 4.03% of 2027 payroll is depreciated in 2027 under the booked method; 3.72% with the current 9 expensed: (5,286)). Carried from v9: Prod Payroll and the labour block unchanged. v11 precision note: computed on the 9-person current-staff base carried from v9; on the v10 8-person base (PO HC r20 in CO) it moves by well under $1k - immaterial; the carried figure is kept. | D45: -5715.33 | E45: 153421.07 | F45: Prod Payroll!B6:C7, H6:H7; 'HC-PO'!D6:D7
A46: Rate base of the current 9 (critic v8 O7) | B46: downside | C46: PO 5110-5140 removes the 9 current staff at PO HC rates (652,820) but the labour block capitalises them at the model's rates (630,504): 22,315 of 2027 payroll is in neither the P&L nor the asset. If the PO HC cost is right, the capitalised labour is 22,315 higher and its 2027 depreciation +899 (same pro rata). Referred to Finance: which rate base the asset uses. Carried from v9: Prod Payroll and PO HC rates unchanged (the model still costs 9 current staff). v11 precision note: computed on the 9-person current-staff base carried from v9; on the v10 8-person base (PO HC r20 in CO) it moves by well under $1k - immaterial; the carried figure is kept. | D46: -898.65 | E46: 158237.75 | F46: PO!U33:AF35 (v7 amounts); 'Depreciation Schedule'!B214
A47: I-17 | B47: RESOLVED | C47: RESOLVED (user decision 2026-10-10): the Logistics&WH model is booked in CO 6610-6640, less seat LOG-01 (already on CO HC r17): 398,492 in the headline (the 7 new seats 336,530 + MH-01 61,963 at model rates). v9 showed it as a downside of (336,530) to (471,093) depending on the reading. | D47: 0 (now in the headline) | E47: 159136.4 | F47: CO!U67:AF69; 'Logistics&WH Payroll'!rows 34-46
A48: I-10 | B48: downside | C48: FO/FE lines with 2026 spend budgeted at 0 for 2027 (5920 software, 6610 SG&A salaries, 7200 contractors); effect if they continue at the 2026 level. | D48: -384424.9 | E48: -225288.5 | F48: FO!N58, N67, N91; FE!N91 (AG = 0)
A49: I-26 | B49: RESOLVED | C49: RESOLVED (user-confirmed 2026-10-09): Head of Service Delivery salary 205,000/year entered in v5 and now inside the headline (2027 cost 254,454: salary 206,538 + payroll tax 14,045 + benefits 33,872; v4 contribution was 393,486). No remaining exposure. | D49: 0 (now in the headline) | E49: 159136.4 | F49: Fld Eng Budget!B21 = 205,000
A50: I-28 | B50: upside | C50: Probable duplicate (name match only; title and salary differ; likely FO->FE move): FO HC r15 Field Technician = Fld Eng Budget r15 Field Engineer. Remove from FO (Fld Ops Payroll B11 14 -> 13), recalculated: payroll +78,198 and +331 on 5330 (Fld Maint Budget!B29 = B30 + Fld Ops Payroll!B11); supervisor headcount unchanged. Pro rata if the move happens mid-year. | D50: 78529.08 | E50: 237665.48 | F50: Fld Ops Payroll!B11, rows 20-24; Fld Maint Budget!B29
A51: I-28 | B51: upside | C51: Same person: remove from FE instead (Fld Eng Budget row 15, at SD burden rates). Pro rata if the move happens mid-year. | D51: 93093 | E51: 252229.4 | F51: Fld Eng Budget!B15; rows 61, 69-70
A52: I-31 | B52: two-way | C52: Shortfall if DeploySum's Q4-26 go-lives are right (3 lifts, 14 trays more than PO's run rate). | D52: -39057.14 | E52: 120079.26 | F52: PO!J20:M21; DeploySum!C19:E20
A53: I-31 | B53: two-way | C53: Double count if PO's Dec-26 step-up (3 lifts, 12 trays; DeploySum Dec-26 go-lives 0) is Jan-27 units (20 lifts, 60 trays go live Jan-27, built Nov-26). Excludes the 5020 Dec step (+12,300 more if it is the same units). | D53: 37457.14 | E53: 196593.54 | F53: PO!L20:M21; DeploySum!E19:F20
A54: I-32 | B54: upside | C54: SlipBot fleet fully depreciated or retired from Jan-27 (5010 = 0). | D54: 1353574.2 | E54: 1512710.6 | F54: PO!M19; 'Depreciation Schedule'!B21
A55: I-32 | B55: upside | C55: Trend alternative: 5010 keeps falling at the 2026 rate (141,122 Jan-26 -> 112,798 Sep-26, (3,541)/month). | D55: 276163.88 | E55: 435300.28 | F55: PO!B19, J19, M19
A56: I-32 | B56: upside | C56: Trend alternative continued from Sep-26: the same (3,541)/month decline also runs through Oct-Dec 26, so Jan-27 starts 4 months below Sep-26 (98,636 in Jan-27, 59,689 in Dec-27; floored at 0, 0 months at the floor). | D56: 403624.13 | E56: 562760.53 | F56: PO!B19, J19, M19
A57: I-33 | B57: two-way | C57: Peripherals life 60 months instead of 84 (a longer life, e.g. 120 months, gives the opposite sign). | D57: -25534.29 | E57: 133602.11 | F57: 'Depreciation Schedule'!B11
A58: I-34 | B58: upside | C58: FE payroll tax and benefits at the FE HC rates (4.069% / 7.223%) instead of the SD rates (6.8% / 16.4%) on the same FE salary base. | D58: 109538.77 | E58: 268675.17 | F58: Fld Eng Budget!B22:B23; 'HC-FE'!D6:D7; FE!AG68:AG69
A59: I-34 with FE tax at 7.65% | B59: upside | C59: The HC T&B tax rates are below the 7.65% employer FICA and unverified (I-37). If FE payroll tax cannot be below 7.65%, the 6630 part of I-34 (+25,120) goes and the SD 6.8% is short: upside benefits only. | D59: 76599.61 | E59: 235736.01 | F59: 'HC-FE'!D6:D7; Fld Eng Budget!B22:B23
A60: I-37 | B60: downside | C60: CO and PE payroll tax below 7.65% (upper bound on every salary dollar). v10: the CO base now includes the new CO employee (user-confirmed, 110k) at the CO HC rate (5.22%) and the logistics salaries at the model rate (6.8%): CO HC 15,525 + logistics 2,715 + PE 43,967. v9: (56,801). | D60: -62207.37 | E60: 96929.03 | F60: 'HC-CO'!D6, Z67; 'Logistics&WH Payroll'!B5; 'HC-PE'!D6; CO!AG68; PE!AG68
A61: I-37 | B61: downside | C61: FO and FE payroll tax uses the SD field rate 6.8%, also below 7.65% (same upper-bound basis; FO salary base 3,100,031 incl. the ramp, FE 919,884). | D61: -34169.28 | E61: 124967.12 | F61: Fld Ops Payroll!B7; Fld Eng Budget!B22
... A66: A-14 | B66: upside | C66: Depreciation convention: start the month after go-live (B13 = 1), recalculated on v10 (same as v9). | D66: 295806.56 | E66: 454942.96 | F66: 'Depreciation Schedule'!B13 = 1
A67: A-22 | B67: downside | C67: Revenue rests on unsigned / forecast bookings (Sep-Dec 26 includes 2,264,000 unsigned at 100%). Revenue effect not determinable from the workbook. | D67: n/d | E67: n/d | F67: DeploySum!A49 (note 5), row 40
A68: Sign-flip statement (computed, v10): with the Logistics&WH payroll and the new CO employee (user-confirmed, 110k) booked in CO, the 2027 COO contribution is 159,136 (v9 687,435). Single quantified items that turn it negative: the sensitivity (current 9 expensed) (558,996) -> (399,860); I-10 (384,425) -> (225,288). The other downsides leave it positive on their own (smallest remaining: idle-month labour expensed (I-40) 32,228; I-41 (7-overlap): Material Handling Team Lead stays expensed 87,076; I-31 shortfall 120,079). Pairs of the remaining range components (idle months, I-41, I-31 shortfall, I-05 burden, O7) that turn it negative: idle-month labour expensed (I-40) + I-41 (7-overlap): Material Handling Team Lead stays expensed (39,833); idle-month labour expensed (I-40) + I-31 shortfall (6,829). With both switches the sensitivity + idle-month pair is recalculated, not added: (480,264). With costs held fixed, revenue 159,136 (1.0%) below plan also takes the contribution to zero.
A69: Upside: I-32 can add up to 1,353,574 (contribution 1,512,711); the trend alternative adds 276,164 (435,300), or 403,624 (562,761) if the decline also ran through Oct-Dec 26. Labour already in the unit cost (O1): up to +104,417 (263,553). Logistics at CO HC burden rates +19,396; MH-01 on the 9-of-9 reading +2,821.
A70: Range (v10): asymmetric by construction, as in v7-v9. Lower bound 1, booked policy, all quantified downsides (I-41 (7-overlap): Material Handling Team Lead stays expensed (72,061); I-10 (384,425); I-31 shortfall (39,057); I-05 burden capitalised (5,715); rate base of the current 9 (O7) (899); idle-month labour expensed (I-40) (126,908)): (469,929). Lower bound 2, the same under the scope sensitivity, components at B131 = 0 (sensitivity: current 9 expensed (558,996); I-10 (384,425); I-31 shortfall (39,057); I-05 burden capitalised, at the B131 = 0 rate (5,286); idle-month labour expensed, at B131 = 0 (80,404); I-41 is 0 there: r16 is expensed in PO 5110-5140): (909,032). Upper end, I-32 in full only: 1,512,711. Not in the range: I-37 (unverified upper bound); B132 = 1 (only with a 2026 restatement); the O1, burden-rate and 9-of-9 MH-01 upsides. The I-17 terms of v9 are gone (booked). v9 range: (340,662) to 2,041,009 (lower bound 2 (841,728)).
A71: Conclusion: booking the Logistics&WH payroll (398,492) and the new CO employee (user-confirmed, 110k) in CO lowers the 2027 COO contribution from 687,435 (v9) to 159,136. Two single items now turn it negative on their own (the scope sensitivity, Decision #10, and I-10, the FO/FE lines budgeted at 0), and two pairs of smaller downsides do as well. Treat 159,136 as a point estimate inside (469,929) to 1,512,711 (lower bound 2: (909,032)) until Decisions #10 (I-40) and #2 (I-32) are answered, I-10 is confirmed, and the PO owner says whether the Material Handling Team Lead (I-41) fills TL-01.
A72: v7-v9 sign-flip and range statements: see 02-build_notes_v9.md.
A74: Logistics & Warehouse payroll booked in CO; new CO employee (v10, user decision 2026-10-10; I-17 RESOLVED)
A75: CO 6610 = 'HC-CO'!row 67 + 'Logistics&WH Payroll'!row 43 - row 34 + row 46; 6630 = 'HC-CO'!row 68 + row 44 - row 34 x B5; 6640 = 'HC-CO'!row 69 + row 45 - row 34 x B6 (2027 months U:AF <- F:Q / M:X). Seat LOG-01 (row 34) is CO HC r17 and is excluded by formula. MH-01 (row 38) = PO HC r20, now out of the PO 5110-5140 base. New-hire cost -> 6610 (A-45). v11: the 'Check (must be 0)' column (H78:H81) holds live formulas (CO!AG67:AG69 less 'HC-CO'!Z67:Z69 less 'Logistics&WH Payroll' S43:S45 net of LOG-01 row 34, + S46 new-hire cost on 6610; H81 = SUM(H78:H80)); previously static values. Cached values are the LibreOffice recalculation of this workbook.
A76: new CO employee (user-confirmed, 110k): HC-CO r18, 110,000 a year, Jan-27 to Dec-27, +3% from Oct-27, CO HC rates 5.221% / 11.906%: 2027 salary 110,825.00, tax 5,786.68, benefits 13,194.61, total 129,806.29 (A-43).
A77: GL (CO, 2027) | B77: v9 | C77: CO HC roster, 5 existing people | D77: new CO employee (user-confirmed, 110k) (HC-CO r18) | E77: Logistics&WH less LOG-01 | F77: v10 | G77: v10 - v9 | H77: Check (must be 0)
A78: 6610 Salaries and Wages (incl. new-hire cost) | B78: 528451.89 | C78: 528451.89 | D78: 110825 | E78: 324393.2 | F78: 963670.08 | G78: 435218.2 | H78: =CO!AG67-'HC-CO'!Z67-('Logistics&WH Payroll'!S43-'Logistics&WH Payroll'!S34+'Logistics&WH Payroll'!S46) -> 0
A79: 6630 Payroll Taxes | B79: 27592.88 | C79: 27592.88 | D79: 5786.68 | E79: 21718.74 | F79: 55098.3 | G79: 27505.42 | H79: =CO!AG68-'HC-CO'!Z68-('Logistics&WH Payroll'!S44-'Logistics&WH Payroll'!S34*'Logistics&WH Payroll'!$B$5) -> 0
A80: 6640 Benefits | B80: 62916.45 | C80: 62916.45 | D80: 13194.61 | E80: 52380.48 | F80: 128491.55 | G80: 65575.09 | H80: =CO!AG69-'HC-CO'!Z69-('Logistics&WH Payroll'!S45-'Logistics&WH Payroll'!S34*'Logistics&WH Payroll'!$B$6) -> 7.2759576e-11
A81: Total 6610-6640 | B81: 618961.22 | C81: 618961.22 | D81: 129806.29 | E81: 398492.42 | F81: 1147259.9 | G81: 528298.71 | H81: =SUM(H78:H80) -> 7.2759576e-11
A83: Logistics&WH seats (model rates 6.8% / 16.4%; 2027)
A84: Seat | B84: Team | C84: Start | D84: Annual base | E84: 2027 salary | F84: 2027 cost at model rates (incl. new-hire cost) | G84: Booked in CO 6610-6640?
A85: LOG-01 Logistics Manager | B85: Central Operations | C85: on payroll | D85: 120000 | E85: 120900 | F85: 148948.8 | G85: no: already CO HC r17 Field Logistics Manager (CO HC rates); excluded by formula (row 43 - row 34)
A86: INV-01 Inventory Control Specialist | B86: Inventory control | C86: Feb-27 | D86: 48000 | E86: 44360 | F86: 55651.52 | G86: yes: new seat (no HC roster)
A87: TL-01 Material Handling Team Lead | B87: Receiving & putaway | C87: Dec-26 | D87: 52000 | E87: 52390 | F87: 64544.48 | G87: yes: new seat (no HC roster); same title as PO HC r16 (I-41); hired Dec-26, on no roster (I-38)
A88: TL-02 Material Handling Team Lead | B88: Kitting & line replenishment | C88: Jul-27 | D88: 52000 | E88: 26000 | F88: 33032 | G88: yes: new seat (no HC roster)
A89: MH-01 Material Handler | B89: Receiving & putaway | C89: on payroll | D89: 49920 | E89: 50294.4 | F89: 61962.7 | G89: yes: = PO HC r20 Material Handler (moved PO -> CO; out of the PO B131 base)
A90: MH-02 Material Handler | B90: Receiving & putaway | C90: Oct-26 | D90: 49920 | E90: 50294.4 | F90: 61962.7 | G90: yes: new seat (no HC roster); hired Oct-26, on no roster (I-38)
A91: MH-06 Material Handler | B91: Receiving & putaway | C91: Jul-27 | D91: 49920 | E91: 24960 | F91: 31750.72 | G91: yes: new seat (no HC roster)
A92: MH-03 Material Handler | B92: Kitting & line replenishment | C92: Mar-27 | D92: 49920 | E92: 41974.4 | F92: 52712.46 | G92: yes: new seat (no HC roster)
A93: MH-04 Material Handler | B93: Kitting & line replenishment | C93: Jun-27 | D93: 49920 | E93: 29120 | F93: 36875.84 | G93: yes: new seat (no HC roster)
A94: Total booked in CO (8 seats) | E94: 319393.2 | F94: 398492.42 | G94: tax 21,719, benefits 52,380, new-hire cost 5,000
A95: Model total (9 seats) | E95: 440293.2 | F95: 547441.22 | G95: 'Logistics&WH Payroll'!S47; LOG-01 148,949
A97: Head of Service Delivery salary (I-26, RESOLVED in v5)
A98: Input: Fld Eng Budget!B21 = 205,000 (annual salary, user-confirmed 2026-10-09: 'Head of Service delivery salary is $205k annually'). This is the only typed input that changed; no formula, label or other cell was edited.
A99: How the model treats it: row 67 uses the same formula as the other roster rows (=IF(B$58>=$C$21,$B$21/12*(1+IF(B$58>=$B$25,$B$24,0)),0)). Start month C21 = 2027-01-01, so all 12 months of 2027 are paid: 17,083.33/month Jan-Sep, then +3% (Fld Eng Budget!B24 = Fld Ops Payroll M5 = Prod Payroll M5) from 2027-10-01 (B25 = Fld Ops Payroll M6 = Prod Payroll M6) = 17,595.83/month for 3 months. No raise-eligibility test applies on this tab (I-29); the salary is treated as the Dec-26 rate.
A100: Burden: payroll taxes 6.8% (B22 = Fld Ops Payroll B7) and benefits 16.4% (B23 = Fld Ops Payroll B8), applied to the salary rows total (rows 69-70).
A101: 2027 cost of the role: salary 206,538 + payroll tax 14,045 + benefits 33,872 = 254,454.
A102: FE 2027 (AG): 6610 713,347 -> 919,884 (+206,538); 6630 48,508 -> 62,552 (+14,045); 6640 116,989 -> 150,861 (+33,872). FE Total - Expense 931,334 -> 1,185,788. COO P&L rows 67-69 move by the same amounts.
A103: 2027 COO contribution (COO P&L AG132): 393,486 (v4) -> 139,032 (v5), (254,454). 2026 FE 6610 was 850,615; FE 6610 2027 is now 919,884 (8% vs 2026; v4 -16%).
A105: Workbook text superseded by these notes
A106: Depreciation Schedule tab text superseded (critic v4 N1): the explanatory text at 'Depreciation Schedule'!B17 ('In run rate', with its note in D17: 'Never both'), D21 and the row 19 heading ('... carried flat') predates the v4 review and is replaced by A-17, A-18, A-19 and I-31 on this sheet: the flat carry is a builder assumption (A-17, A-19), and the Q4-26 treatment is a two-way risk awaiting the PO owner (A-18, I-31), not a settled 'never both' rule. The tab text was not edited, so that no cell other than Fld Eng Budget!B21 changes in v5.
A107: v8: the Depreciation Schedule's section 4 (rows 79-82) still shows depreciation of the units only; PO rows 20/21 add the capitalised-labour depreciation of section 9 (rows 193-194); row 197 gives the total. The headline text at 'Depreciation Schedule'!A2 ('Section 4 feeds PO rows 19-22') predates v8.
A108: v9: the Depreciation Schedule's A129 describes the v9 rules (B132 = 0, idle switch B135); A2 is still not edited (rows 1-126 are outside the allowed areas).
A109: v10: CO!AI67:AI69 describe the v10 CO payroll formulas. PO!AI33:AI35 (v8/v9 notes) were not edited in v10 (its diff is confined to PO!U33:AF35 there); v11 updates AI33:AI35 to the v10 wording - B131 = 0 restores the v7 amount LESS HC-PO r20, which moved to CO (user decision 2026-10-10). Text only; values unchanged.
... A118: v11 fixes one false sentence (full-sweep F1) and five documentation items (v10 verifier notes 1-3 and 5-7). No budget value changes: the v10 -> v11 diff is confined to this sheet (regenerated) and PO!AI33:AI35 (text); COO P&L!AG132 = 159,136.40 (cached value byte-identical to v10). Root cause of F1: the v7 report chain read the SD book's '.modified' document property; the file has no docProps/core.xml, so openpyxl returned the run time, and the sentence was carried v7 -> v10. report_v11.py reads no file properties, no clock and no dates, so the v11 build is not date-dependent. The workfile's 2026-10-07 save date is real and kept.
A119: # | B119: Fix | C119: Where
A120: 1 | B120: F1 (false statement): the I-38 evidence no longer claims a save date read from the SD book's document properties (reported as a 2026-10-09 re-save in v7-v10) - the SD workbook carries no document properties, so its save date cannot be read from the file; the model's as-of date is unknown. | C120: Issues I-38 (Evidence); md I-38 row
...

Sheet COO P&L
A1: Total COO Departments
A2: 2026 Actuals/Forecast & 2027 Budget
B7: Actual | C7: Actual | D7: Actual | E7: Actual | F7: Actual | G7: Actual | H7: Actual | I7: Actual | J7: Forecast | K7: Forecast | L7: Forecast | M7: Forecast | N7: Forecast | O7: Forecast | U7: Budget | V7: Budget | W7: Budget | X7: Budget | Y7: Budget | Z7: Budget | AA7: Budget | AB7: Budget | AC7: Budget | AD7: Budget | AE7: Budget | AF7: Budget | AG7: Budget | AH7: Budget | AJ7: YOY
B8: Jan | C8: Feb | D8: Mar | E8: Apr | F8: May | G8: Jun | H8: Jul | I8: Aug | J8: Sep | K8: Oct | L8: Nov | M8: Dec | N8: 2026 | O8: % Total Rev | U8: Jan | V8: Feb | W8: Mar | X8: Apr | Y8: May | Z8: Jun | AA8: Jul | AB8: Aug | AC8: Sep | AD8: Oct | AE8: Nov | AF8: Dec | AG8: 2027 | AH8: % Total Rev | AJ8: Fav / (Unfav)
A9: Ordinary Income/Expense
A10: Income
A11: 4000 - Sales
A12: 4100 - Subscription/Platform Fees | B12: =SUM(FO!B12,PO!B12,CO!B12,FE!B12,PE!B12) -> 534716.78 | C12: =SUM(FO!C12,PO!C12,CO!C12,FE!C12,PE!C12) -> 494949.28 | D12: =SUM(FO!D12,PO!D12,CO!D12,FE!D12,PE!D12) -> 468603.55 | E12: =SUM(FO!E12,PO!E12,CO!E12,FE!E12,PE!E12) -> 481426.2 | F12: =SUM(FO!F12,PO!F12,CO!F12,FE!F12,PE!F12) -> 501668.11 | G12: =SUM(FO!G12,PO!G12,CO!G12,FE!G12,PE!G12) -> 473687.43 | H12: =SUM(FO!H12,PO!H12,CO!H12,FE!H12,PE!H12) -> 454042.16 | I12: =SUM(FO!I12,PO!I12,CO!I12,FE!I12,PE!I12) -> 467055.56 | ... M12: =SUM(FO!M12,PO!M12,CO!M12,FE!M12,PE!M12) -> 676940.67 | N12: =SUM(B12:M12) -> 6363078.4 | O12: =IFERROR(N12/N$16,"") -> 0.85710267 | U12: =SUM(FO!U12,PO!U12,CO!U12,FE!U12,PE!U12) -> 783428.42 | V12: =SUM(FO!V12,PO!V12,CO!V12,FE!V12,PE!V12) -> 821920.5 | W12: =SUM(FO!W12,PO!W12,CO!W12,FE!W12,PE!W12) -> 807745.92 | X12: =SUM(FO!X12,PO!X12,CO!X12,FE!X12,PE!X12) -> 907121.88 | Y12: =SUM(FO!Y12,PO!Y12,CO!Y12,FE!Y12,PE!Y12) -> 997375.83 | Z12: =SUM(FO!Z12,PO!Z12,CO!Z12,FE!Z12,PE!Z12) -> 1116046.5 | AA12: =SUM(FO!AA12,PO!AA12,CO!AA12,FE!AA12,PE!AA12) -> 1231592.1 | AB12: =SUM(FO!AB12,PO!AB12,CO!AB12,FE!AB12,PE!AB12) -> 1379626 | ... AF12: =SUM(FO!AF12,PO!AF12,CO!AF12,FE!AF12,PE!AF12) -> 2230141.2 | AG12: =SUM(U12:AF12) -> 15563646 | AH12: =IFERROR(AG12/AG$16,"") -> 1 | AJ12: =AG12-N12 -> 9200567.1
A13: 4500 - Implementation Fees | B13: =SUM(FO!B13,PO!B13,CO!B13,FE!B13,PE!B13) -> 8277.78 | C13: =SUM(FO!C13,PO!C13,CO!C13,FE!C13,PE!C13) -> 8277.78 | D13: =SUM(FO!D13,PO!D13,CO!D13,FE!D13,PE!D13) -> 18277.78 | E13: =SUM(FO!E13,PO!E13,CO!E13,FE!E13,PE!E13) -> 18277.78 | F13: =SUM(FO!F13,PO!F13,CO!F13,FE!F13,PE!F13) -> 18277.78 | G13: =SUM(FO!G13,PO!G13,CO!G13,FE!G13,PE!G13) -> 6055.57 | H13: =SUM(FO!H13,PO!H13,CO!H13,FE!H13,PE!H13) -> 2166.67 | I13: =SUM(FO!I13,PO!I13,CO!I13,FE!I13,PE!I13) -> 4250 | ... M13: =SUM(FO!M13,PO!M13,CO!M13,FE!M13,PE!M13) -> 500 | N13: =SUM(B13:M13) -> 85861.14 | O13: =IFERROR(N13/N$16,"") -> 0.011565442 | U13: =SUM(FO!U13,PO!U13,CO!U13,FE!U13,PE!U13) -> 0 | V13: =SUM(FO!V13,PO!V13,CO!V13,FE!V13,PE!V13) -> 0 | W13: =SUM(FO!W13,PO!W13,CO!W13,FE!W13,PE!W13) -> 0 | X13: =SUM(FO!X13,PO!X13,CO!X13,FE!X13,PE!X13) -> 0 | Y13: =SUM(FO!Y13,PO!Y13,CO!Y13,FE!Y13,PE!Y13) -> 0 | Z13: =SUM(FO!Z13,PO!Z13,CO!Z13,FE!Z13,PE!Z13) -> 0 | AA13: =SUM(FO!AA13,PO!AA13,CO!AA13,FE!AA13,PE!AA13) -> 0 | AB13: =SUM(FO!AB13,PO!AB13,CO!AB13,FE!AB13,PE!AB13) -> 0 | ... AF13: =SUM(FO!AF13,PO!AF13,CO!AF13,FE!AF13,PE!AF13) -> 0 | AG13: =SUM(U13:AF13) -> 0 | AH13: =IFERROR(AG13/AG$16,"") -> 0 | AJ13: =AG13-N13 -> -85861.14
A14: Total - 4000 - Sales | B14: =SUM(B12:B13) -> 542994.56 | C14: =SUM(C12:C13) -> 503227.06 | D14: =SUM(D12:D13) -> 486881.33 | E14: =SUM(E12:E13) -> 499703.98 | F14: =SUM(F12:F13) -> 519945.89 | G14: =SUM(G12:G13) -> 479743 | H14: =SUM(H12:H13) -> 456208.83 | I14: =SUM(I12:I13) -> 471305.56 | ... M14: =SUM(M12:M13) -> 677440.67 | N14: =SUM(B14:M14) -> 6448939.5 | O14: =SUM(O12:O13) -> 0.86866811 | U14: =SUM(U12:U13) -> 783428.42 | V14: =SUM(V12:V13) -> 821920.5 | W14: =SUM(W12:W13) -> 807745.92 | X14: =SUM(X12:X13) -> 907121.88 | Y14: =SUM(Y12:Y13) -> 997375.83 | Z14: =SUM(Z12:Z13) -> 1116046.5 | AA14: =SUM(AA12:AA13) -> 1231592.1 | AB14: =SUM(AB12:AB13) -> 1379626 | ... AF14: =SUM(AF12:AF13) -> 2230141.2 | AG14: =SUM(U14:AF14) -> 15563646 | AH14: =SUM(AH12:AH13) -> 1 | AJ14: =AG14-N14 -> 9114706
A15: 4900 - One-Time Revenue | B15: =SUM(FO!B15,PO!B15,CO!B15,FE!B15,PE!B15) -> 0 | C15: =SUM(FO!C15,PO!C15,CO!C15,FE!C15,PE!C15) -> 0 | D15: =SUM(FO!D15,PO!D15,CO!D15,FE!D15,PE!D15) -> 60000 | E15: =SUM(FO!E15,PO!E15,CO!E15,FE!E15,PE!E15) -> 250000 | F15: =SUM(FO!F15,PO!F15,CO!F15,FE!F15,PE!F15) -> 0 | G15: =SUM(FO!G15,PO!G15,CO!G15,FE!G15,PE!G15) -> 0 | H15: =SUM(FO!H15,PO!H15,CO!H15,FE!H15,PE!H15) -> 185000 | I15: =SUM(FO!I15,PO!I15,CO!I15,FE!I15,PE!I15) -> 0 | ... M15: =SUM(FO!M15,PO!M15,CO!M15,FE!M15,PE!M15) -> 120000 | N15: =SUM(B15:M15) -> 975000 | O15: =IFERROR(N15/N$16,"") -> 0.13133189 | U15: =SUM(FO!U15,PO!U15,CO!U15,FE!U15,PE!U15) -> 0 | V15: =SUM(FO!V15,PO!V15,CO!V15,FE!V15,PE!V15) -> 0 | W15: =SUM(FO!W15,PO!W15,CO!W15,FE!W15,PE!W15) -> 0 | X15: =SUM(FO!X15,PO!X15,CO!X15,FE!X15,PE!X15) -> 0 | Y15: =SUM(FO!Y15,PO!Y15,CO!Y15,FE!Y15,PE!Y15) -> 0 | Z15: =SUM(FO!Z15,PO!Z15,CO!Z15,FE!Z15,PE!Z15) -> 0 | AA15: =SUM(FO!AA15,PO!AA15,CO!AA15,FE!AA15,PE!AA15) -> 0 | AB15: =SUM(FO!AB15,PO!AB15,CO!AB15,FE!AB15,PE!AB15) -> 0 | ... AF15: =SUM(FO!AF15,PO!AF15,CO!AF15,FE!AF15,PE!AF15) -> 0 | AG15: =SUM(U15:AF15) -> 0 | AH15: =IFERROR(AG15/AG$16,"") -> 0 | AJ15: =AG15-N15 -> -975000
A16: Total - Income | B16: =B14+B15 -> 542994.56 | C16: =C14+C15 -> 503227.06 | D16: =D14+D15 -> 546881.33 | E16: =E14+E15 -> 749703.98 | F16: =F14+F15 -> 519945.89 | G16: =G14+G15 -> 479743 | H16: =H14+H15 -> 641208.83 | I16: =I14+I15 -> 471305.56 | ... M16: =M14+M15 -> 797440.67 | N16: =SUM(B16:M16) -> 7423939.5 | O16: =SUM(O14:O15) -> 1 | U16: =U14+U15 -> 783428.42 | V16: =V14+V15 -> 821920.5 | W16: =W14+W15 -> 807745.92 | X16: =X14+X15 -> 907121.88 | Y16: =Y14+Y15 -> 997375.83 | Z16: =Z14+Z15 -> 1116046.5 | AA16: =AA14+AA15 -> 1231592.1 | AB16: =AB14+AB15 -> 1379626 | ... AF16: =AF14+AF15 -> 2230141.2 | AG16: =SUM(U16:AF16) -> 15563646 | AH16: =SUM(AH14:AH15) -> 1 | AJ16: =AG16-N16 -> 8139706
A17: Cost Of Sales
A18: 5000 - Robot Production and Deployment
A19: 5010 - SlipBot Depreciation | B19: =SUM(FO!B19,PO!B19,CO!B19,FE!B19,PE!B19) -> 141122.35 | C19: =SUM(FO!C19,PO!C19,CO!C19,FE!C19,PE!C19) -> 122211.9 | D19: =SUM(FO!D19,PO!D19,CO!D19,FE!D19,PE!D19) -> 126630.2 | E19: =SUM(FO!E19,PO!E19,CO!E19,FE!E19,PE!E19) -> 128215.48 | F19: =SUM(FO!F19,PO!F19,CO!F19,FE!F19,PE!F19) -> 133968.64 | G19: =SUM(FO!G19,PO!G19,CO!G19,FE!G19,PE!G19) -> 133968.64 | H19: =SUM(FO!H19,PO!H19,CO!H19,FE!H19,PE!H19) -> 127510 | I19: =SUM(FO!I19,PO!I19,CO!I19,FE!I19,PE!I19) -> 127510 | ... M19: =SUM(FO!M19,PO!M19,CO!M19,FE!M19,PE!M19) -> 112797.85 | N19: =SUM(B19:M19) -> 1492328.6 | O19: =IFERROR(N19/N$16,"") -> 0.20101573 | U19: =SUM(FO!U19,PO!U19,CO!U19,FE!U19,PE!U19) -> 112797.85 | V19: =SUM(FO!V19,PO!V19,CO!V19,FE!V19,PE!V19) -> 112797.85 | W19: =SUM(FO!W19,PO!W19,CO!W19,FE!W19,PE!W19) -> 112797.85 | X19: =SUM(FO!X19,PO!X19,CO!X19,FE!X19,PE!X19) -> 112797.85 | Y19: =SUM(FO!Y19,PO!Y19,CO!Y19,FE!Y19,PE!Y19) -> 112797.85 | Z19: =SUM(FO!Z19,PO!Z19,CO!Z19,FE!Z19,PE!Z19) -> 112797.85 | AA19: =SUM(FO!AA19,PO!AA19,CO!AA19,FE!AA19,PE!AA19) -> 112797.85 | AB19: =SUM(FO!AB19,PO!AB19,CO!AB19,FE!AB19,PE!AB19) -> 112797.85 | ... AF19: =SUM(FO!AF19,PO!AF19,CO!AF19,FE!AF19,PE!AF19) -> 112797.85 | AG19: =SUM(U19:AF19) -> 1353574.2 | AH19: =IFERROR(AG19/AG$16,"") -> 0.086970254 | AJ19: =N19-AG19 -> 138754.41
A20: 5011 - SlipLift Depreciation | B20: =SUM(FO!B20,PO!B20,CO!B20,FE!B20,PE!B20) -> 0 | C20: =SUM(FO!C20,PO!C20,CO!C20,FE!C20,PE!C20) -> 0 | D20: =SUM(FO!D20,PO!D20,CO!D20,FE!D20,PE!D20) -> 1677.96 | E20: =SUM(FO!E20,PO!E20,CO!E20,FE!E20,PE!E20) -> 3263.24 | F20: =SUM(FO!F20,PO!F20,CO!F20,FE!F20,PE!F20) -> 3263.24 | G20: =SUM(FO!G20,PO!G20,CO!G20,FE!G20,PE!G20) -> 11653.04 | H20: =SUM(FO!H20,PO!H20,CO!H20,FE!H20,PE!H20) -> 7458.14 | I20: =SUM(FO!I20,PO!I20,CO!I20,FE!I20,PE!I20) -> 9836.06 | ... M20: =SUM(FO!M20,PO!M20,CO!M20,FE!M20,PE!M20) -> 20444.9 | N20: =SUM(B20:M20) -> 100359.85 | O20: =IFERROR(N20/N$16,"") -> 0.013518409 | U20: =SUM(FO!U20,PO!U20,CO!U20,FE!U20,PE!U20) -> 35921.09 | V20: =SUM(FO!V20,PO!V20,CO!V20,FE!V20,PE!V20) -> 42111.567 | W20: =SUM(FO!W20,PO!W20,CO!W20,FE!W20,PE!W20) -> 42111.567 | X20: =SUM(FO!X20,PO!X20,CO!X20,FE!X20,PE!X20) -> 61801.068 | Y20: =SUM(FO!Y20,PO!Y20,CO!Y20,FE!Y20,PE!Y20) -> 74048.225 | Z20: =SUM(FO!Z20,PO!Z20,CO!Z20,FE!Z20,PE!Z20) -> 90938.24 | AA20: =SUM(FO!AA20,PO!AA20,CO!AA20,FE!AA20,PE!AA20) -> 106292.23 | AB20: =SUM(FO!AB20,PO!AB20,CO!AB20,FE!AB20,PE!AB20) -> 124753.04 | ... AF20: =SUM(FO!AF20,PO!AF20,CO!AF20,FE!AF20,PE!AF20) -> 229855.61 | AG20: =SUM(U20:AF20) -> 1327486.3 | AH20: =IFERROR(AG20/AG$16,"") -> 0.085294049 | AJ20: =N20-AG20 -> -1227126.5
A21: 5012 - SlipCarrier Depreciation | B21: =SUM(FO!B21,PO!B21,CO!B21,FE!B21,PE!B21) -> 0 | C21: =SUM(FO!C21,PO!C21,CO!C21,FE!C21,PE!C21) -> 0 | D21: =SUM(FO!D21,PO!D21,CO!D21,FE!D21,PE!D21) -> 0 | E21: =SUM(FO!E21,PO!E21,CO!E21,FE!E21,PE!E21) -> 1791.23 | F21: =SUM(FO!F21,PO!F21,CO!F21,FE!F21,PE!F21) -> 3124.54 | G21: =SUM(FO!G21,PO!G21,CO!G21,FE!G21,PE!G21) -> 4796.43 | H21: =SUM(FO!H21,PO!H21,CO!H21,FE!H21,PE!H21) -> 3293.79 | I21: =SUM(FO!I21,PO!I21,CO!I21,FE!I21,PE!I21) -> 3909.48 | ... M21: =SUM(FO!M21,PO!M21,CO!M21,FE!M21,PE!M21) -> 6502.64 | N21: =SUM(B21:M21) -> 36992.697 | O21: =IFERROR(N21/N$16,"") -> 0.004982893 | U21: =SUM(FO!U21,PO!U21,CO!U21,FE!U21,PE!U21) -> 10502.64 | V21: =SUM(FO!V21,PO!V21,CO!V21,FE!V21,PE!V21) -> 12102.64 | W21: =SUM(FO!W21,PO!W21,CO!W21,FE!W21,PE!W21) -> 12102.64 | X21: =SUM(FO!X21,PO!X21,CO!X21,FE!X21,PE!X21) -> 18653.335 | Y21: =SUM(FO!Y21,PO!Y21,CO!Y21,FE!Y21,PE!Y21) -> 23190.743 | Z21: =SUM(FO!Z21,PO!Z21,CO!Z21,FE!Z21,PE!Z21) -> 30194.817 | AA21: =SUM(FO!AA21,PO!AA21,CO!AA21,FE!AA21,PE!AA21) -> 35536.068 | AB21: =SUM(FO!AB21,PO!AB21,CO!AB21,FE!AB21,PE!AB21) -> 41681.16 | ... AF21: =SUM(FO!AF21,PO!AF21,CO!AF21,FE!AF21,PE!AF21) -> 80584.496 | AG21: =SUM(U21:AF21) -> 444024.62 | AH21: =IFERROR(AG21/AG$16,"") -> 0.028529603 | AJ21: =N21-AG21 -> -407031.93
A22: 5020 - Robot Peripherals Depreciation | B22: =SUM(FO!B22,PO!B22,CO!B22,FE!B22,PE!B22) -> 8211.9 | C22: =SUM(FO!C22,PO!C22,CO!C22,FE!C22,PE!C22) -> 10913.63 | D22: =SUM(FO!D22,PO!D22,CO!D22,FE!D22,PE!D22) -> 10939.43 | E22: =SUM(FO!E22,PO!E22,CO!E22,FE!E22,PE!E22) -> 13555.74 | F22: =SUM(FO!F22,PO!F22,CO!F22,FE!F22,PE!F22) -> 13555.75 | G22: =SUM(FO!G22,PO!G22,CO!G22,FE!G22,PE!G22) -> 13770.42 | H22: =SUM(FO!H22,PO!H22,CO!H22,FE!H22,PE!H22) -> 8508.95 | I22: =SUM(FO!I22,PO!I22,CO!I22,FE!I22,PE!I22) -> 8591.56 | ... M22: =SUM(FO!M22,PO!M22,CO!M22,FE!M22,PE!M22) -> 19525.33 | N22: =SUM(B22:M22) -> 158415.37 | O22: =IFERROR(N22/N$16,"") -> 0.021338451 | U22: =SUM(FO!U22,PO!U22,CO!U22,FE!U22,PE!U22) -> 20510.449 | V22: =SUM(FO!V22,PO!V22,CO!V22,FE!V22,PE!V22) -> 20904.497 | W22: =SUM(FO!W22,PO!W22,CO!W22,FE!W22,PE!W22) -> 20904.497 | X22: =SUM(FO!X22,PO!X22,CO!X22,FE!X22,PE!X22) -> 21988.128 | Y22: =SUM(FO!Y22,PO!Y22,CO!Y22,FE!Y22,PE!Y22) -> 22677.711 | Z22: =SUM(FO!Z22,PO!Z22,CO!Z22,FE!Z22,PE!Z22) -> 23662.83 | AA22: =SUM(FO!AA22,PO!AA22,CO!AA22,FE!AA22,PE!AA22) -> 24549.437 | AB22: =SUM(FO!AB22,PO!AB22,CO!AB22,FE!AB22,PE!AB22) -> 25633.068 | ... AF22: =SUM(FO!AF22,PO!AF22,CO!AF22,FE!AF22,PE!AF22) -> 31839.318 | AG22: =SUM(U22:AF22) -> 298139.67 | AH22: =IFERROR(AG22/AG$16,"") -> 0.019156159 | AJ22: =N22-AG22 -> -139724.31
A23: 5025 - Freight and Delivery - Production (Summary)
A24: 5025 - Freight and Delivery - Production (Summary) | B24: =SUM(FO!B24,PO!B24,CO!B24,FE!B24,PE!B24) -> 2370.3 | C24: =SUM(FO!C24,PO!C24,CO!C24,FE!C24,PE!C24) -> 3835.05 | D24: =SUM(FO!D24,PO!D24,CO!D24,FE!D24,PE!D24) -> 11053.81 | E24: =SUM(FO!E24,PO!E24,CO!E24,FE!E24,PE!E24) -> 8300.09 | F24: =SUM(FO!F24,PO!F24,CO!F24,FE!F24,PE!F24) -> 0 | G24: =SUM(FO!G24,PO!G24,CO!G24,FE!G24,PE!G24) -> -544.45 | H24: =SUM(FO!H24,PO!H24,CO!H24,FE!H24,PE!H24) -> 0 | I24: =SUM(FO!I24,PO!I24,CO!I24,FE!I24,PE!I24) -> 93.45 | ... M24: =SUM(FO!M24,PO!M24,CO!M24,FE!M24,PE!M24) -> 5400 | N24: =SUM(B24:M24) -> 50108.25 | O24: =IFERROR(N24/N$16,"") -> 0.0067495498 | U24: =SUM(FO!U24,PO!U24,CO!U24,FE!U24,PE!U24) -> 4045.7252 | V24: =SUM(FO!V24,PO!V24,CO!V24,FE!V24,PE!V24) -> 4045.7252 | W24: =SUM(FO!W24,PO!W24,CO!W24,FE!W24,PE!W24) -> 4045.7252 | X24: =SUM(FO!X24,PO!X24,CO!X24,FE!X24,PE!X24) -> 4045.7252 | Y24: =SUM(FO!Y24,PO!Y24,CO!Y24,FE!Y24,PE!Y24) -> 4045.7252 | Z24: =SUM(FO!Z24,PO!Z24,CO!Z24,FE!Z24,PE!Z24) -> 4045.7252 | AA24: =SUM(FO!AA24,PO!AA24,CO!AA24,FE!AA24,PE!AA24) -> 4045.7252 | AB24: =SUM(FO!AB24,PO!AB24,CO!AB24,FE!AB24,PE!AB24) -> 4045.7252 | ... AF24: =SUM(FO!AF24,PO!AF24,CO!AF24,FE!AF24,PE!AF24) -> 4045.7252 | AG24: =SUM(U24:AF24) -> 48548.703 | AH24: =IFERROR(AG24/AG$16,"") -> 0.0031193658 | AJ24: =N24-AG24 -> 1559.547
A25: 5026 - Freight and Delivery - Production - Expedited | B25: =SUM(FO!B25,PO!B25,CO!B25,FE!B25,PE!B25) -> 0 | C25: =SUM(FO!C25,PO!C25,CO!C25,FE!C25,PE!C25) -> 250 | D25: =SUM(FO!D25,PO!D25,CO!D25,FE!D25,PE!D25) -> 2122.44 | E25: =SUM(FO!E25,PO!E25,CO!E25,FE!E25,PE!E25) -> 261.8 | F25: =SUM(FO!F25,PO!F25,CO!F25,FE!F25,PE!F25) -> 0 | G25: =SUM(FO!G25,PO!G25,CO!G25,FE!G25,PE!G25) -> -86.24 | H25: =SUM(FO!H25,PO!H25,CO!H25,FE!H25,PE!H25) -> 0 | I25: =SUM(FO!I25,PO!I25,CO!I25,FE!I25,PE!I25) -> 1638.89 | ... M25: =SUM(FO!M25,PO!M25,CO!M25,FE!M25,PE!M25) -> 0 | N25: =SUM(B25:M25) -> 4186.89 | O25: =IFERROR(N25/N$16,"") -> 0.00056397146 | U25: =SUM(FO!U25,PO!U25,CO!U25,FE!U25,PE!U25) -> 343.44538 | V25: =SUM(FO!V25,PO!V25,CO!V25,FE!V25,PE!V25) -> 343.44538 | W25: =SUM(FO!W25,PO!W25,CO!W25,FE!W25,PE!W25) -> 343.44538 | X25: =SUM(FO!X25,PO!X25,CO!X25,FE!X25,PE!X25) -> 343.44538 | Y25: =SUM(FO!Y25,PO!Y25,CO!Y25,FE!Y25,PE!Y25) -> 343.44538 | Z25: =SUM(FO!Z25,PO!Z25,CO!Z25,FE!Z25,PE!Z25) -> 343.44538 | AA25: =SUM(FO!AA25,PO!AA25,CO!AA25,FE!AA25,PE!AA25) -> 343.44538 | AB25: =SUM(FO!AB25,PO!AB25,CO!AB25,FE!AB25,PE!AB25) -> 343.44538 | ... AF25: =SUM(FO!AF25,PO!AF25,CO!AF25,FE!AF25,PE!AF25) -> 343.44538 | AG25: =SUM(U25:AF25) -> 4121.3445 | AH25: =IFERROR(AG25/AG$16,"") -> 0.00026480586 | AJ25: =N25-AG25 -> 65.5455
A26: 5027 - Freight and Delivery - Production - Standard | B26: =SUM(FO!B26,PO!B26,CO!B26,FE!B26,PE!B26) -> 0 | C26: =SUM(FO!C26,PO!C26,CO!C26,FE!C26,PE!C26) -> 85 | D26: =SUM(FO!D26,PO!D26,CO!D26,FE!D26,PE!D26) -> 149.33 | E26: =SUM(FO!E26,PO!E26,CO!E26,FE!E26,PE!E26) -> 2494.26 | F26: =SUM(FO!F26,PO!F26,CO!F26,FE!F26,PE!F26) -> 177.67 | G26: =SUM(FO!G26,PO!G26,CO!G26,FE!G26,PE!G26) -> -32.02 | H26: =SUM(FO!H26,PO!H26,CO!H26,FE!H26,PE!H26) -> 852.51 | I26: =SUM(FO!I26,PO!I26,CO!I26,FE!I26,PE!I26) -> 3185.91 | ... M26: =SUM(FO!M26,PO!M26,CO!M26,FE!M26,PE!M26) -> 200 | N26: =SUM(B26:M26) -> 7712.66 | O26: =IFERROR(N26/N$16,"") -> 0.0010388905 | U26: =SUM(FO!U26,PO!U26,CO!U26,FE!U26,PE!U26) -> 615.54587 | V26: =SUM(FO!V26,PO!V26,CO!V26,FE!V26,PE!V26) -> 615.54587 | W26: =SUM(FO!W26,PO!W26,CO!W26,FE!W26,PE!W26) -> 615.54587 | X26: =SUM(FO!X26,PO!X26,CO!X26,FE!X26,PE!X26) -> 615.54587 | Y26: =SUM(FO!Y26,PO!Y26,CO!Y26,FE!Y26,PE!Y26) -> 615.54587 | Z26: =SUM(FO!Z26,PO!Z26,CO!Z26,FE!Z26,PE!Z26) -> 615.54587 | AA26: =SUM(FO!AA26,PO!AA26,CO!AA26,FE!AA26,PE!AA26) -> 615.54587 | AB26: =SUM(FO!AB26,PO!AB26,CO!AB26,FE!AB26,PE!AB26) -> 615.54587 | ... AF26: =SUM(FO!AF26,PO!AF26,CO!AF26,FE!AF26,PE!AF26) -> 615.54587 | AG26: =SUM(U26:AF26) -> 7386.5505 | AH26: =IFERROR(AG26/AG$16,"") -> 0.00047460285 | AJ26: =N26-AG26 -> 326.1095
A27: Total - 5025 - Freight and Delivery - Production (Summary) | B27: =SUM(B24:B26) -> 2370.3 | C27: =SUM(C24:C26) -> 4170.05 | D27: =SUM(D24:D26) -> 13325.58 | E27: =SUM(E24:E26) -> 11056.15 | F27: =SUM(F24:F26) -> 177.67 | G27: =SUM(G24:G26) -> -662.71 | H27: =SUM(H24:H26) -> 852.51 | I27: =SUM(I24:I26) -> 4918.25 | ... M27: =SUM(M24:M26) -> 5600 | N27: =SUM(B27:M27) -> 62007.8 | O27: =IFERROR(N27/N$16,"") -> 0.0083524118 | U27: =SUM(U24:U26) -> 5004.7165 | V27: =SUM(V24:V26) -> 5004.7165 | W27: =SUM(W24:W26) -> 5004.7165 | X27: =SUM(X24:X26) -> 5004.7165 | Y27: =SUM(Y24:Y26) -> 5004.7165 | Z27: =SUM(Z24:Z26) -> 5004.7165 | AA27: =SUM(AA24:AA26) -> 5004.7165 | AB27: =SUM(AB24:AB26) -> 5004.7165 | ... AF27: =SUM(AF24:AF26) -> 5004.7165 | AG27: =SUM(U27:AF27) -> 60056.598 | AH27: =IFERROR(AG27/AG$16,"") -> 0.0038587745 | AJ27: =N27-AG27 -> 1951.202
A28: 5030 - Production Tools and Supplies | B28: =SUM(FO!B28,PO!B28,CO!B28,FE!B28,PE!B28) -> 3122.9 | C28: =SUM(FO!C28,PO!C28,CO!C28,FE!C28,PE!C28) -> 4790.65 | D28: =SUM(FO!D28,PO!D28,CO!D28,FE!D28,PE!D28) -> 8308.32 | E28: =SUM(FO!E28,PO!E28,CO!E28,FE!E28,PE!E28) -> 7596.05 | F28: =SUM(FO!F28,PO!F28,CO!F28,FE!F28,PE!F28) -> 983.17 | G28: =SUM(FO!G28,PO!G28,CO!G28,FE!G28,PE!G28) -> 1367.92 | H28: =SUM(FO!H28,PO!H28,CO!H28,FE!H28,PE!H28) -> 3130.51 | I28: =SUM(FO!I28,PO!I28,CO!I28,FE!I28,PE!I28) -> 5242.04 | ... M28: =SUM(FO!M28,PO!M28,CO!M28,FE!M28,PE!M28) -> 4700 | N28: =SUM(B28:M28) -> 54841.56 | O28: =IFERROR(N28/N$16,"") -> 0.0073871237 | U28: =SUM(FO!U28,PO!U28,CO!U28,FE!U28,PE!U28) -> 10416.667 | V28: =SUM(FO!V28,PO!V28,CO!V28,FE!V28,PE!V28) -> 5416.6667 | W28: =SUM(FO!W28,PO!W28,CO!W28,FE!W28,PE!W28) -> 5416.6667 | X28: =SUM(FO!X28,PO!X28,CO!X28,FE!X28,PE!X28) -> 5416.6667 | Y28: =SUM(FO!Y28,PO!Y28,CO!Y28,FE!Y28,PE!Y28) -> 10416.667 | Z28: =SUM(FO!Z28,PO!Z28,CO!Z28,FE!Z28,PE!Z28) -> 5958.3333 | AA28: =SUM(FO!AA28,PO!AA28,CO!AA28,FE!AA28,PE!AA28) -> 6229.1667 | AB28: =SUM(FO!AB28,PO!AB28,CO!AB28,FE!AB28,PE!AB28) -> 6500 | ... AF28: =SUM(FO!AF28,PO!AF28,CO!AF28,FE!AF28,PE!AF28) -> 7583.3333 | AG28: =SUM(U28:AF28) -> 87854.167 | AH28: =IFERROR(AG28/AG$16,"") -> 0.0056448321 | AJ28: =N28-AG28 -> -33012.607
A29: 5040 - Freight & Delivery - Deployment | B29: =SUM(FO!B29,PO!B29,CO!B29,FE!B29,PE!B29) -> 7118.63 | C29: =SUM(FO!C29,PO!C29,CO!C29,FE!C29,PE!C29) -> 7543.76 | D29: =SUM(FO!D29,PO!D29,CO!D29,FE!D29,PE!D29) -> 4922.7 | E29: =SUM(FO!E29,PO!E29,CO!E29,FE!E29,PE!E29) -> 23173.85 | F29: =SUM(FO!F29,PO!F29,CO!F29,FE!F29,PE!F29) -> 98.92 | G29: =SUM(FO!G29,PO!G29,CO!G29,FE!G29,PE!G29) -> 114.77 | H29: =SUM(FO!H29,PO!H29,CO!H29,FE!H29,PE!H29) -> 0 | I29: =SUM(FO!I29,PO!I29,CO!I29,FE!I29,PE!I29) -> 3240.99 | ... M29: =SUM(FO!M29,PO!M29,CO!M29,FE!M29,PE!M29) -> 5000 | N29: =SUM(B29:M29) -> 85213.62 | O29: =IFERROR(N29/N$16,"") -> 0.011478221 | U29: =SUM(FO!U29,PO!U29,CO!U29,FE!U29,PE!U29) -> 45000 | V29: =SUM(FO!V29,PO!V29,CO!V29,FE!V29,PE!V29) -> 20000 | W29: =SUM(FO!W29,PO!W29,CO!W29,FE!W29,PE!W29) -> 0 | X29: =SUM(FO!X29,PO!X29,CO!X29,FE!X29,PE!X29) -> 60000 | Y29: =SUM(FO!Y29,PO!Y29,CO!Y29,FE!Y29,PE!Y29) -> 45000 | Z29: =SUM(FO!Z29,PO!Z29,CO!Z29,FE!Z29,PE!Z29) -> 70000 | AA29: =SUM(FO!AA29,PO!AA29,CO!AA29,FE!AA29,PE!AA29) -> 55000 | AB29: =SUM(FO!AB29,PO!AB29,CO!AB29,FE!AB29,PE!AB29) -> 65000 | ... AF29: =SUM(FO!AF29,PO!AF29,CO!AF29,FE!AF29,PE!AF29) -> 110000 | AG29: =SUM(U29:AF29) -> 765000 | AH29: =IFERROR(AG29/AG$16,"") -> 0.049153008 | AJ29: =N29-AG29 -> -679786.38
A30: 5050 - Travel - Deployment | B30: =SUM(FO!B30,PO!B30,CO!B30,FE!B30,PE!B30) -> 6383.69 | C30: =SUM(FO!C30,PO!C30,CO!C30,FE!C30,PE!C30) -> 4522.11 | D30: =SUM(FO!D30,PO!D30,CO!D30,FE!D30,PE!D30) -> 6516.64 | E30: =SUM(FO!E30,PO!E30,CO!E30,FE!E30,PE!E30) -> 4232.23 | F30: =SUM(FO!F30,PO!F30,CO!F30,FE!F30,PE!F30) -> 13531.9 | G30: =SUM(FO!G30,PO!G30,CO!G30,FE!G30,PE!G30) -> 4225.43 | H30: =SUM(FO!H30,PO!H30,CO!H30,FE!H30,PE!H30) -> 5242.75 | I30: =SUM(FO!I30,PO!I30,CO!I30,FE!I30,PE!I30) -> 8155.61 | ... M30: =SUM(FO!M30,PO!M30,CO!M30,FE!M30,PE!M30) -> 7000 | N30: =SUM(B30:M30) -> 94810.36 | O30: =IFERROR(N30/N$16,"") -> 0.012770896 | U30: =SUM(FO!U30,PO!U30,CO!U30,FE!U30,PE!U30) -> 18838.611 | V30: =SUM(FO!V30,PO!V30,CO!V30,FE!V30,PE!V30) -> 12559.074 | W30: =SUM(FO!W30,PO!W30,CO!W30,FE!W30,PE!W30) -> 0 | X30: =SUM(FO!X30,PO!X30,CO!X30,FE!X30,PE!X30) -> 29548.226 | Y30: =SUM(FO!Y30,PO!Y30,CO!Y30,FE!Y30,PE!Y30) -> 23268.689 | Z30: =SUM(FO!Z30,PO!Z30,CO!Z30,FE!Z30,PE!Z30) -> 33978.305 | AA30: =SUM(FO!AA30,PO!AA30,CO!AA30,FE!AA30,PE!AA30) -> 29548.226 | AB30: =SUM(FO!AB30,PO!AB30,CO!AB30,FE!AB30,PE!AB30) -> 35827.763 | ... AF30: =SUM(FO!AF30,PO!AF30,CO!AF30,FE!AF30,PE!AF30) -> 59096.453 | AG30: =SUM(U30:AF30) -> 392987.1 | AH30: =IFERROR(AG30/AG$16,"") -> 0.025250324 | AJ30: =N30-AG30 -> -298176.74
A31: 5060 - Meals - Deployment | B31: =SUM(FO!B31,PO!B31,CO!B31,FE!B31,PE!B31) -> 635.5 | C31: =SUM(FO!C31,PO!C31,CO!C31,FE!C31,PE!C31) -> 723.15 | D31: =SUM(FO!D31,PO!D31,CO!D31,FE!D31,PE!D31) -> 1053.77 | E31: =SUM(FO!E31,PO!E31,CO!E31,FE!E31,PE!E31) -> 890.31 | F31: =SUM(FO!F31,PO!F31,CO!F31,FE!F31,PE!F31) -> 1479.8 | G31: =SUM(FO!G31,PO!G31,CO!G31,FE!G31,PE!G31) -> 248.89 | H31: =SUM(FO!H31,PO!H31,CO!H31,FE!H31,PE!H31) -> 602.41 | I31: =SUM(FO!I31,PO!I31,CO!I31,FE!I31,PE!I31) -> 1368.86 | ... M31: =SUM(FO!M31,PO!M31,CO!M31,FE!M31,PE!M31) -> 800 | N31: =SUM(B31:M31) -> 11602.69 | O31: =IFERROR(N31/N$16,"") -> 0.0015628751 | U31: =SUM(FO!U31,PO!U31,CO!U31,FE!U31,PE!U31) -> 2014.994 | V31: =SUM(FO!V31,PO!V31,CO!V31,FE!V31,PE!V31) -> 1343.3293 | W31: =SUM(FO!W31,PO!W31,CO!W31,FE!W31,PE!W31) -> 0 | X31: =SUM(FO!X31,PO!X31,CO!X31,FE!X31,PE!X31) -> 3170.2572 | Y31: =SUM(FO!Y31,PO!Y31,CO!Y31,FE!Y31,PE!Y31) -> 2498.5925 | Z31: =SUM(FO!Z31,PO!Z31,CO!Z31,FE!Z31,PE!Z31) -> 3653.8557 | AA31: =SUM(FO!AA31,PO!AA31,CO!AA31,FE!AA31,PE!AA31) -> 3170.2572 | AB31: =SUM(FO!AB31,PO!AB31,CO!AB31,FE!AB31,PE!AB31) -> 3841.9218 | ... AF31: =SUM(FO!AF31,PO!AF31,CO!AF31,FE!AF31,PE!AF31) -> 6340.5144 | AG31: =SUM(U31:AF31) -> 42180.541 | AH31: =IFERROR(AG31/AG$16,"") -> 0.0027101967 | AJ31: =N31-AG31 -> -30577.851
A32: 5100 - Labor Expense - Production
A33: 5110 - Salaries and Wages - Production | B33: =SUM(FO!B33,PO!B33,CO!B33,FE!B33,PE!B33) -> 0 | C33: =SUM(FO!C33,PO!C33,CO!C33,FE!C33,PE!C33) -> 29333.47 | D33: =SUM(FO!D33,PO!D33,CO!D33,FE!D33,PE!D33) -> 11889.74 | E33: =SUM(FO!E33,PO!E33,CO!E33,FE!E33,PE!E33) -> 21646.72 | F33: =SUM(FO!F33,PO!F33,CO!F33,FE!F33,PE!F33) -> 17259.93 | G33: =SUM(FO!G33,PO!G33,CO!G33,FE!G33,PE!G33) -> 17454.2 | H33: =SUM(FO!H33,PO!H33,CO!H33,FE!H33,PE!H33) -> 20023.74 | I33: =SUM(FO!I33,PO!I33,CO!I33,FE!I33,PE!I33) -> 14849.42 | ... M33: =SUM(FO!M33,PO!M33,CO!M33,FE!M33,PE!M33) -> 17500 | N33: =SUM(B33:M33) -> 202457.22 | O33: =IFERROR(N33/N$16,"") -> 0.027270861 | U33: =SUM(FO!U33,PO!U33,CO!U33,FE!U33,PE!U33) -> #REF! | V33: =SUM(FO!V33,PO!V33,CO!V33,FE!V33,PE!V33) -> #REF! | W33: =SUM(FO!W33,PO!W33,CO!W33,FE!W33,PE!W33) -> #REF! | X33: =SUM(FO!X33,PO!X33,CO!X33,FE!X33,PE!X33) -> #REF! | Y33: =SUM(FO!Y33,PO!Y33,CO!Y33,FE!Y33,PE!Y33) -> #REF! | Z33: =SUM(FO!Z33,PO!Z33,CO!Z33,FE!Z33,PE!Z33) -> #REF! | AA33: =SUM(FO!AA33,PO!AA33,CO!AA33,FE!AA33,PE!AA33) -> #REF! | AB33: =SUM(FO!AB33,PO!AB33,CO!AB33,FE!AB33,PE!AB33) -> #REF! | ... AF33: =SUM(FO!AF33,PO!AF33,CO!AF33,FE!AF33,PE!AF33) -> #REF! | AG33: =SUM(U33:AF33) -> #REF! | AH33: =IFERROR(AG33/AG$16,"") | AJ33: =N33-AG33 -> #REF!
A34: 5130 - Payroll Taxes - Production | B34: =SUM(FO!B34,PO!B34,CO!B34,FE!B34,PE!B34) -> 0 | C34: =SUM(FO!C34,PO!C34,CO!C34,FE!C34,PE!C34) -> 842.84 | D34: =SUM(FO!D34,PO!D34,CO!D34,FE!D34,PE!D34) -> 1357.58 | E34: =SUM(FO!E34,PO!E34,CO!E34,FE!E34,PE!E34) -> 703.54 | F34: =SUM(FO!F34,PO!F34,CO!F34,FE!F34,PE!F34) -> 618.04 | G34: =SUM(FO!G34,PO!G34,CO!G34,FE!G34,PE!G34) -> 634.79 | H34: =SUM(FO!H34,PO!H34,CO!H34,FE!H34,PE!H34) -> 768.4 | I34: =SUM(FO!I34,PO!I34,CO!I34,FE!I34,PE!I34) -> 592.79 | ... M34: =SUM(FO!M34,PO!M34,CO!M34,FE!M34,PE!M34) -> 648 | N34: =SUM(B34:M34) -> 8109.98 | O34: =IFERROR(N34/N$16,"") -> 0.0010924092 | U34: =SUM(FO!U34,PO!U34,CO!U34,FE!U34,PE!U34) -> #REF! | V34: =SUM(FO!V34,PO!V34,CO!V34,FE!V34,PE!V34) -> #REF! | W34: =SUM(FO!W34,PO!W34,CO!W34,FE!W34,PE!W34) -> #REF! | X34: =SUM(FO!X34,PO!X34,CO!X34,FE!X34,PE!X34) -> #REF! | Y34: =SUM(FO!Y34,PO!Y34,CO!Y34,FE!Y34,PE!Y34) -> #REF! | Z34: =SUM(FO!Z34,PO!Z34,CO!Z34,FE!Z34,PE!Z34) -> #REF! | AA34: =SUM(FO!AA34,PO!AA34,CO!AA34,FE!AA34,PE!AA34) -> #REF! | AB34: =SUM(FO!AB34,PO!AB34,CO!AB34,FE!AB34,PE!AB34) -> #REF! | ... AF34: =SUM(FO!AF34,PO!AF34,CO!AF34,FE!AF34,PE!AF34) -> #REF! | AG34: =SUM(U34:AF34) -> #REF! | AH34: =IFERROR(AG34/AG$16,"") | AJ34: =N34-AG34 -> #REF!
A35: 5140 - Benefits - Production | B35: =SUM(FO!B35,PO!B35,CO!B35,FE!B35,PE!B35) -> -18903.27 | C35: =SUM(FO!C35,PO!C35,CO!C35,FE!C35,PE!C35) -> -7499.98 | D35: =SUM(FO!D35,PO!D35,CO!D35,FE!D35,PE!D35) -> 1464.77 | E35: =SUM(FO!E35,PO!E35,CO!E35,FE!E35,PE!E35) -> 2876.74 | F35: =SUM(FO!F35,PO!F35,CO!F35,FE!F35,PE!F35) -> 4138.12 | G35: =SUM(FO!G35,PO!G35,CO!G35,FE!G35,PE!G35) -> 3992.14 | H35: =SUM(FO!H35,PO!H35,CO!H35,FE!H35,PE!H35) -> -6793.75 | I35: =SUM(FO!I35,PO!I35,CO!I35,FE!I35,PE!I35) -> 2732.36 | ... M35: =SUM(FO!M35,PO!M35,CO!M35,FE!M35,PE!M35) -> 4000 | N35: =SUM(B35:M35) -> -1992.87 | O35: =IFERROR(N35/N$16,"") -> -0.00026843834 | U35: =SUM(FO!U35,PO!U35,CO!U35,FE!U35,PE!U35) -> #REF! | V35: =SUM(FO!V35,PO!V35,CO!V35,FE!V35,PE!V35) -> #REF! | W35: =SUM(FO!W35,PO!W35,CO!W35,FE!W35,PE!W35) -> #REF! | X35: =SUM(FO!X35,PO!X35,CO!X35,FE!X35,PE!X35) -> #REF! | Y35: =SUM(FO!Y35,PO!Y35,CO!Y35,FE!Y35,PE!Y35) -> #REF! | Z35: =SUM(FO!Z35,PO!Z35,CO!Z35,FE!Z35,PE!Z35) -> #REF! | AA35: =SUM(FO!AA35,PO!AA35,CO!AA35,FE!AA35,PE!AA35) -> #REF! | AB35: =SUM(FO!AB35,PO!AB35,CO!AB35,FE!AB35,PE!AB35) -> #REF! | ... AF35: =SUM(FO!AF35,PO!AF35,CO!AF35,FE!AF35,PE!AF35) -> #REF! | AG35: =SUM(U35:AF35) -> #REF! | AH35: =IFERROR(AG35/AG$16,"") | AJ35: =N35-AG35 -> #REF!
A36: Total - 5100 - Labor Expense - Production | B36: =SUM(B33:B35) -> -18903.27 | C36: =SUM(C33:C35) -> 22676.33 | D36: =SUM(D33:D35) -> 14712.09 | E36: =SUM(E33:E35) -> 25227 | F36: =SUM(F33:F35) -> 22016.09 | G36: =SUM(G33:G35) -> 22081.13 | H36: =SUM(H33:H35) -> 13998.39 | I36: =SUM(I33:I35) -> 18174.57 | ... M36: =SUM(M33:M35) -> 22148 | N36: =SUM(B36:M36) -> 208574.33 | O36: =IFERROR(N36/N$16,"") -> 0.028094831 | U36: =SUM(U33:U35) -> #REF! | V36: =SUM(V33:V35) -> #REF! | W36: =SUM(W33:W35) -> #REF! | X36: =SUM(X33:X35) -> #REF! | Y36: =SUM(Y33:Y35) -> #REF! | Z36: =SUM(Z33:Z35) -> #REF! | AA36: =SUM(AA33:AA35) -> #REF! | AB36: =SUM(AB33:AB35) -> #REF! | ... AF36: =SUM(AF33:AF35) -> #REF! | AG36: =SUM(U36:AF36) -> #REF! | AH36: =IFERROR(AG36/AG$16,"") | AJ36: =N36-AG36 -> #REF!
A37: Total - 5000 - Robot Production and Deployment | B37: =B19+B22+B27+B28+B29+B30+B31+B36+B20+B21 -> 150062 | C37: =C19+C22+C27+C28+C29+C30+C31+C36+C20+C21 -> 177551.58 | D37: =D19+D22+D27+D28+D29+D30+D31+D36+D20+D21 -> 188086.69 | E37: =E19+E22+E27+E28+E29+E30+E31+E36+E20+E21 -> 219001.28 | F37: =F19+F22+F27+F28+F29+F30+F31+F36+F20+F21 -> 192199.72 | G37: =G19+G22+G27+G28+G29+G30+G31+G36+G20+G21 -> 191563.96 | H37: =H19+H22+H27+H28+H29+H30+H31+H36+H20+H21 -> 170597.45 | I37: =I19+I22+I27+I28+I29+I30+I31+I36+I20+I21 -> 190947.42 | ... M37: =M19+M22+M27+M28+M29+M30+M31+M36+M20+M21 -> 204518.72 | N37: =SUM(B37:M37) -> 2305146.9 | O37: =IFERROR(N37/N$16,"") -> 0.31050184 | U37: =U19+U22+U27+U28+U29+U30+U31+U36+U20+U21 -> #REF! | V37: =V19+V22+V27+V28+V29+V30+V31+V36+V20+V21 -> #REF! | W37: =W19+W22+W27+W28+W29+W30+W31+W36+W20+W21 -> #REF! | X37: =X19+X22+X27+X28+X29+X30+X31+X36+X20+X21 -> #REF! | Y37: =Y19+Y22+Y27+Y28+Y29+Y30+Y31+Y36+Y20+Y21 -> #REF! | Z37: =Z19+Z22+Z27+Z28+Z29+Z30+Z31+Z36+Z20+Z21 -> #REF! | AA37: =AA19+AA22+AA27+AA28+AA29+AA30+AA31+AA36+AA20+AA21 -> #REF! | AB37: =AB19+AB22+AB27+AB28+AB29+AB30+AB31+AB36+AB20+AB21 -> #REF! | ... AF37: =AF19+AF22+AF27+AF28+AF29+AF30+AF31+AF36+AF20+AF21 -> #REF! | AG37: =SUM(U37:AF37) -> #REF! | AH37: =IFERROR(AG37/AG$16,"") | AJ37: =N37-AG37 -> #REF!
A38: 5015 - Supplies and Materials | B38: =SUM(FO!B38,PO!B38,CO!B38,FE!B38,PE!B38) -> 0 | C38: =SUM(FO!C38,PO!C38,CO!C38,FE!C38,PE!C38) -> 0 | D38: =SUM(FO!D38,PO!D38,CO!D38,FE!D38,PE!D38) -> 2782.65 | E38: =SUM(FO!E38,PO!E38,CO!E38,FE!E38,PE!E38) -> 56.1 | F38: =SUM(FO!F38,PO!F38,CO!F38,FE!F38,PE!F38) -> 0 | G38: =SUM(FO!G38,PO!G38,CO!G38,FE!G38,PE!G38) -> -352.47 | H38: =SUM(FO!H38,PO!H38,CO!H38,FE!H38,PE!H38) -> 0 | I38: =SUM(FO!I38,PO!I38,CO!I38,FE!I38,PE!I38) -> 0 | ... M38: =SUM(FO!M38,PO!M38,CO!M38,FE!M38,PE!M38) -> 0 | N38: =SUM(B38:M38) -> 2486.28 | O38: =IFERROR(N38/N$16,"") -> 0.00033490036 | U38: =SUM(FO!U38,PO!U38,CO!U38,FE!U38,PE!U38) -> 21250 | V38: =SUM(FO!V38,PO!V38,CO!V38,FE!V38,PE!V38) -> 6250 | W38: =SUM(FO!W38,PO!W38,CO!W38,FE!W38,PE!W38) -> 6250 | X38: =SUM(FO!X38,PO!X38,CO!X38,FE!X38,PE!X38) -> 6250 | Y38: =SUM(FO!Y38,PO!Y38,CO!Y38,FE!Y38,PE!Y38) -> 6562.5 | Z38: =SUM(FO!Z38,PO!Z38,CO!Z38,FE!Z38,PE!Z38) -> 6875 | AA38: =SUM(FO!AA38,PO!AA38,CO!AA38,FE!AA38,PE!AA38) -> 7187.5 | AB38: =SUM(FO!AB38,PO!AB38,CO!AB38,FE!AB38,PE!AB38) -> 7500 | ... AF38: =SUM(FO!AF38,PO!AF38,CO!AF38,FE!AF38,PE!AF38) -> 8750 | AG38: =SUM(U38:AF38) -> 101250 | AH38: =IFERROR(AG38/AG$16,"") -> 0.0065055452 | AJ38: =N38-AG38 -> -98763.72
A39: 5028 - Duties & Tariffs - Production | B39: =SUM(FO!B39,PO!B39,CO!B39,FE!B39,PE!B39) -> 0 | C39: =SUM(FO!C39,PO!C39,CO!C39,FE!C39,PE!C39) -> 0 | D39: =SUM(FO!D39,PO!D39,CO!D39,FE!D39,PE!D39) -> 0 | E39: =SUM(FO!E39,PO!E39,CO!E39,FE!E39,PE!E39) -> 0 | F39: =SUM(FO!F39,PO!F39,CO!F39,FE!F39,PE!F39) -> 6857.32 | G39: =SUM(FO!G39,PO!G39,CO!G39,FE!G39,PE!G39) -> 0 | H39: =SUM(FO!H39,PO!H39,CO!H39,FE!H39,PE!H39) -> 10645.5 | I39: =SUM(FO!I39,PO!I39,CO!I39,FE!I39,PE!I39) -> 6414.69 | ... M39: =SUM(FO!M39,PO!M39,CO!M39,FE!M39,PE!M39) -> 1000 | N39: =SUM(B39:M39) -> 29917.51 | O39: =IFERROR(N39/N$16,"") -> 0.0040298698 | U39: =SUM(FO!U39,PO!U39,CO!U39,FE!U39,PE!U39) -> 2207.0939 | V39: =SUM(FO!V39,PO!V39,CO!V39,FE!V39,PE!V39) -> 2207.0939 | W39: =SUM(FO!W39,PO!W39,CO!W39,FE!W39,PE!W39) -> 2207.0939 | X39: =SUM(FO!X39,PO!X39,CO!X39,FE!X39,PE!X39) -> 2207.0939 | Y39: =SUM(FO!Y39,PO!Y39,CO!Y39,FE!Y39,PE!Y39) -> 2207.0939 | Z39: =SUM(FO!Z39,PO!Z39,CO!Z39,FE!Z39,PE!Z39) -> 2207.0939 | AA39: =SUM(FO!AA39,PO!AA39,CO!AA39,FE!AA39,PE!AA39) -> 2207.0939 | AB39: =SUM(FO!AB39,PO!AB39,CO!AB39,FE!AB39,PE!AB39) -> 2207.0939 | ... AF39: =SUM(FO!AF39,PO!AF39,CO!AF39,FE!AF39,PE!AF39) -> 2207.0939 | AG39: =SUM(U39:AF39) -> 26485.126 | AH39: =IFERROR(AG39/AG$16,"") -> 0.0017017303 | AJ39: =N39-AG39 -> 3432.3835
A40: 5029 - Processing Fee - Production | B40: =SUM(FO!B40,PO!B40,CO!B40,FE!B40,PE!B40) -> 0 | C40: =SUM(FO!C40,PO!C40,CO!C40,FE!C40,PE!C40) -> 0 | D40: =SUM(FO!D40,PO!D40,CO!D40,FE!D40,PE!D40) -> 0 | E40: =SUM(FO!E40,PO!E40,CO!E40,FE!E40,PE!E40) -> 0 | F40: =SUM(FO!F40,PO!F40,CO!F40,FE!F40,PE!F40) -> 125 | G40: =SUM(FO!G40,PO!G40,CO!G40,FE!G40,PE!G40) -> -362.34 | H40: =SUM(FO!H40,PO!H40,CO!H40,FE!H40,PE!H40) -> 0 | I40: =SUM(FO!I40,PO!I40,CO!I40,FE!I40,PE!I40) -> 4095.3 | ... M40: =SUM(FO!M40,PO!M40,CO!M40,FE!M40,PE!M40) -> 125 | N40: =SUM(B40:M40) -> 4357.96 | O40: =IFERROR(N40/N$16,"") -> 0.00058701448 | U40: =SUM(FO!U40,PO!U40,CO!U40,FE!U40,PE!U40) -> 381.3215 | V40: =SUM(FO!V40,PO!V40,CO!V40,FE!V40,PE!V40) -> 381.3215 | W40: =SUM(FO!W40,PO!W40,CO!W40,FE!W40,PE!W40) -> 381.3215 | X40: =SUM(FO!X40,PO!X40,CO!X40,FE!X40,PE!X40) -> 381.3215 | Y40: =SUM(FO!Y40,PO!Y40,CO!Y40,FE!Y40,PE!Y40) -> 381.3215 | Z40: =SUM(FO!Z40,PO!Z40,CO!Z40,FE!Z40,PE!Z40) -> 381.3215 | AA40: =SUM(FO!AA40,PO!AA40,CO!AA40,FE!AA40,PE!AA40) -> 381.3215 | AB40: =SUM(FO!AB40,PO!AB40,CO!AB40,FE!AB40,PE!AB40) -> 381.3215 | ... AF40: =SUM(FO!AF40,PO!AF40,CO!AF40,FE!AF40,PE!AF40) -> 381.3215 | AG40: =SUM(U40:AF40) -> 4575.858 | AH40: =IFERROR(AG40/AG$16,"") -> 0.00029400939 | AJ40: =N40-AG40 -> -217.898
A41: 5070 - Scrap | B41: =SUM(FO!B41,PO!B41,CO!B41,FE!B41,PE!B41) -> 0 | C41: =SUM(FO!C41,PO!C41,CO!C41,FE!C41,PE!C41) -> 0 | D41: =SUM(FO!D41,PO!D41,CO!D41,FE!D41,PE!D41) -> 0 | E41: =SUM(FO!E41,PO!E41,CO!E41,FE!E41,PE!E41) -> 0 | F41: =SUM(FO!F41,PO!F41,CO!F41,FE!F41,PE!F41) -> 0 | G41: =SUM(FO!G41,PO!G41,CO!G41,FE!G41,PE!G41) -> 1662.88 | H41: =SUM(FO!H41,PO!H41,CO!H41,FE!H41,PE!H41) -> 818.38 | I41: =SUM(FO!I41,PO!I41,CO!I41,FE!I41,PE!I41) -> 111429.29 | ... M41: =SUM(FO!M41,PO!M41,CO!M41,FE!M41,PE!M41) -> 0 | N41: =SUM(B41:M41) -> 113910.55 | O41: =IFERROR(N41/N$16,"") -> 0.01534368 | U41: =SUM(FO!U41,PO!U41,CO!U41,FE!U41,PE!U41) -> 9492.5458 | V41: =SUM(FO!V41,PO!V41,CO!V41,FE!V41,PE!V41) -> 9492.5458 | W41: =SUM(FO!W41,PO!W41,CO!W41,FE!W41,PE!W41) -> 9492.5458 | X41: =SUM(FO!X41,PO!X41,CO!X41,FE!X41,PE!X41) -> 9492.5458 | Y41: =SUM(FO!Y41,PO!Y41,CO!Y41,FE!Y41,PE!Y41) -> 9492.5458 | Z41: =SUM(FO!Z41,PO!Z41,CO!Z41,FE!Z41,PE!Z41) -> 9492.5458 | AA41: =SUM(FO!AA41,PO!AA41,CO!AA41,FE!AA41,PE!AA41) -> 9492.5458 | AB41: =SUM(FO!AB41,PO!AB41,CO!AB41,FE!AB41,PE!AB41) -> 9492.5458 | ... AF41: =SUM(FO!AF41,PO!AF41,CO!AF41,FE!AF41,PE!AF41) -> 9492.5458 | AG41: =SUM(U41:AF41) -> 113910.55 | AH41: =IFERROR(AG41/AG$16,"") -> 0.0073190147 | AJ41: =N41-AG41 -> 0
A42: 5201 - Inventory Adjustments | B42: =SUM(FO!B42,PO!B42,CO!B42,FE!B42,PE!B42) -> 0 | C42: =SUM(FO!C42,PO!C42,CO!C42,FE!C42,PE!C42) -> 0 | D42: =SUM(FO!D42,PO!D42,CO!D42,FE!D42,PE!D42) -> 0 | E42: =SUM(FO!E42,PO!E42,CO!E42,FE!E42,PE!E42) -> 0 | F42: =SUM(FO!F42,PO!F42,CO!F42,FE!F42,PE!F42) -> 0 | G42: =SUM(FO!G42,PO!G42,CO!G42,FE!G42,PE!G42) -> 0 | H42: =SUM(FO!H42,PO!H42,CO!H42,FE!H42,PE!H42) -> 0 | I42: =SUM(FO!I42,PO!I42,CO!I42,FE!I42,PE!I42) -> 0 | ... M42: =SUM(FO!M42,PO!M42,CO!M42,FE!M42,PE!M42) -> 4000 | N42: =SUM(B42:M42) -> 22000 | O42: =IFERROR(N42/N$16,"") -> 0.0029633862 | U42: =SUM(FO!U42,PO!U42,CO!U42,FE!U42,PE!U42) -> 20000 | V42: =SUM(FO!V42,PO!V42,CO!V42,FE!V42,PE!V42) -> 5000 | W42: =SUM(FO!W42,PO!W42,CO!W42,FE!W42,PE!W42) -> 5000 | X42: =SUM(FO!X42,PO!X42,CO!X42,FE!X42,PE!X42) -> 5000 | Y42: =SUM(FO!Y42,PO!Y42,CO!Y42,FE!Y42,PE!Y42) -> 5000 | Z42: =SUM(FO!Z42,PO!Z42,CO!Z42,FE!Z42,PE!Z42) -> 5000 | AA42: =SUM(FO!AA42,PO!AA42,CO!AA42,FE!AA42,PE!AA42) -> 5000 | AB42: =SUM(FO!AB42,PO!AB42,CO!AB42,FE!AB42,PE!AB42) -> 5000 | ... AF42: =SUM(FO!AF42,PO!AF42,CO!AF42,FE!AF42,PE!AF42) -> 5000 | AG42: =SUM(U42:AF42) -> 75000 | AH42: =IFERROR(AG42/AG$16,"") -> 0.0048189224 | AJ42: =N42-AG42 -> -53000
A43: 5300 - Maintenance
A44: 5310 - Contractors - Field | B44: =SUM(FO!B44,PO!B44,CO!B44,FE!B44,PE!B44) -> 0 | C44: =SUM(FO!C44,PO!C44,CO!C44,FE!C44,PE!C44) -> 0 | D44: =SUM(FO!D44,PO!D44,CO!D44,FE!D44,PE!D44) -> 0 | E44: =SUM(FO!E44,PO!E44,CO!E44,FE!E44,PE!E44) -> 0 | F44: =SUM(FO!F44,PO!F44,CO!F44,FE!F44,PE!F44) -> 19808 | G44: =SUM(FO!G44,PO!G44,CO!G44,FE!G44,PE!G44) -> 10009 | H44: =SUM(FO!H44,PO!H44,CO!H44,FE!H44,PE!H44) -> 10968.52 | I44: =SUM(FO!I44,PO!I44,CO!I44,FE!I44,PE!I44) -> 6116.47 | ... M44: =SUM(FO!M44,PO!M44,CO!M44,FE!M44,PE!M44) -> 52110 | N44: =SUM(B44:M44) -> 231821.99 | O44: =IFERROR(N44/N$16,"") -> 0.031226277 | U44: =SUM(FO!U44,PO!U44,CO!U44,FE!U44,PE!U44) -> 37614 | V44: =SUM(FO!V44,PO!V44,CO!V44,FE!V44,PE!V44) -> 37614 | W44: =SUM(FO!W44,PO!W44,CO!W44,FE!W44,PE!W44) -> 50004 | X44: =SUM(FO!X44,PO!X44,CO!X44,FE!X44,PE!X44) -> 50004 | Y44: =SUM(FO!Y44,PO!Y44,CO!Y44,FE!Y44,PE!Y44) -> 50004 | Z44: =SUM(FO!Z44,PO!Z44,CO!Z44,FE!Z44,PE!Z44) -> 50004 | AA44: =SUM(FO!AA44,PO!AA44,CO!AA44,FE!AA44,PE!AA44) -> 50004 | AB44: =SUM(FO!AB44,PO!AB44,CO!AB44,FE!AB44,PE!AB44) -> 50004 | ... AF44: =SUM(FO!AF44,PO!AF44,CO!AF44,FE!AF44,PE!AF44) -> 50004 | AG44: =SUM(U44:AF44) -> 575268 | AH44: =IFERROR(AG44/AG$16,"") -> 0.036962291 | AJ44: =N44-AG44 -> -343446.01
A45: 5320 - Freight & Delivery - Maintenance | B45: =SUM(FO!B45,PO!B45,CO!B45,FE!B45,PE!B45) -> 6406.36 | C45: =SUM(FO!C45,PO!C45,CO!C45,FE!C45,PE!C45) -> 256.47 | D45: =SUM(FO!D45,PO!D45,CO!D45,FE!D45,PE!D45) -> 1327.17 | E45: =SUM(FO!E45,PO!E45,CO!E45,FE!E45,PE!E45) -> 7521.93 | F45: =SUM(FO!F45,PO!F45,CO!F45,FE!F45,PE!F45) -> 4983.81 | G45: =SUM(FO!G45,PO!G45,CO!G45,FE!G45,PE!G45) -> 8114.45 | H45: =SUM(FO!H45,PO!H45,CO!H45,FE!H45,PE!H45) -> 14179.16 | I45: =SUM(FO!I45,PO!I45,CO!I45,FE!I45,PE!I45) -> 11260.12 | ... M45: =SUM(FO!M45,PO!M45,CO!M45,FE!M45,PE!M45) -> 6500 | N45: =SUM(B45:M45) -> 78549.47 | O45: =IFERROR(N45/N$16,"") -> 0.010580564 | U45: =SUM(FO!U45,PO!U45,CO!U45,FE!U45,PE!U45) -> 5185.8217 | V45: =SUM(FO!V45,PO!V45,CO!V45,FE!V45,PE!V45) -> 5561.3594 | W45: =SUM(FO!W45,PO!W45,CO!W45,FE!W45,PE!W45) -> 5561.3594 | X45: =SUM(FO!X45,PO!X45,CO!X45,FE!X45,PE!X45) -> 6594.0881 | Y45: =SUM(FO!Y45,PO!Y45,CO!Y45,FE!Y45,PE!Y45) -> 7251.2791 | Z45: =SUM(FO!Z45,PO!Z45,CO!Z45,FE!Z45,PE!Z45) -> 8190.1234 | AA45: =SUM(FO!AA45,PO!AA45,CO!AA45,FE!AA45,PE!AA45) -> 9035.0832 | AB45: =SUM(FO!AB45,PO!AB45,CO!AB45,FE!AB45,PE!AB45) -> 10067.812 | ... AF45: =SUM(FO!AF45,PO!AF45,CO!AF45,FE!AF45,PE!AF45) -> 15982.531 | AG45: =SUM(U45:AF45) -> 111800.84 | AH45: =IFERROR(AG45/AG$16,"") -> 0.0071834608 | AJ45: =N45-AG45 -> -33251.368
A46: 5330 - Maintenance Tools and Supplies | B46: =SUM(FO!B46,PO!B46,CO!B46,FE!B46,PE!B46) -> 3561.5 | C46: =SUM(FO!C46,PO!C46,CO!C46,FE!C46,PE!C46) -> 2541.74 | D46: =SUM(FO!D46,PO!D46,CO!D46,FE!D46,PE!D46) -> 3711.38 | E46: =SUM(FO!E46,PO!E46,CO!E46,FE!E46,PE!E46) -> 37.64 | F46: =SUM(FO!F46,PO!F46,CO!F46,FE!F46,PE!F46) -> 3173.45 | G46: =SUM(FO!G46,PO!G46,CO!G46,FE!G46,PE!G46) -> 694.03 | H46: =SUM(FO!H46,PO!H46,CO!H46,FE!H46,PE!H46) -> 1220.52 | I46: =SUM(FO!I46,PO!I46,CO!I46,FE!I46,PE!I46) -> 9614.79 | ... M46: =SUM(FO!M46,PO!M46,CO!M46,FE!M46,PE!M46) -> 3400 | N46: =SUM(B46:M46) -> 38155.05 | O46: =IFERROR(N46/N$16,"") -> 0.0051394613 | U46: =SUM(FO!U46,PO!U46,CO!U46,FE!U46,PE!U46) -> 14024.02 | V46: =SUM(FO!V46,PO!V46,CO!V46,FE!V46,PE!V46) -> 9524.02 | W46: =SUM(FO!W46,PO!W46,CO!W46,FE!W46,PE!W46) -> 551.6 | X46: =SUM(FO!X46,PO!X46,CO!X46,FE!X46,PE!X46) -> 21334.34 | Y46: =SUM(FO!Y46,PO!Y46,CO!Y46,FE!Y46,PE!Y46) -> 16972.24 | Z46: =SUM(FO!Z46,PO!Z46,CO!Z46,FE!Z46,PE!Z46) -> 24310.14 | AA46: =SUM(FO!AA46,PO!AA46,CO!AA46,FE!AA46,PE!AA46) -> 21775.62 | AB46: =SUM(FO!AB46,PO!AB46,CO!AB46,FE!AB46,PE!AB46) -> 26468.68 | ... AF46: =SUM(FO!AF46,PO!AF46,CO!AF46,FE!AF46,PE!AF46) -> 43578.82 | AG46: =SUM(U46:AF46) -> 288069.36 | AH46: =IFERROR(AG46/AG$16,"") -> 0.018509119 | AJ46: =N46-AG46 -> -249914.31
A47: 5340 - Spare Parts | B47: =SUM(FO!B47,PO!B47,CO!B47,FE!B47,PE!B47) -> 14676.39 | C47: =SUM(FO!C47,PO!C47,CO!C47,FE!C47,PE!C47) -> 19314.55 | D47: =SUM(FO!D47,PO!D47,CO!D47,FE!D47,PE!D47) -> 63529 | E47: =SUM(FO!E47,PO!E47,CO!E47,FE!E47,PE!E47) -> 12929.3 | F47: =SUM(FO!F47,PO!F47,CO!F47,FE!F47,PE!F47) -> 45540.82 | G47: =SUM(FO!G47,PO!G47,CO!G47,FE!G47,PE!G47) -> 39676.61 | H47: =SUM(FO!H47,PO!H47,CO!H47,FE!H47,PE!H47) -> 12049.91 | I47: =SUM(FO!I47,PO!I47,CO!I47,FE!I47,PE!I47) -> -8022.21 | ... M47: =SUM(FO!M47,PO!M47,CO!M47,FE!M47,PE!M47) -> 31000 | N47: =SUM(B47:M47) -> 319694.37 | O47: =IFERROR(N47/N$16,"") -> 0.043062631 | U47: =SUM(FO!U47,PO!U47,CO!U47,FE!U47,PE!U47) -> 51213.618 | V47: =SUM(FO!V47,PO!V47,CO!V47,FE!V47,PE!V47) -> 58299.235 | W47: =SUM(FO!W47,PO!W47,CO!W47,FE!W47,PE!W47) -> 58299.235 | X47: =SUM(FO!X47,PO!X47,CO!X47,FE!X47,PE!X47) -> 77784.682 | Y47: =SUM(FO!Y47,PO!Y47,CO!Y47,FE!Y47,PE!Y47) -> 90309.512 | Z47: =SUM(FO!Z47,PO!Z47,CO!Z47,FE!Z47,PE!Z47) -> 108148.55 | AA47: =SUM(FO!AA47,PO!AA47,CO!AA47,FE!AA47,PE!AA47) -> 124216.19 | AB47: =SUM(FO!AB47,PO!AB47,CO!AB47,FE!AB47,PE!AB47) -> 143826.64 | ... AF47: =SUM(FO!AF47,PO!AF47,CO!AF47,FE!AF47,PE!AF47) -> 255925.11 | AG47: =SUM(U47:AF47) -> 1554364.9 | AH47: =IFERROR(AG47/AG$16,"") -> 0.099871516 | AJ47: =N47-AG47 -> -1234670.5
A48: 5350 - Warehouse | B48: =SUM(FO!B48,PO!B48,CO!B48,FE!B48,PE!B48) -> 2745.99 | C48: =SUM(FO!C48,PO!C48,CO!C48,FE!C48,PE!C48) -> 5395 | D48: =SUM(FO!D48,PO!D48,CO!D48,FE!D48,PE!D48) -> 4120 | E48: =SUM(FO!E48,PO!E48,CO!E48,FE!E48,PE!E48) -> 2500 | F48: =SUM(FO!F48,PO!F48,CO!F48,FE!F48,PE!F48) -> 2680 | G48: =SUM(FO!G48,PO!G48,CO!G48,FE!G48,PE!G48) -> 2560 | H48: =SUM(FO!H48,PO!H48,CO!H48,FE!H48,PE!H48) -> 1240 | I48: =SUM(FO!I48,PO!I48,CO!I48,FE!I48,PE!I48) -> 1060 | ... M48: =SUM(FO!M48,PO!M48,CO!M48,FE!M48,PE!M48) -> 3000 | N48: =SUM(B48:M48) -> 34300.99 | O48: =IFERROR(N48/N$16,"") -> 0.0046203218 | U48: =SUM(FO!U48,PO!U48,CO!U48,FE!U48,PE!U48) -> 3000 | V48: =SUM(FO!V48,PO!V48,CO!V48,FE!V48,PE!V48) -> 3000 | W48: =SUM(FO!W48,PO!W48,CO!W48,FE!W48,PE!W48) -> 3000 | X48: =SUM(FO!X48,PO!X48,CO!X48,FE!X48,PE!X48) -> 3000 | Y48: =SUM(FO!Y48,PO!Y48,CO!Y48,FE!Y48,PE!Y48) -> 3000 | Z48: =SUM(FO!Z48,PO!Z48,CO!Z48,FE!Z48,PE!Z48) -> 3000 | AA48: =SUM(FO!AA48,PO!AA48,CO!AA48,FE!AA48,PE!AA48) -> 3000 | AB48: =SUM(FO!AB48,PO!AB48,CO!AB48,FE!AB48,PE!AB48) -> 3000 | ... AF48: =SUM(FO!AF48,PO!AF48,CO!AF48,FE!AF48,PE!AF48) -> 3000 | AG48: =SUM(U48:AF48) -> 36000 | AH48: =IFERROR(AG48/AG$16,"") -> 0.0023130827 | AJ48: =N48-AG48 -> -1699.01
A49: 5360 - Travel - Maintenance | B49: =SUM(FO!B49,PO!B49,CO!B49,FE!B49,PE!B49) -> 1960.25 | C49: =SUM(FO!C49,PO!C49,CO!C49,FE!C49,PE!C49) -> 1371.12 | D49: =SUM(FO!D49,PO!D49,CO!D49,FE!D49,PE!D49) -> 897.84 | E49: =SUM(FO!E49,PO!E49,CO!E49,FE!E49,PE!E49) -> 881.53 | F49: =SUM(FO!F49,PO!F49,CO!F49,FE!F49,PE!F49) -> 7011.68 | G49: =SUM(FO!G49,PO!G49,CO!G49,FE!G49,PE!G49) -> 4314.54 | H49: =SUM(FO!H49,PO!H49,CO!H49,FE!H49,PE!H49) -> 2792.06 | I49: =SUM(FO!I49,PO!I49,CO!I49,FE!I49,PE!I49) -> 9114.23 | ... M49: =SUM(FO!M49,PO!M49,CO!M49,FE!M49,PE!M49) -> 4000 | N49: =SUM(B49:M49) -> 46343.25 | O49: =IFERROR(N49/N$16,"") -> 0.0062424067 | U49: =SUM(FO!U49,PO!U49,CO!U49,FE!U49,PE!U49) -> 3992 | V49: =SUM(FO!V49,PO!V49,CO!V49,FE!V49,PE!V49) -> 3992 | W49: =SUM(FO!W49,PO!W49,CO!W49,FE!W49,PE!W49) -> 3992 | X49: =SUM(FO!X49,PO!X49,CO!X49,FE!X49,PE!X49) -> 3992 | Y49: =SUM(FO!Y49,PO!Y49,CO!Y49,FE!Y49,PE!Y49) -> 3992 | Z49: =SUM(FO!Z49,PO!Z49,CO!Z49,FE!Z49,PE!Z49) -> 3992 | AA49: =SUM(FO!AA49,PO!AA49,CO!AA49,FE!AA49,PE!AA49) -> 3992 | AB49: =SUM(FO!AB49,PO!AB49,CO!AB49,FE!AB49,PE!AB49) -> 3992 | ... AF49: =SUM(FO!AF49,PO!AF49,CO!AF49,FE!AF49,PE!AF49) -> 3992 | AG49: =SUM(U49:AF49) -> 47904 | AH49: =IFERROR(AG49/AG$16,"") -> 0.0030779421 | AJ49: =N49-AG49 -> -1560.75
A50: 5370 - Meals - Maintenance | B50: =SUM(FO!B50,PO!B50,CO!B50,FE!B50,PE!B50) -> 0 | C50: =SUM(FO!C50,PO!C50,CO!C50,FE!C50,PE!C50) -> 121.5 | D50: =SUM(FO!D50,PO!D50,CO!D50,FE!D50,PE!D50) -> 160.63 | E50: =SUM(FO!E50,PO!E50,CO!E50,FE!E50,PE!E50) -> 0 | F50: =SUM(FO!F50,PO!F50,CO!F50,FE!F50,PE!F50) -> 18.64 | G50: =SUM(FO!G50,PO!G50,CO!G50,FE!G50,PE!G50) -> 0 | H50: =SUM(FO!H50,PO!H50,CO!H50,FE!H50,PE!H50) -> 0 | I50: =SUM(FO!I50,PO!I50,CO!I50,FE!I50,PE!I50) -> 175 | ... M50: =SUM(FO!M50,PO!M50,CO!M50,FE!M50,PE!M50) -> 150 | N50: =SUM(B50:M50) -> 1075.77 | O50: =IFERROR(N50/N$16,"") -> 0.00014490554 | U50: =SUM(FO!U50,PO!U50,CO!U50,FE!U50,PE!U50) -> 0 | V50: =SUM(FO!V50,PO!V50,CO!V50,FE!V50,PE!V50) -> 0 | W50: =SUM(FO!W50,PO!W50,CO!W50,FE!W50,PE!W50) -> 0 | X50: =SUM(FO!X50,PO!X50,CO!X50,FE!X50,PE!X50) -> 0 | Y50: =SUM(FO!Y50,PO!Y50,CO!Y50,FE!Y50,PE!Y50) -> 0 | Z50: =SUM(FO!Z50,PO!Z50,CO!Z50,FE!Z50,PE!Z50) -> 0 | AA50: =SUM(FO!AA50,PO!AA50,CO!AA50,FE!AA50,PE!AA50) -> 0 | AB50: =SUM(FO!AB50,PO!AB50,CO!AB50,FE!AB50,PE!AB50) -> 0 | ... AF50: =SUM(FO!AF50,PO!AF50,CO!AF50,FE!AF50,PE!AF50) -> 0 | AG50: =SUM(U50:AF50) -> 0 | AH50: =IFERROR(AG50/AG$16,"") -> 0 | AJ50: =N50-AG50 -> 1075.77
A51: 5500 - Labor Expense - Field Operations
A52: 5510 - :Salaries and Wages - Field Operations | B52: =SUM(FO!B52,PO!B52,CO!B52,FE!B52,PE!B52) -> 41771.03 | C52: =SUM(FO!C52,PO!C52,CO!C52,FE!C52,PE!C52) -> 38728.5 | D52: =SUM(FO!D52,PO!D52,CO!D52,FE!D52,PE!D52) -> 55703.48 | E52: =SUM(FO!E52,PO!E52,CO!E52,FE!E52,PE!E52) -> 77202.08 | F52: =SUM(FO!F52,PO!F52,CO!F52,FE!F52,PE!F52) -> 72865.8 | G52: =SUM(FO!G52,PO!G52,CO!G52,FE!G52,PE!G52) -> 64701.68 | H52: =SUM(FO!H52,PO!H52,CO!H52,FE!H52,PE!H52) -> 82139.24 | I52: =SUM(FO!I52,PO!I52,CO!I52,FE!I52,PE!I52) -> 79454.55 | ... M52: =SUM(FO!M52,PO!M52,CO!M52,FE!M52,PE!M52) -> 96900 | N52: =SUM(B52:M52) -> 887966.36 | O52: =IFERROR(N52/N$16,"") -> 0.11960851 | U52: =SUM(FO!U52,PO!U52,CO!U52,FE!U52,PE!U52) -> 120126.25 | V52: =SUM(FO!V52,PO!V52,CO!V52,FE!V52,PE!V52) -> 116126.25 | W52: =SUM(FO!W52,PO!W52,CO!W52,FE!W52,PE!W52) -> 154626.25 | X52: =SUM(FO!X52,PO!X52,CO!X52,FE!X52,PE!X52) -> 166376.25 | Y52: =SUM(FO!Y52,PO!Y52,CO!Y52,FE!Y52,PE!Y52) -> 196626.25 | Z52: =SUM(FO!Z52,PO!Z52,CO!Z52,FE!Z52,PE!Z52) -> 222876.25 | AA52: =SUM(FO!AA52,PO!AA52,CO!AA52,FE!AA52,PE!AA52) -> 265876.25 | AB52: =SUM(FO!AB52,PO!AB52,CO!AB52,FE!AB52,PE!AB52) -> 302626.25 | ... AF52: =SUM(FO!AF52,PO!AF52,CO!AF52,FE!AF52,PE!AF52) -> 499215.04 | AG52: =SUM(U52:AF52) -> 3238031.4 | AH52: =IFERROR(AG52/AG$16,"") -> 0.20805096 | AJ52: =N52-AG52 -> -2350065
A53: 5530 - :Payroll Taxes - Field Operations | B53: =SUM(FO!B53,PO!B53,CO!B53,FE!B53,PE!B53) -> 3714.57 | C53: =SUM(FO!C53,PO!C53,CO!C53,FE!C53,PE!C53) -> 3251.23 | D53: =SUM(FO!D53,PO!D53,CO!D53,FE!D53,PE!D53) -> 3711.25 | E53: =SUM(FO!E53,PO!E53,CO!E53,FE!E53,PE!E53) -> 5152.42 | F53: =SUM(FO!F53,PO!F53,CO!F53,FE!F53,PE!F53) -> 4827.71 | G53: =SUM(FO!G53,PO!G53,CO!G53,FE!G53,PE!G53) -> 4403.72 | H53: =SUM(FO!H53,PO!H53,CO!H53,FE!H53,PE!H53) -> 5573.24 | I53: =SUM(FO!I53,PO!I53,CO!I53,FE!I53,PE!I53) -> 5853.77 | ... M53: =SUM(FO!M53,PO!M53,CO!M53,FE!M53,PE!M53) -> 6299 | N53: =SUM(B53:M53) -> 60889.91 | O53: =IFERROR(N53/N$16,"") -> 0.0082018327 | U53: =SUM(FO!U53,PO!U53,CO!U53,FE!U53,PE!U53) -> 7896.585 | V53: =SUM(FO!V53,PO!V53,CO!V53,FE!V53,PE!V53) -> 7896.585 | W53: =SUM(FO!W53,PO!W53,CO!W53,FE!W53,PE!W53) -> 9834.585 | X53: =SUM(FO!X53,PO!X53,CO!X53,FE!X53,PE!X53) -> 10905.585 | Y53: =SUM(FO!Y53,PO!Y53,CO!Y53,FE!Y53,PE!Y53) -> 12690.585 | Z53: =SUM(FO!Z53,PO!Z53,CO!Z53,FE!Z53,PE!Z53) -> 14475.585 | AA53: =SUM(FO!AA53,PO!AA53,CO!AA53,FE!AA53,PE!AA53) -> 17127.585 | AB53: =SUM(FO!AB53,PO!AB53,CO!AB53,FE!AB53,PE!AB53) -> 19626.585 | ... AF53: =SUM(FO!AF53,PO!AF53,CO!AF53,FE!AF53,PE!AF53) -> 32722.623 | AG53: =SUM(U53:AF53) -> 210802.13 | AH53: =IFERROR(AG53/AG$16,"") -> 0.013544522 | AJ53: =N53-AG53 -> -149912.22
A54: 5540 - :Benefits - Field Operations | B54: =SUM(FO!B54,PO!B54,CO!B54,FE!B54,PE!B54) -> 31338.07 | C54: =SUM(FO!C54,PO!C54,CO!C54,FE!C54,PE!C54) -> 21236.59 | D54: =SUM(FO!D54,PO!D54,CO!D54,FE!D54,PE!D54) -> 9448.65 | E54: =SUM(FO!E54,PO!E54,CO!E54,FE!E54,PE!E54) -> 12493.8 | F54: =SUM(FO!F54,PO!F54,CO!F54,FE!F54,PE!F54) -> 12115.76 | G54: =SUM(FO!G54,PO!G54,CO!G54,FE!G54,PE!G54) -> 16324.25 | H54: =SUM(FO!H54,PO!H54,CO!H54,FE!H54,PE!H54) -> 13014.13 | I54: =SUM(FO!I54,PO!I54,CO!I54,FE!I54,PE!I54) -> 17324.26 | ... M54: =SUM(FO!M54,PO!M54,CO!M54,FE!M54,PE!M54) -> 11628 | N54: =SUM(B54:M54) -> 178343.51 | O54: =IFERROR(N54/N$16,"") -> 0.024022759 | U54: =SUM(FO!U54,PO!U54,CO!U54,FE!U54,PE!U54) -> 19044.705 | V54: =SUM(FO!V54,PO!V54,CO!V54,FE!V54,PE!V54) -> 19044.705 | W54: =SUM(FO!W54,PO!W54,CO!W54,FE!W54,PE!W54) -> 23718.705 | X54: =SUM(FO!X54,PO!X54,CO!X54,FE!X54,PE!X54) -> 26301.705 | Y54: =SUM(FO!Y54,PO!Y54,CO!Y54,FE!Y54,PE!Y54) -> 30606.705 | Z54: =SUM(FO!Z54,PO!Z54,CO!Z54,FE!Z54,PE!Z54) -> 34911.705 | AA54: =SUM(FO!AA54,PO!AA54,CO!AA54,FE!AA54,PE!AA54) -> 41307.705 | AB54: =SUM(FO!AB54,PO!AB54,CO!AB54,FE!AB54,PE!AB54) -> 47334.705 | ... AF54: =SUM(FO!AF54,PO!AF54,CO!AF54,FE!AF54,PE!AF54) -> 78919.266 | AG54: =SUM(U54:AF54) -> 508405.14 | AH54: =IFERROR(AG54/AG$16,"") -> 0.032666199 | AJ54: =N54-AG54 -> -330061.63
A55: Total - 5500 - Labor Expense - Field Operations | B55: =SUM(B52:B54) -> 76823.67 | C55: =SUM(C52:C54) -> 63216.32 | D55: =SUM(D52:D54) -> 68863.38 | E55: =SUM(E52:E54) -> 94848.3 | F55: =SUM(F52:F54) -> 89809.27 | G55: =SUM(G52:G54) -> 85429.65 | H55: =SUM(H52:H54) -> 100726.61 | I55: =SUM(I52:I54) -> 102632.58 | ... M55: =SUM(M52:M54) -> 114827 | N55: =SUM(B55:M55) -> 1127199.8 | O55: =IFERROR(N55/N$16,"") -> 0.1518331 | U55: =SUM(U52:U54) -> 147067.54 | V55: =SUM(V52:V54) -> 143067.54 | W55: =SUM(W52:W54) -> 188179.54 | X55: =SUM(X52:X54) -> 203583.54 | Y55: =SUM(Y52:Y54) -> 239923.54 | Z55: =SUM(Z52:Z54) -> 272263.54 | AA55: =SUM(AA52:AA54) -> 324311.54 | AB55: =SUM(AB52:AB54) -> 369587.54 | ... AF55: =SUM(AF52:AF54) -> 610856.93 | AG55: =SUM(U55:AF55) -> 3957238.6 | AH55: =IFERROR(AG55/AG$16,"") -> 0.25426168 | AJ55: =N55-AG55 -> -2830038.9
A56: Total - 5300 - Maintenance | B56: =B44+B45+B46+B47+B48+B49+B50+B55 -> 106174.16 | C56: =C44+C45+C46+C47+C48+C49+C50+C55 -> 92216.7 | D56: =D44+D45+D46+D47+D48+D49+D50+D55 -> 142609.4 | E56: =E44+E45+E46+E47+E48+E49+E50+E55 -> 118718.7 | F56: =F44+F45+F46+F47+F48+F49+F50+F55 -> 173025.67 | G56: =G44+G45+G46+G47+G48+G49+G50+G55 -> 150798.28 | H56: =H44+H45+H46+H47+H48+H49+H50+H55 -> 143176.78 | I56: =I44+I45+I46+I47+I48+I49+I50+I55 -> 131950.98 | ... M56: =M44+M45+M46+M47+M48+M49+M50+M55 -> 214987 | N56: =SUM(B56:M56) -> 1877140.7 | O56: =IFERROR(N56/N$16,"") -> 0.25284967 | U56: =U44+U45+U46+U47+U48+U49+U50+U55 -> 262097 | V56: =V44+V45+V46+V47+V48+V49+V50+V55 -> 261058.15 | W56: =W44+W45+W46+W47+W48+W49+W50+W55 -> 309587.73 | X56: =X44+X45+X46+X47+X48+X49+X50+X55 -> 366292.65 | Y56: =Y44+Y45+Y46+Y47+Y48+Y49+Y50+Y55 -> 411452.57 | Z56: =Z44+Z45+Z46+Z47+Z48+Z49+Z50+Z55 -> 469908.36 | AA56: =AA44+AA45+AA46+AA47+AA48+AA49+AA50+AA55 -> 536334.44 | AB56: =AB44+AB45+AB46+AB47+AB48+AB49+AB50+AB55 -> 606946.67 | ... AF56: =AF44+AF45+AF46+AF47+AF48+AF49+AF50+AF55 -> 983339.39 | AG56: =SUM(U56:AF56) -> 6570645.7 | AH56: =IFERROR(AG56/AG$16,"") -> 0.42217909 | AJ56: =N56-AG56 -> -4693505
A57: 5900 - Other COGS
A58: 5920 - Software - COGS | B58: =SUM(FO!B58,PO!B58,CO!B58,FE!B58,PE!B58) -> 11975.85 | C58: =SUM(FO!C58,PO!C58,CO!C58,FE!C58,PE!C58) -> 11156.17 | D58: =SUM(FO!D58,PO!D58,CO!D58,FE!D58,PE!D58) -> 11961.24 | E58: =SUM(FO!E58,PO!E58,CO!E58,FE!E58,PE!E58) -> 7090.45 | F58: =SUM(FO!F58,PO!F58,CO!F58,FE!F58,PE!F58) -> 12334.88 | G58: =SUM(FO!G58,PO!G58,CO!G58,FE!G58,PE!G58) -> 13958.17 | H58: =SUM(FO!H58,PO!H58,CO!H58,FE!H58,PE!H58) -> 17445.88 | I58: =SUM(FO!I58,PO!I58,CO!I58,FE!I58,PE!I58) -> 13773.96 | ... M58: =SUM(FO!M58,PO!M58,CO!M58,FE!M58,PE!M58) -> 5208 | N58: =SUM(B58:M58) -> 120528.6 | O58: =IFERROR(N58/N$16,"") -> 0.016235127 | U58: =SUM(FO!U58,PO!U58,CO!U58,FE!U58,PE!U58) -> 0 | V58: =SUM(FO!V58,PO!V58,CO!V58,FE!V58,PE!V58) -> 0 | W58: =SUM(FO!W58,PO!W58,CO!W58,FE!W58,PE!W58) -> 0 | X58: =SUM(FO!X58,PO!X58,CO!X58,FE!X58,PE!X58) -> 0 | Y58: =SUM(FO!Y58,PO!Y58,CO!Y58,FE!Y58,PE!Y58) -> 0 | Z58: =SUM(FO!Z58,PO!Z58,CO!Z58,FE!Z58,PE!Z58) -> 0 | AA58: =SUM(FO!AA58,PO!AA58,CO!AA58,FE!AA58,PE!AA58) -> 0 | AB58: =SUM(FO!AB58,PO!AB58,CO!AB58,FE!AB58,PE!AB58) -> 0 | ... AF58: =SUM(FO!AF58,PO!AF58,CO!AF58,FE!AF58,PE!AF58) -> 0 | AG58: =SUM(U58:AF58) -> 0 | AH58: =IFERROR(AG58/AG$16,"") -> 0 | AJ58: =N58-AG58 -> 120528.6
A59: 5950 - Certification Expense | B59: =SUM(FO!B59,PO!B59,CO!B59,FE!B59,PE!B59) -> 65 | C59: =SUM(FO!C59,PO!C59,CO!C59,FE!C59,PE!C59) -> 0 | D59: =SUM(FO!D59,PO!D59,CO!D59,FE!D59,PE!D59) -> 0 | E59: =SUM(FO!E59,PO!E59,CO!E59,FE!E59,PE!E59) -> 0 | F59: =SUM(FO!F59,PO!F59,CO!F59,FE!F59,PE!F59) -> 119.9 | G59: =SUM(FO!G59,PO!G59,CO!G59,FE!G59,PE!G59) -> 0 | H59: =SUM(FO!H59,PO!H59,CO!H59,FE!H59,PE!H59) -> 1921.29 | I59: =SUM(FO!I59,PO!I59,CO!I59,FE!I59,PE!I59) -> 0 | ... M59: =SUM(FO!M59,PO!M59,CO!M59,FE!M59,PE!M59) -> 40 | N59: =SUM(B59:M59) -> 2266.19 | O59: =IFERROR(N59/N$16,"") -> 0.00030525437 | U59: =SUM(FO!U59,PO!U59,CO!U59,FE!U59,PE!U59) -> 41.666667 | V59: =SUM(FO!V59,PO!V59,CO!V59,FE!V59,PE!V59) -> 41.666667 | W59: =SUM(FO!W59,PO!W59,CO!W59,FE!W59,PE!W59) -> 41.666667 | X59: =SUM(FO!X59,PO!X59,CO!X59,FE!X59,PE!X59) -> 41.666667 | Y59: =SUM(FO!Y59,PO!Y59,CO!Y59,FE!Y59,PE!Y59) -> 41.666667 | Z59: =SUM(FO!Z59,PO!Z59,CO!Z59,FE!Z59,PE!Z59) -> 41.666667 | AA59: =SUM(FO!AA59,PO!AA59,CO!AA59,FE!AA59,PE!AA59) -> 41.666667 | AB59: =SUM(FO!AB59,PO!AB59,CO!AB59,FE!AB59,PE!AB59) -> 41.666667 | ... AF59: =SUM(FO!AF59,PO!AF59,CO!AF59,FE!AF59,PE!AF59) -> 41.666667 | AG59: =SUM(U59:AF59) -> 500 | AH59: =IFERROR(AG59/AG$16,"") -> 3.2126149e-05 | AJ59: =N59-AG59 -> 1766.19
A60: 5980 - Employee Meals | B60: =SUM(FO!B60,PO!B60,CO!B60,FE!B60,PE!B60) -> 281.96 | C60: =SUM(FO!C60,PO!C60,CO!C60,FE!C60,PE!C60) -> 47.22 | D60: =SUM(FO!D60,PO!D60,CO!D60,FE!D60,PE!D60) -> 0 | E60: =SUM(FO!E60,PO!E60,CO!E60,FE!E60,PE!E60) -> 0 | F60: =SUM(FO!F60,PO!F60,CO!F60,FE!F60,PE!F60) -> 0 | G60: =SUM(FO!G60,PO!G60,CO!G60,FE!G60,PE!G60) -> 0 | H60: =SUM(FO!H60,PO!H60,CO!H60,FE!H60,PE!H60) -> 20.7 | I60: =SUM(FO!I60,PO!I60,CO!I60,FE!I60,PE!I60) -> 321.5 | ... M60: =SUM(FO!M60,PO!M60,CO!M60,FE!M60,PE!M60) -> 0 | N60: =SUM(B60:M60) -> 671.38 | O60: =IFERROR(N60/N$16,"") -> 9.0434465e-05 | U60: =SUM(FO!U60,PO!U60,CO!U60,FE!U60,PE!U60) -> 0 | V60: =SUM(FO!V60,PO!V60,CO!V60,FE!V60,PE!V60) -> 0 | W60: =SUM(FO!W60,PO!W60,CO!W60,FE!W60,PE!W60) -> 0 | X60: =SUM(FO!X60,PO!X60,CO!X60,FE!X60,PE!X60) -> 0 | Y60: =SUM(FO!Y60,PO!Y60,CO!Y60,FE!Y60,PE!Y60) -> 0 | Z60: =SUM(FO!Z60,PO!Z60,CO!Z60,FE!Z60,PE!Z60) -> 0 | AA60: =SUM(FO!AA60,PO!AA60,CO!AA60,FE!AA60,PE!AA60) -> 0 | AB60: =SUM(FO!AB60,PO!AB60,CO!AB60,FE!AB60,PE!AB60) -> 0 | ... AF60: =SUM(FO!AF60,PO!AF60,CO!AF60,FE!AF60,PE!AF60) -> 0 | AG60: =SUM(U60:AF60) -> 0 | AH60: =IFERROR(AG60/AG$16,"") -> 0 | AJ60: =N60-AG60 -> 671.38
A61: Total - 5900 - Other COGS | B61: =SUM(B58:B60) -> 12322.81 | C61: =SUM(C58:C60) -> 11203.39 | D61: =SUM(D58:D60) -> 11961.24 | E61: =SUM(E58:E60) -> 7090.45 | F61: =SUM(F58:F60) -> 12454.78 | G61: =SUM(G58:G60) -> 13958.17 | H61: =SUM(H58:H60) -> 19387.87 | I61: =SUM(I58:I60) -> 14095.46 | ... M61: =SUM(M58:M60) -> 5248 | N61: =SUM(B61:M61) -> 123466.17 | O61: =IFERROR(N61/N$16,"") -> 0.016630816 | U61: =SUM(U58:U60) -> 41.666667 | V61: =SUM(V58:V60) -> 41.666667 | W61: =SUM(W58:W60) -> 41.666667 | X61: =SUM(X58:X60) -> 41.666667 | Y61: =SUM(Y58:Y60) -> 41.666667 | Z61: =SUM(Z58:Z60) -> 41.666667 | AA61: =SUM(AA58:AA60) -> 41.666667 | AB61: =SUM(AB58:AB60) -> 41.666667 | ... AF61: =SUM(AF58:AF60) -> 41.666667 | AG61: =SUM(U61:AF61) -> 500 | AH61: =IFERROR(AG61/AG$16,"") -> 3.2126149e-05 | AJ61: =N61-AG61 -> 122966.17
A62: 5990 - Purchase Discounts | B62: =SUM(FO!B62,PO!B62,CO!B62,FE!B62,PE!B62) -> 0 | C62: =SUM(FO!C62,PO!C62,CO!C62,FE!C62,PE!C62) -> 0 | D62: =SUM(FO!D62,PO!D62,CO!D62,FE!D62,PE!D62) -> 0 | E62: =SUM(FO!E62,PO!E62,CO!E62,FE!E62,PE!E62) -> 0 | F62: =SUM(FO!F62,PO!F62,CO!F62,FE!F62,PE!F62) -> 0 | G62: =SUM(FO!G62,PO!G62,CO!G62,FE!G62,PE!G62) -> 0 | H62: =SUM(FO!H62,PO!H62,CO!H62,FE!H62,PE!H62) -> -410.41 | I62: =SUM(FO!I62,PO!I62,CO!I62,FE!I62,PE!I62) -> 0 | ... M62: =SUM(FO!M62,PO!M62,CO!M62,FE!M62,PE!M62) -> 0 | N62: =SUM(B62:M62) -> -410.41 | O62: =IFERROR(N62/N$16,"") -> -5.528197e-05 | U62: =SUM(FO!U62,PO!U62,CO!U62,FE!U62,PE!U62) -> 0 | V62: =SUM(FO!V62,PO!V62,CO!V62,FE!V62,PE!V62) -> 0 | W62: =SUM(FO!W62,PO!W62,CO!W62,FE!W62,PE!W62) -> 0 | X62: =SUM(FO!X62,PO!X62,CO!X62,FE!X62,PE!X62) -> 0 | Y62: =SUM(FO!Y62,PO!Y62,CO!Y62,FE!Y62,PE!Y62) -> 0 | Z62: =SUM(FO!Z62,PO!Z62,CO!Z62,FE!Z62,PE!Z62) -> 0 | AA62: =SUM(FO!AA62,PO!AA62,CO!AA62,FE!AA62,PE!AA62) -> 0 | AB62: =SUM(FO!AB62,PO!AB62,CO!AB62,FE!AB62,PE!AB62) -> 0 | ... AF62: =SUM(FO!AF62,PO!AF62,CO!AF62,FE!AF62,PE!AF62) -> 0 | AG62: =SUM(U62:AF62) -> 0 | AH62: =IFERROR(AG62/AG$16,"") -> 0 | AJ62: =N62-AG62 -> -410.41
A63: Total - Cost Of Sales | B63: =B37+B38+B39+B40+B41+B42+B56+B61+B62 -> 268558.97 | C63: =C37+C38+C39+C40+C41+C42+C56+C61+C62 -> 280971.67 | D63: =D37+D38+D39+D40+D41+D42+D56+D61+D62 -> 345439.98 | E63: =E37+E38+E39+E40+E41+E42+E56+E61+E62 -> 344866.53 | F63: =F37+F38+F39+F40+F41+F42+F56+F61+F62 -> 384662.49 | G63: =G37+G38+G39+G40+G41+G42+G56+G61+G62 -> 357268.48 | H63: =H37+H38+H39+H40+H41+H42+H56+H61+H62 -> 344215.57 | I63: =I37+I38+I39+I40+I41+I42+I56+I61+I62 -> 458933.14 | ... M63: =M37+M38+M39+M40+M41+M42+M56+M61+M62 -> 429878.72 | N63: =SUM(B63:M63) -> 4478015.6 | O63: =IFERROR(N63/N$16,"") -> 0.60318589 | U63: =U37+U38+U39+U40+U41+U42+U56+U61+U62 -> #REF! | V63: =V37+V38+V39+V40+V41+V42+V56+V61+V62 -> #REF! | W63: =W37+W38+W39+W40+W41+W42+W56+W61+W62 -> #REF! | X63: =X37+X38+X39+X40+X41+X42+X56+X61+X62 -> #REF! | Y63: =Y37+Y38+Y39+Y40+Y41+Y42+Y56+Y61+Y62 -> #REF! | Z63: =Z37+Z38+Z39+Z40+Z41+Z42+Z56+Z61+Z62 -> #REF! | AA63: =AA37+AA38+AA39+AA40+AA41+AA42+AA56+AA61+AA62 -> #REF! | AB63: =AB37+AB38+AB39+AB40+AB41+AB42+AB56+AB61+AB62 -> #REF! | ... AF63: =AF37+AF38+AF39+AF40+AF41+AF42+AF56+AF61+AF62 -> #REF! | AG63: =SUM(U63:AF63) -> #REF! | AH63: =IFERROR(AG63/AG$16,"") | AJ63: =N63-AG63 -> #REF!
A64: Gross Profit | B64: =B16-B63 -> 274435.59 | C64: =C16-C63 -> 222255.39 | D64: =D16-D63 -> 201441.35 | E64: =E16-E63 -> 404837.45 | F64: =F16-F63 -> 135283.4 | G64: =G16-G63 -> 122474.52 | H64: =H16-H63 -> 296993.26 | I64: =I16-I63 -> 12372.42 | ... M64: =M16-M63 -> 367561.95 | N64: =SUM(B64:M64) -> 2945923.9 | O64: =IFERROR(N64/N$16,"") -> 0.39681411 | U64: =U16-U63 -> #REF! | V64: =V16-V63 -> #REF! | W64: =W16-W63 -> #REF! | X64: =X16-X63 -> #REF! | Y64: =Y16-Y63 -> #REF! | Z64: =Z16-Z63 -> #REF! | AA64: =AA16-AA63 -> #REF! | AB64: =AB16-AB63 -> #REF! | ... AF64: =AF16-AF63 -> #REF! | AG64: =SUM(U64:AF64) -> #REF! | AH64: =IFERROR(AG64/AG$16,"") | AJ64: =AG64-N64 -> #REF!
A65: Expense | B65: =IFERROR(B64/B16,"") -> 0.50541131 | C65: =IFERROR(C64/C16,"") -> 0.44166025 | D65: =IFERROR(D64/D16,"") -> 0.36834563 | E65: =IFERROR(E64/E16,"") -> 0.5399964 | F65: =IFERROR(F64/F16,"") -> 0.26018746 | G65: =IFERROR(G64/G16,"") -> 0.25529194 | H65: =IFERROR(H64/H16,"") -> 0.46317712 | I65: =IFERROR(I64/I16,"") -> 0.026251377 | ... N65: =IFERROR(N64/N16,"") -> 0.39681411 | U65: =IFERROR(U64/U16,"") | V65: =IFERROR(V64/V16,"") | W65: =IFERROR(W64/W16,"") | X65: =IFERROR(X64/X16,"") | Y65: =IFERROR(Y64/Y16,"") | Z65: =IFERROR(Z64/Z16,"") | AA65: =IFERROR(AA64/AA16,"") | AB65: =IFERROR(AB64/AB16,"") | ... AG65: =IFERROR(AG64/AG16,"")
A66: 6000 - Labor Expense - SG&A
A67: 6610 - Salaries and Wages - SG&A | B67: =SUM(FO!B67,PO!B67,CO!B67,FE!B67,PE!B67) -> 54176.66 | C67: =SUM(FO!C67,PO!C67,CO!C67,FE!C67,PE!C67) -> -73775.58 | D67: =SUM(FO!D67,PO!D67,CO!D67,FE!D67,PE!D67) -> 140925.68 | E67: =SUM(FO!E67,PO!E67,CO!E67,FE!E67,PE!E67) -> 134198.53 | F67: =SUM(FO!F67,PO!F67,CO!F67,FE!F67,PE!F67) -> 203069.15 | G67: =SUM(FO!G67,PO!G67,CO!G67,FE!G67,PE!G67) -> 190550.34 | H67: =SUM(FO!H67,PO!H67,CO!H67,FE!H67,PE!H67) -> 184829.3 | I67: =SUM(FO!I67,PO!I67,CO!I67,FE!I67,PE!I67) -> 197514.57 | ... M67: =SUM(FO!M67,PO!M67,CO!M67,FE!M67,PE!M67) -> 299600 | N67: =SUM(B67:M67) -> 2174388.7 | O67: =IFERROR(N67/N$16,"") -> 0.29288879 | U67: =SUM(FO!U67,PO!U67,CO!U67,FE!U67,PE!U67) -> 246828.67 | V67: =SUM(FO!V67,PO!V67,CO!V67,FE!V67,PE!V67) -> 251828.67 | W67: =SUM(FO!W67,PO!W67,CO!W67,FE!W67,PE!W67) -> 255988.67 | X67: =SUM(FO!X67,PO!X67,CO!X67,FE!X67,PE!X67) -> 254988.67 | Y67: =SUM(FO!Y67,PO!Y67,CO!Y67,FE!Y67,PE!Y67) -> 254988.67 | Z67: =SUM(FO!Z67,PO!Z67,CO!Z67,FE!Z67,PE!Z67) -> 260148.67 | AA67: =SUM(FO!AA67,PO!AA67,CO!AA67,FE!AA67,PE!AA67) -> 269642 | AB67: =SUM(FO!AB67,PO!AB67,CO!AB67,FE!AB67,PE!AB67) -> 273058.67 | ... AF67: =SUM(FO!AF67,PO!AF67,CO!AF67,FE!AF67,PE!AF67) -> 280870.83 | AG67: =SUM(U67:AF67) -> 3183143.8 | AH67: =IFERROR(AG67/AG$16,"") -> 0.20452431 | AJ67: =N67-AG67 -> -1008755.2
A68: 6630 - Payroll Taxes - SG&A | B68: =SUM(FO!B68,PO!B68,CO!B68,FE!B68,PE!B68) -> 14246.86 | C68: =SUM(FO!C68,PO!C68,CO!C68,FE!C68,PE!C68) -> 38431.92 | D68: =SUM(FO!D68,PO!D68,CO!D68,FE!D68,PE!D68) -> 6290.03 | E68: =SUM(FO!E68,PO!E68,CO!E68,FE!E68,PE!E68) -> 5633.46 | F68: =SUM(FO!F68,PO!F68,CO!F68,FE!F68,PE!F68) -> 7753.08 | G68: =SUM(FO!G68,PO!G68,CO!G68,FE!G68,PE!G68) -> 7265.23 | H68: =SUM(FO!H68,PO!H68,CO!H68,FE!H68,PE!H68) -> 7181.3 | I68: =SUM(FO!I68,PO!I68,CO!I68,FE!I68,PE!I68) -> 10596.09 | ... M68: =SUM(FO!M68,PO!M68,CO!M68,FE!M68,PE!M68) -> 11444 | N68: =SUM(B68:M68) -> 141078.97 | O68: =IFERROR(N68/N$16,"") -> 0.019003249 | U68: =SUM(FO!U68,PO!U68,CO!U68,FE!U68,PE!U68) -> 12781.614 | V68: =SUM(FO!V68,PO!V68,CO!V68,FE!V68,PE!V68) -> 13053.614 | W68: =SUM(FO!W68,PO!W68,CO!W68,FE!W68,PE!W68) -> 13336.494 | X68: =SUM(FO!X68,PO!X68,CO!X68,FE!X68,PE!X68) -> 13336.494 | Y68: =SUM(FO!Y68,PO!Y68,CO!Y68,FE!Y68,PE!Y68) -> 13336.494 | Z68: =SUM(FO!Z68,PO!Z68,CO!Z68,FE!Z68,PE!Z68) -> 13619.374 | AA68: =SUM(FO!AA68,PO!AA68,CO!AA68,FE!AA68,PE!AA68) -> 14196.92 | AB68: =SUM(FO!AB68,PO!AB68,CO!AB68,FE!AB68,PE!AB68) -> 14565.254 | ... AF68: =SUM(FO!AF68,PO!AF68,CO!AF68,FE!AF68,PE!AF68) -> 14976.398 | AG68: =SUM(U68:AF68) -> 167720.7 | AH68: =IFERROR(AG68/AG$16,"") -> 0.010776441 | AJ68: =N68-AG68 -> -26641.734
A69: 6640 - Benefits - SG&A | B69: =SUM(FO!B69,PO!B69,CO!B69,FE!B69,PE!B69) -> 56302.42 | C69: =SUM(FO!C69,PO!C69,CO!C69,FE!C69,PE!C69) -> 25595.52 | D69: =SUM(FO!D69,PO!D69,CO!D69,FE!D69,PE!D69) -> 20283.02 | E69: =SUM(FO!E69,PO!E69,CO!E69,FE!E69,PE!E69) -> 21911.8 | F69: =SUM(FO!F69,PO!F69,CO!F69,FE!F69,PE!F69) -> 14943.43 | G69: =SUM(FO!G69,PO!G69,CO!G69,FE!G69,PE!G69) -> 18184.32 | H69: =SUM(FO!H69,PO!H69,CO!H69,FE!H69,PE!H69) -> 12933.23 | I69: =SUM(FO!I69,PO!I69,CO!I69,FE!I69,PE!I69) -> 20943.04 | ... M69: =SUM(FO!M69,PO!M69,CO!M69,FE!M69,PE!M69) -> 27124 | N69: =SUM(B69:M69) -> 294743.78 | O69: =IFERROR(N69/N$16,"") -> 0.039701802 | U69: =SUM(FO!U69,PO!U69,CO!U69,FE!U69,PE!U69) -> 30523.973 | V69: =SUM(FO!V69,PO!V69,CO!V69,FE!V69,PE!V69) -> 31179.973 | W69: =SUM(FO!W69,PO!W69,CO!W69,FE!W69,PE!W69) -> 31862.213 | X69: =SUM(FO!X69,PO!X69,CO!X69,FE!X69,PE!X69) -> 31862.213 | Y69: =SUM(FO!Y69,PO!Y69,CO!Y69,FE!Y69,PE!Y69) -> 31862.213 | Z69: =SUM(FO!Z69,PO!Z69,CO!Z69,FE!Z69,PE!Z69) -> 32544.453 | AA69: =SUM(FO!AA69,PO!AA69,CO!AA69,FE!AA69,PE!AA69) -> 33937.36 | AB69: =SUM(FO!AB69,PO!AB69,CO!AB69,FE!AB69,PE!AB69) -> 34825.693 | ... AF69: =SUM(FO!AF69,PO!AF69,CO!AF69,FE!AF69,PE!AF69) -> 35808.21 | AG69: =SUM(U69:AF69) -> 400848.41 | AH69: =IFERROR(AG69/AG$16,"") -> 0.025755432 | AJ69: =N69-AG69 -> -106104.63
A70: 6650 - Commissions - SG&A | B70: =SUM(FO!B70,PO!B70,CO!B70,FE!B70,PE!B70) -> 0 | C70: =SUM(FO!C70,PO!C70,CO!C70,FE!C70,PE!C70) -> 0 | D70: =SUM(FO!D70,PO!D70,CO!D70,FE!D70,PE!D70) -> 0 | E70: =SUM(FO!E70,PO!E70,CO!E70,FE!E70,PE!E70) -> 0 | F70: =SUM(FO!F70,PO!F70,CO!F70,FE!F70,PE!F70) -> 0 | G70: =SUM(FO!G70,PO!G70,CO!G70,FE!G70,PE!G70) -> 0 | H70: =SUM(FO!H70,PO!H70,CO!H70,FE!H70,PE!H70) -> 0 | I70: =SUM(FO!I70,PO!I70,CO!I70,FE!I70,PE!I70) -> 0 | ... M70: =SUM(FO!M70,PO!M70,CO!M70,FE!M70,PE!M70) -> 0 | N70: =SUM(B70:M70) -> 0 | O70: =IFERROR(N70/N$16,"") -> 0 | U70: =SUM(FO!U70,PO!U70,CO!U70,FE!U70,PE!U70) -> 0 | V70: =SUM(FO!V70,PO!V70,CO!V70,FE!V70,PE!V70) -> 0 | W70: =SUM(FO!W70,PO!W70,CO!W70,FE!W70,PE!W70) -> 0 | X70: =SUM(FO!X70,PO!X70,CO!X70,FE!X70,PE!X70) -> 0 | Y70: =SUM(FO!Y70,PO!Y70,CO!Y70,FE!Y70,PE!Y70) -> 0 | Z70: =SUM(FO!Z70,PO!Z70,CO!Z70,FE!Z70,PE!Z70) -> 0 | AA70: =SUM(FO!AA70,PO!AA70,CO!AA70,FE!AA70,PE!AA70) -> 0 | AB70: =SUM(FO!AB70,PO!AB70,CO!AB70,FE!AB70,PE!AB70) -> 0 | ... AF70: =SUM(FO!AF70,PO!AF70,CO!AF70,FE!AF70,PE!AF70) -> 0 | AG70: =SUM(U70:AF70) -> 0 | AH70: =IFERROR(AG70/AG$16,"") -> 0 | AJ70: =N70-AG70 -> 0
A71: 6660 - Recruiting | B71: =SUM(FO!B71,PO!B71,CO!B71,FE!B71,PE!B71) -> 0 | C71: =SUM(FO!C71,PO!C71,CO!C71,FE!C71,PE!C71) -> 0 | D71: =SUM(FO!D71,PO!D71,CO!D71,FE!D71,PE!D71) -> 0 | E71: =SUM(FO!E71,PO!E71,CO!E71,FE!E71,PE!E71) -> 0 | F71: =SUM(FO!F71,PO!F71,CO!F71,FE!F71,PE!F71) -> 0 | G71: =SUM(FO!G71,PO!G71,CO!G71,FE!G71,PE!G71) -> 0 | H71: =SUM(FO!H71,PO!H71,CO!H71,FE!H71,PE!H71) -> 0 | I71: =SUM(FO!I71,PO!I71,CO!I71,FE!I71,PE!I71) -> 0 | ... M71: =SUM(FO!M71,PO!M71,CO!M71,FE!M71,PE!M71) -> 0 | N71: =SUM(B71:M71) -> 0 | O71: =IFERROR(N71/N$16,"") -> 0 | U71: =SUM(FO!U71,PO!U71,CO!U71,FE!U71,PE!U71) -> 0 | V71: =SUM(FO!V71,PO!V71,CO!V71,FE!V71,PE!V71) -> 0 | W71: =SUM(FO!W71,PO!W71,CO!W71,FE!W71,PE!W71) -> 0 | X71: =SUM(FO!X71,PO!X71,CO!X71,FE!X71,PE!X71) -> 0 | Y71: =SUM(FO!Y71,PO!Y71,CO!Y71,FE!Y71,PE!Y71) -> 0 | Z71: =SUM(FO!Z71,PO!Z71,CO!Z71,FE!Z71,PE!Z71) -> 0 | AA71: =SUM(FO!AA71,PO!AA71,CO!AA71,FE!AA71,PE!AA71) -> 0 | AB71: =SUM(FO!AB71,PO!AB71,CO!AB71,FE!AB71,PE!AB71) -> 0 | ... AF71: =SUM(FO!AF71,PO!AF71,CO!AF71,FE!AF71,PE!AF71) -> 0 | AG71: =SUM(U71:AF71) -> 0 | AH71: =IFERROR(AG71/AG$16,"") -> 0 | AJ71: =N71-AG71 -> 0
A72: 6670 - Stock Compensation Expense | B72: =SUM(FO!B72,PO!B72,CO!B72,FE!B72,PE!B72) -> 0 | C72: =SUM(FO!C72,PO!C72,CO!C72,FE!C72,PE!C72) -> 0 | D72: =SUM(FO!D72,PO!D72,CO!D72,FE!D72,PE!D72) -> 0 | E72: =SUM(FO!E72,PO!E72,CO!E72,FE!E72,PE!E72) -> 0 | F72: =SUM(FO!F72,PO!F72,CO!F72,FE!F72,PE!F72) -> 0 | G72: =SUM(FO!G72,PO!G72,CO!G72,FE!G72,PE!G72) -> 0 | H72: =SUM(FO!H72,PO!H72,CO!H72,FE!H72,PE!H72) -> 0 | I72: =SUM(FO!I72,PO!I72,CO!I72,FE!I72,PE!I72) -> 0 | ... M72: =SUM(FO!M72,PO!M72,CO!M72,FE!M72,PE!M72) -> 0 | N72: =SUM(B72:M72) -> 0 | O72: =IFERROR(N72/N$16,"") -> 0 | U72: =SUM(FO!U72,PO!U72,CO!U72,FE!U72,PE!U72) -> 0 | V72: =SUM(FO!V72,PO!V72,CO!V72,FE!V72,PE!V72) -> 0 | W72: =SUM(FO!W72,PO!W72,CO!W72,FE!W72,PE!W72) -> 0 | X72: =SUM(FO!X72,PO!X72,CO!X72,FE!X72,PE!X72) -> 0 | Y72: =SUM(FO!Y72,PO!Y72,CO!Y72,FE!Y72,PE!Y72) -> 0 | Z72: =SUM(FO!Z72,PO!Z72,CO!Z72,FE!Z72,PE!Z72) -> 0 | AA72: =SUM(FO!AA72,PO!AA72,CO!AA72,FE!AA72,PE!AA72) -> 0 | AB72: =SUM(FO!AB72,PO!AB72,CO!AB72,FE!AB72,PE!AB72) -> 0 | ... AF72: =SUM(FO!AF72,PO!AF72,CO!AF72,FE!AF72,PE!AF72) -> 0 | AG72: =SUM(U72:AF72) -> 0 | AH72: =IFERROR(AG72/AG$16,"") -> 0 | AJ72: =N72-AG72 -> 0
A73: Total - 6000 - Labor Expense - SG&A | B73: =SUM(B67:B72) -> 124725.94 | C73: =SUM(C67:C72) -> -9748.14 | D73: =SUM(D67:D72) -> 167498.73 | E73: =SUM(E67:E72) -> 161743.79 | F73: =SUM(F67:F72) -> 225765.66 | G73: =SUM(G67:G72) -> 215999.89 | H73: =SUM(H67:H72) -> 204943.83 | I73: =SUM(I67:I72) -> 229053.7 | ... M73: =SUM(M67:M72) -> 338168 | N73: =SUM(B73:M73) -> 2610211.4 | O73: =IFERROR(N73/N$16,"") -> 0.35159384 | U73: =SUM(U67:U72) -> 290134.25 | V73: =SUM(V67:V72) -> 296062.25 | W73: =SUM(W67:W72) -> 301187.37 | X73: =SUM(X67:X72) -> 300187.37 | Y73: =SUM(Y67:Y72) -> 300187.37 | Z73: =SUM(Z67:Z72) -> 306312.49 | AA73: =SUM(AA67:AA72) -> 317776.28 | AB73: =SUM(AB67:AB72) -> 322449.61 | ... AF73: =SUM(AF67:AF72) -> 331655.43 | AG73: =SUM(U73:AF73) -> 3751712.9 | AH73: =IFERROR(AG73/AG$16,"") -> 0.24105618 | AJ73: =N73-AG73 -> -1141501.5
A74: 6100 - Travel | B74: =SUM(FO!B74,PO!B74,CO!B74,FE!B74,PE!B74) -> 1875.49 | C74: =SUM(FO!C74,PO!C74,CO!C74,FE!C74,PE!C74) -> 1791.21 | D74: =SUM(FO!D74,PO!D74,CO!D74,FE!D74,PE!D74) -> 2123.14 | E74: =SUM(FO!E74,PO!E74,CO!E74,FE!E74,PE!E74) -> 9767.2 | F74: =SUM(FO!F74,PO!F74,CO!F74,FE!F74,PE!F74) -> 6562.35 | G74: =SUM(FO!G74,PO!G74,CO!G74,FE!G74,PE!G74) -> 12287.21 | H74: =SUM(FO!H74,PO!H74,CO!H74,FE!H74,PE!H74) -> 9428.97 | I74: =SUM(FO!I74,PO!I74,CO!I74,FE!I74,PE!I74) -> 3944 | ... M74: =SUM(FO!M74,PO!M74,CO!M74,FE!M74,PE!M74) -> 7500 | N74: =SUM(B74:M74) -> 77779.57 | O74: =IFERROR(N74/N$16,"") -> 0.010476859 | U74: =SUM(FO!U74,PO!U74,CO!U74,FE!U74,PE!U74) -> 4269.5938 | V74: =SUM(FO!V74,PO!V74,CO!V74,FE!V74,PE!V74) -> 4269.5938 | W74: =SUM(FO!W74,PO!W74,CO!W74,FE!W74,PE!W74) -> 5269.5938 | X74: =SUM(FO!X74,PO!X74,CO!X74,FE!X74,PE!X74) -> 5269.5938 | Y74: =SUM(FO!Y74,PO!Y74,CO!Y74,FE!Y74,PE!Y74) -> 5769.5938 | Z74: =SUM(FO!Z74,PO!Z74,CO!Z74,FE!Z74,PE!Z74) -> 5769.5938 | AA74: =SUM(FO!AA74,PO!AA74,CO!AA74,FE!AA74,PE!AA74) -> 6269.5938 | AB74: =SUM(FO!AB74,PO!AB74,CO!AB74,FE!AB74,PE!AB74) -> 6269.5938 | ... AF74: =SUM(FO!AF74,PO!AF74,CO!AF74,FE!AF74,PE!AF74) -> 7769.5938 | AG74: =SUM(U74:AF74) -> 71735.125 | AH74: =IFERROR(AG74/AG$16,"") -> 0.0046091467 | AJ74: =N74-AG74 -> 6044.445
A75: 6110 - Travel Meals | B75: =SUM(FO!B75,PO!B75,CO!B75,FE!B75,PE!B75) -> 399.67 | C75: =SUM(FO!C75,PO!C75,CO!C75,FE!C75,PE!C75) -> 218.65 | D75: =SUM(FO!D75,PO!D75,CO!D75,FE!D75,PE!D75) -> 0 | E75: =SUM(FO!E75,PO!E75,CO!E75,FE!E75,PE!E75) -> 3145.44 | F75: =SUM(FO!F75,PO!F75,CO!F75,FE!F75,PE!F75) -> 0 | G75: =SUM(FO!G75,PO!G75,CO!G75,FE!G75,PE!G75) -> 327.78 | H75: =SUM(FO!H75,PO!H75,CO!H75,FE!H75,PE!H75) -> 234.79 | I75: =SUM(FO!I75,PO!I75,CO!I75,FE!I75,PE!I75) -> 310.75 | ... M75: =SUM(FO!M75,PO!M75,CO!M75,FE!M75,PE!M75) -> 850 | N75: =SUM(B75:M75) -> 8037.08 | O75: =IFERROR(N75/N$16,"") -> 0.0010825896 | U75: =SUM(FO!U75,PO!U75,CO!U75,FE!U75,PE!U75) -> 604.61406 | V75: =SUM(FO!V75,PO!V75,CO!V75,FE!V75,PE!V75) -> 604.61406 | W75: =SUM(FO!W75,PO!W75,CO!W75,FE!W75,PE!W75) -> 604.61406 | X75: =SUM(FO!X75,PO!X75,CO!X75,FE!X75,PE!X75) -> 604.61406 | Y75: =SUM(FO!Y75,PO!Y75,CO!Y75,FE!Y75,PE!Y75) -> 604.61406 | Z75: =SUM(FO!Z75,PO!Z75,CO!Z75,FE!Z75,PE!Z75) -> 604.61406 | AA75: =SUM(FO!AA75,PO!AA75,CO!AA75,FE!AA75,PE!AA75) -> 604.61406 | AB75: =SUM(FO!AB75,PO!AB75,CO!AB75,FE!AB75,PE!AB75) -> 604.61406 | ... AF75: =SUM(FO!AF75,PO!AF75,CO!AF75,FE!AF75,PE!AF75) -> 604.61406 | AG75: =SUM(U75:AF75) -> 7255.3687 | AH75: =IFERROR(AG75/AG$16,"") -> 0.00046617412 | AJ75: =N75-AG75 -> 781.71125
A76: 6120 - Meals and Entertainment | B76: =SUM(FO!B76,PO!B76,CO!B76,FE!B76,PE!B76) -> 410.24 | C76: =SUM(FO!C76,PO!C76,CO!C76,FE!C76,PE!C76) -> 0 | D76: =SUM(FO!D76,PO!D76,CO!D76,FE!D76,PE!D76) -> 356.53 | E76: =SUM(FO!E76,PO!E76,CO!E76,FE!E76,PE!E76) -> 683.77 | F76: =SUM(FO!F76,PO!F76,CO!F76,FE!F76,PE!F76) -> 55.11 | G76: =SUM(FO!G76,PO!G76,CO!G76,FE!G76,PE!G76) -> 0 | H76: =SUM(FO!H76,PO!H76,CO!H76,FE!H76,PE!H76) -> 0 | I76: =SUM(FO!I76,PO!I76,CO!I76,FE!I76,PE!I76) -> 119.7 | ... M76: =SUM(FO!M76,PO!M76,CO!M76,FE!M76,PE!M76) -> 300 | N76: =SUM(B76:M76) -> 2825.35 | O76: =IFERROR(N76/N$16,"") -> 0.00038057287 | U76: =SUM(FO!U76,PO!U76,CO!U76,FE!U76,PE!U76) -> 100 | V76: =SUM(FO!V76,PO!V76,CO!V76,FE!V76,PE!V76) -> 100 | W76: =SUM(FO!W76,PO!W76,CO!W76,FE!W76,PE!W76) -> 300 | X76: =SUM(FO!X76,PO!X76,CO!X76,FE!X76,PE!X76) -> 300 | Y76: =SUM(FO!Y76,PO!Y76,CO!Y76,FE!Y76,PE!Y76) -> 400 | Z76: =SUM(FO!Z76,PO!Z76,CO!Z76,FE!Z76,PE!Z76) -> 400 | AA76: =SUM(FO!AA76,PO!AA76,CO!AA76,FE!AA76,PE!AA76) -> 500 | AB76: =SUM(FO!AB76,PO!AB76,CO!AB76,FE!AB76,PE!AB76) -> 500 | ... AF76: =SUM(FO!AF76,PO!AF76,CO!AF76,FE!AF76,PE!AF76) -> 800 | AG76: =SUM(U76:AF76) -> 5300 | AH76: =IFERROR(AG76/AG$16,"") -> 0.00034053718 | AJ76: =N76-AG76 -> -2474.65
A77: 6200 - Advertising | B77: =SUM(FO!B77,PO!B77,CO!B77,FE!B77,PE!B77) -> 0 | C77: =SUM(FO!C77,PO!C77,CO!C77,FE!C77,PE!C77) -> 0 | D77: =SUM(FO!D77,PO!D77,CO!D77,FE!D77,PE!D77) -> 0 | E77: =SUM(FO!E77,PO!E77,CO!E77,FE!E77,PE!E77) -> 0 | F77: =SUM(FO!F77,PO!F77,CO!F77,FE!F77,PE!F77) -> 0 | G77: =SUM(FO!G77,PO!G77,CO!G77,FE!G77,PE!G77) -> 0 | H77: =SUM(FO!H77,PO!H77,CO!H77,FE!H77,PE!H77) -> 0 | I77: =SUM(FO!I77,PO!I77,CO!I77,FE!I77,PE!I77) -> 0 | ... M77: =SUM(FO!M77,PO!M77,CO!M77,FE!M77,PE!M77) -> 0 | N77: =SUM(B77:M77) -> 0 | O77: =IFERROR(N77/N$16,"") -> 0 | U77: =SUM(FO!U77,PO!U77,CO!U77,FE!U77,PE!U77) -> 0 | V77: =SUM(FO!V77,PO!V77,CO!V77,FE!V77,PE!V77) -> 0 | W77: =SUM(FO!W77,PO!W77,CO!W77,FE!W77,PE!W77) -> 0 | X77: =SUM(FO!X77,PO!X77,CO!X77,FE!X77,PE!X77) -> 0 | Y77: =SUM(FO!Y77,PO!Y77,CO!Y77,FE!Y77,PE!Y77) -> 0 | Z77: =SUM(FO!Z77,PO!Z77,CO!Z77,FE!Z77,PE!Z77) -> 0 | AA77: =SUM(FO!AA77,PO!AA77,CO!AA77,FE!AA77,PE!AA77) -> 0 | AB77: =SUM(FO!AB77,PO!AB77,CO!AB77,FE!AB77,PE!AB77) -> 0 | ... AF77: =SUM(FO!AF77,PO!AF77,CO!AF77,FE!AF77,PE!AF77) -> 0 | AG77: =SUM(U77:AF77) -> 0 | AH77: =IFERROR(AG77/AG$16,"") -> 0 | AJ77: =N77-AG77 -> 0
A78: 6210 - Marketing Expense | B78: =SUM(FO!B78,PO!B78,CO!B78,FE!B78,PE!B78) -> 0 | C78: =SUM(FO!C78,PO!C78,CO!C78,FE!C78,PE!C78) -> 0 | D78: =SUM(FO!D78,PO!D78,CO!D78,FE!D78,PE!D78) -> 0 | E78: =SUM(FO!E78,PO!E78,CO!E78,FE!E78,PE!E78) -> 0 | F78: =SUM(FO!F78,PO!F78,CO!F78,FE!F78,PE!F78) -> 0 | G78: =SUM(FO!G78,PO!G78,CO!G78,FE!G78,PE!G78) -> 0 | H78: =SUM(FO!H78,PO!H78,CO!H78,FE!H78,PE!H78) -> 0 | I78: =SUM(FO!I78,PO!I78,CO!I78,FE!I78,PE!I78) -> 0 | ... M78: =SUM(FO!M78,PO!M78,CO!M78,FE!M78,PE!M78) -> 300 | N78: =SUM(B78:M78) -> 1200 | O78: =IFERROR(N78/N$16,"") -> 0.00016163925 | U78: =SUM(FO!U78,PO!U78,CO!U78,FE!U78,PE!U78) -> 0 | V78: =SUM(FO!V78,PO!V78,CO!V78,FE!V78,PE!V78) -> 0 | W78: =SUM(FO!W78,PO!W78,CO!W78,FE!W78,PE!W78) -> 0 | X78: =SUM(FO!X78,PO!X78,CO!X78,FE!X78,PE!X78) -> 0 | Y78: =SUM(FO!Y78,PO!Y78,CO!Y78,FE!Y78,PE!Y78) -> 0 | Z78: =SUM(FO!Z78,PO!Z78,CO!Z78,FE!Z78,PE!Z78) -> 0 | AA78: =SUM(FO!AA78,PO!AA78,CO!AA78,FE!AA78,PE!AA78) -> 0 | AB78: =SUM(FO!AB78,PO!AB78,CO!AB78,FE!AB78,PE!AB78) -> 0 | ... AF78: =SUM(FO!AF78,PO!AF78,CO!AF78,FE!AF78,PE!AF78) -> 0 | AG78: =SUM(U78:AF78) -> 0 | AH78: =IFERROR(AG78/AG$16,"") -> 0 | AJ78: =N78-AG78 -> 1200
A79: 6220 - Trade Shows | B79: =SUM(FO!B79,PO!B79,CO!B79,FE!B79,PE!B79) -> 0 | C79: =SUM(FO!C79,PO!C79,CO!C79,FE!C79,PE!C79) -> 0 | D79: =SUM(FO!D79,PO!D79,CO!D79,FE!D79,PE!D79) -> 871.4 | E79: =SUM(FO!E79,PO!E79,CO!E79,FE!E79,PE!E79) -> 2711.33 | F79: =SUM(FO!F79,PO!F79,CO!F79,FE!F79,PE!F79) -> 0 | G79: =SUM(FO!G79,PO!G79,CO!G79,FE!G79,PE!G79) -> 2900 | H79: =SUM(FO!H79,PO!H79,CO!H79,FE!H79,PE!H79) -> 0 | I79: =SUM(FO!I79,PO!I79,CO!I79,FE!I79,PE!I79) -> 0 | ... M79: =SUM(FO!M79,PO!M79,CO!M79,FE!M79,PE!M79) -> 1000 | N79: =SUM(B79:M79) -> 12482.73 | O79: =IFERROR(N79/N$16,"") -> 0.0016814159 | U79: =SUM(FO!U79,PO!U79,CO!U79,FE!U79,PE!U79) -> 0 | V79: =SUM(FO!V79,PO!V79,CO!V79,FE!V79,PE!V79) -> 0 | W79: =SUM(FO!W79,PO!W79,CO!W79,FE!W79,PE!W79) -> 0 | X79: =SUM(FO!X79,PO!X79,CO!X79,FE!X79,PE!X79) -> 0 | Y79: =SUM(FO!Y79,PO!Y79,CO!Y79,FE!Y79,PE!Y79) -> 0 | Z79: =SUM(FO!Z79,PO!Z79,CO!Z79,FE!Z79,PE!Z79) -> 0 | AA79: =SUM(FO!AA79,PO!AA79,CO!AA79,FE!AA79,PE!AA79) -> 0 | AB79: =SUM(FO!AB79,PO!AB79,CO!AB79,FE!AB79,PE!AB79) -> 0 | ... AF79: =SUM(FO!AF79,PO!AF79,CO!AF79,FE!AF79,PE!AF79) -> 0 | AG79: =SUM(U79:AF79) -> 0 | AH79: =IFERROR(AG79/AG$16,"") -> 0 | AJ79: =N79-AG79 -> 12482.73
A80: 6400 - Memberships and Subscriptions | B80: =SUM(FO!B80,PO!B80,CO!B80,FE!B80,PE!B80) -> 70.88 | C80: =SUM(FO!C80,PO!C80,CO!C80,FE!C80,PE!C80) -> 205.88 | D80: =SUM(FO!D80,PO!D80,CO!D80,FE!D80,PE!D80) -> 355.89 | E80: =SUM(FO!E80,PO!E80,CO!E80,FE!E80,PE!E80) -> 255.89 | F80: =SUM(FO!F80,PO!F80,CO!F80,FE!F80,PE!F80) -> 34.99 | G80: =SUM(FO!G80,PO!G80,CO!G80,FE!G80,PE!G80) -> 0 | H80: =SUM(FO!H80,PO!H80,CO!H80,FE!H80,PE!H80) -> 0 | I80: =SUM(FO!I80,PO!I80,CO!I80,FE!I80,PE!I80) -> 0 | ... M80: =SUM(FO!M80,PO!M80,CO!M80,FE!M80,PE!M80) -> 210 | N80: =SUM(B80:M80) -> 1763.53 | O80: =IFERROR(N80/N$16,"") -> 0.00023754638 | U80: =SUM(FO!U80,PO!U80,CO!U80,FE!U80,PE!U80) -> 150 | V80: =SUM(FO!V80,PO!V80,CO!V80,FE!V80,PE!V80) -> 150 | W80: =SUM(FO!W80,PO!W80,CO!W80,FE!W80,PE!W80) -> 150 | X80: =SUM(FO!X80,PO!X80,CO!X80,FE!X80,PE!X80) -> 150 | Y80: =SUM(FO!Y80,PO!Y80,CO!Y80,FE!Y80,PE!Y80) -> 150 | Z80: =SUM(FO!Z80,PO!Z80,CO!Z80,FE!Z80,PE!Z80) -> 150 | AA80: =SUM(FO!AA80,PO!AA80,CO!AA80,FE!AA80,PE!AA80) -> 150 | AB80: =SUM(FO!AB80,PO!AB80,CO!AB80,FE!AB80,PE!AB80) -> 150 | ... AF80: =SUM(FO!AF80,PO!AF80,CO!AF80,FE!AF80,PE!AF80) -> 150 | AG80: =SUM(U80:AF80) -> 1800 | AH80: =IFERROR(AG80/AG$16,"") -> 0.00011565414 | AJ80: =N80-AG80 -> -36.47
A81: 6500 - Demos
A82: 6510 - Storage Facilities - Demos | B82: =SUM(FO!B82,PO!B82,CO!B82,FE!B82,PE!B82) -> 0 | C82: =SUM(FO!C82,PO!C82,CO!C82,FE!C82,PE!C82) -> 0 | D82: =SUM(FO!D82,PO!D82,CO!D82,FE!D82,PE!D82) -> 0 | E82: =SUM(FO!E82,PO!E82,CO!E82,FE!E82,PE!E82) -> 0 | F82: =SUM(FO!F82,PO!F82,CO!F82,FE!F82,PE!F82) -> 0 | G82: =SUM(FO!G82,PO!G82,CO!G82,FE!G82,PE!G82) -> 0 | H82: =SUM(FO!H82,PO!H82,CO!H82,FE!H82,PE!H82) -> 0 | I82: =SUM(FO!I82,PO!I82,CO!I82,FE!I82,PE!I82) -> 0 | ... M82: =SUM(FO!M82,PO!M82,CO!M82,FE!M82,PE!M82) -> 0 | N82: =SUM(B82:M82) -> 0 | O82: =IFERROR(N82/N$16,"") -> 0 | U82: =SUM(FO!U82,PO!U82,CO!U82,FE!U82,PE!U82) -> 0 | V82: =SUM(FO!V82,PO!V82,CO!V82,FE!V82,PE!V82) -> 0 | W82: =SUM(FO!W82,PO!W82,CO!W82,FE!W82,PE!W82) -> 0 | X82: =SUM(FO!X82,PO!X82,CO!X82,FE!X82,PE!X82) -> 0 | Y82: =SUM(FO!Y82,PO!Y82,CO!Y82,FE!Y82,PE!Y82) -> 0 | Z82: =SUM(FO!Z82,PO!Z82,CO!Z82,FE!Z82,PE!Z82) -> 0 | AA82: =SUM(FO!AA82,PO!AA82,CO!AA82,FE!AA82,PE!AA82) -> 0 | AB82: =SUM(FO!AB82,PO!AB82,CO!AB82,FE!AB82,PE!AB82) -> 0 | ... AF82: =SUM(FO!AF82,PO!AF82,CO!AF82,FE!AF82,PE!AF82) -> 0 | AG82: =SUM(U82:AF82) -> 0 | AH82: =IFERROR(AG82/AG$16,"") -> 0 | AJ82: =N82-AG82 -> 0
A83: 6520 - Truck Rental - Demos | B83: =SUM(FO!B83,PO!B83,CO!B83,FE!B83,PE!B83) -> 1716.81 | C83: =SUM(FO!C83,PO!C83,CO!C83,FE!C83,PE!C83) -> 1639.89 | D83: =SUM(FO!D83,PO!D83,CO!D83,FE!D83,PE!D83) -> 654.95 | E83: =SUM(FO!E83,PO!E83,CO!E83,FE!E83,PE!E83) -> 0 | F83: =SUM(FO!F83,PO!F83,CO!F83,FE!F83,PE!F83) -> 596.5 | G83: =SUM(FO!G83,PO!G83,CO!G83,FE!G83,PE!G83) -> 1755.52 | H83: =SUM(FO!H83,PO!H83,CO!H83,FE!H83,PE!H83) -> 728.5 | I83: =SUM(FO!I83,PO!I83,CO!I83,FE!I83,PE!I83) -> 0 | ... M83: =SUM(FO!M83,PO!M83,CO!M83,FE!M83,PE!M83) -> 1500 | N83: =SUM(B83:M83) -> 14592.17 | O83: =IFERROR(N83/N$16,"") -> 0.0019655561 | U83: =SUM(FO!U83,PO!U83,CO!U83,FE!U83,PE!U83) -> 0 | V83: =SUM(FO!V83,PO!V83,CO!V83,FE!V83,PE!V83) -> 0 | W83: =SUM(FO!W83,PO!W83,CO!W83,FE!W83,PE!W83) -> 0 | X83: =SUM(FO!X83,PO!X83,CO!X83,FE!X83,PE!X83) -> 0 | Y83: =SUM(FO!Y83,PO!Y83,CO!Y83,FE!Y83,PE!Y83) -> 0 | Z83: =SUM(FO!Z83,PO!Z83,CO!Z83,FE!Z83,PE!Z83) -> 0 | AA83: =SUM(FO!AA83,PO!AA83,CO!AA83,FE!AA83,PE!AA83) -> 0 | AB83: =SUM(FO!AB83,PO!AB83,CO!AB83,FE!AB83,PE!AB83) -> 0 | ... AF83: =SUM(FO!AF83,PO!AF83,CO!AF83,FE!AF83,PE!AF83) -> 0 | AG83: =SUM(U83:AF83) -> 0 | AH83: =IFERROR(AG83/AG$16,"") -> 0 | AJ83: =N83-AG83 -> 14592.17
A84: 6530 - Other Demo Expense | B84: =SUM(FO!B84,PO!B84,CO!B84,FE!B84,PE!B84) -> 153.63 | C84: =SUM(FO!C84,PO!C84,CO!C84,FE!C84,PE!C84) -> 1867.65 | D84: =SUM(FO!D84,PO!D84,CO!D84,FE!D84,PE!D84) -> 0 | E84: =SUM(FO!E84,PO!E84,CO!E84,FE!E84,PE!E84) -> 0 | F84: =SUM(FO!F84,PO!F84,CO!F84,FE!F84,PE!F84) -> 901.61 | G84: =SUM(FO!G84,PO!G84,CO!G84,FE!G84,PE!G84) -> 20 | H84: =SUM(FO!H84,PO!H84,CO!H84,FE!H84,PE!H84) -> 270.05 | I84: =SUM(FO!I84,PO!I84,CO!I84,FE!I84,PE!I84) -> 0 | ... M84: =SUM(FO!M84,PO!M84,CO!M84,FE!M84,PE!M84) -> 600 | N84: =SUM(B84:M84) -> 5612.94 | O84: =IFERROR(N84/N$16,"") -> 0.0007560595 | U84: =SUM(FO!U84,PO!U84,CO!U84,FE!U84,PE!U84) -> 0 | V84: =SUM(FO!V84,PO!V84,CO!V84,FE!V84,PE!V84) -> 0 | W84: =SUM(FO!W84,PO!W84,CO!W84,FE!W84,PE!W84) -> 0 | X84: =SUM(FO!X84,PO!X84,CO!X84,FE!X84,PE!X84) -> 0 | Y84: =SUM(FO!Y84,PO!Y84,CO!Y84,FE!Y84,PE!Y84) -> 0 | Z84: =SUM(FO!Z84,PO!Z84,CO!Z84,FE!Z84,PE!Z84) -> 0 | AA84: =SUM(FO!AA84,PO!AA84,CO!AA84,FE!AA84,PE!AA84) -> 0 | AB84: =SUM(FO!AB84,PO!AB84,CO!AB84,FE!AB84,PE!AB84) -> 0 | ... AF84: =SUM(FO!AF84,PO!AF84,CO!AF84,FE!AF84,PE!AF84) -> 0 | AG84: =SUM(U84:AF84) -> 0 | AH84: =IFERROR(AG84/AG$16,"") -> 0 | AJ84: =N84-AG84 -> 5612.94
A85: 6540 - Travel - Demos | B85: =SUM(FO!B85,PO!B85,CO!B85,FE!B85,PE!B85) -> 2186.21 | C85: =SUM(FO!C85,PO!C85,CO!C85,FE!C85,PE!C85) -> 3511.69 | D85: =SUM(FO!D85,PO!D85,CO!D85,FE!D85,PE!D85) -> 325.9 | E85: =SUM(FO!E85,PO!E85,CO!E85,FE!E85,PE!E85) -> 1638.14 | F85: =SUM(FO!F85,PO!F85,CO!F85,FE!F85,PE!F85) -> 1041.91 | G85: =SUM(FO!G85,PO!G85,CO!G85,FE!G85,PE!G85) -> 721.44 | H85: =SUM(FO!H85,PO!H85,CO!H85,FE!H85,PE!H85) -> 1816.86 | I85: =SUM(FO!I85,PO!I85,CO!I85,FE!I85,PE!I85) -> 0 | ... M85: =SUM(FO!M85,PO!M85,CO!M85,FE!M85,PE!M85) -> 1500 | N85: =SUM(B85:M85) -> 19742.15 | O85: =IFERROR(N85/N$16,"") -> 0.0026592552 | U85: =SUM(FO!U85,PO!U85,CO!U85,FE!U85,PE!U85) -> 0 | V85: =SUM(FO!V85,PO!V85,CO!V85,FE!V85,PE!V85) -> 0 | W85: =SUM(FO!W85,PO!W85,CO!W85,FE!W85,PE!W85) -> 0 | X85: =SUM(FO!X85,PO!X85,CO!X85,FE!X85,PE!X85) -> 0 | Y85: =SUM(FO!Y85,PO!Y85,CO!Y85,FE!Y85,PE!Y85) -> 0 | Z85: =SUM(FO!Z85,PO!Z85,CO!Z85,FE!Z85,PE!Z85) -> 0 | AA85: =SUM(FO!AA85,PO!AA85,CO!AA85,FE!AA85,PE!AA85) -> 0 | AB85: =SUM(FO!AB85,PO!AB85,CO!AB85,FE!AB85,PE!AB85) -> 0 | ... AF85: =SUM(FO!AF85,PO!AF85,CO!AF85,FE!AF85,PE!AF85) -> 0 | AG85: =SUM(U85:AF85) -> 0 | AH85: =IFERROR(AG85/AG$16,"") -> 0 | AJ85: =N85-AG85 -> 19742.15
A86: 6550 - Meals - Demos | B86: =SUM(FO!B86,PO!B86,CO!B86,FE!B86,PE!B86) -> 143.34 | C86: =SUM(FO!C86,PO!C86,CO!C86,FE!C86,PE!C86) -> 368.8 | D86: =SUM(FO!D86,PO!D86,CO!D86,FE!D86,PE!D86) -> 160.18 | E86: =SUM(FO!E86,PO!E86,CO!E86,FE!E86,PE!E86) -> 0 | F86: =SUM(FO!F86,PO!F86,CO!F86,FE!F86,PE!F86) -> 235.48 | G86: =SUM(FO!G86,PO!G86,CO!G86,FE!G86,PE!G86) -> 241.47 | H86: =SUM(FO!H86,PO!H86,CO!H86,FE!H86,PE!H86) -> 169.9 | I86: =SUM(FO!I86,PO!I86,CO!I86,FE!I86,PE!I86) -> 0 | ... M86: =SUM(FO!M86,PO!M86,CO!M86,FE!M86,PE!M86) -> 200 | N86: =SUM(B86:M86) -> 2419.17 | O86: =IFERROR(N86/N$16,"") -> 0.00032586068 | U86: =SUM(FO!U86,PO!U86,CO!U86,FE!U86,PE!U86) -> 0 | V86: =SUM(FO!V86,PO!V86,CO!V86,FE!V86,PE!V86) -> 0 | W86: =SUM(FO!W86,PO!W86,CO!W86,FE!W86,PE!W86) -> 0 | X86: =SUM(FO!X86,PO!X86,CO!X86,FE!X86,PE!X86) -> 0 | Y86: =SUM(FO!Y86,PO!Y86,CO!Y86,FE!Y86,PE!Y86) -> 0 | Z86: =SUM(FO!Z86,PO!Z86,CO!Z86,FE!Z86,PE!Z86) -> 0 | AA86: =SUM(FO!AA86,PO!AA86,CO!AA86,FE!AA86,PE!AA86) -> 0 | AB86: =SUM(FO!AB86,PO!AB86,CO!AB86,FE!AB86,PE!AB86) -> 0 | ... AF86: =SUM(FO!AF86,PO!AF86,CO!AF86,FE!AF86,PE!AF86) -> 0 | AG86: =SUM(U86:AF86) -> 0 | AH86: =IFERROR(AG86/AG$16,"") -> 0 | AJ86: =N86-AG86 -> 2419.17
A87: Total - 6500 - Demos | B87: =SUM(B82:B86) -> 4199.99 | C87: =SUM(C82:C86) -> 7388.03 | D87: =SUM(D82:D86) -> 1141.03 | E87: =SUM(E82:E86) -> 1638.14 | F87: =SUM(F82:F86) -> 2775.5 | G87: =SUM(G82:G86) -> 2738.43 | H87: =SUM(H82:H86) -> 2985.31 | I87: =SUM(I82:I86) -> 0 | ... M87: =SUM(M82:M86) -> 3800 | N87: =SUM(B87:M87) -> 42366.43 | O87: =IFERROR(N87/N$16,"") -> 0.0057067315 | U87: =SUM(U82:U86) -> 0 | V87: =SUM(V82:V86) -> 0 | W87: =SUM(W82:W86) -> 0 | X87: =SUM(X82:X86) -> 0 | Y87: =SUM(Y82:Y86) -> 0 | Z87: =SUM(Z82:Z86) -> 0 | AA87: =SUM(AA82:AA86) -> 0 | AB87: =SUM(AB82:AB86) -> 0 | ... AF87: =SUM(AF82:AF86) -> 0 | AG87: =SUM(U87:AF87) -> 0 | AH87: =IFERROR(AG87/AG$16,"") -> 0 | AJ87: =N87-AG87 -> 42366.43
A88: 7000 - Professional Fees | B88: =SUM(FO!B88,PO!B88,CO!B88,FE!B88,PE!B88) -> 0 | C88: =SUM(FO!C88,PO!C88,CO!C88,FE!C88,PE!C88) -> 0 | D88: =SUM(FO!D88,PO!D88,CO!D88,FE!D88,PE!D88) -> 0 | E88: =SUM(FO!E88,PO!E88,CO!E88,FE!E88,PE!E88) -> 0 | F88: =SUM(FO!F88,PO!F88,CO!F88,FE!F88,PE!F88) -> 0 | G88: =SUM(FO!G88,PO!G88,CO!G88,FE!G88,PE!G88) -> 0 | H88: =SUM(FO!H88,PO!H88,CO!H88,FE!H88,PE!H88) -> 0 | I88: =SUM(FO!I88,PO!I88,CO!I88,FE!I88,PE!I88) -> 0 | ... M88: =SUM(FO!M88,PO!M88,CO!M88,FE!M88,PE!M88) -> 0 | N88: =SUM(B88:M88) -> 0 | O88: =IFERROR(N88/N$16,"") -> 0 | U88: =SUM(FO!U88,PO!U88,CO!U88,FE!U88,PE!U88) -> 0 | V88: =SUM(FO!V88,PO!V88,CO!V88,FE!V88,PE!V88) -> 0 | W88: =SUM(FO!W88,PO!W88,CO!W88,FE!W88,PE!W88) -> 0 | X88: =SUM(FO!X88,PO!X88,CO!X88,FE!X88,PE!X88) -> 0 | Y88: =SUM(FO!Y88,PO!Y88,CO!Y88,FE!Y88,PE!Y88) -> 0 | Z88: =SUM(FO!Z88,PO!Z88,CO!Z88,FE!Z88,PE!Z88) -> 0 | AA88: =SUM(FO!AA88,PO!AA88,CO!AA88,FE!AA88,PE!AA88) -> 0 | AB88: =SUM(FO!AB88,PO!AB88,CO!AB88,FE!AB88,PE!AB88) -> 0 | ... AF88: =SUM(FO!AF88,PO!AF88,CO!AF88,FE!AF88,PE!AF88) -> 0 | AG88: =SUM(U88:AF88) -> 0 | AH88: =IFERROR(AG88/AG$16,"") -> 0 | AJ88: =N88-AG88 -> 0
A89: 7050 - Education | B89: =SUM(FO!B89,PO!B89,CO!B89,FE!B89,PE!B89) -> 0 | C89: =SUM(FO!C89,PO!C89,CO!C89,FE!C89,PE!C89) -> 0 | D89: =SUM(FO!D89,PO!D89,CO!D89,FE!D89,PE!D89) -> 0 | E89: =SUM(FO!E89,PO!E89,CO!E89,FE!E89,PE!E89) -> 0 | F89: =SUM(FO!F89,PO!F89,CO!F89,FE!F89,PE!F89) -> 0 | G89: =SUM(FO!G89,PO!G89,CO!G89,FE!G89,PE!G89) -> 31320 | H89: =SUM(FO!H89,PO!H89,CO!H89,FE!H89,PE!H89) -> -8375 | I89: =SUM(FO!I89,PO!I89,CO!I89,FE!I89,PE!I89) -> -8375 | ... M89: =SUM(FO!M89,PO!M89,CO!M89,FE!M89,PE!M89) -> 0 | N89: =SUM(B89:M89) -> 14570 | O89: =IFERROR(N89/N$16,"") -> 0.0019625699 | U89: =SUM(FO!U89,PO!U89,CO!U89,FE!U89,PE!U89) -> 0 | V89: =SUM(FO!V89,PO!V89,CO!V89,FE!V89,PE!V89) -> 0 | W89: =SUM(FO!W89,PO!W89,CO!W89,FE!W89,PE!W89) -> 0 | X89: =SUM(FO!X89,PO!X89,CO!X89,FE!X89,PE!X89) -> 0 | Y89: =SUM(FO!Y89,PO!Y89,CO!Y89,FE!Y89,PE!Y89) -> 0 | Z89: =SUM(FO!Z89,PO!Z89,CO!Z89,FE!Z89,PE!Z89) -> 0 | AA89: =SUM(FO!AA89,PO!AA89,CO!AA89,FE!AA89,PE!AA89) -> 0 | AB89: =SUM(FO!AB89,PO!AB89,CO!AB89,FE!AB89,PE!AB89) -> 0 | ... AF89: =SUM(FO!AF89,PO!AF89,CO!AF89,FE!AF89,PE!AF89) -> 0 | AG89: =SUM(U89:AF89) -> 0 | AH89: =IFERROR(AG89/AG$16,"") -> 0 | AJ89: =N89-AG89 -> 14570
A90: 7100 - Legal Expense | B90: =SUM(FO!B90,PO!B90,CO!B90,FE!B90,PE!B90) -> 0 | C90: =SUM(FO!C90,PO!C90,CO!C90,FE!C90,PE!C90) -> 0 | D90: =SUM(FO!D90,PO!D90,CO!D90,FE!D90,PE!D90) -> 0 | E90: =SUM(FO!E90,PO!E90,CO!E90,FE!E90,PE!E90) -> 0 | F90: =SUM(FO!F90,PO!F90,CO!F90,FE!F90,PE!F90) -> 0 | G90: =SUM(FO!G90,PO!G90,CO!G90,FE!G90,PE!G90) -> 0 | H90: =SUM(FO!H90,PO!H90,CO!H90,FE!H90,PE!H90) -> 0 | I90: =SUM(FO!I90,PO!I90,CO!I90,FE!I90,PE!I90) -> 0 | ... M90: =SUM(FO!M90,PO!M90,CO!M90,FE!M90,PE!M90) -> 0 | N90: =SUM(B90:M90) -> 0 | O90: =IFERROR(N90/N$16,"") -> 0 | U90: =SUM(FO!U90,PO!U90,CO!U90,FE!U90,PE!U90) -> 0 | V90: =SUM(FO!V90,PO!V90,CO!V90,FE!V90,PE!V90) -> 0 | W90: =SUM(FO!W90,PO!W90,CO!W90,FE!W90,PE!W90) -> 0 | X90: =SUM(FO!X90,PO!X90,CO!X90,FE!X90,PE!X90) -> 0 | Y90: =SUM(FO!Y90,PO!Y90,CO!Y90,FE!Y90,PE!Y90) -> 0 | Z90: =SUM(FO!Z90,PO!Z90,CO!Z90,FE!Z90,PE!Z90) -> 0 | AA90: =SUM(FO!AA90,PO!AA90,CO!AA90,FE!AA90,PE!AA90) -> 0 | AB90: =SUM(FO!AB90,PO!AB90,CO!AB90,FE!AB90,PE!AB90) -> 0 | ... AF90: =SUM(FO!AF90,PO!AF90,CO!AF90,FE!AF90,PE!AF90) -> 0 | AG90: =SUM(U90:AF90) -> 0 | AH90: =IFERROR(AG90/AG$16,"") -> 0 | AJ90: =N90-AG90 -> 0
A91: 7200 - Contractors | B91: =SUM(FO!B91,PO!B91,CO!B91,FE!B91,PE!B91) -> 0 | C91: =SUM(FO!C91,PO!C91,CO!C91,FE!C91,PE!C91) -> 11217.74 | D91: =SUM(FO!D91,PO!D91,CO!D91,FE!D91,PE!D91) -> 51810.95 | E91: =SUM(FO!E91,PO!E91,CO!E91,FE!E91,PE!E91) -> 34690.39 | F91: =SUM(FO!F91,PO!F91,CO!F91,FE!F91,PE!F91) -> 36509.27 | G91: =SUM(FO!G91,PO!G91,CO!G91,FE!G91,PE!G91) -> 56672.78 | H91: =SUM(FO!H91,PO!H91,CO!H91,FE!H91,PE!H91) -> 8883.71 | I91: =SUM(FO!I91,PO!I91,CO!I91,FE!I91,PE!I91) -> 14805.67 | ... M91: =SUM(FO!M91,PO!M91,CO!M91,FE!M91,PE!M91) -> 0 | N91: =SUM(B91:M91) -> 214590.51 | O91: =IFERROR(N91/N$16,"") -> 0.028905207 | U91: =SUM(FO!U91,PO!U91,CO!U91,FE!U91,PE!U91) -> 0 | V91: =SUM(FO!V91,PO!V91,CO!V91,FE!V91,PE!V91) -> 0 | W91: =SUM(FO!W91,PO!W91,CO!W91,FE!W91,PE!W91) -> 0 | X91: =SUM(FO!X91,PO!X91,CO!X91,FE!X91,PE!X91) -> 0 | Y91: =SUM(FO!Y91,PO!Y91,CO!Y91,FE!Y91,PE!Y91) -> 0 | Z91: =SUM(FO!Z91,PO!Z91,CO!Z91,FE!Z91,PE!Z91) -> 0 | AA91: =SUM(FO!AA91,PO!AA91,CO!AA91,FE!AA91,PE!AA91) -> 0 | AB91: =SUM(FO!AB91,PO!AB91,CO!AB91,FE!AB91,PE!AB91) -> 0 | ... AF91: =SUM(FO!AF91,PO!AF91,CO!AF91,FE!AF91,PE!AF91) -> 0 | AG91: =SUM(U91:AF91) -> 0 | AH91: =IFERROR(AG91/AG$16,"") -> 0 | AJ91: =N91-AG91 -> 214590.51
A92: 7300 - R&D Expense | B92: =SUM(FO!B92,PO!B92,CO!B92,FE!B92,PE!B92) -> 2556.61 | C92: =SUM(FO!C92,PO!C92,CO!C92,FE!C92,PE!C92) -> 2642.64 | D92: =SUM(FO!D92,PO!D92,CO!D92,FE!D92,PE!D92) -> 4142.74 | E92: =SUM(FO!E92,PO!E92,CO!E92,FE!E92,PE!E92) -> 3000.52 | F92: =SUM(FO!F92,PO!F92,CO!F92,FE!F92,PE!F92) -> 9578.03 | G92: =SUM(FO!G92,PO!G92,CO!G92,FE!G92,PE!G92) -> 3128.81 | H92: =SUM(FO!H92,PO!H92,CO!H92,FE!H92,PE!H92) -> 0 | I92: =SUM(FO!I92,PO!I92,CO!I92,FE!I92,PE!I92) -> 811.1 | ... M92: =SUM(FO!M92,PO!M92,CO!M92,FE!M92,PE!M92) -> 0 | N92: =SUM(B92:M92) -> 25860.45 | O92: =IFERROR(N92/N$16,"") -> 0.0034833864 | U92: =SUM(FO!U92,PO!U92,CO!U92,FE!U92,PE!U92) -> 0 | V92: =SUM(FO!V92,PO!V92,CO!V92,FE!V92,PE!V92) -> 0 | W92: =SUM(FO!W92,PO!W92,CO!W92,FE!W92,PE!W92) -> 0 | X92: =SUM(FO!X92,PO!X92,CO!X92,FE!X92,PE!X92) -> 0 | Y92: =SUM(FO!Y92,PO!Y92,CO!Y92,FE!Y92,PE!Y92) -> 0 | Z92: =SUM(FO!Z92,PO!Z92,CO!Z92,FE!Z92,PE!Z92) -> 0 | AA92: =SUM(FO!AA92,PO!AA92,CO!AA92,FE!AA92,PE!AA92) -> 0 | AB92: =SUM(FO!AB92,PO!AB92,CO!AB92,FE!AB92,PE!AB92) -> 0 | ... AF92: =SUM(FO!AF92,PO!AF92,CO!AF92,FE!AF92,PE!AF92) -> 0 | AG92: =SUM(U92:AF92) -> 0 | AH92: =IFERROR(AG92/AG$16,"") -> 0 | AJ92: =N92-AG92 -> 25860.45
A93: 7500 - Facility Expenses | B93: =SUM(FO!B93,PO!B93,CO!B93,FE!B93,PE!B93) -> 695.8 | C93: =SUM(FO!C93,PO!C93,CO!C93,FE!C93,PE!C93) -> 1174.04 | D93: =SUM(FO!D93,PO!D93,CO!D93,FE!D93,PE!D93) -> 946.56 | E93: =SUM(FO!E93,PO!E93,CO!E93,FE!E93,PE!E93) -> 2409.75 | F93: =SUM(FO!F93,PO!F93,CO!F93,FE!F93,PE!F93) -> 5233.37 | G93: =SUM(FO!G93,PO!G93,CO!G93,FE!G93,PE!G93) -> 555.44 | H93: =SUM(FO!H93,PO!H93,CO!H93,FE!H93,PE!H93) -> 0 | I93: =SUM(FO!I93,PO!I93,CO!I93,FE!I93,PE!I93) -> 19.07 | ... M93: =SUM(FO!M93,PO!M93,CO!M93,FE!M93,PE!M93) -> 5300 | N93: =SUM(B93:M93) -> 28034.03 | O93: =IFERROR(N93/N$16,"") -> 0.0037761663 | U93: =SUM(FO!U93,PO!U93,CO!U93,FE!U93,PE!U93) -> 1116.6667 | V93: =SUM(FO!V93,PO!V93,CO!V93,FE!V93,PE!V93) -> 1116.6667 | W93: =SUM(FO!W93,PO!W93,CO!W93,FE!W93,PE!W93) -> 1116.6667 | X93: =SUM(FO!X93,PO!X93,CO!X93,FE!X93,PE!X93) -> 1116.6667 | Y93: =SUM(FO!Y93,PO!Y93,CO!Y93,FE!Y93,PE!Y93) -> 1172.5 | Z93: =SUM(FO!Z93,PO!Z93,CO!Z93,FE!Z93,PE!Z93) -> 1228.3333 | AA93: =SUM(FO!AA93,PO!AA93,CO!AA93,FE!AA93,PE!AA93) -> 1284.1667 | AB93: =SUM(FO!AB93,PO!AB93,CO!AB93,FE!AB93,PE!AB93) -> 1340 | ... AF93: =SUM(FO!AF93,PO!AF93,CO!AF93,FE!AF93,PE!AF93) -> 1283.3333 | AG93: =SUM(U93:AF93) -> 15130 | AH93: =IFERROR(AG93/AG$16,"") -> 0.00097213728 | AJ93: =N93-AG93 -> 12904.03
A94: 7510 - Custodial | B94: =SUM(FO!B94,PO!B94,CO!B94,FE!B94,PE!B94) -> 0 | C94: =SUM(FO!C94,PO!C94,CO!C94,FE!C94,PE!C94) -> 0 | D94: =SUM(FO!D94,PO!D94,CO!D94,FE!D94,PE!D94) -> 0 | E94: =SUM(FO!E94,PO!E94,CO!E94,FE!E94,PE!E94) -> 0 | F94: =SUM(FO!F94,PO!F94,CO!F94,FE!F94,PE!F94) -> 0 | G94: =SUM(FO!G94,PO!G94,CO!G94,FE!G94,PE!G94) -> 0 | H94: =SUM(FO!H94,PO!H94,CO!H94,FE!H94,PE!H94) -> 0 | I94: =SUM(FO!I94,PO!I94,CO!I94,FE!I94,PE!I94) -> 0 | ... M94: =SUM(FO!M94,PO!M94,CO!M94,FE!M94,PE!M94) -> 0 | N94: =SUM(B94:M94) -> 0 | O94: =IFERROR(N94/N$16,"") -> 0 | U94: =SUM(FO!U94,PO!U94,CO!U94,FE!U94,PE!U94) -> 0 | V94: =SUM(FO!V94,PO!V94,CO!V94,FE!V94,PE!V94) -> 0 | W94: =SUM(FO!W94,PO!W94,CO!W94,FE!W94,PE!W94) -> 0 | X94: =SUM(FO!X94,PO!X94,CO!X94,FE!X94,PE!X94) -> 0 | Y94: =SUM(FO!Y94,PO!Y94,CO!Y94,FE!Y94,PE!Y94) -> 0 | Z94: =SUM(FO!Z94,PO!Z94,CO!Z94,FE!Z94,PE!Z94) -> 0 | AA94: =SUM(FO!AA94,PO!AA94,CO!AA94,FE!AA94,PE!AA94) -> 0 | AB94: =SUM(FO!AB94,PO!AB94,CO!AB94,FE!AB94,PE!AB94) -> 0 | ... AF94: =SUM(FO!AF94,PO!AF94,CO!AF94,FE!AF94,PE!AF94) -> 0 | AG94: =SUM(U94:AF94) -> 0 | AH94: =IFERROR(AG94/AG$16,"") -> 0 | AJ94: =N94-AG94 -> 0
A95: 7550 - Tools and Equipment | B95: =SUM(FO!B95,PO!B95,CO!B95,FE!B95,PE!B95) -> 5265.28 | C95: =SUM(FO!C95,PO!C95,CO!C95,FE!C95,PE!C95) -> 2452.18 | D95: =SUM(FO!D95,PO!D95,CO!D95,FE!D95,PE!D95) -> 4962.84 | E95: =SUM(FO!E95,PO!E95,CO!E95,FE!E95,PE!E95) -> 6484.85 | F95: =SUM(FO!F95,PO!F95,CO!F95,FE!F95,PE!F95) -> 2744.63 | G95: =SUM(FO!G95,PO!G95,CO!G95,FE!G95,PE!G95) -> -14.29 | H95: =SUM(FO!H95,PO!H95,CO!H95,FE!H95,PE!H95) -> 3654.69 | I95: =SUM(FO!I95,PO!I95,CO!I95,FE!I95,PE!I95) -> 2514.69 | ... M95: =SUM(FO!M95,PO!M95,CO!M95,FE!M95,PE!M95) -> 7450 | N95: =SUM(B95:M95) -> 57864.87 | O95: =IFERROR(N95/N$16,"") -> 0.0077943617 | U95: =SUM(FO!U95,PO!U95,CO!U95,FE!U95,PE!U95) -> 4866.6667 | V95: =SUM(FO!V95,PO!V95,CO!V95,FE!V95,PE!V95) -> 4866.6667 | W95: =SUM(FO!W95,PO!W95,CO!W95,FE!W95,PE!W95) -> 4866.6667 | X95: =SUM(FO!X95,PO!X95,CO!X95,FE!X95,PE!X95) -> 4866.6667 | Y95: =SUM(FO!Y95,PO!Y95,CO!Y95,FE!Y95,PE!Y95) -> 5110 | Z95: =SUM(FO!Z95,PO!Z95,CO!Z95,FE!Z95,PE!Z95) -> 5353.3333 | AA95: =SUM(FO!AA95,PO!AA95,CO!AA95,FE!AA95,PE!AA95) -> 5596.6667 | AB95: =SUM(FO!AB95,PO!AB95,CO!AB95,FE!AB95,PE!AB95) -> 5840 | ... AF95: =SUM(FO!AF95,PO!AF95,CO!AF95,FE!AF95,PE!AF95) -> 5733.3333 | AG95: =SUM(U95:AF95) -> 66080 | AH95: =IFERROR(AG95/AG$16,"") -> 0.0042457919 | AJ95: =N95-AG95 -> -8215.13
A96: 7600 - Freight & Delivery | B96: =SUM(FO!B96,PO!B96,CO!B96,FE!B96,PE!B96) -> 4965.69 | C96: =SUM(FO!C96,PO!C96,CO!C96,FE!C96,PE!C96) -> 15.09 | D96: =SUM(FO!D96,PO!D96,CO!D96,FE!D96,PE!D96) -> 765.15 | E96: =SUM(FO!E96,PO!E96,CO!E96,FE!E96,PE!E96) -> 9652.71 | F96: =SUM(FO!F96,PO!F96,CO!F96,FE!F96,PE!F96) -> 1174.75 | G96: =SUM(FO!G96,PO!G96,CO!G96,FE!G96,PE!G96) -> 4659.04 | H96: =SUM(FO!H96,PO!H96,CO!H96,FE!H96,PE!H96) -> 561.23 | I96: =SUM(FO!I96,PO!I96,CO!I96,FE!I96,PE!I96) -> 273.43 | ... M96: =SUM(FO!M96,PO!M96,CO!M96,FE!M96,PE!M96) -> 600 | N96: =SUM(B96:M96) -> 24467.09 | O96: =IFERROR(N96/N$16,"") -> 0.0032957017 | U96: =SUM(FO!U96,PO!U96,CO!U96,FE!U96,PE!U96) -> 500 | V96: =SUM(FO!V96,PO!V96,CO!V96,FE!V96,PE!V96) -> 500 | W96: =SUM(FO!W96,PO!W96,CO!W96,FE!W96,PE!W96) -> 500 | X96: =SUM(FO!X96,PO!X96,CO!X96,FE!X96,PE!X96) -> 500 | Y96: =SUM(FO!Y96,PO!Y96,CO!Y96,FE!Y96,PE!Y96) -> 500 | Z96: =SUM(FO!Z96,PO!Z96,CO!Z96,FE!Z96,PE!Z96) -> 500 | AA96: =SUM(FO!AA96,PO!AA96,CO!AA96,FE!AA96,PE!AA96) -> 500 | AB96: =SUM(FO!AB96,PO!AB96,CO!AB96,FE!AB96,PE!AB96) -> 500 | ... AF96: =SUM(FO!AF96,PO!AF96,CO!AF96,FE!AF96,PE!AF96) -> 500 | AG96: =SUM(U96:AF96) -> 6000 | AH96: =IFERROR(AG96/AG$16,"") -> 0.00038551379 | AJ96: =N96-AG96 -> 18467.09
A97: 7610 - Duties & Tariffs - Other | B97: =SUM(FO!B97,PO!B97,CO!B97,FE!B97,PE!B97) -> 0 | C97: =SUM(FO!C97,PO!C97,CO!C97,FE!C97,PE!C97) -> 0 | D97: =SUM(FO!D97,PO!D97,CO!D97,FE!D97,PE!D97) -> 0 | E97: =SUM(FO!E97,PO!E97,CO!E97,FE!E97,PE!E97) -> 0 | F97: =SUM(FO!F97,PO!F97,CO!F97,FE!F97,PE!F97) -> 0 | G97: =SUM(FO!G97,PO!G97,CO!G97,FE!G97,PE!G97) -> 0 | H97: =SUM(FO!H97,PO!H97,CO!H97,FE!H97,PE!H97) -> 0 | I97: =SUM(FO!I97,PO!I97,CO!I97,FE!I97,PE!I97) -> 0 | ... M97: =SUM(FO!M97,PO!M97,CO!M97,FE!M97,PE!M97) -> 0 | N97: =SUM(B97:M97) -> 0 | O97: =IFERROR(N97/N$16,"") -> 0 | U97: =SUM(FO!U97,PO!U97,CO!U97,FE!U97,PE!U97) -> 0 | V97: =SUM(FO!V97,PO!V97,CO!V97,FE!V97,PE!V97) -> 0 | W97: =SUM(FO!W97,PO!W97,CO!W97,FE!W97,PE!W97) -> 0 | X97: =SUM(FO!X97,PO!X97,CO!X97,FE!X97,PE!X97) -> 0 | Y97: =SUM(FO!Y97,PO!Y97,CO!Y97,FE!Y97,PE!Y97) -> 0 | Z97: =SUM(FO!Z97,PO!Z97,CO!Z97,FE!Z97,PE!Z97) -> 0 | AA97: =SUM(FO!AA97,PO!AA97,CO!AA97,FE!AA97,PE!AA97) -> 0 | AB97: =SUM(FO!AB97,PO!AB97,CO!AB97,FE!AB97,PE!AB97) -> 0 | ... AF97: =SUM(FO!AF97,PO!AF97,CO!AF97,FE!AF97,PE!AF97) -> 0 | AG97: =SUM(U97:AF97) -> 0 | AH97: =IFERROR(AG97/AG$16,"") -> 0 | AJ97: =N97-AG97 -> 0
A98: 7700 - Inventory Obsolescence-old | B98: =SUM(FO!B98,PO!B98,CO!B98,FE!B98,PE!B98) -> 0 | C98: =SUM(FO!C98,PO!C98,CO!C98,FE!C98,PE!C98) -> 0 | D98: =SUM(FO!D98,PO!D98,CO!D98,FE!D98,PE!D98) -> 0 | E98: =SUM(FO!E98,PO!E98,CO!E98,FE!E98,PE!E98) -> 0 | F98: =SUM(FO!F98,PO!F98,CO!F98,FE!F98,PE!F98) -> 0 | G98: =SUM(FO!G98,PO!G98,CO!G98,FE!G98,PE!G98) -> 0 | H98: =SUM(FO!H98,PO!H98,CO!H98,FE!H98,PE!H98) -> 0 | I98: =SUM(FO!I98,PO!I98,CO!I98,FE!I98,PE!I98) -> 0 | ... M98: =SUM(FO!M98,PO!M98,CO!M98,FE!M98,PE!M98) -> 2000 | N98: =SUM(B98:M98) -> 636000 | O98: =IFERROR(N98/N$16,"") -> 0.085668801 | U98: =SUM(FO!U98,PO!U98,CO!U98,FE!U98,PE!U98) -> 2000 | V98: =SUM(FO!V98,PO!V98,CO!V98,FE!V98,PE!V98) -> 2000 | W98: =SUM(FO!W98,PO!W98,CO!W98,FE!W98,PE!W98) -> 2000 | X98: =SUM(FO!X98,PO!X98,CO!X98,FE!X98,PE!X98) -> 2000 | Y98: =SUM(FO!Y98,PO!Y98,CO!Y98,FE!Y98,PE!Y98) -> 2000 | Z98: =SUM(FO!Z98,PO!Z98,CO!Z98,FE!Z98,PE!Z98) -> 2000 | AA98: =SUM(FO!AA98,PO!AA98,CO!AA98,FE!AA98,PE!AA98) -> 2000 | AB98: =SUM(FO!AB98,PO!AB98,CO!AB98,FE!AB98,PE!AB98) -> 2000 | ... AF98: =SUM(FO!AF98,PO!AF98,CO!AF98,FE!AF98,PE!AF98) -> 2000 | AG98: =SUM(U98:AF98) -> 24000 | AH98: =IFERROR(AG98/AG$16,"") -> 0.0015420552 | AJ98: =N98-AG98 -> 612000
A99: 8100 - Technology | B99: =SUM(FO!B99,PO!B99,CO!B99,FE!B99,PE!B99) -> 5040.75 | C99: =SUM(FO!C99,PO!C99,CO!C99,FE!C99,PE!C99) -> 826.9 | D99: =SUM(FO!D99,PO!D99,CO!D99,FE!D99,PE!D99) -> 303.94 | E99: =SUM(FO!E99,PO!E99,CO!E99,FE!E99,PE!E99) -> 557.39 | F99: =SUM(FO!F99,PO!F99,CO!F99,FE!F99,PE!F99) -> 597.8 | G99: =SUM(FO!G99,PO!G99,CO!G99,FE!G99,PE!G99) -> 497.39 | H99: =SUM(FO!H99,PO!H99,CO!H99,FE!H99,PE!H99) -> 573.49 | I99: =SUM(FO!I99,PO!I99,CO!I99,FE!I99,PE!I99) -> 512.64 | ... M99: =SUM(FO!M99,PO!M99,CO!M99,FE!M99,PE!M99) -> 2210 | N99: =SUM(B99:M99) -> 17750.3 | O99: =IFERROR(N99/N$16,"") -> 0.0023909543 | U99: =SUM(FO!U99,PO!U99,CO!U99,FE!U99,PE!U99) -> 2116.6667 | V99: =SUM(FO!V99,PO!V99,CO!V99,FE!V99,PE!V99) -> 2116.6667 | W99: =SUM(FO!W99,PO!W99,CO!W99,FE!W99,PE!W99) -> 2116.6667 | X99: =SUM(FO!X99,PO!X99,CO!X99,FE!X99,PE!X99) -> 2116.6667 | Y99: =SUM(FO!Y99,PO!Y99,CO!Y99,FE!Y99,PE!Y99) -> 2116.6667 | Z99: =SUM(FO!Z99,PO!Z99,CO!Z99,FE!Z99,PE!Z99) -> 2116.6667 | AA99: =SUM(FO!AA99,PO!AA99,CO!AA99,FE!AA99,PE!AA99) -> 2116.6667 | AB99: =SUM(FO!AB99,PO!AB99,CO!AB99,FE!AB99,PE!AB99) -> 2116.6667 | ... AF99: =SUM(FO!AF99,PO!AF99,CO!AF99,FE!AF99,PE!AF99) -> 2116.6667 | AG99: =SUM(U99:AF99) -> 25400 | AH99: =IFERROR(AG99/AG$16,"") -> 0.0016320084 | AJ99: =N99-AG99 -> -7649.7
... A115: 9999 - Uncategorized Expenses | B115: =SUM(FO!B115,PO!B115,CO!B115,FE!B115,PE!B115) -> 0 | C115: =SUM(FO!C115,PO!C115,CO!C115,FE!C115,PE!C115) -> 0 | D115: =SUM(FO!D115,PO!D115,CO!D115,FE!D115,PE!D115) -> 0 | E115: =SUM(FO!E115,PO!E115,CO!E115,FE!E115,PE!E115) -> 0 | F115: =SUM(FO!F115,PO!F115,CO!F115,FE!F115,PE!F115) -> 0 | G115: =SUM(FO!G115,PO!G115,CO!G115,FE!G115,PE!G115) -> 0 | H115: =SUM(FO!H115,PO!H115,CO!H115,FE!H115,PE!H115) -> 0 | I115: =SUM(FO!I115,PO!I115,CO!I115,FE!I115,PE!I115) -> 0 | ... M115: =SUM(FO!M115,PO!M115,CO!M115,FE!M115,PE!M115) -> 0 | N115: =SUM(B115:M115) -> 0 | O115: =IFERROR(N115/N$16,"") -> 0 | U115: =SUM(FO!U115,PO!U115,CO!U115,FE!U115,PE!U115) -> 0 | V115: =SUM(FO!V115,PO!V115,CO!V115,FE!V115,PE!V115) -> 0 | W115: =SUM(FO!W115,PO!W115,CO!W115,FE!W115,PE!W115) -> 0 | X115: =SUM(FO!X115,PO!X115,CO!X115,FE!X115,PE!X115) -> 0 | Y115: =SUM(FO!Y115,PO!Y115,CO!Y115,FE!Y115,PE!Y115) -> 0 | Z115: =SUM(FO!Z115,PO!Z115,CO!Z115,FE!Z115,PE!Z115) -> 0 | AA115: =SUM(FO!AA115,PO!AA115,CO!AA115,FE!AA115,PE!AA115) -> 0 | AB115: =SUM(FO!AB115,PO!AB115,CO!AB115,FE!AB115,PE!AB115) -> 0 | ... AF115: =SUM(FO!AF115,PO!AF115,CO!AF115,FE!AF115,PE!AF115) -> 0 | AG115: =SUM(U115:AF115) -> 0 | AH115: =IFERROR(AG115/AG$16,"") -> 0 | AJ115: =N115-AG115 -> 0
A116: Total - Expense | B116: =B73+SUM(B74:B80)+B87+SUM(B88:B115) -> 159854.29 | C116: =C73+SUM(C74:C80)+C87+SUM(C88:C115) -> 36073.48 | D116: =D73+SUM(D74:D80)+D87+SUM(D88:D115) -> 248083.34 | E116: =E73+SUM(E74:E80)+E87+SUM(E88:E115) -> 252179.52 | F116: =F73+SUM(F74:F80)+F87+SUM(F88:F115) -> 299699.19 | G116: =G73+SUM(G74:G80)+G87+SUM(G88:G115) -> 345953.53 | H116: =H73+SUM(H74:H80)+H87+SUM(H88:H115) -> 229505.53 | I116: =I73+SUM(I74:I80)+I87+SUM(I88:I115) -> 258700.42 | ... M116: =M73+SUM(M74:M80)+M87+SUM(M88:M115) -> 383688 | N116: =SUM(B116:M116) -> 3929957.3 | O116: =IFERROR(N116/N$16,"") -> 0.52936278 | U116: =U73+SUM(U74:U80)+U87+SUM(U88:U115) -> 321525.13 | V116: =V73+SUM(V74:V80)+V87+SUM(V88:V115) -> 327453.13 | W116: =W73+SUM(W74:W80)+W87+SUM(W88:W115) -> 333778.25 | X116: =X73+SUM(X74:X80)+X87+SUM(X88:X115) -> 332778.25 | Y116: =Y73+SUM(Y74:Y80)+Y87+SUM(Y88:Y115) -> 333677.41 | Z116: =Z73+SUM(Z74:Z80)+Z87+SUM(Z88:Z115) -> 340101.7 | AA116: =AA73+SUM(AA74:AA80)+AA87+SUM(AA88:AA115) -> 352464.65 | AB116: =AB73+SUM(AB74:AB80)+AB87+SUM(AB88:AB115) -> 357437.15 | ... AF116: =AF73+SUM(AF74:AF80)+AF87+SUM(AF88:AF115) -> 368279.64 | AG116: =SUM(U116:AF116) -> 4162413.4 | AH116: =IFERROR(AG116/AG$16,"") -> 0.26744463 | AJ116: =N116-AG116 -> -232456.12
A117: Net Ordinary Income | B117: =B64-B116 -> 114581.3 | C117: =C64-C116 -> 186181.91 | D117: =D64-D116 -> -46641.99 | E117: =E64-E116 -> 152657.93 | F117: =F64-F116 -> -164415.79 | G117: =G64-G116 -> -223479.01 | H117: =H64-H116 -> 67487.73 | I117: =I64-I116 -> -246328 | ... M117: =M64-M116 -> -16126.053 | N117: =SUM(B117:M117) -> -984033.37 | O117: =IFERROR(N117/N$16,"") -> -0.13254868 | U117: =U64-U116 -> #REF! | V117: =V64-V116 -> #REF! | W117: =W64-W116 -> #REF! | X117: =X64-X116 -> #REF! | Y117: =Y64-Y116 -> #REF! | Z117: =Z64-Z116 -> #REF! | AA117: =AA64-AA116 -> #REF! | AB117: =AB64-AB116 -> #REF! | ... AF117: =AF64-AF116 -> #REF! | AG117: =SUM(U117:AF117) -> #REF! | AH117: =IFERROR(AG117/AG$16,"") | AJ117: =AG117-N117 -> #REF!
A118: Other Income and Expenses
A119: Other Income
...

Sheet FO
A1: Field Operations
A2: 2026 Actuals/Forecast & 2027 Budget
B7: Actual | C7: Actual | D7: Actual | E7: Actual | F7: Actual | G7: Actual | H7: Actual | I7: Actual | J7: Forecast | K7: Forecast | L7: Forecast | M7: Forecast | N7: Forecast | O7: Forecast | S7: Annual Input | T7: YOY | U7: Budget | V7: Budget | W7: Budget | X7: Budget | Y7: Budget | Z7: Budget | AA7: Budget | AB7: Budget | AC7: Budget | AD7: Budget | AE7: Budget | AF7: Budget | AG7: Budget | AH7: Budget | AJ7: YOY
B8: Jan | C8: Feb | D8: Mar | E8: Apr | F8: May | G8: Jun | H8: Jul | I8: Aug | J8: Sep | K8: Oct | L8: Nov | M8: Dec | N8: 2026 | O8: % Total Rev | R8: Input Method | S8: "Even" spread | T8: Growth % | U8: Jan | V8: Feb | W8: Mar | X8: Apr | Y8: May | Z8: Jun | AA8: Jul | AB8: Aug | AC8: Sep | AD8: Oct | AE8: Nov | AF8: Dec | AG8: 2027 | AH8: % Total Rev | AJ8: Fav / (Unfav)
A9: Ordinary Income/Expense
A10: Income
A11: 4000 - Sales
A12: 4100 - Subscription/Platform Fees | B12: 0 | C12: 0 | D12: 0 | E12: 0 | F12: 0 | G12: 0 | H12: 0 | I12: 0 | N12: =SUM(B12:M12) -> 0 | O12: =IFERROR(N12/N$16,"") | R12: Even | T12: 0.05 | U12: =IF($R12="Manual","",IFERROR(IF($R12="YOY Growth",$N12*(1+$T12)/12,$S12/12),"")) -> 0 | V12: =IF($R12="Manual","",IFERROR(IF($R12="YOY Growth",$N12*(1+$T12)/12,$S12/12),"")) -> 0 | W12: =IF($R12="Manual","",IFERROR(IF($R12="YOY Growth",$N12*(1+$T12)/12,$S12/12),"")) -> 0 | X12: =IF($R12="Manual","",IFERROR(IF($R12="YOY Growth",$N12*(1+$T12)/12,$S12/12),"")) -> 0 | Y12: =IF($R12="Manual","",IFERROR(IF($R12="YOY Growth",$N12*(1+$T12)/12,$S12/12),"")) -> 0 | Z12: =IF($R12="Manual","",IFERROR(IF($R12="YOY Growth",$N12*(1+$T12)/12,$S12/12),"")) -> 0 | AA12: =IF($R12="Manual","",IFERROR(IF($R12="YOY Growth",$N12*(1+$T12)/12,$S12/12),"")) -> 0 | AB12: =IF($R12="Manual","",IFERROR(IF($R12="YOY Growth",$N12*(1+$T12)/12,$S12/12),"")) -> 0 | ... AF12: =IF($R12="Manual","",IFERROR(IF($R12="YOY Growth",$N12*(1+$T12)/12,$S12/12),"")) -> 0 | AG12: =SUM(U12:AF12) -> 0 | AH12: =IFERROR(AG12/AG$16,"") | AJ12: =AG12-N12 -> 0
A13: 4500 - Implementation Fees | B13: 0 | C13: 0 | D13: 0 | E13: 0 | F13: 0 | G13: 0 | H13: 0 | I13: 0 | N13: =SUM(B13:M13) -> 0 | O13: =IFERROR(N13/N$16,"") | R13: Even | S13: 0 | T13: 0.05 | U13: =IF($R13="Manual","",IFERROR(IF($R13="YOY Growth",$N13*(1+$T13)/12,$S13/12),"")) -> 0 | V13: =IF($R13="Manual","",IFERROR(IF($R13="YOY Growth",$N13*(1+$T13)/12,$S13/12),"")) -> 0 | W13: =IF($R13="Manual","",IFERROR(IF($R13="YOY Growth",$N13*(1+$T13)/12,$S13/12),"")) -> 0 | X13: =IF($R13="Manual","",IFERROR(IF($R13="YOY Growth",$N13*(1+$T13)/12,$S13/12),"")) -> 0 | Y13: =IF($R13="Manual","",IFERROR(IF($R13="YOY Growth",$N13*(1+$T13)/12,$S13/12),"")) -> 0 | Z13: =IF($R13="Manual","",IFERROR(IF($R13="YOY Growth",$N13*(1+$T13)/12,$S13/12),"")) -> 0 | AA13: =IF($R13="Manual","",IFERROR(IF($R13="YOY Growth",$N13*(1+$T13)/12,$S13/12),"")) -> 0 | AB13: =IF($R13="Manual","",IFERROR(IF($R13="YOY Growth",$N13*(1+$T13)/12,$S13/12),"")) -> 0 | ... AF13: =IF($R13="Manual","",IFERROR(IF($R13="YOY Growth",$N13*(1+$T13)/12,$S13/12),"")) -> 0 | AG13: =SUM(U13:AF13) -> 0 | AH13: =IFERROR(AG13/AG$16,"") | AJ13: =AG13-N13 -> 0
A14: Total - 4000 - Sales | B14: =SUM(B12:B13) -> 0 | C14: =SUM(C12:C13) -> 0 | D14: =SUM(D12:D13) -> 0 | E14: =SUM(E12:E13) -> 0 | F14: =SUM(F12:F13) -> 0 | G14: =SUM(G12:G13) -> 0 | H14: =SUM(H12:H13) -> 0 | I14: =SUM(I12:I13) -> 0 | ... M14: =SUM(M12:M13) -> 0 | N14: =SUM(B14:M14) -> 0 | O14: =SUM(O12:O13) -> 0 | U14: =SUM(U12:U13) -> 0 | V14: =SUM(V12:V13) -> 0 | W14: =SUM(W12:W13) -> 0 | X14: =SUM(X12:X13) -> 0 | Y14: =SUM(Y12:Y13) -> 0 | Z14: =SUM(Z12:Z13) -> 0 | AA14: =SUM(AA12:AA13) -> 0 | AB14: =SUM(AB12:AB13) -> 0 | ... AF14: =SUM(AF12:AF13) -> 0 | AG14: =SUM(U14:AF14) -> 0 | AH14: =SUM(AH12:AH13) -> 0 | AJ14: =AG14-N14 -> 0
A15: 4900 - One-Time Revenue | B15: 0 | C15: 0 | D15: 0 | E15: 0 | F15: 0 | G15: 0 | H15: 0 | I15: 0 | N15: =SUM(B15:M15) -> 0 | O15: =IFERROR(N15/N$16,"") | R15: Even | S15: 0 | T15: 0.05 | U15: =IF($R15="Manual","",IFERROR(IF($R15="YOY Growth",$N15*(1+$T15)/12,$S15/12),"")) -> 0 | V15: =IF($R15="Manual","",IFERROR(IF($R15="YOY Growth",$N15*(1+$T15)/12,$S15/12),"")) -> 0 | W15: =IF($R15="Manual","",IFERROR(IF($R15="YOY Growth",$N15*(1+$T15)/12,$S15/12),"")) -> 0 | X15: =IF($R15="Manual","",IFERROR(IF($R15="YOY Growth",$N15*(1+$T15)/12,$S15/12),"")) -> 0 | Y15: =IF($R15="Manual","",IFERROR(IF($R15="YOY Growth",$N15*(1+$T15)/12,$S15/12),"")) -> 0 | Z15: =IF($R15="Manual","",IFERROR(IF($R15="YOY Growth",$N15*(1+$T15)/12,$S15/12),"")) -> 0 | AA15: =IF($R15="Manual","",IFERROR(IF($R15="YOY Growth",$N15*(1+$T15)/12,$S15/12),"")) -> 0 | AB15: =IF($R15="Manual","",IFERROR(IF($R15="YOY Growth",$N15*(1+$T15)/12,$S15/12),"")) -> 0 | ... AF15: =IF($R15="Manual","",IFERROR(IF($R15="YOY Growth",$N15*(1+$T15)/12,$S15/12),"")) -> 0 | AG15: =SUM(U15:AF15) -> 0 | AH15: =IFERROR(AG15/AG$16,"") | AJ15: =AG15-N15 -> 0
A16: Total - Income | B16: =B14+B15 -> 0 | C16: =C14+C15 -> 0 | D16: =D14+D15 -> 0 | E16: =E14+E15 -> 0 | F16: =F14+F15 -> 0 | G16: =G14+G15 -> 0 | H16: =H14+H15 -> 0 | I16: =I14+I15 -> 0 | ... M16: =M14+M15 -> 0 | N16: =SUM(B16:M16) -> 0 | O16: =SUM(O14:O15) -> 0 | U16: =U14+U15 -> 0 | V16: =V14+V15 -> 0 | W16: =W14+W15 -> 0 | X16: =X14+X15 -> 0 | Y16: =Y14+Y15 -> 0 | Z16: =Z14+Z15 -> 0 | AA16: =AA14+AA15 -> 0 | AB16: =AB14+AB15 -> 0 | ... AF16: =AF14+AF15 -> 0 | AG16: =SUM(U16:AF16) -> 0 | AH16: =SUM(AH14:AH15) -> 0 | AJ16: =AG16-N16 -> 0
A17: Cost Of Sales
A18: 5000 - Robot Production and Deployment
A19: 5010 - SlipBot Depreciation | B19: 0 | C19: 0 | D19: 0 | E19: 0 | F19: 0 | G19: 0 | H19: 0 | I19: 0 | N19: =SUM(B19:M19) -> 0 | O19: =IFERROR(N19/N$16,"") | R19: Even | S19: 0 | T19: 0.05 | U19: =IF($R19="Manual","",IFERROR(IF($R19="YOY Growth",$N19*(1+$T19)/12,$S19/12),"")) -> 0 | V19: =IF($R19="Manual","",IFERROR(IF($R19="YOY Growth",$N19*(1+$T19)/12,$S19/12),"")) -> 0 | W19: =IF($R19="Manual","",IFERROR(IF($R19="YOY Growth",$N19*(1+$T19)/12,$S19/12),"")) -> 0 | X19: =IF($R19="Manual","",IFERROR(IF($R19="YOY Growth",$N19*(1+$T19)/12,$S19/12),"")) -> 0 | Y19: =IF($R19="Manual","",IFERROR(IF($R19="YOY Growth",$N19*(1+$T19)/12,$S19/12),"")) -> 0 | Z19: =IF($R19="Manual","",IFERROR(IF($R19="YOY Growth",$N19*(1+$T19)/12,$S19/12),"")) -> 0 | AA19: =IF($R19="Manual","",IFERROR(IF($R19="YOY Growth",$N19*(1+$T19)/12,$S19/12),"")) -> 0 | AB19: =IF($R19="Manual","",IFERROR(IF($R19="YOY Growth",$N19*(1+$T19)/12,$S19/12),"")) -> 0 | ... AF19: =IF($R19="Manual","",IFERROR(IF($R19="YOY Growth",$N19*(1+$T19)/12,$S19/12),"")) -> 0 | AG19: =SUM(U19:AF19) -> 0 | AH19: =IFERROR(AG19/AG$16,"") | AJ19: =N19-AG19 -> 0
A20: 5011 - SlipLift Depreciation | B20: 0 | C20: 0 | D20: 0 | E20: 0 | F20: 0 | G20: 0 | H20: 0 | I20: 0 | N20: =SUM(B20:M20) -> 0 | O20: =IFERROR(N20/N$16,"") | R20: Even | S20: 0 | T20: 0.05 | U20: =IF($R20="Manual","",IFERROR(IF($R20="YOY Growth",$N20*(1+$T20)/12,$S20/12),"")) -> 0 | V20: =IF($R20="Manual","",IFERROR(IF($R20="YOY Growth",$N20*(1+$T20)/12,$S20/12),"")) -> 0 | W20: =IF($R20="Manual","",IFERROR(IF($R20="YOY Growth",$N20*(1+$T20)/12,$S20/12),"")) -> 0 | X20: =IF($R20="Manual","",IFERROR(IF($R20="YOY Growth",$N20*(1+$T20)/12,$S20/12),"")) -> 0 | Y20: =IF($R20="Manual","",IFERROR(IF($R20="YOY Growth",$N20*(1+$T20)/12,$S20/12),"")) -> 0 | Z20: =IF($R20="Manual","",IFERROR(IF($R20="YOY Growth",$N20*(1+$T20)/12,$S20/12),"")) -> 0 | AA20: =IF($R20="Manual","",IFERROR(IF($R20="YOY Growth",$N20*(1+$T20)/12,$S20/12),"")) -> 0 | AB20: =IF($R20="Manual","",IFERROR(IF($R20="YOY Growth",$N20*(1+$T20)/12,$S20/12),"")) -> 0 | ... AF20: =IF($R20="Manual","",IFERROR(IF($R20="YOY Growth",$N20*(1+$T20)/12,$S20/12),"")) -> 0 | AG20: =SUM(U20:AF20) -> 0 | AH20: =IFERROR(AG20/AG$16,"") | AJ20: =N20-AG20 -> 0
A21: 5012 - SlipCarrier Depreciation | B21: 0 | C21: 0 | D21: 0 | E21: 0 | F21: 0 | G21: 0 | H21: 0 | I21: 0 | N21: =SUM(B21:M21) -> 0 | O21: =IFERROR(N21/N$16,"") | R21: Even | S21: 0 | T21: 0.05 | U21: =IF($R21="Manual","",IFERROR(IF($R21="YOY Growth",$N21*(1+$T21)/12,$S21/12),"")) -> 0 | V21: =IF($R21="Manual","",IFERROR(IF($R21="YOY Growth",$N21*(1+$T21)/12,$S21/12),"")) -> 0 | W21: =IF($R21="Manual","",IFERROR(IF($R21="YOY Growth",$N21*(1+$T21)/12,$S21/12),"")) -> 0 | X21: =IF($R21="Manual","",IFERROR(IF($R21="YOY Growth",$N21*(1+$T21)/12,$S21/12),"")) -> 0 | Y21: =IF($R21="Manual","",IFERROR(IF($R21="YOY Growth",$N21*(1+$T21)/12,$S21/12),"")) -> 0 | Z21: =IF($R21="Manual","",IFERROR(IF($R21="YOY Growth",$N21*(1+$T21)/12,$S21/12),"")) -> 0 | AA21: =IF($R21="Manual","",IFERROR(IF($R21="YOY Growth",$N21*(1+$T21)/12,$S21/12),"")) -> 0 | AB21: =IF($R21="Manual","",IFERROR(IF($R21="YOY Growth",$N21*(1+$T21)/12,$S21/12),"")) -> 0 | ... AF21: =IF($R21="Manual","",IFERROR(IF($R21="YOY Growth",$N21*(1+$T21)/12,$S21/12),"")) -> 0 | AG21: =SUM(U21:AF21) -> 0 | AH21: =IFERROR(AG21/AG$16,"") | AJ21: =N21-AG21 -> 0
A22: 5020 - Robot Peripherals Depreciation | B22: 0 | C22: 0 | D22: 0 | E22: 0 | F22: 0 | G22: 0 | H22: 0 | I22: 0 | N22: =SUM(B22:M22) -> 0 | O22: =IFERROR(N22/N$16,"") | R22: Even | S22: 0 | T22: 0.05 | U22: =IF($R22="Manual","",IFERROR(IF($R22="YOY Growth",$N22*(1+$T22)/12,$S22/12),"")) -> 0 | V22: =IF($R22="Manual","",IFERROR(IF($R22="YOY Growth",$N22*(1+$T22)/12,$S22/12),"")) -> 0 | W22: =IF($R22="Manual","",IFERROR(IF($R22="YOY Growth",$N22*(1+$T22)/12,$S22/12),"")) -> 0 | X22: =IF($R22="Manual","",IFERROR(IF($R22="YOY Growth",$N22*(1+$T22)/12,$S22/12),"")) -> 0 | Y22: =IF($R22="Manual","",IFERROR(IF($R22="YOY Growth",$N22*(1+$T22)/12,$S22/12),"")) -> 0 | Z22: =IF($R22="Manual","",IFERROR(IF($R22="YOY Growth",$N22*(1+$T22)/12,$S22/12),"")) -> 0 | AA22: =IF($R22="Manual","",IFERROR(IF($R22="YOY Growth",$N22*(1+$T22)/12,$S22/12),"")) -> 0 | AB22: =IF($R22="Manual","",IFERROR(IF($R22="YOY Growth",$N22*(1+$T22)/12,$S22/12),"")) -> 0 | ... AF22: =IF($R22="Manual","",IFERROR(IF($R22="YOY Growth",$N22*(1+$T22)/12,$S22/12),"")) -> 0 | AG22: =SUM(U22:AF22) -> 0 | AH22: =IFERROR(AG22/AG$16,"") | AJ22: =N22-AG22 -> 0
A23: 5025 - Freight and Delivery - Production (Summary)
A24: 5025 - Freight and Delivery - Production (Summary) | B24: 376 | C24: 850.7 | D24: 783.62 | E24: 1861.07 | F24: 0 | G24: 0 | H24: 0 | I24: 0 | J24: 0 | K24: 0 | L24: 0 | M24: 0 | N24: =SUM(B24:M24) -> 3871.39 | O24: =IFERROR(N24/N$16,"") | R24: Even | S24: 0 | T24: 0.05 | U24: =IF($R24="Manual","",IFERROR(IF($R24="YOY Growth",$N24*(1+$T24)/12,$S24/12),"")) -> 0 | V24: =IF($R24="Manual","",IFERROR(IF($R24="YOY Growth",$N24*(1+$T24)/12,$S24/12),"")) -> 0 | W24: =IF($R24="Manual","",IFERROR(IF($R24="YOY Growth",$N24*(1+$T24)/12,$S24/12),"")) -> 0 | X24: =IF($R24="Manual","",IFERROR(IF($R24="YOY Growth",$N24*(1+$T24)/12,$S24/12),"")) -> 0 | Y24: =IF($R24="Manual","",IFERROR(IF($R24="YOY Growth",$N24*(1+$T24)/12,$S24/12),"")) -> 0 | Z24: =IF($R24="Manual","",IFERROR(IF($R24="YOY Growth",$N24*(1+$T24)/12,$S24/12),"")) -> 0 | AA24: =IF($R24="Manual","",IFERROR(IF($R24="YOY Growth",$N24*(1+$T24)/12,$S24/12),"")) -> 0 | AB24: =IF($R24="Manual","",IFERROR(IF($R24="YOY Growth",$N24*(1+$T24)/12,$S24/12),"")) -> 0 | ... AF24: =IF($R24="Manual","",IFERROR(IF($R24="YOY Growth",$N24*(1+$T24)/12,$S24/12),"")) -> 0 | AG24: =SUM(U24:AF24) -> 0 | AH24: =IFERROR(AG24/AG$16,"") | AJ24: =N24-AG24 -> 3871.39
A25: 5026 - Freight and Delivery - Production - Expedited | B25: 0 | C25: 0 | D25: 0 | E25: 261.8 | F25: 0 | G25: 0 | H25: 0 | I25: 0 | J25: 0 | K25: 0 | L25: 0 | M25: 0 | N25: =SUM(B25:M25) -> 261.8 | O25: =IFERROR(N25/N$16,"") | R25: Even | S25: 0 | T25: 0.05 | U25: =IF($R25="Manual","",IFERROR(IF($R25="YOY Growth",$N25*(1+$T25)/12,$S25/12),"")) -> 0 | V25: =IF($R25="Manual","",IFERROR(IF($R25="YOY Growth",$N25*(1+$T25)/12,$S25/12),"")) -> 0 | W25: =IF($R25="Manual","",IFERROR(IF($R25="YOY Growth",$N25*(1+$T25)/12,$S25/12),"")) -> 0 | X25: =IF($R25="Manual","",IFERROR(IF($R25="YOY Growth",$N25*(1+$T25)/12,$S25/12),"")) -> 0 | Y25: =IF($R25="Manual","",IFERROR(IF($R25="YOY Growth",$N25*(1+$T25)/12,$S25/12),"")) -> 0 | Z25: =IF($R25="Manual","",IFERROR(IF($R25="YOY Growth",$N25*(1+$T25)/12,$S25/12),"")) -> 0 | AA25: =IF($R25="Manual","",IFERROR(IF($R25="YOY Growth",$N25*(1+$T25)/12,$S25/12),"")) -> 0 | AB25: =IF($R25="Manual","",IFERROR(IF($R25="YOY Growth",$N25*(1+$T25)/12,$S25/12),"")) -> 0 | ... AF25: =IF($R25="Manual","",IFERROR(IF($R25="YOY Growth",$N25*(1+$T25)/12,$S25/12),"")) -> 0 | AG25: =SUM(U25:AF25) -> 0 | AH25: =IFERROR(AG25/AG$16,"") | AJ25: =N25-AG25 -> 261.8
A26: 5027 - Freight and Delivery - Production - Standard | B26: 0 | C26: 0 | D26: 0 | E26: 348.38 | F26: 79.47 | G26: 0 | H26: 0 | I26: 250 | J26: 0 | K26: 0 | L26: 0 | M26: 0 | N26: =SUM(B26:M26) -> 677.85 | O26: =IFERROR(N26/N$16,"") | R26: Even | S26: 0 | T26: 0.05 | U26: =IF($R26="Manual","",IFERROR(IF($R26="YOY Growth",$N26*(1+$T26)/12,$S26/12),"")) -> 0 | V26: =IF($R26="Manual","",IFERROR(IF($R26="YOY Growth",$N26*(1+$T26)/12,$S26/12),"")) -> 0 | W26: =IF($R26="Manual","",IFERROR(IF($R26="YOY Growth",$N26*(1+$T26)/12,$S26/12),"")) -> 0 | X26: =IF($R26="Manual","",IFERROR(IF($R26="YOY Growth",$N26*(1+$T26)/12,$S26/12),"")) -> 0 | Y26: =IF($R26="Manual","",IFERROR(IF($R26="YOY Growth",$N26*(1+$T26)/12,$S26/12),"")) -> 0 | Z26: =IF($R26="Manual","",IFERROR(IF($R26="YOY Growth",$N26*(1+$T26)/12,$S26/12),"")) -> 0 | AA26: =IF($R26="Manual","",IFERROR(IF($R26="YOY Growth",$N26*(1+$T26)/12,$S26/12),"")) -> 0 | AB26: =IF($R26="Manual","",IFERROR(IF($R26="YOY Growth",$N26*(1+$T26)/12,$S26/12),"")) -> 0 | ... AF26: =IF($R26="Manual","",IFERROR(IF($R26="YOY Growth",$N26*(1+$T26)/12,$S26/12),"")) -> 0 | AG26: =SUM(U26:AF26) -> 0 | AH26: =IFERROR(AG26/AG$16,"") | AJ26: =N26-AG26 -> 677.85
A27: Total - 5025 - Freight and Delivery - Production (Summary) | B27: =SUM(B24:B26) -> 376 | C27: =SUM(C24:C26) -> 850.7 | D27: =SUM(D24:D26) -> 783.62 | E27: =SUM(E24:E26) -> 2471.25 | F27: =SUM(F24:F26) -> 79.47 | G27: =SUM(G24:G26) -> 0 | H27: =SUM(H24:H26) -> 0 | I27: =SUM(I24:I26) -> 250 | ... M27: =SUM(M24:M26) -> 0 | N27: =SUM(B27:M27) -> 4811.04 | O27: =IFERROR(N27/N$16,"") | U27: =SUM(U24:U26) -> 0 | V27: =SUM(V24:V26) -> 0 | W27: =SUM(W24:W26) -> 0 | X27: =SUM(X24:X26) -> 0 | Y27: =SUM(Y24:Y26) -> 0 | Z27: =SUM(Z24:Z26) -> 0 | AA27: =SUM(AA24:AA26) -> 0 | AB27: =SUM(AB24:AB26) -> 0 | ... AF27: =SUM(AF24:AF26) -> 0 | AG27: =SUM(U27:AF27) -> 0 | AH27: =IFERROR(AG27/AG$16,"") | AJ27: =N27-AG27 -> 4811.04
A28: 5030 - Production Tools and Supplies | B28: 0 | C28: 0 | D28: 0 | E28: 2186.18 | F28: 0 | G28: 0 | H28: 117.53 | I28: 0 | J28: 0 | K28: 0 | L28: 0 | M28: 0 | N28: =SUM(B28:M28) -> 2303.71 | O28: =IFERROR(N28/N$16,"") | R28: Even | S28: 0 | T28: 0.05 | U28: =IF($R28="Manual","",IFERROR(IF($R28="YOY Growth",$N28*(1+$T28)/12,$S28/12),"")) -> 0 | V28: =IF($R28="Manual","",IFERROR(IF($R28="YOY Growth",$N28*(1+$T28)/12,$S28/12),"")) -> 0 | W28: =IF($R28="Manual","",IFERROR(IF($R28="YOY Growth",$N28*(1+$T28)/12,$S28/12),"")) -> 0 | X28: =IF($R28="Manual","",IFERROR(IF($R28="YOY Growth",$N28*(1+$T28)/12,$S28/12),"")) -> 0 | Y28: =IF($R28="Manual","",IFERROR(IF($R28="YOY Growth",$N28*(1+$T28)/12,$S28/12),"")) -> 0 | Z28: =IF($R28="Manual","",IFERROR(IF($R28="YOY Growth",$N28*(1+$T28)/12,$S28/12),"")) -> 0 | AA28: =IF($R28="Manual","",IFERROR(IF($R28="YOY Growth",$N28*(1+$T28)/12,$S28/12),"")) -> 0 | AB28: =IF($R28="Manual","",IFERROR(IF($R28="YOY Growth",$N28*(1+$T28)/12,$S28/12),"")) -> 0 | ... AF28: =IF($R28="Manual","",IFERROR(IF($R28="YOY Growth",$N28*(1+$T28)/12,$S28/12),"")) -> 0 | AG28: =SUM(U28:AF28) -> 0 | AH28: =IFERROR(AG28/AG$16,"") | AJ28: =N28-AG28 -> 2303.71
A29: 5040 - Freight & Delivery - Deployment | B29: 7000 | C29: 5000.95 | D29: 3522.7 | E29: 3294.47 | F29: 0 | G29: 122.59 | H29: 0 | I29: 3240.99 | J29: 15000 | K29: 10000 | L29: 5000 | M29: 5000 | N29: =SUM(B29:M29) -> 57181.7 | O29: =IFERROR(N29/N$16,"") | R29: Manual | S29: 0 | T29: 0.05 | U29: ='Fld Maint Budget'!B89 -> 45000 | V29: ='Fld Maint Budget'!C89 -> 20000 | W29: ='Fld Maint Budget'!D89 -> 0 | X29: ='Fld Maint Budget'!E89 -> 60000 | Y29: ='Fld Maint Budget'!F89 -> 45000 | Z29: ='Fld Maint Budget'!G89 -> 70000 | AA29: ='Fld Maint Budget'!H89 -> 55000 | AB29: ='Fld Maint Budget'!I89 -> 65000 | ... AF29: ='Fld Maint Budget'!M89 -> 110000 | AG29: =SUM(U29:AF29) -> 765000 | AH29: =IFERROR(AG29/AG$16,"") | AJ29: =N29-AG29 -> -707818.3
A30: 5050 - Travel - Deployment | B30: 0 | C30: 0 | D30: 0 | E30: 0 | F30: 0 | G30: 0 | H30: 911.81 | I30: 1772.23 | J30: 0 | K30: 0 | L30: 0 | M30: 0 | N30: =SUM(B30:M30) -> 2684.04 | O30: =IFERROR(N30/N$16,"") | R30: Manual | S30: 0 | T30: 0.05 | U30: ='Fld Maint Budget'!B90 -> 2279.7 | V30: ='Fld Maint Budget'!C90 -> 1519.8 | W30: ='Fld Maint Budget'!D90 -> 0 | X30: ='Fld Maint Budget'!E90 -> 3495.54 | Y30: ='Fld Maint Budget'!F90 -> 2735.64 | Z30: ='Fld Maint Budget'!G90 -> 3951.48 | AA30: ='Fld Maint Budget'!H90 -> 3495.54 | AB30: ='Fld Maint Budget'!I90 -> 4255.44 | ... AF30: ='Fld Maint Budget'!M90 -> 6991.08 | AG30: =SUM(U30:AF30) -> 46353.9 | AH30: =IFERROR(AG30/AG$16,"") | AJ30: =N30-AG30 -> -43669.86
A31: 5060 - Meals - Deployment | B31: 0 | C31: 0 | D31: 0 | E31: 0 | F31: 0 | G31: 20.14 | H31: 0 | I31: 528.6 | J31: 0 | K31: 0 | L31: 0 | M31: 0 | N31: =SUM(B31:M31) -> 548.74 | O31: =IFERROR(N31/N$16,"") | R31: Even | S31: 0 | T31: 0.05 | U31: =IF($R31="Manual","",IFERROR(IF($R31="YOY Growth",$N31*(1+$T31)/12,$S31/12),"")) -> 0 | V31: =IF($R31="Manual","",IFERROR(IF($R31="YOY Growth",$N31*(1+$T31)/12,$S31/12),"")) -> 0 | W31: =IF($R31="Manual","",IFERROR(IF($R31="YOY Growth",$N31*(1+$T31)/12,$S31/12),"")) -> 0 | X31: =IF($R31="Manual","",IFERROR(IF($R31="YOY Growth",$N31*(1+$T31)/12,$S31/12),"")) -> 0 | Y31: =IF($R31="Manual","",IFERROR(IF($R31="YOY Growth",$N31*(1+$T31)/12,$S31/12),"")) -> 0 | Z31: =IF($R31="Manual","",IFERROR(IF($R31="YOY Growth",$N31*(1+$T31)/12,$S31/12),"")) -> 0 | AA31: =IF($R31="Manual","",IFERROR(IF($R31="YOY Growth",$N31*(1+$T31)/12,$S31/12),"")) -> 0 | AB31: =IF($R31="Manual","",IFERROR(IF($R31="YOY Growth",$N31*(1+$T31)/12,$S31/12),"")) -> 0 | ... AF31: =IF($R31="Manual","",IFERROR(IF($R31="YOY Growth",$N31*(1+$T31)/12,$S31/12),"")) -> 0 | AG31: =SUM(U31:AF31) -> 0 | AH31: =IFERROR(AG31/AG$16,"") | AJ31: =N31-AG31 -> 548.74
A32: 5100 - Labor Expense - Production
A33: 5110 - Salaries and Wages - Production | B33: 0 | C33: 0 | D33: 0 | E33: 0 | F33: 0 | G33: 0 | H33: 0 | I33: 0 | J33: 0 | K33: 0 | L33: 0 | M33: 0 | N33: =SUM(B33:M33) -> 0 | O33: =IFERROR(N33/N$16,"") | AG33: =SUM(U33:AF33) -> 0 | AH33: =IFERROR(AG33/AG$16,"") | AJ33: =N33-AG33 -> 0
A34: 5130 - Payroll Taxes - Production | B34: 0 | C34: 0 | D34: 0 | E34: 0 | F34: 0 | G34: 0 | H34: 0 | I34: 0 | J34: 0 | K34: 0 | L34: 0 | M34: 0 | N34: =SUM(B34:M34) -> 0 | O34: =IFERROR(N34/N$16,"") | AG34: =SUM(U34:AF34) -> 0 | AH34: =IFERROR(AG34/AG$16,"") | AJ34: =N34-AG34 -> 0
A35: 5140 - Benefits - Production | B35: 0 | C35: 0 | D35: 0 | E35: 0 | F35: 0 | G35: 0 | H35: 0 | I35: 0 | J35: 0 | K35: 0 | L35: 0 | M35: 0 | N35: =SUM(B35:M35) -> 0 | O35: =IFERROR(N35/N$16,"") | AG35: =SUM(U35:AF35) -> 0 | AH35: =IFERROR(AG35/AG$16,"") | AJ35: =N35-AG35 -> 0
A36: Total - 5100 - Labor Expense - Production | B36: =SUM(B33:B35) -> 0 | C36: =SUM(C33:C35) -> 0 | D36: =SUM(D33:D35) -> 0 | E36: =SUM(E33:E35) -> 0 | F36: =SUM(F33:F35) -> 0 | G36: =SUM(G33:G35) -> 0 | H36: =SUM(H33:H35) -> 0 | I36: =SUM(I33:I35) -> 0 | ... M36: =SUM(M33:M35) -> 0 | N36: =SUM(B36:M36) -> 0 | O36: =IFERROR(N36/N$16,"") | U36: =SUM(U33:U35) -> 0 | V36: =SUM(V33:V35) -> 0 | W36: =SUM(W33:W35) -> 0 | X36: =SUM(X33:X35) -> 0 | Y36: =SUM(Y33:Y35) -> 0 | Z36: =SUM(Z33:Z35) -> 0 | AA36: =SUM(AA33:AA35) -> 0 | AB36: =SUM(AB33:AB35) -> 0 | ... AF36: =SUM(AF33:AF35) -> 0 | AG36: =SUM(U36:AF36) -> 0 | AH36: =IFERROR(AG36/AG$16,"") | AJ36: =N36-AG36 -> 0
A37: Total - 5000 - Robot Production and Deployment | B37: =B19+B22+B27+B28+B29+B30+B31+B36+B20+B21 -> 7376 | C37: =C19+C22+C27+C28+C29+C30+C31+C36+C20+C21 -> 5851.65 | D37: =D19+D22+D27+D28+D29+D30+D31+D36+D20+D21 -> 4306.32 | E37: =E19+E22+E27+E28+E29+E30+E31+E36+E20+E21 -> 7951.9 | F37: =F19+F22+F27+F28+F29+F30+F31+F36+F20+F21 -> 79.47 | G37: =G19+G22+G27+G28+G29+G30+G31+G36+G20+G21 -> 142.73 | H37: =H19+H22+H27+H28+H29+H30+H31+H36+H20+H21 -> 1029.34 | I37: =I19+I22+I27+I28+I29+I30+I31+I36+I20+I21 -> 5791.82 | ... M37: =M19+M22+M27+M28+M29+M30+M31+M36+M20+M21 -> 5000 | N37: =SUM(B37:M37) -> 67529.23 | O37: =IFERROR(N37/N$16,"") | U37: =U19+U22+U27+U28+U29+U30+U31+U36+U20+U21 -> 47279.7 | V37: =V19+V22+V27+V28+V29+V30+V31+V36+V20+V21 -> 21519.8 | W37: =W19+W22+W27+W28+W29+W30+W31+W36+W20+W21 -> 0 | X37: =X19+X22+X27+X28+X29+X30+X31+X36+X20+X21 -> 63495.54 | Y37: =Y19+Y22+Y27+Y28+Y29+Y30+Y31+Y36+Y20+Y21 -> 47735.64 | Z37: =Z19+Z22+Z27+Z28+Z29+Z30+Z31+Z36+Z20+Z21 -> 73951.48 | AA37: =AA19+AA22+AA27+AA28+AA29+AA30+AA31+AA36+AA20+AA21 -> 58495.54 | AB37: =AB19+AB22+AB27+AB28+AB29+AB30+AB31+AB36+AB20+AB21 -> 69255.44 | ... AF37: =AF19+AF22+AF27+AF28+AF29+AF30+AF31+AF36+AF20+AF21 -> 116991.08 | AG37: =SUM(U37:AF37) -> 811353.9 | AH37: =IFERROR(AG37/AG$16,"") | AJ37: =N37-AG37 -> -743824.67
A38: 5015 - Supplies and Materials | B38: 0 | C38: 0 | D38: 0 | E38: 0 | F38: 0 | G38: -352.47 | H38: 0 | I38: 0 | J38: 0 | K38: 0 | L38: 0 | M38: 0 | N38: =SUM(B38:M38) -> -352.47 | O38: =IFERROR(N38/N$16,"") | R38: Even | S38: 0 | T38: 0.05 | U38: =IF($R38="Manual","",IFERROR(IF($R38="YOY Growth",$N38*(1+$T38)/12,$S38/12),"")) -> 0 | V38: =IF($R38="Manual","",IFERROR(IF($R38="YOY Growth",$N38*(1+$T38)/12,$S38/12),"")) -> 0 | W38: =IF($R38="Manual","",IFERROR(IF($R38="YOY Growth",$N38*(1+$T38)/12,$S38/12),"")) -> 0 | X38: =IF($R38="Manual","",IFERROR(IF($R38="YOY Growth",$N38*(1+$T38)/12,$S38/12),"")) -> 0 | Y38: =IF($R38="Manual","",IFERROR(IF($R38="YOY Growth",$N38*(1+$T38)/12,$S38/12),"")) -> 0 | Z38: =IF($R38="Manual","",IFERROR(IF($R38="YOY Growth",$N38*(1+$T38)/12,$S38/12),"")) -> 0 | AA38: =IF($R38="Manual","",IFERROR(IF($R38="YOY Growth",$N38*(1+$T38)/12,$S38/12),"")) -> 0 | AB38: =IF($R38="Manual","",IFERROR(IF($R38="YOY Growth",$N38*(1+$T38)/12,$S38/12),"")) -> 0 | ... AF38: =IF($R38="Manual","",IFERROR(IF($R38="YOY Growth",$N38*(1+$T38)/12,$S38/12),"")) -> 0 | AG38: =SUM(U38:AF38) -> 0 | AH38: =IFERROR(AG38/AG$16,"") | AJ38: =N38-AG38 -> -352.47
A39: 5028 - Duties & Tariffs - Production | B39: 0 | C39: 0 | D39: 0 | E39: 0 | F39: 0 | G39: 0 | H39: 0 | I39: 0 | J39: 0 | K39: 0 | L39: 0 | M39: 0 | N39: =SUM(B39:M39) -> 0 | O39: =IFERROR(N39/N$16,"") | R39: Even | S39: 0 | T39: 0.05 | U39: =IF($R39="Manual","",IFERROR(IF($R39="YOY Growth",$N39*(1+$T39)/12,$S39/12),"")) -> 0 | V39: =IF($R39="Manual","",IFERROR(IF($R39="YOY Growth",$N39*(1+$T39)/12,$S39/12),"")) -> 0 | W39: =IF($R39="Manual","",IFERROR(IF($R39="YOY Growth",$N39*(1+$T39)/12,$S39/12),"")) -> 0 | X39: =IF($R39="Manual","",IFERROR(IF($R39="YOY Growth",$N39*(1+$T39)/12,$S39/12),"")) -> 0 | Y39: =IF($R39="Manual","",IFERROR(IF($R39="YOY Growth",$N39*(1+$T39)/12,$S39/12),"")) -> 0 | Z39: =IF($R39="Manual","",IFERROR(IF($R39="YOY Growth",$N39*(1+$T39)/12,$S39/12),"")) -> 0 | AA39: =IF($R39="Manual","",IFERROR(IF($R39="YOY Growth",$N39*(1+$T39)/12,$S39/12),"")) -> 0 | AB39: =IF($R39="Manual","",IFERROR(IF($R39="YOY Growth",$N39*(1+$T39)/12,$S39/12),"")) -> 0 | ... AF39: =IF($R39="Manual","",IFERROR(IF($R39="YOY Growth",$N39*(1+$T39)/12,$S39/12),"")) -> 0 | AG39: =SUM(U39:AF39) -> 0 | AH39: =IFERROR(AG39/AG$16,"") | AJ39: =N39-AG39 -> 0
A40: 5029 - Processing Fee - Production | B40: 0 | C40: 0 | D40: 0 | E40: 0 | F40: 0 | G40: 0 | H40: 0 | I40: 0 | J40: 0 | K40: 0 | L40: 0 | M40: 0 | N40: =SUM(B40:M40) -> 0 | O40: =IFERROR(N40/N$16,"") | R40: Even | S40: 0 | T40: 0.05 | U40: =IF($R40="Manual","",IFERROR(IF($R40="YOY Growth",$N40*(1+$T40)/12,$S40/12),"")) -> 0 | V40: =IF($R40="Manual","",IFERROR(IF($R40="YOY Growth",$N40*(1+$T40)/12,$S40/12),"")) -> 0 | W40: =IF($R40="Manual","",IFERROR(IF($R40="YOY Growth",$N40*(1+$T40)/12,$S40/12),"")) -> 0 | X40: =IF($R40="Manual","",IFERROR(IF($R40="YOY Growth",$N40*(1+$T40)/12,$S40/12),"")) -> 0 | Y40: =IF($R40="Manual","",IFERROR(IF($R40="YOY Growth",$N40*(1+$T40)/12,$S40/12),"")) -> 0 | Z40: =IF($R40="Manual","",IFERROR(IF($R40="YOY Growth",$N40*(1+$T40)/12,$S40/12),"")) -> 0 | AA40: =IF($R40="Manual","",IFERROR(IF($R40="YOY Growth",$N40*(1+$T40)/12,$S40/12),"")) -> 0 | AB40: =IF($R40="Manual","",IFERROR(IF($R40="YOY Growth",$N40*(1+$T40)/12,$S40/12),"")) -> 0 | ... AF40: =IF($R40="Manual","",IFERROR(IF($R40="YOY Growth",$N40*(1+$T40)/12,$S40/12),"")) -> 0 | AG40: =SUM(U40:AF40) -> 0 | AH40: =IFERROR(AG40/AG$16,"") | AJ40: =N40-AG40 -> 0
A41: 5070 - Scrap | B41: 0 | C41: 0 | D41: 0 | E41: 0 | F41: 0 | G41: 0 | H41: 0 | I41: 0 | N41: =SUM(B41:M41) -> 0 | O41: =IFERROR(N41/N$16,"") | R41: Even | S41: 0 | T41: 0.05 | U41: =IF($R41="Manual","",IFERROR(IF($R41="YOY Growth",$N41*(1+$T41)/12,$S41/12),"")) -> 0 | V41: =IF($R41="Manual","",IFERROR(IF($R41="YOY Growth",$N41*(1+$T41)/12,$S41/12),"")) -> 0 | W41: =IF($R41="Manual","",IFERROR(IF($R41="YOY Growth",$N41*(1+$T41)/12,$S41/12),"")) -> 0 | X41: =IF($R41="Manual","",IFERROR(IF($R41="YOY Growth",$N41*(1+$T41)/12,$S41/12),"")) -> 0 | Y41: =IF($R41="Manual","",IFERROR(IF($R41="YOY Growth",$N41*(1+$T41)/12,$S41/12),"")) -> 0 | Z41: =IF($R41="Manual","",IFERROR(IF($R41="YOY Growth",$N41*(1+$T41)/12,$S41/12),"")) -> 0 | AA41: =IF($R41="Manual","",IFERROR(IF($R41="YOY Growth",$N41*(1+$T41)/12,$S41/12),"")) -> 0 | AB41: =IF($R41="Manual","",IFERROR(IF($R41="YOY Growth",$N41*(1+$T41)/12,$S41/12),"")) -> 0 | ... AF41: =IF($R41="Manual","",IFERROR(IF($R41="YOY Growth",$N41*(1+$T41)/12,$S41/12),"")) -> 0 | AG41: =SUM(U41:AF41) -> 0 | AH41: =IFERROR(AG41/AG$16,"") | AJ41: =N41-AG41 -> 0
A42: 5201 - Inventory Adjustments | B42: 0 | C42: 0 | D42: 0 | E42: 0 | F42: 0 | G42: 0 | H42: 0 | I42: 0 | J42: 0 | K42: 0 | L42: 0 | M42: 0 | N42: =SUM(B42:M42) -> 0 | O42: =IFERROR(N42/N$16,"") | R42: Even | S42: 0 | T42: 0.05 | U42: =IF($R42="Manual","",IFERROR(IF($R42="YOY Growth",$N42*(1+$T42)/12,$S42/12),"")) -> 0 | V42: =IF($R42="Manual","",IFERROR(IF($R42="YOY Growth",$N42*(1+$T42)/12,$S42/12),"")) -> 0 | W42: =IF($R42="Manual","",IFERROR(IF($R42="YOY Growth",$N42*(1+$T42)/12,$S42/12),"")) -> 0 | X42: =IF($R42="Manual","",IFERROR(IF($R42="YOY Growth",$N42*(1+$T42)/12,$S42/12),"")) -> 0 | Y42: =IF($R42="Manual","",IFERROR(IF($R42="YOY Growth",$N42*(1+$T42)/12,$S42/12),"")) -> 0 | Z42: =IF($R42="Manual","",IFERROR(IF($R42="YOY Growth",$N42*(1+$T42)/12,$S42/12),"")) -> 0 | AA42: =IF($R42="Manual","",IFERROR(IF($R42="YOY Growth",$N42*(1+$T42)/12,$S42/12),"")) -> 0 | AB42: =IF($R42="Manual","",IFERROR(IF($R42="YOY Growth",$N42*(1+$T42)/12,$S42/12),"")) -> 0 | ... AF42: =IF($R42="Manual","",IFERROR(IF($R42="YOY Growth",$N42*(1+$T42)/12,$S42/12),"")) -> 0 | AG42: =SUM(U42:AF42) -> 0 | AH42: =IFERROR(AG42/AG$16,"") | AJ42: =N42-AG42 -> 0
A43: 5300 - Maintenance
A44: 5310 - Contractors - Field | B44: 0 | C44: 0 | D44: 0 | E44: 0 | F44: 19808 | G44: 10009 | H44: 10968.52 | I44: 6116.47 | J44: 40350 | K44: 44270 | L44: 48190 | M44: 52110 | N44: =SUM(B44:M44) -> 231821.99 | O44: =IFERROR(N44/N$16,"") | R44: Manual | T44: 0.05 | U44: ='Fld Maint Budget'!B91 -> 37614 | V44: ='Fld Maint Budget'!C91 -> 37614 | W44: ='Fld Maint Budget'!D91 -> 50004 | X44: ='Fld Maint Budget'!E91 -> 50004 | Y44: ='Fld Maint Budget'!F91 -> 50004 | Z44: ='Fld Maint Budget'!G91 -> 50004 | AA44: ='Fld Maint Budget'!H91 -> 50004 | AB44: ='Fld Maint Budget'!I91 -> 50004 | ... AF44: ='Fld Maint Budget'!M91 -> 50004 | AG44: =SUM(U44:AF44) -> 575268 | AH44: =IFERROR(AG44/AG$16,"") | AJ44: =N44-AG44 -> -343446.01
A45: 5320 - Freight & Delivery - Maintenance | B45: 5823.29 | C45: 256.47 | D45: 1327.17 | E45: 6164.18 | F45: 4983.81 | G45: 7888.65 | H45: 14179.16 | I45: 11260.12 | J45: 5750 | K45: 6000 | L45: 6250 | M45: 6500 | N45: =SUM(B45:M45) -> 76382.85 | O45: =IFERROR(N45/N$16,"") | R45: Manual | S45: 0 | T45: 0.05 | U45: ='Fld Maint Budget'!B92 -> 5185.8217 | V45: ='Fld Maint Budget'!C92 -> 5561.3594 | W45: ='Fld Maint Budget'!D92 -> 5561.3594 | X45: ='Fld Maint Budget'!E92 -> 6594.0881 | Y45: ='Fld Maint Budget'!F92 -> 7251.2791 | Z45: ='Fld Maint Budget'!G92 -> 8190.1234 | AA45: ='Fld Maint Budget'!H92 -> 9035.0832 | AB45: ='Fld Maint Budget'!I92 -> 10067.812 | ... AF45: ='Fld Maint Budget'!M92 -> 15982.531 | AG45: =SUM(U45:AF45) -> 111800.84 | AH45: =IFERROR(AG45/AG$16,"") | AJ45: =N45-AG45 -> -35417.988
A46: 5330 - Maintenance Tools and Supplies | B46: 1378.29 | C46: 1054.59 | D46: 2655.82 | E46: 0 | F46: 1059.27 | G46: 334.92 | H46: 1237.14 | I46: 9400.74 | J46: 1500 | K46: 1500 | L46: 1500 | M46: 1500 | N46: =SUM(B46:M46) -> 23120.77 | O46: =IFERROR(N46/N$16,"") | R46: Manual | S46: 0 | T46: 0.05 | U46: ='Fld Maint Budget'!B93 -> 14024.02 | V46: ='Fld Maint Budget'!C93 -> 9524.02 | W46: ='Fld Maint Budget'!D93 -> 551.6 | X46: ='Fld Maint Budget'!E93 -> 21334.34 | Y46: ='Fld Maint Budget'!F93 -> 16972.24 | Z46: ='Fld Maint Budget'!G93 -> 24310.14 | AA46: ='Fld Maint Budget'!H93 -> 21775.62 | AB46: ='Fld Maint Budget'!I93 -> 26468.68 | ... AF46: ='Fld Maint Budget'!M93 -> 43578.82 | AG46: =SUM(U46:AF46) -> 288069.36 | AH46: =IFERROR(AG46/AG$16,"") | AJ46: =N46-AG46 -> -264948.59
A47: 5340 - Spare Parts | B47: 13329.1 | C47: 5064.23 | D47: 58626.27 | E47: 12810.6 | F47: 28158.41 | G47: 19000.31 | H47: 10810.67 | I47: -8095.66 | J47: 28000 | K47: 28000 | L47: 30000 | M47: 30000 | N47: =SUM(B47:M47) -> 255703.93 | O47: =IFERROR(N47/N$16,"") | R47: Manual | S47: 0 | T47: 0.05 | U47: ='Fld Maint Budget'!B94 -> 48713.618 | V47: ='Fld Maint Budget'!C94 -> 55799.235 | W47: ='Fld Maint Budget'!D94 -> 55799.235 | X47: ='Fld Maint Budget'!E94 -> 75284.682 | Y47: ='Fld Maint Budget'!F94 -> 87684.512 | Z47: ='Fld Maint Budget'!G94 -> 105398.55 | AA47: ='Fld Maint Budget'!H94 -> 121341.19 | AB47: ='Fld Maint Budget'!I94 -> 140826.64 | ... AF47: ='Fld Maint Budget'!M94 -> 252425.11 | AG47: =SUM(U47:AF47) -> 1519864.9 | AH47: =IFERROR(AG47/AG$16,"") | AJ47: =N47-AG47 -> -1264160.9
A48: 5350 - Warehouse | B48: 1000 | C48: 3800 | D48: 4120 | E48: 2500 | F48: 2680 | G48: 2560 | H48: 1240 | I48: 1060 | J48: 3000 | K48: 3000 | L48: 3000 | M48: 3000 | N48: =SUM(B48:M48) -> 30960 | O48: =IFERROR(N48/N$16,"") | R48: Manual | S48: 0 | T48: 0.05 | U48: ='Fld Maint Budget'!B95 -> 3000 | V48: ='Fld Maint Budget'!C95 -> 3000 | W48: ='Fld Maint Budget'!D95 -> 3000 | X48: ='Fld Maint Budget'!E95 -> 3000 | Y48: ='Fld Maint Budget'!F95 -> 3000 | Z48: ='Fld Maint Budget'!G95 -> 3000 | AA48: ='Fld Maint Budget'!H95 -> 3000 | AB48: ='Fld Maint Budget'!I95 -> 3000 | ... AF48: ='Fld Maint Budget'!M95 -> 3000 | AG48: =SUM(U48:AF48) -> 36000 | AH48: =IFERROR(AG48/AG$16,"") | AJ48: =N48-AG48 -> -5040
A49: 5360 - Travel - Maintenance | B49: 1900.25 | C49: 1371.12 | D49: 616.4 | E49: 579.5 | F49: 7011.68 | G49: 4314.54 | H49: 2792.06 | I49: 8642.38 | J49: 5000 | K49: 5000 | L49: 4000 | M49: 4000 | N49: =SUM(B49:M49) -> 45227.93 | O49: =IFERROR(N49/N$16,"") | R49: Manual | S49: 0 | T49: 0.05 | U49: ='Fld Maint Budget'!B96 -> 3992 | V49: ='Fld Maint Budget'!C96 -> 3992 | W49: ='Fld Maint Budget'!D96 -> 3992 | X49: ='Fld Maint Budget'!E96 -> 3992 | Y49: ='Fld Maint Budget'!F96 -> 3992 | Z49: ='Fld Maint Budget'!G96 -> 3992 | AA49: ='Fld Maint Budget'!H96 -> 3992 | AB49: ='Fld Maint Budget'!I96 -> 3992 | ... AF49: ='Fld Maint Budget'!M96 -> 3992 | AG49: =SUM(U49:AF49) -> 47904 | AH49: =IFERROR(AG49/AG$16,"") | AJ49: =N49-AG49 -> -2676.07
A50: 5370 - Meals - Maintenance | B50: 0 | C50: 121.5 | D50: 0 | E50: 0 | F50: 18.64 | G50: 0 | H50: 0 | I50: 0 | J50: 150 | K50: 150 | L50: 150 | M50: 150 | N50: =SUM(B50:M50) -> 740.14 | O50: =IFERROR(N50/N$16,"") | R50: Even | S50: 0 | T50: 0.05 | U50: =IF($R50="Manual","",IFERROR(IF($R50="YOY Growth",$N50*(1+$T50)/12,$S50/12),"")) -> 0 | V50: =IF($R50="Manual","",IFERROR(IF($R50="YOY Growth",$N50*(1+$T50)/12,$S50/12),"")) -> 0 | W50: =IF($R50="Manual","",IFERROR(IF($R50="YOY Growth",$N50*(1+$T50)/12,$S50/12),"")) -> 0 | X50: =IF($R50="Manual","",IFERROR(IF($R50="YOY Growth",$N50*(1+$T50)/12,$S50/12),"")) -> 0 | Y50: =IF($R50="Manual","",IFERROR(IF($R50="YOY Growth",$N50*(1+$T50)/12,$S50/12),"")) -> 0 | Z50: =IF($R50="Manual","",IFERROR(IF($R50="YOY Growth",$N50*(1+$T50)/12,$S50/12),"")) -> 0 | AA50: =IF($R50="Manual","",IFERROR(IF($R50="YOY Growth",$N50*(1+$T50)/12,$S50/12),"")) -> 0 | AB50: =IF($R50="Manual","",IFERROR(IF($R50="YOY Growth",$N50*(1+$T50)/12,$S50/12),"")) -> 0 | ... AF50: =IF($R50="Manual","",IFERROR(IF($R50="YOY Growth",$N50*(1+$T50)/12,$S50/12),"")) -> 0 | AG50: =SUM(U50:AF50) -> 0 | AH50: =IFERROR(AG50/AG$16,"") | AJ50: =N50-AG50 -> 740.14
A51: 5500 - Labor Expense - Field Operations
A52: 5510 - :Salaries and Wages - Field Operations | B52: 41771.03 | C52: 27453.8 | D52: 55703.48 | E52: 77202.08 | F52: 72865.8 | G52: 64701.68 | H52: 82139.24 | I52: 79454.55 | J52: 90000 | K52: 92700 | L52: 95800 | M52: 96900 | N52: =SUM(B52:M52) -> 876691.66 | O52: =IFERROR(N52/N$16,"") | U52: ='Fld Ops Payroll'!F21+'Fld Ops Payroll'!F31+'Fld Ops Payroll'!F43+'Fld Ops Payroll'!F56+'Fld Ops Payroll'!F69+'Fld Ops Payroll'!F76+'Fld Ops Payroll'!F77+'Fld Ops Payroll'!F34+'Fld Ops Payroll'!F46+'Fld Ops Payroll'!F59+'Fld Ops Payroll'!F72 -> 120126.25 | V52: ='Fld Ops Payroll'!G21+'Fld Ops Payroll'!G31+'Fld Ops Payroll'!G43+'Fld Ops Payroll'!G56+'Fld Ops Payroll'!G69+'Fld Ops Payroll'!G76+'Fld Ops Payroll'!G77+'Fld Ops Payroll'!G34+'Fld Ops Payroll'!G46+'Fld Ops Payroll'!G59+'Fld Ops Payroll'!G72 -> 116126.25 | W52: ='Fld Ops Payroll'!H21+'Fld Ops Payroll'!H31+'Fld Ops Payroll'!H43+'Fld Ops Payroll'!H56+'Fld Ops Payroll'!H69+'Fld Ops Payroll'!H76+'Fld Ops Payroll'!H77+'Fld Ops Payroll'!H34+'Fld Ops Payroll'!H46+'Fld Ops Payroll'!H59+'Fld Ops Payroll'!H72 -> 154626.25 | X52: ='Fld Ops Payroll'!I21+'Fld Ops Payroll'!I31+'Fld Ops Payroll'!I43+'Fld Ops Payroll'!I56+'Fld Ops Payroll'!I69+'Fld Ops Payroll'!I76+'Fld Ops Payroll'!I77+'Fld Ops Payroll'!I34+'Fld Ops Payroll'!I46+'Fld Ops Payroll'!I59+'Fld Ops Payroll'!I72 -> 166376.25 | Y52: ='Fld Ops Payroll'!J21+'Fld Ops Payroll'!J31+'Fld Ops Payroll'!J43+'Fld Ops Payroll'!J56+'Fld Ops Payroll'!J69+'Fld Ops Payroll'!J76+'Fld Ops Payroll'!J77+'Fld Ops Payroll'!J34+'Fld Ops Payroll'!J46+'Fld Ops Payroll'!J59+'Fld Ops Payroll'!J72 -> 196626.25 | Z52: ='Fld Ops Payroll'!K21+'Fld Ops Payroll'!K31+'Fld Ops Payroll'!K43+'Fld Ops Payroll'!K56+'Fld Ops Payroll'!K69+'Fld Ops Payroll'!K76+'Fld Ops Payroll'!K77+'Fld Ops Payroll'!K34+'Fld Ops Payroll'!K46+'Fld Ops Payroll'!K59+'Fld Ops Payroll'!K72 -> 222876.25 | AA52: ='Fld Ops Payroll'!L21+'Fld Ops Payroll'!L31+'Fld Ops Payroll'!L43+'Fld Ops Payroll'!L56+'Fld Ops Payroll'!L69+'Fld Ops Payroll'!L76+'Fld Ops Payroll'!L77+'Fld Ops Payroll'!L34+'Fld Ops Payroll'!L46+'Fld Ops Payroll'!L59+'Fld Ops Payroll'!L72 -> 265876.25 | AB52: ='Fld Ops Payroll'!M21+'Fld Ops Payroll'!M31+'Fld Ops Payroll'!M43+'Fld Ops Payroll'!M56+'Fld Ops Payroll'!M69+'Fld Ops Payroll'!M76+'Fld Ops Payroll'!M77+'Fld Ops Payroll'!M34+'Fld Ops Payroll'!M46+'Fld Ops Payroll'!M59+'Fld Ops Payroll'!M72 -> 302626.25 | ... AF52: ='Fld Ops Payroll'!Q21+'Fld Ops Payroll'!Q31+'Fld Ops Payroll'!Q43+'Fld Ops Payroll'!Q56+'Fld Ops Payroll'!Q69+'Fld Ops Payroll'!Q76+'Fld Ops Payroll'!Q77+'Fld Ops Payroll'!Q34+'Fld Ops Payroll'!Q46+'Fld Ops Payroll'!Q59+'Fld Ops Payroll'!Q72 -> 499215.04 | AG52: =SUM(U52:AF52) -> 3238031.4 | AH52: =IFERROR(AG52/AG$16,"") | AJ52: =N52-AG52 -> -2361339.7
A53: 5530 - :Payroll Taxes - Field Operations | B53: 3714.57 | C53: 3251.23 | D53: 3711.25 | E53: 5152.42 | F53: 4827.71 | G53: 4403.72 | H53: 5573.24 | I53: 5853.77 | J53: 5850 | K53: 6026 | L53: 6227 | M53: 6299 | N53: =SUM(B53:M53) -> 60889.91 | O53: =IFERROR(N53/N$16,"") | U53: ='Fld Ops Payroll'!F22+'Fld Ops Payroll'!F32+'Fld Ops Payroll'!F44+'Fld Ops Payroll'!F57+'Fld Ops Payroll'!F70+'Fld Ops Payroll'!F78 -> 7896.585 | V53: ='Fld Ops Payroll'!G22+'Fld Ops Payroll'!G32+'Fld Ops Payroll'!G44+'Fld Ops Payroll'!G57+'Fld Ops Payroll'!G70+'Fld Ops Payroll'!G78 -> 7896.585 | W53: ='Fld Ops Payroll'!H22+'Fld Ops Payroll'!H32+'Fld Ops Payroll'!H44+'Fld Ops Payroll'!H57+'Fld Ops Payroll'!H70+'Fld Ops Payroll'!H78 -> 9834.585 | X53: ='Fld Ops Payroll'!I22+'Fld Ops Payroll'!I32+'Fld Ops Payroll'!I44+'Fld Ops Payroll'!I57+'Fld Ops Payroll'!I70+'Fld Ops Payroll'!I78 -> 10905.585 | Y53: ='Fld Ops Payroll'!J22+'Fld Ops Payroll'!J32+'Fld Ops Payroll'!J44+'Fld Ops Payroll'!J57+'Fld Ops Payroll'!J70+'Fld Ops Payroll'!J78 -> 12690.585 | Z53: ='Fld Ops Payroll'!K22+'Fld Ops Payroll'!K32+'Fld Ops Payroll'!K44+'Fld Ops Payroll'!K57+'Fld Ops Payroll'!K70+'Fld Ops Payroll'!K78 -> 14475.585 | AA53: ='Fld Ops Payroll'!L22+'Fld Ops Payroll'!L32+'Fld Ops Payroll'!L44+'Fld Ops Payroll'!L57+'Fld Ops Payroll'!L70+'Fld Ops Payroll'!L78 -> 17127.585 | AB53: ='Fld Ops Payroll'!M22+'Fld Ops Payroll'!M32+'Fld Ops Payroll'!M44+'Fld Ops Payroll'!M57+'Fld Ops Payroll'!M70+'Fld Ops Payroll'!M78 -> 19626.585 | ... AF53: ='Fld Ops Payroll'!Q22+'Fld Ops Payroll'!Q32+'Fld Ops Payroll'!Q44+'Fld Ops Payroll'!Q57+'Fld Ops Payroll'!Q70+'Fld Ops Payroll'!Q78 -> 32722.623 | AG53: =SUM(U53:AF53) -> 210802.13 | AH53: =IFERROR(AG53/AG$16,"") | AJ53: =N53-AG53 -> -149912.22
A54: 5540 - :Benefits - Field Operations | B54: 30690.72 | C54: 21236.59 | D54: 9448.65 | E54: 12493.8 | F54: 12115.76 | G54: 16324.25 | H54: 13014.13 | I54: 17324.26 | J54: 10800 | K54: 11124 | L54: 11496 | M54: 11628 | N54: =SUM(B54:M54) -> 177696.16 | O54: =IFERROR(N54/N$16,"") | U54: ='Fld Ops Payroll'!F23+'Fld Ops Payroll'!F33+'Fld Ops Payroll'!F45+'Fld Ops Payroll'!F58+'Fld Ops Payroll'!F71+'Fld Ops Payroll'!F79 -> 19044.705 | V54: ='Fld Ops Payroll'!G23+'Fld Ops Payroll'!G33+'Fld Ops Payroll'!G45+'Fld Ops Payroll'!G58+'Fld Ops Payroll'!G71+'Fld Ops Payroll'!G79 -> 19044.705 | W54: ='Fld Ops Payroll'!H23+'Fld Ops Payroll'!H33+'Fld Ops Payroll'!H45+'Fld Ops Payroll'!H58+'Fld Ops Payroll'!H71+'Fld Ops Payroll'!H79 -> 23718.705 | X54: ='Fld Ops Payroll'!I23+'Fld Ops Payroll'!I33+'Fld Ops Payroll'!I45+'Fld Ops Payroll'!I58+'Fld Ops Payroll'!I71+'Fld Ops Payroll'!I79 -> 26301.705 | Y54: ='Fld Ops Payroll'!J23+'Fld Ops Payroll'!J33+'Fld Ops Payroll'!J45+'Fld Ops Payroll'!J58+'Fld Ops Payroll'!J71+'Fld Ops Payroll'!J79 -> 30606.705 | Z54: ='Fld Ops Payroll'!K23+'Fld Ops Payroll'!K33+'Fld Ops Payroll'!K45+'Fld Ops Payroll'!K58+'Fld Ops Payroll'!K71+'Fld Ops Payroll'!K79 -> 34911.705 | AA54: ='Fld Ops Payroll'!L23+'Fld Ops Payroll'!L33+'Fld Ops Payroll'!L45+'Fld Ops Payroll'!L58+'Fld Ops Payroll'!L71+'Fld Ops Payroll'!L79 -> 41307.705 | AB54: ='Fld Ops Payroll'!M23+'Fld Ops Payroll'!M33+'Fld Ops Payroll'!M45+'Fld Ops Payroll'!M58+'Fld Ops Payroll'!M71+'Fld Ops Payroll'!M79 -> 47334.705 | ... AF54: ='Fld Ops Payroll'!Q23+'Fld Ops Payroll'!Q33+'Fld Ops Payroll'!Q45+'Fld Ops Payroll'!Q58+'Fld Ops Payroll'!Q71+'Fld Ops Payroll'!Q79 -> 78919.266 | AG54: =SUM(U54:AF54) -> 508405.14 | AH54: =IFERROR(AG54/AG$16,"") | AJ54: =N54-AG54 -> -330708.98
A55: Total - 5500 - Labor Expense - Field Operations | B55: =SUM(B52:B54) -> 76176.32 | C55: =SUM(C52:C54) -> 51941.62 | D55: =SUM(D52:D54) -> 68863.38 | E55: =SUM(E52:E54) -> 94848.3 | F55: =SUM(F52:F54) -> 89809.27 | G55: =SUM(G52:G54) -> 85429.65 | H55: =SUM(H52:H54) -> 100726.61 | I55: =SUM(I52:I54) -> 102632.58 | ... M55: =SUM(M52:M54) -> 114827 | N55: =SUM(B55:M55) -> 1115277.7 | O55: =IFERROR(N55/N$16,"") | U55: =SUM(U52:U54) -> 147067.54 | V55: =SUM(V52:V54) -> 143067.54 | W55: =SUM(W52:W54) -> 188179.54 | X55: =SUM(X52:X54) -> 203583.54 | Y55: =SUM(Y52:Y54) -> 239923.54 | Z55: =SUM(Z52:Z54) -> 272263.54 | AA55: =SUM(AA52:AA54) -> 324311.54 | AB55: =SUM(AB52:AB54) -> 369587.54 | ... AF55: =SUM(AF52:AF54) -> 610856.93 | AG55: =SUM(U55:AF55) -> 3957238.6 | AH55: =IFERROR(AG55/AG$16,"") | AJ55: =N55-AG55 -> -2841960.9
A56: Total - 5300 - Maintenance | B56: =B44+B45+B46+B47+B48+B49+B50+B55 -> 99607.25 | C56: =C44+C45+C46+C47+C48+C49+C50+C55 -> 63609.53 | D56: =D44+D45+D46+D47+D48+D49+D50+D55 -> 136209.04 | E56: =E44+E45+E46+E47+E48+E49+E50+E55 -> 116902.58 | F56: =F44+F45+F46+F47+F48+F49+F50+F55 -> 153529.08 | G56: =G44+G45+G46+G47+G48+G49+G50+G55 -> 129537.07 | H56: =H44+H45+H46+H47+H48+H49+H50+H55 -> 141954.16 | I56: =I44+I45+I46+I47+I48+I49+I50+I55 -> 131016.63 | ... M56: =M44+M45+M46+M47+M48+M49+M50+M55 -> 212087 | N56: =SUM(B56:M56) -> 1779235.3 | O56: =IFERROR(N56/N$16,"") | U56: =U44+U45+U46+U47+U48+U49+U50+U55 -> 259597 | V56: =V44+V45+V46+V47+V48+V49+V50+V55 -> 258558.15 | W56: =W44+W45+W46+W47+W48+W49+W50+W55 -> 307087.73 | X56: =X44+X45+X46+X47+X48+X49+X50+X55 -> 363792.65 | Y56: =Y44+Y45+Y46+Y47+Y48+Y49+Y50+Y55 -> 408827.57 | Z56: =Z44+Z45+Z46+Z47+Z48+Z49+Z50+Z55 -> 467158.36 | AA56: =AA44+AA45+AA46+AA47+AA48+AA49+AA50+AA55 -> 533459.44 | AB56: =AB44+AB45+AB46+AB47+AB48+AB49+AB50+AB55 -> 603946.67 | ... AF56: =AF44+AF45+AF46+AF47+AF48+AF49+AF50+AF55 -> 979839.39 | AG56: =SUM(U56:AF56) -> 6536145.7 | AH56: =IFERROR(AG56/AG$16,"") | AJ56: =N56-AG56 -> -4756910.4
A57: 5900 - Other COGS
A58: 5920 - Software - COGS | B58: 10955.85 | C58: 11156.17 | D58: 11961.24 | E58: 7055.46 | F58: 12334.88 | G58: 13838.18 | H58: 17445.88 | I58: 13679.97 | J58: 5208 | K58: 5208 | L58: 5208 | M58: 5208 | N58: =SUM(B58:M58) -> 119259.63 | O58: =IFERROR(N58/N$16,"") | R58: Even | S58: 0 | T58: 0.05 | U58: =IF($R58="Manual","",IFERROR(IF($R58="YOY Growth",$N58*(1+$T58)/12,$S58/12),"")) -> 0 | V58: =IF($R58="Manual","",IFERROR(IF($R58="YOY Growth",$N58*(1+$T58)/12,$S58/12),"")) -> 0 | W58: =IF($R58="Manual","",IFERROR(IF($R58="YOY Growth",$N58*(1+$T58)/12,$S58/12),"")) -> 0 | X58: =IF($R58="Manual","",IFERROR(IF($R58="YOY Growth",$N58*(1+$T58)/12,$S58/12),"")) -> 0 | Y58: =IF($R58="Manual","",IFERROR(IF($R58="YOY Growth",$N58*(1+$T58)/12,$S58/12),"")) -> 0 | Z58: =IF($R58="Manual","",IFERROR(IF($R58="YOY Growth",$N58*(1+$T58)/12,$S58/12),"")) -> 0 | AA58: =IF($R58="Manual","",IFERROR(IF($R58="YOY Growth",$N58*(1+$T58)/12,$S58/12),"")) -> 0 | AB58: =IF($R58="Manual","",IFERROR(IF($R58="YOY Growth",$N58*(1+$T58)/12,$S58/12),"")) -> 0 | ... AF58: =IF($R58="Manual","",IFERROR(IF($R58="YOY Growth",$N58*(1+$T58)/12,$S58/12),"")) -> 0 | AG58: =SUM(U58:AF58) -> 0 | AH58: =IFERROR(AG58/AG$16,"") | AJ58: =N58-AG58 -> 119259.63
A59: 5950 - Certification Expense | B59: 0 | C59: 0 | D59: 0 | E59: 0 | F59: 0 | G59: 0 | H59: 1861.34 | I59: 0 | J59: 0 | K59: 0 | L59: 0 | M59: 0 | N59: =SUM(B59:M59) -> 1861.34 | O59: =IFERROR(N59/N$16,"") | R59: Even | S59: 0 | T59: 0.05 | U59: =IF($R59="Manual","",IFERROR(IF($R59="YOY Growth",$N59*(1+$T59)/12,$S59/12),"")) -> 0 | V59: =IF($R59="Manual","",IFERROR(IF($R59="YOY Growth",$N59*(1+$T59)/12,$S59/12),"")) -> 0 | W59: =IF($R59="Manual","",IFERROR(IF($R59="YOY Growth",$N59*(1+$T59)/12,$S59/12),"")) -> 0 | X59: =IF($R59="Manual","",IFERROR(IF($R59="YOY Growth",$N59*(1+$T59)/12,$S59/12),"")) -> 0 | Y59: =IF($R59="Manual","",IFERROR(IF($R59="YOY Growth",$N59*(1+$T59)/12,$S59/12),"")) -> 0 | Z59: =IF($R59="Manual","",IFERROR(IF($R59="YOY Growth",$N59*(1+$T59)/12,$S59/12),"")) -> 0 | AA59: =IF($R59="Manual","",IFERROR(IF($R59="YOY Growth",$N59*(1+$T59)/12,$S59/12),"")) -> 0 | AB59: =IF($R59="Manual","",IFERROR(IF($R59="YOY Growth",$N59*(1+$T59)/12,$S59/12),"")) -> 0 | ... AF59: =IF($R59="Manual","",IFERROR(IF($R59="YOY Growth",$N59*(1+$T59)/12,$S59/12),"")) -> 0 | AG59: =SUM(U59:AF59) -> 0 | AH59: =IFERROR(AG59/AG$16,"") | AJ59: =N59-AG59 -> 1861.34
A60: 5980 - Employee Meals | B60: 0 | C60: 47.22 | D60: 0 | E60: 0 | F60: 0 | G60: 0 | H60: 0 | I60: 0 | J60: 0 | K60: 0 | L60: 0 | M60: 0 | N60: =SUM(B60:M60) -> 47.22 | O60: =IFERROR(N60/N$16,"") | R60: Even | S60: 0 | T60: 0.05 | U60: =IF($R60="Manual","",IFERROR(IF($R60="YOY Growth",$N60*(1+$T60)/12,$S60/12),"")) -> 0 | V60: =IF($R60="Manual","",IFERROR(IF($R60="YOY Growth",$N60*(1+$T60)/12,$S60/12),"")) -> 0 | W60: =IF($R60="Manual","",IFERROR(IF($R60="YOY Growth",$N60*(1+$T60)/12,$S60/12),"")) -> 0 | X60: =IF($R60="Manual","",IFERROR(IF($R60="YOY Growth",$N60*(1+$T60)/12,$S60/12),"")) -> 0 | Y60: =IF($R60="Manual","",IFERROR(IF($R60="YOY Growth",$N60*(1+$T60)/12,$S60/12),"")) -> 0 | Z60: =IF($R60="Manual","",IFERROR(IF($R60="YOY Growth",$N60*(1+$T60)/12,$S60/12),"")) -> 0 | AA60: =IF($R60="Manual","",IFERROR(IF($R60="YOY Growth",$N60*(1+$T60)/12,$S60/12),"")) -> 0 | AB60: =IF($R60="Manual","",IFERROR(IF($R60="YOY Growth",$N60*(1+$T60)/12,$S60/12),"")) -> 0 | ... AF60: =IF($R60="Manual","",IFERROR(IF($R60="YOY Growth",$N60*(1+$T60)/12,$S60/12),"")) -> 0 | AG60: =SUM(U60:AF60) -> 0 | AH60: =IFERROR(AG60/AG$16,"") | AJ60: =N60-AG60 -> 47.22
A61: Total - 5900 - Other COGS | B61: =SUM(B58:B60) -> 10955.85 | C61: =SUM(C58:C60) -> 11203.39 | D61: =SUM(D58:D60) -> 11961.24 | E61: =SUM(E58:E60) -> 7055.46 | F61: =SUM(F58:F60) -> 12334.88 | G61: =SUM(G58:G60) -> 13838.18 | H61: =SUM(H58:H60) -> 19307.22 | I61: =SUM(I58:I60) -> 13679.97 | ... M61: =SUM(M58:M60) -> 5208 | N61: =SUM(B61:M61) -> 121168.19 | O61: =IFERROR(N61/N$16,"") | U61: =SUM(U58:U60) -> 0 | V61: =SUM(V58:V60) -> 0 | W61: =SUM(W58:W60) -> 0 | X61: =SUM(X58:X60) -> 0 | Y61: =SUM(Y58:Y60) -> 0 | Z61: =SUM(Z58:Z60) -> 0 | AA61: =SUM(AA58:AA60) -> 0 | AB61: =SUM(AB58:AB60) -> 0 | ... AF61: =SUM(AF58:AF60) -> 0 | AG61: =SUM(U61:AF61) -> 0 | AH61: =IFERROR(AG61/AG$16,"") | AJ61: =N61-AG61 -> 121168.19
A62: 5990 - Purchase Discounts | B62: 0 | C62: 0 | D62: 0 | E62: 0 | F62: 0 | G62: 0 | H62: 0 | I62: 0 | J62: 0 | K62: 0 | L62: 0 | M62: 0 | N62: =SUM(B62:M62) -> 0 | O62: =IFERROR(N62/N$16,"") | R62: Even | S62: 0 | T62: 0.05 | U62: =IF($R62="Manual","",IFERROR(IF($R62="YOY Growth",$N62*(1+$T62)/12,$S62/12),"")) -> 0 | V62: =IF($R62="Manual","",IFERROR(IF($R62="YOY Growth",$N62*(1+$T62)/12,$S62/12),"")) -> 0 | W62: =IF($R62="Manual","",IFERROR(IF($R62="YOY Growth",$N62*(1+$T62)/12,$S62/12),"")) -> 0 | X62: =IF($R62="Manual","",IFERROR(IF($R62="YOY Growth",$N62*(1+$T62)/12,$S62/12),"")) -> 0 | Y62: =IF($R62="Manual","",IFERROR(IF($R62="YOY Growth",$N62*(1+$T62)/12,$S62/12),"")) -> 0 | Z62: =IF($R62="Manual","",IFERROR(IF($R62="YOY Growth",$N62*(1+$T62)/12,$S62/12),"")) -> 0 | AA62: =IF($R62="Manual","",IFERROR(IF($R62="YOY Growth",$N62*(1+$T62)/12,$S62/12),"")) -> 0 | AB62: =IF($R62="Manual","",IFERROR(IF($R62="YOY Growth",$N62*(1+$T62)/12,$S62/12),"")) -> 0 | ... AF62: =IF($R62="Manual","",IFERROR(IF($R62="YOY Growth",$N62*(1+$T62)/12,$S62/12),"")) -> 0 | AG62: =SUM(U62:AF62) -> 0 | AH62: =IFERROR(AG62/AG$16,"") | AJ62: =N62-AG62 -> 0
A63: Total - Cost Of Sales | B63: =B37+B38+B39+B40+B41+B42+B56+B61+B62 -> 117939.1 | C63: =C37+C38+C39+C40+C41+C42+C56+C61+C62 -> 80664.57 | D63: =D37+D38+D39+D40+D41+D42+D56+D61+D62 -> 152476.6 | E63: =E37+E38+E39+E40+E41+E42+E56+E61+E62 -> 131909.94 | F63: =F37+F38+F39+F40+F41+F42+F56+F61+F62 -> 165943.43 | G63: =G37+G38+G39+G40+G41+G42+G56+G61+G62 -> 143165.51 | H63: =H37+H38+H39+H40+H41+H42+H56+H61+H62 -> 162290.72 | I63: =I37+I38+I39+I40+I41+I42+I56+I61+I62 -> 150488.42 | ... M63: =M37+M38+M39+M40+M41+M42+M56+M61+M62 -> 222295 | N63: =SUM(B63:M63) -> 1967580.3 | O63: =IFERROR(N63/N$16,"") | U63: =U37+U38+U39+U40+U41+U42+U56+U61+U62 -> 306876.7 | V63: =V37+V38+V39+V40+V41+V42+V56+V61+V62 -> 280077.95 | W63: =W37+W38+W39+W40+W41+W42+W56+W61+W62 -> 307087.73 | X63: =X37+X38+X39+X40+X41+X42+X56+X61+X62 -> 427288.19 | Y63: =Y37+Y38+Y39+Y40+Y41+Y42+Y56+Y61+Y62 -> 456563.21 | Z63: =Z37+Z38+Z39+Z40+Z41+Z42+Z56+Z61+Z62 -> 541109.84 | AA63: =AA37+AA38+AA39+AA40+AA41+AA42+AA56+AA61+AA62 -> 591954.98 | AB63: =AB37+AB38+AB39+AB40+AB41+AB42+AB56+AB61+AB62 -> 673202.11 | ... AF63: =AF37+AF38+AF39+AF40+AF41+AF42+AF56+AF61+AF62 -> 1096830.5 | AG63: =SUM(U63:AF63) -> 7347499.6 | AH63: =IFERROR(AG63/AG$16,"") | AJ63: =N63-AG63 -> -5379919.3
A64: Gross Profit | B64: =B16-B63 -> -117939.1 | C64: =C16-C63 -> -80664.57 | D64: =D16-D63 -> -152476.6 | E64: =E16-E63 -> -131909.94 | F64: =F16-F63 -> -165943.43 | G64: =G16-G63 -> -143165.51 | H64: =H16-H63 -> -162290.72 | I64: =I16-I63 -> -150488.42 | ... M64: =M16-M63 -> -222295 | N64: =SUM(B64:M64) -> -1967580.3 | O64: =IFERROR(N64/N$16,"") | U64: =U16-U63 -> -306876.7 | V64: =V16-V63 -> -280077.95 | W64: =W16-W63 -> -307087.73 | X64: =X16-X63 -> -427288.19 | Y64: =Y16-Y63 -> -456563.21 | Z64: =Z16-Z63 -> -541109.84 | AA64: =AA16-AA63 -> -591954.98 | AB64: =AB16-AB63 -> -673202.11 | ... AF64: =AF16-AF63 -> -1096830.5 | AG64: =SUM(U64:AF64) -> -7347499.6 | AH64: =IFERROR(AG64/AG$16,"") | AJ64: =AG64-N64 -> -5379919.3
A65: Expense
A66: 6000 - Labor Expense - SG&A
A67: 6610 - Salaries and Wages - SG&A | B67: 28787.31 | C67: 8716.01 | D67: 13071.44 | E67: 0 | F67: 0 | G67: 0 | H67: 0 | I67: 0 | J67: 0 | K67: 0 | L67: 0 | M67: 0 | N67: =SUM(B67:M67) -> 50574.76 | O67: =IFERROR(N67/N$16,"") | AG67: =SUM(U67:AF67) -> 0 | AH67: =IFERROR(AG67/AG$16,"") | AJ67: =N67-AG67 -> 50574.76
A68: 6630 - Payroll Taxes - SG&A | B68: 2063.17 | C68: 0 | D68: 1025.96 | E68: 0 | F68: 0 | G68: 0 | H68: 0 | I68: 0 | J68: 0 | K68: 0 | L68: 0 | M68: 0 | N68: =SUM(B68:M68) -> 3089.13 | O68: =IFERROR(N68/N$16,"") | AG68: =SUM(U68:AF68) -> 0 | AH68: =IFERROR(AG68/AG$16,"") | AJ68: =N68-AG68 -> 3089.13
A69: 6640 - Benefits - SG&A | B69: 167.72 | C69: 413.16 | D69: -353.62 | E69: 0 | F69: 0 | G69: 0 | H69: 0 | I69: 0 | J69: 0 | K69: 0 | L69: 0 | M69: 0 | N69: =SUM(B69:M69) -> 227.26 | O69: =IFERROR(N69/N$16,"") | AG69: =SUM(U69:AF69) -> 0 | AH69: =IFERROR(AG69/AG$16,"") | AJ69: =N69-AG69 -> 227.26
A70: 6650 - Commissions - SG&A | B70: 0 | C70: 0 | D70: 0 | E70: 0 | F70: 0 | G70: 0 | H70: 0 | I70: 0 | J70: 0 | K70: 0 | L70: 0 | M70: 0 | N70: =SUM(B70:M70) -> 0 | O70: =IFERROR(N70/N$16,"") | R70: Even | S70: 0 | T70: 0.05 | U70: =IF($R70="Manual","",IFERROR(IF($R70="YOY Growth",$N70*(1+$T70)/12,$S70/12),"")) -> 0 | V70: =IF($R70="Manual","",IFERROR(IF($R70="YOY Growth",$N70*(1+$T70)/12,$S70/12),"")) -> 0 | W70: =IF($R70="Manual","",IFERROR(IF($R70="YOY Growth",$N70*(1+$T70)/12,$S70/12),"")) -> 0 | X70: =IF($R70="Manual","",IFERROR(IF($R70="YOY Growth",$N70*(1+$T70)/12,$S70/12),"")) -> 0 | Y70: =IF($R70="Manual","",IFERROR(IF($R70="YOY Growth",$N70*(1+$T70)/12,$S70/12),"")) -> 0 | Z70: =IF($R70="Manual","",IFERROR(IF($R70="YOY Growth",$N70*(1+$T70)/12,$S70/12),"")) -> 0 | AA70: =IF($R70="Manual","",IFERROR(IF($R70="YOY Growth",$N70*(1+$T70)/12,$S70/12),"")) -> 0 | AB70: =IF($R70="Manual","",IFERROR(IF($R70="YOY Growth",$N70*(1+$T70)/12,$S70/12),"")) -> 0 | ... AF70: =IF($R70="Manual","",IFERROR(IF($R70="YOY Growth",$N70*(1+$T70)/12,$S70/12),"")) -> 0 | AG70: =SUM(U70:AF70) -> 0 | AH70: =IFERROR(AG70/AG$16,"") | AJ70: =N70-AG70 -> 0
A71: 6660 - Recruiting | B71: 0 | C71: 0 | D71: 0 | E71: 0 | F71: 0 | G71: 0 | H71: 0 | I71: 0 | J71: 0 | K71: 0 | L71: 0 | M71: 0 | N71: =SUM(B71:M71) -> 0 | O71: =IFERROR(N71/N$16,"") | R71: Even | S71: 0 | T71: 0.05 | U71: =IF($R71="Manual","",IFERROR(IF($R71="YOY Growth",$N71*(1+$T71)/12,$S71/12),"")) -> 0 | V71: =IF($R71="Manual","",IFERROR(IF($R71="YOY Growth",$N71*(1+$T71)/12,$S71/12),"")) -> 0 | W71: =IF($R71="Manual","",IFERROR(IF($R71="YOY Growth",$N71*(1+$T71)/12,$S71/12),"")) -> 0 | X71: =IF($R71="Manual","",IFERROR(IF($R71="YOY Growth",$N71*(1+$T71)/12,$S71/12),"")) -> 0 | Y71: =IF($R71="Manual","",IFERROR(IF($R71="YOY Growth",$N71*(1+$T71)/12,$S71/12),"")) -> 0 | Z71: =IF($R71="Manual","",IFERROR(IF($R71="YOY Growth",$N71*(1+$T71)/12,$S71/12),"")) -> 0 | AA71: =IF($R71="Manual","",IFERROR(IF($R71="YOY Growth",$N71*(1+$T71)/12,$S71/12),"")) -> 0 | AB71: =IF($R71="Manual","",IFERROR(IF($R71="YOY Growth",$N71*(1+$T71)/12,$S71/12),"")) -> 0 | ... AF71: =IF($R71="Manual","",IFERROR(IF($R71="YOY Growth",$N71*(1+$T71)/12,$S71/12),"")) -> 0 | AG71: =SUM(U71:AF71) -> 0 | AH71: =IFERROR(AG71/AG$16,"") | AJ71: =N71-AG71 -> 0
A72: 6670 - Stock Compensation Expense | B72: 0 | C72: 0 | D72: 0 | E72: 0 | F72: 0 | G72: 0 | H72: 0 | I72: 0 | J72: 0 | K72: 0 | L72: 0 | M72: 0 | N72: =SUM(B72:M72) -> 0 | O72: =IFERROR(N72/N$16,"") | R72: Even | S72: 0 | T72: 0.05 | U72: =IF($R72="Manual","",IFERROR(IF($R72="YOY Growth",$N72*(1+$T72)/12,$S72/12),"")) -> 0 | V72: =IF($R72="Manual","",IFERROR(IF($R72="YOY Growth",$N72*(1+$T72)/12,$S72/12),"")) -> 0 | W72: =IF($R72="Manual","",IFERROR(IF($R72="YOY Growth",$N72*(1+$T72)/12,$S72/12),"")) -> 0 | X72: =IF($R72="Manual","",IFERROR(IF($R72="YOY Growth",$N72*(1+$T72)/12,$S72/12),"")) -> 0 | Y72: =IF($R72="Manual","",IFERROR(IF($R72="YOY Growth",$N72*(1+$T72)/12,$S72/12),"")) -> 0 | Z72: =IF($R72="Manual","",IFERROR(IF($R72="YOY Growth",$N72*(1+$T72)/12,$S72/12),"")) -> 0 | AA72: =IF($R72="Manual","",IFERROR(IF($R72="YOY Growth",$N72*(1+$T72)/12,$S72/12),"")) -> 0 | AB72: =IF($R72="Manual","",IFERROR(IF($R72="YOY Growth",$N72*(1+$T72)/12,$S72/12),"")) -> 0 | ... AF72: =IF($R72="Manual","",IFERROR(IF($R72="YOY Growth",$N72*(1+$T72)/12,$S72/12),"")) -> 0 | AG72: =SUM(U72:AF72) -> 0 | AH72: =IFERROR(AG72/AG$16,"") | AJ72: =N72-AG72 -> 0
A73: Total - 6000 - Labor Expense - SG&A | B73: =SUM(B67:B72) -> 31018.2 | C73: =SUM(C67:C72) -> 9129.17 | D73: =SUM(D67:D72) -> 13743.78 | E73: =SUM(E67:E72) -> 0 | F73: =SUM(F67:F72) -> 0 | G73: =SUM(G67:G72) -> 0 | H73: =SUM(H67:H72) -> 0 | I73: =SUM(I67:I72) -> 0 | ... M73: =SUM(M67:M72) -> 0 | N73: =SUM(B73:M73) -> 53891.15 | O73: =IFERROR(N73/N$16,"") | U73: =SUM(U67:U72) -> 0 | V73: =SUM(V67:V72) -> 0 | W73: =SUM(W67:W72) -> 0 | X73: =SUM(X67:X72) -> 0 | Y73: =SUM(Y67:Y72) -> 0 | Z73: =SUM(Z67:Z72) -> 0 | AA73: =SUM(AA67:AA72) -> 0 | AB73: =SUM(AB67:AB72) -> 0 | ... AF73: =SUM(AF67:AF72) -> 0 | AG73: =SUM(U73:AF73) -> 0 | AH73: =IFERROR(AG73/AG$16,"") | AJ73: =N73-AG73 -> 53891.15
A74: 6100 - Travel | B74: 11.96 | C74: 9.99 | D74: 960.43 | E74: 1228.86 | F74: 2504.31 | G74: 3441.65 | H74: 8082.14 | I74: 666.92 | J74: 2500 | K74: 2500 | L74: 2500 | M74: 2500 | N74: =SUM(B74:M74) -> 26906.26 | O74: =IFERROR(N74/N$16,"") | R74: Even | S74: 0 | T74: 0.05 | U74: =IF($R74="Manual","",IFERROR(IF($R74="YOY Growth",$N74*(1+$T74)/12,$S74/12),"")) -> 0 | V74: =IF($R74="Manual","",IFERROR(IF($R74="YOY Growth",$N74*(1+$T74)/12,$S74/12),"")) -> 0 | W74: =IF($R74="Manual","",IFERROR(IF($R74="YOY Growth",$N74*(1+$T74)/12,$S74/12),"")) -> 0 | X74: =IF($R74="Manual","",IFERROR(IF($R74="YOY Growth",$N74*(1+$T74)/12,$S74/12),"")) -> 0 | Y74: =IF($R74="Manual","",IFERROR(IF($R74="YOY Growth",$N74*(1+$T74)/12,$S74/12),"")) -> 0 | Z74: =IF($R74="Manual","",IFERROR(IF($R74="YOY Growth",$N74*(1+$T74)/12,$S74/12),"")) -> 0 | AA74: =IF($R74="Manual","",IFERROR(IF($R74="YOY Growth",$N74*(1+$T74)/12,$S74/12),"")) -> 0 | AB74: =IF($R74="Manual","",IFERROR(IF($R74="YOY Growth",$N74*(1+$T74)/12,$S74/12),"")) -> 0 | ... AF74: =IF($R74="Manual","",IFERROR(IF($R74="YOY Growth",$N74*(1+$T74)/12,$S74/12),"")) -> 0 | AG74: =SUM(U74:AF74) -> 0 | AH74: =IFERROR(AG74/AG$16,"") | AJ74: =N74-AG74 -> 26906.26
A75: 6110 - Travel Meals | B75: 0 | C75: 0 | D75: 0 | E75: 139.29 | F75: 0 | G75: -147.89 | H75: 0 | I75: 0 | J75: 150 | K75: 150 | L75: 150 | M75: 150 | N75: =SUM(B75:M75) -> 591.4 | O75: =IFERROR(N75/N$16,"") | R75: Even | S75: 0 | T75: 0.05 | U75: =IF($R75="Manual","",IFERROR(IF($R75="YOY Growth",$N75*(1+$T75)/12,$S75/12),"")) -> 0 | V75: =IF($R75="Manual","",IFERROR(IF($R75="YOY Growth",$N75*(1+$T75)/12,$S75/12),"")) -> 0 | W75: =IF($R75="Manual","",IFERROR(IF($R75="YOY Growth",$N75*(1+$T75)/12,$S75/12),"")) -> 0 | X75: =IF($R75="Manual","",IFERROR(IF($R75="YOY Growth",$N75*(1+$T75)/12,$S75/12),"")) -> 0 | Y75: =IF($R75="Manual","",IFERROR(IF($R75="YOY Growth",$N75*(1+$T75)/12,$S75/12),"")) -> 0 | Z75: =IF($R75="Manual","",IFERROR(IF($R75="YOY Growth",$N75*(1+$T75)/12,$S75/12),"")) -> 0 | AA75: =IF($R75="Manual","",IFERROR(IF($R75="YOY Growth",$N75*(1+$T75)/12,$S75/12),"")) -> 0 | AB75: =IF($R75="Manual","",IFERROR(IF($R75="YOY Growth",$N75*(1+$T75)/12,$S75/12),"")) -> 0 | ... AF75: =IF($R75="Manual","",IFERROR(IF($R75="YOY Growth",$N75*(1+$T75)/12,$S75/12),"")) -> 0 | AG75: =SUM(U75:AF75) -> 0 | AH75: =IFERROR(AG75/AG$16,"") | AJ75: =N75-AG75 -> 591.4
A76: 6120 - Meals and Entertainment | B76: 0 | C76: 0 | D76: 256.68 | E76: 655.57 | F76: 0 | G76: 0 | H76: 0 | I76: 0 | J76: 200 | K76: 200 | L76: 200 | M76: 200 | N76: =SUM(B76:M76) -> 1712.25 | O76: =IFERROR(N76/N$16,"") | R76: Even | S76: 0 | T76: 0.05 | U76: =IF($R76="Manual","",IFERROR(IF($R76="YOY Growth",$N76*(1+$T76)/12,$S76/12),"")) -> 0 | V76: =IF($R76="Manual","",IFERROR(IF($R76="YOY Growth",$N76*(1+$T76)/12,$S76/12),"")) -> 0 | W76: =IF($R76="Manual","",IFERROR(IF($R76="YOY Growth",$N76*(1+$T76)/12,$S76/12),"")) -> 0 | X76: =IF($R76="Manual","",IFERROR(IF($R76="YOY Growth",$N76*(1+$T76)/12,$S76/12),"")) -> 0 | Y76: =IF($R76="Manual","",IFERROR(IF($R76="YOY Growth",$N76*(1+$T76)/12,$S76/12),"")) -> 0 | Z76: =IF($R76="Manual","",IFERROR(IF($R76="YOY Growth",$N76*(1+$T76)/12,$S76/12),"")) -> 0 | AA76: =IF($R76="Manual","",IFERROR(IF($R76="YOY Growth",$N76*(1+$T76)/12,$S76/12),"")) -> 0 | AB76: =IF($R76="Manual","",IFERROR(IF($R76="YOY Growth",$N76*(1+$T76)/12,$S76/12),"")) -> 0 | ... AF76: =IF($R76="Manual","",IFERROR(IF($R76="YOY Growth",$N76*(1+$T76)/12,$S76/12),"")) -> 0 | AG76: =SUM(U76:AF76) -> 0 | AH76: =IFERROR(AG76/AG$16,"") | AJ76: =N76-AG76 -> 1712.25
A77: 6200 - Advertising | B77: 0 | C77: 0 | D77: 0 | E77: 0 | F77: 0 | G77: 0 | H77: 0 | I77: 0 | J77: 0 | K77: 0 | L77: 0 | M77: 0 | N77: =SUM(B77:M77) -> 0 | O77: =IFERROR(N77/N$16,"") | R77: Even | S77: 0 | T77: 0.05 | U77: =IF($R77="Manual","",IFERROR(IF($R77="YOY Growth",$N77*(1+$T77)/12,$S77/12),"")) -> 0 | V77: =IF($R77="Manual","",IFERROR(IF($R77="YOY Growth",$N77*(1+$T77)/12,$S77/12),"")) -> 0 | W77: =IF($R77="Manual","",IFERROR(IF($R77="YOY Growth",$N77*(1+$T77)/12,$S77/12),"")) -> 0 | X77: =IF($R77="Manual","",IFERROR(IF($R77="YOY Growth",$N77*(1+$T77)/12,$S77/12),"")) -> 0 | Y77: =IF($R77="Manual","",IFERROR(IF($R77="YOY Growth",$N77*(1+$T77)/12,$S77/12),"")) -> 0 | Z77: =IF($R77="Manual","",IFERROR(IF($R77="YOY Growth",$N77*(1+$T77)/12,$S77/12),"")) -> 0 | AA77: =IF($R77="Manual","",IFERROR(IF($R77="YOY Growth",$N77*(1+$T77)/12,$S77/12),"")) -> 0 | AB77: =IF($R77="Manual","",IFERROR(IF($R77="YOY Growth",$N77*(1+$T77)/12,$S77/12),"")) -> 0 | ... AF77: =IF($R77="Manual","",IFERROR(IF($R77="YOY Growth",$N77*(1+$T77)/12,$S77/12),"")) -> 0 | AG77: =SUM(U77:AF77) -> 0 | AH77: =IFERROR(AG77/AG$16,"") | AJ77: =N77-AG77 -> 0
A78: 6210 - Marketing Expense | B78: 0 | C78: 0 | D78: 0 | E78: 0 | F78: 0 | G78: 0 | H78: 0 | I78: 0 | J78: 0 | K78: 0 | L78: 0 | M78: 0 | N78: =SUM(B78:M78) -> 0 | O78: =IFERROR(N78/N$16,"") | R78: Even | S78: 0 | T78: 0.05 | U78: =IF($R78="Manual","",IFERROR(IF($R78="YOY Growth",$N78*(1+$T78)/12,$S78/12),"")) -> 0 | V78: =IF($R78="Manual","",IFERROR(IF($R78="YOY Growth",$N78*(1+$T78)/12,$S78/12),"")) -> 0 | W78: =IF($R78="Manual","",IFERROR(IF($R78="YOY Growth",$N78*(1+$T78)/12,$S78/12),"")) -> 0 | X78: =IF($R78="Manual","",IFERROR(IF($R78="YOY Growth",$N78*(1+$T78)/12,$S78/12),"")) -> 0 | Y78: =IF($R78="Manual","",IFERROR(IF($R78="YOY Growth",$N78*(1+$T78)/12,$S78/12),"")) -> 0 | Z78: =IF($R78="Manual","",IFERROR(IF($R78="YOY Growth",$N78*(1+$T78)/12,$S78/12),"")) -> 0 | AA78: =IF($R78="Manual","",IFERROR(IF($R78="YOY Growth",$N78*(1+$T78)/12,$S78/12),"")) -> 0 | AB78: =IF($R78="Manual","",IFERROR(IF($R78="YOY Growth",$N78*(1+$T78)/12,$S78/12),"")) -> 0 | ... AF78: =IF($R78="Manual","",IFERROR(IF($R78="YOY Growth",$N78*(1+$T78)/12,$S78/12),"")) -> 0 | AG78: =SUM(U78:AF78) -> 0 | AH78: =IFERROR(AG78/AG$16,"") | AJ78: =N78-AG78 -> 0
A79: 6220 - Trade Shows | B79: 0 | C79: 0 | D79: 0 | E79: 0 | F79: 0 | G79: 2900 | H79: 0 | I79: 0 | J79: 0 | K79: 0 | L79: 0 | M79: 0 | N79: =SUM(B79:M79) -> 2900 | O79: =IFERROR(N79/N$16,"") | R79: Even | S79: 0 | T79: 0.05 | U79: =IF($R79="Manual","",IFERROR(IF($R79="YOY Growth",$N79*(1+$T79)/12,$S79/12),"")) -> 0 | V79: =IF($R79="Manual","",IFERROR(IF($R79="YOY Growth",$N79*(1+$T79)/12,$S79/12),"")) -> 0 | W79: =IF($R79="Manual","",IFERROR(IF($R79="YOY Growth",$N79*(1+$T79)/12,$S79/12),"")) -> 0 | X79: =IF($R79="Manual","",IFERROR(IF($R79="YOY Growth",$N79*(1+$T79)/12,$S79/12),"")) -> 0 | Y79: =IF($R79="Manual","",IFERROR(IF($R79="YOY Growth",$N79*(1+$T79)/12,$S79/12),"")) -> 0 | Z79: =IF($R79="Manual","",IFERROR(IF($R79="YOY Growth",$N79*(1+$T79)/12,$S79/12),"")) -> 0 | AA79: =IF($R79="Manual","",IFERROR(IF($R79="YOY Growth",$N79*(1+$T79)/12,$S79/12),"")) -> 0 | AB79: =IF($R79="Manual","",IFERROR(IF($R79="YOY Growth",$N79*(1+$T79)/12,$S79/12),"")) -> 0 | ... AF79: =IF($R79="Manual","",IFERROR(IF($R79="YOY Growth",$N79*(1+$T79)/12,$S79/12),"")) -> 0 | AG79: =SUM(U79:AF79) -> 0 | AH79: =IFERROR(AG79/AG$16,"") | AJ79: =N79-AG79 -> 2900
A80: 6400 - Memberships and Subscriptions | B80: 0 | C80: 0 | D80: 0 | E80: 0 | F80: 0 | G80: 0 | H80: 0 | I80: 0 | J80: 0 | K80: 0 | L80: 0 | M80: 0 | N80: =SUM(B80:M80) -> 0 | O80: =IFERROR(N80/N$16,"") | R80: Even | S80: 0 | T80: 0.05 | U80: =IF($R80="Manual","",IFERROR(IF($R80="YOY Growth",$N80*(1+$T80)/12,$S80/12),"")) -> 0 | V80: =IF($R80="Manual","",IFERROR(IF($R80="YOY Growth",$N80*(1+$T80)/12,$S80/12),"")) -> 0 | W80: =IF($R80="Manual","",IFERROR(IF($R80="YOY Growth",$N80*(1+$T80)/12,$S80/12),"")) -> 0 | X80: =IF($R80="Manual","",IFERROR(IF($R80="YOY Growth",$N80*(1+$T80)/12,$S80/12),"")) -> 0 | Y80: =IF($R80="Manual","",IFERROR(IF($R80="YOY Growth",$N80*(1+$T80)/12,$S80/12),"")) -> 0 | Z80: =IF($R80="Manual","",IFERROR(IF($R80="YOY Growth",$N80*(1+$T80)/12,$S80/12),"")) -> 0 | AA80: =IF($R80="Manual","",IFERROR(IF($R80="YOY Growth",$N80*(1+$T80)/12,$S80/12),"")) -> 0 | AB80: =IF($R80="Manual","",IFERROR(IF($R80="YOY Growth",$N80*(1+$T80)/12,$S80/12),"")) -> 0 | ... AF80: =IF($R80="Manual","",IFERROR(IF($R80="YOY Growth",$N80*(1+$T80)/12,$S80/12),"")) -> 0 | AG80: =SUM(U80:AF80) -> 0 | AH80: =IFERROR(AG80/AG$16,"") | AJ80: =N80-AG80 -> 0
A81: 6500 - Demos
